{
  "type": "Feature",
  "properties": {
    "gn:admin1_code":"32.0",
    "gn:admin2_code":"7.0",
    "gn:asciiname":"El Salero",
    "gn:country_code":"MX",
    "gn:dem":1835,
    "gn:feature_class":"P",
    "gn:feature_code":"PPL",
    "gn:name":"El Salero",
    "gn:population":0,
    "gn:timezone":"America/Mexico_City",
    "iso:country":"MX",
    "name:spa_x_preferred":[
        "El Salero"
    ],
    "wof:name":"El Salero",
    "wof:placetype":"locality"
},
  "geometry": {"coordinates":[-101.34231,24.59858],"type":"Point"}
}