{
  "type": "Feature",
  "properties": {
    "gn:admin1_code":"15",
    "gn:admin2_code":"123",
    "gn:asciiname":"La Canoa",
    "gn:country_code":"MX",
    "gn:dem":973,
    "gn:feature_class":"P",
    "gn:feature_code":"PPL",
    "gn:name":"La Canoa",
    "gn:population":15,
    "gn:timezone":"America/Mexico_City",
    "iso:country":"MX",
    "wof:name":"La Canoa",
    "wof:placetype":"locality",
    "wof:population":15
},
  "geometry": {"coordinates":[-100.51564,18.86834],"type":"Point"}
}