{
  "type": "Feature",
  "properties": {
    "gn:admin1_code":"26",
    "gn:admin2_code":"49.0",
    "gn:asciiname":"El Potrerillo",
    "gn:country_code":"MX",
    "gn:dem":323,
    "gn:feature_class":"P",
    "gn:feature_code":"PPL",
    "gn:name":"El Potrerillo",
    "gn:population":0,
    "gn:timezone":"America/Hermosillo",
    "iso:country":"MX",
    "name:spa_x_preferred":[
        "El Potrerillo"
    ],
    "wof:name":"El Potrerillo",
    "wof:placetype":"locality"
},
  "geometry": {"coordinates":[-109.17107,27.5717],"type":"Point"}
}