{
  "type": "Feature",
  "properties": {
    "gn:admin1_code":"27",
    "gn:admin2_code":"6.0",
    "gn:asciiname":"Seccion San Pedro",
    "gn:country_code":"MX",
    "gn:dem":13,
    "gn:feature_class":"P",
    "gn:feature_code":"PPL",
    "gn:name":"Secci\u00f3n San Pedro",
    "gn:population":0,
    "gn:timezone":"America/Mexico_City",
    "iso:country":"MX",
    "name:spa_x_preferred":[
        "San Pedro"
    ],
    "name:spa_x_variant":[
        "Secci\u00f3n San Pedro"
    ],
    "wof:name":"Seccion San Pedro",
    "wof:placetype":"locality"
},
  "geometry": {"coordinates":[-93.14069000000001,18.06889],"type":"Point"}
}