{
  "type": "Feature",
  "properties": {
    "gn:admin1_code":"24",
    "gn:admin2_code":"32.0",
    "gn:asciiname":"El Laurel",
    "gn:country_code":"MX",
    "gn:dem":1798,
    "gn:feature_class":"P",
    "gn:feature_code":"PPL",
    "gn:name":"El Laurel",
    "gn:population":77,
    "gn:timezone":"America/Mexico_City",
    "iso:country":"MX",
    "wof:name":"El Laurel",
    "wof:placetype":"locality",
    "wof:population":77
},
  "geometry": {"coordinates":[-100.59111,21.82028],"type":"Point"}
}