{
  "type": "Feature",
  "properties": {
    "gn:admin1_code":"13",
    "gn:admin2_code":"77.0",
    "gn:asciiname":"Colonia Buenos Aires (Ejido Ahuehuetitla)",
    "gn:country_code":"MX",
    "gn:dem":2139,
    "gn:feature_class":"P",
    "gn:feature_code":"PPL",
    "gn:name":"Colonia Buenos Aires (Ejido Ahuehuetitla)",
    "gn:population":198,
    "gn:timezone":"America/Mexico_City",
    "iso:country":"MX",
    "wof:name":"Colonia Buenos Aires (Ejido Ahuehuetitla)",
    "wof:placetype":"locality",
    "wof:population":198
},
  "geometry": {"coordinates":[-98.39667,20.116],"type":"Point"}
}