{
  "type": "Feature",
  "properties": {
    "gn:admin1_code":"30",
    "gn:admin2_code":"178.0",
    "gn:asciiname":"San Jose de Chazaro",
    "gn:cc2":"MX",
    "gn:country_code":"MX",
    "gn:dem":7,
    "gn:feature_class":"P",
    "gn:feature_code":"PPL",
    "gn:name":"San Jos\u00e9 de Ch\u00e1zaro",
    "gn:population":43,
    "gn:timezone":"America/Mexico_City",
    "iso:country":"MX",
    "name:und_x_variant":[
        "San Jos\u00e9",
        "San Jos\u00e9 Zapotal"
    ],
    "wof:name":"San Jose de Chazaro",
    "wof:placetype":"locality",
    "wof:population":43
},
  "geometry": {"coordinates":[-95.58972,18.42889],"type":"Point"}
}