{
  "type": "Feature",
  "properties": {
    "gn:admin1_code":"32",
    "gn:admin2_code":"49.0",
    "gn:asciiname":"Cienega de la Esperanza (Cordon de la Mula)",
    "gn:country_code":"MX",
    "gn:dem":2561,
    "gn:feature_class":"P",
    "gn:feature_code":"PPL",
    "gn:name":"Cienega de la Esperanza (Cord\u00f3n de la Mula)",
    "gn:population":82,
    "gn:timezone":"America/Monterrey",
    "iso:country":"MX",
    "name:und_x_variant":[
        "Cienega de la Esperanza (Cord\u00f3n de la Mula)"
    ],
    "wof:name":"Cienega de la Esperanza (Cordon de la Mula)",
    "wof:placetype":"locality",
    "wof:population":82
},
  "geometry": {"coordinates":[-104.28917,22.54444],"type":"Point"}
}