{
  "type": "Feature",
  "properties": {
    "gn:admin1_code":"16.0",
    "gn:admin2_code":"9.0",
    "gn:asciiname":"El Mortero",
    "gn:country_code":"MX",
    "gn:dem":1785,
    "gn:feature_class":"P",
    "gn:feature_code":"PPL",
    "gn:name":"El Mortero",
    "gn:population":0,
    "gn:timezone":"America/Mexico_City",
    "iso:country":"MX",
    "name:spa_x_preferred":[
        "El Mortero"
    ],
    "name:und_x_variant":[
        "Mortero"
    ],
    "wof:name":"El Mortero",
    "wof:placetype":"locality"
},
  "geometry": {"coordinates":[-101.70613,19.07085],"type":"Point"}
}