{
  "type": "Feature",
  "properties": {
    "gn:admin1_code":"24",
    "gn:admin2_code":"33",
    "gn:asciiname":"La Merced",
    "gn:country_code":"MX",
    "gn:dem":2055,
    "gn:feature_class":"P",
    "gn:feature_code":"PPL",
    "gn:name":"La Merced",
    "gn:population":50,
    "gn:timezone":"America/Mexico_City",
    "iso:country":"MX",
    "name:ceb_x_preferred":[
        "La Merced"
    ],
    "name:deu_x_preferred":[
        "La Merced"
    ],
    "name:fra_x_preferred":[
        "La Merced"
    ],
    "name:ita_x_preferred":[
        "La Merced"
    ],
    "name:nld_x_preferred":[
        "La Merced"
    ],
    "name:pol_x_preferred":[
        "La Merced"
    ],
    "name:por_x_preferred":[
        "La Merced"
    ],
    "name:spa_x_preferred":[
        "La Merced"
    ],
    "name:swe_x_preferred":[
        "La Merced"
    ],
    "name:vie_x_preferred":[
        "La Merced"
    ],
    "wof:name":"La Merced",
    "wof:placetype":"locality",
    "wof:population":50
},
  "geometry": {"coordinates":[-101.33917,23.69611],"type":"Point"}
}