{
  "type": "Feature",
  "properties": {
    "gn:admin1_code":"6",
    "gn:admin2_code":"32.0",
    "gn:asciiname":"Maturana",
    "gn:country_code":"MX",
    "gn:dem":1712,
    "gn:feature_class":"P",
    "gn:feature_code":"PPL",
    "gn:name":"Maturana",
    "gn:population":44,
    "gn:timezone":"America/Chihuahua",
    "iso:country":"MX",
    "name:und_x_variant":[
        "Maturan"
    ],
    "wof:name":"Maturana",
    "wof:placetype":"locality",
    "wof:population":44
},
  "geometry": {"coordinates":[-105.66503,27.01133],"type":"Point"}
}