{
  "type": "Feature",
  "properties": {
    "gn:admin1_code":"30",
    "gn:admin2_code":"124.0",
    "gn:asciiname":"Santa Agueda",
    "gn:country_code":"MX",
    "gn:dem":89,
    "gn:feature_class":"P",
    "gn:feature_code":"PPL",
    "gn:name":"Santa \u00c1gueda",
    "gn:population":0,
    "gn:timezone":"America/Mexico_City",
    "iso:country":"MX",
    "name:spa_x_preferred":[
        "Santa \u00c1gueda"
    ],
    "wof:name":"Santa Agueda",
    "wof:placetype":"locality"
},
  "geometry": {"coordinates":[-97.31605,20.54989],"type":"Point"}
}