{
  "type": "Feature",
  "properties": {
    "gn:admin1_code":"13",
    "gn:admin2_code":"18",
    "gn:asciiname":"El Naranjal",
    "gn:country_code":"MX",
    "gn:dem":201,
    "gn:feature_class":"P",
    "gn:feature_code":"PPL",
    "gn:name":"El Naranjal",
    "gn:population":36,
    "gn:timezone":"America/Mexico_City",
    "iso:country":"MX",
    "wof:name":"El Naranjal",
    "wof:placetype":"locality",
    "wof:population":36
},
  "geometry": {"coordinates":[-98.92889,21.19806],"type":"Point"}
}