{
  "type": "Feature",
  "properties": {
    "gn:admin1_code":"27",
    "gn:admin2_code":"12.0",
    "gn:asciiname":"Chiquihuite",
    "gn:country_code":"MX",
    "gn:dem":6,
    "gn:feature_class":"P",
    "gn:feature_code":"PPL",
    "gn:name":"Chiquihuite",
    "gn:population":0,
    "gn:timezone":"America/Mexico_City",
    "iso:country":"MX",
    "name:spa_x_preferred":[
        "Chiguihuite"
    ],
    "name:spa_x_variant":[
        "Chiquihuite"
    ],
    "wof:name":"Chiquihuite",
    "wof:placetype":"locality"
},
  "geometry": {"coordinates":[-92.40781,17.81845],"type":"Point"}
}