{
  "type": "Feature",
  "properties": {
    "gn:admin1_code":"22.0",
    "gn:admin2_code":"11.0",
    "gn:asciiname":"Nuevo Torreon",
    "gn:country_code":"MX",
    "gn:dem":2033,
    "gn:feature_class":"P",
    "gn:feature_code":"PPL",
    "gn:name":"Nuevo Torre\u00f3n",
    "gn:population":0,
    "gn:timezone":"America/Mexico_City",
    "iso:country":"MX",
    "name:spa_x_preferred":[
        "Nuevo Torre\u00f3n"
    ],
    "wof:name":"Nuevo Torreon",
    "wof:placetype":"locality"
},
  "geometry": {"coordinates":[-100.32017999999999,20.56173],"type":"Point"}
}