{
  "type": "Feature",
  "properties": {
    "gn:admin1_code":"30",
    "gn:admin2_code":"129.0",
    "gn:asciiname":"Zapotal",
    "gn:country_code":"MX",
    "gn:dem":88,
    "gn:feature_class":"P",
    "gn:feature_code":"PPL",
    "gn:name":"Zapotal",
    "gn:population":8,
    "gn:timezone":"America/Mexico_City",
    "iso:country":"MX",
    "name:spa_x_preferred":[
        "Zapotal"
    ],
    "wof:name":"Zapotal",
    "wof:placetype":"locality",
    "wof:population":8
},
  "geometry": {"coordinates":[-98.32722,21.2225],"type":"Point"}
}