{
  "type": "Feature",
  "properties": {
    "gn:admin1_code":"14",
    "gn:admin2_code":"56",
    "gn:asciiname":"Piedra Ancha",
    "gn:country_code":"MX",
    "gn:dem":1474,
    "gn:feature_class":"P",
    "gn:feature_code":"PPL",
    "gn:name":"Piedra Ancha",
    "gn:population":13,
    "gn:timezone":"America/Mexico_City",
    "iso:country":"MX",
    "wof:name":"Piedra Ancha",
    "wof:placetype":"locality",
    "wof:population":13
},
  "geometry": {"coordinates":[-102.92278,19.63306],"type":"Point"}
}