{
  "type": "Feature",
  "properties": {
    "gn:admin1_code":"5",
    "gn:admin2_code":"65.0",
    "gn:asciiname":"El Caobano",
    "gn:country_code":"MX",
    "gn:dem":458,
    "gn:feature_class":"P",
    "gn:feature_code":"PPL",
    "gn:name":"El Caobano",
    "gn:population":0,
    "gn:timezone":"America/Mexico_City",
    "iso:country":"MX",
    "wof:name":"El Caobano",
    "wof:placetype":"locality"
},
  "geometry": {"coordinates":[-91.46666999999999,17.11667000000001],"type":"Point"}
}