{
  "type": "Feature",
  "properties": {
    "gn:admin1_code":"20",
    "gn:admin2_code":"446.0",
    "gn:asciiname":"Ino-Itun",
    "gn:country_code":"MX",
    "gn:dem":2452,
    "gn:feature_class":"P",
    "gn:feature_code":"PPL",
    "gn:name":"Ino-It\u00fan",
    "gn:population":140,
    "gn:timezone":"America/Mexico_City",
    "iso:country":"MX",
    "name:und_x_variant":[
        "Ino-It\u00fan"
    ],
    "wof:name":"Ino-Itun",
    "wof:placetype":"locality",
    "wof:population":140
},
  "geometry": {"coordinates":[-97.78610999999999,17.03639],"type":"Point"}
}