{
  "type": "Feature",
  "properties": {
    "gn:admin1_code":"6",
    "gn:admin2_code":"36.0",
    "gn:asciiname":"La Flor",
    "gn:country_code":"MX",
    "gn:dem":1340,
    "gn:feature_class":"P",
    "gn:feature_code":"PPL",
    "gn:name":"La Flor",
    "gn:population":2,
    "gn:timezone":"America/Chihuahua",
    "iso:country":"MX",
    "name:fra_x_preferred":[
        "La flor"
    ],
    "name:spa_x_preferred":[
        "La Flor"
    ],
    "wof:name":"La Flor",
    "wof:placetype":"locality",
    "wof:population":2
},
  "geometry": {"coordinates":[-104.82885,27.24891],"type":"Point"}
}