{
  "type": "Feature",
  "properties": {
    "gn:admin1_code":"29",
    "gn:admin2_code":"46",
    "gn:asciiname":"Rancho Guardamonte",
    "gn:country_code":"MX",
    "gn:dem":2946,
    "gn:feature_class":"P",
    "gn:feature_code":"PPL",
    "gn:name":"Rancho Guardamonte",
    "gn:population":24,
    "gn:timezone":"America/Mexico_City",
    "iso:country":"MX",
    "wof:name":"Rancho Guardamonte",
    "wof:placetype":"locality",
    "wof:population":24
},
  "geometry": {"coordinates":[-97.90049,19.5582],"type":"Point"}
}