{
  "type": "Feature",
  "properties": {
    "gn:admin1_code":"12",
    "gn:admin2_code":"18",
    "gn:asciiname":"El Fogon",
    "gn:country_code":"MX",
    "gn:dem":22,
    "gn:feature_class":"P",
    "gn:feature_code":"PPL",
    "gn:name":"El Fog\u00f3n",
    "gn:population":20,
    "gn:timezone":"America/Mexico_City",
    "iso:country":"MX",
    "name:und_x_variant":[
        "El Fog\u00f3n"
    ],
    "wof:name":"El Fogon",
    "wof:placetype":"locality",
    "wof:population":20
},
  "geometry": {"coordinates":[-98.93071999999999,16.58514],"type":"Point"}
}