{
  "type": "Feature",
  "properties": {
    "gn:admin1_code":"15.0",
    "gn:admin2_code":"110.0",
    "gn:asciiname":"Mesa de Jaimes",
    "gn:country_code":"MX",
    "gn:dem":2051,
    "gn:feature_class":"P",
    "gn:feature_code":"PPL",
    "gn:name":"Mesa de Jaimes",
    "gn:population":0,
    "gn:timezone":"America/Mexico_City",
    "iso:country":"MX",
    "name:spa_x_preferred":[
        "Mesa de Jaimes"
    ],
    "wof:name":"Mesa de Jaimes",
    "wof:placetype":"locality"
},
  "geometry": {"coordinates":[-100.10212,19.1614],"type":"Point"}
}