{
  "type": "Feature",
  "properties": {
    "gn:admin1_code":"6",
    "gn:admin2_code":"30.0",
    "gn:asciiname":"Rechorichi",
    "gn:country_code":"MX",
    "gn:dem":1883,
    "gn:feature_class":"P",
    "gn:feature_code":"PPL",
    "gn:name":"Rechorichi",
    "gn:population":1,
    "gn:timezone":"America/Chihuahua",
    "iso:country":"MX",
    "name:spa_x_preferred":[
        "Rechorichi"
    ],
    "wof:name":"Rechorichi",
    "wof:placetype":"locality",
    "wof:population":1
},
  "geometry": {"coordinates":[-108.16048000000001,27.5452],"type":"Point"}
}