{
  "type": "Feature",
  "properties": {
    "gn:admin1_code":"4",
    "gn:admin2_code":"4.0",
    "gn:asciiname":"Lopez Portillo Numero 2",
    "gn:country_code":"MX",
    "gn:dem":21,
    "gn:feature_class":"P",
    "gn:feature_code":"PPL",
    "gn:name":"L\u00f3pez Portillo N\u00famero 2",
    "gn:population":102,
    "gn:timezone":"America/Merida",
    "iso:country":"MX",
    "name:und_x_variant":[
        "L\u00f3pez Portillo N\u00famero 2"
    ],
    "wof:name":"Lopez Portillo Numero 2",
    "wof:placetype":"locality",
    "wof:population":102
},
  "geometry": {"coordinates":[-90.25389,19.23639],"type":"Point"}
}