{
  "type": "Feature",
  "properties": {
    "gn:admin1_code":"14",
    "gn:admin2_code":"43",
    "gn:asciiname":"Norberto Aguirre Palancares",
    "gn:country_code":"MX",
    "gn:dem":43,
    "gn:feature_class":"P",
    "gn:feature_code":"PPL",
    "gn:name":"Norberto Aguirre Palancares",
    "gn:population":26,
    "gn:timezone":"America/Mexico_City",
    "iso:country":"MX",
    "wof:name":"Norberto Aguirre Palancares",
    "wof:placetype":"locality",
    "wof:population":26
},
  "geometry": {"coordinates":[-105.12306,19.71778],"type":"Point"}
}