{
  "type": "Feature",
  "properties": {
    "gn:admin1_code":"14",
    "gn:admin2_code":"68.0",
    "gn:asciiname":"Rancho Gonzalez",
    "gn:country_code":"MX",
    "gn:dem":398,
    "gn:feature_class":"P",
    "gn:feature_code":"PPL",
    "gn:name":"Rancho Gonz\u00e1lez",
    "gn:population":6,
    "gn:timezone":"America/Mexico_City",
    "iso:country":"MX",
    "name:und_x_variant":[
        "Rancho Gonz\u00e1lez"
    ],
    "wof:name":"Rancho Gonzalez",
    "wof:placetype":"locality",
    "wof:population":6
},
  "geometry": {"coordinates":[-104.59222,19.68833],"type":"Point"}
}