{
  "type": "Feature",
  "properties": {
    "gn:admin1_code":"10",
    "gn:admin2_code":"6.0",
    "gn:asciiname":"Sauces",
    "gn:country_code":"MX",
    "gn:dem":1864,
    "gn:feature_class":"P",
    "gn:feature_code":"PPL",
    "gn:name":"Sauces",
    "gn:population":0,
    "gn:timezone":"America/Monterrey",
    "iso:country":"MX",
    "name:und_x_variant":[
        "Los Sauces"
    ],
    "wof:name":"Sauces",
    "wof:placetype":"locality"
},
  "geometry": {"coordinates":[-103.15025,24.49832],"type":"Point"}
}