{
  "type": "Feature",
  "properties": {
    "gn:admin1_code":"5",
    "gn:admin2_code":"77",
    "gn:asciiname":"Benito Juarez",
    "gn:country_code":"MX",
    "gn:dem":375,
    "gn:feature_class":"P",
    "gn:feature_code":"PPL",
    "gn:name":"Benito Ju\u00e1rez",
    "gn:population":35,
    "gn:timezone":"America/Mexico_City",
    "iso:country":"MX",
    "name:und_x_variant":[
        "Benito Ju\u00e1rez"
    ],
    "wof:name":"Benito Juarez",
    "wof:placetype":"locality",
    "wof:population":35
},
  "geometry": {"coordinates":[-92.33667,17.48278],"type":"Point"}
}