{
  "type": "Feature",
  "properties": {
    "gn:admin1_code":"15",
    "gn:admin2_code":"60.0",
    "gn:asciiname":"Paredeno (Rancho Paredeno)",
    "gn:country_code":"MX",
    "gn:dem":2685,
    "gn:feature_class":"P",
    "gn:feature_code":"PPL",
    "gn:name":"Parede\u00f1o (Rancho Parede\u00f1o)",
    "gn:population":8,
    "gn:timezone":"America/Mexico_City",
    "iso:country":"MX",
    "name:und_x_variant":[
        "Parede\u00f1o (Rancho Parede\u00f1o)"
    ],
    "wof:name":"Paredeno (Rancho Paredeno)",
    "wof:placetype":"locality",
    "wof:population":8
},
  "geometry": {"coordinates":[-99.40328,19.64111],"type":"Point"}
}