{
  "type": "Feature",
  "properties": {
    "gn:admin1_code":"26",
    "gn:admin2_code":"66.0",
    "gn:asciiname":"La Tigra",
    "gn:country_code":"MX",
    "gn:dem":576,
    "gn:feature_class":"P",
    "gn:feature_code":"PPL",
    "gn:name":"La Tigra",
    "gn:population":0,
    "gn:timezone":"America/Hermosillo",
    "iso:country":"MX",
    "name:spa_x_preferred":[
        "La Tigra"
    ],
    "wof:name":"La Tigra",
    "wof:placetype":"locality"
},
  "geometry": {"coordinates":[-110.21934,29.04365],"type":"Point"}
}