{
  "type": "Feature",
  "properties": {
    "gn:admin1_code":"4",
    "gn:admin2_code":"10.0",
    "gn:asciiname":"Bel-ha",
    "gn:country_code":"MX",
    "gn:dem":141,
    "gn:feature_class":"P",
    "gn:feature_code":"PPL",
    "gn:name":"Bel-h\u00e1",
    "gn:population":0,
    "gn:timezone":"America/Cancun",
    "iso:country":"MX",
    "name:spa_x_preferred":[
        "Bel-h\u00e1"
    ],
    "name:und_x_variant":[
        "Bel-Ha"
    ],
    "wof:name":"Bel-ha",
    "wof:placetype":"locality"
},
  "geometry": {"coordinates":[-89.32340000000001,18.93018],"type":"Point"}
}