{
  "type": "Feature",
  "properties": {
    "gn:admin1_code":"18",
    "gn:admin2_code":"5",
    "gn:asciiname":"La Mesa del Coco",
    "gn:country_code":"MX",
    "gn:dem":1030,
    "gn:feature_class":"P",
    "gn:feature_code":"PPL",
    "gn:name":"La Mesa del Coco",
    "gn:population":42,
    "gn:timezone":"America/Mazatlan",
    "iso:country":"MX",
    "wof:name":"La Mesa del Coco",
    "wof:placetype":"locality",
    "wof:population":42
},
  "geometry": {"coordinates":[-105.17749999999999,22.92833],"type":"Point"}
}