{
  "type": "Feature",
  "properties": {
    "gn:admin1_code":"30",
    "gn:admin2_code":"135.0",
    "gn:asciiname":"Omiquila",
    "gn:country_code":"MX",
    "gn:dem":1588,
    "gn:feature_class":"P",
    "gn:feature_code":"PPL",
    "gn:name":"Omiquila",
    "gn:population":249,
    "gn:timezone":"America/Mexico_City",
    "iso:country":"MX",
    "wof:name":"Omiquila",
    "wof:placetype":"locality",
    "wof:population":249
},
  "geometry": {"coordinates":[-97.11806,18.80528],"type":"Point"}
}