{
  "type": "Feature",
  "properties": {
    "gn:admin1_code":"5.0",
    "gn:admin2_code":"27.0",
    "gn:asciiname":"El Chorro",
    "gn:country_code":"MX",
    "gn:dem":507,
    "gn:feature_class":"P",
    "gn:feature_code":"PPL",
    "gn:name":"El Chorro",
    "gn:population":0,
    "gn:timezone":"America/Mexico_City",
    "iso:country":"MX",
    "name:ceb_x_preferred":[
        "El Chorro"
    ],
    "name:dan_x_preferred":[
        "El Chorro"
    ],
    "name:epo_x_preferred":[
        "El Chorro"
    ],
    "name:eus_x_preferred":[
        "El Chorro"
    ],
    "name:fra_x_preferred":[
        "El Chorro"
    ],
    "name:glg_x_preferred":[
        "El Chorro"
    ],
    "name:hat_x_preferred":[
        "El Chorro"
    ],
    "name:nld_x_preferred":[
        "El Chorro"
    ],
    "name:pol_x_preferred":[
        "El Chorro"
    ],
    "name:spa_x_preferred":[
        "El Chorro"
    ],
    "name:swe_x_preferred":[
        "El Chorro"
    ],
    "wof:name":"El Chorro",
    "wof:placetype":"locality"
},
  "geometry": {"coordinates":[-93.09672,16.40364],"type":"Point"}
}