{
  "type": "Feature",
  "properties": {
    "gn:admin1_code":"16",
    "gn:admin2_code":"96.0",
    "gn:asciiname":"El Charapo",
    "gn:country_code":"MX",
    "gn:dem":658,
    "gn:feature_class":"P",
    "gn:feature_code":"PPL",
    "gn:name":"El Charapo",
    "gn:population":9,
    "gn:timezone":"America/Mexico_City",
    "iso:country":"MX",
    "wof:name":"El Charapo",
    "wof:placetype":"locality",
    "wof:population":9
},
  "geometry": {"coordinates":[-102.38222,18.60972000000001],"type":"Point"}
}