{
  "type": "Feature",
  "properties": {
    "gn:admin1_code":"6.0",
    "gn:admin2_code":"3.0",
    "gn:asciiname":"Ejido La Palma",
    "gn:country_code":"MX",
    "gn:dem":1542,
    "gn:feature_class":"P",
    "gn:feature_code":"PPL",
    "gn:name":"Ejido La Palma",
    "gn:population":0,
    "gn:timezone":"America/Chihuahua",
    "iso:country":"MX",
    "wof:name":"Ejido La Palma",
    "wof:placetype":"locality"
},
  "geometry": {"coordinates":[-105.28333000000001,26.85],"type":"Point"}
}