{
  "type": "Feature",
  "properties": {
    "gn:admin1_code":"26",
    "gn:admin2_code":"29.0",
    "gn:asciiname":"Represo de Tapia",
    "gn:country_code":"MX",
    "gn:dem":245,
    "gn:feature_class":"P",
    "gn:feature_code":"PPL",
    "gn:name":"Represo de Tapia",
    "gn:population":0,
    "gn:timezone":"America/Hermosillo",
    "iso:country":"MX",
    "name:spa_x_preferred":[
        "Represo de Tapia"
    ],
    "name:spa_x_variant":[
        "Rancho Represo de Tapia"
    ],
    "wof:name":"Represo de Tapia",
    "wof:placetype":"locality"
},
  "geometry": {"coordinates":[-110.72493,28.50117],"type":"Point"}
}