{
  "type": "Feature",
  "properties": {
    "gn:admin1_code":"24",
    "gn:admin2_code":"12.0",
    "gn:asciiname":"Chiltzapuyo",
    "gn:country_code":"MX",
    "gn:dem":233,
    "gn:feature_class":"P",
    "gn:feature_code":"PPL",
    "gn:name":"Chiltzapuyo",
    "gn:population":74,
    "gn:timezone":"America/Mexico_City",
    "iso:country":"MX",
    "wof:name":"Chiltzapuyo",
    "wof:placetype":"locality",
    "wof:population":74
},
  "geometry": {"coordinates":[-98.93694000000001,21.58333],"type":"Point"}
}