{
  "type": "Feature",
  "properties": {
    "gn:admin1_code":"12",
    "gn:admin2_code":"16.0",
    "gn:asciiname":"San Isidro el Gallo",
    "gn:country_code":"MX",
    "gn:dem":688,
    "gn:feature_class":"P",
    "gn:feature_code":"PPL",
    "gn:name":"San Isidro el Gallo",
    "gn:population":0,
    "gn:timezone":"America/Mexico_City",
    "iso:country":"MX",
    "name:spa_x_preferred":[
        "San Isidro"
    ],
    "name:spa_x_variant":[
        "San Isidro el Gallo"
    ],
    "name:und_x_variant":[
        "El Gallo"
    ],
    "wof:name":"San Isidro el Gallo",
    "wof:placetype":"locality"
},
  "geometry": {"coordinates":[-101.50411,18.24955],"type":"Point"}
}