{
  "type": "Feature",
  "properties": {
    "gn:admin1_code":"19",
    "gn:admin2_code":"43.0",
    "gn:asciiname":"Lagunillas",
    "gn:country_code":"MX",
    "gn:dem":2117,
    "gn:feature_class":"P",
    "gn:feature_code":"PPL",
    "gn:name":"Lagunillas",
    "gn:population":8,
    "gn:timezone":"America/Monterrey",
    "iso:country":"MX",
    "name:ceb_x_preferred":[
        "Lagunillas"
    ],
    "name:deu_x_preferred":[
        "Lagunillas"
    ],
    "name:fra_x_preferred":[
        "Lagunillas"
    ],
    "name:ita_x_preferred":[
        "Lagunillas"
    ],
    "name:lit_x_preferred":[
        "Laguniljasas"
    ],
    "name:nld_x_preferred":[
        "Lagunillas"
    ],
    "name:sco_x_preferred":[
        "Lagunillas"
    ],
    "name:spa_x_preferred":[
        "Lagunillas"
    ],
    "name:swe_x_preferred":[
        "Lagunillas"
    ],
    "wof:name":"Lagunillas",
    "wof:placetype":"locality",
    "wof:population":8
},
  "geometry": {"coordinates":[-100.21917999999999,25.26784],"type":"Point"}
}