{
  "type": "Feature",
  "properties": {
    "gn:admin1_code":"22",
    "gn:admin2_code":"7.0",
    "gn:asciiname":"Bernal",
    "gn:country_code":"MX",
    "gn:dem":2069,
    "gn:feature_class":"P",
    "gn:feature_code":"PPL",
    "gn:name":"Bernal",
    "gn:population":0,
    "gn:timezone":"America/Mexico_City",
    "iso:country":"MX",
    "name:ceb_x_preferred":[
        "Bernal"
    ],
    "name:deu_x_preferred":[
        "Bernal"
    ],
    "name:fas_x_preferred":[
        "\u0628\u0631\u0646\u0627\u0644"
    ],
    "name:fra_x_preferred":[
        "Bernal"
    ],
    "name:jpn_x_preferred":[
        "\u30d9\u30eb\u30ca\u30eb"
    ],
    "name:nld_x_preferred":[
        "Bernal"
    ],
    "name:por_x_preferred":[
        "Bernal"
    ],
    "name:ron_x_preferred":[
        "Bernal"
    ],
    "name:spa_x_preferred":[
        "Bernal"
    ],
    "name:srp_x_preferred":[
        "\u0411\u0435\u0440\u043d\u0430\u043b"
    ],
    "name:swe_x_preferred":[
        "Bernal"
    ],
    "wof:name":"Bernal",
    "wof:placetype":"locality"
},
  "geometry": {"coordinates":[-99.94125,20.7403],"type":"Point"}
}