{
  "type": "Feature",
  "properties": {
    "gn:admin1_code":"22",
    "gn:admin2_code":"7.0",
    "gn:asciiname":"Bernal",
    "gn:country_code":"MX",
    "gn:dem":2069,
    "gn:feature_class":"P",
    "gn:feature_code":"PPL",
    "gn:name":"Bernal",
    "gn:population":0,
    "gn:timezone":"America/Mexico_City",
    "iso:country":"MX",
    "wof:name":"Bernal",
    "wof:placetype":"locality"
},
  "geometry": {"coordinates":[-99.94125,20.7403],"type":"Point"}
}