{
  "type": "Feature",
  "properties": {
    "gn:admin1_code":"13",
    "gn:admin2_code":"55.0",
    "gn:asciiname":"Jagueey",
    "gn:country_code":"MX",
    "gn:dem":2039,
    "gn:feature_class":"P",
    "gn:feature_code":"PPL",
    "gn:name":"Jag\u00fcey",
    "gn:population":383,
    "gn:timezone":"America/Mexico_City",
    "iso:country":"MX",
    "name:und_x_variant":[
        "Jag\u00fcey"
    ],
    "wof:name":"Jagueey",
    "wof:placetype":"locality",
    "wof:population":383
},
  "geometry": {"coordinates":[-98.9675,20.35889],"type":"Point"}
}