{
  "type": "Feature",
  "properties": {
    "gn:admin1_code":"30",
    "gn:admin2_code":"189",
    "gn:asciiname":"La Linea (La Victoria)",
    "gn:country_code":"MX",
    "gn:dem":12,
    "gn:feature_class":"P",
    "gn:feature_code":"PPL",
    "gn:name":"La L\u00ednea (La Victoria)",
    "gn:population":10,
    "gn:timezone":"America/Mexico_City",
    "iso:country":"MX",
    "name:und_x_variant":[
        "La L\u00ednea (La Victoria)"
    ],
    "wof:name":"La Linea (La Victoria)",
    "wof:placetype":"locality",
    "wof:population":10
},
  "geometry": {"coordinates":[-97.38611,20.90139],"type":"Point"}
}