{
  "type": "Feature",
  "properties": {
    "gn:admin1_code":"6.0",
    "gn:admin2_code":"27.0",
    "gn:asciiname":"El Tecolote",
    "gn:country_code":"MX",
    "gn:dem":2426,
    "gn:feature_class":"P",
    "gn:feature_code":"PPL",
    "gn:name":"El Tecolote",
    "gn:population":0,
    "gn:timezone":"America/Chihuahua",
    "iso:country":"MX",
    "name:ceb_x_preferred":[
        "El Tecolote"
    ],
    "name:spa_x_preferred":[
        "El Tecolote"
    ],
    "name:swe_x_preferred":[
        "El Tecolote"
    ],
    "wof:name":"El Tecolote",
    "wof:placetype":"locality"
},
  "geometry": {"coordinates":[-106.95499,26.90297],"type":"Point"}
}