{
  "type": "Feature",
  "properties": {
    "gn:admin1_code":"20",
    "gn:admin2_code":"96.0",
    "gn:asciiname":"Tapia",
    "gn:country_code":"MX",
    "gn:dem":2125,
    "gn:feature_class":"P",
    "gn:feature_code":"PPL",
    "gn:name":"Tapia",
    "gn:population":6,
    "gn:timezone":"America/Mexico_City",
    "iso:country":"MX",
    "name:ast_x_preferred":[
        "Tapia"
    ],
    "name:cat_x_preferred":[
        "Tapia"
    ],
    "name:ceb_x_preferred":[
        "Tapia"
    ],
    "name:ces_x_preferred":[
        "Tapia"
    ],
    "name:deu_x_preferred":[
        "Tapia"
    ],
    "name:eus_x_preferred":[
        "Tapia"
    ],
    "name:fin_x_preferred":[
        "Tapia"
    ],
    "name:fra_x_preferred":[
        "Tapia"
    ],
    "name:hun_x_preferred":[
        "Tapia"
    ],
    "name:ita_x_preferred":[
        "Tapia"
    ],
    "name:rus_x_preferred":[
        "\u0422\u0430\u043f\u0438\u044f"
    ],
    "name:spa_x_preferred":[
        "Tapia"
    ],
    "name:swe_x_preferred":[
        "Tapia"
    ],
    "name:ukr_x_preferred":[
        "\u0422\u0430\u043f\u0456\u044f"
    ],
    "wof:name":"Tapia",
    "wof:placetype":"locality",
    "wof:population":6
},
  "geometry": {"coordinates":[-97.31917,17.49917],"type":"Point"}
}