{
  "type": "Feature",
  "properties": {
    "gn:admin1_code":"5",
    "gn:admin2_code":"69.0",
    "gn:asciiname":"Villahermosa",
    "gn:country_code":"MX",
    "gn:dem":16,
    "gn:feature_class":"P",
    "gn:feature_code":"PPL",
    "gn:name":"Villahermosa",
    "gn:population":89,
    "gn:timezone":"America/Mexico_City",
    "iso:country":"MX",
    "wof:name":"Villahermosa",
    "wof:placetype":"locality",
    "wof:population":89
},
  "geometry": {"coordinates":[-93.30110999999999,15.64111],"type":"Point"}
}