{
  "type": "Feature",
  "properties": {
    "gn:admin1_code":"27",
    "gn:admin2_code":"8.0",
    "gn:asciiname":"Rio Seco y Montana Primera Seccion",
    "gn:country_code":"MX",
    "gn:dem":31,
    "gn:feature_class":"P",
    "gn:feature_code":"PPL",
    "gn:name":"R\u00edo Seco y Monta\u00f1a Primera Secci\u00f3n",
    "gn:population":0,
    "gn:timezone":"America/Mexico_City",
    "iso:country":"MX",
    "name:spa_x_preferred":[
        "R\u00edo Seco y Monta\u00f1a"
    ],
    "name:spa_x_variant":[
        "R\u00edo Seco y Monta\u00f1a Primera Secci\u00f3n",
        "Primera Secci\u00f3n"
    ],
    "wof:name":"Rio Seco y Montana Primera Seccion",
    "wof:placetype":"locality"
},
  "geometry": {"coordinates":[-93.38321000000001,17.94305],"type":"Point"}
}