{
  "type": "Feature",
  "properties": {
    "gn:admin1_code":"6.0",
    "gn:admin2_code":"17.0",
    "gn:asciiname":"El Canon",
    "gn:cc2":"MX",
    "gn:country_code":"MX",
    "gn:dem":2131,
    "gn:feature_class":"P",
    "gn:feature_code":"PPL",
    "gn:name":"El Ca\u00f1\u00f3n",
    "gn:population":0,
    "gn:timezone":"America/Chihuahua",
    "iso:country":"MX",
    "name:und_x_variant":[
        "Rancho Ca\u00f1\u00f3n",
        "El Ca\u00f1\u00f3n"
    ],
    "wof:name":"El Canon",
    "wof:placetype":"locality"
},
  "geometry": {"coordinates":[-107.06667,28.61667000000001],"type":"Point"}
}