{
  "type": "Feature",
  "properties": {
    "gn:admin1_code":"6",
    "gn:admin2_code":"29",
    "gn:asciiname":"El Pirame (Arroyo de la Onza)",
    "gn:country_code":"MX",
    "gn:dem":2484,
    "gn:feature_class":"P",
    "gn:feature_code":"PPL",
    "gn:name":"El Pirame (Arroyo de la Onza)",
    "gn:population":33,
    "gn:timezone":"America/Chihuahua",
    "iso:country":"MX",
    "wof:name":"El Pirame (Arroyo de la Onza)",
    "wof:placetype":"locality",
    "wof:population":33
},
  "geometry": {"coordinates":[-106.68344999999999,25.95218],"type":"Point"}
}