{
  "type": "Feature",
  "properties": {
    "gn:admin1_code":"18.0",
    "gn:admin2_code":"19.0",
    "gn:asciiname":"El Jordan",
    "gn:country_code":"MX",
    "gn:dem":1542,
    "gn:feature_class":"P",
    "gn:feature_code":"PPL",
    "gn:name":"El Jord\u00e1n",
    "gn:population":0,
    "gn:timezone":"America/Mazatlan",
    "iso:country":"MX",
    "name:spa_x_preferred":[
        "El Jord\u00e1n"
    ],
    "name:spa_x_variant":[
        "Jord\u00e1n"
    ],
    "wof:name":"El Jordan",
    "wof:placetype":"locality"
},
  "geometry": {"coordinates":[-104.02674,21.29716],"type":"Point"}
}