{
  "type": "Feature",
  "properties": {
    "gn:admin1_code":"1",
    "gn:admin2_code":"10",
    "gn:asciiname":"El Consuelo",
    "gn:country_code":"MX",
    "gn:dem":2018,
    "gn:feature_class":"P",
    "gn:feature_code":"PPL",
    "gn:name":"El Consuelo",
    "gn:population":34,
    "gn:timezone":"America/Mexico_City",
    "iso:country":"MX",
    "wof:name":"El Consuelo",
    "wof:placetype":"locality",
    "wof:population":34
},
  "geometry": {"coordinates":[-102.05722,21.87694],"type":"Point"}
}