{
  "type": "Feature",
  "properties": {
    "gn:admin1_code":"31",
    "gn:admin2_code":"104.0",
    "gn:asciiname":"San Buenaventura",
    "gn:country_code":"MX",
    "gn:dem":35,
    "gn:feature_class":"P",
    "gn:feature_code":"PPL",
    "gn:name":"San Buenaventura",
    "gn:population":7,
    "gn:timezone":"America/Merida",
    "iso:country":"MX",
    "name:ceb_x_preferred":[
        "San Buenaventura"
    ],
    "name:deu_x_preferred":[
        "San Buenaventura"
    ],
    "name:epo_x_preferred":[
        "San Buenaventura"
    ],
    "name:fin_x_preferred":[
        "San Buenaventura"
    ],
    "name:ita_x_preferred":[
        "San Buenaventura"
    ],
    "name:nld_x_preferred":[
        "San Buenaventura"
    ],
    "name:pol_x_preferred":[
        "San Buenaventura"
    ],
    "name:por_x_preferred":[
        "San Buenaventura"
    ],
    "name:rus_x_preferred":[
        "\u0421\u0430\u043d-\u0411\u0443\u044d\u043d\u0430\u0432\u0435\u043d\u0442\u0443\u0440\u0430"
    ],
    "name:sco_x_preferred":[
        "San Buenaventura"
    ],
    "name:spa_x_preferred":[
        "San Buenaventura"
    ],
    "name:srp_x_preferred":[
        "\u0421\u0430\u043d \u0411\u0443\u0435\u043d\u0430\u0432\u0435\u043d\u0442\u0443\u0440\u0430"
    ],
    "name:swe_x_preferred":[
        "San Buenaventura"
    ],
    "wof:name":"San Buenaventura",
    "wof:placetype":"locality",
    "wof:population":7
},
  "geometry": {"coordinates":[-88.81139,20.30778],"type":"Point"}
}