{
  "type": "Feature",
  "properties": {
    "gn:admin1_code":"31",
    "gn:admin2_code":"104.0",
    "gn:asciiname":"San Buenaventura",
    "gn:country_code":"MX",
    "gn:dem":35,
    "gn:feature_class":"P",
    "gn:feature_code":"PPL",
    "gn:name":"San Buenaventura",
    "gn:population":7,
    "gn:timezone":"America/Merida",
    "iso:country":"MX",
    "wof:name":"San Buenaventura",
    "wof:placetype":"locality",
    "wof:population":7
},
  "geometry": {"coordinates":[-88.81139,20.30778],"type":"Point"}
}