{
  "type": "Feature",
  "properties": {
    "gn:admin1_code":"5",
    "gn:admin2_code":"16",
    "gn:asciiname":"Villa Paraiso",
    "gn:country_code":"MX",
    "gn:dem":48,
    "gn:feature_class":"P",
    "gn:feature_code":"PPL",
    "gn:name":"Villa Para\u00edso",
    "gn:population":11,
    "gn:timezone":"America/Mexico_City",
    "iso:country":"MX",
    "name:und_x_variant":[
        "Villa Para\u00edso"
    ],
    "wof:name":"Villa Paraiso",
    "wof:placetype":"locality",
    "wof:population":11
},
  "geometry": {"coordinates":[-92.0275,17.62833],"type":"Point"}
}