{
  "type": "Feature",
  "properties": {
    "gn:admin1_code":"6.0",
    "gn:admin2_code":"1.0",
    "gn:asciiname":"El Escondido",
    "gn:country_code":"MX",
    "gn:dem":1490,
    "gn:feature_class":"P",
    "gn:feature_code":"PPL",
    "gn:name":"El Escondido",
    "gn:population":0,
    "gn:timezone":"America/Chihuahua",
    "iso:country":"MX",
    "name:spa_x_preferred":[
        "Volc\u00e1n El Escondido"
    ],
    "name:und_x_variant":[
        "Rancho La Escondida",
        "El Escondido"
    ],
    "name:zho_x_preferred":[
        "\u57c3\u723e\u57c3\u65af\u5b54\u8fea\u591a\u706b\u5c71"
    ],
    "wof:name":"El Escondido",
    "wof:placetype":"locality"
},
  "geometry": {"coordinates":[-106.10943,30.31412000000001],"type":"Point"}
}