{
  "type": "Feature",
  "properties": {
    "gn:admin1_code":"32",
    "gn:admin2_code":"2.0",
    "gn:asciiname":"Tinajas",
    "gn:country_code":"MX",
    "gn:dem":1942,
    "gn:feature_class":"P",
    "gn:feature_code":"PPL",
    "gn:name":"Tinajas",
    "gn:population":61,
    "gn:timezone":"America/Mexico_City",
    "iso:country":"MX",
    "name:ceb_x_preferred":[
        "Tinajas"
    ],
    "name:spa_x_preferred":[
        "Tinajas"
    ],
    "name:swe_x_preferred":[
        "Tinajas"
    ],
    "wof:name":"Tinajas",
    "wof:placetype":"locality",
    "wof:population":61
},
  "geometry": {"coordinates":[-102.72944,21.52528],"type":"Point"}
}