{
  "type": "Feature",
  "properties": {
    "gn:admin1_code":"6",
    "gn:admin2_code":"28.0",
    "gn:asciiname":"Beto Avila",
    "gn:country_code":"MX",
    "gn:dem":1232,
    "gn:feature_class":"P",
    "gn:feature_code":"PPL",
    "gn:name":"Beto \u00c1vila",
    "gn:population":0,
    "gn:timezone":"America/Chihuahua",
    "iso:country":"MX",
    "name:spa_x_preferred":[
        "Beto \u00c1vila"
    ],
    "wof:name":"Beto Avila",
    "wof:placetype":"locality"
},
  "geometry": {"coordinates":[-105.33566999999999,30.66989],"type":"Point"}
}