{
  "type": "Feature",
  "properties": {
    "gn:admin1_code":"15",
    "gn:admin2_code":"105.0",
    "gn:asciiname":"San Mateo",
    "gn:country_code":"MX",
    "gn:dem":1208,
    "gn:feature_class":"P",
    "gn:feature_code":"PPL",
    "gn:name":"San Mateo",
    "gn:population":0,
    "gn:timezone":"America/Mexico_City",
    "iso:country":"MX",
    "name:spa_x_preferred":[
        "San Mateo"
    ],
    "wof:name":"San Mateo",
    "wof:placetype":"locality"
},
  "geometry": {"coordinates":[-100.15028,18.63265],"type":"Point"}
}