{
  "type": "Feature",
  "properties": {
    "gn:admin1_code":"24",
    "gn:admin2_code":"24.0",
    "gn:asciiname":"Ildefonso Turrubiartes (La Boquilla)",
    "gn:country_code":"MX",
    "gn:dem":1025,
    "gn:feature_class":"P",
    "gn:feature_code":"PPL",
    "gn:name":"Ildefonso Turrubiartes (La Boquilla)",
    "gn:population":527,
    "gn:timezone":"America/Mexico_City",
    "iso:country":"MX",
    "wof:name":"Ildefonso Turrubiartes (La Boquilla)",
    "wof:placetype":"locality",
    "wof:population":527
},
  "geometry": {"coordinates":[-99.86888999999999,21.92639],"type":"Point"}
}