{
  "type": "Feature",
  "properties": {
    "gn:admin1_code":"12",
    "gn:admin2_code":"28.0",
    "gn:asciiname":"El Calvario",
    "gn:country_code":"MX",
    "gn:dem":1723,
    "gn:feature_class":"P",
    "gn:feature_code":"PPL",
    "gn:name":"El Calvario",
    "gn:population":294,
    "gn:timezone":"America/Mexico_City",
    "iso:country":"MX",
    "wof:name":"El Calvario",
    "wof:placetype":"locality",
    "wof:population":294
},
  "geometry": {"coordinates":[-99.155,17.5275],"type":"Point"}
}