{
  "type": "Feature",
  "properties": {
    "gn:admin1_code":"6.0",
    "gn:admin2_code":"67.0",
    "gn:asciiname":"La Morita",
    "gn:country_code":"MX",
    "gn:dem":1714,
    "gn:feature_class":"P",
    "gn:feature_code":"PPL",
    "gn:name":"La Morita",
    "gn:population":5,
    "gn:timezone":"America/Chihuahua",
    "iso:country":"MX",
    "name:spa_x_preferred":[
        "La Morita"
    ],
    "wof:name":"La Morita",
    "wof:placetype":"locality",
    "wof:population":5
},
  "geometry": {"coordinates":[-106.16708,27.60086],"type":"Point"}
}