{
  "type": "Feature",
  "properties": {
    "gn:admin1_code":"24",
    "gn:admin2_code":"39.0",
    "gn:asciiname":"Los Tamarindos",
    "gn:country_code":"MX",
    "gn:dem":151,
    "gn:feature_class":"P",
    "gn:feature_code":"PPL",
    "gn:name":"Los Tamarindos",
    "gn:population":0,
    "gn:timezone":"America/Mexico_City",
    "iso:country":"MX",
    "name:spa_x_preferred":[
        "Los Tamarindos"
    ],
    "wof:name":"Los Tamarindos",
    "wof:placetype":"locality"
},
  "geometry": {"coordinates":[-98.67806,21.53041],"type":"Point"}
}