{
  "type": "Feature",
  "properties": {
    "gn:admin1_code":"5",
    "gn:admin2_code":"108.0",
    "gn:asciiname":"La Cabana",
    "gn:country_code":"MX",
    "gn:dem":663,
    "gn:feature_class":"P",
    "gn:feature_code":"PPL",
    "gn:name":"La Caba\u00f1a",
    "gn:population":4,
    "gn:timezone":"America/Mexico_City",
    "iso:country":"MX",
    "name:und_x_variant":[
        "La Caba\u00f1a"
    ],
    "wof:name":"La Cabana",
    "wof:placetype":"locality",
    "wof:population":4
},
  "geometry": {"coordinates":[-93.37333,16.28778],"type":"Point"}
}