{
  "type": "Feature",
  "properties": {
    "gn:admin1_code":"13",
    "gn:admin2_code":"29.0",
    "gn:asciiname":"Zamorano",
    "gn:country_code":"MX",
    "gn:dem":2030,
    "gn:feature_class":"P",
    "gn:feature_code":"PPL",
    "gn:name":"Zamorano",
    "gn:population":266,
    "gn:timezone":"America/Mexico_City",
    "iso:country":"MX",
    "wof:name":"Zamorano",
    "wof:placetype":"locality",
    "wof:population":266
},
  "geometry": {"coordinates":[-99.61750000000001,20.43639],"type":"Point"}
}