{
  "type": "Feature",
  "properties": {
    "gn:admin1_code":"6",
    "gn:admin2_code":"36.0",
    "gn:asciiname":"Santa Elena",
    "gn:country_code":"MX",
    "gn:dem":1308,
    "gn:feature_class":"P",
    "gn:feature_code":"PPL",
    "gn:name":"Santa Elena",
    "gn:population":8,
    "gn:timezone":"America/Chihuahua",
    "iso:country":"MX",
    "name:spa_x_preferred":[
        "Santa Elena"
    ],
    "wof:name":"Santa Elena",
    "wof:placetype":"locality",
    "wof:population":8
},
  "geometry": {"coordinates":[-104.92092,27.40145],"type":"Point"}
}