{
  "type": "Feature",
  "properties": {
    "gn:admin1_code":"6",
    "gn:admin2_code":"45.0",
    "gn:asciiname":"El Tizonazo",
    "gn:country_code":"MX",
    "gn:dem":1160,
    "gn:feature_class":"P",
    "gn:feature_code":"PPL",
    "gn:name":"El Tizonazo",
    "gn:population":7,
    "gn:timezone":"America/Chihuahua",
    "iso:country":"MX",
    "wof:name":"El Tizonazo",
    "wof:placetype":"locality",
    "wof:population":7
},
  "geometry": {"coordinates":[-105.39658,28.27937],"type":"Point"}
}