{
  "type": "Feature",
  "properties": {
    "gn:admin1_code":"30",
    "gn:admin2_code":"14.0",
    "gn:asciiname":"Cacahuatal",
    "gn:country_code":"MX",
    "gn:dem":577,
    "gn:feature_class":"P",
    "gn:feature_code":"PPL",
    "gn:name":"Cacahuatal",
    "gn:population":0,
    "gn:timezone":"America/Mexico_City",
    "iso:country":"MX",
    "name:spa_x_preferred":[
        "Cacahuatal"
    ],
    "wof:name":"Cacahuatal",
    "wof:placetype":"locality"
},
  "geometry": {"coordinates":[-96.84192,18.83098],"type":"Point"}
}