{
  "type": "Feature",
  "properties": {
    "gn:admin1_code":"26",
    "gn:admin2_code":"17.0",
    "gn:asciiname":"6 de Abril Sector Dos",
    "gn:country_code":"MX",
    "gn:dem":257,
    "gn:feature_class":"P",
    "gn:feature_code":"PPL",
    "gn:name":"6 de Abril Sector Dos",
    "gn:population":7,
    "gn:timezone":"America/Hermosillo",
    "iso:country":"MX",
    "wof:name":"6 de Abril Sector Dos",
    "wof:placetype":"locality",
    "wof:population":7
},
  "geometry": {"coordinates":[-112.19835,30.50349000000001],"type":"Point"}
}