{
  "type": "Feature",
  "properties": {
    "gn:admin1_code":"24",
    "gn:admin2_code":"24.0",
    "gn:asciiname":"El Nogalito",
    "gn:country_code":"MX",
    "gn:dem":1252,
    "gn:feature_class":"P",
    "gn:feature_code":"PPL",
    "gn:name":"El Nogalito",
    "gn:population":0,
    "gn:timezone":"America/Mexico_City",
    "iso:country":"MX",
    "name:spa_x_preferred":[
        "El Nogalito"
    ],
    "wof:name":"El Nogalito",
    "wof:placetype":"locality"
},
  "geometry": {"coordinates":[-99.95990999999999,21.70213],"type":"Point"}
}