{
  "type": "Feature",
  "properties": {
    "gn:admin1_code":"30",
    "gn:admin2_code":"174",
    "gn:asciiname":"Paso de Laja",
    "gn:country_code":"MX",
    "gn:dem":31,
    "gn:feature_class":"P",
    "gn:feature_code":"PPL",
    "gn:name":"Paso de Laja",
    "gn:population":21,
    "gn:timezone":"America/Mexico_City",
    "iso:country":"MX",
    "wof:name":"Paso de Laja",
    "wof:placetype":"locality",
    "wof:population":21
},
  "geometry": {"coordinates":[-96.18472,18.64139],"type":"Point"}
}