{
  "type": "Feature",
  "properties": {
    "gn:admin1_code":"25.0",
    "gn:admin2_code":"6.0",
    "gn:asciiname":"Campo Camato",
    "gn:country_code":"MX",
    "gn:dem":12,
    "gn:feature_class":"P",
    "gn:feature_code":"PPL",
    "gn:name":"Campo Camato",
    "gn:population":6,
    "gn:timezone":"America/Mazatlan",
    "iso:country":"MX",
    "wof:name":"Campo Camato",
    "wof:placetype":"locality",
    "wof:population":6
},
  "geometry": {"coordinates":[-107.44472,24.53643],"type":"Point"}
}