{
  "type": "Feature",
  "properties": {
    "gn:admin1_code":"12",
    "gn:admin2_code":"17.0",
    "gn:asciiname":"El Real del Limon",
    "gn:country_code":"MX",
    "gn:dem":804,
    "gn:feature_class":"P",
    "gn:feature_code":"PPL",
    "gn:name":"El Real del Lim\u00f3n",
    "gn:population":157,
    "gn:timezone":"America/Mexico_City",
    "iso:country":"MX",
    "name:und_x_variant":[
        "El Real del Lim\u00f3n"
    ],
    "wof:name":"El Real del Limon",
    "wof:placetype":"locality",
    "wof:population":157
},
  "geometry": {"coordinates":[-99.71344999999999,18.00401],"type":"Point"}
}