{
  "type": "Feature",
  "properties": {
    "gn:admin1_code":"4",
    "gn:admin2_code":"4.0",
    "gn:asciiname":"Hool",
    "gn:country_code":"MX",
    "gn:dem":43,
    "gn:feature_class":"P",
    "gn:feature_code":"PPL",
    "gn:name":"Hool",
    "gn:population":0,
    "gn:timezone":"America/Merida",
    "iso:country":"MX",
    "name:spa_x_preferred":[
        "Hool"
    ],
    "wof:name":"Hool",
    "wof:placetype":"locality"
},
  "geometry": {"coordinates":[-90.44631,19.51294],"type":"Point"}
}