{
  "type": "Feature",
  "properties": {
    "gn:admin1_code":"4",
    "gn:admin2_code":"6.0",
    "gn:asciiname":"Pachuitz",
    "gn:country_code":"MX",
    "gn:dem":134,
    "gn:feature_class":"P",
    "gn:feature_code":"PPL",
    "gn:name":"Pachuitz",
    "gn:population":266,
    "gn:timezone":"America/Cancun",
    "iso:country":"MX",
    "name:spa_x_preferred":[
        "Pachuitz"
    ],
    "wof:name":"Pachuitz",
    "wof:placetype":"locality",
    "wof:population":266
},
  "geometry": {"coordinates":[-89.24859000000002,19.14763],"type":"Point"}
}