{
  "type": "Feature",
  "properties": {
    "gn:admin1_code":"6.0",
    "gn:admin2_code":"7.0",
    "gn:asciiname":"Bajio del Arbolito",
    "gn:country_code":"MX",
    "gn:dem":2468,
    "gn:feature_class":"P",
    "gn:feature_code":"PPL",
    "gn:name":"Bajio del Arbolito",
    "gn:population":0,
    "gn:timezone":"America/Chihuahua",
    "iso:country":"MX",
    "name:spa_x_preferred":[
        "Bajio del Arbolito"
    ],
    "wof:name":"Bajio del Arbolito",
    "wof:placetype":"locality"
},
  "geometry": {"coordinates":[-106.6589,26.72997],"type":"Point"}
}