{
  "type": "Feature",
  "properties": {
    "gn:admin1_code":"21",
    "gn:admin2_code":"23.0",
    "gn:asciiname":"San Antonio el Alto (Rancho Montiel)",
    "gn:country_code":"MX",
    "gn:dem":2730,
    "gn:feature_class":"P",
    "gn:feature_code":"PPL",
    "gn:name":"San Antonio el Alto (Rancho Montiel)",
    "gn:population":76,
    "gn:timezone":"America/Mexico_City",
    "iso:country":"MX",
    "wof:name":"San Antonio el Alto (Rancho Montiel)",
    "wof:placetype":"locality",
    "wof:population":76
},
  "geometry": {"coordinates":[-97.32523999999999,18.86804],"type":"Point"}
}