{
  "type": "Feature",
  "properties": {
    "iso:country":"MX",
    "name:unk_x_variant":[
        "Ixtayopan"
    ],
    "qs:a0":"Mexico",
    "qs:a1":"*Distrito Federal",
    "qs:a1_lc":"09",
    "qs:a1r":"*",
    "qs:a2":"Tl\u00e1huac",
    "qs:a2_lc":"09011",
    "qs:adm0":"Mexico",
    "qs:la_lc":"*",
    "qs:level":"locality",
    "qs:loc":"San Juan Ixtayopan",
    "qs:pop":0,
    "wof:name":"San Juan Ixtayopan",
    "wof:placetype":"neighbourhood"
},
  "geometry": {"coordinates":[-99.001017,19.233779],"type":"Point"}
}