{
  "type": "Feature",
  "properties": {
    "gn:admin1_code":"6.0",
    "gn:admin2_code":"12.0",
    "gn:asciiname":"La Maquina",
    "gn:country_code":"MX",
    "gn:dem":2172,
    "gn:feature_class":"P",
    "gn:feature_code":"PPL",
    "gn:name":"La M\u00e1quina",
    "gn:population":0,
    "gn:timezone":"America/Chihuahua",
    "iso:country":"MX",
    "wof:name":"La Maquina",
    "wof:placetype":"locality"
},
  "geometry": {"coordinates":[-106.95,28.01667],"type":"Point"}
}