{
  "type": "Feature",
  "properties": {
    "gn:admin1_code":"14",
    "gn:admin2_code":"53.0",
    "gn:asciiname":"Salsipuedes (El Puerto)",
    "gn:country_code":"MX",
    "gn:dem":2168,
    "gn:feature_class":"P",
    "gn:feature_code":"PPL",
    "gn:name":"Salsipuedes (El Puerto)",
    "gn:population":123,
    "gn:timezone":"America/Mexico_City",
    "iso:country":"MX",
    "wof:name":"Salsipuedes (El Puerto)",
    "wof:placetype":"locality",
    "wof:population":123
},
  "geometry": {"coordinates":[-101.97111,21.56083],"type":"Point"}
}