{
  "type": "Feature",
  "properties": {
    "gn:admin1_code":"15",
    "gn:admin2_code":"45",
    "gn:asciiname":"Rancho Santa Ana el Sauz",
    "gn:country_code":"MX",
    "gn:dem":2450,
    "gn:feature_class":"P",
    "gn:feature_code":"PPL",
    "gn:name":"Rancho Santa Ana el Sauz",
    "gn:population":28,
    "gn:timezone":"America/Mexico_City",
    "iso:country":"MX",
    "wof:name":"Rancho Santa Ana el Sauz",
    "wof:placetype":"locality",
    "wof:population":28
},
  "geometry": {"coordinates":[-99.53187,19.94895],"type":"Point"}
}