{
  "type": "Feature",
  "properties": {
    "gn:admin1_code":"6",
    "gn:admin2_code":"36.0",
    "gn:asciiname":"El Chamizal",
    "gn:country_code":"MX",
    "gn:dem":1326,
    "gn:feature_class":"P",
    "gn:feature_code":"PPL",
    "gn:name":"El Chamizal",
    "gn:population":0,
    "gn:timezone":"America/Chihuahua",
    "iso:country":"MX",
    "name:spa_x_preferred":[
        "El Chamizal"
    ],
    "wof:name":"El Chamizal",
    "wof:placetype":"locality"
},
  "geometry": {"coordinates":[-104.2479,27.42478],"type":"Point"}
}