{
  "type": "Feature",
  "properties": {
    "gn:admin1_code":"8",
    "gn:admin2_code":"2.0",
    "gn:asciiname":"La Barrosa",
    "gn:country_code":"MX",
    "gn:dem":455,
    "gn:feature_class":"P",
    "gn:feature_code":"PPL",
    "gn:name":"La Barrosa",
    "gn:population":5,
    "gn:timezone":"America/Mexico_City",
    "iso:country":"MX",
    "name:pol_x_preferred":[
        "La Barrosa"
    ],
    "wof:name":"La Barrosa",
    "wof:placetype":"locality",
    "wof:population":5
},
  "geometry": {"coordinates":[-103.54083,19.095],"type":"Point"}
}