{
  "type": "Feature",
  "properties": {
    "gn:admin1_code":"6.0",
    "gn:admin2_code":"65.0",
    "gn:asciiname":"Baque",
    "gn:country_code":"MX",
    "gn:dem":1414,
    "gn:feature_class":"P",
    "gn:feature_code":"PPL",
    "gn:name":"Baque",
    "gn:population":0,
    "gn:timezone":"America/Chihuahua",
    "iso:country":"MX",
    "name:spa_x_preferred":[
        "Baque"
    ],
    "wof:name":"Baque",
    "wof:placetype":"locality"
},
  "geometry": {"coordinates":[-107.79702,27.40497],"type":"Point"}
}