{
  "type": "Feature",
  "properties": {
    "gn:admin1_code":"5",
    "gn:admin2_code":"98.0",
    "gn:asciiname":"Nuevo Dolores",
    "gn:country_code":"MX",
    "gn:dem":632,
    "gn:feature_class":"P",
    "gn:feature_code":"PPL",
    "gn:name":"Nuevo Dolores",
    "gn:population":107,
    "gn:timezone":"America/Mexico_City",
    "iso:country":"MX",
    "wof:name":"Nuevo Dolores",
    "wof:placetype":"locality",
    "wof:population":107
},
  "geometry": {"coordinates":[-92.65555999999999,16.4975],"type":"Point"}
}