{
  "type": "Feature",
  "properties": {
    "gn:admin1_code":"30",
    "gn:admin2_code":"152",
    "gn:asciiname":"La Curva",
    "gn:country_code":"MX",
    "gn:dem":22,
    "gn:feature_class":"P",
    "gn:feature_code":"PPL",
    "gn:name":"La Curva",
    "gn:population":10,
    "gn:timezone":"America/Mexico_City",
    "iso:country":"MX",
    "wof:name":"La Curva",
    "wof:placetype":"locality",
    "wof:population":10
},
  "geometry": {"coordinates":[-97.96583,22.01222000000001],"type":"Point"}
}