{
  "type": "Feature",
  "properties": {
    "gn:admin1_code":"10",
    "gn:admin2_code":"37",
    "gn:asciiname":"Las Cupias",
    "gn:country_code":"MX",
    "gn:dem":569,
    "gn:feature_class":"P",
    "gn:feature_code":"PPL",
    "gn:name":"Las Cup\u00edas",
    "gn:population":12,
    "gn:timezone":"America/Monterrey",
    "iso:country":"MX",
    "name:und_x_variant":[
        "Las Cup\u00edas"
    ],
    "wof:name":"Las Cupias",
    "wof:placetype":"locality",
    "wof:population":12
},
  "geometry": {"coordinates":[-106.69481,25.12498],"type":"Point"}
}