{
  "type": "Feature",
  "properties": {
    "gn:admin1_code":"18",
    "gn:admin2_code":"2",
    "gn:asciiname":"Amequita",
    "gn:country_code":"MX",
    "gn:dem":1015,
    "gn:feature_class":"P",
    "gn:feature_code":"PPL",
    "gn:name":"Amequita",
    "gn:population":27,
    "gn:timezone":"America/Mazatlan",
    "iso:country":"MX",
    "wof:name":"Amequita",
    "wof:placetype":"locality",
    "wof:population":27
},
  "geometry": {"coordinates":[-104.44777999999999,21.04056],"type":"Point"}
}