{
  "type": "Feature",
  "properties": {
    "gn:admin1_code":"6",
    "gn:admin2_code":"27.0",
    "gn:asciiname":"Ranigochi",
    "gn:country_code":"MX",
    "gn:dem":2196,
    "gn:feature_class":"P",
    "gn:feature_code":"PPL",
    "gn:name":"Ranigochi",
    "gn:population":5,
    "gn:timezone":"America/Chihuahua",
    "iso:country":"MX",
    "wof:name":"Ranigochi",
    "wof:placetype":"locality",
    "wof:population":5
},
  "geometry": {"coordinates":[-107.64964000000001,27.59048],"type":"Point"}
}