{
  "type": "Feature",
  "properties": {
    "gn:admin1_code":"10",
    "gn:admin2_code":"18.0",
    "gn:asciiname":"San Vicente",
    "gn:country_code":"MX",
    "gn:dem":1582,
    "gn:feature_class":"P",
    "gn:feature_code":"PPL",
    "gn:name":"San Vicente",
    "gn:population":69,
    "gn:timezone":"America/Monterrey",
    "iso:country":"MX",
    "wof:name":"San Vicente",
    "wof:placetype":"locality",
    "wof:population":69
},
  "geometry": {"coordinates":[-105.35826000000002,25.8394],"type":"Point"}
}