{
  "type": "Feature",
  "properties": {
    "gn:admin1_code":"10",
    "gn:admin2_code":"4.0",
    "gn:asciiname":"Los Novios",
    "gn:country_code":"MX",
    "gn:dem":1988,
    "gn:feature_class":"P",
    "gn:feature_code":"PPL",
    "gn:name":"Los Novios",
    "gn:population":0,
    "gn:timezone":"America/Monterrey",
    "iso:country":"MX",
    "name:spa_x_preferred":[
        "Los Novios"
    ],
    "name:spa_x_variant":[
        "El Mezquite"
    ],
    "wof:name":"Los Novios",
    "wof:placetype":"locality"
},
  "geometry": {"coordinates":[-103.73488999999999,24.65791],"type":"Point"}
}