{
  "type": "Feature",
  "properties": {
    "gn:admin1_code":"15.0",
    "gn:admin2_code":"78.0",
    "gn:asciiname":"Salitre Bramador",
    "gn:country_code":"MX",
    "gn:dem":1262,
    "gn:feature_class":"P",
    "gn:feature_code":"PPL",
    "gn:name":"Salitre Bramador",
    "gn:population":0,
    "gn:timezone":"America/Mexico_City",
    "iso:country":"MX",
    "name:spa_x_preferred":[
        "Salitre Bramador"
    ],
    "name:und_x_variant":[
        "Salitre Labrador"
    ],
    "wof:name":"Salitre Bramador",
    "wof:placetype":"locality"
},
  "geometry": {"coordinates":[-100.27131,19.15787000000001],"type":"Point"}
}