{
  "type": "Feature",
  "properties": {
    "gn:admin1_code":"15",
    "gn:admin2_code":"35.0",
    "gn:asciiname":"Casa Nueva",
    "gn:country_code":"MX",
    "gn:dem":2256,
    "gn:feature_class":"P",
    "gn:feature_code":"PPL",
    "gn:name":"Casa Nueva",
    "gn:population":1578,
    "gn:timezone":"America/Mexico_City",
    "iso:country":"MX",
    "wof:name":"Casa Nueva",
    "wof:placetype":"locality",
    "wof:population":1578
},
  "geometry": {"coordinates":[-99.20944,19.83333],"type":"Point"}
}