{
  "type": "Feature",
  "properties": {
    "gn:admin1_code":"30",
    "gn:admin2_code":"125.0",
    "gn:asciiname":"El Cedro",
    "gn:country_code":"MX",
    "gn:dem":321,
    "gn:feature_class":"P",
    "gn:feature_code":"PPL",
    "gn:name":"El Cedro",
    "gn:population":54,
    "gn:timezone":"America/Mexico_City",
    "iso:country":"MX",
    "wof:name":"El Cedro",
    "wof:placetype":"locality",
    "wof:population":54
},
  "geometry": {"coordinates":[-96.625,18.92083],"type":"Point"}
}