{
  "type": "Feature",
  "properties": {
    "gn:admin1_code":"3.0",
    "gn:admin2_code":"3.0",
    "gn:asciiname":"San Bernardo",
    "gn:country_code":"MX",
    "gn:dem":178,
    "gn:feature_class":"P",
    "gn:feature_code":"PPL",
    "gn:name":"San Bernardo",
    "gn:population":0,
    "gn:timezone":"America/Mazatlan",
    "iso:country":"MX",
    "name:ceb_x_preferred":[
        "San Bernardo"
    ],
    "name:deu_x_preferred":[
        "San Bernardo"
    ],
    "name:epo_x_preferred":[
        "San Bernardo"
    ],
    "name:fin_x_preferred":[
        "San Bernardo"
    ],
    "name:fra_x_preferred":[
        "San Bernardo"
    ],
    "name:ita_x_preferred":[
        "San Bernardo"
    ],
    "name:nld_x_preferred":[
        "San Bernardo"
    ],
    "name:pol_x_preferred":[
        "San Bernardo"
    ],
    "name:por_x_preferred":[
        "San Bernardo"
    ],
    "name:ron_x_preferred":[
        "San Bernardo"
    ],
    "name:rus_x_preferred":[
        "\u0421\u0430\u043d-\u0411\u0435\u0440\u043d\u0430\u0440\u0434\u043e"
    ],
    "name:sco_x_preferred":[
        "San Bernardo"
    ],
    "name:spa_x_preferred":[
        "San Bernardo"
    ],
    "name:srp_x_preferred":[
        "San Bernardo"
    ],
    "name:swe_x_preferred":[
        "San Bernardo"
    ],
    "name:tgl_x_preferred":[
        "San Bernardo"
    ],
    "name:vie_x_preferred":[
        "San Bernardo"
    ],
    "name:war_x_preferred":[
        "San Bernardo"
    ],
    "wof:name":"San Bernardo",
    "wof:placetype":"locality"
},
  "geometry": {"coordinates":[-110.27354,23.64374],"type":"Point"}
}