{
  "type": "Feature",
  "properties": {
    "gn:admin1_code":"3.0",
    "gn:admin2_code":"3.0",
    "gn:asciiname":"San Bernardo",
    "gn:country_code":"MX",
    "gn:dem":178,
    "gn:feature_class":"P",
    "gn:feature_code":"PPL",
    "gn:name":"San Bernardo",
    "gn:population":0,
    "gn:timezone":"America/Mazatlan",
    "iso:country":"MX",
    "name:spa_x_preferred":[
        "San Bernardo"
    ],
    "wof:name":"San Bernardo",
    "wof:placetype":"locality"
},
  "geometry": {"coordinates":[-110.27354,23.64374],"type":"Point"}
}