{
  "type": "Feature",
  "properties": {
    "gn:admin1_code":"32",
    "gn:admin2_code":"10.0",
    "gn:asciiname":"La Zanja",
    "gn:country_code":"MX",
    "gn:dem":2041,
    "gn:feature_class":"P",
    "gn:feature_code":"PPL",
    "gn:name":"La Zanja",
    "gn:population":0,
    "gn:timezone":"America/Mexico_City",
    "iso:country":"MX",
    "name:spa_x_preferred":[
        "La Zanja"
    ],
    "wof:name":"La Zanja",
    "wof:placetype":"locality"
},
  "geometry": {"coordinates":[-102.99460999999999,23.31831],"type":"Point"}
}