{
  "type": "Feature",
  "properties": {
    "gn:admin1_code":"11",
    "gn:admin2_code":"18",
    "gn:asciiname":"Rancho Hernandez",
    "gn:country_code":"MX",
    "gn:dem":1727,
    "gn:feature_class":"P",
    "gn:feature_code":"PPL",
    "gn:name":"Rancho Hern\u00e1ndez",
    "gn:population":22,
    "gn:timezone":"America/Mexico_City",
    "iso:country":"MX",
    "name:und_x_variant":[
        "Rancho Hern\u00e1ndez"
    ],
    "wof:name":"Rancho Hernandez",
    "wof:placetype":"locality",
    "wof:population":22
},
  "geometry": {"coordinates":[-101.04416999999999,20.37917],"type":"Point"}
}