{
  "type": "Feature",
  "properties": {
    "gn:admin1_code":"13",
    "gn:admin2_code":"52.0",
    "gn:asciiname":"Tecamatl",
    "gn:country_code":"MX",
    "gn:dem":2340,
    "gn:feature_class":"P",
    "gn:feature_code":"PPL",
    "gn:name":"Tecamatl",
    "gn:population":56,
    "gn:timezone":"America/Mexico_City",
    "iso:country":"MX",
    "wof:name":"Tecamatl",
    "wof:placetype":"locality",
    "wof:population":56
},
  "geometry": {"coordinates":[-98.88800999999999,20.12941],"type":"Point"}
}