{
  "type": "Feature",
  "properties": {
    "gn:admin1_code":"30.0",
    "gn:asciiname":"La Berenga",
    "gn:country_code":"MX",
    "gn:dem":77,
    "gn:feature_class":"P",
    "gn:feature_code":"PPL",
    "gn:name":"La Berenga",
    "gn:population":0,
    "gn:timezone":"America/Mexico_City",
    "iso:country":"MX",
    "name:spa_x_preferred":[
        "La Berenga"
    ],
    "wof:name":"La Berenga",
    "wof:placetype":"locality"
},
  "geometry": {"coordinates":[-95.02057000000001,17.3155],"type":"Point"}
}