{
  "type": "Feature",
  "properties": {
    "gn:admin1_code":"32",
    "gn:admin2_code":"33.0",
    "gn:asciiname":"Los Bajios",
    "gn:country_code":"MX",
    "gn:dem":1516,
    "gn:feature_class":"P",
    "gn:feature_code":"PPL",
    "gn:name":"Los Baj\u00edos",
    "gn:population":0,
    "gn:timezone":"America/Mexico_City",
    "iso:country":"MX",
    "wof:name":"Los Bajios",
    "wof:placetype":"locality"
},
  "geometry": {"coordinates":[-103.14993,21.08699],"type":"Point"}
}