{
  "type": "Feature",
  "properties": {
    "gn:admin1_code":"26.0",
    "gn:admin2_code":"26.0",
    "gn:asciiname":"Bayojori",
    "gn:country_code":"MX",
    "gn:dem":18,
    "gn:feature_class":"P",
    "gn:feature_code":"PPL",
    "gn:name":"Bayojori",
    "gn:population":0,
    "gn:timezone":"America/Hermosillo",
    "iso:country":"MX",
    "wof:name":"Bayojori",
    "wof:placetype":"locality"
},
  "geometry": {"coordinates":[-109.65000000000001,27.08333],"type":"Point"}
}