{
  "type": "Feature",
  "properties": {
    "gn:admin1_code":"30",
    "gn:admin2_code":"70.0",
    "gn:asciiname":"Luis Hernandez Salazar",
    "gn:country_code":"MX",
    "gn:dem":52,
    "gn:feature_class":"P",
    "gn:feature_code":"PPL",
    "gn:name":"Luis Hern\u00e1ndez Salazar",
    "gn:population":5,
    "gn:timezone":"America/Mexico_City",
    "iso:country":"MX",
    "name:und_x_variant":[
        "Luis Hern\u00e1ndez Salazar"
    ],
    "wof:name":"Luis Hernandez Salazar",
    "wof:placetype":"locality",
    "wof:population":5
},
  "geometry": {"coordinates":[-94.54472,17.62222000000001],"type":"Point"}
}