{
  "type": "Feature",
  "properties": {
    "gn:admin1_code":"25",
    "gn:admin2_code":"4.0",
    "gn:asciiname":"El Batel",
    "gn:country_code":"MX",
    "gn:dem":1753,
    "gn:feature_class":"P",
    "gn:feature_code":"PPL",
    "gn:name":"El Batel",
    "gn:population":105,
    "gn:timezone":"America/Mazatlan",
    "iso:country":"MX",
    "wof:name":"El Batel",
    "wof:placetype":"locality",
    "wof:population":105
},
  "geometry": {"coordinates":[-105.83446000000001,23.46946],"type":"Point"}
}