{
  "type": "Feature",
  "properties": {
    "gn:admin1_code":"3",
    "gn:admin2_code":"1.0",
    "gn:asciiname":"Caleju",
    "gn:country_code":"MX",
    "gn:dem":197,
    "gn:feature_class":"P",
    "gn:feature_code":"PPL",
    "gn:name":"Calej\u00fa",
    "gn:population":0,
    "gn:timezone":"America/Mazatlan",
    "iso:country":"MX",
    "name:spa_x_preferred":[
        "Calej\u00fa"
    ],
    "wof:name":"Caleju",
    "wof:placetype":"locality"
},
  "geometry": {"coordinates":[-111.97257999999999,26.32497],"type":"Point"}
}