{
  "type": "Feature",
  "properties": {
    "gn:admin1_code":"25",
    "gn:admin2_code":"17.0",
    "gn:asciiname":"El Chapotillo",
    "gn:country_code":"MX",
    "gn:dem":1281,
    "gn:feature_class":"P",
    "gn:feature_code":"PPL",
    "gn:name":"El Chapotillo",
    "gn:population":0,
    "gn:timezone":"America/Mazatlan",
    "iso:country":"MX",
    "name:spa_x_preferred":[
        "El Chapotillo"
    ],
    "wof:name":"El Chapotillo",
    "wof:placetype":"locality"
},
  "geometry": {"coordinates":[-107.67935,25.99449],"type":"Point"}
}