{
  "type": "Feature",
  "properties": {
    "gn:admin1_code":"8.0",
    "gn:admin2_code":"4.0",
    "gn:asciiname":"La Fundicion",
    "gn:country_code":"MX",
    "gn:dem":350,
    "gn:feature_class":"P",
    "gn:feature_code":"PPL",
    "gn:name":"La Fundici\u00f3n",
    "gn:population":0,
    "gn:timezone":"America/Mexico_City",
    "iso:country":"MX",
    "wof:name":"La Fundicion",
    "wof:placetype":"locality"
},
  "geometry": {"coordinates":[-103.98333,19.13333],"type":"Point"}
}