{
  "type": "Feature",
  "properties": {
    "gn:admin1_code":"5",
    "gn:admin2_code":"107.0",
    "gn:asciiname":"Las Limas",
    "gn:country_code":"MX",
    "gn:dem":698,
    "gn:feature_class":"P",
    "gn:feature_code":"PPL",
    "gn:name":"Las Limas",
    "gn:population":6,
    "gn:timezone":"America/Mexico_City",
    "iso:country":"MX",
    "wof:name":"Las Limas",
    "wof:placetype":"locality",
    "wof:population":6
},
  "geometry": {"coordinates":[-93.04167,16.00556],"type":"Point"}
}