{
  "type": "Feature",
  "properties": {
    "gn:admin1_code":"6",
    "gn:admin2_code":"48.0",
    "gn:asciiname":"Rancho el Yaqui",
    "gn:country_code":"MX",
    "gn:dem":2023,
    "gn:feature_class":"P",
    "gn:feature_code":"PPL",
    "gn:name":"Rancho el Yaqui",
    "gn:population":4,
    "gn:timezone":"America/Chihuahua",
    "iso:country":"MX",
    "wof:name":"Rancho el Yaqui",
    "wof:placetype":"locality",
    "wof:population":4
},
  "geometry": {"coordinates":[-107.57501000000001,29.12778],"type":"Point"}
}