{
  "type": "Feature",
  "properties": {
    "gn:admin1_code":"21",
    "gn:admin2_code":"112.0",
    "gn:asciiname":"Ranchito Providencia",
    "gn:country_code":"MX",
    "gn:dem":1414,
    "gn:feature_class":"P",
    "gn:feature_code":"PPL",
    "gn:name":"Ranchito Providencia",
    "gn:population":74,
    "gn:timezone":"America/Mexico_City",
    "iso:country":"MX",
    "wof:name":"Ranchito Providencia",
    "wof:placetype":"locality",
    "wof:population":74
},
  "geometry": {"coordinates":[-97.90092,18.10938],"type":"Point"}
}