{
  "type": "Feature",
  "properties": {
    "gn:admin1_code":"14",
    "gn:admin2_code":"9",
    "gn:asciiname":"El Panchote",
    "gn:country_code":"MX",
    "gn:dem":1396,
    "gn:feature_class":"P",
    "gn:feature_code":"PPL",
    "gn:name":"El Panchote",
    "gn:population":26,
    "gn:timezone":"America/Mexico_City",
    "iso:country":"MX",
    "wof:name":"El Panchote",
    "wof:placetype":"locality",
    "wof:population":26
},
  "geometry": {"coordinates":[-103.6825,20.75194],"type":"Point"}
}