{
  "type": "Feature",
  "properties": {
    "gn:admin1_code":"15",
    "gn:admin2_code":"94",
    "gn:asciiname":"Nepantla [Granja]",
    "gn:country_code":"MX",
    "gn:dem":2171,
    "gn:feature_class":"P",
    "gn:feature_code":"PPL",
    "gn:name":"Nepantla [Granja]",
    "gn:population":35,
    "gn:timezone":"America/Mexico_City",
    "iso:country":"MX",
    "wof:name":"Nepantla [Granja]",
    "wof:placetype":"locality",
    "wof:population":35
},
  "geometry": {"coordinates":[-98.84139999999999,18.99873],"type":"Point"}
}