{
  "type": "Feature",
  "properties": {
    "gn:admin1_code":"7.0",
    "gn:admin2_code":"38.0",
    "gn:asciiname":"Lagunitas",
    "gn:country_code":"MX",
    "gn:dem":916,
    "gn:feature_class":"P",
    "gn:feature_code":"PPL",
    "gn:name":"Lagunitas",
    "gn:population":0,
    "gn:timezone":"America/Monterrey",
    "iso:country":"MX",
    "name:ceb_x_preferred":[
        "Lagunitas"
    ],
    "name:deu_x_preferred":[
        "Lagunitas"
    ],
    "name:fra_x_preferred":[
        "Lagunitas"
    ],
    "name:spa_x_preferred":[
        "Lagunitas"
    ],
    "name:srp_x_preferred":[
        "\u041b\u0430\u0433\u0443\u043d\u0438\u0442\u0430\u0441"
    ],
    "name:swe_x_preferred":[
        "Lagunitas"
    ],
    "name:und_x_variant":[
        "Rancho Lagunitas"
    ],
    "wof:name":"Lagunitas",
    "wof:placetype":"locality"
},
  "geometry": {"coordinates":[-101.82626999999999,29.09721],"type":"Point"}
}