{
  "type": "Feature",
  "properties": {
    "gn:admin1_code":"32.0",
    "gn:admin2_code":"21.0",
    "gn:asciiname":"Potrero de Arriba",
    "gn:country_code":"MX",
    "gn:dem":2138,
    "gn:feature_class":"P",
    "gn:feature_code":"PPL",
    "gn:name":"Potrero de Arriba",
    "gn:population":0,
    "gn:timezone":"America/Mexico_City",
    "iso:country":"MX",
    "name:spa_x_preferred":[
        "Potrero de Arriba"
    ],
    "wof:name":"Potrero de Arriba",
    "wof:placetype":"locality"
},
  "geometry": {"coordinates":[-103.71455,23.22034],"type":"Point"}
}