{
  "type": "Feature",
  "properties": {
    "gn:admin1_code":"10",
    "gn:admin2_code":"35",
    "gn:asciiname":"Las Cuevas",
    "gn:country_code":"MX",
    "gn:dem":2476,
    "gn:feature_class":"P",
    "gn:feature_code":"PPL",
    "gn:name":"Las Cuevas",
    "gn:population":22,
    "gn:timezone":"America/Monterrey",
    "iso:country":"MX",
    "name:ceb_x_preferred":[
        "Las Cuevas"
    ],
    "name:deu_x_preferred":[
        "Las Cuevas"
    ],
    "name:nds_x_preferred":[
        "Las Cuevas"
    ],
    "name:spa_x_preferred":[
        "Las Cuevas"
    ],
    "name:swe_x_preferred":[
        "Las Cuevas"
    ],
    "wof:name":"Las Cuevas",
    "wof:placetype":"locality",
    "wof:population":22
},
  "geometry": {"coordinates":[-106.3327,25.4315],"type":"Point"}
}