{
  "type": "Feature",
  "properties": {
    "gn:admin1_code":"14",
    "gn:admin2_code":"116",
    "gn:asciiname":"Los Aceros",
    "gn:country_code":"MX",
    "gn:dem":1875,
    "gn:feature_class":"P",
    "gn:feature_code":"PPL",
    "gn:name":"Los Aceros",
    "gn:population":30,
    "gn:timezone":"America/Mexico_City",
    "iso:country":"MX",
    "wof:name":"Los Aceros",
    "wof:placetype":"locality",
    "wof:population":30
},
  "geometry": {"coordinates":[-102.62361,21.58111],"type":"Point"}
}