{
  "type": "Feature",
  "properties": {
    "gn:admin1_code":"6.0",
    "gn:admin2_code":"27.0",
    "gn:asciiname":"Chutanachi",
    "gn:country_code":"MX",
    "gn:dem":2339,
    "gn:feature_class":"P",
    "gn:feature_code":"PPL",
    "gn:name":"Chutanachi",
    "gn:population":0,
    "gn:timezone":"America/Chihuahua",
    "iso:country":"MX",
    "name:spa_x_preferred":[
        "Chutanachi"
    ],
    "wof:name":"Chutanachi",
    "wof:placetype":"locality"
},
  "geometry": {"coordinates":[-107.22946,27.13439],"type":"Point"}
}