{
  "type": "Feature",
  "properties": {
    "gn:admin1_code":"13",
    "gn:admin2_code":"62.0",
    "gn:asciiname":"Tlalcuapa",
    "gn:country_code":"MX",
    "gn:dem":667,
    "gn:feature_class":"P",
    "gn:feature_code":"PPL",
    "gn:name":"Tlalcuapa",
    "gn:population":0,
    "gn:timezone":"America/Mexico_City",
    "iso:country":"MX",
    "name:spa_x_preferred":[
        "Tlalcuapa"
    ],
    "wof:name":"Tlalcuapa",
    "wof:placetype":"locality"
},
  "geometry": {"coordinates":[-98.78086,21.01641],"type":"Point"}
}