{
  "type": "Feature",
  "properties": {
    "gn:admin1_code":"13",
    "gn:admin2_code":"24.0",
    "gn:asciiname":"Palmillas",
    "gn:country_code":"MX",
    "gn:dem":2060,
    "gn:feature_class":"P",
    "gn:feature_code":"PPL",
    "gn:name":"Palmillas",
    "gn:population":130,
    "gn:timezone":"America/Mexico_City",
    "iso:country":"MX",
    "wof:name":"Palmillas",
    "wof:placetype":"locality",
    "wof:population":130
},
  "geometry": {"coordinates":[-98.53124,20.26578],"type":"Point"}
}