{
  "type": "Feature",
  "properties": {
    "gn:admin1_code":"4",
    "gn:admin2_code":"3.0",
    "gn:asciiname":"La Florida",
    "gn:country_code":"MX",
    "gn:dem":6,
    "gn:feature_class":"P",
    "gn:feature_code":"PPL",
    "gn:name":"La Florida",
    "gn:population":28,
    "gn:timezone":"America/Merida",
    "iso:country":"MX",
    "name:bre_x_preferred":[
        "La Florida"
    ],
    "name:ceb_x_preferred":[
        "La Florida"
    ],
    "name:fra_x_preferred":[
        "La Florida"
    ],
    "name:ita_x_preferred":[
        "La Florida"
    ],
    "name:nld_x_preferred":[
        "La Florida"
    ],
    "name:sco_x_preferred":[
        "La Florida"
    ],
    "name:spa_x_preferred":[
        "La Florida"
    ],
    "name:srp_x_preferred":[
        "\u041b\u0430 \u0424\u043b\u043e\u0440\u0438\u0434\u0430"
    ],
    "name:swe_x_preferred":[
        "La Florida"
    ],
    "wof:name":"La Florida",
    "wof:placetype":"locality",
    "wof:population":28
},
  "geometry": {"coordinates":[-91.49972,18.12667],"type":"Point"}
}