{
  "type": "Feature",
  "properties": {
    "gn:admin1_code":"30",
    "gn:admin2_code":"199.0",
    "gn:asciiname":"Colonia Marco Antonio Munoz",
    "gn:country_code":"MX",
    "gn:dem":29,
    "gn:feature_class":"P",
    "gn:feature_code":"PPL",
    "gn:name":"Colonia Marco Antonio Mu\u00f1oz",
    "gn:population":189,
    "gn:timezone":"America/Mexico_City",
    "iso:country":"MX",
    "name:und_x_variant":[
        "Colonia Marco Antonio Mu\u00f1oz"
    ],
    "wof:name":"Colonia Marco Antonio Munoz",
    "wof:placetype":"locality",
    "wof:population":189
},
  "geometry": {"coordinates":[-94.63583,17.96417000000001],"type":"Point"}
}