{
  "type": "Feature",
  "properties": {
    "gn:admin1_code":"32",
    "gn:admin2_code":"13.0",
    "gn:asciiname":"El Palmarito",
    "gn:country_code":"MX",
    "gn:dem":2175,
    "gn:feature_class":"P",
    "gn:feature_code":"PPL",
    "gn:name":"El Palmarito",
    "gn:population":0,
    "gn:timezone":"America/Mexico_City",
    "iso:country":"MX",
    "name:spa_x_preferred":[
        "El Palmarito"
    ],
    "wof:name":"El Palmarito",
    "wof:placetype":"locality"
},
  "geometry": {"coordinates":[-102.79667000000001,23.05448],"type":"Point"}
}