{
  "type": "Feature",
  "properties": {
    "gn:admin1_code":"17",
    "gn:admin2_code":"4",
    "gn:asciiname":"Campo los Pilares",
    "gn:country_code":"MX",
    "gn:dem":1362,
    "gn:feature_class":"P",
    "gn:feature_code":"PPL",
    "gn:name":"Campo los Pilares",
    "gn:population":23,
    "gn:timezone":"America/Mexico_City",
    "iso:country":"MX",
    "wof:name":"Campo los Pilares",
    "wof:placetype":"locality",
    "wof:population":23
},
  "geometry": {"coordinates":[-98.88916999999999,18.78306],"type":"Point"}
}