{
  "type": "Feature",
  "properties": {
    "gn:admin1_code":"6.0",
    "gn:admin2_code":"11.0",
    "gn:asciiname":"Laguna San Francisco",
    "gn:country_code":"MX",
    "gn:dem":1232,
    "gn:feature_class":"P",
    "gn:feature_code":"PPL",
    "gn:name":"Laguna San Francisco",
    "gn:population":0,
    "gn:timezone":"America/Chihuahua",
    "iso:country":"MX",
    "wof:name":"Laguna San Francisco",
    "wof:placetype":"locality"
},
  "geometry": {"coordinates":[-105.21129000000001,27.64826],"type":"Point"}
}