{
  "type": "Feature",
  "properties": {
    "gn:admin1_code":"2.0",
    "gn:admin2_code":"1.0",
    "gn:asciiname":"El Pescado",
    "gn:country_code":"MX",
    "gn:dem":988,
    "gn:feature_class":"P",
    "gn:feature_code":"PPL",
    "gn:name":"El Pescado",
    "gn:population":2,
    "gn:timezone":"America/Tijuana",
    "iso:country":"MX",
    "name:spa_x_preferred":[
        "El Pescado"
    ],
    "wof:name":"El Pescado",
    "wof:placetype":"locality",
    "wof:population":2
},
  "geometry": {"coordinates":[-116.10250000000001,31.7725],"type":"Point"}
}