{
  "type": "Feature",
  "properties": {
    "gn:admin1_code":"30.0",
    "gn:admin2_code":"124.0",
    "gn:asciiname":"San Antonio Ojital",
    "gn:country_code":"MX",
    "gn:dem":236,
    "gn:feature_class":"P",
    "gn:feature_code":"PPL",
    "gn:name":"San Antonio Ojital",
    "gn:population":193,
    "gn:timezone":"America/Mexico_City",
    "iso:country":"MX",
    "name:spa_x_preferred":[
        "San Antonio Ojital"
    ],
    "wof:name":"San Antonio Ojital",
    "wof:placetype":"locality",
    "wof:population":193
},
  "geometry": {"coordinates":[-97.36360999999999,20.46111],"type":"Point"}
}