{
  "type": "Feature",
  "properties": {
    "gn:admin1_code":"30",
    "gn:admin2_code":"54.0",
    "gn:asciiname":"El Sardinel",
    "gn:country_code":"MX",
    "gn:dem":18,
    "gn:feature_class":"P",
    "gn:feature_code":"PPL",
    "gn:name":"El Sardinel",
    "gn:population":7,
    "gn:timezone":"America/Mexico_City",
    "iso:country":"MX",
    "wof:name":"El Sardinel",
    "wof:placetype":"locality",
    "wof:population":7
},
  "geometry": {"coordinates":[-95.83278,18.30833],"type":"Point"}
}