{
  "type": "Feature",
  "properties": {
    "gn:admin1_code":"5",
    "gn:admin2_code":"97.0",
    "gn:asciiname":"Barbona",
    "gn:country_code":"MX",
    "gn:dem":42,
    "gn:feature_class":"P",
    "gn:feature_code":"PPL",
    "gn:name":"Barbona",
    "gn:population":0,
    "gn:timezone":"America/Mexico_City",
    "iso:country":"MX",
    "name:azb_x_preferred":[
        "\u0628\u0627\u0631\u0628\u0648\u0646\u0627"
    ],
    "name:bul_x_preferred":[
        "\u0411\u0430\u0440\u0431\u043e\u043d\u0430"
    ],
    "name:ceb_x_preferred":[
        "Barbona"
    ],
    "name:deu_x_preferred":[
        "Barbona"
    ],
    "name:epo_x_preferred":[
        "Barbona"
    ],
    "name:est_x_preferred":[
        "Barbona"
    ],
    "name:eus_x_preferred":[
        "Barbona"
    ],
    "name:fas_x_preferred":[
        "\u0628\u0627\u0631\u0628\u0648\u0646\u0627"
    ],
    "name:fra_x_preferred":[
        "Barbona"
    ],
    "name:hun_x_preferred":[
        "Barbona"
    ],
    "name:hye_x_preferred":[
        "\u0532\u0561\u0580\u0562\u0578\u0576\u0561"
    ],
    "name:ind_x_preferred":[
        "Barbona"
    ],
    "name:ita_x_preferred":[
        "Barbona"
    ],
    "name:jpn_x_preferred":[
        "\u30d0\u30eb\u30dc\u30fc\u30ca"
    ],
    "name:kaz_x_preferred":[
        "\u0411\u0430\u0440\u0431\u043e\u043d\u0430"
    ],
    "name:lat_x_preferred":[
        "Barbona"
    ],
    "name:lmo_x_preferred":[
        "Barbona"
    ],
    "name:msa_x_preferred":[
        "Barbona"
    ],
    "name:nap_x_preferred":[
        "Barbona"
    ],
    "name:nld_x_preferred":[
        "Barbona"
    ],
    "name:pms_x_preferred":[
        "Barbona"
    ],
    "name:pol_x_preferred":[
        "Barbona"
    ],
    "name:por_x_preferred":[
        "Barbona"
    ],
    "name:ron_x_preferred":[
        "Barbona"
    ],
    "name:rus_x_preferred":[
        "\u0411\u0430\u0440\u0431\u043e\u043d\u0430"
    ],
    "name:scn_x_preferred":[
        "Barbona"
    ],
    "name:spa_x_preferred":[
        "Barbona"
    ],
    "name:srp_x_preferred":[
        "\u0411\u0430\u0440\u0431\u043e\u043d\u0430"
    ],
    "name:tgl_x_preferred":[
        "Barbona"
    ],
    "name:ukr_x_preferred":[
        "\u0411\u0430\u0440\u0431\u043e\u043d\u0430"
    ],
    "name:uzb_x_preferred":[
        "Barbona"
    ],
    "name:vec_x_preferred":[
        "Barbona"
    ],
    "name:vie_x_preferred":[
        "Barbona"
    ],
    "name:vol_x_preferred":[
        "Barbona"
    ],
    "name:war_x_preferred":[
        "Barbona"
    ],
    "name:zho_x_preferred":[
        "\u5df4\u5c14\u535a\u7eb3"
    ],
    "wof:name":"Barbona",
    "wof:placetype":"locality"
},
  "geometry": {"coordinates":[-93.78333000000001,16.11667000000001],"type":"Point"}
}