{
  "type": "Feature",
  "properties": {
    "gn:admin1_code":"25",
    "gn:admin2_code":"7",
    "gn:asciiname":"El Orito",
    "gn:country_code":"MX",
    "gn:dem":370,
    "gn:feature_class":"P",
    "gn:feature_code":"PPL",
    "gn:name":"El Orito",
    "gn:population":15,
    "gn:timezone":"America/Mazatlan",
    "iso:country":"MX",
    "wof:name":"El Orito",
    "wof:placetype":"locality",
    "wof:population":15
},
  "geometry": {"coordinates":[-108.18161000000001,26.73423],"type":"Point"}
}