{
  "type": "Feature",
  "properties": {
    "gn:admin1_code":"11.0",
    "gn:admin2_code":"19.0",
    "gn:asciiname":"Sabino Seco",
    "gn:country_code":"MX",
    "gn:dem":1934,
    "gn:feature_class":"P",
    "gn:feature_code":"PPL",
    "gn:name":"Sabino Seco",
    "gn:population":0,
    "gn:timezone":"America/Mexico_City",
    "iso:country":"MX",
    "name:spa_x_preferred":[
        "Sabino Seco"
    ],
    "name:spa_x_variant":[
        "San Lorenzo"
    ],
    "wof:name":"Sabino Seco",
    "wof:placetype":"locality"
},
  "geometry": {"coordinates":[-100.48647,20.02727],"type":"Point"}
}