{
  "type": "Feature",
  "properties": {
    "gn:admin1_code":"3",
    "gn:admin2_code":"9.0",
    "gn:asciiname":"Lote Diez",
    "gn:country_code":"MX",
    "gn:dem":53,
    "gn:feature_class":"P",
    "gn:feature_code":"PPL",
    "gn:name":"Lote Diez",
    "gn:population":0,
    "gn:timezone":"America/Mazatlan",
    "iso:country":"MX",
    "name:spa_x_preferred":[
        "Lote Diez"
    ],
    "wof:name":"Lote Diez",
    "wof:placetype":"locality"
},
  "geometry": {"coordinates":[-111.55822000000001,26.26779],"type":"Point"}
}