{
  "type": "Feature",
  "properties": {
    "gn:admin1_code":"28.0",
    "gn:admin2_code":"5.0",
    "gn:asciiname":"El Cipres",
    "gn:country_code":"MX",
    "gn:dem":107,
    "gn:feature_class":"P",
    "gn:feature_code":"PPL",
    "gn:name":"El Cipr\u00e9s",
    "gn:population":10,
    "gn:timezone":"America/Monterrey",
    "iso:country":"MX",
    "name:spa_x_preferred":[
        "El Cipr\u00e9s"
    ],
    "wof:name":"El Cipres",
    "wof:placetype":"locality",
    "wof:population":10
},
  "geometry": {"coordinates":[-98.47221999999999,24.91861],"type":"Point"}
}