{
  "type": "Feature",
  "properties": {
    "gn:admin1_code":"30",
    "gn:admin2_code":"85",
    "gn:asciiname":"Cruz Verde",
    "gn:country_code":"MX",
    "gn:dem":1135,
    "gn:feature_class":"P",
    "gn:feature_code":"PPL",
    "gn:name":"Cruz Verde",
    "gn:population":26,
    "gn:timezone":"America/Mexico_City",
    "iso:country":"MX",
    "wof:name":"Cruz Verde",
    "wof:placetype":"locality",
    "wof:population":26
},
  "geometry": {"coordinates":[-97.05056,18.86278],"type":"Point"}
}