{
  "type": "Feature",
  "properties": {
    "gn:admin1_code":"14",
    "gn:admin2_code":"19.0",
    "gn:asciiname":"El Conejo (Agua Bendita)",
    "gn:country_code":"MX",
    "gn:dem":1418,
    "gn:feature_class":"P",
    "gn:feature_code":"PPL",
    "gn:name":"El Conejo (Agua Bendita)",
    "gn:population":7,
    "gn:timezone":"America/Mazatlan",
    "iso:country":"MX",
    "wof:name":"El Conejo (Agua Bendita)",
    "wof:placetype":"locality",
    "wof:population":7
},
  "geometry": {"coordinates":[-104.13472,21.80111],"type":"Point"}
}