{
  "type": "Feature",
  "properties": {
    "gn:admin1_code":"10",
    "gn:admin2_code":"26",
    "gn:asciiname":"Las Delicias",
    "gn:country_code":"MX",
    "gn:dem":2510,
    "gn:feature_class":"P",
    "gn:feature_code":"PPL",
    "gn:name":"Las Delicias",
    "gn:population":16,
    "gn:timezone":"America/Monterrey",
    "iso:country":"MX",
    "wof:name":"Las Delicias",
    "wof:placetype":"locality",
    "wof:population":16
},
  "geometry": {"coordinates":[-105.98366,24.43638],"type":"Point"}
}