{
  "type": "Feature",
  "properties": {
    "gn:admin1_code":"24",
    "gn:admin2_code":"3.0",
    "gn:asciiname":"La Laja",
    "gn:country_code":"MX",
    "gn:dem":449,
    "gn:feature_class":"P",
    "gn:feature_code":"PPL",
    "gn:name":"La Laja",
    "gn:population":115,
    "gn:timezone":"America/Mexico_City",
    "iso:country":"MX",
    "wof:name":"La Laja",
    "wof:placetype":"locality",
    "wof:population":115
},
  "geometry": {"coordinates":[-99.0575,21.60083],"type":"Point"}
}