{
  "type": "Feature",
  "properties": {
    "gn:admin1_code":"30.0",
    "gn:asciiname":"Los Laureles",
    "gn:country_code":"MX",
    "gn:dem":33,
    "gn:feature_class":"P",
    "gn:feature_code":"PPL",
    "gn:name":"Los Laureles",
    "gn:population":0,
    "gn:timezone":"America/Mexico_City",
    "iso:country":"MX",
    "name:por_x_preferred":[
        "Los Laureles"
    ],
    "name:spa_x_preferred":[
        "Los Laureles"
    ],
    "wof:name":"Los Laureles",
    "wof:placetype":"locality"
},
  "geometry": {"coordinates":[-95.38369,18.25351],"type":"Point"}
}