{
  "type": "Feature",
  "properties": {
    "gn:admin1_code":"28.0",
    "gn:admin2_code":"34.0",
    "gn:asciiname":"Guadalupe",
    "gn:country_code":"MX",
    "gn:dem":321,
    "gn:feature_class":"P",
    "gn:feature_code":"PPL",
    "gn:name":"Guadalupe",
    "gn:population":2,
    "gn:timezone":"America/Monterrey",
    "iso:country":"MX",
    "name:spa_x_preferred":[
        "Guadalupe"
    ],
    "wof:name":"Guadalupe",
    "wof:placetype":"locality",
    "wof:population":2
},
  "geometry": {"coordinates":[-99.05222000000001,24.42333],"type":"Point"}
}