{
  "type": "Feature",
  "properties": {
    "gn:admin1_code":"26",
    "gn:admin2_code":"36.0",
    "gn:asciiname":"Charco Hondo",
    "gn:country_code":"MX",
    "gn:dem":772,
    "gn:feature_class":"P",
    "gn:feature_code":"PPL",
    "gn:name":"Charco Hondo",
    "gn:population":8,
    "gn:timezone":"America/Hermosillo",
    "iso:country":"MX",
    "wof:name":"Charco Hondo",
    "wof:placetype":"locality",
    "wof:population":8
},
  "geometry": {"coordinates":[-111.13388999999999,30.76639],"type":"Point"}
}