{
  "type": "Feature",
  "properties": {
    "gn:admin1_code":"17",
    "gn:admin2_code":"13.0",
    "gn:asciiname":"Colonia Juarez",
    "gn:country_code":"MX",
    "gn:dem":1399,
    "gn:feature_class":"P",
    "gn:feature_code":"PPL",
    "gn:name":"Colonia Ju\u00e1rez",
    "gn:population":5,
    "gn:timezone":"America/Mexico_City",
    "iso:country":"MX",
    "name:und_x_variant":[
        "Colonia Ju\u00e1rez"
    ],
    "wof:name":"Colonia Juarez",
    "wof:placetype":"locality",
    "wof:population":5
},
  "geometry": {"coordinates":[-98.85167,18.71],"type":"Point"}
}