{
  "type": "Feature",
  "properties": {
    "gn:admin1_code":"16",
    "gn:admin2_code":"97.0",
    "gn:asciiname":"Los Nogales",
    "gn:country_code":"MX",
    "gn:dem":916,
    "gn:feature_class":"P",
    "gn:feature_code":"PPL",
    "gn:name":"Los Nogales",
    "gn:population":91,
    "gn:timezone":"America/Mexico_City",
    "iso:country":"MX",
    "wof:name":"Los Nogales",
    "wof:placetype":"locality",
    "wof:population":91
},
  "geometry": {"coordinates":[-101.55139,18.95722],"type":"Point"}
}