{
  "type": "Feature",
  "properties": {
    "gn:admin1_code":"10",
    "gn:admin2_code":"32.0",
    "gn:asciiname":"Palo Blanco",
    "gn:country_code":"MX",
    "gn:dem":1856,
    "gn:feature_class":"P",
    "gn:feature_code":"PPL",
    "gn:name":"Palo Blanco",
    "gn:population":0,
    "gn:timezone":"America/Monterrey",
    "iso:country":"MX",
    "name:spa_x_preferred":[
        "Palo Blanco"
    ],
    "wof:name":"Palo Blanco",
    "wof:placetype":"locality"
},
  "geometry": {"coordinates":[-105.49039,25.26353],"type":"Point"}
}