{
  "type": "Feature",
  "properties": {
    "gn:admin1_code":"18",
    "gn:admin2_code":"3",
    "gn:asciiname":"El Ombligo",
    "gn:country_code":"MX",
    "gn:dem":608,
    "gn:feature_class":"P",
    "gn:feature_code":"PPL",
    "gn:name":"El Ombligo",
    "gn:population":15,
    "gn:timezone":"America/Mazatlan",
    "iso:country":"MX",
    "wof:name":"El Ombligo",
    "wof:placetype":"locality",
    "wof:population":15
},
  "geometry": {"coordinates":[-104.53055999999999,20.92833],"type":"Point"}
}