{
  "type": "Feature",
  "properties": {
    "gn:admin1_code":"10",
    "gn:admin2_code":"14.0",
    "gn:asciiname":"La Tinajita",
    "gn:country_code":"MX",
    "gn:dem":1972,
    "gn:feature_class":"P",
    "gn:feature_code":"PPL",
    "gn:name":"La Tinajita",
    "gn:population":0,
    "gn:timezone":"America/Monterrey",
    "iso:country":"MX",
    "name:spa_x_preferred":[
        "La Tinajita"
    ],
    "wof:name":"La Tinajita",
    "wof:placetype":"locality"
},
  "geometry": {"coordinates":[-104.38437999999999,23.74798],"type":"Point"}
}