{
  "type": "Feature",
  "properties": {
    "gn:admin1_code":"6.0",
    "gn:admin2_code":"29.0",
    "gn:asciiname":"Los Algodones",
    "gn:country_code":"MX",
    "gn:dem":1147,
    "gn:feature_class":"P",
    "gn:feature_code":"PPL",
    "gn:name":"Los Algodones",
    "gn:population":0,
    "gn:timezone":"America/Chihuahua",
    "iso:country":"MX",
    "name:dan_x_preferred":[
        "Los Algodones"
    ],
    "name:deu_x_preferred":[
        "Vicente Guerrero"
    ],
    "name:fra_x_preferred":[
        "Los Algodones"
    ],
    "name:nld_x_preferred":[
        "Los Algodones"
    ],
    "name:nor_x_preferred":[
        "Los Algodones"
    ],
    "name:rus_x_preferred":[
        "\u041b\u043e\u0441-\u0410\u043b\u044c\u0433\u043e\u0434\u043e\u043d\u0435\u0441"
    ],
    "name:spa_x_preferred":[
        "Los Algodones"
    ],
    "name:spa_x_variant":[
        "Algodones"
    ],
    "wof:name":"Los Algodones",
    "wof:placetype":"locality"
},
  "geometry": {"coordinates":[-107.62596000000001,26.23093],"type":"Point"}
}