{
  "type": "Feature",
  "properties": {
    "gn:admin1_code":"28",
    "gn:admin2_code":"33.0",
    "gn:asciiname":"Gatos Gueeros",
    "gn:country_code":"MX",
    "gn:dem":27,
    "gn:feature_class":"P",
    "gn:feature_code":"PPL",
    "gn:name":"Gatos G\u00fceros",
    "gn:population":6,
    "gn:timezone":"America/Monterrey",
    "iso:country":"MX",
    "name:und_x_variant":[
        "Gatos G\u00fceros"
    ],
    "wof:name":"Gatos Gueeros",
    "wof:placetype":"locality",
    "wof:population":6
},
  "geometry": {"coordinates":[-98.05389,25.83611],"type":"Point"}
}