{
  "type": "Feature",
  "properties": {
    "gn:admin1_code":"20",
    "gn:admin2_code":"122",
    "gn:asciiname":"Colonia Extranjera",
    "gn:country_code":"MX",
    "gn:dem":888,
    "gn:feature_class":"P",
    "gn:feature_code":"PPL",
    "gn:name":"Colonia Extranjera",
    "gn:population":20,
    "gn:timezone":"America/Mexico_City",
    "iso:country":"MX",
    "wof:name":"Colonia Extranjera",
    "wof:placetype":"locality",
    "wof:population":20
},
  "geometry": {"coordinates":[-95.9725,16.43278],"type":"Point"}
}