{
  "type": "Feature",
  "properties": {
    "gn:admin1_code":"16.0",
    "gn:admin2_code":"83.0",
    "gn:asciiname":"Los Monos",
    "gn:country_code":"MX",
    "gn:dem":1765,
    "gn:feature_class":"P",
    "gn:feature_code":"PPL",
    "gn:name":"Los Monos",
    "gn:population":0,
    "gn:timezone":"America/Mexico_City",
    "iso:country":"MX",
    "name:spa_x_preferred":[
        "Los Monos"
    ],
    "wof:name":"Los Monos",
    "wof:placetype":"locality"
},
  "geometry": {"coordinates":[-102.33456,19.21844],"type":"Point"}
}