{
  "type": "Feature",
  "properties": {
    "gn:admin1_code":"5",
    "gn:admin2_code":"69.0",
    "gn:asciiname":"Nueva Urbina",
    "gn:country_code":"MX",
    "gn:dem":78,
    "gn:feature_class":"P",
    "gn:feature_code":"PPL",
    "gn:name":"Nueva Urbina",
    "gn:population":0,
    "gn:timezone":"America/Mexico_City",
    "iso:country":"MX",
    "name:spa_x_preferred":[
        "Nueva Urbina"
    ],
    "name:und_x_variant":[
        "Nuevo Urbina"
    ],
    "wof:name":"Nueva Urbina",
    "wof:placetype":"locality"
},
  "geometry": {"coordinates":[-93.24863999999999,15.72758],"type":"Point"}
}