{
  "type": "Feature",
  "properties": {
    "gn:admin1_code":"14",
    "gn:admin2_code":"6.0",
    "gn:asciiname":"El Portezuelo",
    "gn:country_code":"MX",
    "gn:dem":1388,
    "gn:feature_class":"P",
    "gn:feature_code":"PPL",
    "gn:name":"El Portezuelo",
    "gn:population":649,
    "gn:timezone":"America/Mexico_City",
    "iso:country":"MX",
    "name:spa_x_preferred":[
        "El Portezuelo"
    ],
    "name:und_x_variant":[
        "Portezuelo"
    ],
    "wof:name":"El Portezuelo",
    "wof:placetype":"locality",
    "wof:population":649
},
  "geometry": {"coordinates":[-104.04646,20.59968],"type":"Point"}
}