{
  "type": "Feature",
  "properties": {
    "gn:admin1_code":"5.0",
    "gn:asciiname":"Nueva Linda",
    "gn:country_code":"MX",
    "gn:dem":553,
    "gn:feature_class":"P",
    "gn:feature_code":"PPL",
    "gn:name":"Nueva Linda",
    "gn:population":0,
    "gn:timezone":"America/Mexico_City",
    "iso:country":"MX",
    "name:spa_x_preferred":[
        "Nueva Linda"
    ],
    "wof:name":"Nueva Linda",
    "wof:placetype":"locality"
},
  "geometry": {"coordinates":[-92.48829000000001,15.9647],"type":"Point"}
}