{
  "type": "Feature",
  "properties": {
    "gn:admin1_code":"11",
    "gn:admin2_code":"14",
    "gn:asciiname":"Las Crucitas (Rancho de Guadalupe)",
    "gn:country_code":"MX",
    "gn:dem":2132,
    "gn:feature_class":"P",
    "gn:feature_code":"PPL",
    "gn:name":"Las Crucitas (Rancho de Guadalupe)",
    "gn:population":42,
    "gn:timezone":"America/Mexico_City",
    "iso:country":"MX",
    "wof:name":"Las Crucitas (Rancho de Guadalupe)",
    "wof:placetype":"locality",
    "wof:population":42
},
  "geometry": {"coordinates":[-101.06639,20.9475],"type":"Point"}
}