{
  "type": "Feature",
  "properties": {
    "gn:admin1_code":"7",
    "gn:admin2_code":"30.0",
    "gn:asciiname":"El Pozo",
    "gn:country_code":"MX",
    "gn:dem":1953,
    "gn:feature_class":"P",
    "gn:feature_code":"PPL",
    "gn:name":"El Pozo",
    "gn:population":0,
    "gn:timezone":"America/Monterrey",
    "iso:country":"MX",
    "name:deu_x_preferred":[
        "El Pozo"
    ],
    "name:spa_x_preferred":[
        "El Pozo"
    ],
    "name:srp_x_preferred":[
        "\u0415\u043b \u041f\u043e\u0437\u043e"
    ],
    "wof:name":"El Pozo",
    "wof:placetype":"locality"
},
  "geometry": {"coordinates":[-100.9945,24.61241],"type":"Point"}
}