{
  "type": "Feature",
  "properties": {
    "gn:admin1_code":"6.0",
    "gn:admin2_code":"48.0",
    "gn:asciiname":"Montano",
    "gn:country_code":"MX",
    "gn:dem":1904,
    "gn:feature_class":"P",
    "gn:feature_code":"PPL",
    "gn:name":"Monta\u00f1o",
    "gn:population":0,
    "gn:timezone":"America/Chihuahua",
    "iso:country":"MX",
    "name:spa_x_preferred":[
        "Monta\u00f1o"
    ],
    "name:spa_x_variant":[
        "Rancho Monta\u00f1o"
    ],
    "wof:name":"Montano",
    "wof:placetype":"locality"
},
  "geometry": {"coordinates":[-107.41795999999999,29.04094000000001],"type":"Point"}
}