{
  "type": "Feature",
  "properties": {
    "gn:admin1_code":"15",
    "gn:admin2_code":"120.0",
    "gn:asciiname":"El Nido",
    "gn:country_code":"MX",
    "gn:dem":2310,
    "gn:feature_class":"P",
    "gn:feature_code":"PPL",
    "gn:name":"El Nido",
    "gn:population":456,
    "gn:timezone":"America/Mexico_City",
    "iso:country":"MX",
    "name:ceb_x_preferred":[
        "El Nido"
    ],
    "name:ita_x_preferred":[
        "El nido"
    ],
    "name:spa_x_preferred":[
        "El Nido"
    ],
    "name:srp_x_preferred":[
        "\u0415\u043b \u041d\u0438\u0434\u043e"
    ],
    "name:swe_x_preferred":[
        "El Nido"
    ],
    "wof:name":"El Nido",
    "wof:placetype":"locality",
    "wof:population":456
},
  "geometry": {"coordinates":[-99.07528000000001,19.83778],"type":"Point"}
}