{
  "type": "Feature",
  "properties": {
    "gn:admin1_code":"10.0",
    "gn:admin2_code":"37.0",
    "gn:asciiname":"El Rincon de Galancita (El Rincon de los Alisos)",
    "gn:cc2":"MX",
    "gn:country_code":"MX",
    "gn:dem":1126,
    "gn:feature_class":"P",
    "gn:feature_code":"PPL",
    "gn:name":"El Rinc\u00f3n de Galancita (El Rinc\u00f3n de los Alisos)",
    "gn:population":54,
    "gn:timezone":"America/Monterrey",
    "iso:country":"MX",
    "name:und_x_variant":[
        "Rinc\u00f3n",
        "El Rinc\u00f3n"
    ],
    "wof:name":"El Rincon de Galancita (El Rincon de los Alisos)",
    "wof:placetype":"locality",
    "wof:population":54
},
  "geometry": {"coordinates":[-106.73869999999999,25.16053],"type":"Point"}
}