{
  "type": "Feature",
  "properties": {
    "gn:admin1_code":"6",
    "gn:admin2_code":"7",
    "gn:asciiname":"El Riito",
    "gn:country_code":"MX",
    "gn:dem":2516,
    "gn:feature_class":"P",
    "gn:feature_code":"PPL",
    "gn:name":"El Ri\u00edto",
    "gn:population":15,
    "gn:timezone":"America/Chihuahua",
    "iso:country":"MX",
    "name:und_x_variant":[
        "El Ri\u00edto"
    ],
    "wof:name":"El Riito",
    "wof:placetype":"locality",
    "wof:population":15
},
  "geometry": {"coordinates":[-106.47324999999999,26.5297],"type":"Point"}
}