{
  "type": "Feature",
  "properties": {
    "gn:admin1_code":"26.0",
    "gn:admin2_code":"47.0",
    "gn:asciiname":"Arivaipa Uno",
    "gn:country_code":"MX",
    "gn:dem":157,
    "gn:feature_class":"P",
    "gn:feature_code":"PPL",
    "gn:name":"Arivaipa Uno",
    "gn:population":0,
    "gn:timezone":"America/Hermosillo",
    "iso:country":"MX",
    "name:spa_x_preferred":[
        "Arivaipa Uno"
    ],
    "wof:name":"Arivaipa Uno",
    "wof:placetype":"locality"
},
  "geometry": {"coordinates":[-112.20797,29.61098],"type":"Point"}
}