{
  "type": "Feature",
  "properties": {
    "gn:admin1_code":"24",
    "gn:admin2_code":"13.0",
    "gn:asciiname":"Rancho las Aguilas",
    "gn:country_code":"MX",
    "gn:dem":51,
    "gn:feature_class":"P",
    "gn:feature_code":"PPL",
    "gn:name":"Rancho las \u00c1guilas",
    "gn:population":7,
    "gn:timezone":"America/Mexico_City",
    "iso:country":"MX",
    "name:und_x_variant":[
        "Rancho las \u00c1guilas"
    ],
    "wof:name":"Rancho las Aguilas",
    "wof:placetype":"locality",
    "wof:population":7
},
  "geometry": {"coordinates":[-98.99861,21.89639],"type":"Point"}
}