{
  "type": "Feature",
  "properties": {
    "gn:admin1_code":"30",
    "gn:admin2_code":"168.0",
    "gn:asciiname":"Popocatepetl",
    "gn:country_code":"MX",
    "gn:dem":1128,
    "gn:feature_class":"P",
    "gn:feature_code":"PPL",
    "gn:name":"Popocat\u00e9petl",
    "gn:population":91,
    "gn:timezone":"America/Mexico_City",
    "iso:country":"MX",
    "name:und_x_variant":[
        "Popocat\u00e9petl"
    ],
    "wof:name":"Popocatepetl",
    "wof:placetype":"locality",
    "wof:population":91
},
  "geometry": {"coordinates":[-97.00167,18.71556],"type":"Point"}
}