{
  "type": "Feature",
  "properties": {
    "gn:admin1_code":"12",
    "gn:admin2_code":"70",
    "gn:asciiname":"Paraje de Coatzingo",
    "gn:country_code":"MX",
    "gn:dem":1165,
    "gn:feature_class":"P",
    "gn:feature_code":"PPL",
    "gn:name":"Paraje de Coatzingo",
    "gn:population":20,
    "gn:timezone":"America/Mexico_City",
    "iso:country":"MX",
    "wof:name":"Paraje de Coatzingo",
    "wof:placetype":"locality",
    "wof:population":20
},
  "geometry": {"coordinates":[-98.48305000000001,17.89384],"type":"Point"}
}