{
  "type": "Feature",
  "properties": {
    "gn:admin1_code":"28",
    "gn:admin2_code":"23.0",
    "gn:asciiname":"Las Albercas",
    "gn:country_code":"MX",
    "gn:dem":153,
    "gn:feature_class":"P",
    "gn:feature_code":"PPL",
    "gn:name":"Las Albercas",
    "gn:population":8,
    "gn:timezone":"America/Monterrey",
    "iso:country":"MX",
    "wof:name":"Las Albercas",
    "wof:placetype":"locality",
    "wof:population":8
},
  "geometry": {"coordinates":[-98.40306,25.23611],"type":"Point"}
}