{
  "type": "Feature",
  "properties": {
    "gn:admin1_code":"26",
    "gn:admin2_code":"8.0",
    "gn:asciiname":"Rancho Tereverachi",
    "gn:country_code":"MX",
    "gn:dem":1156,
    "gn:feature_class":"P",
    "gn:feature_code":"PPL",
    "gn:name":"Rancho Terev\u00e9rachi",
    "gn:population":0,
    "gn:timezone":"America/Hermosillo",
    "iso:country":"MX",
    "wof:name":"Rancho Tereverachi",
    "wof:placetype":"locality"
},
  "geometry": {"coordinates":[-109.08333,29.75],"type":"Point"}
}