{
  "type": "Feature",
  "properties": {
    "gn:admin1_code":"14.0",
    "gn:admin2_code":"68.0",
    "gn:asciiname":"El Sauz",
    "gn:country_code":"MX",
    "gn:dem":925,
    "gn:feature_class":"P",
    "gn:feature_code":"PPL",
    "gn:name":"El Sauz",
    "gn:population":0,
    "gn:timezone":"America/Mexico_City",
    "iso:country":"MX",
    "name:spa_x_preferred":[
        "El Sauz"
    ],
    "wof:name":"El Sauz",
    "wof:placetype":"locality"
},
  "geometry": {"coordinates":[-104.89418999999999,19.71105],"type":"Point"}
}