{
  "type": "Feature",
  "properties": {
    "gn:admin1_code":"18",
    "gn:admin2_code":"1.0",
    "gn:asciiname":"La Alarcona",
    "gn:country_code":"MX",
    "gn:dem":115,
    "gn:feature_class":"P",
    "gn:feature_code":"PPL",
    "gn:name":"La Alarcona",
    "gn:population":0,
    "gn:timezone":"America/Mazatlan",
    "iso:country":"MX",
    "name:spa_x_preferred":[
        "La Alarcona"
    ],
    "wof:name":"La Alarcona",
    "wof:placetype":"locality"
},
  "geometry": {"coordinates":[-105.2719,22.49501],"type":"Point"}
}