{
  "type": "Feature",
  "properties": {
    "gn:admin1_code":"24",
    "gn:admin2_code":"32",
    "gn:asciiname":"El Corral (El Corral Dos)",
    "gn:country_code":"MX",
    "gn:dem":2119,
    "gn:feature_class":"P",
    "gn:feature_code":"PPL",
    "gn:name":"El Corral (El Corral Dos)",
    "gn:population":51,
    "gn:timezone":"America/Mexico_City",
    "iso:country":"MX",
    "wof:name":"El Corral (El Corral Dos)",
    "wof:placetype":"locality",
    "wof:population":51
},
  "geometry": {"coordinates":[-100.60778000000001,21.86917],"type":"Point"}
}