{
  "type": "Feature",
  "properties": {
    "gn:admin1_code":"6",
    "gn:admin2_code":"47",
    "gn:asciiname":"El Realito",
    "gn:country_code":"MX",
    "gn:dem":1329,
    "gn:feature_class":"P",
    "gn:feature_code":"PPL",
    "gn:name":"El Realito",
    "gn:population":13,
    "gn:timezone":"America/Chihuahua",
    "iso:country":"MX",
    "wof:name":"El Realito",
    "wof:placetype":"locality",
    "wof:population":13
},
  "geometry": {"coordinates":[-108.57968,28.09046],"type":"Point"}
}