{
  "type": "Feature",
  "properties": {
    "gn:admin1_code":"20",
    "gn:admin2_code":"279.0",
    "gn:asciiname":"Rio el Molino",
    "gn:country_code":"MX",
    "gn:dem":2300,
    "gn:feature_class":"P",
    "gn:feature_code":"PPL",
    "gn:name":"R\u00edo el Molino",
    "gn:population":90,
    "gn:timezone":"America/Mexico_City",
    "iso:country":"MX",
    "name:und_x_variant":[
        "R\u00edo el Molino"
    ],
    "wof:name":"Rio el Molino",
    "wof:placetype":"locality",
    "wof:population":90
},
  "geometry": {"coordinates":[-96.47,16.07667],"type":"Point"}
}