{
  "type": "Feature",
  "properties": {
    "iso:country":"MX",
    "name:spa_x_preferred":[
        "Palito Verde"
    ],
    "qs:gn_adm0_cc":"MX",
    "qs:gn_fcode":"PPL",
    "qs:gn_local":3991328,
    "qs:gn_nam_loc":"Puerto Vallarta, Puerto Vallarta, Jalisco, MX",
    "qs:gn_namadm1":"14",
    "qs:gn_name":"Palo Verde",
    "qs:local_max":6256,
    "qs:local_sum":18911,
    "qs:localhoods":15,
    "qs:name":"Palito Verde",
    "qs:name_adm0":"M\u00e9xico",
    "qs:name_adm1":"Jalisco",
    "qs:name_adm2":"Puerto Vallarta",
    "qs:name_local":"Puerto Vallarta",
    "qs:photo_max":206,
    "qs:photo_sum":531,
    "qs:placetype":"Suburb",
    "qs:quad_count":15,
    "qs:woe_adm0":23424900,
    "qs:woe_adm1":2346277,
    "qs:woe_adm2":12600264,
    "qs:woe_lau":0,
    "qs:woe_local":137895,
    "qs:woe_ver":"7.10.0",
    "wof:lang":[
        "spa"
    ],
    "wof:name":"Palito Verde",
    "wof:placetype":"neighbourhood"
},
  "geometry": {"coordinates":[-105.228988,20.610414],"type":"Point"}
}