{
  "type": "Feature",
  "properties": {
    "gn:admin1_code":"2",
    "gn:admin2_code":"3.0",
    "gn:asciiname":"El Desierto",
    "gn:country_code":"MX",
    "gn:dem":863,
    "gn:feature_class":"P",
    "gn:feature_code":"PPL",
    "gn:name":"El Desierto",
    "gn:population":0,
    "gn:timezone":"America/Tijuana",
    "iso:country":"MX",
    "wof:name":"El Desierto",
    "wof:placetype":"locality"
},
  "geometry": {"coordinates":[-116.50042999999999,32.53709],"type":"Point"}
}