{
  "type": "Feature",
  "properties": {
    "gn:admin1_code":"5.0",
    "gn:admin2_code":"16.0",
    "gn:asciiname":"Zipote Vaina",
    "gn:country_code":"MX",
    "gn:dem":29,
    "gn:feature_class":"P",
    "gn:feature_code":"PPL",
    "gn:name":"Zipote Vaina",
    "gn:population":0,
    "gn:timezone":"America/Mexico_City",
    "iso:country":"MX",
    "name:spa_x_preferred":[
        "Zipote Vaina"
    ],
    "wof:name":"Zipote Vaina",
    "wof:placetype":"locality"
},
  "geometry": {"coordinates":[-92.09889,17.7144],"type":"Point"}
}