{
  "type": "Feature",
  "properties": {
    "gn:admin1_code":"30.0",
    "gn:admin2_code":"27.0",
    "gn:asciiname":"Poncojtla",
    "gn:country_code":"MX",
    "gn:dem":628,
    "gn:feature_class":"P",
    "gn:feature_code":"PPL",
    "gn:name":"Poncojtla",
    "gn:population":93,
    "gn:timezone":"America/Mexico_City",
    "iso:country":"MX",
    "name:spa_x_preferred":[
        "Poncojtla"
    ],
    "wof:name":"Poncojtla",
    "wof:placetype":"locality",
    "wof:population":93
},
  "geometry": {"coordinates":[-98.25194,20.86778],"type":"Point"}
}