{
  "type": "Feature",
  "properties": {
    "gn:admin1_code":"30",
    "gn:admin2_code":"204.0",
    "gn:asciiname":"Ingeniero Mario Hernandez Posada",
    "gn:country_code":"MX",
    "gn:dem":81,
    "gn:feature_class":"P",
    "gn:feature_code":"PPL",
    "gn:name":"Ingeniero Mario Hern\u00e1ndez Posada",
    "gn:population":175,
    "gn:timezone":"America/Mexico_City",
    "iso:country":"MX",
    "name:und_x_variant":[
        "Ingeniero Mario Hern\u00e1ndez Posada"
    ],
    "wof:name":"Ingeniero Mario Hernandez Posada",
    "wof:placetype":"locality",
    "wof:population":175
},
  "geometry": {"coordinates":[-94.22833,18.04833],"type":"Point"}
}