{
  "type": "Feature",
  "properties": {
    "gn:admin1_code":"1",
    "gn:admin2_code":"7.0",
    "gn:asciiname":"Lazaro Cardenas [Fraccionamiento]",
    "gn:country_code":"MX",
    "gn:dem":1955,
    "gn:feature_class":"P",
    "gn:feature_code":"PPL",
    "gn:name":"L\u00e1zaro C\u00e1rdenas [Fraccionamiento]",
    "gn:population":231,
    "gn:timezone":"America/Mexico_City",
    "iso:country":"MX",
    "name:und_x_variant":[
        "L\u00e1zaro C\u00e1rdenas [Fraccionamiento]"
    ],
    "wof:name":"Lazaro Cardenas [Fraccionamiento]",
    "wof:placetype":"locality",
    "wof:population":231
},
  "geometry": {"coordinates":[-102.32778,22.23972],"type":"Point"}
}