{
  "type": "Feature",
  "properties": {
    "gn:admin1_code":"1",
    "gn:admin2_code":"7.0",
    "gn:asciiname":"Vinedos San Juan",
    "gn:country_code":"MX",
    "gn:dem":1953,
    "gn:feature_class":"P",
    "gn:feature_code":"PPL",
    "gn:name":"Vi\u00f1edos San Juan",
    "gn:population":4,
    "gn:timezone":"America/Mexico_City",
    "iso:country":"MX",
    "name:und_x_variant":[
        "Vi\u00f1edos San Juan"
    ],
    "wof:name":"Vinedos San Juan",
    "wof:placetype":"locality",
    "wof:population":4
},
  "geometry": {"coordinates":[-102.325,22.21528],"type":"Point"}
}