{
  "type": "Feature",
  "properties": {
    "gn:admin1_code":"15",
    "gn:admin2_code":"9",
    "gn:asciiname":"Rancho Tepeyehual",
    "gn:country_code":"MX",
    "gn:dem":2781,
    "gn:feature_class":"P",
    "gn:feature_code":"PPL",
    "gn:name":"Rancho Tepeyehual",
    "gn:population":28,
    "gn:timezone":"America/Mexico_City",
    "iso:country":"MX",
    "wof:name":"Rancho Tepeyehual",
    "wof:placetype":"locality",
    "wof:population":28
},
  "geometry": {"coordinates":[-98.71387,19.12041],"type":"Point"}
}