{
  "type": "Feature",
  "properties": {
    "gn:admin1_code":"6",
    "gn:admin2_code":"13.0",
    "gn:asciiname":"Los Cristianos",
    "gn:country_code":"MX",
    "gn:dem":1937,
    "gn:feature_class":"P",
    "gn:feature_code":"PPL",
    "gn:name":"Los Cristianos",
    "gn:population":0,
    "gn:timezone":"America/Chihuahua",
    "iso:country":"MX",
    "name:spa_x_preferred":[
        "Los Cristianos"
    ],
    "wof:name":"Los Cristianos",
    "wof:placetype":"locality"
},
  "geometry": {"coordinates":[-107.9452,30.08013],"type":"Point"}
}