{
  "type": "Feature",
  "properties": {
    "gn:admin1_code":"6",
    "gn:admin2_code":"13.0",
    "gn:asciiname":"Los Cristianos",
    "gn:country_code":"MX",
    "gn:dem":1937,
    "gn:feature_class":"P",
    "gn:feature_code":"PPL",
    "gn:name":"Los Cristianos",
    "gn:population":0,
    "gn:timezone":"America/Chihuahua",
    "iso:country":"MX",
    "name:cat_x_preferred":[
        "Los Cristianos"
    ],
    "name:dan_x_preferred":[
        "Los Cristianos"
    ],
    "name:deu_x_preferred":[
        "Los Cristianos"
    ],
    "name:epo_x_preferred":[
        "Los Cristianos"
    ],
    "name:fin_x_preferred":[
        "Los Cristianos"
    ],
    "name:fra_x_preferred":[
        "Los Cristianos"
    ],
    "name:glg_x_preferred":[
        "Los Cristianos"
    ],
    "name:lit_x_preferred":[
        "Los Kristianosas"
    ],
    "name:nld_x_preferred":[
        "Los Cristianos"
    ],
    "name:nor_x_preferred":[
        "Los Cristianos"
    ],
    "name:pol_x_preferred":[
        "Los Cristianos"
    ],
    "name:rus_x_preferred":[
        "\u041b\u043e\u0441-\u041a\u0440\u0438\u0441\u0442\u0438\u0430\u043d\u043e\u0441"
    ],
    "name:spa_x_preferred":[
        "Los Cristianos"
    ],
    "name:swe_x_preferred":[
        "Los Cristianos"
    ],
    "wof:name":"Los Cristianos",
    "wof:placetype":"locality"
},
  "geometry": {"coordinates":[-107.9452,30.08013],"type":"Point"}
}