{
  "type": "Feature",
  "properties": {
    "gn:admin1_code":"11",
    "gn:admin2_code":"45",
    "gn:asciiname":"Aurora",
    "gn:country_code":"MX",
    "gn:dem":1133,
    "gn:feature_class":"P",
    "gn:feature_code":"PPL",
    "gn:name":"Aurora",
    "gn:population":38,
    "gn:timezone":"America/Mexico_City",
    "iso:country":"MX",
    "wof:name":"Aurora",
    "wof:placetype":"locality",
    "wof:population":38
},
  "geometry": {"coordinates":[-100.03417,21.32556],"type":"Point"}
}