{
  "type": "Feature",
  "properties": {
    "gn:admin1_code":"26",
    "gn:admin2_code":"64.0",
    "gn:asciiname":"La Verbena",
    "gn:country_code":"MX",
    "gn:dem":396,
    "gn:feature_class":"P",
    "gn:feature_code":"PPL",
    "gn:name":"La Verbena",
    "gn:population":0,
    "gn:timezone":"America/Hermosillo",
    "iso:country":"MX",
    "name:und_x_variant":[
        "Rancho la Verbena",
        "La Verbena"
    ],
    "wof:name":"La Verbena",
    "wof:placetype":"locality"
},
  "geometry": {"coordinates":[-111.80027,30.50343],"type":"Point"}
}