{
  "type": "Feature",
  "properties": {
    "gn:admin1_code":"26",
    "gn:admin2_code":"30",
    "gn:asciiname":"La Cuichi (Pelicano)",
    "gn:country_code":"MX",
    "gn:dem":30,
    "gn:feature_class":"P",
    "gn:feature_code":"PPL",
    "gn:name":"La Cuichi (Pel\u00edcano)",
    "gn:population":50,
    "gn:timezone":"America/Hermosillo",
    "iso:country":"MX",
    "name:und_x_variant":[
        "La Cuichi (Pel\u00edcano)"
    ],
    "wof:name":"La Cuichi (Pelicano)",
    "wof:placetype":"locality",
    "wof:population":50
},
  "geometry": {"coordinates":[-111.38611000000002,28.53861],"type":"Point"}
}