{
  "type": "Feature",
  "properties": {
    "gn:admin1_code":"23",
    "gn:admin2_code":"4.0",
    "gn:asciiname":"La Buena Fe",
    "gn:country_code":"MX",
    "gn:dem":28,
    "gn:feature_class":"P",
    "gn:feature_code":"PPL",
    "gn:name":"La Buena Fe",
    "gn:population":0,
    "gn:timezone":"America/Cancun",
    "iso:country":"MX",
    "name:und_x_variant":[
        "Buenaf\u00e9"
    ],
    "wof:name":"La Buena Fe",
    "wof:placetype":"locality"
},
  "geometry": {"coordinates":[-88.50779,18.9827],"type":"Point"}
}