{
  "type": "Feature",
  "properties": {
    "gn:admin1_code":"6",
    "gn:admin2_code":"29.0",
    "gn:asciiname":"Mesa de San Jose",
    "gn:country_code":"MX",
    "gn:dem":2349,
    "gn:feature_class":"P",
    "gn:feature_code":"PPL",
    "gn:name":"Mesa de San Jos\u00e9",
    "gn:population":302,
    "gn:timezone":"America/Chihuahua",
    "iso:country":"MX",
    "name:und_x_variant":[
        "Mesa de San Jos\u00e9"
    ],
    "wof:name":"Mesa de San Jose",
    "wof:placetype":"locality",
    "wof:population":302
},
  "geometry": {"coordinates":[-106.90167,25.97944],"type":"Point"}
}