{
  "type": "Feature",
  "properties": {
    "gn:admin1_code":"26",
    "gn:admin2_code":"30.0",
    "gn:asciiname":"Isla del Carmen",
    "gn:country_code":"MX",
    "gn:dem":41,
    "gn:feature_class":"P",
    "gn:feature_code":"PPL",
    "gn:name":"Isla del Carmen",
    "gn:population":0,
    "gn:timezone":"America/Hermosillo",
    "iso:country":"MX",
    "name:spa_x_preferred":[
        "Isla del Carmen"
    ],
    "name:spa_x_variant":[
        "El Carmen"
    ],
    "wof:name":"Isla del Carmen",
    "wof:placetype":"locality"
},
  "geometry": {"coordinates":[-111.38767,28.61268],"type":"Point"}
}