{
  "type": "Feature",
  "properties": {
    "gn:admin1_code":"23.0",
    "gn:admin2_code":"4.0",
    "gn:asciiname":"Canaima",
    "gn:country_code":"MX",
    "gn:dem":3,
    "gn:feature_class":"P",
    "gn:feature_code":"PPL",
    "gn:name":"Canaima",
    "gn:population":0,
    "gn:timezone":"America/Cancun",
    "iso:country":"MX",
    "name:fra_x_preferred":[
        "Canaima"
    ],
    "name:spa_x_preferred":[
        "Canaima"
    ],
    "wof:name":"Canaima",
    "wof:placetype":"locality"
},
  "geometry": {"coordinates":[-87.65359000000002,18.84785],"type":"Point"}
}