{
  "type": "Feature",
  "properties": {
    "gn:admin1_code":"26.0",
    "gn:admin2_code":"69.0",
    "gn:asciiname":"Mina del Campanero",
    "gn:country_code":"MX",
    "gn:dem":1878,
    "gn:feature_class":"P",
    "gn:feature_code":"PPL",
    "gn:name":"Mina del Campanero",
    "gn:population":0,
    "gn:timezone":"America/Hermosillo",
    "iso:country":"MX",
    "name:spa_x_preferred":[
        "Mina del Campanero"
    ],
    "wof:name":"Mina del Campanero",
    "wof:placetype":"locality"
},
  "geometry": {"coordinates":[-109.01888999999998,28.36493],"type":"Point"}
}