{
  "type": "Feature",
  "properties": {
    "gn:admin1_code":"26",
    "gn:admin2_code":"30.0",
    "gn:asciiname":"Crucero Doce y Veintiseis",
    "gn:country_code":"MX",
    "gn:dem":30,
    "gn:feature_class":"P",
    "gn:feature_code":"PPL",
    "gn:name":"Crucero Doce y Veintis\u00e9is",
    "gn:population":7,
    "gn:timezone":"America/Hermosillo",
    "iso:country":"MX",
    "name:und_x_variant":[
        "Crucero Doce y Veintis\u00e9is"
    ],
    "wof:name":"Crucero Doce y Veintiseis",
    "wof:placetype":"locality",
    "wof:population":7
},
  "geometry": {"coordinates":[-111.47278,28.56833],"type":"Point"}
}