{
  "type": "Feature",
  "properties": {
    "gn:admin1_code":"30",
    "gn:admin2_code":"132.0",
    "gn:asciiname":"Encino Gacho",
    "gn:country_code":"MX",
    "gn:dem":2403,
    "gn:feature_class":"P",
    "gn:feature_code":"PPL",
    "gn:name":"Encino Gacho",
    "gn:population":190,
    "gn:timezone":"America/Mexico_City",
    "iso:country":"MX",
    "wof:name":"Encino Gacho",
    "wof:placetype":"locality",
    "wof:population":190
},
  "geometry": {"coordinates":[-97.07805999999999,19.63],"type":"Point"}
}