{
  "type": "Feature",
  "properties": {
    "gn:admin1_code":"6",
    "gn:admin2_code":"29",
    "gn:asciiname":"El Alamillo",
    "gn:country_code":"MX",
    "gn:dem":2436,
    "gn:feature_class":"P",
    "gn:feature_code":"PPL",
    "gn:name":"El Alamillo",
    "gn:population":10,
    "gn:timezone":"America/Chihuahua",
    "iso:country":"MX",
    "wof:name":"El Alamillo",
    "wof:placetype":"locality",
    "wof:population":10
},
  "geometry": {"coordinates":[-106.81123999999998,26.13829],"type":"Point"}
}