{
  "type": "Feature",
  "properties": {
    "gn:admin1_code":"32",
    "gn:admin2_code":"49.0",
    "gn:asciiname":"San Lucas del Valle",
    "gn:country_code":"MX",
    "gn:dem":2560,
    "gn:feature_class":"P",
    "gn:feature_code":"PPL",
    "gn:name":"San Lucas del Valle",
    "gn:population":0,
    "gn:timezone":"America/Mexico_City",
    "iso:country":"MX",
    "name:spa_x_preferred":[
        "San Lucas del Valle"
    ],
    "wof:name":"San Lucas del Valle",
    "wof:placetype":"locality"
},
  "geometry": {"coordinates":[-103.71080000000001,22.86331],"type":"Point"}
}