{
  "type": "Feature",
  "properties": {
    "gn:admin1_code":"15",
    "gn:admin2_code":"65.0",
    "gn:asciiname":"San Martin Ahuatepec",
    "gn:country_code":"MX",
    "gn:dem":2443,
    "gn:feature_class":"P",
    "gn:feature_code":"PPL",
    "gn:name":"San Mart\u00edn Ahuatepec",
    "gn:population":1651,
    "gn:timezone":"America/Mexico_City",
    "iso:country":"MX",
    "name:und_x_variant":[
        "San Mart\u00edn Ahuatepec"
    ],
    "wof:name":"San Martin Ahuatepec",
    "wof:placetype":"locality",
    "wof:population":1651
},
  "geometry": {"coordinates":[-98.72806,19.68139],"type":"Point"}
}