{
  "type": "Feature",
  "properties": {
    "gn:admin1_code":"6",
    "gn:admin2_code":"49.0",
    "gn:asciiname":"La Timba",
    "gn:country_code":"MX",
    "gn:dem":2241,
    "gn:feature_class":"P",
    "gn:feature_code":"PPL",
    "gn:name":"La Timba",
    "gn:population":0,
    "gn:timezone":"America/Chihuahua",
    "iso:country":"MX",
    "name:spa_x_preferred":[
        "La Timba"
    ],
    "wof:name":"La Timba",
    "wof:placetype":"locality"
},
  "geometry": {"coordinates":[-106.60771,27.30741],"type":"Point"}
}