{
  "type": "Feature",
  "properties": {
    "gn:admin1_code":"18.0",
    "gn:admin2_code":"10.0",
    "gn:asciiname":"El Ochenta",
    "gn:country_code":"MX",
    "gn:dem":30,
    "gn:feature_class":"P",
    "gn:feature_code":"PPL",
    "gn:name":"El Ochenta",
    "gn:population":0,
    "gn:timezone":"America/Mazatlan",
    "iso:country":"MX",
    "name:spa_x_preferred":[
        "El Ochenta"
    ],
    "wof:name":"El Ochenta",
    "wof:placetype":"locality"
},
  "geometry": {"coordinates":[-105.14879999999999,21.97276],"type":"Point"}
}