{
  "type": "Feature",
  "properties": {
    "gn:admin1_code":"5",
    "gn:admin2_code":"67.0",
    "gn:asciiname":"El Carrizal",
    "gn:country_code":"MX",
    "gn:dem":1264,
    "gn:feature_class":"P",
    "gn:feature_code":"PPL",
    "gn:name":"El Carrizal",
    "gn:population":889,
    "gn:timezone":"America/Mexico_City",
    "iso:country":"MX",
    "name:spa_x_preferred":[
        "El Carrizal"
    ],
    "wof:name":"El Carrizal",
    "wof:placetype":"locality",
    "wof:population":889
},
  "geometry": {"coordinates":[-93.0771,17.16213],"type":"Point"}
}