{
  "type": "Feature",
  "properties": {
    "gn:admin1_code":"15.0",
    "gn:admin2_code":"82.0",
    "gn:asciiname":"Pueblo de San Lucas",
    "gn:country_code":"MX",
    "gn:dem":1855,
    "gn:feature_class":"P",
    "gn:feature_code":"PPL",
    "gn:name":"Pueblo de San Lucas",
    "gn:population":0,
    "gn:timezone":"America/Mexico_City",
    "iso:country":"MX",
    "name:und_x_variant":[
        "San Lucas del Ma\u00edz"
    ],
    "wof:name":"Pueblo de San Lucas",
    "wof:placetype":"locality"
},
  "geometry": {"coordinates":[-100.18456,18.96458],"type":"Point"}
}