{
  "type": "Feature",
  "properties": {
    "gn:admin1_code":"5.0",
    "gn:admin2_code":"19.0",
    "gn:asciiname":"Santa Rosa las Palmas",
    "gn:country_code":"MX",
    "gn:dem":625,
    "gn:feature_class":"P",
    "gn:feature_code":"PPL",
    "gn:name":"Santa Rosa las Palmas",
    "gn:population":0,
    "gn:timezone":"America/Mexico_City",
    "iso:country":"MX",
    "name:spa_x_preferred":[
        "Santa Rosa las Palmas"
    ],
    "wof:name":"Santa Rosa las Palmas",
    "wof:placetype":"locality"
},
  "geometry": {"coordinates":[-92.18481,16.03917],"type":"Point"}
}