{
  "type": "Feature",
  "properties": {
    "gn:admin1_code":"4",
    "gn:admin2_code":"3",
    "gn:asciiname":"El Caribe (El Moskit)",
    "gn:country_code":"MX",
    "gn:dem":19,
    "gn:feature_class":"P",
    "gn:feature_code":"PPL",
    "gn:name":"El Caribe (El Moskit)",
    "gn:population":24,
    "gn:timezone":"America/Merida",
    "iso:country":"MX",
    "wof:name":"El Caribe (El Moskit)",
    "wof:placetype":"locality",
    "wof:population":24
},
  "geometry": {"coordinates":[-91.395,18.23944],"type":"Point"}
}