{
  "type": "Feature",
  "properties": {
    "gn:admin1_code":"18.0",
    "gn:admin2_code":"9.0",
    "gn:asciiname":"El Chalate",
    "gn:country_code":"MX",
    "gn:dem":1359,
    "gn:feature_class":"P",
    "gn:feature_code":"PPL",
    "gn:name":"El Chalate",
    "gn:population":0,
    "gn:timezone":"America/Mazatlan",
    "iso:country":"MX",
    "name:spa_x_preferred":[
        "El Chalate"
    ],
    "wof:name":"El Chalate",
    "wof:placetype":"locality"
},
  "geometry": {"coordinates":[-104.33450999999999,22.30071],"type":"Point"}
}