{
  "type": "Feature",
  "properties": {
    "gn:admin1_code":"30",
    "gn:admin2_code":"160.0",
    "gn:asciiname":"La Pasadita",
    "gn:country_code":"MX",
    "gn:dem":82,
    "gn:feature_class":"P",
    "gn:feature_code":"PPL",
    "gn:name":"La Pasadita",
    "gn:population":9,
    "gn:timezone":"America/Mexico_City",
    "iso:country":"MX",
    "wof:name":"La Pasadita",
    "wof:placetype":"locality",
    "wof:population":9
},
  "geometry": {"coordinates":[-97.73222,21.09361],"type":"Point"}
}