{
  "type": "Feature",
  "properties": {
    "gn:admin1_code":"6.0",
    "gn:admin2_code":"48.0",
    "gn:asciiname":"La Presita",
    "gn:country_code":"MX",
    "gn:dem":1871,
    "gn:feature_class":"P",
    "gn:feature_code":"PPL",
    "gn:name":"La Presita",
    "gn:population":0,
    "gn:timezone":"America/Chihuahua",
    "iso:country":"MX",
    "name:spa_x_preferred":[
        "La Presita"
    ],
    "wof:name":"La Presita",
    "wof:placetype":"locality"
},
  "geometry": {"coordinates":[-107.39483,29.13788],"type":"Point"}
}