{
  "type": "Feature",
  "properties": {
    "gn:admin1_code":"11",
    "gn:admin2_code":"32.0",
    "gn:asciiname":"El Florete",
    "gn:country_code":"MX",
    "gn:dem":2110,
    "gn:feature_class":"P",
    "gn:feature_code":"PPL",
    "gn:name":"El Florete",
    "gn:population":7,
    "gn:timezone":"America/Mexico_City",
    "iso:country":"MX",
    "wof:name":"El Florete",
    "wof:placetype":"locality",
    "wof:population":7
},
  "geometry": {"coordinates":[-100.32333,21.07],"type":"Point"}
}