{
  "type": "Feature",
  "properties": {
    "gn:admin1_code":"30",
    "gn:admin2_code":"65.0",
    "gn:asciiname":"Campo Nuevo",
    "gn:country_code":"MX",
    "gn:dem":1071,
    "gn:feature_class":"P",
    "gn:feature_code":"PPL",
    "gn:name":"Campo Nuevo",
    "gn:population":0,
    "gn:timezone":"America/Mexico_City",
    "iso:country":"MX",
    "name:spa_x_preferred":[
        "Campo Nuevo"
    ],
    "wof:name":"Campo Nuevo",
    "wof:placetype":"locality"
},
  "geometry": {"coordinates":[-96.86883,19.46033],"type":"Point"}
}