{
  "type": "Feature",
  "properties": {
    "gn:admin1_code":"14.0",
    "gn:admin2_code":"61.0",
    "gn:asciiname":"El Bosque",
    "gn:country_code":"MX",
    "gn:dem":1469,
    "gn:feature_class":"P",
    "gn:feature_code":"PPL",
    "gn:name":"El Bosque",
    "gn:population":0,
    "gn:timezone":"America/Mexico_City",
    "iso:country":"MX",
    "name:ceb_x_preferred":[
        "El Bosque"
    ],
    "name:deu_x_preferred":[
        "El Bosque"
    ],
    "name:eus_x_preferred":[
        "El Bosque"
    ],
    "name:fra_x_preferred":[
        "El Bosque"
    ],
    "name:glg_x_preferred":[
        "El Bosque"
    ],
    "name:ita_x_preferred":[
        "El Bosque"
    ],
    "name:nds_x_preferred":[
        "El Bosque"
    ],
    "name:nld_x_preferred":[
        "El Bosque"
    ],
    "name:por_x_preferred":[
        "El Bosque"
    ],
    "name:ron_x_preferred":[
        "El Bosque"
    ],
    "name:rus_x_preferred":[
        "\u042d\u043b\u044c-\u0411\u043e\u0441\u043a\u0435"
    ],
    "name:sco_x_preferred":[
        "El Bosque"
    ],
    "name:spa_x_preferred":[
        "El Bosque"
    ],
    "name:swe_x_preferred":[
        "El Bosque"
    ],
    "name:vie_x_preferred":[
        "El Bosque"
    ],
    "name:war_x_preferred":[
        "El Bosque"
    ],
    "wof:name":"El Bosque",
    "wof:placetype":"locality"
},
  "geometry": {"coordinates":[-104.316,22.08225],"type":"Point"}
}