{
  "type": "Feature",
  "properties": {
    "gn:admin1_code":"21.0",
    "gn:admin2_code":"178.0",
    "gn:asciiname":"Arroyo el Caliche",
    "gn:country_code":"MX",
    "gn:dem":394,
    "gn:feature_class":"P",
    "gn:feature_code":"PPL",
    "gn:name":"Arroyo el Caliche",
    "gn:population":0,
    "gn:timezone":"America/Mexico_City",
    "iso:country":"MX",
    "name:spa_x_preferred":[
        "Arroyo el Caliche"
    ],
    "wof:name":"Arroyo el Caliche",
    "wof:placetype":"locality"
},
  "geometry": {"coordinates":[-97.90903,20.40407],"type":"Point"}
}