{
  "type": "Feature",
  "properties": {
    "gn:admin1_code":"14.0",
    "gn:admin2_code":"33.0",
    "gn:asciiname":"La Bajada",
    "gn:country_code":"MX",
    "gn:dem":1552,
    "gn:feature_class":"P",
    "gn:feature_code":"PPL",
    "gn:name":"La Bajada",
    "gn:population":0,
    "gn:timezone":"America/Mexico_City",
    "iso:country":"MX",
    "name:spa_x_preferred":[
        "La Bajada"
    ],
    "wof:name":"La Bajada",
    "wof:placetype":"locality"
},
  "geometry": {"coordinates":[-102.17664000000001,20.35623],"type":"Point"}
}