{
  "type": "Feature",
  "properties": {
    "gn:admin1_code":"16",
    "gn:admin2_code":"52.0",
    "gn:asciiname":"Jicalan",
    "gn:country_code":"MX",
    "gn:dem":230,
    "gn:feature_class":"P",
    "gn:feature_code":"PPL",
    "gn:name":"Jical\u00e1n",
    "gn:population":0,
    "gn:timezone":"America/Mexico_City",
    "iso:country":"MX",
    "name:spa_x_preferred":[
        "Jical\u00e1n"
    ],
    "wof:name":"Jicalan",
    "wof:placetype":"locality"
},
  "geometry": {"coordinates":[-102.25503999999999,18.14567000000001],"type":"Point"}
}