{
  "type": "Feature",
  "properties": {
    "gn:admin1_code":"21",
    "gn:admin2_code":"170.0",
    "gn:asciiname":"Techachalco",
    "gn:country_code":"MX",
    "gn:dem":2342,
    "gn:feature_class":"P",
    "gn:feature_code":"PPL",
    "gn:name":"Techachalco",
    "gn:population":0,
    "gn:timezone":"America/Mexico_City",
    "iso:country":"MX",
    "name:spa_x_preferred":[
        "Techachalco"
    ],
    "wof:name":"Techachalco",
    "wof:placetype":"locality"
},
  "geometry": {"coordinates":[-97.43586999999999,19.38081],"type":"Point"}
}