{
  "type": "Feature",
  "properties": {
    "gn:admin1_code":"30",
    "gn:admin2_code":"142.0",
    "gn:asciiname":"Michapan de Osorio",
    "gn:country_code":"MX",
    "gn:dem":43,
    "gn:feature_class":"P",
    "gn:feature_code":"PPL",
    "gn:name":"Michapan de Osorio",
    "gn:population":0,
    "gn:timezone":"America/Mexico_City",
    "iso:country":"MX",
    "name:spa_x_preferred":[
        "Michapan de Osorio"
    ],
    "name:und_x_variant":[
        "Michapan"
    ],
    "wof:name":"Michapan de Osorio",
    "wof:placetype":"locality"
},
  "geometry": {"coordinates":[-95.08734,17.96183],"type":"Point"}
}