{
  "type": "Feature",
  "properties": {
    "gn:admin1_code":"26",
    "gn:admin2_code":"69.0",
    "gn:asciiname":"El Huerigo",
    "gn:country_code":"MX",
    "gn:dem":913,
    "gn:feature_class":"P",
    "gn:feature_code":"PPL",
    "gn:name":"El Hu\u00e9rigo",
    "gn:population":0,
    "gn:timezone":"America/Hermosillo",
    "iso:country":"MX",
    "name:spa_x_preferred":[
        "El Hu\u00e9rigo"
    ],
    "wof:name":"El Huerigo",
    "wof:placetype":"locality"
},
  "geometry": {"coordinates":[-109.12354999999999,28.44077],"type":"Point"}
}