{
  "type": "Feature",
  "properties": {
    "gn:admin1_code":"16",
    "gn:admin2_code":"33.0",
    "gn:asciiname":"Gutierrez de Velasco [Vivero]",
    "gn:country_code":"MX",
    "gn:dem":596,
    "gn:feature_class":"P",
    "gn:feature_code":"PPL",
    "gn:name":"Guti\u00e9rrez de Velasco [Vivero]",
    "gn:population":7,
    "gn:timezone":"America/Mexico_City",
    "iso:country":"MX",
    "name:und_x_variant":[
        "Guti\u00e9rrez de Velasco [Vivero]"
    ],
    "wof:name":"Gutierrez de Velasco [Vivero]",
    "wof:placetype":"locality",
    "wof:population":7
},
  "geometry": {"coordinates":[-102.03444,19.145],"type":"Point"}
}