{
  "type": "Feature",
  "properties": {
    "gn:admin1_code":"21",
    "gn:admin2_code":"44.0",
    "gn:asciiname":"San Miguel Barrientos",
    "gn:country_code":"MX",
    "gn:dem":2354,
    "gn:feature_class":"P",
    "gn:feature_code":"PPL",
    "gn:name":"San Miguel Barrientos",
    "gn:population":0,
    "gn:timezone":"America/Mexico_City",
    "iso:country":"MX",
    "name:spa_x_preferred":[
        "San Miguel Barrientos"
    ],
    "wof:name":"San Miguel Barrientos",
    "wof:placetype":"locality"
},
  "geometry": {"coordinates":[-97.56937000000001,19.50358],"type":"Point"}
}