{
  "type": "Feature",
  "properties": {
    "gn:admin1_code":"32",
    "gn:admin2_code":"10.0",
    "gn:asciiname":"La Cabeza",
    "gn:country_code":"MX",
    "gn:dem":2066,
    "gn:feature_class":"P",
    "gn:feature_code":"PPL",
    "gn:name":"La Cabeza",
    "gn:population":0,
    "gn:timezone":"America/Mexico_City",
    "iso:country":"MX",
    "name:spa_x_preferred":[
        "La Cabeza"
    ],
    "wof:name":"La Cabeza",
    "wof:placetype":"locality"
},
  "geometry": {"coordinates":[-102.89109000000001,23.33177],"type":"Point"}
}