{
  "type": "Feature",
  "properties": {
    "gn:admin1_code":"13",
    "gn:admin2_code":"77.0",
    "gn:asciiname":"Rancho Buenos Aires",
    "gn:country_code":"MX",
    "gn:dem":2144,
    "gn:feature_class":"P",
    "gn:feature_code":"PPL",
    "gn:name":"Rancho Buenos Aires",
    "gn:population":6,
    "gn:timezone":"America/Mexico_City",
    "iso:country":"MX",
    "wof:name":"Rancho Buenos Aires",
    "wof:placetype":"locality",
    "wof:population":6
},
  "geometry": {"coordinates":[-98.38583,20.11972],"type":"Point"}
}