{
  "type": "Feature",
  "properties": {
    "gn:admin1_code":"30",
    "gn:admin2_code":"39.0",
    "gn:asciiname":"El Tigrillo",
    "gn:country_code":"MX",
    "gn:dem":37,
    "gn:feature_class":"P",
    "gn:feature_code":"PPL",
    "gn:name":"El Tigrillo",
    "gn:population":0,
    "gn:timezone":"America/Mexico_City",
    "iso:country":"MX",
    "name:spa_x_preferred":[
        "El Tigrillo"
    ],
    "wof:name":"El Tigrillo",
    "wof:placetype":"locality"
},
  "geometry": {"coordinates":[-94.29107999999999,18.09889],"type":"Point"}
}