{
  "type": "Feature",
  "properties": {
    "gn:admin1_code":"14",
    "gn:admin2_code":"86",
    "gn:asciiname":"Churintzio",
    "gn:country_code":"MX",
    "gn:dem":1801,
    "gn:feature_class":"P",
    "gn:feature_code":"PPL",
    "gn:name":"Churintzio",
    "gn:population":25,
    "gn:timezone":"America/Mexico_City",
    "iso:country":"MX",
    "name:ceb_x_preferred":[
        "Churintzio"
    ],
    "name:eus_x_preferred":[
        "Churintzio"
    ],
    "name:ita_x_preferred":[
        "Churintzio"
    ],
    "name:srd_x_preferred":[
        "Tzurintziu"
    ],
    "name:srp_x_preferred":[
        "\u041e\u043f\u0448\u0442\u0438\u043d\u0430 \u0427\u0443\u0440\u0438\u043d\u0437\u0438\u043e"
    ],
    "name:swe_x_preferred":[
        "Churintzio"
    ],
    "wof:name":"Churintzio",
    "wof:placetype":"locality",
    "wof:population":25
},
  "geometry": {"coordinates":[-103.85861,20.00556],"type":"Point"}
}