{
  "type": "Feature",
  "properties": {
    "gn:admin1_code":"25",
    "gn:admin2_code":"6.0",
    "gn:asciiname":"El Tecomatal Dos",
    "gn:country_code":"MX",
    "gn:dem":105,
    "gn:feature_class":"P",
    "gn:feature_code":"PPL",
    "gn:name":"El Tecomatal Dos",
    "gn:population":7,
    "gn:timezone":"America/Mazatlan",
    "iso:country":"MX",
    "wof:name":"El Tecomatal Dos",
    "wof:placetype":"locality",
    "wof:population":7
},
  "geometry": {"coordinates":[-107.23900999999999,24.74449],"type":"Point"}
}