{
  "type": "Feature",
  "properties": {
    "gn:admin1_code":"30.0",
    "gn:admin2_code":"121.0",
    "gn:asciiname":"El Beneficio",
    "gn:country_code":"MX",
    "gn:dem":39,
    "gn:feature_class":"P",
    "gn:feature_code":"PPL",
    "gn:name":"El Beneficio",
    "gn:population":1,
    "gn:timezone":"America/Mexico_City",
    "iso:country":"MX",
    "name:spa_x_preferred":[
        "El Beneficio"
    ],
    "wof:name":"El Beneficio",
    "wof:placetype":"locality",
    "wof:population":1
},
  "geometry": {"coordinates":[-98.13791000000001,21.71353],"type":"Point"}
}