{
  "type": "Feature",
  "properties": {
    "gn:admin1_code":"30",
    "gn:admin2_code":"72.0",
    "gn:asciiname":"El Cupil",
    "gn:country_code":"MX",
    "gn:dem":757,
    "gn:feature_class":"P",
    "gn:feature_code":"PPL",
    "gn:name":"El Cupil",
    "gn:population":98,
    "gn:timezone":"America/Mexico_City",
    "iso:country":"MX",
    "wof:name":"El Cupil",
    "wof:placetype":"locality",
    "wof:population":98
},
  "geometry": {"coordinates":[-98.36028,20.6525],"type":"Point"}
}