{
  "type": "Feature",
  "properties": {
    "gn:admin1_code":"5",
    "gn:admin2_code":"65",
    "gn:asciiname":"San Jose",
    "gn:country_code":"MX",
    "gn:dem":12,
    "gn:feature_class":"P",
    "gn:feature_code":"PPL",
    "gn:name":"San Jos\u00e9",
    "gn:population":18,
    "gn:timezone":"America/Mexico_City",
    "iso:country":"MX",
    "name:ara_x_preferred":[
        "\u0633\u0627\u0646 \u062e\u0648\u0633\u064a\u0647"
    ],
    "name:ben_x_preferred":[
        "\u09b8\u09be\u09a8 \u099c\u09cb\u09b8"
    ],
    "name:ell_x_preferred":[
        "\u03a3\u03b1\u03bd \u03a7\u03bf\u03c3\u03ad"
    ],
    "name:fas_x_preferred":[
        "\u0633\u0646 \u062e\u0648\u0632\u0647"
    ],
    "name:heb_x_preferred":[
        "\u05e1\u05d0\u05df \u05d7\u05d5\u05d6\u05d4"
    ],
    "name:hin_x_preferred":[
        "\u0938\u0948\u0928 \u091c\u094b\u0938"
    ],
    "name:hun_x_preferred":[
        "San Jose"
    ],
    "name:ita_x_preferred":[
        "San Jos\u00e9"
    ],
    "name:kor_x_preferred":[
        "\uc0b0 \ud638\uc138"
    ],
    "name:rus_x_preferred":[
        "\u0421\u0430\u043d-\u0425\u043e\u0441\u0435"
    ],
    "name:tur_x_preferred":[
        "San Jose"
    ],
    "name:ukr_x_preferred":[
        "\u0421\u0430\u043d-\u0425\u043e\u0441\u0435"
    ],
    "name:und_x_variant":[
        "San Jos\u00e9"
    ],
    "name:vie_x_preferred":[
        "San Jose"
    ],
    "wof:name":"San Jose",
    "wof:placetype":"locality",
    "wof:population":18
},
  "geometry": {"coordinates":[-91.78583,17.79528],"type":"Point"}
}