{
  "type": "Feature",
  "properties": {
    "gn:admin1_code":"26",
    "gn:admin2_code":"51.0",
    "gn:asciiname":"Progenitora Nucleo Uno (Bachoco)",
    "gn:country_code":"MX",
    "gn:dem":391,
    "gn:feature_class":"P",
    "gn:feature_code":"PPL",
    "gn:name":"Progenitora N\u00facleo Uno (Bachoco)",
    "gn:population":6,
    "gn:timezone":"America/Hermosillo",
    "iso:country":"MX",
    "name:und_x_variant":[
        "Progenitora N\u00facleo Uno (Bachoco)"
    ],
    "wof:name":"Progenitora Nucleo Uno (Bachoco)",
    "wof:placetype":"locality",
    "wof:population":6
},
  "geometry": {"coordinates":[-109.29944,27.80694],"type":"Point"}
}