{
  "type": "Feature",
  "properties": {
    "gn:admin1_code":"3",
    "gn:admin2_code":"3.0",
    "gn:asciiname":"San Jose del Quelele",
    "gn:country_code":"MX",
    "gn:dem":7,
    "gn:feature_class":"P",
    "gn:feature_code":"PPL",
    "gn:name":"San Jos\u00e9 del Quelele",
    "gn:population":0,
    "gn:timezone":"America/Mazatlan",
    "iso:country":"MX",
    "name:spa_x_preferred":[
        "San Jos\u00e9 del Quelele"
    ],
    "wof:name":"San Jose del Quelele",
    "wof:placetype":"locality"
},
  "geometry": {"coordinates":[-110.5072,24.1933],"type":"Point"}
}