{
  "type": "Feature",
  "properties": {
    "gn:admin1_code":"18",
    "gn:admin2_code":"19",
    "gn:asciiname":"Platanar de los Lopez",
    "gn:country_code":"MX",
    "gn:dem":718,
    "gn:feature_class":"P",
    "gn:feature_code":"PPL",
    "gn:name":"Platanar de los L\u00f3pez",
    "gn:population":36,
    "gn:timezone":"America/Mazatlan",
    "iso:country":"MX",
    "name:und_x_variant":[
        "Platanar de los L\u00f3pez"
    ],
    "wof:name":"Platanar de los Lopez",
    "wof:placetype":"locality",
    "wof:population":36
},
  "geometry": {"coordinates":[-104.35889,21.34333],"type":"Point"}
}