{
  "type": "Feature",
  "properties": {
    "gn:admin1_code":"10",
    "gn:admin2_code":"37",
    "gn:asciiname":"El Zapote (Chapote)",
    "gn:country_code":"MX",
    "gn:dem":568,
    "gn:feature_class":"P",
    "gn:feature_code":"PPL",
    "gn:name":"El Zapote (Chapote)",
    "gn:population":12,
    "gn:timezone":"America/Monterrey",
    "iso:country":"MX",
    "wof:name":"El Zapote (Chapote)",
    "wof:placetype":"locality",
    "wof:population":12
},
  "geometry": {"coordinates":[-106.74148999999998,25.33775],"type":"Point"}
}