{
  "type": "Feature",
  "properties": {
    "gn:admin1_code":"32",
    "gn:admin2_code":"58.0",
    "gn:asciiname":"El Zapotito",
    "gn:country_code":"MX",
    "gn:dem":1892,
    "gn:feature_class":"P",
    "gn:feature_code":"PPL",
    "gn:name":"El Zapotito",
    "gn:population":50,
    "gn:timezone":"America/Mexico_City",
    "iso:country":"MX",
    "wof:name":"El Zapotito",
    "wof:placetype":"locality",
    "wof:population":50
},
  "geometry": {"coordinates":[-103.4325,21.56556],"type":"Point"}
}