{
  "type": "Feature",
  "properties": {
    "gn:admin1_code":"30.0",
    "gn:admin2_code":"109.0",
    "gn:asciiname":"Sabana Grande",
    "gn:country_code":"MX",
    "gn:dem":60,
    "gn:feature_class":"P",
    "gn:feature_code":"PPL",
    "gn:name":"S\u00e1bana Grande",
    "gn:population":0,
    "gn:timezone":"America/Mexico_City",
    "iso:country":"MX",
    "name:ceb_x_preferred":[
        "Sabana Grande"
    ],
    "name:fra_x_preferred":[
        "Sabana Grande"
    ],
    "name:ita_x_preferred":[
        "Sabana Grande"
    ],
    "name:nld_x_preferred":[
        "Sabana Grande"
    ],
    "name:pol_x_preferred":[
        "Sabana Grande"
    ],
    "name:spa_x_preferred":[
        "S\u00e1bana Grande"
    ],
    "name:spa_x_variant":[
        "Sabanagrande"
    ],
    "name:srp_x_preferred":[
        "\u0421\u0430\u0431\u0430\u043d\u0430 \u0413\u0440\u0430\u043d\u0434\u0435"
    ],
    "name:swe_x_preferred":[
        "Sabana Grande"
    ],
    "wof:name":"Sabana Grande",
    "wof:placetype":"locality"
},
  "geometry": {"coordinates":[-96.87551000000001,20.05183],"type":"Point"}
}