{
  "type": "Feature",
  "properties": {
    "gn:admin1_code":"32",
    "gn:admin2_code":"21.0",
    "gn:asciiname":"El Mimbre",
    "gn:country_code":"MX",
    "gn:dem":2322,
    "gn:feature_class":"P",
    "gn:feature_code":"PPL",
    "gn:name":"El Mimbre",
    "gn:population":0,
    "gn:timezone":"America/Mexico_City",
    "iso:country":"MX",
    "name:spa_x_preferred":[
        "El Mimbre"
    ],
    "wof:name":"El Mimbre",
    "wof:placetype":"locality"
},
  "geometry": {"coordinates":[-103.91839,23.15434],"type":"Point"}
}