{
  "type": "Feature",
  "properties": {
    "gn:admin1_code":"30",
    "gn:admin2_code":"71.0",
    "gn:asciiname":"El Horno",
    "gn:country_code":"MX",
    "gn:dem":1071,
    "gn:feature_class":"P",
    "gn:feature_code":"PPL",
    "gn:name":"El Horno",
    "gn:population":60,
    "gn:timezone":"America/Mexico_City",
    "iso:country":"MX",
    "wof:name":"El Horno",
    "wof:placetype":"locality",
    "wof:population":60
},
  "geometry": {"coordinates":[-96.94,19.08556],"type":"Point"}
}