{
  "type": "Feature",
  "properties": {
    "gn:admin1_code":"24",
    "gn:admin2_code":"37.0",
    "gn:asciiname":"Xilhuazo",
    "gn:country_code":"MX",
    "gn:dem":451,
    "gn:feature_class":"P",
    "gn:feature_code":"PPL",
    "gn:name":"Xilhuazo",
    "gn:population":246,
    "gn:timezone":"America/Mexico_City",
    "iso:country":"MX",
    "wof:name":"Xilhuazo",
    "wof:placetype":"locality",
    "wof:population":246
},
  "geometry": {"coordinates":[-98.86417,21.26472],"type":"Point"}
}