{
  "type": "Feature",
  "properties": {
    "gn:admin1_code":"11",
    "gn:admin2_code":"33",
    "gn:asciiname":"Noria de San Rafael",
    "gn:country_code":"MX",
    "gn:dem":2006,
    "gn:feature_class":"P",
    "gn:feature_code":"PPL",
    "gn:name":"Noria de San Rafael",
    "gn:population":10,
    "gn:timezone":"America/Mexico_City",
    "iso:country":"MX",
    "wof:name":"Noria de San Rafael",
    "wof:placetype":"locality",
    "wof:population":10
},
  "geometry": {"coordinates":[-100.58278,21.10389],"type":"Point"}
}