{
  "type": "Feature",
  "properties": {
    "gn:admin1_code":"22.0",
    "gn:admin2_code":"8.0",
    "gn:asciiname":"Las Lupitas",
    "gn:country_code":"MX",
    "gn:dem":2227,
    "gn:feature_class":"P",
    "gn:feature_code":"PPL",
    "gn:name":"Las Lupitas",
    "gn:population":0,
    "gn:timezone":"America/Mexico_City",
    "iso:country":"MX",
    "name:spa_x_preferred":[
        "Las Lupitas"
    ],
    "wof:name":"Las Lupitas",
    "wof:placetype":"locality"
},
  "geometry": {"coordinates":[-100.31346000000001,20.47337000000001],"type":"Point"}
}