{
  "type": "Feature",
  "properties": {
    "gn:admin1_code":"18.0",
    "gn:admin2_code":"9.0",
    "gn:asciiname":"La Bola Negra",
    "gn:country_code":"MX",
    "gn:dem":691,
    "gn:feature_class":"P",
    "gn:feature_code":"PPL",
    "gn:name":"La Bola Negra",
    "gn:population":0,
    "gn:timezone":"America/Mazatlan",
    "iso:country":"MX",
    "name:spa_x_preferred":[
        "La Bola Negra"
    ],
    "wof:name":"La Bola Negra",
    "wof:placetype":"locality"
},
  "geometry": {"coordinates":[-104.47305,21.56707],"type":"Point"}
}