{
  "type": "Feature",
  "properties": {
    "gn:admin1_code":"10.0",
    "gn:asciiname":"El Saltillo",
    "gn:country_code":"MX",
    "gn:dem":649,
    "gn:feature_class":"P",
    "gn:feature_code":"PPL",
    "gn:name":"El Saltillo",
    "gn:population":0,
    "gn:timezone":"America/Monterrey",
    "iso:country":"MX",
    "name:spa_x_preferred":[
        "El Saltillo"
    ],
    "wof:name":"El Saltillo",
    "wof:placetype":"locality"
},
  "geometry": {"coordinates":[-106.51123,24.44951],"type":"Point"}
}