{
  "type": "Feature",
  "properties": {
    "gn:admin1_code":"28",
    "gn:admin2_code":"21.0",
    "gn:asciiname":"Rosalinda",
    "gn:country_code":"MX",
    "gn:dem":119,
    "gn:feature_class":"P",
    "gn:feature_code":"PPL",
    "gn:name":"Rosalinda",
    "gn:population":5,
    "gn:timezone":"America/Monterrey",
    "iso:country":"MX",
    "name:ita_x_preferred":[
        "Rosalinda"
    ],
    "name:por_x_preferred":[
        "Rosalinda"
    ],
    "name:spa_x_preferred":[
        "Rosalinda"
    ],
    "name:srp_x_preferred":[
        "\u0420\u043e\u0441\u0430\u043b\u0438\u043d\u0434\u0430"
    ],
    "wof:name":"Rosalinda",
    "wof:placetype":"locality",
    "wof:population":5
},
  "geometry": {"coordinates":[-99.02139,22.63167],"type":"Point"}
}