{
  "type": "Feature",
  "properties": {
    "gn:admin1_code":"28",
    "gn:admin2_code":"17.0",
    "gn:asciiname":"Avila y Urbina",
    "gn:country_code":"MX",
    "gn:dem":1643,
    "gn:feature_class":"P",
    "gn:feature_code":"PPL",
    "gn:name":"Avila y Urbina",
    "gn:population":0,
    "gn:timezone":"America/Monterrey",
    "iso:country":"MX",
    "wof:name":"Avila y Urbina",
    "wof:placetype":"locality"
},
  "geometry": {"coordinates":[-99.59999999999999,23.68333],"type":"Point"}
}