{
  "type": "Feature",
  "properties": {
    "gn:admin1_code":"6",
    "gn:admin2_code":"7",
    "gn:asciiname":"Matejoachi",
    "gn:country_code":"MX",
    "gn:dem":2550,
    "gn:feature_class":"P",
    "gn:feature_code":"PPL",
    "gn:name":"Matejoachi",
    "gn:population":10,
    "gn:timezone":"America/Chihuahua",
    "iso:country":"MX",
    "wof:name":"Matejoachi",
    "wof:placetype":"locality",
    "wof:population":10
},
  "geometry": {"coordinates":[-106.63191,26.497],"type":"Point"}
}