{
  "type": "Feature",
  "properties": {
    "gn:admin1_code":"6",
    "gn:admin2_code":"63.0",
    "gn:asciiname":"El Doscientos Uno",
    "gn:country_code":"MX",
    "gn:dem":2629,
    "gn:feature_class":"P",
    "gn:feature_code":"PPL",
    "gn:name":"El Doscientos Uno",
    "gn:population":0,
    "gn:timezone":"America/Chihuahua",
    "iso:country":"MX",
    "name:spa_x_preferred":[
        "El Doscientos Uno"
    ],
    "wof:name":"El Doscientos Uno",
    "wof:placetype":"locality"
},
  "geometry": {"coordinates":[-108.3019,28.72322],"type":"Point"}
}