{
  "type": "Feature",
  "properties": {
    "gn:admin1_code":"26.0",
    "gn:admin2_code":"35.0",
    "gn:asciiname":"Agua Caliente (Elias)",
    "gn:country_code":"MX",
    "gn:dem":986,
    "gn:feature_class":"P",
    "gn:feature_code":"PPL",
    "gn:name":"Agua Caliente (El\u00edas)",
    "gn:population":6,
    "gn:timezone":"America/Hermosillo",
    "iso:country":"MX",
    "name:und_x_variant":[
        "Rancho Agua Caliente",
        "Agua Caliente"
    ],
    "wof:name":"Agua Caliente (Elias)",
    "wof:placetype":"locality",
    "wof:population":6
},
  "geometry": {"coordinates":[-110.85046,30.9503],"type":"Point"}
}