{
  "type": "Feature",
  "properties": {
    "gn:admin1_code":"6.0",
    "gn:asciiname":"Colonia Bellavista",
    "gn:country_code":"MX",
    "gn:dem":1200,
    "gn:feature_class":"P",
    "gn:feature_code":"PPL",
    "gn:name":"Colonia Bellavista",
    "gn:population":0,
    "gn:timezone":"America/Chihuahua",
    "iso:country":"MX",
    "name:spa_x_preferred":[
        "Colonia Bellavista"
    ],
    "wof:name":"Colonia Bellavista",
    "wof:placetype":"locality"
},
  "geometry": {"coordinates":[-105.35736,28.21446],"type":"Point"}
}