{
  "type": "Feature",
  "properties": {
    "gn:admin1_code":"10.0",
    "gn:admin2_code":"35.0",
    "gn:asciiname":"La Loma del Pilar",
    "gn:country_code":"MX",
    "gn:dem":2433,
    "gn:feature_class":"P",
    "gn:feature_code":"PPL",
    "gn:name":"La Loma del Pilar",
    "gn:population":0,
    "gn:timezone":"America/Monterrey",
    "iso:country":"MX",
    "name:spa_x_preferred":[
        "La Loma del Pilar"
    ],
    "wof:name":"La Loma del Pilar",
    "wof:placetype":"locality"
},
  "geometry": {"coordinates":[-106.51558,25.65665],"type":"Point"}
}