{
  "type": "Feature",
  "properties": {
    "gn:admin1_code":"30.0",
    "gn:admin2_code":"13.0",
    "gn:asciiname":"Zapupe",
    "gn:country_code":"MX",
    "gn:dem":96,
    "gn:feature_class":"P",
    "gn:feature_code":"PPL",
    "gn:name":"Zapupe",
    "gn:population":8,
    "gn:timezone":"America/Mexico_City",
    "iso:country":"MX",
    "name:spa_x_preferred":[
        "Zapupe"
    ],
    "wof:name":"Zapupe",
    "wof:placetype":"locality",
    "wof:population":8
},
  "geometry": {"coordinates":[-97.6481,21.32917],"type":"Point"}
}