{
  "type": "Feature",
  "properties": {
    "gn:admin1_code":"6",
    "gn:admin2_code":"12.0",
    "gn:asciiname":"Baderachi",
    "gn:country_code":"MX",
    "gn:dem":1977,
    "gn:feature_class":"P",
    "gn:feature_code":"PPL",
    "gn:name":"Baderachi",
    "gn:population":0,
    "gn:timezone":"America/Chihuahua",
    "iso:country":"MX",
    "name:spa_x_preferred":[
        "Baderachi"
    ],
    "wof:name":"Baderachi",
    "wof:placetype":"locality"
},
  "geometry": {"coordinates":[-107.10824,27.5692],"type":"Point"}
}