{
  "type": "Feature",
  "properties": {
    "gn:admin1_code":"25",
    "gn:admin2_code":"6.0",
    "gn:asciiname":"El Reencuentro",
    "gn:country_code":"MX",
    "gn:dem":62,
    "gn:feature_class":"P",
    "gn:feature_code":"PPL",
    "gn:name":"El Reencuentro",
    "gn:population":5,
    "gn:timezone":"America/Mazatlan",
    "iso:country":"MX",
    "name:spa_x_preferred":[
        "El Reencuentro"
    ],
    "wof:name":"El Reencuentro",
    "wof:placetype":"locality",
    "wof:population":5
},
  "geometry": {"coordinates":[-107.29819000000001,24.59385],"type":"Point"}
}