{
  "type": "Feature",
  "properties": {
    "gn:admin1_code":"30.0",
    "gn:admin2_code":"189.0",
    "gn:asciiname":"Rancho Viejo",
    "gn:country_code":"MX",
    "gn:dem":32,
    "gn:feature_class":"P",
    "gn:feature_code":"PPL",
    "gn:name":"Rancho Viejo",
    "gn:population":4,
    "gn:timezone":"America/Mexico_City",
    "iso:country":"MX",
    "name:spa_x_preferred":[
        "Rancho Viejo"
    ],
    "wof:name":"Rancho Viejo",
    "wof:placetype":"locality",
    "wof:population":4
},
  "geometry": {"coordinates":[-97.52889,21.05444],"type":"Point"}
}