{
  "type": "Feature",
  "properties": {
    "gn:admin1_code":"12",
    "gn:admin2_code":"12.0",
    "gn:asciiname":"La Unificada",
    "gn:country_code":"MX",
    "gn:dem":718,
    "gn:feature_class":"P",
    "gn:feature_code":"PPL",
    "gn:name":"La Unificada",
    "gn:population":91,
    "gn:timezone":"America/Mexico_City",
    "iso:country":"MX",
    "wof:name":"La Unificada",
    "wof:placetype":"locality",
    "wof:population":91
},
  "geometry": {"coordinates":[-99.00906000000001,17.04873],"type":"Point"}
}