{
  "type": "Feature",
  "properties": {
    "gn:admin1_code":"19.0",
    "gn:admin2_code":"8.0",
    "gn:asciiname":"El Bufalo [Agropecuaria]",
    "gn:country_code":"MX",
    "gn:dem":437,
    "gn:feature_class":"P",
    "gn:feature_code":"PPL",
    "gn:name":"El B\u00fafalo [Agropecuaria]",
    "gn:population":4,
    "gn:timezone":"America/Monterrey",
    "iso:country":"MX",
    "name:spa_x_preferred":[
        "B\u00fafalo"
    ],
    "wof:name":"El Bufalo [Agropecuaria]",
    "wof:placetype":"locality",
    "wof:population":4
},
  "geometry": {"coordinates":[-100.46033,26.50726],"type":"Point"}
}