{
  "type": "Feature",
  "properties": {
    "gn:admin1_code":"6",
    "gn:admin2_code":"29.0",
    "gn:asciiname":"Las Piedras",
    "gn:country_code":"MX",
    "gn:dem":2347,
    "gn:feature_class":"P",
    "gn:feature_code":"PPL",
    "gn:name":"Las Piedras",
    "gn:population":25,
    "gn:timezone":"America/Chihuahua",
    "iso:country":"MX",
    "name:bul_x_preferred":[
        "\u041b\u0430\u0441 \u041f\u0438\u0435\u0434\u0440\u0430\u0441"
    ],
    "name:cat_x_preferred":[
        "Las Piedras"
    ],
    "name:ceb_x_preferred":[
        "Las Piedras"
    ],
    "name:deu_x_preferred":[
        "Las Piedras"
    ],
    "name:glg_x_preferred":[
        "Las Piedras"
    ],
    "name:hye_x_preferred":[
        "\u053c\u0561\u057d \u054a\u0565\u0564\u0580\u0561\u057d"
    ],
    "name:ita_x_preferred":[
        "Las Piedras"
    ],
    "name:mlg_x_preferred":[
        "Las Piedras"
    ],
    "name:nld_x_preferred":[
        "Las Piedras"
    ],
    "name:pol_x_preferred":[
        "Las Piedras"
    ],
    "name:por_x_preferred":[
        "Las Piedras"
    ],
    "name:rus_x_preferred":[
        "\u041b\u0430\u0441-\u041f\u044c\u0435\u0434\u0440\u0430\u0441"
    ],
    "name:spa_x_preferred":[
        "Las Piedras"
    ],
    "name:swe_x_preferred":[
        "Las Piedras"
    ],
    "name:vep_x_preferred":[
        "Las Pjedras"
    ],
    "wof:name":"Las Piedras",
    "wof:placetype":"locality",
    "wof:population":25
},
  "geometry": {"coordinates":[-107.25133,26.51629],"type":"Point"}
}