{
  "type": "Feature",
  "properties": {
    "gn:admin1_code":"20",
    "gn:admin2_code":"309.0",
    "gn:asciiname":"Colonia Buena Vista",
    "gn:country_code":"MX",
    "gn:dem":80,
    "gn:feature_class":"P",
    "gn:feature_code":"PPL",
    "gn:name":"Colonia Buena Vista",
    "gn:population":86,
    "gn:timezone":"America/Mexico_City",
    "iso:country":"MX",
    "wof:name":"Colonia Buena Vista",
    "wof:placetype":"locality",
    "wof:population":86
},
  "geometry": {"coordinates":[-96.52,18.13611],"type":"Point"}
}