{
  "type": "Feature",
  "properties": {
    "gn:admin1_code":"11.0",
    "gn:admin2_code":"1.0",
    "gn:asciiname":"Ahualulco",
    "gn:country_code":"MX",
    "gn:dem":1703,
    "gn:feature_class":"P",
    "gn:feature_code":"PPL",
    "gn:name":"Ahualulco",
    "gn:population":0,
    "gn:timezone":"America/Mexico_City",
    "iso:country":"MX",
    "name:epo_x_preferred":[
        "Ahualulco"
    ],
    "name:eus_x_preferred":[
        "Ahualulco"
    ],
    "name:fas_x_preferred":[
        "\u0627\u0647\u0648\u0627\u0644\u0627\u0644\u06a9\u0648"
    ],
    "name:ita_x_preferred":[
        "Ahualulco"
    ],
    "name:por_x_preferred":[
        "Ahualulco"
    ],
    "name:spa_x_preferred":[
        "Ahualulco"
    ],
    "name:und_x_variant":[
        "Ahualulca",
        "Ahualulco"
    ],
    "name:vie_x_preferred":[
        "Ahualulco"
    ],
    "wof:name":"Ahualulco",
    "wof:placetype":"locality"
},
  "geometry": {"coordinates":[-101.50749999999999,20.57389],"type":"Point"}
}