{
  "type": "Feature",
  "properties": {
    "gn:admin1_code":"15",
    "gn:admin2_code":"66",
    "gn:asciiname":"El Zapote (La Parota)",
    "gn:country_code":"MX",
    "gn:dem":1281,
    "gn:feature_class":"P",
    "gn:feature_code":"PPL",
    "gn:name":"El Zapote (La Parota)",
    "gn:population":21,
    "gn:timezone":"America/Mexico_City",
    "iso:country":"MX",
    "wof:name":"El Zapote (La Parota)",
    "wof:placetype":"locality",
    "wof:population":21
},
  "geometry": {"coordinates":[-100.34393,19.14388],"type":"Point"}
}