{
  "type": "Feature",
  "properties": {
    "gn:admin1_code":"15",
    "gn:admin2_code":"120.0",
    "gn:asciiname":"La Soledad",
    "gn:country_code":"MX",
    "gn:dem":2308,
    "gn:feature_class":"P",
    "gn:feature_code":"PPL",
    "gn:name":"La Soledad",
    "gn:population":56,
    "gn:timezone":"America/Mexico_City",
    "iso:country":"MX",
    "wof:name":"La Soledad",
    "wof:placetype":"locality",
    "wof:population":56
},
  "geometry": {"coordinates":[-99.17055000000001,19.82675],"type":"Point"}
}