{
  "type": "Feature",
  "properties": {
    "gn:admin1_code":"6.0",
    "gn:admin2_code":"65.0",
    "gn:asciiname":"La Y Griega",
    "gn:country_code":"MX",
    "gn:dem":2044,
    "gn:feature_class":"P",
    "gn:feature_code":"PPL",
    "gn:name":"La Y Griega",
    "gn:population":0,
    "gn:timezone":"America/Chihuahua",
    "iso:country":"MX",
    "name:spa_x_preferred":[
        "La Y Griega"
    ],
    "wof:name":"La Y Griega",
    "wof:placetype":"locality"
},
  "geometry": {"coordinates":[-108.08880000000001,27.44974],"type":"Point"}
}