{
  "type": "Feature",
  "properties": {
    "gn:admin1_code":"21",
    "gn:admin2_code":"99.0",
    "gn:asciiname":"El Calvario",
    "gn:country_code":"MX",
    "gn:dem":2336,
    "gn:feature_class":"P",
    "gn:feature_code":"PPL",
    "gn:name":"El Calvario",
    "gn:population":121,
    "gn:timezone":"America/Mexico_City",
    "iso:country":"MX",
    "wof:name":"El Calvario",
    "wof:placetype":"locality",
    "wof:population":121
},
  "geometry": {"coordinates":[-97.43138999999999,18.73556],"type":"Point"}
}