{
  "type": "Feature",
  "properties": {
    "gn:admin1_code":"27",
    "gn:admin2_code":"8.0",
    "gn:asciiname":"El Dorado",
    "gn:country_code":"MX",
    "gn:dem":33,
    "gn:feature_class":"P",
    "gn:feature_code":"PPL",
    "gn:name":"El Dorado",
    "gn:population":1025,
    "gn:timezone":"America/Mexico_City",
    "iso:country":"MX",
    "wof:name":"El Dorado",
    "wof:placetype":"locality",
    "wof:population":1025
},
  "geometry": {"coordinates":[-93.36788,17.88322999999999],"type":"Point"}
}