{
  "type": "Feature",
  "properties": {
    "gn:admin1_code":"2.0",
    "gn:admin2_code":"2.0",
    "gn:asciiname":"Familia Gutierrez Romero (Ejido Plan de Ayala)",
    "gn:country_code":"MX",
    "gn:dem":10,
    "gn:feature_class":"P",
    "gn:feature_code":"PPL",
    "gn:name":"Familia Guti\u00e9rrez Romero (Ejido Plan de Ayala)",
    "gn:population":15,
    "gn:timezone":"America/Tijuana",
    "iso:country":"MX",
    "name:spa_x_preferred":[
        "Romero"
    ],
    "wof:name":"Familia Gutierrez Romero (Ejido Plan de Ayala)",
    "wof:placetype":"locality",
    "wof:population":15
},
  "geometry": {"coordinates":[-115.07277999999999,32.18444],"type":"Point"}
}