{
  "type": "Feature",
  "properties": {
    "gn:admin1_code":"32.0",
    "gn:admin2_code":"56.0",
    "gn:asciiname":"Casa Blanca",
    "gn:country_code":"MX",
    "gn:dem":2449,
    "gn:feature_class":"P",
    "gn:feature_code":"PPL",
    "gn:name":"Casa Blanca",
    "gn:population":0,
    "gn:timezone":"America/Mexico_City",
    "iso:country":"MX",
    "wof:name":"Casa Blanca",
    "wof:placetype":"locality"
},
  "geometry": {"coordinates":[-102.78333000000001,22.68333],"type":"Point"}
}