{
  "type": "Feature",
  "properties": {
    "gn:admin1_code":"30.0",
    "gn:admin2_code":"155.0",
    "gn:asciiname":"Corea",
    "gn:country_code":"MX",
    "gn:dem":94,
    "gn:feature_class":"P",
    "gn:feature_code":"PPL",
    "gn:name":"Corea",
    "gn:population":2,
    "gn:timezone":"America/Mexico_City",
    "iso:country":"MX",
    "name:spa_x_preferred":[
        "Corea"
    ],
    "wof:name":"Corea",
    "wof:placetype":"locality",
    "wof:population":2
},
  "geometry": {"coordinates":[-98.06268,21.37884],"type":"Point"}
}