{
  "type": "Feature",
  "properties": {
    "gn:admin1_code":"30",
    "gn:admin2_code":"175.0",
    "gn:asciiname":"Daniel Solis",
    "gn:country_code":"MX",
    "gn:dem":118,
    "gn:feature_class":"P",
    "gn:feature_code":"PPL",
    "gn:name":"Daniel Sol\u00eds",
    "gn:population":6,
    "gn:timezone":"America/Mexico_City",
    "iso:country":"MX",
    "name:und_x_variant":[
        "Daniel Sol\u00eds"
    ],
    "wof:name":"Daniel Solis",
    "wof:placetype":"locality",
    "wof:population":6
},
  "geometry": {"coordinates":[-97.53749999999999,20.70528],"type":"Point"}
}