{
  "type": "Feature",
  "properties": {
    "gn:admin1_code":"16.0",
    "gn:admin2_code":"46.0",
    "gn:asciiname":"La Finca de los Tepehuajes",
    "gn:country_code":"MX",
    "gn:dem":1215,
    "gn:feature_class":"P",
    "gn:feature_code":"PPL",
    "gn:name":"La Finca de los Tepehuajes",
    "gn:population":0,
    "gn:timezone":"America/Mexico_City",
    "iso:country":"MX",
    "name:spa_x_preferred":[
        "La Finca de los Tepehuajes"
    ],
    "wof:name":"La Finca de los Tepehuajes",
    "wof:placetype":"locality"
},
  "geometry": {"coordinates":[-100.46928,19.31764],"type":"Point"}
}