{
  "type": "Feature",
  "properties": {
    "gn:admin1_code":"5",
    "gn:admin2_code":"31.0",
    "gn:asciiname":"Bapaxila San Sebastian",
    "gn:country_code":"MX",
    "gn:dem":772,
    "gn:feature_class":"P",
    "gn:feature_code":"PPL",
    "gn:name":"Bapaxil\u00e1 San Sebasti\u00e1n",
    "gn:population":128,
    "gn:timezone":"America/Mexico_City",
    "iso:country":"MX",
    "name:und_x_variant":[
        "Bapaxil\u00e1 San Sebasti\u00e1n"
    ],
    "wof:name":"Bapaxila San Sebastian",
    "wof:placetype":"locality",
    "wof:population":128
},
  "geometry": {"coordinates":[-92.08667,17.15556],"type":"Point"}
}