{
  "type": "Feature",
  "properties": {
    "gn:admin1_code":"16",
    "gn:admin2_code":"66",
    "gn:asciiname":"Las Cabanas",
    "gn:country_code":"MX",
    "gn:dem":2111,
    "gn:feature_class":"P",
    "gn:feature_code":"PPL",
    "gn:name":"Las Caba\u00f1as",
    "gn:population":34,
    "gn:timezone":"America/Mexico_City",
    "iso:country":"MX",
    "name:und_x_variant":[
        "Las Caba\u00f1as"
    ],
    "wof:name":"Las Cabanas",
    "wof:placetype":"locality",
    "wof:population":34
},
  "geometry": {"coordinates":[-101.54555999999999,19.53472],"type":"Point"}
}