{
  "type": "Feature",
  "properties": {
    "gn:admin1_code":"6",
    "gn:admin2_code":"10.0",
    "gn:asciiname":"La Laguna Chiquita",
    "gn:country_code":"MX",
    "gn:dem":1289,
    "gn:feature_class":"P",
    "gn:feature_code":"PPL",
    "gn:name":"La Laguna Chiquita",
    "gn:population":0,
    "gn:timezone":"America/Chihuahua",
    "iso:country":"MX",
    "wof:name":"La Laguna Chiquita",
    "wof:placetype":"locality"
},
  "geometry": {"coordinates":[-107.31667,30.43333],"type":"Point"}
}