{
  "type": "Feature",
  "properties": {
    "gn:admin1_code":"26.0",
    "gn:admin2_code":"3.0",
    "gn:asciiname":"Chorijoa",
    "gn:country_code":"MX",
    "gn:dem":205,
    "gn:feature_class":"P",
    "gn:feature_code":"PPL",
    "gn:name":"Chorijoa",
    "gn:population":0,
    "gn:timezone":"America/Hermosillo",
    "iso:country":"MX",
    "name:und_x_variant":[
        "Chirijoa",
        "Chorijoa"
    ],
    "wof:name":"Chorijoa",
    "wof:placetype":"locality"
},
  "geometry": {"coordinates":[-108.87178,27.46603],"type":"Point"}
}