{
  "type": "Feature",
  "properties": {
    "gn:admin1_code":"10",
    "gn:admin2_code":"14.0",
    "gn:asciiname":"Agua Puerca",
    "gn:country_code":"MX",
    "gn:dem":2021,
    "gn:feature_class":"P",
    "gn:feature_code":"PPL",
    "gn:name":"Agua Puerca",
    "gn:population":0,
    "gn:timezone":"America/Monterrey",
    "iso:country":"MX",
    "name:spa_x_preferred":[
        "Agua Puerca"
    ],
    "name:srp_x_preferred":[
        "\u0410\u0433\u0432\u0430 \u041f\u0443\u0435\u0440\u043a\u0430"
    ],
    "wof:name":"Agua Puerca",
    "wof:placetype":"locality"
},
  "geometry": {"coordinates":[-104.62853,23.22833],"type":"Point"}
}