{
  "type": "Feature",
  "properties": {
    "gn:admin1_code":"2.0",
    "gn:admin2_code":"1.0",
    "gn:asciiname":"El Ramajal",
    "gn:country_code":"MX",
    "gn:dem":107,
    "gn:feature_class":"P",
    "gn:feature_code":"PPL",
    "gn:name":"El Ramajal",
    "gn:population":50,
    "gn:timezone":"America/Tijuana",
    "iso:country":"MX",
    "name:spa_x_preferred":[
        "El Ramajal"
    ],
    "wof:name":"El Ramajal",
    "wof:placetype":"locality",
    "wof:population":50
},
  "geometry": {"coordinates":[-116.625,31.68556],"type":"Point"}
}