{
  "type": "Feature",
  "properties": {
    "iso:country":"MX",
    "name:spa_x_preferred":[
        "Zona Centro"
    ],
    "name:unk_x_variant":[
        "Zona Centro"
    ],
    "qs:gn_adm0_cc":"MX",
    "qs:gn_local":3979844,
    "qs:gn_nam_loc":"Zacatecas, Zacatecas, Zacatecas, MX",
    "qs:gn_namadm1":"32",
    "qs:local_max":2496,
    "qs:local_sum":3952,
    "qs:localhoods":7,
    "qs:name":"Zona Centro",
    "qs:name_adm0":"M\u00e9xico",
    "qs:name_adm1":"Zacatecas",
    "qs:name_adm2":"Zacatecas",
    "qs:name_local":"Zacatecas",
    "qs:photo_max":532,
    "qs:photo_sum":2496,
    "qs:placetype":"Suburb",
    "qs:quad_count":32,
    "qs:woe_adm0":23424900,
    "qs:woe_adm1":2346295,
    "qs:woe_adm2":12602087,
    "qs:woe_lau":0,
    "qs:woe_local":151495,
    "qs:woe_ver":"7.10.0",
    "wof:lang":[
        "spa"
    ],
    "wof:name":"Zona Centro",
    "wof:placetype":"neighbourhood"
},
  "geometry": {"coordinates":[-102.574888,22.771991],"type":"Point"}
}