{
  "type": "Feature",
  "properties": {
    "gn:admin1_code":"21.0",
    "gn:admin2_code":"114.0",
    "gn:asciiname":"Colonia Valle del Pinal",
    "gn:country_code":"MX",
    "gn:dem":2102,
    "gn:feature_class":"P",
    "gn:feature_code":"PPL",
    "gn:name":"Colonia Valle del Pinal",
    "gn:population":0,
    "gn:timezone":"America/Mexico_City",
    "iso:country":"MX",
    "name:spa_x_preferred":[
        "Colonia Valle del Pinal"
    ],
    "wof:name":"Colonia Valle del Pinal",
    "wof:placetype":"locality"
},
  "geometry": {"coordinates":[-98.18346,18.97317],"type":"Point"}
}