{
  "type": "Feature",
  "properties": {
    "gn:admin1_code":"29",
    "gn:admin2_code":"8.0",
    "gn:asciiname":"San Diego Coyotepec",
    "gn:country_code":"MX",
    "gn:dem":2427,
    "gn:feature_class":"P",
    "gn:feature_code":"PPL",
    "gn:name":"San Diego Coyotepec",
    "gn:population":4,
    "gn:timezone":"America/Mexico_City",
    "iso:country":"MX",
    "wof:name":"San Diego Coyotepec",
    "wof:placetype":"locality",
    "wof:population":4
},
  "geometry": {"coordinates":[-97.73217,19.29818],"type":"Point"}
}