{
  "type": "Feature",
  "properties": {
    "gn:admin1_code":"5",
    "gn:admin2_code":"106.0",
    "gn:asciiname":"Fraccion Santa Lucia",
    "gn:country_code":"MX",
    "gn:dem":597,
    "gn:feature_class":"P",
    "gn:feature_code":"PPL",
    "gn:name":"Fracci\u00f3n Santa Luc\u00eda",
    "gn:population":7,
    "gn:timezone":"America/Mexico_City",
    "iso:country":"MX",
    "name:und_x_variant":[
        "Fracci\u00f3n Santa Luc\u00eda"
    ],
    "wof:name":"Fraccion Santa Lucia",
    "wof:placetype":"locality",
    "wof:population":7
},
  "geometry": {"coordinates":[-92.57306,16.31833],"type":"Point"}
}