{
  "type": "Feature",
  "properties": {
    "gn:admin1_code":"25",
    "gn:admin2_code":"7.0",
    "gn:asciiname":"Rancho de Baymena",
    "gn:country_code":"MX",
    "gn:dem":284,
    "gn:feature_class":"P",
    "gn:feature_code":"PPL",
    "gn:name":"Rancho de Baymena",
    "gn:population":173,
    "gn:timezone":"America/Mazatlan",
    "iso:country":"MX",
    "wof:name":"Rancho de Baymena",
    "wof:placetype":"locality",
    "wof:population":173
},
  "geometry": {"coordinates":[-108.3275,26.52333],"type":"Point"}
}