{
  "type": "Feature",
  "properties": {
    "gn:admin1_code":"12",
    "gn:admin2_code":"31",
    "gn:asciiname":"Nueva Esperanza",
    "gn:country_code":"MX",
    "gn:dem":1100,
    "gn:feature_class":"P",
    "gn:feature_code":"PPL",
    "gn:name":"Nueva Esperanza",
    "gn:population":41,
    "gn:timezone":"America/Mexico_City",
    "iso:country":"MX",
    "wof:name":"Nueva Esperanza",
    "wof:placetype":"locality",
    "wof:population":41
},
  "geometry": {"coordinates":[-100.01972000000001,18.46389],"type":"Point"}
}