{
  "type": "Feature",
  "properties": {
    "gn:admin1_code":"32",
    "gn:admin2_code":"31",
    "gn:asciiname":"El Guaje",
    "gn:country_code":"MX",
    "gn:dem":2171,
    "gn:feature_class":"P",
    "gn:feature_code":"PPL",
    "gn:name":"El Guaje",
    "gn:population":23,
    "gn:timezone":"America/Mexico_City",
    "iso:country":"MX",
    "wof:name":"El Guaje",
    "wof:placetype":"locality",
    "wof:population":23
},
  "geometry": {"coordinates":[-103.47,22.545],"type":"Point"}
}