{
  "type": "Feature",
  "properties": {
    "gn:admin1_code":"14.0",
    "gn:admin2_code":"87.0",
    "gn:asciiname":"Favor",
    "gn:country_code":"MX",
    "gn:dem":1519,
    "gn:feature_class":"P",
    "gn:feature_code":"PPL",
    "gn:name":"Favor",
    "gn:population":0,
    "gn:timezone":"America/Mexico_City",
    "iso:country":"MX",
    "wof:name":"Favor",
    "wof:placetype":"locality"
},
  "geometry": {"coordinates":[-103.23333,19.46667],"type":"Point"}
}