{
  "type": "Feature",
  "properties": {
    "gn:admin1_code":"24",
    "gn:admin2_code":"54.0",
    "gn:asciiname":"Moloxco",
    "gn:country_code":"MX",
    "gn:dem":803,
    "gn:feature_class":"P",
    "gn:feature_code":"PPL",
    "gn:name":"Moloxco",
    "gn:population":294,
    "gn:timezone":"America/Mexico_City",
    "iso:country":"MX",
    "wof:name":"Moloxco",
    "wof:placetype":"locality",
    "wof:population":294
},
  "geometry": {"coordinates":[-98.94361000000001,21.38889],"type":"Point"}
}