{
  "type": "Feature",
  "properties": {
    "gn:admin1_code":"13",
    "gn:admin2_code":"53",
    "gn:asciiname":"El Cojolite",
    "gn:country_code":"MX",
    "gn:dem":969,
    "gn:feature_class":"P",
    "gn:feature_code":"PPL",
    "gn:name":"El Cojolite",
    "gn:population":47,
    "gn:timezone":"America/Mexico_City",
    "iso:country":"MX",
    "wof:name":"El Cojolite",
    "wof:placetype":"locality",
    "wof:population":47
},
  "geometry": {"coordinates":[-98.13929,20.50315],"type":"Point"}
}