{
  "type": "Feature",
  "properties": {
    "gn:admin1_code":"6",
    "gn:admin2_code":"13.0",
    "gn:asciiname":"Leona Vicario",
    "gn:country_code":"MX",
    "gn:dem":1431,
    "gn:feature_class":"P",
    "gn:feature_code":"PPL",
    "gn:name":"Leona Vicario",
    "gn:population":71,
    "gn:timezone":"America/Chihuahua",
    "iso:country":"MX",
    "name:ast_x_preferred":[
        "Leona Vicario"
    ],
    "name:ben_x_preferred":[
        "\u09b2\u09bf\u0993\u09a8\u09be \u09ad\u09bf\u0995\u09be\u09b0\u09bf\u0993"
    ],
    "name:cat_x_preferred":[
        "Leona Vicario"
    ],
    "name:fra_x_preferred":[
        "Leona Vicario"
    ],
    "name:hun_x_preferred":[
        "Leona Vicario"
    ],
    "name:ita_x_preferred":[
        "Leona Vicario"
    ],
    "name:pan_x_preferred":[
        "\u0a32\u0a3f\u0a13\u0a28\u0a3e \u0a35\u0a3f\u0a15\u0a3e\u0a30\u0a40\u0a13"
    ],
    "name:por_x_preferred":[
        "Leona Vicario"
    ],
    "name:rus_x_preferred":[
        "\u0412\u0438\u043a\u0430\u0440\u0438\u043e"
    ],
    "name:spa_x_preferred":[
        "Leona Vicario"
    ],
    "name:swe_x_preferred":[
        "Leona Vicario"
    ],
    "name:vie_x_preferred":[
        "Leona Vicario"
    ],
    "wof:name":"Leona Vicario",
    "wof:placetype":"locality",
    "wof:population":71
},
  "geometry": {"coordinates":[-107.93562,30.51805],"type":"Point"}
}