{
  "type": "Feature",
  "properties": {
    "gn:admin1_code":"6",
    "gn:admin2_code":"13.0",
    "gn:asciiname":"Leona Vicario",
    "gn:country_code":"MX",
    "gn:dem":1431,
    "gn:feature_class":"P",
    "gn:feature_code":"PPL",
    "gn:name":"Leona Vicario",
    "gn:population":71,
    "gn:timezone":"America/Chihuahua",
    "iso:country":"MX",
    "name:spa_x_preferred":[
        "Leona Vicario"
    ],
    "wof:name":"Leona Vicario",
    "wof:placetype":"locality",
    "wof:population":71
},
  "geometry": {"coordinates":[-107.93562,30.51805],"type":"Point"}
}