{
  "type": "Feature",
  "properties": {
    "gn:admin1_code":"6",
    "gn:admin2_code":"65",
    "gn:asciiname":"Las Arenitas",
    "gn:country_code":"MX",
    "gn:dem":1990,
    "gn:feature_class":"P",
    "gn:feature_code":"PPL",
    "gn:name":"Las Arenitas",
    "gn:population":9,
    "gn:timezone":"America/Chihuahua",
    "iso:country":"MX",
    "wof:name":"Las Arenitas",
    "wof:placetype":"locality",
    "wof:population":9
},
  "geometry": {"coordinates":[-108.0577,27.50381],"type":"Point"}
}