{
  "type": "Feature",
  "properties": {
    "gn:admin1_code":"11",
    "gn:admin2_code":"3",
    "gn:asciiname":"Nicolas Rosas Aguado",
    "gn:country_code":"MX",
    "gn:dem":2095,
    "gn:feature_class":"P",
    "gn:feature_code":"PPL",
    "gn:name":"Nicol\u00e1s Rosas Aguado",
    "gn:population":13,
    "gn:timezone":"America/Mexico_City",
    "iso:country":"MX",
    "name:und_x_variant":[
        "Nicol\u00e1s Rosas Aguado"
    ],
    "wof:name":"Nicolas Rosas Aguado",
    "wof:placetype":"locality",
    "wof:population":13
},
  "geometry": {"coordinates":[-100.57194,20.88222],"type":"Point"}
}