{
  "type": "Feature",
  "properties": {
    "gn:admin1_code":"16",
    "gn:admin2_code":"98.0",
    "gn:asciiname":"Los Lobos",
    "gn:country_code":"MX",
    "gn:dem":1770,
    "gn:feature_class":"P",
    "gn:feature_code":"PPL",
    "gn:name":"Los Lobos",
    "gn:population":179,
    "gn:timezone":"America/Mexico_City",
    "iso:country":"MX",
    "wof:name":"Los Lobos",
    "wof:placetype":"locality",
    "wof:population":179
},
  "geometry": {"coordinates":[-100.48166999999999,19.53444],"type":"Point"}
}