{
  "type": "Feature",
  "properties": {
    "gn:admin1_code":"31",
    "gn:admin2_code":"50.0",
    "gn:asciiname":"Sotuta de Peon",
    "gn:country_code":"MX",
    "gn:dem":14,
    "gn:feature_class":"P",
    "gn:feature_code":"PPL",
    "gn:name":"Sotuta de Pe\u00f3n",
    "gn:population":0,
    "gn:timezone":"America/Merida",
    "iso:country":"MX",
    "name:und_x_variant":[
        "Sotuta",
        "Sotula",
        "Sotuta de Pe\u00f3n"
    ],
    "wof:name":"Sotuta de Peon",
    "wof:placetype":"locality"
},
  "geometry": {"coordinates":[-89.57785,20.74178],"type":"Point"}
}