{
  "type": "Feature",
  "properties": {
    "gn:admin1_code":"24",
    "gn:admin2_code":"4.0",
    "gn:asciiname":"Temascal",
    "gn:country_code":"MX",
    "gn:dem":1821,
    "gn:feature_class":"P",
    "gn:feature_code":"PPL",
    "gn:name":"Temascal",
    "gn:population":0,
    "gn:timezone":"America/Mexico_City",
    "iso:country":"MX",
    "wof:name":"Temascal",
    "wof:placetype":"locality"
},
  "geometry": {"coordinates":[-100.51433,22.39361],"type":"Point"}
}