{
  "type": "Feature",
  "properties": {
    "gn:admin1_code":"11",
    "gn:admin2_code":"45.0",
    "gn:asciiname":"El Contadero",
    "gn:country_code":"MX",
    "gn:dem":2534,
    "gn:feature_class":"P",
    "gn:feature_code":"PPL",
    "gn:name":"El Contadero",
    "gn:population":77,
    "gn:timezone":"America/Mexico_City",
    "iso:country":"MX",
    "wof:name":"El Contadero",
    "wof:placetype":"locality",
    "wof:population":77
},
  "geometry": {"coordinates":[-100.07889,21.23361],"type":"Point"}
}