{
  "type": "Feature",
  "properties": {
    "gn:admin1_code":"11",
    "gn:admin2_code":"23.0",
    "gn:asciiname":"San Vicente del Marmol",
    "gn:country_code":"MX",
    "gn:dem":1692,
    "gn:feature_class":"P",
    "gn:feature_code":"PPL",
    "gn:name":"San Vicente del M\u00e1rmol",
    "gn:population":82,
    "gn:timezone":"America/Mexico_City",
    "iso:country":"MX",
    "name:und_x_variant":[
        "San Vicente del M\u00e1rmol"
    ],
    "wof:name":"San Vicente del Marmol",
    "wof:placetype":"locality",
    "wof:population":82
},
  "geometry": {"coordinates":[-101.74694,20.21361],"type":"Point"}
}