{
  "type": "Feature",
  "properties": {
    "gn:admin1_code":"6",
    "gn:admin2_code":"11.0",
    "gn:asciiname":"Maravillas",
    "gn:country_code":"MX",
    "gn:dem":1216,
    "gn:feature_class":"P",
    "gn:feature_code":"PPL",
    "gn:name":"Maravillas",
    "gn:population":0,
    "gn:timezone":"America/Chihuahua",
    "iso:country":"MX",
    "name:ceb_x_preferred":[
        "Maravillas"
    ],
    "name:deu_x_preferred":[
        "Maravillas"
    ],
    "name:swe_x_preferred":[
        "Maravillas"
    ],
    "name:und_x_variant":[
        "Rancho Maravillas",
        "Maravillas",
        "Las Maravillas"
    ],
    "wof:name":"Maravillas",
    "wof:placetype":"locality"
},
  "geometry": {"coordinates":[-105.18461000000001,27.77679],"type":"Point"}
}