{
  "type": "Feature",
  "properties": {
    "gn:admin1_code":"15",
    "gn:admin2_code":"111.0",
    "gn:asciiname":"El Puerto Lengua de Vaca",
    "gn:country_code":"MX",
    "gn:dem":2876,
    "gn:feature_class":"P",
    "gn:feature_code":"PPL",
    "gn:name":"El Puerto Lengua de Vaca",
    "gn:population":179,
    "gn:timezone":"America/Mexico_City",
    "iso:country":"MX",
    "wof:name":"El Puerto Lengua de Vaca",
    "wof:placetype":"locality",
    "wof:population":179
},
  "geometry": {"coordinates":[-100.18922000000001,19.44372000000001],"type":"Point"}
}