{
  "type": "Feature",
  "properties": {
    "gn:admin1_code":"10",
    "gn:admin2_code":"23.0",
    "gn:asciiname":"La Calera",
    "gn:country_code":"MX",
    "gn:dem":1085,
    "gn:feature_class":"P",
    "gn:feature_code":"PPL",
    "gn:name":"La Calera",
    "gn:population":5,
    "gn:timezone":"America/Monterrey",
    "iso:country":"MX",
    "wof:name":"La Calera",
    "wof:placetype":"locality",
    "wof:population":5
},
  "geometry": {"coordinates":[-105.69744,23.50023],"type":"Point"}
}