{
  "type": "Feature",
  "properties": {
    "gn:admin1_code":"10",
    "gn:admin2_code":"23.0",
    "gn:asciiname":"La Calera",
    "gn:country_code":"MX",
    "gn:dem":1085,
    "gn:feature_class":"P",
    "gn:feature_code":"PPL",
    "gn:name":"La Calera",
    "gn:population":5,
    "gn:timezone":"America/Monterrey",
    "iso:country":"MX",
    "name:ceb_x_preferred":[
        "La Calera"
    ],
    "name:deu_x_preferred":[
        "La Calera"
    ],
    "name:ita_x_preferred":[
        "La Calera"
    ],
    "name:nld_x_preferred":[
        "La Calera"
    ],
    "name:pol_x_preferred":[
        "La Calera"
    ],
    "name:rus_x_preferred":[
        "\u041b\u0430-\u041a\u0430\u043b\u0435\u0440\u0430"
    ],
    "name:sco_x_preferred":[
        "La Calera"
    ],
    "name:spa_x_preferred":[
        "La Calera"
    ],
    "name:swe_x_preferred":[
        "La Calera"
    ],
    "wof:name":"La Calera",
    "wof:placetype":"locality",
    "wof:population":5
},
  "geometry": {"coordinates":[-105.69744,23.50023],"type":"Point"}
}