{
  "type": "Feature",
  "properties": {
    "gn:admin1_code":"12",
    "gn:admin2_code":"67.0",
    "gn:asciiname":"Rincon del Gallo (San Jose Guadalupe)",
    "gn:country_code":"MX",
    "gn:dem":330,
    "gn:feature_class":"P",
    "gn:feature_code":"PPL",
    "gn:name":"Rinc\u00f3n del Gallo (San Jos\u00e9 Guadalupe)",
    "gn:population":606,
    "gn:timezone":"America/Mexico_City",
    "iso:country":"MX",
    "name:und_x_variant":[
        "Rinc\u00f3n del Gallo (San Jos\u00e9 Guadalupe)"
    ],
    "wof:name":"Rincon del Gallo (San Jose Guadalupe)",
    "wof:placetype":"locality",
    "wof:population":606
},
  "geometry": {"coordinates":[-100.50833,18.27389],"type":"Point"}
}