{
  "type": "Feature",
  "properties": {
    "gn:admin1_code":"6.0",
    "gn:asciiname":"Sector el Alto",
    "gn:country_code":"MX",
    "gn:dem":1304,
    "gn:feature_class":"P",
    "gn:feature_code":"PPL",
    "gn:name":"Sector el Alto",
    "gn:population":0,
    "gn:timezone":"America/Chihuahua",
    "iso:country":"MX",
    "name:spa_x_preferred":[
        "Sector el Alto"
    ],
    "wof:name":"Sector el Alto",
    "wof:placetype":"locality"
},
  "geometry": {"coordinates":[-107.97768000000001,31.05038],"type":"Point"}
}