{
  "type": "Feature",
  "properties": {
    "gn:admin1_code":"6",
    "gn:admin2_code":"27",
    "gn:asciiname":"Baquiriachi",
    "gn:country_code":"MX",
    "gn:dem":2184,
    "gn:feature_class":"P",
    "gn:feature_code":"PPL",
    "gn:name":"Baquiriachi",
    "gn:population":40,
    "gn:timezone":"America/Chihuahua",
    "iso:country":"MX",
    "wof:name":"Baquiriachi",
    "wof:placetype":"locality",
    "wof:population":40
},
  "geometry": {"coordinates":[-107.43989000000001,26.81549],"type":"Point"}
}