{
  "type": "Feature",
  "properties": {
    "gn:admin1_code":"10",
    "gn:admin2_code":"4.0",
    "gn:asciiname":"El Salvaje",
    "gn:country_code":"MX",
    "gn:dem":1957,
    "gn:feature_class":"P",
    "gn:feature_code":"PPL",
    "gn:name":"El Salvaje",
    "gn:population":0,
    "gn:timezone":"America/Monterrey",
    "iso:country":"MX",
    "name:spa_x_preferred":[
        "El Salvaje"
    ],
    "wof:name":"El Salvaje",
    "wof:placetype":"locality"
},
  "geometry": {"coordinates":[-103.77070000000001,24.6956],"type":"Point"}
}