{
  "type": "Feature",
  "properties": {
    "gn:admin1_code":"4",
    "gn:admin2_code":"4.0",
    "gn:asciiname":"San Antonio Teop",
    "gn:country_code":"MX",
    "gn:dem":22,
    "gn:feature_class":"P",
    "gn:feature_code":"PPL",
    "gn:name":"San Antonio Teop",
    "gn:population":4,
    "gn:timezone":"America/Merida",
    "iso:country":"MX",
    "wof:name":"San Antonio Teop",
    "wof:placetype":"locality",
    "wof:population":4
},
  "geometry": {"coordinates":[-90.49944000000001,19.45],"type":"Point"}
}