{
  "type": "Feature",
  "properties": {
    "gn:admin1_code":"2",
    "gn:admin2_code":"2",
    "gn:asciiname":"Los Arellano (Ejido Oaxaca)",
    "gn:country_code":"MX",
    "gn:dem":11,
    "gn:feature_class":"P",
    "gn:feature_code":"PPL",
    "gn:name":"Los Arellano (Ejido Oaxaca)",
    "gn:population":14,
    "gn:timezone":"America/Tijuana",
    "iso:country":"MX",
    "wof:name":"Los Arellano (Ejido Oaxaca)",
    "wof:placetype":"locality",
    "wof:population":14
},
  "geometry": {"coordinates":[-115.15222,32.30417],"type":"Point"}
}