{
  "type": "Feature",
  "properties": {
    "gn:admin1_code":"16.0",
    "gn:admin2_code":"92.0",
    "gn:asciiname":"San Pedro",
    "gn:country_code":"MX",
    "gn:dem":463,
    "gn:feature_class":"P",
    "gn:feature_code":"PPL",
    "gn:name":"San Pedro",
    "gn:population":125,
    "gn:timezone":"America/Mexico_City",
    "iso:country":"MX",
    "name:spa_x_preferred":[
        "San Pedro"
    ],
    "wof:name":"San Pedro",
    "wof:placetype":"locality",
    "wof:population":125
},
  "geometry": {"coordinates":[-100.80852,19.05934],"type":"Point"}
}