{
  "type": "Feature",
  "properties": {
    "gn:admin1_code":"13",
    "gn:admin2_code":"16.0",
    "gn:asciiname":"Xayahualulco",
    "gn:country_code":"MX",
    "gn:dem":2583,
    "gn:feature_class":"P",
    "gn:feature_code":"PPL",
    "gn:name":"Xayahualulco",
    "gn:population":0,
    "gn:timezone":"America/Mexico_City",
    "iso:country":"MX",
    "name:spa_x_preferred":[
        "Xayahualco"
    ],
    "wof:name":"Xayahualulco",
    "wof:placetype":"locality"
},
  "geometry": {"coordinates":[-98.19282,19.99364],"type":"Point"}
}