{
  "type": "Feature",
  "properties": {
    "gn:admin1_code":"17",
    "gn:admin2_code":"28",
    "gn:asciiname":"Palo Bolero",
    "gn:country_code":"MX",
    "gn:dem":1084,
    "gn:feature_class":"P",
    "gn:feature_code":"PPL",
    "gn:name":"Palo Bolero",
    "gn:population":37,
    "gn:timezone":"America/Mexico_City",
    "iso:country":"MX",
    "wof:name":"Palo Bolero",
    "wof:placetype":"locality",
    "wof:population":37
},
  "geometry": {"coordinates":[-99.23778,18.76778],"type":"Point"}
}