{
  "type": "Feature",
  "properties": {
    "gn:admin1_code":"30",
    "gn:admin2_code":"95.0",
    "gn:asciiname":"La Frontera",
    "gn:country_code":"MX",
    "gn:dem":801,
    "gn:feature_class":"P",
    "gn:feature_code":"PPL",
    "gn:name":"La Frontera",
    "gn:population":91,
    "gn:timezone":"America/Mexico_City",
    "iso:country":"MX",
    "wof:name":"La Frontera",
    "wof:placetype":"locality",
    "wof:population":91
},
  "geometry": {"coordinates":[-96.72583,19.79694],"type":"Point"}
}