{
  "type": "Feature",
  "properties": {
    "gn:admin1_code":"20.0",
    "gn:asciiname":"El Tanaroa",
    "gn:country_code":"MX",
    "gn:dem":207,
    "gn:feature_class":"P",
    "gn:feature_code":"PPL",
    "gn:name":"El Tanaroa",
    "gn:population":0,
    "gn:timezone":"America/Mexico_City",
    "iso:country":"MX",
    "name:spa_x_preferred":[
        "El Tanaroa"
    ],
    "wof:name":"El Tanaroa",
    "wof:placetype":"locality"
},
  "geometry": {"coordinates":[-98.09703,16.36188],"type":"Point"}
}