{
  "type": "Feature",
  "properties": {
    "gn:admin1_code":"10.0",
    "gn:admin2_code":"2.0",
    "gn:asciiname":"El Recodo",
    "gn:cc2":"MX",
    "gn:country_code":"MX",
    "gn:dem":1903,
    "gn:feature_class":"P",
    "gn:feature_code":"PPL",
    "gn:name":"El Recodo",
    "gn:population":0,
    "gn:timezone":"America/Monterrey",
    "iso:country":"MX",
    "name:und_x_variant":[
        "Recodo",
        "El Recodo"
    ],
    "wof:name":"El Recodo",
    "wof:placetype":"locality"
},
  "geometry": {"coordinates":[-106.65000000000001,24.98333],"type":"Point"}
}