{
  "type": "Feature",
  "properties": {
    "gn:admin1_code":"6.0",
    "gn:admin2_code":"9.0",
    "gn:asciiname":"Cueva Pinta",
    "gn:country_code":"MX",
    "gn:dem":2335,
    "gn:feature_class":"P",
    "gn:feature_code":"PPL",
    "gn:name":"Cueva Pinta",
    "gn:population":0,
    "gn:timezone":"America/Chihuahua",
    "iso:country":"MX",
    "name:spa_x_preferred":[
        "Cueva Pinta"
    ],
    "name:und_x_variant":[
        "Rancho Cueva Pinta"
    ],
    "wof:name":"Cueva Pinta",
    "wof:placetype":"locality",
    "wof:population":22
},
  "geometry": {"coordinates":[-107.67631,27.8349],"type":"Point"}
}