{
  "type": "Feature",
  "properties": {
    "gn:admin1_code":"10",
    "gn:admin2_code":"2.0",
    "gn:asciiname":"Tisnada",
    "gn:cc2":"MX",
    "gn:country_code":"MX",
    "gn:dem":2707,
    "gn:feature_class":"P",
    "gn:feature_code":"PPL",
    "gn:name":"Tisnada",
    "gn:population":0,
    "gn:timezone":"America/Monterrey",
    "iso:country":"MX",
    "name:und_x_variant":[
        "Rancho Tisnada",
        "Tiznada",
        "Tisnada"
    ],
    "wof:name":"Tisnada",
    "wof:placetype":"locality"
},
  "geometry": {"coordinates":[-106.41667,25.11667000000001],"type":"Point"}
}