{
  "type": "Feature",
  "properties": {
    "gn:admin1_code":"6",
    "gn:admin2_code":"8.0",
    "gn:asciiname":"Huimayvo",
    "gn:country_code":"MX",
    "gn:dem":1025,
    "gn:feature_class":"P",
    "gn:feature_code":"PPL",
    "gn:name":"Huimayvo",
    "gn:population":84,
    "gn:timezone":"America/Chihuahua",
    "iso:country":"MX",
    "name:spa_x_preferred":[
        "Huimayvo"
    ],
    "wof:name":"Huimayvo",
    "wof:placetype":"locality",
    "wof:population":84
},
  "geometry": {"coordinates":[-107.63074,27.15326],"type":"Point"}
}