{
  "type": "Feature",
  "properties": {
    "gn:admin1_code":"6",
    "gn:admin2_code":"15.0",
    "gn:asciiname":"Temporales",
    "gn:country_code":"MX",
    "gn:dem":925,
    "gn:feature_class":"P",
    "gn:feature_code":"PPL",
    "gn:name":"Temporales",
    "gn:population":0,
    "gn:timezone":"America/Chihuahua",
    "iso:country":"MX",
    "wof:name":"Temporales",
    "wof:placetype":"locality"
},
  "geometry": {"coordinates":[-104.93547,29.36053],"type":"Point"}
}