{
  "type": "Feature",
  "properties": {
    "gn:admin1_code":"32",
    "gn:admin2_code":"38.0",
    "gn:asciiname":"Saucito de Escajedo",
    "gn:country_code":"MX",
    "gn:dem":2341,
    "gn:feature_class":"P",
    "gn:feature_code":"PPL",
    "gn:name":"Saucito de Escajedo",
    "gn:population":0,
    "gn:timezone":"America/Mexico_City",
    "iso:country":"MX",
    "name:und_x_variant":[
        "Saucito de Escagedo"
    ],
    "wof:name":"Saucito de Escajedo",
    "wof:placetype":"locality"
},
  "geometry": {"coordinates":[-101.46804,22.31311],"type":"Point"}
}