{
  "type": "Feature",
  "properties": {
    "gn:admin1_code":"31.0",
    "gn:asciiname":"Pakam",
    "gn:country_code":"MX",
    "gn:dem":21,
    "gn:feature_class":"P",
    "gn:feature_code":"PPL",
    "gn:name":"Pakam",
    "gn:population":0,
    "gn:timezone":"America/Merida",
    "iso:country":"MX",
    "name:spa_x_preferred":[
        "Pakam"
    ],
    "wof:name":"Pakam",
    "wof:placetype":"locality"
},
  "geometry": {"coordinates":[-88.28289000000002,21.07817],"type":"Point"}
}