{
  "type": "Feature",
  "properties": {
    "gn:admin1_code":"18",
    "gn:admin2_code":"19.0",
    "gn:asciiname":"Palmillas",
    "gn:country_code":"MX",
    "gn:dem":1525,
    "gn:feature_class":"P",
    "gn:feature_code":"PPL",
    "gn:name":"Palmillas",
    "gn:population":89,
    "gn:timezone":"America/Mazatlan",
    "iso:country":"MX",
    "name:srp_x_preferred":[
        "\u041f\u0430\u043b\u043c\u0438\u0459\u0430\u0441"
    ],
    "wof:name":"Palmillas",
    "wof:placetype":"locality",
    "wof:population":89
},
  "geometry": {"coordinates":[-104.21465999999999,21.23052],"type":"Point"}
}