{
  "type": "Feature",
  "properties": {
    "gn:admin1_code":"14",
    "gn:admin2_code":"36.0",
    "gn:asciiname":"San Rafael (Hacienda de San Rafael)",
    "gn:country_code":"MX",
    "gn:dem":1440,
    "gn:feature_class":"P",
    "gn:feature_code":"PPL",
    "gn:name":"San Rafael (Hacienda de San Rafael)",
    "gn:population":166,
    "gn:timezone":"America/Mexico_City",
    "iso:country":"MX",
    "wof:name":"San Rafael (Hacienda de San Rafael)",
    "wof:placetype":"locality",
    "wof:population":166
},
  "geometry": {"coordinates":[-104.1793,20.74314],"type":"Point"}
}