{
  "type": "Feature",
  "properties": {
    "gn:admin1_code":"28.0",
    "gn:admin2_code":"12.0",
    "gn:asciiname":"La Arboleda",
    "gn:country_code":"MX",
    "gn:dem":38,
    "gn:feature_class":"P",
    "gn:feature_code":"PPL",
    "gn:name":"La Arboleda",
    "gn:population":0,
    "gn:timezone":"America/Monterrey",
    "iso:country":"MX",
    "name:spa_x_preferred":[
        "La Arboleda"
    ],
    "wof:name":"La Arboleda",
    "wof:placetype":"locality"
},
  "geometry": {"coordinates":[-98.48551999999999,22.64831],"type":"Point"}
}