{
  "type": "Feature",
  "properties": {
    "gn:admin1_code":"5.0",
    "gn:admin2_code":"20.0",
    "gn:asciiname":"Frontera",
    "gn:country_code":"MX",
    "gn:dem":933,
    "gn:feature_class":"P",
    "gn:feature_code":"PPL",
    "gn:name":"Frontera",
    "gn:population":0,
    "gn:timezone":"America/Mexico_City",
    "iso:country":"MX",
    "name:bre_x_preferred":[
        "Frontera"
    ],
    "name:ceb_x_preferred":[
        "Frontera"
    ],
    "name:deu_x_preferred":[
        "Frontera"
    ],
    "name:fin_x_preferred":[
        "Frontera"
    ],
    "name:fra_x_preferred":[
        "Frontera"
    ],
    "name:nld_x_preferred":[
        "Frontera"
    ],
    "name:por_x_preferred":[
        "Frontera"
    ],
    "name:rus_x_preferred":[
        "\u0424\u0440\u043e\u043d\u0442\u0435\u0440\u0430"
    ],
    "name:spa_x_preferred":[
        "Frontera"
    ],
    "name:srp_x_preferred":[
        "\u0424\u0440\u043e\u043d\u0442\u0435\u0440\u0430"
    ],
    "name:swe_x_preferred":[
        "Frontera"
    ],
    "wof:name":"Frontera",
    "wof:placetype":"locality"
},
  "geometry": {"coordinates":[-92.83879,15.7353],"type":"Point"}
}