{
  "type": "Feature",
  "properties": {
    "gn:admin1_code":"20",
    "gn:admin2_code":"418",
    "gn:asciiname":"Cerro del Marques",
    "gn:country_code":"MX",
    "gn:dem":190,
    "gn:feature_class":"P",
    "gn:feature_code":"PPL",
    "gn:name":"Cerro del Marqu\u00e9s",
    "gn:population":23,
    "gn:timezone":"America/Mexico_City",
    "iso:country":"MX",
    "name:und_x_variant":[
        "Cerro del Marqu\u00e9s"
    ],
    "wof:name":"Cerro del Marques",
    "wof:placetype":"locality",
    "wof:population":23
},
  "geometry": {"coordinates":[-95.43722,16.45028],"type":"Point"}
}