{
  "type": "Feature",
  "properties": {
    "gn:admin1_code":"6",
    "gn:admin2_code":"1",
    "gn:asciiname":"San Rafael",
    "gn:country_code":"MX",
    "gn:dem":1220,
    "gn:feature_class":"P",
    "gn:feature_code":"PPL",
    "gn:name":"San Rafael",
    "gn:population":9,
    "gn:timezone":"America/Chihuahua",
    "iso:country":"MX",
    "wof:name":"San Rafael",
    "wof:placetype":"locality",
    "wof:population":9
},
  "geometry": {"coordinates":[-106.53136000000001,30.43347],"type":"Point"}
}