{
  "type": "Feature",
  "properties": {
    "gn:admin1_code":"15.0",
    "gn:admin2_code":"66.0",
    "gn:asciiname":"San Miguel Piru",
    "gn:country_code":"MX",
    "gn:dem":1292,
    "gn:feature_class":"P",
    "gn:feature_code":"PPL",
    "gn:name":"San Miguel Pir\u00fa",
    "gn:population":0,
    "gn:timezone":"America/Mexico_City",
    "iso:country":"MX",
    "name:spa_x_preferred":[
        "San Miguel Pir\u00fa"
    ],
    "name:spa_x_variant":[
        "El Pir\u00fa"
    ],
    "wof:name":"San Miguel Piru",
    "wof:placetype":"locality"
},
  "geometry": {"coordinates":[-100.31451,19.1167],"type":"Point"}
}