{
  "type": "Feature",
  "properties": {
    "gn:admin1_code":"6",
    "gn:admin2_code":"65",
    "gn:asciiname":"Matabuchi",
    "gn:country_code":"MX",
    "gn:dem":2056,
    "gn:feature_class":"P",
    "gn:feature_code":"PPL",
    "gn:name":"Matabuchi",
    "gn:population":23,
    "gn:timezone":"America/Chihuahua",
    "iso:country":"MX",
    "wof:name":"Matabuchi",
    "wof:placetype":"locality",
    "wof:population":23
},
  "geometry": {"coordinates":[-107.9302,27.4427],"type":"Point"}
}