{
  "type": "Feature",
  "properties": {
    "gn:admin1_code":"24",
    "gn:admin2_code":"4.0",
    "gn:asciiname":"Mezquitalillo",
    "gn:country_code":"MX",
    "gn:dem":2043,
    "gn:feature_class":"P",
    "gn:feature_code":"PPL",
    "gn:name":"Mezquitalillo",
    "gn:population":179,
    "gn:timezone":"America/Mexico_City",
    "iso:country":"MX",
    "wof:name":"Mezquitalillo",
    "wof:placetype":"locality",
    "wof:population":179
},
  "geometry": {"coordinates":[-100.65806000000001,22.12944],"type":"Point"}
}