{
  "type": "Feature",
  "properties": {
    "gn:admin1_code":"16.0",
    "gn:admin2_code":"9.0",
    "gn:asciiname":"Hacienda los Ates",
    "gn:country_code":"MX",
    "gn:dem":1598,
    "gn:feature_class":"P",
    "gn:feature_code":"PPL",
    "gn:name":"Hacienda los Ates",
    "gn:population":0,
    "gn:timezone":"America/Mexico_City",
    "iso:country":"MX",
    "name:spa_x_preferred":[
        "Hacienda los Ates"
    ],
    "wof:name":"Hacienda los Ates",
    "wof:placetype":"locality"
},
  "geometry": {"coordinates":[-101.71451999999999,19.1693],"type":"Point"}
}