{
  "type": "Feature",
  "properties": {
    "gn:admin1_code":"19.0",
    "gn:admin2_code":"5.0",
    "gn:asciiname":"Veinticinco Nueve",
    "gn:country_code":"MX",
    "gn:dem":237,
    "gn:feature_class":"P",
    "gn:feature_code":"PPL",
    "gn:name":"Veinticinco Nueve",
    "gn:population":0,
    "gn:timezone":"America/Matamoros",
    "iso:country":"MX",
    "name:spa_x_preferred":[
        "Veinticinco Nueve"
    ],
    "wof:name":"Veinticinco Nueve",
    "wof:placetype":"locality"
},
  "geometry": {"coordinates":[-100.34446,27.42526],"type":"Point"}
}