{
  "type": "Feature",
  "properties": {
    "gn:admin1_code":"20",
    "gn:admin2_code":"526.0",
    "gn:asciiname":"San Martin Pie del Cerro",
    "gn:country_code":"MX",
    "gn:dem":857,
    "gn:feature_class":"P",
    "gn:feature_code":"PPL",
    "gn:name":"San Mart\u00edn Pie del Cerro",
    "gn:population":116,
    "gn:timezone":"America/Mexico_City",
    "iso:country":"MX",
    "name:und_x_variant":[
        "San Mart\u00edn Pie del Cerro"
    ],
    "wof:name":"San Martin Pie del Cerro",
    "wof:placetype":"locality",
    "wof:population":116
},
  "geometry": {"coordinates":[-97.25444,16.11333],"type":"Point"}
}