{
  "type": "Feature",
  "properties": {
    "gn:admin1_code":"6",
    "gn:admin2_code":"29",
    "gn:asciiname":"El Naranjo",
    "gn:country_code":"MX",
    "gn:dem":2651,
    "gn:feature_class":"P",
    "gn:feature_code":"PPL",
    "gn:name":"El Naranjo",
    "gn:population":17,
    "gn:timezone":"America/Chihuahua",
    "iso:country":"MX",
    "wof:name":"El Naranjo",
    "wof:placetype":"locality",
    "wof:population":17
},
  "geometry": {"coordinates":[-106.78234999999999,26.11357000000001],"type":"Point"}
}