{
  "type": "Feature",
  "properties": {
    "gn:admin1_code":"15.0",
    "gn:admin2_code":"82.0",
    "gn:asciiname":"Cuadrilla de Martinez",
    "gn:country_code":"MX",
    "gn:dem":1391,
    "gn:feature_class":"P",
    "gn:feature_code":"PPL",
    "gn:name":"Cuadrilla de Martinez",
    "gn:population":0,
    "gn:timezone":"America/Mexico_City",
    "iso:country":"MX",
    "name:spa_x_preferred":[
        "Cuadrilla de Martinez"
    ],
    "name:und_x_variant":[
        "Los Mart\u00ednez"
    ],
    "wof:name":"Cuadrilla de Martinez",
    "wof:placetype":"locality"
},
  "geometry": {"coordinates":[-100.18418,18.98461],"type":"Point"}
}