{
  "type": "Feature",
  "properties": {
    "gn:admin1_code":"20",
    "gn:admin2_code":"55",
    "gn:asciiname":"San Miguel Tiuxi",
    "gn:country_code":"MX",
    "gn:dem":1083,
    "gn:feature_class":"P",
    "gn:feature_code":"PPL",
    "gn:name":"San Miguel Tiuxi",
    "gn:population":49,
    "gn:timezone":"America/Mexico_City",
    "iso:country":"MX",
    "wof:name":"San Miguel Tiuxi",
    "wof:placetype":"locality",
    "wof:population":49
},
  "geometry": {"coordinates":[-98.1425,17.85167000000001],"type":"Point"}
}