{
  "type": "Feature",
  "properties": {
    "gn:admin1_code":"5",
    "gn:admin2_code":"114",
    "gn:asciiname":"Octavio Perez G.",
    "gn:country_code":"MX",
    "gn:dem":162,
    "gn:feature_class":"P",
    "gn:feature_code":"PPL",
    "gn:name":"Octavio P\u00e9rez G.",
    "gn:population":15,
    "gn:timezone":"America/Mexico_City",
    "iso:country":"MX",
    "name:und_x_variant":[
        "Octavio P\u00e9rez G."
    ],
    "wof:name":"Octavio Perez G.",
    "wof:placetype":"locality",
    "wof:population":15
},
  "geometry": {"coordinates":[-90.46556,16.35417],"type":"Point"}
}