{
  "type": "Feature",
  "properties": {
    "gn:admin1_code":"18",
    "gn:admin2_code":"19.0",
    "gn:asciiname":"San Juan Ixtapalapa",
    "gn:country_code":"MX",
    "gn:dem":1779,
    "gn:feature_class":"P",
    "gn:feature_code":"PPL",
    "gn:name":"San Juan Ixtapalapa",
    "gn:population":117,
    "gn:timezone":"America/Mexico_City",
    "iso:country":"MX",
    "name:spa_x_preferred":[
        "San Juan Ixtapalapa"
    ],
    "name:spa_x_variant":[
        "San Juan"
    ],
    "wof:name":"San Juan Ixtapalapa",
    "wof:placetype":"locality",
    "wof:population":117
},
  "geometry": {"coordinates":[-104.07832999999999,21.49306],"type":"Point"}
}