{
  "type": "Feature",
  "properties": {
    "gn:admin1_code":"12",
    "gn:admin2_code":"56.0",
    "gn:asciiname":"Colonia Nueva Reforma",
    "gn:country_code":"MX",
    "gn:dem":408,
    "gn:feature_class":"P",
    "gn:feature_code":"PPL",
    "gn:name":"Colonia Nueva Reforma",
    "gn:population":84,
    "gn:timezone":"America/Mexico_City",
    "iso:country":"MX",
    "wof:name":"Colonia Nueva Reforma",
    "wof:placetype":"locality",
    "wof:population":84
},
  "geometry": {"coordinates":[-99.19204999999999,17.02456],"type":"Point"}
}