{
  "type": "Feature",
  "properties": {
    "gn:admin1_code":"5",
    "gn:admin2_code":"49.0",
    "gn:asciiname":"Naxoch",
    "gn:country_code":"MX",
    "gn:dem":2026,
    "gn:feature_class":"P",
    "gn:feature_code":"PPL",
    "gn:name":"Naxoch",
    "gn:population":174,
    "gn:timezone":"America/Mexico_City",
    "iso:country":"MX",
    "wof:name":"Naxoch",
    "wof:placetype":"locality",
    "wof:population":174
},
  "geometry": {"coordinates":[-92.75611000000001,16.8875],"type":"Point"}
}