{
  "type": "Feature",
  "properties": {
    "gn:admin1_code":"11",
    "gn:admin2_code":"5",
    "gn:asciiname":"La Esperanza",
    "gn:country_code":"MX",
    "gn:dem":1783,
    "gn:feature_class":"P",
    "gn:feature_code":"PPL",
    "gn:name":"La Esperanza",
    "gn:population":13,
    "gn:timezone":"America/Mexico_City",
    "iso:country":"MX",
    "wof:name":"La Esperanza",
    "wof:placetype":"locality",
    "wof:population":13
},
  "geometry": {"coordinates":[-100.63083,20.56139],"type":"Point"}
}