{
  "type": "Feature",
  "properties": {
    "gn:admin1_code":"26",
    "gn:admin2_code":"29",
    "gn:asciiname":"El Rebombeo",
    "gn:country_code":"MX",
    "gn:dem":8,
    "gn:feature_class":"P",
    "gn:feature_code":"PPL",
    "gn:name":"El Rebombeo",
    "gn:population":12,
    "gn:timezone":"America/Hermosillo",
    "iso:country":"MX",
    "wof:name":"El Rebombeo",
    "wof:placetype":"locality",
    "wof:population":12
},
  "geometry": {"coordinates":[-110.89306000000001,27.98778],"type":"Point"}
}