{
  "type": "Feature",
  "properties": {
    "gn:admin1_code":"20",
    "gn:admin2_code":"2.0",
    "gn:asciiname":"Tembladera Vista Hermosa",
    "gn:country_code":"MX",
    "gn:dem":104,
    "gn:feature_class":"P",
    "gn:feature_code":"PPL",
    "gn:name":"Tembladera Vista Hermosa",
    "gn:population":361,
    "gn:timezone":"America/Mexico_City",
    "iso:country":"MX",
    "wof:name":"Tembladera Vista Hermosa",
    "wof:placetype":"locality",
    "wof:population":361
},
  "geometry": {"coordinates":[-96.50861,18.43028],"type":"Point"}
}