{
  "type": "Feature",
  "properties": {
    "gn:admin1_code":"14.0",
    "gn:admin2_code":"49.0",
    "gn:asciiname":"Chilatan Nuevo",
    "gn:country_code":"MX",
    "gn:dem":486,
    "gn:feature_class":"P",
    "gn:feature_code":"PPL",
    "gn:name":"Chilat\u00e1n Nuevo",
    "gn:population":0,
    "gn:timezone":"America/Mexico_City",
    "iso:country":"MX",
    "name:spa_x_preferred":[
        "Chilat\u00e1n Nuevo"
    ],
    "wof:name":"Chilatan Nuevo",
    "wof:placetype":"locality"
},
  "geometry": {"coordinates":[-102.7268,19.28964],"type":"Point"}
}