{
  "type": "Feature",
  "properties": {
    "gn:admin1_code":"5",
    "gn:admin2_code":"89.0",
    "gn:asciiname":"Las Delicias Viejas",
    "gn:country_code":"MX",
    "gn:dem":23,
    "gn:feature_class":"P",
    "gn:feature_code":"PPL",
    "gn:name":"Las Delicias Viejas",
    "gn:population":6,
    "gn:timezone":"America/Mexico_City",
    "iso:country":"MX",
    "wof:name":"Las Delicias Viejas",
    "wof:placetype":"locality",
    "wof:population":6
},
  "geometry": {"coordinates":[-92.26582999999999,14.73417],"type":"Point"}
}