{
  "type": "Feature",
  "properties": {
    "gn:admin1_code":"30.0",
    "gn:admin2_code":"33.0",
    "gn:asciiname":"Morisco Numero Uno",
    "gn:country_code":"MX",
    "gn:dem":13,
    "gn:feature_class":"P",
    "gn:feature_code":"PPL",
    "gn:name":"Morisco N\u00famero Uno",
    "gn:population":0,
    "gn:timezone":"America/Mexico_City",
    "iso:country":"MX",
    "name:spa_x_preferred":[
        "Morisco N\u00famero Uno"
    ],
    "wof:name":"Morisco Numero Uno",
    "wof:placetype":"locality"
},
  "geometry": {"coordinates":[-97.3049,20.73091],"type":"Point"}
}