{
  "type": "Feature",
  "properties": {
    "gn:admin1_code":"6",
    "gn:admin2_code":"29.0",
    "gn:asciiname":"Pie Grande",
    "gn:country_code":"MX",
    "gn:dem":1656,
    "gn:feature_class":"P",
    "gn:feature_code":"PPL",
    "gn:name":"Pie Grande",
    "gn:population":0,
    "gn:timezone":"America/Chihuahua",
    "iso:country":"MX",
    "name:spa_x_preferred":[
        "Pie Grande"
    ],
    "wof:name":"Pie Grande",
    "wof:placetype":"locality"
},
  "geometry": {"coordinates":[-107.51548,26.2165],"type":"Point"}
}