{
  "type": "Feature",
  "properties": {
    "gn:admin1_code":"32",
    "gn:admin2_code":"38.0",
    "gn:asciiname":"Pueblito de Guadalupe (El Pueblito)",
    "gn:country_code":"MX",
    "gn:dem":2163,
    "gn:feature_class":"P",
    "gn:feature_code":"PPL",
    "gn:name":"Pueblito de Guadalupe (El Pueblito)",
    "gn:population":328,
    "gn:timezone":"America/Mexico_City",
    "iso:country":"MX",
    "wof:name":"Pueblito de Guadalupe (El Pueblito)",
    "wof:placetype":"locality",
    "wof:population":328
},
  "geometry": {"coordinates":[-101.58127,22.03547],"type":"Point"}
}