{
  "type": "Feature",
  "properties": {
    "gn:admin1_code":"28.0",
    "gn:admin2_code":"37.0",
    "gn:asciiname":"Risco Amarillo",
    "gn:country_code":"MX",
    "gn:dem":256,
    "gn:feature_class":"P",
    "gn:feature_code":"PPL",
    "gn:name":"Risco Amarillo",
    "gn:population":0,
    "gn:timezone":"America/Monterrey",
    "iso:country":"MX",
    "name:spa_x_preferred":[
        "Risco Amarillo"
    ],
    "wof:name":"Risco Amarillo",
    "wof:placetype":"locality"
},
  "geometry": {"coordinates":[-98.25,23.42194],"type":"Point"}
}