{
  "type": "Feature",
  "properties": {
    "gn:admin1_code":"6.0",
    "gn:admin2_code":"39.0",
    "gn:asciiname":"Troya",
    "gn:country_code":"MX",
    "gn:dem":1454,
    "gn:feature_class":"P",
    "gn:feature_code":"PPL",
    "gn:name":"Troya",
    "gn:population":0,
    "gn:timezone":"America/Chihuahua",
    "iso:country":"MX",
    "name:ara_x_preferred":[
        "\u062a\u0631\u0648\u064a"
    ],
    "name:bel_x_preferred":[
        "\u0422\u0440\u043e\u044f"
    ],
    "name:ben_x_preferred":[
        "\u099f\u09cd\u09b0\u09af\u09bc"
    ],
    "name:ceb_x_preferred":[
        "Troya"
    ],
    "name:fas_x_preferred":[
        "\u062a\u0631\u0648\u06cc"
    ],
    "name:fra_x_preferred":[
        "Troie"
    ],
    "name:hye_x_preferred":[
        "\u054f\u0580\u0578\u0575\u0561"
    ],
    "name:mzn_x_preferred":[
        "\u062a\u0631\u0648\u0627"
    ],
    "name:rus_x_preferred":[
        "\u0422\u0440\u043e\u044f"
    ],
    "name:spa_x_preferred":[
        "Troya"
    ],
    "name:swe_x_preferred":[
        "Troya"
    ],
    "name:tur_x_preferred":[
        "Truva"
    ],
    "name:ukr_x_preferred":[
        "\u0422\u0440\u043e\u044f"
    ],
    "name:urd_x_preferred":[
        "\u0679\u0631\u0627\u0626\u06d2"
    ],
    "name:zho_x_preferred":[
        "\u7279\u6d1b\u4f0a"
    ],
    "wof:name":"Troya",
    "wof:placetype":"locality"
},
  "geometry": {"coordinates":[-105.18555000000001,27.13462],"type":"Point"}
}