{
  "type": "Feature",
  "properties": {
    "gn:admin1_code":"6.0",
    "gn:admin2_code":"39.0",
    "gn:asciiname":"Troya",
    "gn:country_code":"MX",
    "gn:dem":1454,
    "gn:feature_class":"P",
    "gn:feature_code":"PPL",
    "gn:name":"Troya",
    "gn:population":0,
    "gn:timezone":"America/Chihuahua",
    "iso:country":"MX",
    "name:spa_x_preferred":[
        "Troya"
    ],
    "wof:name":"Troya",
    "wof:placetype":"locality"
},
  "geometry": {"coordinates":[-105.18555000000001,27.13462],"type":"Point"}
}