{
  "type": "Feature",
  "properties": {
    "gn:admin1_code":"10.0",
    "gn:admin2_code":"32.0",
    "gn:asciiname":"Mimbres",
    "gn:country_code":"MX",
    "gn:dem":2331,
    "gn:feature_class":"P",
    "gn:feature_code":"PPL",
    "gn:name":"Mimbres",
    "gn:population":0,
    "gn:timezone":"America/Monterrey",
    "iso:country":"MX",
    "name:ceb_x_preferred":[
        "Mimbres"
    ],
    "name:spa_x_preferred":[
        "Mimbres"
    ],
    "name:srp_x_preferred":[
        "\u041c\u0438\u043c\u0431\u0440\u0435\u0441"
    ],
    "name:swe_x_preferred":[
        "Mimbres"
    ],
    "wof:name":"Mimbres",
    "wof:placetype":"locality"
},
  "geometry": {"coordinates":[-105.65367000000001,24.88701],"type":"Point"}
}