{
  "type": "Feature",
  "properties": {
    "gn:admin1_code":"29",
    "gn:admin2_code":"34",
    "gn:asciiname":"El Paraiso",
    "gn:country_code":"MX",
    "gn:dem":2771,
    "gn:feature_class":"P",
    "gn:feature_code":"PPL",
    "gn:name":"El Para\u00edso",
    "gn:population":34,
    "gn:timezone":"America/Mexico_City",
    "iso:country":"MX",
    "name:und_x_variant":[
        "El Para\u00edso"
    ],
    "wof:name":"El Paraiso",
    "wof:placetype":"locality",
    "wof:population":34
},
  "geometry": {"coordinates":[-98.05552,19.6112],"type":"Point"}
}