{
  "type": "Feature",
  "properties": {
    "gn:admin1_code":"5",
    "gn:admin2_code":"31",
    "gn:asciiname":"Nuevo Chiviltic",
    "gn:country_code":"MX",
    "gn:dem":1049,
    "gn:feature_class":"P",
    "gn:feature_code":"PPL",
    "gn:name":"Nuevo Chiviltic",
    "gn:population":27,
    "gn:timezone":"America/Mexico_City",
    "iso:country":"MX",
    "wof:name":"Nuevo Chiviltic",
    "wof:placetype":"locality",
    "wof:population":27
},
  "geometry": {"coordinates":[-92.24139,17.11694],"type":"Point"}
}