{
  "type": "Feature",
  "properties": {
    "gn:admin1_code":"2.0",
    "gn:admin2_code":"2.0",
    "gn:asciiname":"Estrella",
    "gn:country_code":"MX",
    "gn:dem":0,
    "gn:feature_class":"P",
    "gn:feature_code":"PPL",
    "gn:name":"Estrella",
    "gn:population":0,
    "gn:timezone":"America/Tijuana",
    "iso:country":"MX",
    "name:cat_x_preferred":[
        "Estrella"
    ],
    "name:ceb_x_preferred":[
        "Estrella"
    ],
    "name:dan_x_preferred":[
        "Estrella"
    ],
    "name:deu_x_preferred":[
        "Estrella"
    ],
    "name:fin_x_preferred":[
        "Estrella"
    ],
    "name:fra_x_preferred":[
        "Estrella"
    ],
    "name:ita_x_preferred":[
        "Estrella"
    ],
    "name:nds_x_preferred":[
        "Estrella"
    ],
    "name:nor_x_preferred":[
        "Estrella"
    ],
    "name:por_x_preferred":[
        "Estrella"
    ],
    "name:rus_x_preferred":[
        "\u042d\u0441\u0442\u0440\u0435\u043b\u044c\u044f"
    ],
    "name:spa_x_preferred":[
        "Estrella"
    ],
    "name:swe_x_preferred":[
        "Estrella"
    ],
    "wof:name":"Estrella",
    "wof:placetype":"locality"
},
  "geometry": {"coordinates":[-115.57926999999999,32.62878],"type":"Point"}
}