{
  "type": "Feature",
  "properties": {
    "gn:admin1_code":"2.0",
    "gn:admin2_code":"2.0",
    "gn:asciiname":"Estrella",
    "gn:country_code":"MX",
    "gn:dem":0,
    "gn:feature_class":"P",
    "gn:feature_code":"PPL",
    "gn:name":"Estrella",
    "gn:population":0,
    "gn:timezone":"America/Tijuana",
    "iso:country":"MX",
    "name:spa_x_preferred":[
        "Estrella"
    ],
    "wof:name":"Estrella",
    "wof:placetype":"locality"
},
  "geometry": {"coordinates":[-115.57926999999999,32.62878],"type":"Point"}
}