{
  "type": "Feature",
  "properties": {
    "gn:admin1_code":"30",
    "gn:admin2_code":"23.0",
    "gn:asciiname":"Pilares",
    "gn:country_code":"MX",
    "gn:dem":593,
    "gn:feature_class":"P",
    "gn:feature_code":"PPL",
    "gn:name":"Pilares",
    "gn:population":461,
    "gn:timezone":"America/Mexico_City",
    "iso:country":"MX",
    "name:ita_x_preferred":[
        "Pilares"
    ],
    "name:por_x_preferred":[
        "Pilares"
    ],
    "wof:name":"Pilares",
    "wof:placetype":"locality",
    "wof:population":461
},
  "geometry": {"coordinates":[-97.21583,19.92028],"type":"Point"}
}