{
  "type": "Feature",
  "properties": {
    "gn:admin1_code":"15.0",
    "gn:admin2_code":"123.0",
    "gn:asciiname":"Jalpa",
    "gn:country_code":"MX",
    "gn:dem":1136,
    "gn:feature_class":"P",
    "gn:feature_code":"PPL",
    "gn:name":"Jalpa",
    "gn:population":0,
    "gn:timezone":"America/Mexico_City",
    "iso:country":"MX",
    "name:ceb_x_preferred":[
        "Jalpa"
    ],
    "name:deu_x_preferred":[
        "Jalpa"
    ],
    "name:rus_x_preferred":[
        "\u0425\u0430\u043b\u044c\u043f\u0430"
    ],
    "name:spa_x_preferred":[
        "Jalpa"
    ],
    "name:swe_x_preferred":[
        "Jalpa"
    ],
    "name:vie_x_preferred":[
        "Jalpa"
    ],
    "wof:name":"Jalpa",
    "wof:placetype":"locality"
},
  "geometry": {"coordinates":[-100.36168000000001,19.00513],"type":"Point"}
}