{
  "type": "Feature",
  "properties": {
    "gn:admin1_code":"14",
    "gn:admin2_code":"78.0",
    "gn:asciiname":"Monte Alto",
    "gn:country_code":"MX",
    "gn:dem":2217,
    "gn:feature_class":"P",
    "gn:feature_code":"PPL",
    "gn:name":"Monte Alto",
    "gn:population":56,
    "gn:timezone":"America/Mexico_City",
    "iso:country":"MX",
    "wof:name":"Monte Alto",
    "wof:placetype":"locality",
    "wof:population":56
},
  "geometry": {"coordinates":[-102.28222,20.9125],"type":"Point"}
}