{
  "type": "Feature",
  "properties": {
    "gn:admin1_code":"6.0",
    "gn:admin2_code":"67.0",
    "gn:asciiname":"Agostadero y Anexas",
    "gn:country_code":"MX",
    "gn:dem":1439,
    "gn:feature_class":"P",
    "gn:feature_code":"PPL",
    "gn:name":"Agostadero y Anexas",
    "gn:population":0,
    "gn:timezone":"America/Chihuahua",
    "iso:country":"MX",
    "wof:name":"Agostadero y Anexas",
    "wof:placetype":"locality"
},
  "geometry": {"coordinates":[-105.91007999999999,27.51096],"type":"Point"}
}