{
  "type": "Feature",
  "properties": {
    "gn:admin1_code":"26",
    "gn:admin2_code":"12.0",
    "gn:asciiname":"Lourdes Guamuchil",
    "gn:country_code":"MX",
    "gn:dem":30,
    "gn:feature_class":"P",
    "gn:feature_code":"PPL",
    "gn:name":"Lourdes Guam\u00fachil",
    "gn:population":0,
    "gn:timezone":"America/Hermosillo",
    "iso:country":"MX",
    "name:spa_x_preferred":[
        "Lourdes Guam\u00fachil"
    ],
    "wof:name":"Lourdes Guamuchil",
    "wof:placetype":"locality"
},
  "geometry": {"coordinates":[-110.02732,27.52615],"type":"Point"}
}