{
  "type": "Feature",
  "properties": {
    "gn:admin1_code":"6",
    "gn:admin2_code":"29.0",
    "gn:asciiname":"Santa Rosalia",
    "gn:country_code":"MX",
    "gn:dem":2170,
    "gn:feature_class":"P",
    "gn:feature_code":"PPL",
    "gn:name":"Santa Rosal\u00eda",
    "gn:population":0,
    "gn:timezone":"America/Chihuahua",
    "iso:country":"MX",
    "name:spa_x_preferred":[
        "Santa Rosal\u00eda"
    ],
    "name:und_x_variant":[
        "Rosalia"
    ],
    "wof:name":"Santa Rosalia",
    "wof:placetype":"locality"
},
  "geometry": {"coordinates":[-107.04850999999999,26.21414],"type":"Point"}
}