{
  "type": "Feature",
  "properties": {
    "gn:admin1_code":"12",
    "gn:admin2_code":"47",
    "gn:asciiname":"Tecamachalco",
    "gn:country_code":"MX",
    "gn:dem":1565,
    "gn:feature_class":"P",
    "gn:feature_code":"PPL",
    "gn:name":"Tecamachalco",
    "gn:population":46,
    "gn:timezone":"America/Mexico_City",
    "iso:country":"MX",
    "name:ceb_x_preferred":[
        "Tecamachalco"
    ],
    "name:sco_x_preferred":[
        "Tecamachalco"
    ],
    "name:spa_x_preferred":[
        "Tecamachalco"
    ],
    "name:swe_x_preferred":[
        "Tecamachalco"
    ],
    "wof:name":"Tecamachalco",
    "wof:placetype":"locality",
    "wof:population":46
},
  "geometry": {"coordinates":[-99.87882,18.49769],"type":"Point"}
}