{
  "type": "Feature",
  "properties": {
    "gn:admin1_code":"28",
    "gn:admin2_code":"35",
    "gn:asciiname":"Leonel Salinas Curiel",
    "gn:country_code":"MX",
    "gn:dem":76,
    "gn:feature_class":"P",
    "gn:feature_code":"PPL",
    "gn:name":"Leonel Salinas Curiel",
    "gn:population":13,
    "gn:timezone":"America/Monterrey",
    "iso:country":"MX",
    "wof:name":"Leonel Salinas Curiel",
    "wof:placetype":"locality",
    "wof:population":13
},
  "geometry": {"coordinates":[-98.10944000000001,24.86472],"type":"Point"}
}