{
  "type": "Feature",
  "properties": {
    "gn:admin1_code":"12.0",
    "gn:admin2_code":"57.0",
    "gn:asciiname":"El Cobano",
    "gn:country_code":"MX",
    "gn:dem":20,
    "gn:feature_class":"P",
    "gn:feature_code":"PPL",
    "gn:name":"El Cobano",
    "gn:population":278,
    "gn:timezone":"America/Mexico_City",
    "iso:country":"MX",
    "wof:name":"El Cobano",
    "wof:placetype":"locality",
    "wof:population":278
},
  "geometry": {"coordinates":[-101.01381000000001,17.27855],"type":"Point"}
}