{
  "type": "Feature",
  "properties": {
    "gn:admin1_code":"20",
    "gn:admin2_code":"324.0",
    "gn:asciiname":"Santa Maria Limon",
    "gn:country_code":"MX",
    "gn:dem":193,
    "gn:feature_class":"P",
    "gn:feature_code":"PPL",
    "gn:name":"Santa Mar\u00eda Lim\u00f3n",
    "gn:population":0,
    "gn:timezone":"America/Mexico_City",
    "iso:country":"MX",
    "name:spa_x_preferred":[
        "Santa Mar\u00eda Lim\u00f3n"
    ],
    "wof:name":"Santa Maria Limon",
    "wof:placetype":"locality"
},
  "geometry": {"coordinates":[-96.36924999999999,15.80205],"type":"Point"}
}