{
  "type": "Feature",
  "properties": {
    "gn:admin1_code":"4",
    "gn:admin2_code":"2.0",
    "gn:asciiname":"San Francisco Koben",
    "gn:country_code":"MX",
    "gn:dem":6,
    "gn:feature_class":"P",
    "gn:feature_code":"PPL",
    "gn:name":"San Francisco Kob\u00e9n",
    "gn:population":0,
    "gn:timezone":"America/Merida",
    "iso:country":"MX",
    "name:spa_x_preferred":[
        "San Francisco Koben"
    ],
    "name:spa_x_variant":[
        "San Francisco Kob\u00e9n"
    ],
    "name:und_x_variant":[
        "Kob\u00e9n"
    ],
    "wof:name":"San Francisco Koben",
    "wof:placetype":"locality"
},
  "geometry": {"coordinates":[-90.41709,19.91516],"type":"Point"}
}