{
  "type": "Feature",
  "properties": {
    "gn:admin1_code":"14",
    "gn:admin2_code":"16.0",
    "gn:asciiname":"Carretas",
    "gn:country_code":"MX",
    "gn:dem":1548,
    "gn:feature_class":"P",
    "gn:feature_code":"PPL",
    "gn:name":"Carretas",
    "gn:population":127,
    "gn:timezone":"America/Mexico_City",
    "iso:country":"MX",
    "wof:name":"Carretas",
    "wof:placetype":"locality",
    "wof:population":127
},
  "geometry": {"coordinates":[-102.42417,20.44222],"type":"Point"}
}