{
  "type": "Feature",
  "properties": {
    "gn:admin1_code":"24",
    "gn:asciiname":"Tanchanaquito",
    "gn:country_code":"MX",
    "gn:dem":256,
    "gn:feature_class":"P",
    "gn:feature_code":"PPL",
    "gn:name":"Tanchanaquito",
    "gn:population":0,
    "gn:timezone":"America/Mexico_City",
    "iso:country":"MX",
    "name:und_x_variant":[
        "Tanchaguaco",
        "Tanchanaco",
        "Tanchanaquito",
        "Tanchabaquito"
    ],
    "wof:name":"Tanchanaquito",
    "wof:placetype":"locality"
},
  "geometry": {"coordinates":[-99.22020000000001,21.63766],"type":"Point"}
}