{
  "type": "Feature",
  "properties": {
    "gn:admin1_code":"16",
    "gn:admin2_code":"6.0",
    "gn:asciiname":"Porrazo",
    "gn:country_code":"MX",
    "gn:dem":234,
    "gn:feature_class":"P",
    "gn:feature_code":"PPL",
    "gn:name":"Porrazo",
    "gn:population":5,
    "gn:timezone":"America/Mexico_City",
    "iso:country":"MX",
    "wof:name":"Porrazo",
    "wof:placetype":"locality",
    "wof:population":5
},
  "geometry": {"coordinates":[-102.37917,19.00917],"type":"Point"}
}