{
  "type": "Feature",
  "properties": {
    "gn:admin1_code":"6.0",
    "gn:admin2_code":"57.0",
    "gn:asciiname":"Avendanos",
    "gn:country_code":"MX",
    "gn:dem":1606,
    "gn:feature_class":"P",
    "gn:feature_code":"PPL",
    "gn:name":"Avenda\u00f1os",
    "gn:population":0,
    "gn:timezone":"America/Chihuahua",
    "iso:country":"MX",
    "name:spa_x_preferred":[
        "Avenda\u00f1os"
    ],
    "wof:name":"Avendanos",
    "wof:placetype":"locality"
},
  "geometry": {"coordinates":[-106.56667,27.83951],"type":"Point"}
}