{
  "type": "Feature",
  "properties": {
    "gn:admin1_code":"6",
    "gn:admin2_code":"10.0",
    "gn:asciiname":"El Huerfano",
    "gn:country_code":"MX",
    "gn:dem":1378,
    "gn:feature_class":"P",
    "gn:feature_code":"PPL",
    "gn:name":"El Hu\u00e9rfano",
    "gn:population":0,
    "gn:timezone":"America/Chihuahua",
    "iso:country":"MX",
    "name:spa_x_preferred":[
        "El Hu\u00e9rfano"
    ],
    "wof:name":"El Huerfano",
    "wof:placetype":"locality"
},
  "geometry": {"coordinates":[-107.41642,30.1582],"type":"Point"}
}