{
  "type": "Feature",
  "properties": {
    "gn:admin1_code":"5",
    "gn:admin2_code":"80.0",
    "gn:asciiname":"Las Culebras",
    "gn:cc2":"MX",
    "gn:country_code":"MX",
    "gn:dem":1116,
    "gn:feature_class":"P",
    "gn:feature_code":"PPL",
    "gn:name":"Las Culebras",
    "gn:population":0,
    "gn:timezone":"America/Mexico_City",
    "iso:country":"MX",
    "name:und_x_variant":[
        "La Culebra",
        "Las Culebras"
    ],
    "wof:name":"Las Culebras",
    "wof:placetype":"locality"
},
  "geometry": {"coordinates":[-92.46666999999999,15.58333],"type":"Point"}
}