{
  "type": "Feature",
  "properties": {
    "gn:admin1_code":"30",
    "gn:admin2_code":"16.0",
    "gn:asciiname":"Playa Chalchihuecan",
    "gn:country_code":"MX",
    "gn:dem":9,
    "gn:feature_class":"P",
    "gn:feature_code":"PPL",
    "gn:name":"Playa Chalchihuecan",
    "gn:population":5,
    "gn:timezone":"America/Mexico_City",
    "iso:country":"MX",
    "wof:name":"Playa Chalchihuecan",
    "wof:placetype":"locality",
    "wof:population":5
},
  "geometry": {"coordinates":[-96.30833,19.34417],"type":"Point"}
}