{
  "type": "Feature",
  "properties": {
    "gn:admin1_code":"10",
    "gn:admin2_code":"21.0",
    "gn:asciiname":"Tortuguillas",
    "gn:country_code":"MX",
    "gn:dem":1957,
    "gn:feature_class":"P",
    "gn:feature_code":"PPL",
    "gn:name":"Tortuguillas",
    "gn:population":0,
    "gn:timezone":"America/Monterrey",
    "iso:country":"MX",
    "name:spa_x_preferred":[
        "Tortuguillas"
    ],
    "wof:name":"Tortuguillas",
    "wof:placetype":"locality"
},
  "geometry": {"coordinates":[-103.99176,24.60188],"type":"Point"}
}