{
  "type": "Feature",
  "properties": {
    "gn:admin1_code":"10",
    "gn:admin2_code":"14",
    "gn:asciiname":"Cerro Viejo",
    "gn:country_code":"MX",
    "gn:dem":2458,
    "gn:feature_class":"P",
    "gn:feature_code":"PPL",
    "gn:name":"Cerro Viejo",
    "gn:population":12,
    "gn:timezone":"America/Monterrey",
    "iso:country":"MX",
    "name:ara_x_preferred":[
        "\u0633\u064a\u0631\u0648 \u0641\u064a\u062c\u0648"
    ],
    "name:ben_x_preferred":[
        "\u09b8\u09c7\u09b0\u09b0\u09cb \u09ad\u09bf\u09df\u09c7\u099c\u09cb"
    ],
    "name:deu_x_preferred":[
        "Cerro Viejo"
    ],
    "name:ell_x_preferred":[
        "\u03a3\u03ad\u03c1\u03c1\u03bf \u0392\u03b9\u03ad\u03c7\u03bf"
    ],
    "name:fas_x_preferred":[
        "\u0633\u0631\u0648 \u0648\u06cc\u062c\u0648"
    ],
    "name:fra_x_preferred":[
        "Cerro Viejo"
    ],
    "name:heb_x_preferred":[
        "\u05d4\u05e8 \u05d5\u05d9\u05d9\u05d7\u05d5"
    ],
    "name:hin_x_preferred":[
        "\u0938\u0947\u0930\u094b \u0935\u0940\u091c\u094b"
    ],
    "name:hun_x_preferred":[
        "Cerro Viejo"
    ],
    "name:ind_x_preferred":[
        "Cerro Viejo"
    ],
    "name:ita_x_preferred":[
        "Cerro Viejo"
    ],
    "name:jpn_x_preferred":[
        "\u30bb\u30ed\u30fb\u30d3\u30a8\u30db\u5c71"
    ],
    "name:kor_x_preferred":[
        "\uc138\ub85c \ube44\uc5d0\ud638"
    ],
    "name:nld_x_preferred":[
        "Cerro Viejo"
    ],
    "name:pol_x_preferred":[
        "Cerro Viejo"
    ],
    "name:por_x_preferred":[
        "Cerro Viejo"
    ],
    "name:rus_x_preferred":[
        "\u0421\u0435\u0440\u0440\u043e-\u0412\u044c\u0435\u0445\u043e"
    ],
    "name:spa_x_preferred":[
        "Cerro Viejo"
    ],
    "name:tur_x_preferred":[
        "Cerro Viejo"
    ],
    "name:ukr_x_preferred":[
        "\u0421\u0435\u0440\u0440\u043e-\u0412\u0456\u0454\u0445\u043e"
    ],
    "name:urd_x_preferred":[
        "\u06a9\u06cc\u0631\u0648 \u0648\u06cc\u062c\u0648"
    ],
    "name:vie_x_preferred":[
        "N\u00fai Viejo"
    ],
    "name:zho_cn_x_preferred":[
        "\u522b\u970d\u5c71"
    ],
    "name:zho_tw_x_preferred":[
        "\u7dad\u8036\u970d\u5c71"
    ],
    "name:zho_x_preferred":[
        "\u585e\u7f85\u5225\u970d"
    ],
    "wof:name":"Cerro Viejo",
    "wof:placetype":"locality",
    "wof:population":12
},
  "geometry": {"coordinates":[-104.53357,22.79559],"type":"Point"}
}