{
  "type": "Feature",
  "properties": {
    "gn:admin1_code":"10",
    "gn:admin2_code":"14",
    "gn:asciiname":"Cerro Viejo",
    "gn:country_code":"MX",
    "gn:dem":2458,
    "gn:feature_class":"P",
    "gn:feature_code":"PPL",
    "gn:name":"Cerro Viejo",
    "gn:population":12,
    "gn:timezone":"America/Monterrey",
    "iso:country":"MX",
    "wof:name":"Cerro Viejo",
    "wof:placetype":"locality",
    "wof:population":12
},
  "geometry": {"coordinates":[-104.53357,22.79559],"type":"Point"}
}