{
  "type": "Feature",
  "properties": {
    "gn:admin1_code":"16.0",
    "gn:admin2_code":"6.0",
    "gn:asciiname":"Acahuato",
    "gn:country_code":"MX",
    "gn:dem":1015,
    "gn:feature_class":"P",
    "gn:feature_code":"PPL",
    "gn:name":"Acahuato",
    "gn:population":0,
    "gn:timezone":"America/Mexico_City",
    "iso:country":"MX",
    "name:spa_x_preferred":[
        "Acahuato"
    ],
    "wof:name":"Acahuato",
    "wof:placetype":"locality"
},
  "geometry": {"coordinates":[-102.32962999999999,19.15067],"type":"Point"}
}