{
  "type": "Feature",
  "properties": {
    "gn:admin1_code":"14",
    "gn:admin2_code":"14.0",
    "gn:asciiname":"Los Puentes",
    "gn:country_code":"MX",
    "gn:dem":1350,
    "gn:feature_class":"P",
    "gn:feature_code":"PPL",
    "gn:name":"Los Puentes",
    "gn:population":5,
    "gn:timezone":"America/Mexico_City",
    "iso:country":"MX",
    "wof:name":"Los Puentes",
    "wof:placetype":"locality",
    "wof:population":5
},
  "geometry": {"coordinates":[-103.52361000000001,19.94944],"type":"Point"}
}