{
  "type": "Feature",
  "properties": {
    "gn:admin1_code":"12",
    "gn:admin2_code":"66.0",
    "gn:asciiname":"San Pedro Petlacala",
    "gn:country_code":"MX",
    "gn:dem":1343,
    "gn:feature_class":"P",
    "gn:feature_code":"PPL",
    "gn:name":"San Pedro Petlacala",
    "gn:population":0,
    "gn:timezone":"America/Mexico_City",
    "iso:country":"MX",
    "name:spa_x_preferred":[
        "San Pedro Petlacala"
    ],
    "name:und_x_variant":[
        "San Pedro Petatl\u00e1n",
        "San Pedro Petal\u00e1n"
    ],
    "wof:name":"San Pedro Petlacala",
    "wof:placetype":"locality"
},
  "geometry": {"coordinates":[-98.67529,17.58214],"type":"Point"}
}