{
  "type": "Feature",
  "properties": {
    "gn:admin1_code":"20",
    "gn:admin2_code":"482.0",
    "gn:asciiname":"El Frio",
    "gn:country_code":"MX",
    "gn:dem":12,
    "gn:feature_class":"P",
    "gn:feature_code":"PPL",
    "gn:name":"El Fr\u00edo",
    "gn:population":7,
    "gn:timezone":"America/Mexico_City",
    "iso:country":"MX",
    "name:und_x_variant":[
        "El Fr\u00edo"
    ],
    "wof:name":"El Frio",
    "wof:placetype":"locality",
    "wof:population":7
},
  "geometry": {"coordinates":[-98.17306000000001,16.25333],"type":"Point"}
}