{
  "type": "Feature",
  "properties": {
    "gn:admin1_code":"25.0",
    "gn:admin2_code":"11.0",
    "gn:asciiname":"Guamuchil",
    "gn:country_code":"MX",
    "gn:dem":-2,
    "gn:feature_class":"P",
    "gn:feature_code":"PPL",
    "gn:name":"Guam\u00fachil",
    "gn:population":0,
    "gn:timezone":"America/Mazatlan",
    "iso:country":"MX",
    "wof:name":"Guamuchil",
    "wof:placetype":"locality"
},
  "geometry": {"coordinates":[-108.36667,25.36667000000001],"type":"Point"}
}