{
  "type": "Feature",
  "properties": {
    "gn:admin1_code":"25",
    "gn:admin2_code":"17",
    "gn:asciiname":"El Papalote",
    "gn:country_code":"MX",
    "gn:dem":204,
    "gn:feature_class":"P",
    "gn:feature_code":"PPL",
    "gn:name":"El Papalote",
    "gn:population":13,
    "gn:timezone":"America/Mazatlan",
    "iso:country":"MX",
    "wof:name":"El Papalote",
    "wof:placetype":"locality",
    "wof:population":13
},
  "geometry": {"coordinates":[-108.29879,26.21584],"type":"Point"}
}