{
  "type": "Feature",
  "properties": {
    "gn:admin1_code":"20",
    "gn:admin2_code":"215.0",
    "gn:asciiname":"San Andres Andua",
    "gn:country_code":"MX",
    "gn:dem":2116,
    "gn:feature_class":"P",
    "gn:feature_code":"PPL",
    "gn:name":"San Andr\u00e9s And\u00faa",
    "gn:population":0,
    "gn:timezone":"America/Mexico_City",
    "iso:country":"MX",
    "name:spa_x_preferred":[
        "San Andr\u00e9s And\u00faa"
    ],
    "name:spa_x_variant":[
        "Andua"
    ],
    "wof:name":"San Andres Andua",
    "wof:placetype":"locality"
},
  "geometry": {"coordinates":[-97.31588000000001,17.43953],"type":"Point"}
}