{
  "type": "Feature",
  "properties": {
    "gn:admin1_code":"17",
    "gn:admin2_code":"9",
    "gn:asciiname":"Zacapexco",
    "gn:country_code":"MX",
    "gn:dem":2790,
    "gn:feature_class":"P",
    "gn:feature_code":"PPL",
    "gn:name":"Zacapexco",
    "gn:population":30,
    "gn:timezone":"America/Mexico_City",
    "iso:country":"MX",
    "wof:name":"Zacapexco",
    "wof:placetype":"locality",
    "wof:population":30
},
  "geometry": {"coordinates":[-99.2525,19.04611],"type":"Point"}
}