{
  "type": "Feature",
  "properties": {
    "gn:admin1_code":"12.0",
    "gn:admin2_code":"48.0",
    "gn:asciiname":"El Espinalillo",
    "gn:country_code":"MX",
    "gn:dem":157,
    "gn:feature_class":"P",
    "gn:feature_code":"PPL",
    "gn:name":"El Espinalillo",
    "gn:population":0,
    "gn:timezone":"America/Mexico_City",
    "iso:country":"MX",
    "name:spa_x_preferred":[
        "El Espinalillo"
    ],
    "wof:name":"El Espinalillo",
    "wof:placetype":"locality"
},
  "geometry": {"coordinates":[-101.30616999999999,17.71395],"type":"Point"}
}