{
  "type": "Feature",
  "properties": {
    "gn:admin1_code":"24",
    "gn:admin2_code":"3.0",
    "gn:asciiname":"La Reforma",
    "gn:country_code":"MX",
    "gn:dem":819,
    "gn:feature_class":"P",
    "gn:feature_code":"PPL",
    "gn:name":"La Reforma",
    "gn:population":246,
    "gn:timezone":"America/Mexico_City",
    "iso:country":"MX",
    "name:cym_x_preferred":[
        "La Reforma"
    ],
    "name:nld_x_preferred":[
        "Reforma"
    ],
    "name:por_x_preferred":[
        "La Reforma"
    ],
    "wof:name":"La Reforma",
    "wof:placetype":"locality",
    "wof:population":246
},
  "geometry": {"coordinates":[-99.15028,21.64111],"type":"Point"}
}