{
  "type": "Feature",
  "properties": {
    "gn:admin1_code":"10",
    "gn:admin2_code":"34.0",
    "gn:asciiname":"El Platanar",
    "gn:country_code":"MX",
    "gn:dem":559,
    "gn:feature_class":"P",
    "gn:feature_code":"PPL",
    "gn:name":"El Platanar",
    "gn:population":8,
    "gn:timezone":"America/Monterrey",
    "iso:country":"MX",
    "wof:name":"El Platanar",
    "wof:placetype":"locality",
    "wof:population":8
},
  "geometry": {"coordinates":[-106.23145,24.59193],"type":"Point"}
}