{
  "type": "Feature",
  "properties": {
    "gn:admin1_code":"8",
    "gn:admin2_code":"7.0",
    "gn:asciiname":"Venustiano Carranza",
    "gn:country_code":"MX",
    "gn:dem":17,
    "gn:feature_class":"P",
    "gn:feature_code":"PPL",
    "gn:name":"Venustiano Carranza",
    "gn:population":0,
    "gn:timezone":"America/Mexico_City",
    "iso:country":"MX",
    "name:spa_x_preferred":[
        "Venustiano Carranza"
    ],
    "name:spa_x_variant":[
        "Cualata"
    ],
    "wof:name":"Venustiano Carranza",
    "wof:placetype":"locality"
},
  "geometry": {"coordinates":[-104.11033,19.01112],"type":"Point"}
}