{
  "type": "Feature",
  "properties": {
    "gn:admin1_code":"5",
    "gn:admin2_code":"78.0",
    "gn:asciiname":"El Pinar",
    "gn:country_code":"MX",
    "gn:dem":2427,
    "gn:feature_class":"P",
    "gn:feature_code":"PPL",
    "gn:name":"El Pinar",
    "gn:population":0,
    "gn:timezone":"America/Mexico_City",
    "iso:country":"MX",
    "name:cat_x_preferred":[
        "El Pinar"
    ],
    "name:ceb_x_preferred":[
        "El Pinar"
    ],
    "name:deu_x_preferred":[
        "El Pinar"
    ],
    "name:epo_x_preferred":[
        "El Pinar"
    ],
    "name:fra_x_preferred":[
        "El Pinar"
    ],
    "name:hun_x_preferred":[
        "El Pinar"
    ],
    "name:hye_x_preferred":[
        "\u0537\u056c \u054a\u056b\u0576\u0561\u0580"
    ],
    "name:nld_x_preferred":[
        "El Pinar"
    ],
    "name:nor_x_preferred":[
        "El Pinar"
    ],
    "name:spa_x_preferred":[
        "El Pinar"
    ],
    "name:spa_x_variant":[
        "Pinal"
    ],
    "name:srp_x_preferred":[
        "\u0415\u043b \u041f\u0438\u043d\u0430\u0440"
    ],
    "name:swe_x_preferred":[
        "El Pinar"
    ],
    "wof:name":"El Pinar",
    "wof:placetype":"locality"
},
  "geometry": {"coordinates":[-92.60565,16.75845],"type":"Point"}
}