{
  "type": "Feature",
  "properties": {
    "gn:admin1_code":"21.0",
    "gn:admin2_code":"3.0",
    "gn:asciiname":"El Banquito",
    "gn:country_code":"MX",
    "gn:dem":1149,
    "gn:feature_class":"P",
    "gn:feature_code":"PPL",
    "gn:name":"El Banquito",
    "gn:population":0,
    "gn:timezone":"America/Mexico_City",
    "iso:country":"MX",
    "name:spa_x_preferred":[
        "El Banquito"
    ],
    "wof:name":"El Banquito",
    "wof:placetype":"locality"
},
  "geometry": {"coordinates":[-98.07464,18.1648],"type":"Point"}
}