{
  "type": "Feature",
  "properties": {
    "gn:admin1_code":"5",
    "gn:admin2_code":"59",
    "gn:asciiname":"Santa Margarita Tres",
    "gn:country_code":"MX",
    "gn:dem":587,
    "gn:feature_class":"P",
    "gn:feature_code":"PPL",
    "gn:name":"Santa Margarita Tres",
    "gn:population":29,
    "gn:timezone":"America/Mexico_City",
    "iso:country":"MX",
    "wof:name":"Santa Margarita Tres",
    "wof:placetype":"locality",
    "wof:population":29
},
  "geometry": {"coordinates":[-91.72694,16.91417],"type":"Point"}
}