{
  "type": "Feature",
  "properties": {
    "gn:admin1_code":"5",
    "gn:admin2_code":"59.0",
    "gn:asciiname":"Ach Lumal",
    "gn:country_code":"MX",
    "gn:dem":797,
    "gn:feature_class":"P",
    "gn:feature_code":"PPL",
    "gn:name":"Ach Lumal",
    "gn:population":119,
    "gn:timezone":"America/Mexico_City",
    "iso:country":"MX",
    "wof:name":"Ach Lumal",
    "wof:placetype":"locality",
    "wof:population":119
},
  "geometry": {"coordinates":[-91.83139,16.85778],"type":"Point"}
}