{
  "type": "Feature",
  "properties": {
    "gn:admin1_code":"15",
    "gn:admin2_code":"106.0",
    "gn:asciiname":"San Isidro Ejido de Calixtlahuaca",
    "gn:country_code":"MX",
    "gn:dem":2631,
    "gn:feature_class":"P",
    "gn:feature_code":"PPL",
    "gn:name":"San Isidro Ejido de Calixtlahuaca",
    "gn:population":360,
    "gn:timezone":"America/Mexico_City",
    "iso:country":"MX",
    "wof:name":"San Isidro Ejido de Calixtlahuaca",
    "wof:placetype":"locality",
    "wof:population":360
},
  "geometry": {"coordinates":[-99.72889000000001,19.375],"type":"Point"}
}