{
  "type": "Feature",
  "properties": {
    "gn:admin1_code":"28",
    "gn:admin2_code":"23.0",
    "gn:asciiname":"Rancho Santa Maria",
    "gn:country_code":"MX",
    "gn:dem":241,
    "gn:feature_class":"P",
    "gn:feature_code":"PPL",
    "gn:name":"Rancho Santa Maria",
    "gn:population":0,
    "gn:timezone":"America/Monterrey",
    "iso:country":"MX",
    "wof:name":"Rancho Santa Maria",
    "wof:placetype":"locality"
},
  "geometry": {"coordinates":[-98.46259999999999,25.25424],"type":"Point"}
}