{
  "type": "Feature",
  "properties": {
    "gn:admin1_code":"27.0",
    "gn:admin2_code":"13.0",
    "gn:asciiname":"Congregacion Chicozapote",
    "gn:country_code":"MX",
    "gn:dem":6,
    "gn:feature_class":"P",
    "gn:feature_code":"PPL",
    "gn:name":"Congregaci\u00f3n Chicozapote",
    "gn:population":0,
    "gn:timezone":"America/Mexico_City",
    "iso:country":"MX",
    "name:spa_x_preferred":[
        "Congregaci\u00f3n Chicozapote"
    ],
    "wof:name":"Congregacion Chicozapote",
    "wof:placetype":"locality"
},
  "geometry": {"coordinates":[-92.905,18.22959],"type":"Point"}
}