{
  "type": "Feature",
  "properties": {
    "gn:admin1_code":"30",
    "gn:admin2_code":"163.0",
    "gn:asciiname":"Tetlepanquetzalt",
    "gn:country_code":"MX",
    "gn:dem":682,
    "gn:feature_class":"P",
    "gn:feature_code":"PPL",
    "gn:name":"Tetlepanquetzalt",
    "gn:population":106,
    "gn:timezone":"America/Mexico_City",
    "iso:country":"MX",
    "wof:name":"Tetlepanquetzalt",
    "wof:placetype":"locality",
    "wof:population":106
},
  "geometry": {"coordinates":[-96.94028,19.88],"type":"Point"}
}