{
  "type": "Feature",
  "properties": {
    "gn:admin1_code":"14.0",
    "gn:admin2_code":"85.0",
    "gn:asciiname":"Los Tepetates",
    "gn:country_code":"MX",
    "gn:dem":1966,
    "gn:feature_class":"P",
    "gn:feature_code":"PPL",
    "gn:name":"Los Tepetates",
    "gn:population":0,
    "gn:timezone":"America/Mexico_City",
    "iso:country":"MX",
    "name:spa_x_preferred":[
        "Los Tepetates"
    ],
    "wof:name":"Los Tepetates",
    "wof:placetype":"locality"
},
  "geometry": {"coordinates":[-103.03346999999999,19.6246],"type":"Point"}
}