{
  "type": "Feature",
  "properties": {
    "gn:admin1_code":"6.0",
    "gn:admin2_code":"27.0",
    "gn:asciiname":"Orachi",
    "gn:country_code":"MX",
    "gn:dem":2115,
    "gn:feature_class":"P",
    "gn:feature_code":"PPL",
    "gn:name":"Orachi",
    "gn:population":0,
    "gn:timezone":"America/Chihuahua",
    "iso:country":"MX",
    "name:spa_x_preferred":[
        "Orachi"
    ],
    "wof:name":"Orachi",
    "wof:placetype":"locality"
},
  "geometry": {"coordinates":[-107.47745,26.83374],"type":"Point"}
}