{
  "type": "Feature",
  "properties": {
    "gn:admin1_code":"6",
    "gn:admin2_code":"66",
    "gn:asciiname":"Las Tinajas",
    "gn:country_code":"MX",
    "gn:dem":1882,
    "gn:feature_class":"P",
    "gn:feature_code":"PPL",
    "gn:name":"Las Tinajas",
    "gn:population":17,
    "gn:timezone":"America/Chihuahua",
    "iso:country":"MX",
    "wof:name":"Las Tinajas",
    "wof:placetype":"locality",
    "wof:population":17
},
  "geometry": {"coordinates":[-108.31189000000001,27.96907],"type":"Point"}
}