{
  "type": "Feature",
  "properties": {
    "gn:admin1_code":"24",
    "gn:admin2_code":"3.0",
    "gn:asciiname":"Los Canelos",
    "gn:country_code":"MX",
    "gn:dem":795,
    "gn:feature_class":"P",
    "gn:feature_code":"PPL",
    "gn:name":"Los Canelos",
    "gn:population":53,
    "gn:timezone":"America/Mexico_City",
    "iso:country":"MX",
    "name:ita_x_preferred":[
        "Los Canelos"
    ],
    "name:spa_x_preferred":[
        "Los Canelos"
    ],
    "name:zho_x_preferred":[
        "\u6d1b\u65af\u5361\u6d85\u6d1b\u65af"
    ],
    "wof:name":"Los Canelos",
    "wof:placetype":"locality",
    "wof:population":53
},
  "geometry": {"coordinates":[-99.13694,21.64083],"type":"Point"}
}