{
  "type": "Feature",
  "properties": {
    "gn:admin1_code":"5",
    "gn:admin2_code":"9.0",
    "gn:asciiname":"Ana M. Garcia R.",
    "gn:country_code":"MX",
    "gn:dem":7,
    "gn:feature_class":"P",
    "gn:feature_code":"PPL",
    "gn:name":"Ana M. Garc\u00eda R.",
    "gn:population":6,
    "gn:timezone":"America/Mexico_City",
    "iso:country":"MX",
    "name:und_x_variant":[
        "Ana M. Garc\u00eda R."
    ],
    "wof:name":"Ana M. Garcia R.",
    "wof:placetype":"locality",
    "wof:population":6
},
  "geometry": {"coordinates":[-94.07361,16.17361],"type":"Point"}
}