{
  "type": "Feature",
  "properties": {
    "gn:admin1_code":"6",
    "gn:admin2_code":"23.0",
    "gn:asciiname":"La Curva",
    "gn:country_code":"MX",
    "gn:dem":1410,
    "gn:feature_class":"P",
    "gn:feature_code":"PPL",
    "gn:name":"La Curva",
    "gn:population":0,
    "gn:timezone":"America/Chihuahua",
    "iso:country":"MX",
    "name:spa_x_preferred":[
        "La Curva"
    ],
    "wof:name":"La Curva",
    "wof:placetype":"locality"
},
  "geometry": {"coordinates":[-107.61995,30.17846],"type":"Point"}
}