{
  "type": "Feature",
  "properties": {
    "gn:admin1_code":"25.0",
    "gn:admin2_code":"11.0",
    "gn:asciiname":"La Brecha",
    "gn:country_code":"MX",
    "gn:dem":7,
    "gn:feature_class":"P",
    "gn:feature_code":"PPL",
    "gn:name":"La Brecha",
    "gn:population":2085,
    "gn:timezone":"America/Mazatlan",
    "iso:country":"MX",
    "name:spa_x_preferred":[
        "La Brecha"
    ],
    "name:srp_x_preferred":[
        "\u041b\u0430 \u0411\u0440\u0435\u0447\u0430"
    ],
    "name:und_x_variant":[
        "Brecha"
    ],
    "wof:name":"La Brecha",
    "wof:placetype":"locality",
    "wof:population":2085
},
  "geometry": {"coordinates":[-108.41922,25.37078],"type":"Point"}
}