{
  "type": "Feature",
  "properties": {
    "gn:admin1_code":"10.0",
    "gn:admin2_code":"14.0",
    "gn:asciiname":"Nopalera",
    "gn:country_code":"MX",
    "gn:dem":812,
    "gn:feature_class":"P",
    "gn:feature_code":"PPL",
    "gn:name":"Nopalera",
    "gn:population":0,
    "gn:timezone":"America/Monterrey",
    "iso:country":"MX",
    "name:spa_x_preferred":[
        "Nopalera"
    ],
    "wof:name":"Nopalera",
    "wof:placetype":"locality"
},
  "geometry": {"coordinates":[-104.53462,22.47018],"type":"Point"}
}