{
  "type": "Feature",
  "properties": {
    "gn:admin1_code":"26",
    "gn:admin2_code":"42.0",
    "gn:asciiname":"Los Arvizu (Campo Arvizu)",
    "gn:country_code":"MX",
    "gn:dem":25,
    "gn:feature_class":"P",
    "gn:feature_code":"PPL",
    "gn:name":"Los Arvizu (Campo Arvizu)",
    "gn:population":7,
    "gn:timezone":"America/Hermosillo",
    "iso:country":"MX",
    "wof:name":"Los Arvizu (Campo Arvizu)",
    "wof:placetype":"locality",
    "wof:population":7
},
  "geometry": {"coordinates":[-109.52028,27.04444],"type":"Point"}
}