{
  "type": "Feature",
  "properties": {
    "gn:admin1_code":"14",
    "gn:admin2_code":"17.0",
    "gn:asciiname":"Santa Monica (Ruiz Cortinez)",
    "gn:country_code":"MX",
    "gn:dem":1938,
    "gn:feature_class":"P",
    "gn:feature_code":"PPL",
    "gn:name":"Santa M\u00f3nica (Ruiz Cortinez)",
    "gn:population":104,
    "gn:timezone":"America/Mexico_City",
    "iso:country":"MX",
    "name:und_x_variant":[
        "Santa M\u00f3nica (Ruiz Cortinez)"
    ],
    "wof:name":"Santa Monica (Ruiz Cortinez)",
    "wof:placetype":"locality",
    "wof:population":104
},
  "geometry": {"coordinates":[-104.51944,19.92611],"type":"Point"}
}