{
  "type": "Feature",
  "properties": {
    "gn:admin1_code":"32",
    "gn:admin2_code":"1",
    "gn:asciiname":"El Mezquite",
    "gn:country_code":"MX",
    "gn:dem":1471,
    "gn:feature_class":"P",
    "gn:feature_code":"PPL",
    "gn:name":"El Mezquite",
    "gn:population":14,
    "gn:timezone":"America/Mexico_City",
    "iso:country":"MX",
    "wof:name":"El Mezquite",
    "wof:placetype":"locality",
    "wof:population":14
},
  "geometry": {"coordinates":[-103.01806000000001,21.46639],"type":"Point"}
}