{
  "type": "Feature",
  "properties": {
    "gn:admin1_code":"6",
    "gn:admin2_code":"66.0",
    "gn:asciiname":"Chagayvo",
    "gn:country_code":"MX",
    "gn:dem":1306,
    "gn:feature_class":"P",
    "gn:feature_code":"PPL",
    "gn:name":"Chagayvo",
    "gn:population":76,
    "gn:timezone":"America/Chihuahua",
    "iso:country":"MX",
    "name:spa_x_preferred":[
        "Chagayvo"
    ],
    "wof:name":"Chagayvo",
    "wof:placetype":"locality",
    "wof:population":76
},
  "geometry": {"coordinates":[-108.61939,27.87991],"type":"Point"}
}