{
  "type": "Feature",
  "properties": {
    "gn:admin1_code":"14",
    "gn:admin2_code":"78",
    "gn:asciiname":"Santo Domingo (La Comba)",
    "gn:country_code":"MX",
    "gn:dem":1878,
    "gn:feature_class":"P",
    "gn:feature_code":"PPL",
    "gn:name":"Santo Domingo (La Comba)",
    "gn:population":13,
    "gn:timezone":"America/Mexico_City",
    "iso:country":"MX",
    "wof:name":"Santo Domingo (La Comba)",
    "wof:placetype":"locality",
    "wof:population":13
},
  "geometry": {"coordinates":[-102.45999999999999,21.01917000000001],"type":"Point"}
}