{
  "type": "Feature",
  "properties": {
    "gn:admin1_code":"14",
    "gn:admin2_code":"8.0",
    "gn:asciiname":"El Saucillo",
    "gn:country_code":"MX",
    "gn:dem":2169,
    "gn:feature_class":"P",
    "gn:feature_code":"PPL",
    "gn:name":"El Saucillo",
    "gn:population":77,
    "gn:timezone":"America/Mexico_City",
    "iso:country":"MX",
    "wof:name":"El Saucillo",
    "wof:placetype":"locality",
    "wof:population":77
},
  "geometry": {"coordinates":[-102.35333,20.75778],"type":"Point"}
}