{
  "type": "Feature",
  "properties": {
    "gn:admin1_code":"20",
    "gn:admin2_code":"377.0",
    "gn:asciiname":"El Zapote",
    "gn:country_code":"MX",
    "gn:dem":1216,
    "gn:feature_class":"P",
    "gn:feature_code":"PPL",
    "gn:name":"El Zapote",
    "gn:population":62,
    "gn:timezone":"America/Mexico_City",
    "iso:country":"MX",
    "wof:name":"El Zapote",
    "wof:placetype":"locality",
    "wof:population":62
},
  "geometry": {"coordinates":[-97.56778,16.72444],"type":"Point"}
}