{
  "type": "Feature",
  "properties": {
    "gn:admin1_code":"14",
    "gn:admin2_code":"124",
    "gn:asciiname":"Partidas",
    "gn:country_code":"MX",
    "gn:dem":1730,
    "gn:feature_class":"P",
    "gn:feature_code":"PPL",
    "gn:name":"Partidas",
    "gn:population":40,
    "gn:timezone":"America/Mexico_City",
    "iso:country":"MX",
    "wof:name":"Partidas",
    "wof:placetype":"locality",
    "wof:population":40
},
  "geometry": {"coordinates":[-102.98778,20.62222],"type":"Point"}
}