{
  "type": "Feature",
  "properties": {
    "gn:admin1_code":"6",
    "gn:admin2_code":"20.0",
    "gn:asciiname":"Las Palomas",
    "gn:country_code":"MX",
    "gn:dem":1278,
    "gn:feature_class":"P",
    "gn:feature_code":"PPL",
    "gn:name":"Las Palomas",
    "gn:population":10,
    "gn:timezone":"America/Chihuahua",
    "iso:country":"MX",
    "name:spa_x_preferred":[
        "Las Palomas"
    ],
    "wof:name":"Las Palomas",
    "wof:placetype":"locality",
    "wof:population":10
},
  "geometry": {"coordinates":[-108.65105,27.5563],"type":"Point"}
}