{
  "type": "Feature",
  "properties": {
    "gn:admin1_code":"30",
    "gn:admin2_code":"108.0",
    "gn:asciiname":"Nueva Reforma",
    "gn:country_code":"MX",
    "gn:dem":15,
    "gn:feature_class":"P",
    "gn:feature_code":"PPL",
    "gn:name":"Nueva Reforma",
    "gn:population":254,
    "gn:timezone":"America/Mexico_City",
    "iso:country":"MX",
    "wof:name":"Nueva Reforma",
    "wof:placetype":"locality",
    "wof:population":254
},
  "geometry": {"coordinates":[-94.41694,17.77194],"type":"Point"}
}