{
  "type": "Feature",
  "properties": {
    "gn:admin1_code":"20",
    "gn:admin2_code":"560.0",
    "gn:asciiname":"Santa Catarina Albarradas",
    "gn:country_code":"MX",
    "gn:dem":1913,
    "gn:feature_class":"P",
    "gn:feature_code":"PPL",
    "gn:name":"Santa Catarina Albarradas",
    "gn:population":0,
    "gn:timezone":"America/Mexico_City",
    "iso:country":"MX",
    "name:spa_x_preferred":[
        "Santa Catarina Albarradas"
    ],
    "wof:name":"Santa Catarina Albarradas",
    "wof:placetype":"locality"
},
  "geometry": {"coordinates":[-96.27110999999999,17.07667],"type":"Point"}
}