{
  "type": "Feature",
  "properties": {
    "gn:admin1_code":"20",
    "gn:admin2_code":"339.0",
    "gn:asciiname":"Yucumesa",
    "gn:country_code":"MX",
    "gn:dem":2268,
    "gn:feature_class":"P",
    "gn:feature_code":"PPL",
    "gn:name":"Yucumesa",
    "gn:population":0,
    "gn:timezone":"America/Mexico_City",
    "iso:country":"MX",
    "name:spa_x_preferred":[
        "Yucumesa"
    ],
    "name:spa_x_variant":[
        "Yucamesa"
    ],
    "wof:name":"Yucumesa",
    "wof:placetype":"locality"
},
  "geometry": {"coordinates":[-97.44689,17.50275],"type":"Point"}
}