{
  "type": "Feature",
  "properties": {
    "gn:admin1_code":"2",
    "gn:admin2_code":"3.0",
    "gn:asciiname":"Oro Blanco",
    "gn:country_code":"MX",
    "gn:dem":1370,
    "gn:feature_class":"P",
    "gn:feature_code":"PPL",
    "gn:name":"Oro Blanco",
    "gn:population":0,
    "gn:timezone":"America/Tijuana",
    "iso:country":"MX",
    "name:spa_x_preferred":[
        "Oro Blanco"
    ],
    "wof:name":"Oro Blanco",
    "wof:placetype":"locality"
},
  "geometry": {"coordinates":[-116.05132,32.36494],"type":"Point"}
}