{
  "type": "Feature",
  "properties": {
    "gn:admin1_code":"16",
    "gn:admin2_code":"82.0",
    "gn:asciiname":"Joyas Bajas",
    "gn:country_code":"MX",
    "gn:dem":1441,
    "gn:feature_class":"P",
    "gn:feature_code":"PPL",
    "gn:name":"Joyas Bajas",
    "gn:population":0,
    "gn:timezone":"America/Mexico_City",
    "iso:country":"MX",
    "name:spa_x_preferred":[
        "Joyas Bajas"
    ],
    "wof:name":"Joyas Bajas",
    "wof:placetype":"locality"
},
  "geometry": {"coordinates":[-101.43237000000001,19.20602],"type":"Point"}
}