{
  "type": "Feature",
  "properties": {
    "gn:admin1_code":"16.0",
    "gn:admin2_code":"6.0",
    "gn:asciiname":"Chila",
    "gn:country_code":"MX",
    "gn:dem":472,
    "gn:feature_class":"P",
    "gn:feature_code":"PPL",
    "gn:name":"Chila",
    "gn:population":0,
    "gn:timezone":"America/Mexico_City",
    "iso:country":"MX",
    "name:ceb_x_preferred":[
        "Chila"
    ],
    "name:deu_x_preferred":[
        "Chila"
    ],
    "name:spa_x_preferred":[
        "Chila"
    ],
    "name:swe_x_preferred":[
        "Chila"
    ],
    "name:vie_x_preferred":[
        "Chila"
    ],
    "wof:name":"Chila",
    "wof:placetype":"locality"
},
  "geometry": {"coordinates":[-102.46666999999999,18.91667],"type":"Point"}
}