{
  "type": "Feature",
  "properties": {
    "gn:admin1_code":"15",
    "gn:admin2_code":"50",
    "gn:asciiname":"El Tititlal",
    "gn:country_code":"MX",
    "gn:dem":2498,
    "gn:feature_class":"P",
    "gn:feature_code":"PPL",
    "gn:name":"El Tititlal",
    "gn:population":44,
    "gn:timezone":"America/Mexico_City",
    "iso:country":"MX",
    "wof:name":"El Tititlal",
    "wof:placetype":"locality",
    "wof:population":44
},
  "geometry": {"coordinates":[-98.85508,19.07901],"type":"Point"}
}