{
  "type": "Feature",
  "properties": {
    "gn:admin1_code":"14",
    "gn:admin2_code":"80.0",
    "gn:asciiname":"El Naranjito",
    "gn:country_code":"MX",
    "gn:dem":821,
    "gn:feature_class":"P",
    "gn:feature_code":"PPL",
    "gn:name":"El Naranjito",
    "gn:population":9,
    "gn:timezone":"America/Mexico_City",
    "iso:country":"MX",
    "wof:name":"El Naranjito",
    "wof:placetype":"locality",
    "wof:population":9
},
  "geometry": {"coordinates":[-104.79277999999999,20.85583],"type":"Point"}
}