{
  "type": "Feature",
  "properties": {
    "gn:admin1_code":"28",
    "gn:admin2_code":"3.0",
    "gn:asciiname":"Punta Gorda",
    "gn:country_code":"MX",
    "gn:dem":7,
    "gn:feature_class":"P",
    "gn:feature_code":"PPL",
    "gn:name":"Punta Gorda",
    "gn:population":7,
    "gn:timezone":"America/Monterrey",
    "iso:country":"MX",
    "wof:name":"Punta Gorda",
    "wof:placetype":"locality",
    "wof:population":7
},
  "geometry": {"coordinates":[-98.17389,22.49083],"type":"Point"}
}