{
  "type": "Feature",
  "properties": {
    "gn:admin1_code":"28",
    "gn:admin2_code":"3.0",
    "gn:asciiname":"Punta Gorda",
    "gn:country_code":"MX",
    "gn:dem":7,
    "gn:feature_class":"P",
    "gn:feature_code":"PPL",
    "gn:name":"Punta Gorda",
    "gn:population":7,
    "gn:timezone":"America/Monterrey",
    "iso:country":"MX",
    "name:ast_x_preferred":[
        "Punta Gorda"
    ],
    "name:ceb_x_preferred":[
        "Punta Gorda"
    ],
    "name:deu_x_preferred":[
        "Punta Gorda"
    ],
    "name:fra_x_preferred":[
        "Punta Gorda"
    ],
    "name:ita_x_preferred":[
        "Punta Gorda"
    ],
    "name:nds_x_preferred":[
        "Punta Gorda"
    ],
    "name:nld_x_preferred":[
        "Punta Gorda"
    ],
    "name:pol_x_preferred":[
        "Punta Gorda"
    ],
    "name:por_x_preferred":[
        "Punta Gorda"
    ],
    "name:rus_x_preferred":[
        "\u041f\u0443\u043d\u0442\u0430-\u0413\u043e\u0440\u0434\u0430"
    ],
    "name:sco_x_preferred":[
        "Punta Gorda"
    ],
    "name:spa_x_preferred":[
        "Punta Gorda"
    ],
    "name:srp_x_preferred":[
        "\u041f\u0443\u043d\u0442\u0430 \u0413\u043e\u0440\u0434\u0430"
    ],
    "name:swe_x_preferred":[
        "Punta Gorda"
    ],
    "wof:name":"Punta Gorda",
    "wof:placetype":"locality",
    "wof:population":7
},
  "geometry": {"coordinates":[-98.17389,22.49083],"type":"Point"}
}