{
  "type": "Feature",
  "properties": {
    "gn:admin1_code":"25",
    "gn:admin2_code":"1.0",
    "gn:asciiname":"Campo Gastelum",
    "gn:country_code":"MX",
    "gn:dem":15,
    "gn:feature_class":"P",
    "gn:feature_code":"PPL",
    "gn:name":"Campo Gast\u00e9lum",
    "gn:population":402,
    "gn:timezone":"America/Mazatlan",
    "iso:country":"MX",
    "name:und_x_variant":[
        "Campo Gast\u00e9lum"
    ],
    "wof:name":"Campo Gastelum",
    "wof:placetype":"locality",
    "wof:population":402
},
  "geometry": {"coordinates":[-109.17556,25.94528],"type":"Point"}
}