{
  "type": "Feature",
  "properties": {
    "gn:admin1_code":"5.0",
    "gn:asciiname":"Santa Isabel la Cienega",
    "gn:country_code":"MX",
    "gn:dem":633,
    "gn:feature_class":"P",
    "gn:feature_code":"PPL",
    "gn:name":"Santa Isabel la Ci\u00e9nega",
    "gn:population":0,
    "gn:timezone":"America/Mexico_City",
    "iso:country":"MX",
    "name:spa_x_preferred":[
        "Santa Isabel la Ci\u00e9nega"
    ],
    "wof:name":"Santa Isabel la Cienega",
    "wof:placetype":"locality"
},
  "geometry": {"coordinates":[-92.94109,16.44008],"type":"Point"}
}