{
  "type": "Feature",
  "properties": {
    "gn:admin1_code":"30",
    "gn:admin2_code":"77.0",
    "gn:asciiname":"San Agustin de Guerrero",
    "gn:country_code":"MX",
    "gn:dem":24,
    "gn:feature_class":"P",
    "gn:feature_code":"PPL",
    "gn:name":"San Agust\u00edn de Guerrero",
    "gn:population":0,
    "gn:timezone":"America/Mexico_City",
    "iso:country":"MX",
    "name:spa_x_preferred":[
        "San Agust\u00edn de Guerrero"
    ],
    "name:und_x_variant":[
        "Guerrero"
    ],
    "wof:name":"San Agustin de Guerrero",
    "wof:placetype":"locality"
},
  "geometry": {"coordinates":[-95.58413,18.11135],"type":"Point"}
}