{
  "type": "Feature",
  "properties": {
    "gn:admin1_code":"28",
    "gn:admin2_code":"40",
    "gn:asciiname":"18 de Marzo (Brecha 118 con Kilometro 89)",
    "gn:country_code":"MX",
    "gn:dem":16,
    "gn:feature_class":"P",
    "gn:feature_code":"PPL",
    "gn:name":"18 de Marzo (Brecha 118 con Kil\u00f3metro 89)",
    "gn:population":18,
    "gn:timezone":"America/Monterrey",
    "iso:country":"MX",
    "name:und_x_variant":[
        "18 de Marzo (Brecha 118 con Kil\u00f3metro 89)"
    ],
    "wof:name":"18 de Marzo (Brecha 118 con Kilometro 89)",
    "wof:placetype":"locality",
    "wof:population":18
},
  "geometry": {"coordinates":[-97.83638999999999,25.60028],"type":"Point"}
}