{
  "type": "Feature",
  "properties": {
    "gn:admin1_code":"19",
    "gn:admin2_code":"31.0",
    "gn:asciiname":"La Paz (Camino a la Paz)",
    "gn:country_code":"MX",
    "gn:dem":418,
    "gn:feature_class":"P",
    "gn:feature_code":"PPL",
    "gn:name":"La Paz (Camino a la Paz)",
    "gn:population":8,
    "gn:timezone":"America/Monterrey",
    "iso:country":"MX",
    "wof:name":"La Paz (Camino a la Paz)",
    "wof:placetype":"locality",
    "wof:population":8
},
  "geometry": {"coordinates":[-100.12,25.63083],"type":"Point"}
}