{
  "type": "Feature",
  "properties": {
    "gn:admin1_code":"5",
    "gn:admin2_code":"46.0",
    "gn:asciiname":"El Nuevo Porvenir",
    "gn:country_code":"MX",
    "gn:dem":578,
    "gn:feature_class":"P",
    "gn:feature_code":"PPL",
    "gn:name":"El Nuevo Porvenir",
    "gn:population":8,
    "gn:timezone":"America/Mexico_City",
    "iso:country":"MX",
    "wof:name":"El Nuevo Porvenir",
    "wof:placetype":"locality",
    "wof:population":8
},
  "geometry": {"coordinates":[-93.55333,16.63332999999999],"type":"Point"}
}