{
  "type": "Feature",
  "properties": {
    "gn:admin1_code":"30",
    "gn:admin2_code":"11.0",
    "gn:asciiname":"Chocotan",
    "gn:country_code":"MX",
    "gn:dem":8,
    "gn:feature_class":"P",
    "gn:feature_code":"PPL",
    "gn:name":"Chocot\u00e1n",
    "gn:population":171,
    "gn:timezone":"America/Mexico_City",
    "iso:country":"MX",
    "name:und_x_variant":[
        "Chacat\u00e1n",
        "Chocot\u00e1n"
    ],
    "wof:name":"Chocotan",
    "wof:placetype":"locality",
    "wof:population":171
},
  "geometry": {"coordinates":[-95.71635999999999,18.74112],"type":"Point"}
}