{
  "type": "Feature",
  "properties": {
    "gn:admin1_code":"26.0",
    "gn:admin2_code":"35.0",
    "gn:asciiname":"Los Mercedes",
    "gn:country_code":"MX",
    "gn:dem":865,
    "gn:feature_class":"P",
    "gn:feature_code":"PPL",
    "gn:name":"Los Mercedes",
    "gn:population":0,
    "gn:timezone":"America/Hermosillo",
    "iso:country":"MX",
    "name:spa_x_preferred":[
        "Los Mercedes"
    ],
    "wof:name":"Los Mercedes",
    "wof:placetype":"locality"
},
  "geometry": {"coordinates":[-110.84122000000001,30.79918],"type":"Point"}
}