{
  "type": "Feature",
  "properties": {
    "gn:admin1_code":"6",
    "gn:admin2_code":"52.0",
    "gn:asciiname":"Punta de Agua",
    "gn:country_code":"MX",
    "gn:dem":1434,
    "gn:feature_class":"P",
    "gn:feature_code":"PPL",
    "gn:name":"Punta de Agua",
    "gn:population":0,
    "gn:timezone":"America/Chihuahua",
    "iso:country":"MX",
    "name:spa_x_preferred":[
        "Punta de Agua"
    ],
    "name:und_x_variant":[
        "Rancho Punta de Agua"
    ],
    "wof:name":"Punta de Agua",
    "wof:placetype":"locality"
},
  "geometry": {"coordinates":[-104.28793,28.6871],"type":"Point"}
}