{
  "type": "Feature",
  "properties": {
    "gn:admin1_code":"24",
    "gn:admin2_code":"46.0",
    "gn:asciiname":"Masisilau",
    "gn:country_code":"MX",
    "gn:dem":2206,
    "gn:feature_class":"P",
    "gn:feature_code":"PPL",
    "gn:name":"Masisilau",
    "gn:population":0,
    "gn:timezone":"America/Mexico_City",
    "iso:country":"MX",
    "name:spa_x_preferred":[
        "San Francisco"
    ],
    "wof:name":"Masisilau",
    "wof:placetype":"locality"
},
  "geometry": {"coordinates":[-101.15855000000001,21.99839],"type":"Point"}
}