{
  "type": "Feature",
  "properties": {
    "gn:admin1_code":"31",
    "gn:admin2_code":"96.0",
    "gn:asciiname":"San Anis",
    "gn:country_code":"MX",
    "gn:dem":12,
    "gn:feature_class":"P",
    "gn:feature_code":"PPL",
    "gn:name":"San An\u00eds",
    "gn:population":0,
    "gn:timezone":"America/Merida",
    "iso:country":"MX",
    "name:spa_x_preferred":[
        "San An\u00eds"
    ],
    "wof:name":"San Anis",
    "wof:placetype":"locality"
},
  "geometry": {"coordinates":[-88.07744,21.3715],"type":"Point"}
}