{
  "type": "Feature",
  "properties": {
    "gn:admin1_code":"28.0",
    "gn:admin2_code":"15.0",
    "gn:asciiname":"El Picacho",
    "gn:country_code":"MX",
    "gn:dem":40,
    "gn:feature_class":"P",
    "gn:feature_code":"PPL",
    "gn:name":"El Picacho",
    "gn:population":0,
    "gn:timezone":"America/Monterrey",
    "iso:country":"MX",
    "name:ceb_x_preferred":[
        "El Picacho"
    ],
    "name:spa_x_preferred":[
        "El Picacho"
    ],
    "name:swe_x_preferred":[
        "El Picacho"
    ],
    "wof:name":"El Picacho",
    "wof:placetype":"locality"
},
  "geometry": {"coordinates":[-98.55472,26.23017],"type":"Point"}
}