{
  "type": "Feature",
  "properties": {
    "gn:admin1_code":"14.0",
    "gn:asciiname":"El Cuastecomate",
    "gn:country_code":"MX",
    "gn:dem":1551,
    "gn:feature_class":"P",
    "gn:feature_code":"PPL",
    "gn:name":"El Cuastecomate",
    "gn:population":0,
    "gn:timezone":"America/Mexico_City",
    "iso:country":"MX",
    "name:spa_x_preferred":[
        "El Cuastecomate"
    ],
    "wof:name":"El Cuastecomate",
    "wof:placetype":"locality"
},
  "geometry": {"coordinates":[-103.88932,21.31811],"type":"Point"}
}