{
  "type": "Feature",
  "properties": {
    "gn:admin1_code":"24",
    "gn:admin2_code":"12.0",
    "gn:asciiname":"Chapalamel",
    "gn:country_code":"MX",
    "gn:dem":362,
    "gn:feature_class":"P",
    "gn:feature_code":"PPL",
    "gn:name":"Chapalamel",
    "gn:population":132,
    "gn:timezone":"America/Mexico_City",
    "iso:country":"MX",
    "wof:name":"Chapalamel",
    "wof:placetype":"locality",
    "wof:population":132
},
  "geometry": {"coordinates":[-98.91388999999999,21.56278],"type":"Point"}
}