{
  "type": "Feature",
  "properties": {
    "gn:admin1_code":"5",
    "gn:admin2_code":"46.0",
    "gn:asciiname":"El Clarin",
    "gn:country_code":"MX",
    "gn:dem":569,
    "gn:feature_class":"P",
    "gn:feature_code":"PPL",
    "gn:name":"El Clar\u00edn",
    "gn:population":4,
    "gn:timezone":"America/Mexico_City",
    "iso:country":"MX",
    "name:und_x_variant":[
        "El Clar\u00edn"
    ],
    "wof:name":"El Clarin",
    "wof:placetype":"locality",
    "wof:population":4
},
  "geometry": {"coordinates":[-93.63249999999999,16.69139],"type":"Point"}
}