{
  "type": "Feature",
  "properties": {
    "gn:admin1_code":"2",
    "gn:admin2_code":"1",
    "gn:asciiname":"Rancho Primer Mandamiento",
    "gn:country_code":"MX",
    "gn:dem":292,
    "gn:feature_class":"P",
    "gn:feature_code":"PPL",
    "gn:name":"Rancho Primer Mandamiento",
    "gn:population":9,
    "gn:timezone":"America/Tijuana",
    "iso:country":"MX",
    "wof:name":"Rancho Primer Mandamiento",
    "wof:placetype":"locality",
    "wof:population":9
},
  "geometry": {"coordinates":[-116.52083,31.90361],"type":"Point"}
}