{
  "type": "Feature",
  "properties": {
    "gn:admin1_code":"15",
    "gn:admin2_code":"105.0",
    "gn:asciiname":"La Guacamaya",
    "gn:country_code":"MX",
    "gn:dem":1303,
    "gn:feature_class":"P",
    "gn:feature_code":"PPL",
    "gn:name":"La Guacamaya",
    "gn:population":100,
    "gn:timezone":"America/Mexico_City",
    "iso:country":"MX",
    "wof:name":"La Guacamaya",
    "wof:placetype":"locality",
    "wof:population":100
},
  "geometry": {"coordinates":[-100.11830999999999,18.62786],"type":"Point"}
}