{
  "type": "Feature",
  "properties": {
    "gn:admin1_code":"16.0",
    "gn:admin2_code":"19.0",
    "gn:asciiname":"Los Cajones",
    "gn:country_code":"MX",
    "gn:dem":1627,
    "gn:feature_class":"P",
    "gn:feature_code":"PPL",
    "gn:name":"Los Cajones",
    "gn:population":0,
    "gn:timezone":"America/Mexico_City",
    "iso:country":"MX",
    "name:ceb_x_preferred":[
        "Los Cajones"
    ],
    "name:spa_x_preferred":[
        "Los Cajones"
    ],
    "wof:name":"Los Cajones",
    "wof:placetype":"locality"
},
  "geometry": {"coordinates":[-102.60644000000001,19.74795],"type":"Point"}
}