{
  "type": "Feature",
  "properties": {
    "gn:admin1_code":"24.0",
    "gn:admin2_code":"50.0",
    "gn:asciiname":"Zugarramuroi",
    "gn:country_code":"MX",
    "gn:dem":1831,
    "gn:feature_class":"P",
    "gn:feature_code":"PPL",
    "gn:name":"Zugarramuroi",
    "gn:population":0,
    "gn:timezone":"America/Mexico_City",
    "iso:country":"MX",
    "name:spa_x_preferred":[
        "Zugarramuroi"
    ],
    "wof:name":"Zugarramuroi",
    "wof:placetype":"locality"
},
  "geometry": {"coordinates":[-100.99003,21.75543],"type":"Point"}
}