{
  "type": "Feature",
  "properties": {
    "gn:admin1_code":"11",
    "gn:admin2_code":"20.0",
    "gn:asciiname":"San Jose de Malpaso",
    "gn:country_code":"MX",
    "gn:dem":1972,
    "gn:feature_class":"P",
    "gn:feature_code":"PPL",
    "gn:name":"San Jos\u00e9 de Malpaso",
    "gn:population":0,
    "gn:timezone":"America/Mexico_City",
    "iso:country":"MX",
    "name:und_x_variant":[
        "San Jos\u00e9",
        "San Jos\u00e9 de Malpaso"
    ],
    "wof:name":"San Jose de Malpaso",
    "wof:placetype":"locality"
},
  "geometry": {"coordinates":[-101.78676,21.14486],"type":"Point"}
}