{
  "type": "Feature",
  "properties": {
    "gn:admin1_code":"24",
    "gn:admin2_code":"37.0",
    "gn:asciiname":"Mecatlan",
    "gn:country_code":"MX",
    "gn:dem":164,
    "gn:feature_class":"P",
    "gn:feature_code":"PPL",
    "gn:name":"Mecatl\u00e1n",
    "gn:population":0,
    "gn:timezone":"America/Mexico_City",
    "iso:country":"MX",
    "name:spa_x_preferred":[
        "Mecatl\u00e1n"
    ],
    "wof:name":"Mecatlan",
    "wof:placetype":"locality"
},
  "geometry": {"coordinates":[-98.79294,21.21942],"type":"Point"}
}