{
  "type": "Feature",
  "properties": {
    "gn:admin1_code":"6",
    "gn:admin2_code":"40.0",
    "gn:asciiname":"Las Truchas",
    "gn:country_code":"MX",
    "gn:dem":2092,
    "gn:feature_class":"P",
    "gn:feature_code":"PPL",
    "gn:name":"Las Truchas",
    "gn:population":0,
    "gn:timezone":"America/Chihuahua",
    "iso:country":"MX",
    "name:spa_x_preferred":[
        "Las Truchas"
    ],
    "wof:name":"Las Truchas",
    "wof:placetype":"locality"
},
  "geometry": {"coordinates":[-108.51568,29.92011],"type":"Point"}
}