{
  "type": "Feature",
  "properties": {
    "gn:admin1_code":"14",
    "gn:admin2_code":"59.0",
    "gn:asciiname":"El Llano de los Toros",
    "gn:country_code":"MX",
    "gn:dem":2139,
    "gn:feature_class":"P",
    "gn:feature_code":"PPL",
    "gn:name":"El Llano de los Toros",
    "gn:population":419,
    "gn:timezone":"America/Mexico_City",
    "iso:country":"MX",
    "wof:name":"El Llano de los Toros",
    "wof:placetype":"locality",
    "wof:population":419
},
  "geometry": {"coordinates":[-103.00944,19.935],"type":"Point"}
}