{
  "type": "Feature",
  "properties": {
    "gn:admin1_code":"5",
    "gn:admin2_code":"65",
    "gn:asciiname":"La Nueva Fortuna",
    "gn:country_code":"MX",
    "gn:dem":129,
    "gn:feature_class":"P",
    "gn:feature_code":"PPL",
    "gn:name":"La Nueva Fortuna",
    "gn:population":21,
    "gn:timezone":"America/Mexico_City",
    "iso:country":"MX",
    "wof:name":"La Nueva Fortuna",
    "wof:placetype":"locality",
    "wof:population":21
},
  "geometry": {"coordinates":[-91.81889,17.44417],"type":"Point"}
}