{
  "type": "Feature",
  "properties": {
    "gn:admin1_code":"14.0",
    "gn:admin2_code":"91.0",
    "gn:asciiname":"La Congoja",
    "gn:country_code":"MX",
    "gn:dem":1894,
    "gn:feature_class":"P",
    "gn:feature_code":"PPL",
    "gn:name":"La Congoja",
    "gn:population":0,
    "gn:timezone":"America/Mexico_City",
    "iso:country":"MX",
    "name:spa_x_preferred":[
        "La Congoja"
    ],
    "wof:name":"La Congoja",
    "wof:placetype":"locality"
},
  "geometry": {"coordinates":[-102.63057000000001,21.57939],"type":"Point"}
}