{
  "type": "Feature",
  "properties": {
    "gn:admin1_code":"5",
    "gn:admin2_code":"2.0",
    "gn:asciiname":"Las Casitas",
    "gn:country_code":"MX",
    "gn:dem":488,
    "gn:feature_class":"P",
    "gn:feature_code":"PPL",
    "gn:name":"Las Casitas",
    "gn:population":8,
    "gn:timezone":"America/Mexico_City",
    "iso:country":"MX",
    "wof:name":"Las Casitas",
    "wof:placetype":"locality",
    "wof:population":8
},
  "geometry": {"coordinates":[-92.81,16.49444],"type":"Point"}
}