{
  "type": "Feature",
  "properties": {
    "gn:admin1_code":"14",
    "gn:admin2_code":"122.0",
    "gn:asciiname":"El Huacal",
    "gn:country_code":"MX",
    "gn:dem":1235,
    "gn:feature_class":"P",
    "gn:feature_code":"PPL",
    "gn:name":"El Huacal",
    "gn:population":8,
    "gn:timezone":"America/Mexico_City",
    "iso:country":"MX",
    "wof:name":"El Huacal",
    "wof:placetype":"locality",
    "wof:population":8
},
  "geometry": {"coordinates":[-103.76167,19.47444],"type":"Point"}
}