{
  "type": "Feature",
  "properties": {
    "gn:admin1_code":"6",
    "gn:admin2_code":"65.0",
    "gn:asciiname":"Guagueybo",
    "gn:country_code":"MX",
    "gn:dem":1664,
    "gn:feature_class":"P",
    "gn:feature_code":"PPL",
    "gn:name":"Guagueybo",
    "gn:population":0,
    "gn:timezone":"America/Chihuahua",
    "iso:country":"MX",
    "name:spa_x_preferred":[
        "Guagueybo"
    ],
    "name:und_x_variant":[
        "Rancho Guetoybo"
    ],
    "wof:name":"Guagueybo",
    "wof:placetype":"locality"
},
  "geometry": {"coordinates":[-108.03319999999999,27.33109],"type":"Point"}
}