{
  "type": "Feature",
  "properties": {
    "gn:admin1_code":"13",
    "gn:admin2_code":"18.0",
    "gn:asciiname":"Puerto del Caballo",
    "gn:country_code":"MX",
    "gn:dem":1032,
    "gn:feature_class":"P",
    "gn:feature_code":"PPL",
    "gn:name":"Puerto del Caballo",
    "gn:population":0,
    "gn:timezone":"America/Mexico_City",
    "iso:country":"MX",
    "name:spa_x_preferred":[
        "Puerto Caballo"
    ],
    "name:spa_x_variant":[
        "Puerto del Caballo"
    ],
    "wof:name":"Puerto del Caballo",
    "wof:placetype":"locality"
},
  "geometry": {"coordinates":[-98.92355999999999,21.17278],"type":"Point"}
}