{
  "type": "Feature",
  "properties": {
    "gn:admin1_code":"19.0",
    "gn:admin2_code":"51.0",
    "gn:asciiname":"Once de Mayo (Rancho Escondido)",
    "gn:country_code":"MX",
    "gn:dem":489,
    "gn:feature_class":"P",
    "gn:feature_code":"PPL",
    "gn:name":"Once de Mayo (Rancho Escondido)",
    "gn:population":2,
    "gn:timezone":"America/Monterrey",
    "iso:country":"MX",
    "name:spa_x_preferred":[
        "Rancho Escondido"
    ],
    "wof:name":"Once de Mayo (Rancho Escondido)",
    "wof:placetype":"locality",
    "wof:population":2
},
  "geometry": {"coordinates":[-100.39232,26.408],"type":"Point"}
}