{
  "type": "Feature",
  "properties": {
    "gn:admin1_code":"13",
    "gn:asciiname":"Los Sosa",
    "gn:country_code":"MX",
    "gn:dem":2252,
    "gn:feature_class":"P",
    "gn:feature_code":"PPL",
    "gn:name":"Los Sosa",
    "gn:population":0,
    "gn:timezone":"America/Mexico_City",
    "iso:country":"MX",
    "name:spa_x_preferred":[
        "Los Sosa"
    ],
    "wof:name":"Los Sosa",
    "wof:placetype":"locality"
},
  "geometry": {"coordinates":[-98.96389000000001,19.75],"type":"Point"}
}