{
  "type": "Feature",
  "properties": {
    "gn:admin1_code":"15.0",
    "gn:asciiname":"El Progreso",
    "gn:country_code":"MX",
    "gn:dem":2252,
    "gn:feature_class":"P",
    "gn:feature_code":"PPL",
    "gn:name":"El Progreso",
    "gn:population":0,
    "gn:timezone":"America/Mexico_City",
    "iso:country":"MX",
    "name:spa_x_preferred":[
        "El Progreso"
    ],
    "wof:name":"El Progreso",
    "wof:placetype":"locality"
},
  "geometry": {"coordinates":[-101.4956,19.96848],"type":"Point"}
}