{
  "type": "Feature",
  "properties": {
    "gn:admin1_code":"13",
    "gn:admin2_code":"57.0",
    "gn:asciiname":"El Liston",
    "gn:country_code":"MX",
    "gn:dem":2766,
    "gn:feature_class":"P",
    "gn:feature_code":"PPL",
    "gn:name":"El List\u00f3n",
    "gn:population":0,
    "gn:timezone":"America/Mexico_City",
    "iso:country":"MX",
    "name:spa_x_preferred":[
        "El List\u00f3n"
    ],
    "wof:name":"El Liston",
    "wof:placetype":"locality"
},
  "geometry": {"coordinates":[-98.50660000000001,19.9337],"type":"Point"}
}