{
  "type": "Feature",
  "properties": {
    "gn:admin1_code":"20.0",
    "gn:admin2_code":"170.0",
    "gn:asciiname":"Portillo el Cuatle",
    "gn:country_code":"MX",
    "gn:dem":1548,
    "gn:feature_class":"P",
    "gn:feature_code":"PPL",
    "gn:name":"Portillo el Cuatle",
    "gn:population":0,
    "gn:timezone":"America/Mexico_City",
    "iso:country":"MX",
    "name:spa_x_preferred":[
        "Portillo el Cuatle"
    ],
    "wof:name":"Portillo el Cuatle",
    "wof:placetype":"locality"
},
  "geometry": {"coordinates":[-96.33204000000001,16.43397],"type":"Point"}
}