{
  "type": "Feature",
  "properties": {
    "gn:country":"MX",
    "gn:fcode":"PPL",
    "gn:population":0,
    "iso:country":"MX",
    "name:ceb_x_preferred":[
        "Santa Anita"
    ],
    "name:deu_x_preferred":[
        "Santa Anita"
    ],
    "name:spa_x_preferred":[
        "Santa Ana"
    ],
    "name:spa_x_variant":[
        "Santa Anita"
    ],
    "name:srp_x_preferred":[
        "\u0421\u0430\u043d\u0442\u0430 \u0410\u043d\u0438\u0442\u0430"
    ],
    "name:swe_x_preferred":[
        "Santa Anita"
    ],
    "qs_pg:aaroncc":"MX",
    "qs_pg:gn_country":"MX",
    "qs_pg:gn_fcode":"PPL",
    "qs_pg:gn_pop":0,
    "qs_pg:name":"Santa Anita",
    "qs_pg:name_adm0":"M\u00e9xico",
    "qs_pg:name_adm1":"Oaxaca",
    "qs_pg:photos":1,
    "qs_pg:photos_1k":1,
    "qs_pg:photos_9k":1,
    "qs_pg:photos_9r":1,
    "qs_pg:photos_all":1,
    "qs_pg:photos_sr":1,
    "qs_pg:pop_sr":0,
    "qs_pg:qs_pg_placetype":"neighbourhood",
    "qs_pg:qs_pg_placetype_gp":"Suburb",
    "qs_pg:woe_adm0":23424900,
    "woe:adm0_id":23424900,
    "woe:name_adm0":"M\u00e9xico",
    "woe:name_adm1":"Oaxaca",
    "woe:placetype":"Suburb",
    "wof:name":"Santa Anita",
    "wof:placetype":"neighbourhood"
},
  "geometry": {"coordinates":[-97.04787,16.42549],"type":"Point"}
}