{
  "type": "Feature",
  "properties": {
    "gn:admin1_code":"23.0",
    "gn:admin2_code":"4.0",
    "gn:asciiname":"Tito",
    "gn:country_code":"MX",
    "gn:dem":22,
    "gn:feature_class":"P",
    "gn:feature_code":"PPL",
    "gn:name":"Tito",
    "gn:population":6,
    "gn:timezone":"America/Cancun",
    "iso:country":"MX",
    "name:ara_x_preferred":[
        "\u062a\u064a\u062a\u0648"
    ],
    "name:arg_x_preferred":[
        "Tito"
    ],
    "name:ben_x_preferred":[
        "\u099f\u09bf\u099f\u09cb"
    ],
    "name:cat_x_preferred":[
        "Tito"
    ],
    "name:ceb_x_preferred":[
        "Tito"
    ],
    "name:ces_x_preferred":[
        "Tito"
    ],
    "name:deu_x_preferred":[
        "Tito"
    ],
    "name:epo_x_preferred":[
        "Tito"
    ],
    "name:eus_x_preferred":[
        "Tito"
    ],
    "name:fas_x_preferred":[
        "\u062a\u06cc\u062a\u0648"
    ],
    "name:fin_x_preferred":[
        "Tito"
    ],
    "name:fra_x_preferred":[
        "Tito"
    ],
    "name:glg_x_preferred":[
        "Tito"
    ],
    "name:hrv_x_preferred":[
        "Tito"
    ],
    "name:hun_x_preferred":[
        "Tito"
    ],
    "name:ita_x_preferred":[
        "Tito"
    ],
    "name:jpn_x_preferred":[
        "\u30c6\u30a3\u30c8"
    ],
    "name:nld_x_preferred":[
        "Tito"
    ],
    "name:pol_x_preferred":[
        "Tito"
    ],
    "name:por_x_preferred":[
        "Tito"
    ],
    "name:rus_x_preferred":[
        "\u0422\u0438\u0442\u043e"
    ],
    "name:slk_x_preferred":[
        "Tito"
    ],
    "name:slv_x_preferred":[
        "Tito"
    ],
    "name:spa_x_preferred":[
        "Tito"
    ],
    "name:srp_x_preferred":[
        "\u0422\u0438\u0442\u043e"
    ],
    "name:swe_x_preferred":[
        "Tito"
    ],
    "name:tgl_x_preferred":[
        "Tito"
    ],
    "name:tha_x_preferred":[
        "\u0e15\u0e34\u0e42\u0e15"
    ],
    "name:ukr_x_preferred":[
        "\u0422\u0456\u0442\u043e"
    ],
    "name:vie_x_preferred":[
        "Tito"
    ],
    "wof:name":"Tito",
    "wof:placetype":"locality",
    "wof:population":6
},
  "geometry": {"coordinates":[-88.41889,18.83639],"type":"Point"}
}