{
  "type": "Feature",
  "properties": {
    "gn:admin1_code":"23.0",
    "gn:admin2_code":"4.0",
    "gn:asciiname":"Tito",
    "gn:country_code":"MX",
    "gn:dem":22,
    "gn:feature_class":"P",
    "gn:feature_code":"PPL",
    "gn:name":"Tito",
    "gn:population":6,
    "gn:timezone":"America/Cancun",
    "iso:country":"MX",
    "name:spa_x_preferred":[
        "Tito"
    ],
    "wof:name":"Tito",
    "wof:placetype":"locality",
    "wof:population":6
},
  "geometry": {"coordinates":[-88.41889,18.83639],"type":"Point"}
}