{
  "type": "Feature",
  "properties": {
    "gn:admin1_code":"20",
    "gn:admin2_code":"324",
    "gn:asciiname":"Azulillo",
    "gn:country_code":"MX",
    "gn:dem":196,
    "gn:feature_class":"P",
    "gn:feature_code":"PPL",
    "gn:name":"Azulillo",
    "gn:population":34,
    "gn:timezone":"America/Mexico_City",
    "iso:country":"MX",
    "wof:name":"Azulillo",
    "wof:placetype":"locality",
    "wof:population":34
},
  "geometry": {"coordinates":[-96.41361000000001,15.78139],"type":"Point"}
}