{
  "type": "Feature",
  "properties": {
    "gn:admin1_code":"8.0",
    "gn:admin2_code":"7.0",
    "gn:asciiname":"Rancho Yatai",
    "gn:country_code":"MX",
    "gn:dem":23,
    "gn:feature_class":"P",
    "gn:feature_code":"PPL",
    "gn:name":"Rancho Yatai",
    "gn:population":0,
    "gn:timezone":"America/Mexico_City",
    "iso:country":"MX",
    "name:spa_x_preferred":[
        "Rancho Yatai"
    ],
    "wof:name":"Rancho Yatai",
    "wof:placetype":"locality"
},
  "geometry": {"coordinates":[-104.08897,19.01412],"type":"Point"}
}