{
  "type": "Feature",
  "properties": {
    "gn:admin1_code":"6",
    "gn:admin2_code":"27.0",
    "gn:asciiname":"Basigochi",
    "gn:country_code":"MX",
    "gn:dem":2262,
    "gn:feature_class":"P",
    "gn:feature_code":"PPL",
    "gn:name":"Basigochi",
    "gn:population":40,
    "gn:timezone":"America/Chihuahua",
    "iso:country":"MX",
    "name:spa_x_preferred":[
        "Basigochi"
    ],
    "wof:name":"Basigochi",
    "wof:placetype":"locality",
    "wof:population":40
},
  "geometry": {"coordinates":[-107.04213,27.32771],"type":"Point"}
}