{
  "type": "Feature",
  "properties": {
    "gn:admin1_code":"16.0",
    "gn:admin2_code":"89.0",
    "gn:asciiname":"Punta de Agua",
    "gn:country_code":"MX",
    "gn:dem":340,
    "gn:feature_class":"P",
    "gn:feature_code":"PPL",
    "gn:name":"Punta de Agua",
    "gn:population":0,
    "gn:timezone":"America/Mexico_City",
    "iso:country":"MX",
    "name:spa_x_preferred":[
        "Punta de Agua"
    ],
    "wof:name":"Punta de Agua",
    "wof:placetype":"locality"
},
  "geometry": {"coordinates":[-102.78725,19.15737],"type":"Point"}
}