{
  "type": "Feature",
  "properties": {
    "gn:admin1_code":"26",
    "gn:admin2_code":"26.0",
    "gn:asciiname":"San Jorge",
    "gn:country_code":"MX",
    "gn:dem":39,
    "gn:feature_class":"P",
    "gn:feature_code":"PPL",
    "gn:name":"San Jorge",
    "gn:population":3,
    "gn:timezone":"America/Hermosillo",
    "iso:country":"MX",
    "name:ceb_x_preferred":[
        "San Jorge"
    ],
    "name:deu_x_preferred":[
        "San Jorge"
    ],
    "name:ita_x_preferred":[
        "San Jorge"
    ],
    "name:nld_x_preferred":[
        "San Jorge"
    ],
    "name:por_x_preferred":[
        "San Jorge"
    ],
    "name:rus_x_preferred":[
        "\u0421\u0430\u043d-\u0425\u043e\u0440\u0445\u0435"
    ],
    "name:sco_x_preferred":[
        "San Jorge"
    ],
    "name:spa_x_preferred":[
        "San Jorge"
    ],
    "name:swe_x_preferred":[
        "San Jorge"
    ],
    "name:vie_x_preferred":[
        "San Jorge"
    ],
    "name:war_x_preferred":[
        "San Jorge"
    ],
    "wof:name":"San Jorge",
    "wof:placetype":"locality",
    "wof:population":3
},
  "geometry": {"coordinates":[-109.68611,27.15139000000001],"type":"Point"}
}