{
  "type": "Feature",
  "properties": {
    "gn:admin1_code":"26",
    "gn:admin2_code":"57.0",
    "gn:asciiname":"Hacendradita",
    "gn:country_code":"MX",
    "gn:dem":1016,
    "gn:feature_class":"P",
    "gn:feature_code":"PPL",
    "gn:name":"Hacendradita",
    "gn:population":0,
    "gn:timezone":"America/Hermosillo",
    "iso:country":"MX",
    "name:spa_x_preferred":[
        "Hacendradita"
    ],
    "wof:name":"Hacendradita",
    "wof:placetype":"locality"
},
  "geometry": {"coordinates":[-109.93377,29.53601],"type":"Point"}
}