{
  "type": "Feature",
  "properties": {
    "gn:admin1_code":"19",
    "gn:admin2_code":"24.0",
    "gn:asciiname":"Tepozanes",
    "gn:country_code":"MX",
    "gn:dem":2305,
    "gn:feature_class":"P",
    "gn:feature_code":"PPL",
    "gn:name":"Tepozanes",
    "gn:population":171,
    "gn:timezone":"America/Monterrey",
    "iso:country":"MX",
    "name:spa_x_preferred":[
        "Tepozanes"
    ],
    "wof:name":"Tepozanes",
    "wof:placetype":"locality",
    "wof:population":171
},
  "geometry": {"coordinates":[-99.71693999999999,23.91806],"type":"Point"}
}