{
  "type": "Feature",
  "properties": {
    "gn:admin1_code":"31",
    "gn:admin2_code":"86.0",
    "gn:asciiname":"Poccheina",
    "gn:country_code":"MX",
    "gn:dem":14,
    "gn:feature_class":"P",
    "gn:feature_code":"PPL",
    "gn:name":"Pocchein\u00e1",
    "gn:population":2,
    "gn:timezone":"America/Merida",
    "iso:country":"MX",
    "wof:name":"Poccheina",
    "wof:placetype":"locality",
    "wof:population":2
},
  "geometry": {"coordinates":[-88.98555999999998,21.06944],"type":"Point"}
}