{
  "type": "Feature",
  "properties": {
    "gn:admin1_code":"20",
    "gn:admin2_code":"198.0",
    "gn:asciiname":"El Ocotalito",
    "gn:country_code":"MX",
    "gn:dem":456,
    "gn:feature_class":"P",
    "gn:feature_code":"PPL",
    "gn:name":"El Ocotalito",
    "gn:population":323,
    "gn:timezone":"America/Mexico_City",
    "iso:country":"MX",
    "wof:name":"El Ocotalito",
    "wof:placetype":"locality",
    "wof:population":323
},
  "geometry": {"coordinates":[-95.12944,16.96027999999999],"type":"Point"}
}