{
  "type": "Feature",
  "properties": {
    "gn:admin1_code":"10",
    "gn:admin2_code":"11.0",
    "gn:asciiname":"Los Machos",
    "gn:country_code":"MX",
    "gn:dem":2065,
    "gn:feature_class":"P",
    "gn:feature_code":"PPL",
    "gn:name":"Los Machos",
    "gn:population":0,
    "gn:timezone":"America/Monterrey",
    "iso:country":"MX",
    "wof:name":"Los Machos",
    "wof:placetype":"locality"
},
  "geometry": {"coordinates":[-105.0536,25.97612],"type":"Point"}
}