{
  "type": "Feature",
  "properties": {
    "gn:admin1_code":"10",
    "gn:admin2_code":"9.0",
    "gn:asciiname":"Dispensas de Arriba",
    "gn:country_code":"MX",
    "gn:dem":2702,
    "gn:feature_class":"P",
    "gn:feature_code":"PPL",
    "gn:name":"Dispensas de Arriba",
    "gn:population":0,
    "gn:timezone":"America/Monterrey",
    "iso:country":"MX",
    "name:und_x_variant":[
        "Rancho Las D\u00edspensas de Arriba",
        "Dispensas de Arriba"
    ],
    "wof:name":"Dispensas de Arriba",
    "wof:placetype":"locality"
},
  "geometry": {"coordinates":[-106.1918,26.2106],"type":"Point"}
}