{
  "type": "Feature",
  "properties": {
    "gn:admin1_code":"6.0",
    "gn:admin2_code":"29.0",
    "gn:asciiname":"El Cacastle",
    "gn:country_code":"MX",
    "gn:dem":2265,
    "gn:feature_class":"P",
    "gn:feature_code":"PPL",
    "gn:name":"El Cacastle",
    "gn:population":0,
    "gn:timezone":"America/Chihuahua",
    "iso:country":"MX",
    "name:spa_x_preferred":[
        "El Cacastle"
    ],
    "name:und_x_variant":[
        "Rancho Cacaste"
    ],
    "wof:name":"El Cacastle",
    "wof:placetype":"locality"
},
  "geometry": {"coordinates":[-107.08347000000001,26.20613],"type":"Point"}
}