{
  "type": "Feature",
  "properties": {
    "gn:admin1_code":"19",
    "gn:admin2_code":"14",
    "gn:asciiname":"San Mateo",
    "gn:country_code":"MX",
    "gn:dem":1638,
    "gn:feature_class":"P",
    "gn:feature_code":"PPL",
    "gn:name":"San Mateo",
    "gn:population":31,
    "gn:timezone":"America/Monterrey",
    "iso:country":"MX",
    "name:bul_x_preferred":[
        "\u0421\u0430\u043d \u041c\u0430\u0442\u0435\u043e"
    ],
    "name:cat_x_preferred":[
        "San Mateo"
    ],
    "name:ceb_x_preferred":[
        "San Mateo"
    ],
    "name:deu_x_preferred":[
        "San Mateo"
    ],
    "name:fra_x_preferred":[
        "San Mateo"
    ],
    "name:glg_x_preferred":[
        "San Mateo"
    ],
    "name:ilo_x_preferred":[
        "San Mateo"
    ],
    "name:ita_x_preferred":[
        "San Mateo"
    ],
    "name:jpn_x_preferred":[
        "\u30b5\u30f3\u30de\u30c6\u30aa"
    ],
    "name:nld_x_preferred":[
        "San Mateo"
    ],
    "name:nor_x_preferred":[
        "San Mateo"
    ],
    "name:pol_x_preferred":[
        "San Mateo"
    ],
    "name:por_x_preferred":[
        "San Mateo"
    ],
    "name:ron_x_preferred":[
        "San Mateo"
    ],
    "name:rus_x_preferred":[
        "\u0421\u0430\u043d-\u041c\u0430\u0442\u0435\u043e"
    ],
    "name:sco_x_preferred":[
        "San Mateo"
    ],
    "name:spa_x_preferred":[
        "San Mateo"
    ],
    "name:srp_x_preferred":[
        "\u0421\u0430\u043d \u041c\u0430\u0442\u0435\u043e"
    ],
    "name:swe_x_preferred":[
        "San Mateo"
    ],
    "name:tgl_x_preferred":[
        "San Mateo"
    ],
    "name:ukr_x_preferred":[
        "\u0421\u0430\u043d-\u041c\u0430\u0442\u0435\u043e"
    ],
    "name:vie_x_preferred":[
        "San Mateo"
    ],
    "name:war_x_preferred":[
        "San Mateo"
    ],
    "wof:name":"San Mateo",
    "wof:placetype":"locality",
    "wof:population":31
},
  "geometry": {"coordinates":[-100.06995000000001,23.83925],"type":"Point"}
}