{
  "type": "Feature",
  "properties": {
    "gn:admin1_code":"19",
    "gn:admin2_code":"14",
    "gn:asciiname":"San Mateo",
    "gn:country_code":"MX",
    "gn:dem":1638,
    "gn:feature_class":"P",
    "gn:feature_code":"PPL",
    "gn:name":"San Mateo",
    "gn:population":31,
    "gn:timezone":"America/Monterrey",
    "iso:country":"MX",
    "wof:name":"San Mateo",
    "wof:placetype":"locality",
    "wof:population":31
},
  "geometry": {"coordinates":[-100.06995000000001,23.83925],"type":"Point"}
}