{
  "type": "Feature",
  "properties": {
    "gn:admin1_code":"9",
    "gn:admin2_code":"12.0",
    "gn:asciiname":"El Arcoiris",
    "gn:country_code":"MX",
    "gn:dem":3024,
    "gn:feature_class":"P",
    "gn:feature_code":"PPL",
    "gn:name":"El Arcoiris",
    "gn:population":61,
    "gn:timezone":"America/Mexico_City",
    "iso:country":"MX",
    "wof:name":"El Arcoiris",
    "wof:placetype":"locality",
    "wof:population":61
},
  "geometry": {"coordinates":[-99.21306,19.20861],"type":"Point"}
}