{
  "type": "Feature",
  "properties": {
    "gn:admin1_code":"14.0",
    "gn:asciiname":"Chimo",
    "gn:country_code":"MX",
    "gn:dem":10,
    "gn:feature_class":"P",
    "gn:feature_code":"PPL",
    "gn:name":"Chimo",
    "gn:population":0,
    "gn:timezone":"America/Mexico_City",
    "iso:country":"MX",
    "name:ceb_x_preferred":[
        "Chimo"
    ],
    "name:deu_x_preferred":[
        "Chimo"
    ],
    "name:fra_x_preferred":[
        "Chimo"
    ],
    "name:spa_x_preferred":[
        "Chimo"
    ],
    "name:swe_x_preferred":[
        "Chimo"
    ],
    "wof:name":"Chimo",
    "wof:placetype":"locality"
},
  "geometry": {"coordinates":[-105.59248999999998,20.47373],"type":"Point"}
}