{
  "type": "Feature",
  "properties": {
    "gn:admin1_code":"20",
    "gn:admin2_code":"184.0",
    "gn:asciiname":"San Isidro las Pinas",
    "gn:country_code":"MX",
    "gn:dem":28,
    "gn:feature_class":"P",
    "gn:feature_code":"PPL",
    "gn:name":"San Isidro las Pi\u00f1as",
    "gn:population":408,
    "gn:timezone":"America/Mexico_City",
    "iso:country":"MX",
    "name:und_x_variant":[
        "San Isidro las Pi\u00f1as"
    ],
    "wof:name":"San Isidro las Pinas",
    "wof:placetype":"locality",
    "wof:population":408
},
  "geometry": {"coordinates":[-96.05278,18.12167],"type":"Point"}
}