{
  "type": "Feature",
  "properties": {
    "gn:admin1_code":"21",
    "gn:admin2_code":"91.0",
    "gn:asciiname":"Nuevo Necaxa",
    "gn:country_code":"MX",
    "gn:dem":1354,
    "gn:feature_class":"P",
    "gn:feature_code":"PPLA2",
    "gn:name":"Nuevo Necaxa",
    "gn:population":0,
    "gn:timezone":"America/Mexico_City",
    "iso:country":"MX",
    "name:spa_x_preferred":[
        "Nuevo Necaxa"
    ],
    "wof:name":"Nuevo Necaxa",
    "wof:placetype":"locality"
},
  "geometry": {"coordinates":[-98.00657,20.21049],"type":"Point"}
}