{
  "type": "Feature",
  "properties": {
    "gn:admin1_code":"30",
    "gn:admin2_code":"176",
    "gn:asciiname":"Bajo de Cepayapan",
    "gn:country_code":"MX",
    "gn:dem":11,
    "gn:feature_class":"P",
    "gn:feature_code":"PPL",
    "gn:name":"Bajo de Cepayapan",
    "gn:population":12,
    "gn:timezone":"America/Mexico_City",
    "iso:country":"MX",
    "wof:name":"Bajo de Cepayapan",
    "wof:placetype":"locality",
    "wof:population":12
},
  "geometry": {"coordinates":[-95.93722,18.23639],"type":"Point"}
}