{
  "type": "Feature",
  "properties": {
    "gn:admin1_code":"12.0",
    "gn:admin2_code":"58.0",
    "gn:asciiname":"Texcalco",
    "gn:country_code":"MX",
    "gn:dem":1706,
    "gn:feature_class":"P",
    "gn:feature_code":"PPL",
    "gn:name":"Texcalco",
    "gn:population":0,
    "gn:timezone":"America/Mexico_City",
    "iso:country":"MX",
    "name:spa_x_preferred":[
        "Texcalco"
    ],
    "wof:name":"Texcalco",
    "wof:placetype":"locality"
},
  "geometry": {"coordinates":[-99.77410999999999,18.32959],"type":"Point"}
}