{
  "type": "Feature",
  "properties": {
    "gn:admin1_code":"24.0",
    "gn:admin2_code":"46.0",
    "gn:asciiname":"Lagunita",
    "gn:country_code":"MX",
    "gn:dem":2215,
    "gn:feature_class":"P",
    "gn:feature_code":"PPL",
    "gn:name":"Lagunita",
    "gn:population":0,
    "gn:timezone":"America/Mexico_City",
    "iso:country":"MX",
    "name:nld_x_preferred":[
        "Lagunita"
    ],
    "name:spa_x_preferred":[
        "Lagunita"
    ],
    "name:swe_x_preferred":[
        "Lagunita"
    ],
    "wof:name":"Lagunita",
    "wof:placetype":"locality"
},
  "geometry": {"coordinates":[-101.41667,21.85],"type":"Point"}
}