{
  "type": "Feature",
  "properties": {
    "gn:admin1_code":"5",
    "gn:admin2_code":"17.0",
    "gn:asciiname":"Bethel",
    "gn:country_code":"MX",
    "gn:dem":1118,
    "gn:feature_class":"P",
    "gn:feature_code":"PPL",
    "gn:name":"Bethel",
    "gn:population":115,
    "gn:timezone":"America/Mexico_City",
    "iso:country":"MX",
    "wof:name":"Bethel",
    "wof:placetype":"locality",
    "wof:population":115
},
  "geometry": {"coordinates":[-94.05107,16.62682],"type":"Point"}
}