{
  "type": "Feature",
  "properties": {
    "gn:admin1_code":"31",
    "gn:admin2_code":"69.0",
    "gn:asciiname":"Tibolon",
    "gn:country_code":"MX",
    "gn:dem":23,
    "gn:feature_class":"P",
    "gn:feature_code":"PPL",
    "gn:name":"Tibol\u00f3n",
    "gn:population":0,
    "gn:timezone":"America/Merida",
    "iso:country":"MX",
    "wof:name":"Tibolon",
    "wof:placetype":"locality"
},
  "geometry": {"coordinates":[-88.95,20.66667],"type":"Point"}
}