{
  "type": "Feature",
  "properties": {
    "gn:admin1_code":"5",
    "gn:admin2_code":"81.0",
    "gn:asciiname":"Rio Blanco",
    "gn:country_code":"MX",
    "gn:dem":470,
    "gn:feature_class":"P",
    "gn:feature_code":"PPL",
    "gn:name":"R\u00edo Blanco",
    "gn:population":134,
    "gn:timezone":"America/Mexico_City",
    "iso:country":"MX",
    "name:und_x_variant":[
        "R\u00edo Blanco"
    ],
    "wof:name":"Rio Blanco",
    "wof:placetype":"locality",
    "wof:population":134
},
  "geometry": {"coordinates":[-92.52889,17.13306],"type":"Point"}
}