{
  "type": "Feature",
  "properties": {
    "gn:admin1_code":"24",
    "gn:admin2_code":"39",
    "gn:asciiname":"Rancho Santana",
    "gn:country_code":"MX",
    "gn:dem":90,
    "gn:feature_class":"P",
    "gn:feature_code":"PPL",
    "gn:name":"Rancho Santana",
    "gn:population":13,
    "gn:timezone":"America/Mexico_City",
    "iso:country":"MX",
    "wof:name":"Rancho Santana",
    "wof:placetype":"locality",
    "wof:population":13
},
  "geometry": {"coordinates":[-98.76361,21.575],"type":"Point"}
}