{
  "type": "Feature",
  "properties": {
    "gn:admin1_code":"3",
    "gn:admin2_code":"1.0",
    "gn:asciiname":"Las Tasajeras",
    "gn:country_code":"MX",
    "gn:dem":276,
    "gn:feature_class":"P",
    "gn:feature_code":"PPL",
    "gn:name":"Las Tasajeras",
    "gn:population":0,
    "gn:timezone":"America/Mazatlan",
    "iso:country":"MX",
    "name:spa_x_preferred":[
        "Las Tasajeras"
    ],
    "name:und_x_variant":[
        "Tasajera"
    ],
    "wof:name":"Las Tasajeras",
    "wof:placetype":"locality"
},
  "geometry": {"coordinates":[-111.8065,26.38131],"type":"Point"}
}