{
  "type": "Feature",
  "properties": {
    "gn:admin1_code":"32",
    "gn:admin2_code":"2.0",
    "gn:asciiname":"Las Tijeras",
    "gn:country_code":"MX",
    "gn:dem":1933,
    "gn:feature_class":"P",
    "gn:feature_code":"PPL",
    "gn:name":"Las Tijeras",
    "gn:population":64,
    "gn:timezone":"America/Mexico_City",
    "iso:country":"MX",
    "wof:name":"Las Tijeras",
    "wof:placetype":"locality",
    "wof:population":64
},
  "geometry": {"coordinates":[-102.70806,21.45806],"type":"Point"}
}