{
  "type": "Feature",
  "properties": {
    "gn:admin1_code":"16",
    "gn:admin2_code":"15",
    "gn:asciiname":"La Patacuera",
    "gn:country_code":"MX",
    "gn:dem":792,
    "gn:feature_class":"P",
    "gn:feature_code":"PPL",
    "gn:name":"La Patacuera",
    "gn:population":16,
    "gn:timezone":"America/Mexico_City",
    "iso:country":"MX",
    "wof:name":"La Patacuera",
    "wof:placetype":"locality",
    "wof:population":16
},
  "geometry": {"coordinates":[-103.06528,18.37194],"type":"Point"}
}