{
  "type": "Feature",
  "properties": {
    "gn:admin1_code":"5",
    "gn:admin2_code":"64.0",
    "gn:asciiname":"Nuevo San Ramon",
    "gn:country_code":"MX",
    "gn:dem":1880,
    "gn:feature_class":"P",
    "gn:feature_code":"PPL",
    "gn:name":"Nuevo San Ram\u00f3n",
    "gn:population":73,
    "gn:timezone":"America/Mexico_City",
    "iso:country":"MX",
    "name:und_x_variant":[
        "Nuevo San Ram\u00f3n"
    ],
    "wof:name":"Nuevo San Ramon",
    "wof:placetype":"locality",
    "wof:population":73
},
  "geometry": {"coordinates":[-92.21693999999999,16.71167],"type":"Point"}
}