{
  "type": "Feature",
  "properties": {
    "gn:admin1_code":"31",
    "gn:admin2_code":"87.0",
    "gn:asciiname":"Chicche",
    "gn:cc2":"MX",
    "gn:country_code":"MX",
    "gn:dem":3,
    "gn:feature_class":"P",
    "gn:feature_code":"PPL",
    "gn:name":"Chicch\u00e9",
    "gn:population":0,
    "gn:timezone":"America/Merida",
    "iso:country":"MX",
    "name:und_x_variant":[
        "Chiche",
        "Chicch\u00e9"
    ],
    "wof:name":"Chicche",
    "wof:placetype":"locality"
},
  "geometry": {"coordinates":[-89.98333000000002,20.98333],"type":"Point"}
}