{
  "type": "Feature",
  "properties": {
    "gn:admin1_code":"5",
    "gn:admin2_code":"52.0",
    "gn:asciiname":"Playas del Carmen",
    "gn:country_code":"MX",
    "gn:dem":1237,
    "gn:feature_class":"P",
    "gn:feature_code":"PPL",
    "gn:name":"Playas del Carmen",
    "gn:population":148,
    "gn:timezone":"America/Mexico_City",
    "iso:country":"MX",
    "wof:name":"Playas del Carmen",
    "wof:placetype":"locality",
    "wof:population":148
},
  "geometry": {"coordinates":[-91.73694,16.30139],"type":"Point"}
}