{
  "type": "Feature",
  "properties": {
    "gn:admin1_code":"13",
    "gn:admin2_code":"61.0",
    "gn:asciiname":"Palmillas",
    "gn:country_code":"MX",
    "gn:dem":2670,
    "gn:feature_class":"P",
    "gn:feature_code":"PPL",
    "gn:name":"Palmillas",
    "gn:population":65,
    "gn:timezone":"America/Mexico_City",
    "iso:country":"MX",
    "name:srp_x_preferred":[
        "\u041f\u0430\u043b\u043c\u0438\u0459\u0430\u0441"
    ],
    "wof:name":"Palmillas",
    "wof:placetype":"locality",
    "wof:population":65
},
  "geometry": {"coordinates":[-98.45058,19.86044],"type":"Point"}
}