{
  "type": "Feature",
  "properties": {
    "gn:admin1_code":"11",
    "gn:admin2_code":"5.0",
    "gn:asciiname":"Miguel Olvera Acosta",
    "gn:country_code":"MX",
    "gn:dem":1828,
    "gn:feature_class":"P",
    "gn:feature_code":"PPL",
    "gn:name":"Miguel Olvera Acosta",
    "gn:population":4,
    "gn:timezone":"America/Mexico_City",
    "iso:country":"MX",
    "wof:name":"Miguel Olvera Acosta",
    "wof:placetype":"locality",
    "wof:population":4
},
  "geometry": {"coordinates":[-100.66639000000001,20.55222],"type":"Point"}
}