{
  "type": "Feature",
  "properties": {
    "gn:admin1_code":"5",
    "gn:admin2_code":"65.0",
    "gn:asciiname":"Tzeltal Mukul-Ja",
    "gn:country_code":"MX",
    "gn:dem":59,
    "gn:feature_class":"P",
    "gn:feature_code":"PPL",
    "gn:name":"Tzeltal Mukul-J\u00e1",
    "gn:population":507,
    "gn:timezone":"America/Mexico_City",
    "iso:country":"MX",
    "name:und_x_variant":[
        "Tzeltal Mukul-J\u00e1"
    ],
    "wof:name":"Tzeltal Mukul-Ja",
    "wof:placetype":"locality",
    "wof:population":507
},
  "geometry": {"coordinates":[-92.10333,17.61361],"type":"Point"}
}