{
  "type": "Feature",
  "properties": {
    "gn:admin1_code":"24",
    "gn:admin2_code":"15.0",
    "gn:asciiname":"El Pame",
    "gn:country_code":"MX",
    "gn:dem":2261,
    "gn:feature_class":"P",
    "gn:feature_code":"PPL",
    "gn:name":"El Pame",
    "gn:population":0,
    "gn:timezone":"America/Mexico_City",
    "iso:country":"MX",
    "name:und_x_variant":[
        "El Paisano"
    ],
    "wof:name":"El Pame",
    "wof:placetype":"locality"
},
  "geometry": {"coordinates":[-101.29606,23.07868],"type":"Point"}
}