{
  "type": "Feature",
  "properties": {
    "gn:admin1_code":"5.0",
    "gn:admin2_code":"71.0",
    "gn:asciiname":"Marandu",
    "gn:country_code":"MX",
    "gn:dem":9,
    "gn:feature_class":"P",
    "gn:feature_code":"PPL",
    "gn:name":"Marand\u00fa",
    "gn:population":0,
    "gn:timezone":"America/Mexico_City",
    "iso:country":"MX",
    "name:spa_x_preferred":[
        "Marand\u00fa"
    ],
    "wof:name":"Marandu",
    "wof:placetype":"locality"
},
  "geometry": {"coordinates":[-92.68322000000001,15.12398],"type":"Point"}
}