{
  "type": "Feature",
  "properties": {
    "gn:admin1_code":"5",
    "gn:admin2_code":"31.0",
    "gn:asciiname":"Bawitz Mango",
    "gn:country_code":"MX",
    "gn:dem":1155,
    "gn:feature_class":"P",
    "gn:feature_code":"PPL",
    "gn:name":"Bawitz Mango",
    "gn:population":154,
    "gn:timezone":"America/Mexico_City",
    "iso:country":"MX",
    "wof:name":"Bawitz Mango",
    "wof:placetype":"locality",
    "wof:population":154
},
  "geometry": {"coordinates":[-91.83889000000001,17.06472],"type":"Point"}
}