{
  "type": "Feature",
  "properties": {
    "gn:admin1_code":"14.0",
    "gn:admin2_code":"88.0",
    "gn:asciiname":"Rancho Vida Nueva",
    "gn:country_code":"MX",
    "gn:dem":1125,
    "gn:feature_class":"P",
    "gn:feature_code":"PPL",
    "gn:name":"Rancho Vida Nueva",
    "gn:population":0,
    "gn:timezone":"America/Mexico_City",
    "iso:country":"MX",
    "name:spa_x_preferred":[
        "Rancho Vida Nueva"
    ],
    "wof:name":"Rancho Vida Nueva",
    "wof:placetype":"locality"
},
  "geometry": {"coordinates":[-104.07644000000001,20.12665],"type":"Point"}
}