{
  "type": "Feature",
  "properties": {
    "gn:admin1_code":"11",
    "gn:admin2_code":"32.0",
    "gn:asciiname":"El Mosqueado (Allende)",
    "gn:country_code":"MX",
    "gn:dem":2182,
    "gn:feature_class":"P",
    "gn:feature_code":"PPL",
    "gn:name":"El Mosqueado (Allende)",
    "gn:population":174,
    "gn:timezone":"America/Mexico_City",
    "iso:country":"MX",
    "wof:name":"El Mosqueado (Allende)",
    "wof:placetype":"locality",
    "wof:population":174
},
  "geometry": {"coordinates":[-100.45806,20.97972],"type":"Point"}
}