{
  "type": "Feature",
  "properties": {
    "gn:admin1_code":"27",
    "gn:admin2_code":"5.0",
    "gn:asciiname":"Norte",
    "gn:country_code":"MX",
    "gn:dem":9,
    "gn:feature_class":"P",
    "gn:feature_code":"PPL",
    "gn:name":"Norte",
    "gn:population":0,
    "gn:timezone":"America/Mexico_City",
    "iso:country":"MX",
    "name:bre_x_preferred":[
        "Norte"
    ],
    "name:ceb_x_preferred":[
        "Norte"
    ],
    "name:deu_x_preferred":[
        "Norte"
    ],
    "name:fra_x_preferred":[
        "Norte"
    ],
    "name:glg_x_preferred":[
        "Norte"
    ],
    "name:nld_x_preferred":[
        "Norte"
    ],
    "name:por_x_preferred":[
        "Norte"
    ],
    "name:sco_x_preferred":[
        "Norte"
    ],
    "name:slk_x_preferred":[
        "Norte"
    ],
    "name:spa_x_preferred":[
        "Norte Primera Secci\u00f3n"
    ],
    "name:spa_x_variant":[
        "Norte",
        "Primera Seccion"
    ],
    "name:swe_x_preferred":[
        "Norte"
    ],
    "name:ukr_x_preferred":[
        "\u041d\u043e\u0440\u0442\u0435"
    ],
    "wof:name":"Norte",
    "wof:placetype":"locality"
},
  "geometry": {"coordinates":[-93.20792,18.28639],"type":"Point"}
}