{
  "type": "Feature",
  "properties": {
    "gn:admin1_code":"5",
    "gn:admin2_code":"99",
    "gn:asciiname":"San Antonio el Puente",
    "gn:country_code":"MX",
    "gn:dem":668,
    "gn:feature_class":"P",
    "gn:feature_code":"PPL",
    "gn:name":"San Antonio el Puente",
    "gn:population":23,
    "gn:timezone":"America/Mexico_City",
    "iso:country":"MX",
    "wof:name":"San Antonio el Puente",
    "wof:placetype":"locality",
    "wof:population":23
},
  "geometry": {"coordinates":[-91.87667,15.85806],"type":"Point"}
}