{
  "type": "Feature",
  "properties": {
    "gn:admin1_code":"23",
    "gn:admin2_code":"7.0",
    "gn:asciiname":"Villa Infantil Maya",
    "gn:country_code":"MX",
    "gn:dem":21,
    "gn:feature_class":"P",
    "gn:feature_code":"PPL",
    "gn:name":"Villa Infantil Maya",
    "gn:population":7,
    "gn:timezone":"America/Cancun",
    "iso:country":"MX",
    "wof:name":"Villa Infantil Maya",
    "wof:placetype":"locality",
    "wof:population":7
},
  "geometry": {"coordinates":[-87.55694,20.875],"type":"Point"}
}