{
  "type": "Feature",
  "properties": {
    "gn:admin1_code":"16",
    "gn:admin2_code":"88.0",
    "gn:asciiname":"Fraccionamiento Mirador de las Monarcas",
    "gn:country_code":"MX",
    "gn:dem":1865,
    "gn:feature_class":"P",
    "gn:feature_code":"PPL",
    "gn:name":"Fraccionamiento Mirador de las Monarcas",
    "gn:population":377,
    "gn:timezone":"America/Mexico_City",
    "iso:country":"MX",
    "wof:name":"Fraccionamiento Mirador de las Monarcas",
    "wof:placetype":"locality",
    "wof:population":377
},
  "geometry": {"coordinates":[-101.14444,19.77167],"type":"Point"}
}