{
  "type": "Feature",
  "properties": {
    "gn:admin1_code":"24",
    "gn:admin2_code":"49.0",
    "gn:asciiname":"Morales",
    "gn:country_code":"MX",
    "gn:dem":2228,
    "gn:feature_class":"P",
    "gn:feature_code":"PPL",
    "gn:name":"Morales",
    "gn:population":0,
    "gn:timezone":"America/Mexico_City",
    "iso:country":"MX",
    "name:ces_x_preferred":[
        "Morales"
    ],
    "name:deu_x_preferred":[
        "Morales"
    ],
    "name:lav_x_preferred":[
        "Moraless"
    ],
    "name:spa_x_preferred":[
        "Morales"
    ],
    "name:srp_x_preferred":[
        "\u041c\u043e\u0440\u0430\u043b\u0435\u0441"
    ],
    "wof:name":"Morales",
    "wof:placetype":"locality"
},
  "geometry": {"coordinates":[-101.83951,22.87123],"type":"Point"}
}