{
  "type": "Feature",
  "properties": {
    "gn:admin1_code":"6",
    "gn:admin2_code":"63.0",
    "gn:asciiname":"Los Pilares",
    "gn:cc2":"MX",
    "gn:country_code":"MX",
    "gn:dem":1493,
    "gn:feature_class":"P",
    "gn:feature_code":"PPL",
    "gn:name":"Los Pilares",
    "gn:population":2,
    "gn:timezone":"America/Chihuahua",
    "iso:country":"MX",
    "name:und_x_variant":[
        "Rancho Pilares",
        "Pilares"
    ],
    "wof:name":"Los Pilares",
    "wof:placetype":"locality",
    "wof:population":2
},
  "geometry": {"coordinates":[-108.52506,28.70777],"type":"Point"}
}