{
  "type": "Feature",
  "properties": {
    "gn:admin1_code":"6",
    "gn:admin2_code":"27.0",
    "gn:asciiname":"Huirinapachi",
    "gn:country_code":"MX",
    "gn:dem":2360,
    "gn:feature_class":"P",
    "gn:feature_code":"PPL",
    "gn:name":"Huirin\u00e1pachi",
    "gn:population":0,
    "gn:timezone":"America/Chihuahua",
    "iso:country":"MX",
    "name:spa_x_preferred":[
        "Huirin\u00e1pachi"
    ],
    "wof:name":"Huirinapachi",
    "wof:placetype":"locality"
},
  "geometry": {"coordinates":[-107.56498999999999,27.54847],"type":"Point"}
}