{
  "type": "Feature",
  "properties": {
    "gn:admin1_code":"7",
    "gn:admin2_code":"38.0",
    "gn:asciiname":"Manuel Valdez",
    "gn:country_code":"MX",
    "gn:dem":365,
    "gn:feature_class":"P",
    "gn:feature_code":"PPL",
    "gn:name":"Manuel Valdez",
    "gn:population":4,
    "gn:timezone":"America/Monterrey",
    "iso:country":"MX",
    "wof:name":"Manuel Valdez",
    "wof:placetype":"locality",
    "wof:population":4
},
  "geometry": {"coordinates":[-100.91275,28.46997],"type":"Point"}
}