{
  "type": "Feature",
  "properties": {
    "gn:admin1_code":"14",
    "gn:admin2_code":"17.0",
    "gn:asciiname":"San Pedro",
    "gn:country_code":"MX",
    "gn:dem":1385,
    "gn:feature_class":"P",
    "gn:feature_code":"PPL",
    "gn:name":"San Pedro",
    "gn:population":0,
    "gn:timezone":"America/Mexico_City",
    "iso:country":"MX",
    "name:spa_x_preferred":[
        "San Pedro"
    ],
    "wof:name":"San Pedro",
    "wof:placetype":"locality"
},
  "geometry": {"coordinates":[-104.27901,20.09667],"type":"Point"}
}