{
  "type": "Feature",
  "properties": {
    "gn:admin1_code":"2",
    "gn:admin2_code":"3.0",
    "gn:asciiname":"Rancho Macho Gueero",
    "gn:country_code":"MX",
    "gn:dem":971,
    "gn:feature_class":"P",
    "gn:feature_code":"PPL",
    "gn:name":"Rancho Macho G\u00fcero",
    "gn:population":0,
    "gn:timezone":"America/Tijuana",
    "iso:country":"MX",
    "name:spa_x_preferred":[
        "Rancho Macho G\u00fcero"
    ],
    "wof:name":"Rancho Macho Gueero",
    "wof:placetype":"locality"
},
  "geometry": {"coordinates":[-116.35928,32.55659],"type":"Point"}
}