{
  "type": "Feature",
  "properties": {
    "gn:admin1_code":"5",
    "gn:admin2_code":"4.0",
    "gn:asciiname":"Nueva Revolucion",
    "gn:country_code":"MX",
    "gn:dem":985,
    "gn:feature_class":"P",
    "gn:feature_code":"PPL",
    "gn:name":"Nueva Revoluci\u00f3n",
    "gn:population":282,
    "gn:timezone":"America/Mexico_City",
    "iso:country":"MX",
    "name:und_x_variant":[
        "Nueva Revoluci\u00f3n"
    ],
    "wof:name":"Nueva Revolucion",
    "wof:placetype":"locality",
    "wof:population":282
},
  "geometry": {"coordinates":[-91.86749,16.69828],"type":"Point"}
}