{
  "type": "Feature",
  "properties": {
    "iso:country":"MX",
    "name:spa_x_preferred":[
        "Paseo Del Rio"
    ],
    "qs:gn_adm0_cc":"MX",
    "qs:gn_local":4012176,
    "qs:gn_nam_loc":"Culiacan, Culiacan Rosales, Sinaloa, MX",
    "qs:gn_namadm1":"25",
    "qs:local_max":247,
    "qs:local_sum":299,
    "qs:localhoods":5,
    "qs:name":"Paseo Del Rio",
    "qs:name_adm0":"M\u00e9xico",
    "qs:name_adm1":"Sinaloa",
    "qs:name_adm2":"Culiacan",
    "qs:name_local":"Culiacan Rosales",
    "qs:photo_max":3,
    "qs:photo_sum":3,
    "qs:placetype":"Suburb",
    "qs:quad_count":1,
    "qs:woe_adm0":23424900,
    "qs:woe_adm1":2346288,
    "qs:woe_adm2":12601533,
    "qs:woe_lau":0,
    "qs:woe_local":55915652,
    "qs:woe_ver":"7.10.0",
    "wof:lang":[
        "spa"
    ],
    "wof:name":"Paseo Del Rio",
    "wof:placetype":"neighbourhood"
},
  "geometry": {"coordinates":[-107.36663799999999,24.824133],"type":"Point"}
}