{
  "type": "Feature",
  "properties": {
    "gn:admin1_code":"14.0",
    "gn:admin2_code":"21.0",
    "gn:asciiname":"Los Arboles",
    "gn:country_code":"MX",
    "gn:dem":804,
    "gn:feature_class":"P",
    "gn:feature_code":"PPL",
    "gn:name":"Los Arboles",
    "gn:population":0,
    "gn:timezone":"America/Mexico_City",
    "iso:country":"MX",
    "name:spa_x_preferred":[
        "Los Arboles"
    ],
    "wof:name":"Los Arboles",
    "wof:placetype":"locality"
},
  "geometry": {"coordinates":[-104.42140000000001,19.70075],"type":"Point"}
}