{
  "type": "Feature",
  "properties": {
    "gn:admin1_code":"30",
    "gn:admin2_code":"157.0",
    "gn:asciiname":"Rancho Nuevo",
    "gn:country_code":"MX",
    "gn:dem":118,
    "gn:feature_class":"P",
    "gn:feature_code":"PPL",
    "gn:name":"Rancho Nuevo",
    "gn:population":13,
    "gn:timezone":"America/Mexico_City",
    "iso:country":"MX",
    "name:spa_x_preferred":[
        "Rancho Nuevo"
    ],
    "wof:name":"Rancho Nuevo",
    "wof:placetype":"locality",
    "wof:population":13
},
  "geometry": {"coordinates":[-97.62824999999999,20.72198],"type":"Point"}
}