{
  "type": "Feature",
  "properties": {
    "gn:admin1_code":"5.0",
    "gn:admin2_code":"77.0",
    "gn:asciiname":"Campanario Chico",
    "gn:country_code":"MX",
    "gn:dem":589,
    "gn:feature_class":"P",
    "gn:feature_code":"PPL",
    "gn:name":"Campanario Chico",
    "gn:population":0,
    "gn:timezone":"America/Mexico_City",
    "iso:country":"MX",
    "name:spa_x_preferred":[
        "Campanario Chico"
    ],
    "wof:name":"Campanario Chico",
    "wof:placetype":"locality"
},
  "geometry": {"coordinates":[-92.35290999999999,17.48564],"type":"Point"}
}