{
  "type": "Feature",
  "properties": {
    "gn:admin1_code":"20.0",
    "gn:admin2_code":"499.0",
    "gn:asciiname":"Nduayute",
    "gn:country_code":"MX",
    "gn:dem":2091,
    "gn:feature_class":"P",
    "gn:feature_code":"PPL",
    "gn:name":"Nduayute",
    "gn:population":0,
    "gn:timezone":"America/Mexico_City",
    "iso:country":"MX",
    "name:spa_x_preferred":[
        "Nduayute"
    ],
    "wof:name":"Nduayute",
    "wof:placetype":"locality"
},
  "geometry": {"coordinates":[-97.57279,17.44992],"type":"Point"}
}