{
  "type": "Feature",
  "properties": {
    "gn:admin1_code":"28.0",
    "gn:admin2_code":"16.0",
    "gn:asciiname":"Las Curvas del Huisache",
    "gn:country_code":"MX",
    "gn:dem":689,
    "gn:feature_class":"P",
    "gn:feature_code":"PPL",
    "gn:name":"Las Curvas del Huisache",
    "gn:population":0,
    "gn:timezone":"America/Monterrey",
    "iso:country":"MX",
    "name:spa_x_preferred":[
        "Las Curvas del Huisache"
    ],
    "wof:name":"Las Curvas del Huisache",
    "wof:placetype":"locality"
},
  "geometry": {"coordinates":[-99.42959999999999,24.08466],"type":"Point"}
}