{
  "type": "Feature",
  "properties": {
    "gn:admin1_code":"25.0",
    "gn:admin2_code":"17.0",
    "gn:asciiname":"El Alamito",
    "gn:country_code":"MX",
    "gn:dem":56,
    "gn:feature_class":"P",
    "gn:feature_code":"PPL",
    "gn:name":"El Alamito",
    "gn:population":0,
    "gn:timezone":"America/Mazatlan",
    "iso:country":"MX",
    "name:spa_x_preferred":[
        "El Alamito"
    ],
    "wof:name":"El Alamito",
    "wof:placetype":"locality"
},
  "geometry": {"coordinates":[-108.47906999999999,25.84456],"type":"Point"}
}