{
  "type": "Feature",
  "properties": {
    "gn:admin1_code":"14.0",
    "gn:asciiname":"Casillas",
    "gn:country_code":"MX",
    "gn:dem":1944,
    "gn:feature_class":"P",
    "gn:feature_code":"PPL",
    "gn:name":"Casillas",
    "gn:population":0,
    "gn:timezone":"America/Mexico_City",
    "iso:country":"MX",
    "name:ast_x_preferred":[
        "Casillas"
    ],
    "name:cat_x_preferred":[
        "Casillas"
    ],
    "name:ceb_x_preferred":[
        "Casillas"
    ],
    "name:deu_x_preferred":[
        "Casillas"
    ],
    "name:eus_x_preferred":[
        "Casillas"
    ],
    "name:fra_x_preferred":[
        "Casillas"
    ],
    "name:ita_x_preferred":[
        "Casillas"
    ],
    "name:pol_x_preferred":[
        "Casillas"
    ],
    "name:por_x_preferred":[
        "Casillas"
    ],
    "name:rus_x_preferred":[
        "\u041a\u0430\u0441\u0438\u043b\u044c\u044f\u0441"
    ],
    "name:spa_x_preferred":[
        "Casillas"
    ],
    "name:swe_x_preferred":[
        "Casillas"
    ],
    "wof:name":"Casillas",
    "wof:placetype":"locality"
},
  "geometry": {"coordinates":[-101.94353,20.99173],"type":"Point"}
}