{
  "type": "Feature",
  "properties": {
    "gn:admin1_code":"6.0",
    "gn:admin2_code":"11.0",
    "gn:asciiname":"Cerro Solo",
    "gn:country_code":"MX",
    "gn:dem":1318,
    "gn:feature_class":"P",
    "gn:feature_code":"PPL",
    "gn:name":"Cerro Solo",
    "gn:population":0,
    "gn:timezone":"America/Chihuahua",
    "iso:country":"MX",
    "name:spa_x_preferred":[
        "Cerro Solo"
    ],
    "name:und_x_variant":[
        "Rancho Cerro Solo"
    ],
    "wof:name":"Cerro Solo",
    "wof:placetype":"locality"
},
  "geometry": {"coordinates":[-104.4807,28.64934],"type":"Point"}
}