{
  "type": "Feature",
  "properties": {
    "gn:admin1_code":"13",
    "gn:admin2_code":"27.0",
    "gn:asciiname":"Rio Beltran",
    "gn:country_code":"MX",
    "gn:dem":301,
    "gn:feature_class":"P",
    "gn:feature_code":"PPL",
    "gn:name":"R\u00edo Beltr\u00e1n",
    "gn:population":313,
    "gn:timezone":"America/Mexico_City",
    "iso:country":"MX",
    "name:spa_x_preferred":[
        "R\u00edo Beltr\u00e1n"
    ],
    "wof:name":"Rio Beltran",
    "wof:placetype":"locality",
    "wof:population":313
},
  "geometry": {"coordinates":[-98.05409,20.5721],"type":"Point"}
}