{
  "type": "Feature",
  "properties": {
    "gn:admin1_code":"30",
    "gn:admin2_code":"94.0",
    "gn:asciiname":"El Jatillo (El Hatillo)",
    "gn:country_code":"MX",
    "gn:dem":33,
    "gn:feature_class":"P",
    "gn:feature_code":"PPL",
    "gn:name":"El Jatillo (El Hatillo)",
    "gn:population":144,
    "gn:timezone":"America/Mexico_City",
    "iso:country":"MX",
    "wof:name":"El Jatillo (El Hatillo)",
    "wof:placetype":"locality",
    "wof:population":144
},
  "geometry": {"coordinates":[-95.46556,18.16306],"type":"Point"}
}