{
  "type": "Feature",
  "properties": {
    "gn:admin1_code":"18",
    "gn:admin2_code":"19.0",
    "gn:asciiname":"Salvatierra",
    "gn:country_code":"MX",
    "gn:dem":1078,
    "gn:feature_class":"P",
    "gn:feature_code":"PPL",
    "gn:name":"Salvatierra",
    "gn:population":5,
    "gn:timezone":"America/Mazatlan",
    "iso:country":"MX",
    "name:arg_x_preferred":[
        "Salvatierra"
    ],
    "name:bre_x_preferred":[
        "Salvatierra"
    ],
    "name:cat_x_preferred":[
        "Salvatierra"
    ],
    "name:ceb_x_preferred":[
        "Salvatierra"
    ],
    "name:deu_x_preferred":[
        "Salvatierra"
    ],
    "name:fra_x_preferred":[
        "Salvatierra"
    ],
    "name:glg_x_preferred":[
        "Salvatierra"
    ],
    "name:hun_x_preferred":[
        "Salvatierra"
    ],
    "name:ita_x_preferred":[
        "Salvatierra"
    ],
    "name:rus_x_preferred":[
        "\u0421\u0430\u043b\u044c\u0432\u0430\u0442\u044c\u0435\u0440\u0440\u0430"
    ],
    "name:sco_x_preferred":[
        "Salvatierra"
    ],
    "name:spa_x_preferred":[
        "Salvatierra"
    ],
    "name:swe_x_preferred":[
        "Salvatierra"
    ],
    "wof:name":"Salvatierra",
    "wof:placetype":"locality",
    "wof:population":5
},
  "geometry": {"coordinates":[-104.16943999999999,21.325],"type":"Point"}
}