{
  "type": "Feature",
  "properties": {
    "gn:admin1_code":"18",
    "gn:admin2_code":"19.0",
    "gn:asciiname":"Salvatierra",
    "gn:country_code":"MX",
    "gn:dem":1078,
    "gn:feature_class":"P",
    "gn:feature_code":"PPL",
    "gn:name":"Salvatierra",
    "gn:population":5,
    "gn:timezone":"America/Mazatlan",
    "iso:country":"MX",
    "wof:name":"Salvatierra",
    "wof:placetype":"locality",
    "wof:population":5
},
  "geometry": {"coordinates":[-104.16943999999999,21.325],"type":"Point"}
}