{
  "type": "Feature",
  "properties": {
    "gn:admin1_code":"26",
    "gn:admin2_code":"63.0",
    "gn:asciiname":"Rancheria",
    "gn:country_code":"MX",
    "gn:dem":944,
    "gn:feature_class":"P",
    "gn:feature_code":"PPL",
    "gn:name":"Rancher\u00eda",
    "gn:population":0,
    "gn:timezone":"America/Hermosillo",
    "iso:country":"MX",
    "name:und_x_variant":[
        "Rancher\u00eda",
        "La Rancher\u00eda"
    ],
    "wof:name":"Rancheria",
    "wof:placetype":"locality"
},
  "geometry": {"coordinates":[-109.69723,29.49688],"type":"Point"}
}