{
  "type": "Feature",
  "properties": {
    "gn:admin1_code":"20",
    "gn:admin2_code":"406.0",
    "gn:asciiname":"La Paz",
    "gn:country_code":"MX",
    "gn:dem":1134,
    "gn:feature_class":"P",
    "gn:feature_code":"PPL",
    "gn:name":"La Paz",
    "gn:population":103,
    "gn:timezone":"America/Mexico_City",
    "iso:country":"MX",
    "wof:name":"La Paz",
    "wof:placetype":"locality",
    "wof:population":103
},
  "geometry": {"coordinates":[-96.77972,18.31694],"type":"Point"}
}