{
  "type": "Feature",
  "properties": {
    "gn:admin1_code":"5",
    "gn:admin2_code":"64",
    "gn:asciiname":"Santo Tomas",
    "gn:country_code":"MX",
    "gn:dem":2022,
    "gn:feature_class":"P",
    "gn:feature_code":"PPL",
    "gn:name":"Santo Tom\u00e1s",
    "gn:population":36,
    "gn:timezone":"America/Mexico_City",
    "iso:country":"MX",
    "name:und_x_variant":[
        "Santo Tom\u00e1s"
    ],
    "wof:name":"Santo Tomas",
    "wof:placetype":"locality",
    "wof:population":36
},
  "geometry": {"coordinates":[-92.35361,16.79861],"type":"Point"}
}