{
  "type": "Feature",
  "properties": {
    "gn:admin1_code":"6",
    "gn:admin2_code":"44.0",
    "gn:asciiname":"Campestre [Corrales]",
    "gn:country_code":"MX",
    "gn:dem":1739,
    "gn:feature_class":"P",
    "gn:feature_code":"PPL",
    "gn:name":"Campestre [Corrales]",
    "gn:population":5,
    "gn:timezone":"America/Chihuahua",
    "iso:country":"MX",
    "wof:name":"Campestre [Corrales]",
    "wof:placetype":"locality",
    "wof:population":5
},
  "geometry": {"coordinates":[-105.60568000000001,26.85184000000001],"type":"Point"}
}