{
  "type": "Feature",
  "properties": {
    "gn:admin1_code":"30.0",
    "gn:admin2_code":"114.0",
    "gn:asciiname":"Paso Novillo",
    "gn:country_code":"MX",
    "gn:dem":40,
    "gn:feature_class":"P",
    "gn:feature_code":"PPL",
    "gn:name":"Paso Novillo",
    "gn:population":2,
    "gn:timezone":"America/Mexico_City",
    "iso:country":"MX",
    "name:spa_x_preferred":[
        "Paso Novillo"
    ],
    "wof:name":"Paso Novillo",
    "wof:placetype":"locality",
    "wof:population":2
},
  "geometry": {"coordinates":[-96.75472000000001,20.10778],"type":"Point"}
}