{
  "type": "Feature",
  "properties": {
    "gn:admin1_code":"11.0",
    "gn:admin2_code":"14.0",
    "gn:asciiname":"La Presa de la Pastora",
    "gn:country_code":"MX",
    "gn:dem":2220,
    "gn:feature_class":"P",
    "gn:feature_code":"PPL",
    "gn:name":"La Presa de la Pastora",
    "gn:population":0,
    "gn:timezone":"America/Mexico_City",
    "iso:country":"MX",
    "name:spa_x_preferred":[
        "La Presa de la Pastora"
    ],
    "wof:name":"La Presa de la Pastora",
    "wof:placetype":"locality"
},
  "geometry": {"coordinates":[-101.02809000000001,21.07036],"type":"Point"}
}