{
  "type": "Feature",
  "properties": {
    "gn:admin1_code":"22",
    "gn:admin2_code":"2",
    "gn:asciiname":"Palo de Agua",
    "gn:country_code":"MX",
    "gn:dem":1674,
    "gn:feature_class":"P",
    "gn:feature_code":"PPL",
    "gn:name":"Palo de Agua",
    "gn:population":50,
    "gn:timezone":"America/Mexico_City",
    "iso:country":"MX",
    "wof:name":"Palo de Agua",
    "wof:placetype":"locality",
    "wof:population":50
},
  "geometry": {"coordinates":[-99.47389,21.10861],"type":"Point"}
}