{
  "type": "Feature",
  "properties": {
    "gn:admin1_code":"6",
    "gn:admin2_code":"3.0",
    "gn:asciiname":"Las Carolinas",
    "gn:country_code":"MX",
    "gn:dem":1388,
    "gn:feature_class":"P",
    "gn:feature_code":"PPL",
    "gn:name":"Las Carolinas",
    "gn:population":0,
    "gn:timezone":"America/Chihuahua",
    "iso:country":"MX",
    "name:spa_x_preferred":[
        "Las Carolinas"
    ],
    "wof:name":"Las Carolinas",
    "wof:placetype":"locality"
},
  "geometry": {"coordinates":[-105.17789999999999,27.29503],"type":"Point"}
}