{
  "type": "Feature",
  "properties": {
    "gn:admin1_code":"7.0",
    "gn:admin2_code":"18.0",
    "gn:asciiname":"El Huizache",
    "gn:country_code":"MX",
    "gn:dem":623,
    "gn:feature_class":"P",
    "gn:feature_code":"PPL",
    "gn:name":"El Huizache",
    "gn:population":0,
    "gn:timezone":"America/Monterrey",
    "iso:country":"MX",
    "name:und_x_variant":[
        "El Huisache"
    ],
    "wof:name":"El Huizache",
    "wof:placetype":"locality"
},
  "geometry": {"coordinates":[-101.16208,26.87001],"type":"Point"}
}