{
  "type": "Feature",
  "properties": {
    "gn:admin1_code":"2",
    "gn:admin2_code":"4.0",
    "gn:asciiname":"Tetas de Julia",
    "gn:cc2":"MX",
    "gn:country_code":"MX",
    "gn:dem":576,
    "gn:feature_class":"P",
    "gn:feature_code":"PPL",
    "gn:name":"Tetas de Julia",
    "gn:population":0,
    "gn:timezone":"America/Tijuana",
    "iso:country":"MX",
    "name:und_x_variant":[
        "Telas de Julia",
        "Tetas de Julia"
    ],
    "wof:name":"Tetas de Julia",
    "wof:placetype":"locality"
},
  "geometry": {"coordinates":[-116.86667,32.35],"type":"Point"}
}