{
  "type": "Feature",
  "properties": {
    "gn:admin1_code":"20",
    "gn:admin2_code":"134.0",
    "gn:asciiname":"La Permuta",
    "gn:country_code":"MX",
    "gn:dem":108,
    "gn:feature_class":"P",
    "gn:feature_code":"PPL",
    "gn:name":"La Permuta",
    "gn:population":714,
    "gn:timezone":"America/Mexico_City",
    "iso:country":"MX",
    "wof:name":"La Permuta",
    "wof:placetype":"locality",
    "wof:population":714
},
  "geometry": {"coordinates":[-96.48917,18.09528],"type":"Point"}
}