{
  "type": "Feature",
  "properties": {
    "gn:admin1_code":"4",
    "gn:admin2_code":"3.0",
    "gn:asciiname":"Santa Cruz",
    "gn:country_code":"MX",
    "gn:dem":9,
    "gn:feature_class":"P",
    "gn:feature_code":"PPL",
    "gn:name":"Santa Cruz",
    "gn:population":8,
    "gn:timezone":"America/Mexico_City",
    "iso:country":"MX",
    "wof:name":"Santa Cruz",
    "wof:placetype":"locality",
    "wof:population":8
},
  "geometry": {"coordinates":[-91.67722000000001,17.92361],"type":"Point"}
}