{
  "type": "Feature",
  "properties": {
    "gn:admin1_code":"30",
    "gn:admin2_code":"188.0",
    "gn:asciiname":"Colonia los Naranjos (El Roble)",
    "gn:country_code":"MX",
    "gn:dem":1079,
    "gn:feature_class":"P",
    "gn:feature_code":"PPL",
    "gn:name":"Colonia los Naranjos (El Roble)",
    "gn:population":110,
    "gn:timezone":"America/Mexico_City",
    "iso:country":"MX",
    "wof:name":"Colonia los Naranjos (El Roble)",
    "wof:placetype":"locality",
    "wof:population":110
},
  "geometry": {"coordinates":[-96.88333,19.18917],"type":"Point"}
}