{
  "type": "Feature",
  "properties": {
    "gn:admin1_code":"16",
    "gn:admin2_code":"1.0",
    "gn:asciiname":"La Penita",
    "gn:country_code":"MX",
    "gn:dem":2600,
    "gn:feature_class":"P",
    "gn:feature_code":"PPL",
    "gn:name":"La Pe\u00f1ita",
    "gn:population":134,
    "gn:timezone":"America/Mexico_City",
    "iso:country":"MX",
    "name:und_x_variant":[
        "La Pe\u00f1ita"
    ],
    "wof:name":"La Penita",
    "wof:placetype":"locality",
    "wof:population":134
},
  "geometry": {"coordinates":[-101.36111,19.43639],"type":"Point"}
}