{
  "type": "Feature",
  "properties": {
    "gn:admin1_code":"30",
    "gn:admin2_code":"144",
    "gn:asciiname":"Colonia los Delfines",
    "gn:country_code":"MX",
    "gn:dem":43,
    "gn:feature_class":"P",
    "gn:feature_code":"PPL",
    "gn:name":"Colonia los Delfines",
    "gn:population":30,
    "gn:timezone":"America/Mexico_City",
    "iso:country":"MX",
    "wof:name":"Colonia los Delfines",
    "wof:placetype":"locality",
    "wof:population":30
},
  "geometry": {"coordinates":[-94.91167,17.73556],"type":"Point"}
}