{
  "type": "Feature",
  "properties": {
    "iso:country":"MX",
    "qs_pg:aaroncc":"MX",
    "qs_pg:name":"Atlatzingo",
    "qs_pg:name_adm0":"M\u00e9xico",
    "qs_pg:name_adm1":"Tlaxcala",
    "qs_pg:photos":26,
    "qs_pg:photos_1k":5,
    "qs_pg:photos_9k":1,
    "qs_pg:photos_9r":2,
    "qs_pg:photos_all":26,
    "qs_pg:photos_sr":2,
    "qs_pg:pop_sr":0,
    "qs_pg:qs_pg_placetype":"neighbourhood",
    "qs_pg:qs_pg_placetype_gp":"Suburb",
    "qs_pg:woe_adm0":23424900,
    "woe:adm0_id":23424900,
    "woe:name_adm0":"M\u00e9xico",
    "woe:name_adm1":"Tlaxcala",
    "woe:placetype":"Suburb",
    "wof:name":"Atlatzingo",
    "wof:placetype":"neighbourhood"
},
  "geometry": {"coordinates":[-98.238,19.311629],"type":"Point"}
}