{
  "type": "Feature",
  "properties": {
    "gn:admin1_code":"21",
    "gn:admin2_code":"116.0",
    "gn:asciiname":"Quiliayo",
    "gn:country_code":"MX",
    "gn:dem":1839,
    "gn:feature_class":"P",
    "gn:feature_code":"PPL",
    "gn:name":"Quiliayo",
    "gn:population":297,
    "gn:timezone":"America/Mexico_City",
    "iso:country":"MX",
    "wof:name":"Quiliayo",
    "wof:placetype":"locality",
    "wof:population":297
},
  "geometry": {"coordinates":[-97.12582999999999,19.30056],"type":"Point"}
}