{
  "type": "Feature",
  "properties": {
    "gn:admin1_code":"21",
    "gn:admin2_code":"213.0",
    "gn:asciiname":"Zihuateutla",
    "gn:country_code":"MX",
    "gn:dem":982,
    "gn:feature_class":"P",
    "gn:feature_code":"PPL",
    "gn:name":"Zihuateutla",
    "gn:population":0,
    "gn:timezone":"America/Mexico_City",
    "iso:country":"MX",
    "name:ceb_x_preferred":[
        "Zihuateutla"
    ],
    "name:epo_x_preferred":[
        "Zihuateutla"
    ],
    "name:eus_x_preferred":[
        "Zihuateutla"
    ],
    "name:rus_x_preferred":[
        "\u0421\u0438\u0443\u0430\u0442\u0435\u0443\u0442\u043b\u0430"
    ],
    "name:spa_x_preferred":[
        "Zihuateutla"
    ],
    "name:srp_x_preferred":[
        "\u041e\u043f\u0448\u0442\u0438\u043d\u0430 \u0417\u0438\u0432\u0430\u0442\u0435\u0443\u0442\u043b\u0430"
    ],
    "name:swe_x_preferred":[
        "Zihuateutla"
    ],
    "name:vie_x_preferred":[
        "Zihuateutla"
    ],
    "wof:name":"Zihuateutla",
    "wof:placetype":"locality"
},
  "geometry": {"coordinates":[-97.88772,20.25074],"type":"Point"}
}