{
  "type": "Feature",
  "properties": {
    "gn:admin1_code":"21",
    "gn:admin2_code":"213.0",
    "gn:asciiname":"Zihuateutla",
    "gn:country_code":"MX",
    "gn:dem":982,
    "gn:feature_class":"P",
    "gn:feature_code":"PPL",
    "gn:name":"Zihuateutla",
    "gn:population":0,
    "gn:timezone":"America/Mexico_City",
    "iso:country":"MX",
    "name:spa_x_preferred":[
        "Zihuateutla"
    ],
    "wof:name":"Zihuateutla",
    "wof:placetype":"locality"
},
  "geometry": {"coordinates":[-97.88772,20.25074],"type":"Point"}
}