{
  "type": "Feature",
  "properties": {
    "gn:admin1_code":"30.0",
    "gn:admin2_code":"161.0",
    "gn:asciiname":"El Polvorin",
    "gn:country_code":"MX",
    "gn:dem":96,
    "gn:feature_class":"P",
    "gn:feature_code":"PPL",
    "gn:name":"El Polvor\u00edn",
    "gn:population":13,
    "gn:timezone":"America/Mexico_City",
    "iso:country":"MX",
    "name:spa_x_preferred":[
        "El Polvor\u00edn"
    ],
    "wof:name":"El Polvorin",
    "wof:placetype":"locality",
    "wof:population":13
},
  "geometry": {"coordinates":[-98.34788,21.5236],"type":"Point"}
}