{
  "type": "Feature",
  "properties": {
    "gn:admin1_code":"6.0",
    "gn:admin2_code":"40.0",
    "gn:asciiname":"Las Gasolinas",
    "gn:country_code":"MX",
    "gn:dem":2197,
    "gn:feature_class":"P",
    "gn:feature_code":"PPL",
    "gn:name":"Las Gasolinas",
    "gn:population":0,
    "gn:timezone":"America/Chihuahua",
    "iso:country":"MX",
    "name:spa_x_preferred":[
        "Las Gasolinas"
    ],
    "name:und_x_variant":[
        "Rancho La Gasolina"
    ],
    "wof:name":"Las Gasolinas",
    "wof:placetype":"locality"
},
  "geometry": {"coordinates":[-108.23707,29.71928],"type":"Point"}
}