{
  "type": "Feature",
  "properties": {
    "gn:admin1_code":"5",
    "gn:admin2_code":"61.0",
    "gn:asciiname":"Velasco Suarez Uno",
    "gn:country_code":"MX",
    "gn:dem":393,
    "gn:feature_class":"P",
    "gn:feature_code":"PPL",
    "gn:name":"Velasco Su\u00e1rez Uno",
    "gn:population":297,
    "gn:timezone":"America/Mexico_City",
    "iso:country":"MX",
    "name:und_x_variant":[
        "Velasco Su\u00e1rez Uno"
    ],
    "wof:name":"Velasco Suarez Uno",
    "wof:placetype":"locality",
    "wof:population":297
},
  "geometry": {"coordinates":[-93.7466,17.07409],"type":"Point"}
}