{
  "type": "Feature",
  "properties": {
    "gn:admin1_code":"27",
    "gn:admin2_code":"4.0",
    "gn:asciiname":"La Lagartera",
    "gn:country_code":"MX",
    "gn:dem":11,
    "gn:feature_class":"P",
    "gn:feature_code":"PPL",
    "gn:name":"La Lagartera",
    "gn:population":0,
    "gn:timezone":"America/Mexico_City",
    "iso:country":"MX",
    "name:spa_x_preferred":[
        "Boquer\u00f3n Quinta Secci\u00f3n"
    ],
    "name:spa_x_variant":[
        "La Lagartera",
        "Boquer\u00f3n",
        "Quinta Secci\u00f3n"
    ],
    "wof:name":"La Lagartera",
    "wof:placetype":"locality"
},
  "geometry": {"coordinates":[-93.01447,17.86928],"type":"Point"}
}