{
  "type": "Feature",
  "properties": {
    "gn:admin1_code":"20",
    "gn:admin2_code":"45.0",
    "gn:asciiname":"De Lache",
    "gn:country_code":"MX",
    "gn:dem":1640,
    "gn:feature_class":"P",
    "gn:feature_code":"PPL",
    "gn:name":"De Lache",
    "gn:population":360,
    "gn:timezone":"America/Mexico_City",
    "iso:country":"MX",
    "wof:name":"De Lache",
    "wof:placetype":"locality",
    "wof:population":360
},
  "geometry": {"coordinates":[-96.83,17.22361],"type":"Point"}
}