{
  "type": "Feature",
  "properties": {
    "gn:admin1_code":"16.0",
    "gn:admin2_code":"19.0",
    "gn:asciiname":"Lorenzo",
    "gn:country_code":"MX",
    "gn:dem":1659,
    "gn:feature_class":"P",
    "gn:feature_code":"PPL",
    "gn:name":"Lorenzo",
    "gn:population":0,
    "gn:timezone":"America/Mexico_City",
    "iso:country":"MX",
    "name:ceb_x_preferred":[
        "Lorenzo"
    ],
    "name:ces_x_preferred":[
        "Lorenzo"
    ],
    "name:deu_x_preferred":[
        "Lorenzo"
    ],
    "name:fra_x_preferred":[
        "Lorenzo"
    ],
    "name:ita_x_preferred":[
        "Lorenzo"
    ],
    "name:jpn_x_preferred":[
        "\u30ed\u30ec\u30f3\u30bd"
    ],
    "name:nor_x_preferred":[
        "Lorenzo"
    ],
    "name:por_x_preferred":[
        "Lorenzo"
    ],
    "name:rus_x_preferred":[
        "\u041b\u043e\u0440\u0435\u043d\u0446\u043e"
    ],
    "name:spa_x_preferred":[
        "Lorenzo"
    ],
    "name:srp_x_preferred":[
        "\u041b\u043e\u0440\u0435\u043d\u0437\u043e"
    ],
    "name:swe_x_preferred":[
        "Lorenzo"
    ],
    "name:ukr_x_preferred":[
        "\u041b\u043e\u0440\u0435\u043d\u0446\u043e"
    ],
    "wof:name":"Lorenzo",
    "wof:placetype":"locality"
},
  "geometry": {"coordinates":[-102.76638,19.71344],"type":"Point"}
}