{
  "type": "Feature",
  "properties": {
    "gn:admin1_code":"10.0",
    "gn:admin2_code":"13.0",
    "gn:asciiname":"El Refugio",
    "gn:country_code":"MX",
    "gn:dem":1249,
    "gn:feature_class":"P",
    "gn:feature_code":"PPL",
    "gn:name":"El Refugio",
    "gn:population":0,
    "gn:timezone":"America/Monterrey",
    "iso:country":"MX",
    "name:ceb_x_preferred":[
        "El Refugio"
    ],
    "name:deu_x_preferred":[
        "El Refugio"
    ],
    "name:ita_x_preferred":[
        "El Refugio"
    ],
    "name:nld_x_preferred":[
        "El Refugio"
    ],
    "name:por_x_preferred":[
        "El Refugio"
    ],
    "name:spa_x_preferred":[
        "Los Acebuches"
    ],
    "name:spa_x_variant":[
        "El Refugio",
        "El refugio"
    ],
    "name:swe_x_preferred":[
        "El Refugio"
    ],
    "name:und_x_variant":[
        "Rancho Los Acebuches",
        "Acebuches"
    ],
    "wof:name":"El Refugio",
    "wof:placetype":"locality"
},
  "geometry": {"coordinates":[-104.35617000000001,26.55847],"type":"Point"}
}