{
  "type": "Feature",
  "properties": {
    "gn:admin1_code":"1.0",
    "gn:admin2_code":"5.0",
    "gn:asciiname":"Pensamiento",
    "gn:country_code":"MX",
    "gn:dem":2213,
    "gn:feature_class":"P",
    "gn:feature_code":"PPL",
    "gn:name":"Pensamiento",
    "gn:population":0,
    "gn:timezone":"America/Mexico_City",
    "iso:country":"MX",
    "wof:name":"Pensamiento",
    "wof:placetype":"locality"
},
  "geometry": {"coordinates":[-102.56578,21.91592],"type":"Point"}
}