{
  "type": "Feature",
  "properties": {
    "gn:admin1_code":"14.0",
    "gn:admin2_code":"35.0",
    "gn:asciiname":"Las Aguilas",
    "gn:country_code":"MX",
    "gn:dem":1985,
    "gn:feature_class":"P",
    "gn:feature_code":"PPL",
    "gn:name":"Las \u00c1guilas",
    "gn:population":0,
    "gn:timezone":"America/Mexico_City",
    "iso:country":"MX",
    "name:spa_x_preferred":[
        "Las \u00c1guilas"
    ],
    "wof:name":"Las Aguilas",
    "wof:placetype":"locality"
},
  "geometry": {"coordinates":[-102.12539,21.67989],"type":"Point"}
}