{
  "type": "Feature",
  "properties": {
    "gn:admin1_code":"30",
    "gn:admin2_code":"61.0",
    "gn:asciiname":"El Saucito (Crispin Gomez Jimenez)",
    "gn:country_code":"MX",
    "gn:dem":24,
    "gn:feature_class":"P",
    "gn:feature_code":"PPL",
    "gn:name":"El Saucito (Crisp\u00edn G\u00f3mez Jim\u00e9nez)",
    "gn:population":6,
    "gn:timezone":"America/Mexico_City",
    "iso:country":"MX",
    "name:und_x_variant":[
        "El Saucito (Crisp\u00edn G\u00f3mez Jim\u00e9nez)"
    ],
    "wof:name":"El Saucito (Crispin Gomez Jimenez)",
    "wof:placetype":"locality",
    "wof:population":6
},
  "geometry": {"coordinates":[-94.18472,17.48444],"type":"Point"}
}