{
  "type": "Feature",
  "properties": {
    "gn:admin1_code":"20.0",
    "gn:admin2_code":"66.0",
    "gn:asciiname":"Caquito",
    "gn:country_code":"MX",
    "gn:dem":230,
    "gn:feature_class":"P",
    "gn:feature_code":"PPL",
    "gn:name":"Caquito",
    "gn:population":0,
    "gn:timezone":"America/Mexico_City",
    "iso:country":"MX",
    "name:spa_x_preferred":[
        "Caquito"
    ],
    "wof:name":"Caquito",
    "wof:placetype":"locality"
},
  "geometry": {"coordinates":[-94.55425,16.61352999999999],"type":"Point"}
}