{
  "type": "Feature",
  "properties": {
    "gn:admin1_code":"1",
    "gn:admin2_code":"9.0",
    "gn:asciiname":"Los Pavoreales (Antonio Munoz Acosta) [Rancho]",
    "gn:country_code":"MX",
    "gn:dem":1921,
    "gn:feature_class":"P",
    "gn:feature_code":"PPL",
    "gn:name":"Los Pavoreales (Antonio Mu\u00f1oz Acosta) [Rancho]",
    "gn:population":6,
    "gn:timezone":"America/Mexico_City",
    "iso:country":"MX",
    "name:und_x_variant":[
        "Los Pavoreales (Antonio Mu\u00f1oz Acosta) [Rancho]"
    ],
    "wof:name":"Los Pavoreales (Antonio Munoz Acosta) [Rancho]",
    "wof:placetype":"locality",
    "wof:population":6
},
  "geometry": {"coordinates":[-102.27611,22.20111],"type":"Point"}
}