{
  "type": "Feature",
  "properties": {
    "gn:admin1_code":"14.0",
    "gn:admin2_code":"15.0",
    "gn:asciiname":"La Tronconera",
    "gn:country_code":"MX",
    "gn:dem":893,
    "gn:feature_class":"P",
    "gn:feature_code":"PPL",
    "gn:name":"La Tronconera",
    "gn:population":0,
    "gn:timezone":"America/Mexico_City",
    "iso:country":"MX",
    "name:spa_x_preferred":[
        "La Tronconera"
    ],
    "wof:name":"La Tronconera",
    "wof:placetype":"locality"
},
  "geometry": {"coordinates":[-104.25608,19.79947],"type":"Point"}
}