{
  "type": "Feature",
  "properties": {
    "gn:admin1_code":"21",
    "gn:admin2_code":"114.0",
    "gn:asciiname":"18 de Marzo",
    "gn:country_code":"MX",
    "gn:dem":2124,
    "gn:feature_class":"P",
    "gn:feature_code":"PPL",
    "gn:name":"18 de Marzo",
    "gn:population":1029,
    "gn:timezone":"America/Mexico_City",
    "iso:country":"MX",
    "wof:name":"18 de Marzo",
    "wof:placetype":"locality",
    "wof:population":1029
},
  "geometry": {"coordinates":[-98.16028,18.96889],"type":"Point"}
}