{
  "type": "Feature",
  "properties": {
    "gn:admin1_code":"28",
    "gn:admin2_code":"37",
    "gn:asciiname":"El Catorce",
    "gn:country_code":"MX",
    "gn:dem":48,
    "gn:feature_class":"P",
    "gn:feature_code":"PPL",
    "gn:name":"El Catorce",
    "gn:population":17,
    "gn:timezone":"America/Monterrey",
    "iso:country":"MX",
    "wof:name":"El Catorce",
    "wof:placetype":"locality",
    "wof:population":17
},
  "geometry": {"coordinates":[-98.13556,23.77556],"type":"Point"}
}