{
  "type": "Feature",
  "properties": {
    "gn:admin1_code":"20",
    "gn:admin2_code":"123.0",
    "gn:asciiname":"Barrio del Rosario",
    "gn:country_code":"MX",
    "gn:dem":1973,
    "gn:feature_class":"P",
    "gn:feature_code":"PPL",
    "gn:name":"Barrio del Rosario",
    "gn:population":92,
    "gn:timezone":"America/Mexico_City",
    "iso:country":"MX",
    "wof:name":"Barrio del Rosario",
    "wof:placetype":"locality",
    "wof:population":92
},
  "geometry": {"coordinates":[-96.94833,16.86889],"type":"Point"}
}