{
  "type": "Feature",
  "properties": {
    "gn:admin1_code":"20",
    "gn:admin2_code":"39",
    "gn:asciiname":"El Tatoto (Palo de Flor)",
    "gn:country_code":"MX",
    "gn:dem":1724,
    "gn:feature_class":"P",
    "gn:feature_code":"PPL",
    "gn:name":"El Tatoto (Palo de Flor)",
    "gn:population":49,
    "gn:timezone":"America/Mexico_City",
    "iso:country":"MX",
    "wof:name":"El Tatoto (Palo de Flor)",
    "wof:placetype":"locality",
    "wof:population":49
},
  "geometry": {"coordinates":[-97.81528,17.80056],"type":"Point"}
}