{
  "type": "Feature",
  "properties": {
    "gn:admin1_code":"24",
    "gn:admin2_code":"11.0",
    "gn:asciiname":"Sermon",
    "gn:country_code":"MX",
    "gn:dem":1162,
    "gn:feature_class":"P",
    "gn:feature_code":"PPL",
    "gn:name":"Serm\u00f3n",
    "gn:population":0,
    "gn:timezone":"America/Mexico_City",
    "iso:country":"MX",
    "name:ara_x_preferred":[
        "\u0645\u0648\u0639\u0638\u0629"
    ],
    "name:bul_x_preferred":[
        "\u041f\u0440\u043e\u043f\u043e\u0432\u0435\u0434"
    ],
    "name:cat_x_preferred":[
        "Serm\u00f3"
    ],
    "name:ces_x_preferred":[
        "K\u00e1z\u00e1n\u00ed"
    ],
    "name:cym_x_preferred":[
        "Pregeth"
    ],
    "name:dan_x_preferred":[
        "Pr\u00e6diken"
    ],
    "name:deu_x_preferred":[
        "Predigt"
    ],
    "name:epo_x_preferred":[
        "Prediko"
    ],
    "name:est_x_preferred":[
        "Jutlus"
    ],
    "name:fas_x_preferred":[
        "\u0645\u0648\u0639\u0638\u0647"
    ],
    "name:fin_x_preferred":[
        "Saarna"
    ],
    "name:fra_x_preferred":[
        "Sermon"
    ],
    "name:heb_x_preferred":[
        "\u05d4\u05d8\u05e4\u05d4"
    ],
    "name:hye_x_preferred":[
        "\u0554\u0561\u0580\u0578\u0566"
    ],
    "name:hyw_x_preferred":[
        "\u0554\u0561\u0580\u0578\u0566"
    ],
    "name:ina_x_preferred":[
        "Predication"
    ],
    "name:ind_x_preferred":[
        "Khotbah"
    ],
    "name:kan_x_preferred":[
        "\u0c89\u0caa\u0ca6\u0cc7\u0cb6 \u0cad\u0cbe\u0cb7\u0ca3"
    ],
    "name:kaz_x_preferred":[
        "\u0423\u0430\u0493\u044b\u0437"
    ],
    "name:msa_x_preferred":[
        "Khutbah"
    ],
    "name:nld_x_preferred":[
        "Preek"
    ],
    "name:nno_x_preferred":[
        "Preike"
    ],
    "name:nor_x_preferred":[
        "Preken"
    ],
    "name:pol_x_preferred":[
        "Kazanie"
    ],
    "name:por_x_preferred":[
        "Serm\u00e3o"
    ],
    "name:roh_x_preferred":[
        "Pregia"
    ],
    "name:rus_x_preferred":[
        "\u041f\u0440\u043e\u043f\u043e\u0432\u0435\u0434\u044c"
    ],
    "name:slv_x_preferred":[
        "Pridiga"
    ],
    "name:spa_x_preferred":[
        "Serm\u00f3n"
    ],
    "name:swe_x_preferred":[
        "Predikan"
    ],
    "name:tur_x_preferred":[
        "Vaaz"
    ],
    "name:ukr_x_preferred":[
        "\u041f\u0440\u043e\u043f\u043e\u0432\u0456\u0434\u044c"
    ],
    "name:urd_x_preferred":[
        "\u0648\u0639\u0638"
    ],
    "name:wln_x_preferred":[
        "Pretchmint"
    ],
    "wof:name":"Sermon",
    "wof:placetype":"locality"
},
  "geometry": {"coordinates":[-100.3152,22.07044],"type":"Point"}
}