{
  "type": "Feature",
  "properties": {
    "gn:admin1_code":"24",
    "gn:admin2_code":"50.0",
    "gn:asciiname":"Ejido el Saucillo",
    "gn:country_code":"MX",
    "gn:dem":1870,
    "gn:feature_class":"P",
    "gn:feature_code":"PPL",
    "gn:name":"Ejido el Saucillo",
    "gn:population":0,
    "gn:timezone":"America/Mexico_City",
    "iso:country":"MX",
    "name:spa_x_preferred":[
        "Ejido el Saucillo"
    ],
    "name:spa_x_variant":[
        "Saucillo"
    ],
    "wof:name":"Ejido el Saucillo",
    "wof:placetype":"locality"
},
  "geometry": {"coordinates":[-100.9949,21.83666],"type":"Point"}
}