{
  "type": "Feature",
  "properties": {
    "gn:admin1_code":"19.0",
    "gn:admin2_code":"5.0",
    "gn:asciiname":"El Pintotle",
    "gn:country_code":"MX",
    "gn:dem":153,
    "gn:feature_class":"P",
    "gn:feature_code":"PPL",
    "gn:name":"El Pintotle",
    "gn:population":0,
    "gn:timezone":"America/Matamoros",
    "iso:country":"MX",
    "name:spa_x_preferred":[
        "El Pintotle"
    ],
    "wof:name":"El Pintotle",
    "wof:placetype":"locality"
},
  "geometry": {"coordinates":[-99.90131,26.97753],"type":"Point"}
}