{
  "type": "Feature",
  "properties": {
    "gn:admin1_code":"11",
    "gn:admin2_code":"30.0",
    "gn:asciiname":"Rancho Nuevo de San Vicente",
    "gn:country_code":"MX",
    "gn:dem":2104,
    "gn:feature_class":"P",
    "gn:feature_code":"PPL",
    "gn:name":"Rancho Nuevo de San Vicente",
    "gn:population":393,
    "gn:timezone":"America/Mexico_City",
    "iso:country":"MX",
    "wof:name":"Rancho Nuevo de San Vicente",
    "wof:placetype":"locality",
    "wof:population":393
},
  "geometry": {"coordinates":[-101.21278,21.60611],"type":"Point"}
}