{
  "type": "Feature",
  "properties": {
    "gn:admin1_code":"30",
    "gn:admin2_code":"201.0",
    "gn:asciiname":"San Geronimo Tonacalco",
    "gn:country_code":"MX",
    "gn:dem":785,
    "gn:feature_class":"P",
    "gn:feature_code":"PPL",
    "gn:name":"San Ger\u00f3nimo Tonacalco",
    "gn:population":156,
    "gn:timezone":"America/Mexico_City",
    "iso:country":"MX",
    "name:und_x_variant":[
        "San Ger\u00f3nimo Tonacalco"
    ],
    "wof:name":"San Geronimo Tonacalco",
    "wof:placetype":"locality",
    "wof:population":156
},
  "geometry": {"coordinates":[-96.97556,18.66028],"type":"Point"}
}