{
  "type": "Feature",
  "properties": {
    "gn:admin1_code":"7",
    "gn:admin2_code":"23.0",
    "gn:asciiname":"La Sabina",
    "gn:country_code":"MX",
    "gn:dem":1747,
    "gn:feature_class":"P",
    "gn:feature_code":"PPL",
    "gn:name":"La Sabina",
    "gn:population":167,
    "gn:timezone":"America/Monterrey",
    "iso:country":"MX",
    "wof:name":"La Sabina",
    "wof:placetype":"locality",
    "wof:population":167
},
  "geometry": {"coordinates":[-102.50306,28.53333],"type":"Point"}
}