{
  "type": "Feature",
  "properties": {
    "gn:admin1_code":"19.0",
    "gn:admin2_code":"42.0",
    "gn:asciiname":"El Reloj",
    "gn:country_code":"MX",
    "gn:dem":199,
    "gn:feature_class":"P",
    "gn:feature_code":"PPL",
    "gn:name":"El Reloj",
    "gn:population":0,
    "gn:timezone":"America/Monterrey",
    "iso:country":"MX",
    "name:spa_x_preferred":[
        "El Reloj"
    ],
    "wof:name":"El Reloj",
    "wof:placetype":"locality"
},
  "geometry": {"coordinates":[-99.63527999999999,25.77134],"type":"Point"}
}