{
  "type": "Feature",
  "properties": {
    "gn:admin1_code":"12.0",
    "gn:admin2_code":"35.0",
    "gn:asciiname":"Colonia Agua Manteca",
    "gn:country_code":"MX",
    "gn:dem":872,
    "gn:feature_class":"P",
    "gn:feature_code":"PPL",
    "gn:name":"Colonia Agua Manteca",
    "gn:population":0,
    "gn:timezone":"America/Mexico_City",
    "iso:country":"MX",
    "name:spa_x_preferred":[
        "Colonia Agua Manteca"
    ],
    "wof:name":"Colonia Agua Manteca",
    "wof:placetype":"locality"
},
  "geometry": {"coordinates":[-99.53915000000001,18.37487],"type":"Point"}
}