{
  "type": "Feature",
  "properties": {
    "gn:admin1_code":"14.0",
    "gn:admin2_code":"115.0",
    "gn:asciiname":"Laborcita",
    "gn:cc2":"MX",
    "gn:country_code":"MX",
    "gn:dem":1288,
    "gn:feature_class":"P",
    "gn:feature_code":"PPL",
    "gn:name":"Laborcita",
    "gn:population":0,
    "gn:timezone":"America/Mexico_City",
    "iso:country":"MX",
    "name:und_x_variant":[
        "Laboracita",
        "Laborcilla",
        "Laborcita"
    ],
    "wof:name":"Laborcita",
    "wof:placetype":"locality"
},
  "geometry": {"coordinates":[-103.68333,22.06667],"type":"Point"}
}