{
  "type": "Feature",
  "properties": {
    "gn:admin1_code":"3",
    "gn:admin2_code":"3.0",
    "gn:asciiname":"Virgen de los Milagros",
    "gn:country_code":"MX",
    "gn:dem":48,
    "gn:feature_class":"P",
    "gn:feature_code":"PPL",
    "gn:name":"Virgen de los Milagros",
    "gn:population":0,
    "gn:timezone":"America/Mazatlan",
    "iso:country":"MX",
    "name:spa_x_preferred":[
        "Virgen de los Milagros"
    ],
    "name:spa_x_variant":[
        "La Ardilla"
    ],
    "wof:name":"Virgen de los Milagros",
    "wof:placetype":"locality"
},
  "geometry": {"coordinates":[-110.4744,24.12295],"type":"Point"}
}