{
  "type": "Feature",
  "properties": {
    "gn:admin1_code":"26",
    "gn:admin2_code":"18",
    "gn:asciiname":"Nueve y Media y 5 de Febrero (Bloque 1008)",
    "gn:country_code":"MX",
    "gn:dem":37,
    "gn:feature_class":"P",
    "gn:feature_code":"PPL",
    "gn:name":"Nueve y Media y 5 de Febrero (Bloque 1008)",
    "gn:population":10,
    "gn:timezone":"America/Hermosillo",
    "iso:country":"MX",
    "wof:name":"Nueve y Media y 5 de Febrero (Bloque 1008)",
    "wof:placetype":"locality",
    "wof:population":10
},
  "geometry": {"coordinates":[-109.93333,27.34472],"type":"Point"}
}