{
  "type": "Feature",
  "properties": {
    "gn:admin1_code":"2.0",
    "gn:admin2_code":"2.0",
    "gn:asciiname":"Pachuca",
    "gn:country_code":"MX",
    "gn:dem":30,
    "gn:feature_class":"P",
    "gn:feature_code":"PPL",
    "gn:name":"Pachuca",
    "gn:population":0,
    "gn:timezone":"America/Tijuana",
    "iso:country":"MX",
    "name:spa_x_preferred":[
        "Pachuca"
    ],
    "name:und_x_variant":[
        "Ejido Pachuca"
    ],
    "wof:name":"Pachuca",
    "wof:placetype":"locality"
},
  "geometry": {"coordinates":[-114.82426,32.61182],"type":"Point"}
}