{
  "type": "Feature",
  "properties": {
    "gn:admin1_code":"2.0",
    "gn:admin2_code":"2.0",
    "gn:asciiname":"Pachuca",
    "gn:country_code":"MX",
    "gn:dem":30,
    "gn:feature_class":"P",
    "gn:feature_code":"PPL",
    "gn:name":"Pachuca",
    "gn:population":0,
    "gn:timezone":"America/Tijuana",
    "iso:country":"MX",
    "name:ara_x_preferred":[
        "\u0628\u0627\u062a\u0634\u0648\u0643\u0627"
    ],
    "name:bul_x_preferred":[
        "\u041f\u0430\u0447\u0443\u043a\u0430"
    ],
    "name:eus_x_preferred":[
        "Pachuca"
    ],
    "name:fas_x_preferred":[
        "\u067e\u0627\u0686\u0648\u06a9\u0627"
    ],
    "name:fin_x_preferred":[
        "Pachuca"
    ],
    "name:fra_x_preferred":[
        "Pachuca"
    ],
    "name:heb_x_preferred":[
        "\u05e4\u05e6'\u05d5\u05e7\u05d4"
    ],
    "name:hye_x_preferred":[
        "\u054a\u0561\u0579\u0578\u0582\u056f\u0561"
    ],
    "name:ilo_x_preferred":[
        "Pachuca"
    ],
    "name:ita_x_preferred":[
        "Pachuca"
    ],
    "name:jpn_x_preferred":[
        "\u30d1\u30c1\u30e5\u30fc\u30ab"
    ],
    "name:kat_x_preferred":[
        "\u10de\u10d0\u10e9\u10e3\u10d9\u10d0"
    ],
    "name:kor_x_preferred":[
        "\ud30c\ucd94\uce74"
    ],
    "name:lat_x_preferred":[
        "Pasuca Sotoensis"
    ],
    "name:lav_x_preferred":[
        "Pa\u010duka"
    ],
    "name:lit_x_preferred":[
        "Pa\u010duka"
    ],
    "name:nld_x_preferred":[
        "Pachuca"
    ],
    "name:nno_x_preferred":[
        "Pachuca"
    ],
    "name:pol_x_preferred":[
        "Pachuca"
    ],
    "name:ron_x_preferred":[
        "Pachuca"
    ],
    "name:rus_x_preferred":[
        "\u041f\u0430\u0447\u0443\u043a\u0430-\u0434\u0435-\u0421\u043e\u0442\u043e"
    ],
    "name:sco_x_preferred":[
        "Pachuca"
    ],
    "name:spa_x_preferred":[
        "Pachuca"
    ],
    "name:swa_x_preferred":[
        "Pachuca"
    ],
    "name:tgl_x_preferred":[
        "Pachuca"
    ],
    "name:tur_x_preferred":[
        "Pachuca"
    ],
    "name:ukr_x_preferred":[
        "\u041f\u0430\u0447\u0443\u043a\u0430-\u0434\u0435-\u0421\u043e\u0442\u043e"
    ],
    "name:und_x_variant":[
        "Ejido Pachuca"
    ],
    "name:urd_x_preferred":[
        "\u067e\u0627\u0686\u0648\u06a9\u0627"
    ],
    "name:war_x_preferred":[
        "Pachuca"
    ],
    "name:wuu_x_preferred":[
        "\u5e15\u4e18\u5361"
    ],
    "name:zho_x_preferred":[
        "\u5e15\u4e18\u5361"
    ],
    "wof:name":"Pachuca",
    "wof:placetype":"locality"
},
  "geometry": {"coordinates":[-114.82426,32.61182],"type":"Point"}
}