{
  "type": "Feature",
  "properties": {
    "gn:admin1_code":"19.0",
    "gn:admin2_code":"32.0",
    "gn:asciiname":"El Cibolo",
    "gn:country_code":"MX",
    "gn:dem":249,
    "gn:feature_class":"P",
    "gn:feature_code":"PPL",
    "gn:name":"El C\u00edbolo",
    "gn:population":0,
    "gn:timezone":"America/Monterrey",
    "iso:country":"MX",
    "name:spa_x_preferred":[
        "El C\u00edbolo"
    ],
    "name:und_x_variant":[
        "Rancho El Cibolo"
    ],
    "wof:name":"El Cibolo",
    "wof:placetype":"locality"
},
  "geometry": {"coordinates":[-100.28579000000001,27.05369],"type":"Point"}
}