{
  "type": "Feature",
  "properties": {
    "gn:admin1_code":"30",
    "gn:admin2_code":"127",
    "gn:asciiname":"La Paloma",
    "gn:country_code":"MX",
    "gn:dem":3068,
    "gn:feature_class":"P",
    "gn:feature_code":"PPL",
    "gn:name":"La Paloma",
    "gn:population":22,
    "gn:timezone":"America/Mexico_City",
    "iso:country":"MX",
    "wof:name":"La Paloma",
    "wof:placetype":"locality",
    "wof:population":22
},
  "geometry": {"coordinates":[-97.20193999999999,19.02889],"type":"Point"}
}