{
  "type": "Feature",
  "properties": {
    "gn:admin1_code":"10.0",
    "gn:admin2_code":"4.0",
    "gn:asciiname":"El Huerfano",
    "gn:country_code":"MX",
    "gn:dem":2350,
    "gn:feature_class":"P",
    "gn:feature_code":"PPL",
    "gn:name":"El Hu\u00e9rfano",
    "gn:population":0,
    "gn:timezone":"America/Monterrey",
    "iso:country":"MX",
    "name:spa_x_preferred":[
        "El Hu\u00e9rfano"
    ],
    "wof:name":"El Huerfano",
    "wof:placetype":"locality"
},
  "geometry": {"coordinates":[-103.91613,24.20776],"type":"Point"}
}