{
  "type": "Feature",
  "properties": {
    "gn:admin1_code":"11",
    "gn:admin2_code":"7.0",
    "gn:asciiname":"Elias Gonzalez Ramirez (El Charro)",
    "gn:country_code":"MX",
    "gn:dem":1769,
    "gn:feature_class":"P",
    "gn:feature_code":"PPL",
    "gn:name":"El\u00edas Gonz\u00e1lez Ram\u00edrez (El Charro)",
    "gn:population":8,
    "gn:timezone":"America/Mexico_City",
    "iso:country":"MX",
    "name:und_x_variant":[
        "El\u00edas Gonz\u00e1lez Ram\u00edrez (El Charro)"
    ],
    "wof:name":"Elias Gonzalez Ramirez (El Charro)",
    "wof:placetype":"locality",
    "wof:population":8
},
  "geometry": {"coordinates":[-100.78082999999999,20.41944],"type":"Point"}
}