{
  "type": "Feature",
  "properties": {
    "gn:admin1_code":"23.0",
    "gn:admin2_code":"2.0",
    "gn:asciiname":"El Triunfo",
    "gn:country_code":"MX",
    "gn:dem":3,
    "gn:feature_class":"P",
    "gn:feature_code":"PPL",
    "gn:name":"El Triunfo",
    "gn:population":0,
    "gn:timezone":"America/Cancun",
    "iso:country":"MX",
    "name:spa_x_preferred":[
        "El Triunfo"
    ],
    "wof:name":"El Triunfo",
    "wof:placetype":"locality"
},
  "geometry": {"coordinates":[-87.49509999999999,19.25722],"type":"Point"}
}