{
  "type": "Feature",
  "properties": {
    "gn:admin1_code":"10",
    "gn:admin2_code":"13.0",
    "gn:asciiname":"San Jose de Bellavista",
    "gn:country_code":"MX",
    "gn:dem":1139,
    "gn:feature_class":"P",
    "gn:feature_code":"PPL",
    "gn:name":"San Jos\u00e9 de Bellavista",
    "gn:population":3,
    "gn:timezone":"America/Monterrey",
    "iso:country":"MX",
    "wof:name":"San Jose de Bellavista",
    "wof:placetype":"locality",
    "wof:population":3
},
  "geometry": {"coordinates":[-103.75024000000001,26.09506],"type":"Point"}
}