{
  "type": "Feature",
  "properties": {
    "gn:admin1_code":"7",
    "gn:admin2_code":"30.0",
    "gn:asciiname":"Las Calandrias",
    "gn:country_code":"MX",
    "gn:dem":1943,
    "gn:feature_class":"P",
    "gn:feature_code":"PPL",
    "gn:name":"Las Calandrias",
    "gn:population":0,
    "gn:timezone":"America/Monterrey",
    "iso:country":"MX",
    "name:spa_x_preferred":[
        "Las Calandrias"
    ],
    "wof:name":"Las Calandrias",
    "wof:placetype":"locality"
},
  "geometry": {"coordinates":[-101.17225000000001,25.36282000000001],"type":"Point"}
}