{
  "type": "Feature",
  "properties": {
    "gn:admin1_code":"14",
    "gn:admin2_code":"87.0",
    "gn:asciiname":"Mesa el Gringo",
    "gn:country_code":"MX",
    "gn:dem":1411,
    "gn:feature_class":"P",
    "gn:feature_code":"PPL",
    "gn:name":"Mesa el Gringo",
    "gn:population":0,
    "gn:timezone":"America/Mexico_City",
    "iso:country":"MX",
    "name:spa_x_preferred":[
        "Mesa el Gringo"
    ],
    "wof:name":"Mesa el Gringo",
    "wof:placetype":"locality"
},
  "geometry": {"coordinates":[-103.16764999999999,19.40539],"type":"Point"}
}