{
  "type": "Feature",
  "properties": {
    "gn:admin1_code":"30",
    "gn:admin2_code":"33.0",
    "gn:asciiname":"Barra de Cazones",
    "gn:country_code":"MX",
    "gn:dem":18,
    "gn:feature_class":"P",
    "gn:feature_code":"PPL",
    "gn:name":"Barra de Cazones",
    "gn:population":1111,
    "gn:timezone":"America/Mexico_City",
    "iso:country":"MX",
    "wof:name":"Barra de Cazones",
    "wof:placetype":"locality",
    "wof:population":1111
},
  "geometry": {"coordinates":[-97.2025,20.72222],"type":"Point"}
}