{
  "type": "Feature",
  "properties": {
    "gn:admin1_code":"11",
    "gn:admin2_code":"17.0",
    "gn:asciiname":"Nuevo Ejido de San Lorenzo",
    "gn:country_code":"MX",
    "gn:dem":1741,
    "gn:feature_class":"P",
    "gn:feature_code":"PPL",
    "gn:name":"Nuevo Ejido de San Lorenzo",
    "gn:population":442,
    "gn:timezone":"America/Mexico_City",
    "iso:country":"MX",
    "wof:name":"Nuevo Ejido de San Lorenzo",
    "wof:placetype":"locality",
    "wof:population":442
},
  "geometry": {"coordinates":[-101.43694000000001,20.77556],"type":"Point"}
}