{
  "type": "Feature",
  "properties": {
    "gn:admin1_code":"13",
    "gn:admin2_code":"68",
    "gn:asciiname":"Tilasco",
    "gn:country_code":"MX",
    "gn:dem":626,
    "gn:feature_class":"P",
    "gn:feature_code":"PPL",
    "gn:name":"Tilasco",
    "gn:population":16,
    "gn:timezone":"America/Mexico_City",
    "iso:country":"MX",
    "wof:name":"Tilasco",
    "wof:placetype":"locality",
    "wof:population":16
},
  "geometry": {"coordinates":[-98.54965,20.77068],"type":"Point"}
}