{
  "type": "Feature",
  "properties": {
    "gn:admin1_code":"14",
    "gn:admin2_code":"73",
    "gn:asciiname":"Potrero de la Tuna (Ejido la Jara)",
    "gn:country_code":"MX",
    "gn:dem":1807,
    "gn:feature_class":"P",
    "gn:feature_code":"PPL",
    "gn:name":"Potrero de la Tuna (Ejido la Jara)",
    "gn:population":46,
    "gn:timezone":"America/Mexico_City",
    "iso:country":"MX",
    "wof:name":"Potrero de la Tuna (Ejido la Jara)",
    "wof:placetype":"locality",
    "wof:population":46
},
  "geometry": {"coordinates":[-102.37417000000001,21.33083],"type":"Point"}
}