{
  "type": "Feature",
  "properties": {
    "gn:admin1_code":"10",
    "gn:admin2_code":"4.0",
    "gn:asciiname":"Las Liebres",
    "gn:country_code":"MX",
    "gn:dem":1948,
    "gn:feature_class":"P",
    "gn:feature_code":"PPL",
    "gn:name":"Las Liebres",
    "gn:population":0,
    "gn:timezone":"America/Monterrey",
    "iso:country":"MX",
    "name:spa_x_preferred":[
        "Las Liebres"
    ],
    "wof:name":"Las Liebres",
    "wof:placetype":"locality"
},
  "geometry": {"coordinates":[-103.64537,24.7021],"type":"Point"}
}