{
  "type": "Feature",
  "properties": {
    "gn:admin1_code":"5.0",
    "gn:asciiname":"El Morro",
    "gn:country_code":"MX",
    "gn:dem":9,
    "gn:feature_class":"P",
    "gn:feature_code":"PPL",
    "gn:name":"El Morro",
    "gn:population":0,
    "gn:timezone":"America/Mexico_City",
    "iso:country":"MX",
    "name:ceb_x_preferred":[
        "El Morro"
    ],
    "name:deu_x_preferred":[
        "El Morro"
    ],
    "name:fra_x_preferred":[
        "El Morro"
    ],
    "name:spa_x_preferred":[
        "El Morro"
    ],
    "name:swe_x_preferred":[
        "El Morro"
    ],
    "wof:name":"El Morro",
    "wof:placetype":"locality"
},
  "geometry": {"coordinates":[-93.65804,15.87597],"type":"Point"}
}