{
  "type": "Feature",
  "properties": {
    "gn:admin1_code":"8.0",
    "gn:admin2_code":"2.0",
    "gn:asciiname":"San Juan",
    "gn:country_code":"MX",
    "gn:dem":490,
    "gn:feature_class":"P",
    "gn:feature_code":"PPL",
    "gn:name":"San Juan",
    "gn:population":0,
    "gn:timezone":"America/Mexico_City",
    "iso:country":"MX",
    "name:spa_x_preferred":[
        "San Juan"
    ],
    "wof:name":"San Juan",
    "wof:placetype":"locality"
},
  "geometry": {"coordinates":[-103.56310000000001,19.14054],"type":"Point"}
}