{
  "type": "Feature",
  "properties": {
    "gn:admin1_code":"15",
    "gn:admin2_code":"66.0",
    "gn:asciiname":"San Miguel Piru (El Piru)",
    "gn:country_code":"MX",
    "gn:dem":1305,
    "gn:feature_class":"P",
    "gn:feature_code":"PPL",
    "gn:name":"San Miguel Piru (El Piru)",
    "gn:population":247,
    "gn:timezone":"America/Mexico_City",
    "iso:country":"MX",
    "wof:name":"San Miguel Piru (El Piru)",
    "wof:placetype":"locality",
    "wof:population":247
},
  "geometry": {"coordinates":[-100.31505,19.11756],"type":"Point"}
}