{
  "type": "Feature",
  "properties": {
    "gn:admin1_code":"12.0",
    "gn:admin2_code":"48.0",
    "gn:asciiname":"La Lajita",
    "gn:country_code":"MX",
    "gn:dem":161,
    "gn:feature_class":"P",
    "gn:feature_code":"PPL",
    "gn:name":"La Lajita",
    "gn:population":152,
    "gn:timezone":"America/Mexico_City",
    "iso:country":"MX",
    "wof:name":"La Lajita",
    "wof:placetype":"locality",
    "wof:population":152
},
  "geometry": {"coordinates":[-101.04192999999999,17.44175],"type":"Point"}
}