{
  "type": "Feature",
  "properties": {
    "gn:admin1_code":"30",
    "gn:admin2_code":"133",
    "gn:asciiname":"Bugambilias",
    "gn:country_code":"MX",
    "gn:dem":33,
    "gn:feature_class":"P",
    "gn:feature_code":"PPL",
    "gn:name":"Bugambilias",
    "gn:population":13,
    "gn:timezone":"America/Mexico_City",
    "iso:country":"MX",
    "wof:name":"Bugambilias",
    "wof:placetype":"locality",
    "wof:population":13
},
  "geometry": {"coordinates":[-97.82944000000001,22.15972],"type":"Point"}
}