{
  "type": "Feature",
  "properties": {
    "gn:admin1_code":"30.0",
    "gn:admin2_code":"4.0",
    "gn:asciiname":"Callejones",
    "gn:country_code":"MX",
    "gn:dem":410,
    "gn:feature_class":"P",
    "gn:feature_code":"PPL",
    "gn:name":"Callejones",
    "gn:population":0,
    "gn:timezone":"America/Mexico_City",
    "iso:country":"MX",
    "name:spa_x_preferred":[
        "Callejones"
    ],
    "wof:name":"Callejones",
    "wof:placetype":"locality"
},
  "geometry": {"coordinates":[-96.62549,19.47214],"type":"Point"}
}