{
  "type": "Feature",
  "properties": {
    "gn:admin1_code":"6",
    "gn:admin2_code":"7.0",
    "gn:asciiname":"Coquenas",
    "gn:country_code":"MX",
    "gn:dem":2681,
    "gn:feature_class":"P",
    "gn:feature_code":"PPL",
    "gn:name":"Coquenas",
    "gn:population":60,
    "gn:timezone":"America/Chihuahua",
    "iso:country":"MX",
    "wof:name":"Coquenas",
    "wof:placetype":"locality",
    "wof:population":60
},
  "geometry": {"coordinates":[-106.4289,26.3802],"type":"Point"}
}