{
  "type": "Feature",
  "properties": {
    "gn:admin1_code":"28.0",
    "gn:admin2_code":"3.0",
    "gn:asciiname":"La Sevillana",
    "gn:country_code":"MX",
    "gn:dem":28,
    "gn:feature_class":"P",
    "gn:feature_code":"PPL",
    "gn:name":"La Sevillana",
    "gn:population":0,
    "gn:timezone":"America/Monterrey",
    "iso:country":"MX",
    "name:spa_x_preferred":[
        "La Sevillana"
    ],
    "wof:name":"La Sevillana",
    "wof:placetype":"locality"
},
  "geometry": {"coordinates":[-97.94777999999999,22.48583],"type":"Point"}
}