{
  "type": "Feature",
  "properties": {
    "gn:admin1_code":"14.0",
    "gn:admin2_code":"21.0",
    "gn:asciiname":"La Zopilota",
    "gn:country_code":"MX",
    "gn:dem":292,
    "gn:feature_class":"P",
    "gn:feature_code":"PPL",
    "gn:name":"La Zopilota",
    "gn:population":0,
    "gn:timezone":"America/Mexico_City",
    "iso:country":"MX",
    "name:spa_x_preferred":[
        "La Zopilota"
    ],
    "wof:name":"La Zopilota",
    "wof:placetype":"locality"
},
  "geometry": {"coordinates":[-104.49524,19.60023],"type":"Point"}
}