{
  "type": "Feature",
  "properties": {
    "gn:admin1_code":"10",
    "gn:admin2_code":"32.0",
    "gn:asciiname":"San Gregorio de Bosos",
    "gn:country_code":"MX",
    "gn:dem":770,
    "gn:feature_class":"P",
    "gn:feature_code":"PPL",
    "gn:name":"San Gregorio de Bos\u00f3s",
    "gn:population":67,
    "gn:timezone":"America/Monterrey",
    "iso:country":"MX",
    "wof:name":"San Gregorio de Bosos",
    "wof:placetype":"locality",
    "wof:population":67
},
  "geometry": {"coordinates":[-106.20117999999999,24.83998],"type":"Point"}
}