{
  "type": "Feature",
  "properties": {
    "gn:admin1_code":"16.0",
    "gn:admin2_code":"6.0",
    "gn:asciiname":"Mezquital",
    "gn:country_code":"MX",
    "gn:dem":209,
    "gn:feature_class":"P",
    "gn:feature_code":"PPL",
    "gn:name":"Mezquital",
    "gn:population":0,
    "gn:timezone":"America/Mexico_City",
    "iso:country":"MX",
    "name:spa_x_preferred":[
        "Mezquital"
    ],
    "name:spa_x_variant":[
        "Quelele"
    ],
    "wof:name":"Mezquital",
    "wof:placetype":"locality"
},
  "geometry": {"coordinates":[-102.34905000000001,18.91427],"type":"Point"}
}