{
  "type": "Feature",
  "properties": {
    "gn:admin1_code":"23",
    "gn:asciiname":"Trinidad Hernandez",
    "gn:country_code":"MX",
    "gn:dem":107,
    "gn:feature_class":"P",
    "gn:feature_code":"PPL",
    "gn:name":"Trinidad Hern\u00e1ndez",
    "gn:population":0,
    "gn:timezone":"America/Cancun",
    "iso:country":"MX",
    "name:spa_x_preferred":[
        "Trinidad Hern\u00e1ndez"
    ],
    "wof:name":"Trinidad Hernandez",
    "wof:placetype":"locality"
},
  "geometry": {"coordinates":[-89.13815,18.76969],"type":"Point"}
}