{
  "type": "Feature",
  "properties": {
    "gn:admin1_code":"30.0",
    "gn:admin2_code":"83.0",
    "gn:asciiname":"Rancho Nuevo",
    "gn:country_code":"MX",
    "gn:dem":258,
    "gn:feature_class":"P",
    "gn:feature_code":"PPL",
    "gn:name":"Rancho Nuevo",
    "gn:population":294,
    "gn:timezone":"America/Mexico_City",
    "iso:country":"MX",
    "name:spa_x_preferred":[
        "Rancho Nuevo"
    ],
    "wof:name":"Rancho Nuevo",
    "wof:placetype":"locality",
    "wof:population":294
},
  "geometry": {"coordinates":[-98.08417,20.68472],"type":"Point"}
}