{
  "type": "Feature",
  "properties": {
    "gn:admin1_code":"19.0",
    "gn:admin2_code":"17.0",
    "gn:asciiname":"Los Pocitos",
    "gn:country_code":"MX",
    "gn:dem":1883,
    "gn:feature_class":"P",
    "gn:feature_code":"PPL",
    "gn:name":"Los Pocitos",
    "gn:population":0,
    "gn:timezone":"America/Monterrey",
    "iso:country":"MX",
    "name:spa_x_preferred":[
        "Los Positos"
    ],
    "name:spa_x_variant":[
        "Los Pocitos"
    ],
    "wof:name":"Los Pocitos",
    "wof:placetype":"locality"
},
  "geometry": {"coordinates":[-100.31433,24.76638],"type":"Point"}
}