{
  "type": "Feature",
  "properties": {
    "gn:admin1_code":"32",
    "gn:admin2_code":"28",
    "gn:asciiname":"El Coyotillo",
    "gn:country_code":"MX",
    "gn:dem":1316,
    "gn:feature_class":"P",
    "gn:feature_code":"PPL",
    "gn:name":"El Coyotillo",
    "gn:population":12,
    "gn:timezone":"America/Mexico_City",
    "iso:country":"MX",
    "wof:name":"El Coyotillo",
    "wof:placetype":"locality",
    "wof:population":12
},
  "geometry": {"coordinates":[-103.39944,21.13833],"type":"Point"}
}