{
  "type": "Feature",
  "properties": {
    "gn:admin1_code":"26",
    "gn:admin2_code":"66.0",
    "gn:asciiname":"La Pitahaya",
    "gn:cc2":"MX",
    "gn:country_code":"MX",
    "gn:dem":438,
    "gn:feature_class":"P",
    "gn:feature_code":"PPL",
    "gn:name":"La Pitahaya",
    "gn:population":0,
    "gn:timezone":"America/Hermosillo",
    "iso:country":"MX",
    "name:und_x_variant":[
        "Pitahaya",
        "La Pitahaya"
    ],
    "wof:name":"La Pitahaya",
    "wof:placetype":"locality"
},
  "geometry": {"coordinates":[-110.40000000000001,29.03333],"type":"Point"}
}