{
  "type": "Feature",
  "properties": {
    "gn:admin1_code":"11",
    "gn:admin2_code":"44.0",
    "gn:asciiname":"Santa Fe (Caseta 40)",
    "gn:country_code":"MX",
    "gn:dem":1728,
    "gn:feature_class":"P",
    "gn:feature_code":"PPL",
    "gn:name":"Santa Fe (Caseta 40)",
    "gn:population":6,
    "gn:timezone":"America/Mexico_City",
    "iso:country":"MX",
    "wof:name":"Santa Fe (Caseta 40)",
    "wof:placetype":"locality",
    "wof:population":6
},
  "geometry": {"coordinates":[-101.04971999999999,20.55278],"type":"Point"}
}