{
  "type": "Feature",
  "properties": {
    "gn:admin1_code":"5",
    "gn:admin2_code":"107.0",
    "gn:asciiname":"Sierra Morena",
    "gn:country_code":"MX",
    "gn:dem":1172,
    "gn:feature_class":"P",
    "gn:feature_code":"PPL",
    "gn:name":"Sierra Morena",
    "gn:population":163,
    "gn:timezone":"America/Mexico_City",
    "iso:country":"MX",
    "wof:name":"Sierra Morena",
    "wof:placetype":"locality",
    "wof:population":163
},
  "geometry": {"coordinates":[-93.59028000000001,16.15222],"type":"Point"}
}