{
  "type": "Feature",
  "properties": {
    "gn:admin1_code":"21",
    "gn:admin2_code":"179.0",
    "gn:asciiname":"Jose Maria Morelos",
    "gn:country_code":"MX",
    "gn:dem":2483,
    "gn:feature_class":"P",
    "gn:feature_code":"PPL",
    "gn:name":"Jos\u00e9 Mar\u00eda Morelos",
    "gn:population":1366,
    "gn:timezone":"America/Mexico_City",
    "iso:country":"MX",
    "name:spa_x_preferred":[
        "Jos\u00e9 Mar\u00eda Morelos"
    ],
    "wof:name":"Jose Maria Morelos",
    "wof:placetype":"locality",
    "wof:population":1366
},
  "geometry": {"coordinates":[-97.46809,19.14147],"type":"Point"}
}