{
  "type": "Feature",
  "properties": {
    "gn:admin1_code":"19.0",
    "gn:asciiname":"El Temporal de los Silva",
    "gn:country_code":"MX",
    "gn:dem":309,
    "gn:feature_class":"P",
    "gn:feature_code":"PPL",
    "gn:name":"El Temporal de los Silva",
    "gn:population":0,
    "gn:timezone":"America/Monterrey",
    "iso:country":"MX",
    "name:spa_x_preferred":[
        "El Temporal de los Silva"
    ],
    "wof:name":"El Temporal de los Silva",
    "wof:placetype":"locality"
},
  "geometry": {"coordinates":[-99.47747,24.85928],"type":"Point"}
}