{
  "type": "Feature",
  "properties": {
    "gn:admin1_code":"12",
    "gn:admin2_code":"47",
    "gn:asciiname":"Zalquitzaya",
    "gn:country_code":"MX",
    "gn:dem":2304,
    "gn:feature_class":"P",
    "gn:feature_code":"PPL",
    "gn:name":"Zalquitzaya",
    "gn:population":39,
    "gn:timezone":"America/Mexico_City",
    "iso:country":"MX",
    "wof:name":"Zalquitzaya",
    "wof:placetype":"locality",
    "wof:population":39
},
  "geometry": {"coordinates":[-99.79115,18.60658],"type":"Point"}
}