{
  "type": "Feature",
  "properties": {
    "gn:admin1_code":"7",
    "gn:admin2_code":"11.0",
    "gn:asciiname":"Las Cuatas",
    "gn:country_code":"MX",
    "gn:dem":1495,
    "gn:feature_class":"P",
    "gn:feature_code":"PPL",
    "gn:name":"Las Cuatas",
    "gn:population":0,
    "gn:timezone":"America/Monterrey",
    "iso:country":"MX",
    "wof:name":"Las Cuatas",
    "wof:placetype":"locality"
},
  "geometry": {"coordinates":[-101.55704,25.38572000000001],"type":"Point"}
}