{
  "type": "Feature",
  "properties": {
    "gn:admin1_code":"11",
    "gn:admin2_code":"24.0",
    "gn:asciiname":"Padres Martires",
    "gn:country_code":"MX",
    "gn:dem":1718,
    "gn:feature_class":"P",
    "gn:feature_code":"PPL",
    "gn:name":"Padres M\u00e1rtires",
    "gn:population":231,
    "gn:timezone":"America/Mexico_City",
    "iso:country":"MX",
    "name:und_x_variant":[
        "Padres M\u00e1rtires"
    ],
    "wof:name":"Padres Martires",
    "wof:placetype":"locality",
    "wof:population":231
},
  "geometry": {"coordinates":[-101.37333,20.55083],"type":"Point"}
}