{
  "type": "Feature",
  "properties": {
    "gn:admin1_code":"14.0",
    "gn:admin2_code":"35.0",
    "gn:asciiname":"Atotonilquillo",
    "gn:country_code":"MX",
    "gn:dem":1748,
    "gn:feature_class":"P",
    "gn:feature_code":"PPL",
    "gn:name":"Atotonilquillo",
    "gn:population":0,
    "gn:timezone":"America/Mexico_City",
    "iso:country":"MX",
    "name:spa_x_preferred":[
        "Atotonilquillo"
    ],
    "wof:name":"Atotonilquillo",
    "wof:placetype":"locality"
},
  "geometry": {"coordinates":[-102.39126,21.50186],"type":"Point"}
}