{
  "type": "Feature",
  "properties": {
    "gn:admin1_code":"25",
    "gn:admin2_code":"13.0",
    "gn:asciiname":"El Ebanal",
    "gn:country_code":"MX",
    "gn:dem":105,
    "gn:feature_class":"P",
    "gn:feature_code":"PPL",
    "gn:name":"El Ebanal",
    "gn:population":0,
    "gn:timezone":"America/Mazatlan",
    "iso:country":"MX",
    "name:spa_x_preferred":[
        "El Ebanal"
    ],
    "wof:name":"El Ebanal",
    "wof:placetype":"locality"
},
  "geometry": {"coordinates":[-107.86162,25.13705],"type":"Point"}
}