{
  "type": "Feature",
  "properties": {
    "gn:admin1_code":"19.0",
    "gn:admin2_code":"20.0",
    "gn:asciiname":"El Chacual",
    "gn:country_code":"MX",
    "gn:dem":156,
    "gn:feature_class":"P",
    "gn:feature_code":"PPL",
    "gn:name":"El Chacual",
    "gn:population":0,
    "gn:timezone":"America/Monterrey",
    "iso:country":"MX",
    "name:spa_x_preferred":[
        "El Chacual"
    ],
    "wof:name":"El Chacual",
    "wof:placetype":"locality"
},
  "geometry": {"coordinates":[-99.13415000000001,25.73599],"type":"Point"}
}