{
  "type": "Feature",
  "properties": {
    "gn:admin1_code":"30",
    "gn:admin2_code":"142.0",
    "gn:asciiname":"Los Cedros",
    "gn:country_code":"MX",
    "gn:dem":72,
    "gn:feature_class":"P",
    "gn:feature_code":"PPL",
    "gn:name":"Los Cedros",
    "gn:population":5,
    "gn:timezone":"America/Mexico_City",
    "iso:country":"MX",
    "wof:name":"Los Cedros",
    "wof:placetype":"locality",
    "wof:population":5
},
  "geometry": {"coordinates":[-95.13,17.72778],"type":"Point"}
}