{
  "type": "Feature",
  "properties": {
    "gn:admin1_code":"11",
    "gn:admin2_code":"39.0",
    "gn:asciiname":"La Boveda",
    "gn:country_code":"MX",
    "gn:dem":1822,
    "gn:feature_class":"P",
    "gn:feature_code":"PPL",
    "gn:name":"La B\u00f3veda",
    "gn:population":96,
    "gn:timezone":"America/Mexico_City",
    "iso:country":"MX",
    "name:und_x_variant":[
        "La B\u00f3veda"
    ],
    "wof:name":"La Boveda",
    "wof:placetype":"locality",
    "wof:population":96
},
  "geometry": {"coordinates":[-100.75306,20.32111],"type":"Point"}
}