{
  "type": "Feature",
  "properties": {
    "gn:admin1_code":"6.0",
    "gn:admin2_code":"20.0",
    "gn:asciiname":"El Zapote de Chinipas",
    "gn:country_code":"MX",
    "gn:dem":430,
    "gn:feature_class":"P",
    "gn:feature_code":"PPL",
    "gn:name":"El Zapote de Chinipas",
    "gn:population":0,
    "gn:timezone":"America/Chihuahua",
    "iso:country":"MX",
    "name:spa_x_preferred":[
        "El Zapote de Chinipas"
    ],
    "name:und_x_variant":[
        "Zapote",
        "El Zapote",
        "El Zapote de Ch\u00ednipas"
    ],
    "wof:name":"El Zapote de Chinipas",
    "wof:placetype":"locality"
},
  "geometry": {"coordinates":[-108.51494,27.37979],"type":"Point"}
}