{
  "type": "Feature",
  "properties": {
    "gn:admin1_code":"24",
    "gn:admin2_code":"56.0",
    "gn:asciiname":"San Elias",
    "gn:country_code":"MX",
    "gn:dem":1610,
    "gn:feature_class":"P",
    "gn:feature_code":"PPL",
    "gn:name":"San Elias",
    "gn:population":0,
    "gn:timezone":"America/Mexico_City",
    "iso:country":"MX",
    "wof:name":"San Elias",
    "wof:placetype":"locality"
},
  "geometry": {"coordinates":[-100.85768,22.66882],"type":"Point"}
}