{
  "type": "Feature",
  "properties": {
    "gn:admin1_code":"6.0",
    "gn:admin2_code":"46.0",
    "gn:asciiname":"La Mesita",
    "gn:country_code":"MX",
    "gn:dem":1676,
    "gn:feature_class":"P",
    "gn:feature_code":"PPL",
    "gn:name":"La Mesita",
    "gn:population":0,
    "gn:timezone":"America/Mazatlan",
    "iso:country":"MX",
    "name:spa_x_preferred":[
        "La Mesita"
    ],
    "wof:name":"La Mesita",
    "wof:placetype":"locality"
},
  "geometry": {"coordinates":[-107.86606999999999,26.50597],"type":"Point"}
}