{
  "type": "Feature",
  "properties": {
    "gn:admin1_code":"5",
    "gn:admin2_code":"115.0",
    "gn:asciiname":"San Felipe Jatate",
    "gn:country_code":"MX",
    "gn:dem":200,
    "gn:feature_class":"P",
    "gn:feature_code":"PPL",
    "gn:name":"San Felipe Jatate",
    "gn:population":285,
    "gn:timezone":"America/Mexico_City",
    "iso:country":"MX",
    "wof:name":"San Felipe Jatate",
    "wof:placetype":"locality",
    "wof:population":285
},
  "geometry": {"coordinates":[-91.25833,16.2275],"type":"Point"}
}