{
  "type": "Feature",
  "properties": {
    "gn:admin1_code":"16",
    "gn:admin2_code":"2",
    "gn:asciiname":"La Venadera",
    "gn:country_code":"MX",
    "gn:dem":1182,
    "gn:feature_class":"P",
    "gn:feature_code":"PPL",
    "gn:name":"La Venadera",
    "gn:population":14,
    "gn:timezone":"America/Mexico_City",
    "iso:country":"MX",
    "wof:name":"La Venadera",
    "wof:placetype":"locality",
    "wof:population":14
},
  "geometry": {"coordinates":[-102.8425,18.57833],"type":"Point"}
}