{
  "type": "Feature",
  "properties": {
    "gn:admin1_code":"19",
    "gn:admin2_code":"45",
    "gn:asciiname":"San Miguel",
    "gn:country_code":"MX",
    "gn:dem":444,
    "gn:feature_class":"P",
    "gn:feature_code":"PPL",
    "gn:name":"San Miguel",
    "gn:population":24,
    "gn:timezone":"America/Monterrey",
    "iso:country":"MX",
    "wof:name":"San Miguel",
    "wof:placetype":"locality",
    "wof:population":24
},
  "geometry": {"coordinates":[-100.26555999999999,25.90944],"type":"Point"}
}