{
  "type": "Feature",
  "properties": {
    "gn:admin1_code":"20.0",
    "gn:admin2_code":"312.0",
    "gn:asciiname":"Yutakoyoo",
    "gn:country_code":"MX",
    "gn:dem":234,
    "gn:feature_class":"P",
    "gn:feature_code":"PPL",
    "gn:name":"Yutakoyoo",
    "gn:population":0,
    "gn:timezone":"America/Mexico_City",
    "iso:country":"MX",
    "name:spa_x_preferred":[
        "Yutakoyoo"
    ],
    "name:spa_x_variant":[
        "Yutacoyo"
    ],
    "wof:name":"Yutakoyoo",
    "wof:placetype":"locality"
},
  "geometry": {"coordinates":[-97.98621,16.46475],"type":"Point"}
}