{
  "type": "Feature",
  "properties": {
    "gn:admin1_code":"30",
    "gn:admin2_code":"143.0",
    "gn:asciiname":"El Zapotal",
    "gn:country_code":"MX",
    "gn:dem":49,
    "gn:feature_class":"P",
    "gn:feature_code":"PPL",
    "gn:name":"El Zapotal",
    "gn:population":601,
    "gn:timezone":"America/Mexico_City",
    "iso:country":"MX",
    "name:fra_x_preferred":[
        "El Zapotal"
    ],
    "name:spa_x_preferred":[
        "El Zapotal"
    ],
    "wof:name":"El Zapotal",
    "wof:placetype":"locality",
    "wof:population":601
},
  "geometry": {"coordinates":[-95.39,18.28139],"type":"Point"}
}