{
  "type": "Feature",
  "properties": {
    "gn:admin1_code":"11",
    "gn:admin2_code":"29.0",
    "gn:asciiname":"Ejido Gomez Villanueva",
    "gn:country_code":"MX",
    "gn:dem":1953,
    "gn:feature_class":"P",
    "gn:feature_code":"PPL",
    "gn:name":"Ejido G\u00f3mez Villanueva",
    "gn:population":226,
    "gn:timezone":"America/Mexico_City",
    "iso:country":"MX",
    "name:und_x_variant":[
        "Ejido G\u00f3mez Villanueva"
    ],
    "wof:name":"Ejido Gomez Villanueva",
    "wof:placetype":"locality",
    "wof:population":226
},
  "geometry": {"coordinates":[-100.80500000000001,21.33889],"type":"Point"}
}