{
  "type": "Feature",
  "properties": {
    "gn:admin1_code":"28.0",
    "gn:admin2_code":"42.0",
    "gn:asciiname":"Las Lajitas",
    "gn:country_code":"MX",
    "gn:dem":317,
    "gn:feature_class":"P",
    "gn:feature_code":"PPL",
    "gn:name":"Las Lajitas",
    "gn:population":0,
    "gn:timezone":"America/Monterrey",
    "iso:country":"MX",
    "name:ceb_x_preferred":[
        "Las Lajitas"
    ],
    "name:por_x_preferred":[
        "Las Lajitas"
    ],
    "name:spa_x_preferred":[
        "Las Lajitas"
    ],
    "name:urd_x_preferred":[
        "\u0644\u0627\u0633 \u0644\u0627\u062c\u06cc\u0679\u0627\u0633"
    ],
    "wof:name":"Las Lajitas",
    "wof:placetype":"locality"
},
  "geometry": {"coordinates":[-99.381,24.51159],"type":"Point"}
}