{
  "type": "Feature",
  "properties": {
    "gn:admin1_code":"10",
    "gn:admin2_code":"5.0",
    "gn:asciiname":"Carpintero",
    "gn:country_code":"MX",
    "gn:dem":1912,
    "gn:feature_class":"P",
    "gn:feature_code":"PPL",
    "gn:name":"Carpintero",
    "gn:population":0,
    "gn:timezone":"America/Monterrey",
    "iso:country":"MX",
    "name:spa_x_preferred":[
        "Carpintero"
    ],
    "wof:name":"Carpintero",
    "wof:placetype":"locality"
},
  "geometry": {"coordinates":[-104.72274,24.27571],"type":"Point"}
}