{
  "type": "Feature",
  "properties": {
    "gn:admin1_code":"5",
    "gn:admin2_code":"107",
    "gn:asciiname":"Rancho Bonito",
    "gn:country_code":"MX",
    "gn:dem":611,
    "gn:feature_class":"P",
    "gn:feature_code":"PPL",
    "gn:name":"Rancho Bonito",
    "gn:population":12,
    "gn:timezone":"America/Mexico_City",
    "iso:country":"MX",
    "wof:name":"Rancho Bonito",
    "wof:placetype":"locality",
    "wof:population":12
},
  "geometry": {"coordinates":[-93.28361,16.13944],"type":"Point"}
}