{
  "type": "Feature",
  "properties": {
    "gn:admin1_code":"11",
    "gn:admin2_code":"28.0",
    "gn:asciiname":"El Coyol",
    "gn:country_code":"MX",
    "gn:dem":1735,
    "gn:feature_class":"P",
    "gn:feature_code":"PPL",
    "gn:name":"El Coyol",
    "gn:population":82,
    "gn:timezone":"America/Mexico_City",
    "iso:country":"MX",
    "wof:name":"El Coyol",
    "wof:placetype":"locality",
    "wof:population":82
},
  "geometry": {"coordinates":[-101.005,20.26139],"type":"Point"}
}