{
  "type": "Feature",
  "properties": {
    "gn:admin1_code":"11",
    "gn:admin2_code":"26",
    "gn:asciiname":"San Ramon Viejo",
    "gn:country_code":"MX",
    "gn:dem":1766,
    "gn:feature_class":"P",
    "gn:feature_code":"PPL",
    "gn:name":"San Ram\u00f3n Viejo",
    "gn:population":48,
    "gn:timezone":"America/Mexico_City",
    "iso:country":"MX",
    "name:und_x_variant":[
        "San Ram\u00f3n Viejo"
    ],
    "wof:name":"San Ramon Viejo",
    "wof:placetype":"locality",
    "wof:population":48
},
  "geometry": {"coordinates":[-101.71083,20.78889],"type":"Point"}
}