{
  "type": "Feature",
  "properties": {
    "gn:admin1_code":"12",
    "gn:admin2_code":"11",
    "gn:asciiname":"Colonia la Cima",
    "gn:country_code":"MX",
    "gn:dem":39,
    "gn:feature_class":"P",
    "gn:feature_code":"PPL",
    "gn:name":"Colonia la Cima",
    "gn:population":9,
    "gn:timezone":"America/Mexico_City",
    "iso:country":"MX",
    "wof:name":"Colonia la Cima",
    "wof:placetype":"locality",
    "wof:population":9
},
  "geometry": {"coordinates":[-100.30643999999999,17.07001],"type":"Point"}
}