{
  "type": "Feature",
  "properties": {
    "gn:admin1_code":"25",
    "gn:admin2_code":"4.0",
    "gn:asciiname":"Santa Catarina",
    "gn:country_code":"MX",
    "gn:dem":189,
    "gn:feature_class":"P",
    "gn:feature_code":"PPL",
    "gn:name":"Santa Catarina",
    "gn:population":408,
    "gn:timezone":"America/Mazatlan",
    "iso:country":"MX",
    "name:spa_x_preferred":[
        "Santa Catarina"
    ],
    "wof:name":"Santa Catarina",
    "wof:placetype":"locality",
    "wof:population":408
},
  "geometry": {"coordinates":[-106.08125,23.4106],"type":"Point"}
}