{
  "type": "Feature",
  "properties": {
    "gn:admin1_code":"6",
    "gn:admin2_code":"27",
    "gn:asciiname":"Rochivo",
    "gn:country_code":"MX",
    "gn:dem":2237,
    "gn:feature_class":"P",
    "gn:feature_code":"PPL",
    "gn:name":"Rochivo",
    "gn:population":12,
    "gn:timezone":"America/Chihuahua",
    "iso:country":"MX",
    "wof:name":"Rochivo",
    "wof:placetype":"locality",
    "wof:population":12
},
  "geometry": {"coordinates":[-107.17768,27.35687],"type":"Point"}
}