{
  "type": "Feature",
  "properties": {
    "gn:admin1_code":"16",
    "gn:admin2_code":"34.0",
    "gn:asciiname":"La Mina",
    "gn:country_code":"MX",
    "gn:dem":2421,
    "gn:feature_class":"P",
    "gn:feature_code":"PPL",
    "gn:name":"La Mina",
    "gn:population":136,
    "gn:timezone":"America/Mexico_City",
    "iso:country":"MX",
    "name:ita_x_preferred":[
        "La Mina"
    ],
    "wof:name":"La Mina",
    "wof:placetype":"locality",
    "wof:population":136
},
  "geometry": {"coordinates":[-100.77388999999999,19.63833],"type":"Point"}
}