{
  "type": "Feature",
  "properties": {
    "gn:admin1_code":"16",
    "gn:admin2_code":"37.0",
    "gn:asciiname":"Ojo de Agua (Ojo de Agua de Manza)",
    "gn:country_code":"MX",
    "gn:dem":2018,
    "gn:feature_class":"P",
    "gn:feature_code":"PPL",
    "gn:name":"Ojo de Agua (Ojo de Agua de Manza)",
    "gn:population":101,
    "gn:timezone":"America/Mexico_City",
    "iso:country":"MX",
    "wof:name":"Ojo de Agua (Ojo de Agua de Manza)",
    "wof:placetype":"locality",
    "wof:population":101
},
  "geometry": {"coordinates":[-101.57805999999999,19.92917000000001],"type":"Point"}
}