{
  "type": "Feature",
  "properties": {
    "gn:admin1_code":"12",
    "gn:admin2_code":"56.0",
    "gn:asciiname":"Pochotillo",
    "gn:country_code":"MX",
    "gn:dem":363,
    "gn:feature_class":"P",
    "gn:feature_code":"PPL",
    "gn:name":"Pochotillo",
    "gn:population":0,
    "gn:timezone":"America/Mexico_City",
    "iso:country":"MX",
    "name:spa_x_preferred":[
        "Pochotillo"
    ],
    "wof:name":"Pochotillo",
    "wof:placetype":"locality"
},
  "geometry": {"coordinates":[-99.42725,17.02075],"type":"Point"}
}