{
  "type": "Feature",
  "properties": {
    "gn:admin1_code":"5",
    "gn:admin2_code":"32.0",
    "gn:asciiname":"Ovando Turquia",
    "gn:country_code":"MX",
    "gn:dem":174,
    "gn:feature_class":"P",
    "gn:feature_code":"PPL",
    "gn:name":"Ovando Turqu\u00eda",
    "gn:population":367,
    "gn:timezone":"America/Mexico_City",
    "iso:country":"MX",
    "wof:name":"Ovando Turquia",
    "wof:placetype":"locality",
    "wof:population":367
},
  "geometry": {"coordinates":[-92.63472,15.35917],"type":"Point"}
}