{
  "type": "Feature",
  "properties": {
    "gn:admin1_code":"5.0",
    "gn:admin2_code":"40.0",
    "gn:asciiname":"Canton Cuba",
    "gn:country_code":"MX",
    "gn:dem":70,
    "gn:feature_class":"P",
    "gn:feature_code":"PPL",
    "gn:name":"Cant\u00f3n Cuba",
    "gn:population":0,
    "gn:timezone":"America/Mexico_City",
    "iso:country":"MX",
    "name:spa_x_preferred":[
        "Cant\u00f3n Cuba"
    ],
    "wof:name":"Canton Cuba",
    "wof:placetype":"locality"
},
  "geometry": {"coordinates":[-92.46274,15.16389],"type":"Point"}
}