{
  "type": "Feature",
  "properties": {
    "gn:admin1_code":"30.0",
    "gn:admin2_code":"123.0",
    "gn:asciiname":"Mahuaves",
    "gn:country_code":"MX",
    "gn:dem":11,
    "gn:feature_class":"P",
    "gn:feature_code":"PPL",
    "gn:name":"Mahuaves",
    "gn:population":0,
    "gn:timezone":"America/Mexico_City",
    "iso:country":"MX",
    "name:spa_x_preferred":[
        "Mahuaves"
    ],
    "wof:name":"Mahuaves",
    "wof:placetype":"locality"
},
  "geometry": {"coordinates":[-98.17812000000001,22.10898],"type":"Point"}
}