{
  "type": "Feature",
  "properties": {
    "gn:admin1_code":"6",
    "gn:admin2_code":"29.0",
    "gn:asciiname":"Paraje Los Sotoles",
    "gn:country_code":"MX",
    "gn:dem":2198,
    "gn:feature_class":"P",
    "gn:feature_code":"PPL",
    "gn:name":"Paraje Los Sotoles",
    "gn:population":0,
    "gn:timezone":"America/Chihuahua",
    "iso:country":"MX",
    "name:spa_x_preferred":[
        "Paraje Los Sotoles"
    ],
    "wof:name":"Paraje Los Sotoles",
    "wof:placetype":"locality"
},
  "geometry": {"coordinates":[-107.33766,26.59819],"type":"Point"}
}