{
  "type": "Feature",
  "properties": {
    "gn:admin1_code":"18",
    "gn:admin2_code":"4.0",
    "gn:asciiname":"San Isidro",
    "gn:country_code":"MX",
    "gn:dem":29,
    "gn:feature_class":"P",
    "gn:feature_code":"PPL",
    "gn:name":"San Isidro",
    "gn:population":266,
    "gn:timezone":"America/Mazatlan",
    "iso:country":"MX",
    "wof:name":"San Isidro",
    "wof:placetype":"locality",
    "wof:population":266
},
  "geometry": {"coordinates":[-105.16583,21.27389],"type":"Point"}
}