{
  "type": "Feature",
  "properties": {
    "gn:admin1_code":"15",
    "gn:admin2_code":"63.0",
    "gn:asciiname":"El Capulin",
    "gn:country_code":"MX",
    "gn:dem":2467,
    "gn:feature_class":"P",
    "gn:feature_code":"PPL",
    "gn:name":"El Capul\u00edn",
    "gn:population":105,
    "gn:timezone":"America/Mexico_City",
    "iso:country":"MX",
    "wof:name":"El Capulin",
    "wof:placetype":"locality",
    "wof:population":105
},
  "geometry": {"coordinates":[-99.35832000000001,18.9721],"type":"Point"}
}