{
  "type": "Feature",
  "properties": {
    "gn:admin1_code":"21",
    "gn:admin2_code":"77.0",
    "gn:asciiname":"La Cruz de Chaca",
    "gn:country_code":"MX",
    "gn:dem":896,
    "gn:feature_class":"P",
    "gn:feature_code":"PPL",
    "gn:name":"La Cruz de Chaca",
    "gn:population":405,
    "gn:timezone":"America/Mexico_City",
    "iso:country":"MX",
    "wof:name":"La Cruz de Chaca",
    "wof:placetype":"locality",
    "wof:population":405
},
  "geometry": {"coordinates":[-97.71666999999999,20.03556],"type":"Point"}
}