{
  "type": "Feature",
  "properties": {
    "gn:admin1_code":"5",
    "gn:admin2_code":"107",
    "gn:asciiname":"La Nueva Dos",
    "gn:country_code":"MX",
    "gn:dem":699,
    "gn:feature_class":"P",
    "gn:feature_code":"PPL",
    "gn:name":"La Nueva Dos",
    "gn:population":17,
    "gn:timezone":"America/Mexico_City",
    "iso:country":"MX",
    "wof:name":"La Nueva Dos",
    "wof:placetype":"locality",
    "wof:population":17
},
  "geometry": {"coordinates":[-93.36,16.075],"type":"Point"}
}