{
  "type": "Feature",
  "properties": {
    "gn:admin1_code":"18",
    "gn:admin2_code":"7.0",
    "gn:asciiname":"La Anona",
    "gn:country_code":"MX",
    "gn:dem":1096,
    "gn:feature_class":"P",
    "gn:feature_code":"PPL",
    "gn:name":"La Anona",
    "gn:population":5,
    "gn:timezone":"America/Mazatlan",
    "iso:country":"MX",
    "wof:name":"La Anona",
    "wof:placetype":"locality",
    "wof:population":5
},
  "geometry": {"coordinates":[-104.42194000000001,21.10194],"type":"Point"}
}