{
  "type": "Feature",
  "properties": {
    "gn:admin1_code":"15",
    "gn:admin2_code":"112",
    "gn:asciiname":"Fraccionamiento la Arrastradera",
    "gn:country_code":"MX",
    "gn:dem":2523,
    "gn:feature_class":"P",
    "gn:feature_code":"PPL",
    "gn:name":"Fraccionamiento la Arrastradera",
    "gn:population":49,
    "gn:timezone":"America/Mexico_City",
    "iso:country":"MX",
    "wof:name":"Fraccionamiento la Arrastradera",
    "wof:placetype":"locality",
    "wof:population":49
},
  "geometry": {"coordinates":[-99.47756,19.76717],"type":"Point"}
}