{
  "type": "Feature",
  "properties": {
    "gn:admin1_code":"31",
    "gn:admin2_code":"17.0",
    "gn:asciiname":"Kancabdzonot",
    "gn:country_code":"MX",
    "gn:dem":32,
    "gn:feature_class":"P",
    "gn:feature_code":"PPL",
    "gn:name":"Kancabdzonot",
    "gn:population":0,
    "gn:timezone":"America/Merida",
    "iso:country":"MX",
    "name:und_x_variant":[
        "Kancabzonot",
        "Kancabdzonot"
    ],
    "wof:name":"Kancabdzonot",
    "wof:placetype":"locality"
},
  "geometry": {"coordinates":[-88.61201,20.37269],"type":"Point"}
}