{
  "type": "Feature",
  "properties": {
    "gn:admin1_code":"26.0",
    "gn:admin2_code":"55.0",
    "gn:asciiname":"El Muelle",
    "gn:country_code":"MX",
    "gn:dem":7,
    "gn:feature_class":"P",
    "gn:feature_code":"PPL",
    "gn:name":"El Muelle",
    "gn:population":0,
    "gn:timezone":"America/Hermosillo",
    "iso:country":"MX",
    "name:spa_x_preferred":[
        "El Muelle"
    ],
    "wof:name":"El Muelle",
    "wof:placetype":"locality"
},
  "geometry": {"coordinates":[-114.58566,31.78497],"type":"Point"}
}