{
  "type": "Feature",
  "properties": {
    "gn:admin1_code":"21",
    "gn:admin2_code":"111",
    "gn:asciiname":"El Jonote",
    "gn:country_code":"MX",
    "gn:dem":466,
    "gn:feature_class":"P",
    "gn:feature_code":"PPL",
    "gn:name":"El Jonote",
    "gn:population":23,
    "gn:timezone":"America/Mexico_City",
    "iso:country":"MX",
    "wof:name":"El Jonote",
    "wof:placetype":"locality",
    "wof:population":23
},
  "geometry": {"coordinates":[-97.92191,20.54726],"type":"Point"}
}