{
  "type": "Feature",
  "properties": {
    "gn:admin1_code":"18.0",
    "gn:admin2_code":"1.0",
    "gn:asciiname":"Buenavista (Las Paredes)",
    "gn:country_code":"MX",
    "gn:dem":12,
    "gn:feature_class":"P",
    "gn:feature_code":"PPL",
    "gn:name":"Buenavista (Las Paredes)",
    "gn:population":254,
    "gn:timezone":"America/Mazatlan",
    "iso:country":"MX",
    "wof:name":"Buenavista (Las Paredes)",
    "wof:placetype":"locality",
    "wof:population":254
},
  "geometry": {"coordinates":[-105.45291,22.46444],"type":"Point"}
}