{
  "type": "Feature",
  "properties": {
    "gn:admin1_code":"10.0",
    "gn:admin2_code":"39.0",
    "gn:asciiname":"El Nuevo Porvenir",
    "gn:country_code":"MX",
    "gn:dem":1971,
    "gn:feature_class":"P",
    "gn:feature_code":"PPL",
    "gn:name":"El Nuevo Porvenir",
    "gn:population":560,
    "gn:timezone":"America/Monterrey",
    "iso:country":"MX",
    "wof:name":"El Nuevo Porvenir",
    "wof:placetype":"locality",
    "wof:population":560
},
  "geometry": {"coordinates":[-104.97028,24.855],"type":"Point"}
}