{
  "type": "Feature",
  "properties": {
    "gn:admin1_code":"4.0",
    "gn:asciiname":"Cristo Negro",
    "gn:country_code":"MX",
    "gn:dem":5,
    "gn:feature_class":"P",
    "gn:feature_code":"PPL",
    "gn:name":"Cristo Negro",
    "gn:population":0,
    "gn:timezone":"America/Merida",
    "iso:country":"MX",
    "name:spa_x_preferred":[
        "Cristo Negro"
    ],
    "wof:name":"Cristo Negro",
    "wof:placetype":"locality"
},
  "geometry": {"coordinates":[-91.30043999999999,18.25608],"type":"Point"}
}