{
  "type": "Feature",
  "properties": {
    "gn:admin1_code":"13",
    "gn:admin2_code":"5.0",
    "gn:asciiname":"El Mezquite",
    "gn:country_code":"MX",
    "gn:dem":2114,
    "gn:feature_class":"P",
    "gn:feature_code":"PPL",
    "gn:name":"El Mezquite",
    "gn:population":0,
    "gn:timezone":"America/Mexico_City",
    "iso:country":"MX",
    "wof:name":"El Mezquite",
    "wof:placetype":"locality"
},
  "geometry": {"coordinates":[-99.05,20.15],"type":"Point"}
}