{
  "type": "Feature",
  "properties": {
    "gn:admin1_code":"30",
    "gn:admin2_code":"181.0",
    "gn:asciiname":"Canal Veintiseis",
    "gn:country_code":"MX",
    "gn:dem":54,
    "gn:feature_class":"P",
    "gn:feature_code":"PPL",
    "gn:name":"Canal Veintis\u00e9is",
    "gn:population":85,
    "gn:timezone":"America/Mexico_City",
    "iso:country":"MX",
    "name:und_x_variant":[
        "Canal Veintis\u00e9is"
    ],
    "wof:name":"Canal Veintiseis",
    "wof:placetype":"locality",
    "wof:population":85
},
  "geometry": {"coordinates":[-96.24861,18.74444],"type":"Point"}
}