{
  "type": "Feature",
  "properties": {
    "gn:admin1_code":"18.0",
    "gn:admin2_code":"17.0",
    "gn:asciiname":"Jumatan",
    "gn:country_code":"MX",
    "gn:dem":389,
    "gn:feature_class":"P",
    "gn:feature_code":"PPL",
    "gn:name":"Jumat\u00e1n",
    "gn:population":0,
    "gn:timezone":"America/Mazatlan",
    "iso:country":"MX",
    "name:spa_x_preferred":[
        "Jumat\u00e1n"
    ],
    "wof:name":"Jumatan",
    "wof:placetype":"locality"
},
  "geometry": {"coordinates":[-105.03216,21.6429],"type":"Point"}
}