{
  "type": "Feature",
  "properties": {
    "gn:admin1_code":"24",
    "gn:admin2_code":"29.0",
    "gn:asciiname":"El Aquiche",
    "gn:country_code":"MX",
    "gn:dem":89,
    "gn:feature_class":"P",
    "gn:feature_code":"PPL",
    "gn:name":"El Aquiche",
    "gn:population":5,
    "gn:timezone":"America/Mexico_City",
    "iso:country":"MX",
    "wof:name":"El Aquiche",
    "wof:placetype":"locality",
    "wof:population":5
},
  "geometry": {"coordinates":[-98.63527999999999,21.44861],"type":"Point"}
}