{
  "type": "Feature",
  "properties": {
    "gn:admin1_code":"25",
    "gn:admin2_code":"17",
    "gn:asciiname":"La Lagunilla",
    "gn:country_code":"MX",
    "gn:dem":60,
    "gn:feature_class":"P",
    "gn:feature_code":"PPL",
    "gn:name":"La Lagunilla",
    "gn:population":22,
    "gn:timezone":"America/Mazatlan",
    "iso:country":"MX",
    "wof:name":"La Lagunilla",
    "wof:placetype":"locality",
    "wof:population":22
},
  "geometry": {"coordinates":[-108.24068,25.80858],"type":"Point"}
}