{
  "type": "Feature",
  "properties": {
    "gn:admin1_code":"20",
    "gn:admin2_code":"39.0",
    "gn:asciiname":"Colonia San Mateo",
    "gn:country_code":"MX",
    "gn:dem":1608,
    "gn:feature_class":"P",
    "gn:feature_code":"PPL",
    "gn:name":"Colonia San Mateo",
    "gn:population":346,
    "gn:timezone":"America/Mexico_City",
    "iso:country":"MX",
    "wof:name":"Colonia San Mateo",
    "wof:placetype":"locality",
    "wof:population":346
},
  "geometry": {"coordinates":[-97.76027999999999,17.81389],"type":"Point"}
}