{
  "type": "Feature",
  "properties": {
    "gn:admin1_code":"30.0",
    "gn:admin2_code":"33.0",
    "gn:asciiname":"La Curva",
    "gn:country_code":"MX",
    "gn:dem":28,
    "gn:feature_class":"P",
    "gn:feature_code":"PPL",
    "gn:name":"La Curva",
    "gn:population":242,
    "gn:timezone":"America/Mexico_City",
    "iso:country":"MX",
    "name:spa_x_preferred":[
        "La Curva"
    ],
    "name:spa_x_variant":[
        "Kil\u00f3metro Treinta y Tres"
    ],
    "wof:name":"La Curva",
    "wof:placetype":"locality",
    "wof:population":242
},
  "geometry": {"coordinates":[-97.35028,20.6825],"type":"Point"}
}