{
  "type": "Feature",
  "properties": {
    "gn:admin1_code":"16.0",
    "gn:admin2_code":"9.0",
    "gn:asciiname":"Colimilla",
    "gn:country_code":"MX",
    "gn:dem":1397,
    "gn:feature_class":"P",
    "gn:feature_code":"PPL",
    "gn:name":"Colimilla",
    "gn:population":0,
    "gn:timezone":"America/Mexico_City",
    "iso:country":"MX",
    "name:spa_x_preferred":[
        "Colimilla"
    ],
    "name:und_x_variant":[
        "Colimillas"
    ],
    "wof:name":"Colimilla",
    "wof:placetype":"locality"
},
  "geometry": {"coordinates":[-101.76433,19.07125],"type":"Point"}
}