{
  "type": "Feature",
  "properties": {
    "gn:admin1_code":"20",
    "gn:admin2_code":"64.0",
    "gn:asciiname":"Colonia Morelos",
    "gn:country_code":"MX",
    "gn:dem":650,
    "gn:feature_class":"P",
    "gn:feature_code":"PPL",
    "gn:name":"Colonia Morelos",
    "gn:population":57,
    "gn:timezone":"America/Mexico_City",
    "iso:country":"MX",
    "wof:name":"Colonia Morelos",
    "wof:placetype":"locality",
    "wof:population":57
},
  "geometry": {"coordinates":[-95.98444000000001,16.60111],"type":"Point"}
}