{
  "type": "Feature",
  "properties": {
    "gn:admin1_code":"22",
    "gn:admin2_code":"14.0",
    "gn:asciiname":"Paseos del Pedregal",
    "gn:country_code":"MX",
    "gn:dem":1921,
    "gn:feature_class":"P",
    "gn:feature_code":"PPL",
    "gn:name":"Paseos del Pedregal",
    "gn:population":2432,
    "gn:timezone":"America/Mexico_City",
    "iso:country":"MX",
    "wof:name":"Paseos del Pedregal",
    "wof:placetype":"locality",
    "wof:population":2432
},
  "geometry": {"coordinates":[-100.39806,20.66417],"type":"Point"}
}