{
  "type": "Feature",
  "properties": {
    "gn:admin1_code":"11.0",
    "gn:asciiname":"El Guayabo de Ascencio",
    "gn:country_code":"MX",
    "gn:dem":1960,
    "gn:feature_class":"P",
    "gn:feature_code":"PPL",
    "gn:name":"El Guayabo de Ascencio",
    "gn:population":0,
    "gn:timezone":"America/Mexico_City",
    "iso:country":"MX",
    "name:spa_x_preferred":[
        "El Guayabo de Ascencio"
    ],
    "name:spa_x_variant":[
        "Guayabo de Ascencio"
    ],
    "wof:name":"El Guayabo de Ascencio",
    "wof:placetype":"locality"
},
  "geometry": {"coordinates":[-101.87538000000001,20.59566],"type":"Point"}
}