{
  "type": "Feature",
  "properties": {
    "gn:admin1_code":"19.0",
    "gn:asciiname":"El Lucero",
    "gn:country_code":"MX",
    "gn:dem":338,
    "gn:feature_class":"P",
    "gn:feature_code":"PPL",
    "gn:name":"El Lucero",
    "gn:population":0,
    "gn:timezone":"America/Monterrey",
    "iso:country":"MX",
    "name:spa_x_preferred":[
        "El Lucero"
    ],
    "name:spa_x_variant":[
        "Lucero"
    ],
    "wof:name":"El Lucero",
    "wof:placetype":"locality"
},
  "geometry": {"coordinates":[-100.07034,25.84132],"type":"Point"}
}