{
  "type": "Feature",
  "properties": {
    "gn:admin1_code":"15.0",
    "gn:asciiname":"Acalpican de Morelos",
    "gn:country_code":"MX",
    "gn:dem":27,
    "gn:feature_class":"P",
    "gn:feature_code":"PPL",
    "gn:name":"Acalpican de Morelos",
    "gn:population":0,
    "gn:timezone":"America/Mexico_City",
    "iso:country":"MX",
    "name:spa_x_preferred":[
        "Acalpican de Morelos"
    ],
    "wof:name":"Acalpican de Morelos",
    "wof:placetype":"locality"
},
  "geometry": {"coordinates":[-102.34032999999999,18.01854],"type":"Point"}
}