{
  "type": "Feature",
  "properties": {
    "gn:admin1_code":"30.0",
    "gn:admin2_code":"127.0",
    "gn:asciiname":"Chilapilla",
    "gn:country_code":"MX",
    "gn:dem":2202,
    "gn:feature_class":"P",
    "gn:feature_code":"PPL",
    "gn:name":"Chilapilla",
    "gn:population":0,
    "gn:timezone":"America/Mexico_City",
    "iso:country":"MX",
    "name:spa_x_preferred":[
        "Chilapilla"
    ],
    "wof:name":"Chilapilla",
    "wof:placetype":"locality"
},
  "geometry": {"coordinates":[-97.13945,18.99478],"type":"Point"}
}