{
  "type": "Feature",
  "properties": {
    "gn:admin1_code":"31",
    "gn:admin2_code":"102.0",
    "gn:asciiname":"El Gato Negro",
    "gn:country_code":"MX",
    "gn:dem":23,
    "gn:feature_class":"P",
    "gn:feature_code":"PPL",
    "gn:name":"El Gato Negro",
    "gn:population":8,
    "gn:timezone":"America/Merida",
    "iso:country":"MX",
    "wof:name":"El Gato Negro",
    "wof:placetype":"locality",
    "wof:population":8
},
  "geometry": {"coordinates":[-88.16694,20.69444],"type":"Point"}
}