{
  "type": "Feature",
  "properties": {
    "gn:admin1_code":"16.0",
    "gn:admin2_code":"92.0",
    "gn:asciiname":"La Junta de los Arrayanes",
    "gn:country_code":"MX",
    "gn:dem":562,
    "gn:feature_class":"P",
    "gn:feature_code":"PPL",
    "gn:name":"La Junta de los Arrayanes",
    "gn:population":0,
    "gn:timezone":"America/Mexico_City",
    "iso:country":"MX",
    "name:spa_x_preferred":[
        "La Junta de los Arrayanes"
    ],
    "wof:name":"La Junta de los Arrayanes",
    "wof:placetype":"locality"
},
  "geometry": {"coordinates":[-100.90485,19.06317],"type":"Point"}
}