{
  "type": "Feature",
  "properties": {
    "gn:admin1_code":"16",
    "gn:admin2_code":"13.0",
    "gn:asciiname":"Tarepe",
    "gn:country_code":"MX",
    "gn:dem":923,
    "gn:feature_class":"P",
    "gn:feature_code":"PPL",
    "gn:name":"Tarepe",
    "gn:population":8,
    "gn:timezone":"America/Mexico_City",
    "iso:country":"MX",
    "wof:name":"Tarepe",
    "wof:placetype":"locality",
    "wof:population":8
},
  "geometry": {"coordinates":[-101.06417,19.13111],"type":"Point"}
}