{
  "type": "Feature",
  "properties": {
    "gn:admin1_code":"22",
    "gn:admin2_code":"4",
    "gn:asciiname":"La Mojonera",
    "gn:country_code":"MX",
    "gn:dem":2057,
    "gn:feature_class":"P",
    "gn:feature_code":"PPL",
    "gn:name":"La Mojonera",
    "gn:population":43,
    "gn:timezone":"America/Mexico_City",
    "iso:country":"MX",
    "wof:name":"La Mojonera",
    "wof:placetype":"locality",
    "wof:population":43
},
  "geometry": {"coordinates":[-99.49611,20.90611],"type":"Point"}
}