{
  "type": "Feature",
  "properties": {
    "gn:admin1_code":"19.0",
    "gn:admin2_code":"42.0",
    "gn:asciiname":"El Norteno",
    "gn:country_code":"MX",
    "gn:dem":239,
    "gn:feature_class":"P",
    "gn:feature_code":"PPL",
    "gn:name":"El Norte\u00f1o",
    "gn:population":0,
    "gn:timezone":"America/Monterrey",
    "iso:country":"MX",
    "name:spa_x_preferred":[
        "El Norte\u00f1o"
    ],
    "wof:name":"El Norteno",
    "wof:placetype":"locality"
},
  "geometry": {"coordinates":[-99.64695,25.48689],"type":"Point"}
}