{
  "type": "Feature",
  "properties": {
    "gn:admin1_code":"20",
    "gn:admin2_code":"10.0",
    "gn:asciiname":"Cuajinicuil",
    "gn:country_code":"MX",
    "gn:dem":161,
    "gn:feature_class":"P",
    "gn:feature_code":"PPL",
    "gn:name":"Cuajinicuil",
    "gn:population":156,
    "gn:timezone":"America/Mexico_City",
    "iso:country":"MX",
    "wof:name":"Cuajinicuil",
    "wof:placetype":"locality",
    "wof:population":156
},
  "geometry": {"coordinates":[-95.01333,16.82472000000001],"type":"Point"}
}