{
  "type": "Feature",
  "properties": {
    "gn:admin1_code":"16.0",
    "gn:admin2_code":"96.0",
    "gn:asciiname":"La Gregoria",
    "gn:country_code":"MX",
    "gn:dem":1519,
    "gn:feature_class":"P",
    "gn:feature_code":"PPL",
    "gn:name":"La Gregoria",
    "gn:population":0,
    "gn:timezone":"America/Mexico_City",
    "iso:country":"MX",
    "name:spa_x_preferred":[
        "La Gregoria"
    ],
    "wof:name":"La Gregoria",
    "wof:placetype":"locality"
},
  "geometry": {"coordinates":[-102.49025,18.6461],"type":"Point"}
}