{
  "type": "Feature",
  "properties": {
    "gn:admin1_code":"6",
    "gn:admin2_code":"45.0",
    "gn:asciiname":"El Mirage",
    "gn:country_code":"MX",
    "gn:dem":1146,
    "gn:feature_class":"P",
    "gn:feature_code":"PPL",
    "gn:name":"El Mirage",
    "gn:population":8,
    "gn:timezone":"America/Chihuahua",
    "iso:country":"MX",
    "name:deu_x_preferred":[
        "El Mirage"
    ],
    "name:ita_x_preferred":[
        "El Mirage"
    ],
    "name:swe_x_preferred":[
        "El Mirage"
    ],
    "name:ukr_x_preferred":[
        "\u0415\u043b\u044c-\u041c\u0456\u0440\u0430\u0436"
    ],
    "wof:name":"El Mirage",
    "wof:placetype":"locality",
    "wof:population":8
},
  "geometry": {"coordinates":[-105.49518999999999,28.37298],"type":"Point"}
}