{
  "type": "Feature",
  "properties": {
    "gn:admin1_code":"6",
    "gn:admin2_code":"45.0",
    "gn:asciiname":"El Mirage",
    "gn:country_code":"MX",
    "gn:dem":1146,
    "gn:feature_class":"P",
    "gn:feature_code":"PPL",
    "gn:name":"El Mirage",
    "gn:population":8,
    "gn:timezone":"America/Chihuahua",
    "iso:country":"MX",
    "wof:name":"El Mirage",
    "wof:placetype":"locality",
    "wof:population":8
},
  "geometry": {"coordinates":[-105.49518999999999,28.37298],"type":"Point"}
}