{
  "type": "Feature",
  "properties": {
    "gn:admin1_code":"11",
    "gn:admin2_code":"7.0",
    "gn:asciiname":"Granja las Palomas",
    "gn:country_code":"MX",
    "gn:dem":1753,
    "gn:feature_class":"P",
    "gn:feature_code":"PPL",
    "gn:name":"Granja las Palomas",
    "gn:population":7,
    "gn:timezone":"America/Mexico_City",
    "iso:country":"MX",
    "wof:name":"Granja las Palomas",
    "wof:placetype":"locality",
    "wof:population":7
},
  "geometry": {"coordinates":[-100.86806,20.55694],"type":"Point"}
}