{
  "type": "Feature",
  "properties": {
    "gn:admin1_code":"32",
    "gn:admin2_code":"14.0",
    "gn:asciiname":"Rancho Blanco",
    "gn:country_code":"MX",
    "gn:dem":1825,
    "gn:feature_class":"P",
    "gn:feature_code":"PPL",
    "gn:name":"Rancho Blanco",
    "gn:population":0,
    "gn:timezone":"America/Mexico_City",
    "iso:country":"MX",
    "name:spa_x_preferred":[
        "Rancho Blanco"
    ],
    "wof:name":"Rancho Blanco",
    "wof:placetype":"locality"
},
  "geometry": {"coordinates":[-102.93720999999999,23.95171],"type":"Point"}
}