{
  "type": "Feature",
  "properties": {
    "gn:admin1_code":"6.0",
    "gn:admin2_code":"29.0",
    "gn:asciiname":"Cerro Alto",
    "gn:country_code":"MX",
    "gn:dem":2354,
    "gn:feature_class":"P",
    "gn:feature_code":"PPL",
    "gn:name":"Cerro Alto",
    "gn:population":0,
    "gn:timezone":"America/Chihuahua",
    "iso:country":"MX",
    "name:ceb_x_preferred":[
        "Cerro Alto"
    ],
    "name:spa_x_preferred":[
        "Cerro Alto"
    ],
    "name:swe_x_preferred":[
        "Cerro Alto"
    ],
    "wof:name":"Cerro Alto",
    "wof:placetype":"locality"
},
  "geometry": {"coordinates":[-107.28794000000001,26.57429],"type":"Point"}
}