{
  "type": "Feature",
  "properties": {
    "gn:admin1_code":"11",
    "gn:admin2_code":"27",
    "gn:asciiname":"El Tepeyac",
    "gn:country_code":"MX",
    "gn:dem":1720,
    "gn:feature_class":"P",
    "gn:feature_code":"PPL",
    "gn:name":"El Tepeyac",
    "gn:population":32,
    "gn:timezone":"America/Mexico_City",
    "iso:country":"MX",
    "wof:name":"El Tepeyac",
    "wof:placetype":"locality",
    "wof:population":32
},
  "geometry": {"coordinates":[-101.17471999999999,20.54889],"type":"Point"}
}