{
  "type": "Feature",
  "properties": {
    "gn:admin1_code":"16",
    "gn:admin2_code":"34.0",
    "gn:asciiname":"El Pitorreal (Cerro Prieto)",
    "gn:country_code":"MX",
    "gn:dem":2497,
    "gn:feature_class":"P",
    "gn:feature_code":"PPL",
    "gn:name":"El Pitorreal (Cerro Prieto)",
    "gn:population":91,
    "gn:timezone":"America/Mexico_City",
    "iso:country":"MX",
    "wof:name":"El Pitorreal (Cerro Prieto)",
    "wof:placetype":"locality",
    "wof:population":91
},
  "geometry": {"coordinates":[-100.55194,19.76583],"type":"Point"}
}