{
  "type": "Feature",
  "properties": {
    "gn:admin1_code":"16",
    "gn:admin2_code":"87.0",
    "gn:asciiname":"Tomendan",
    "gn:country_code":"MX",
    "gn:dem":980,
    "gn:feature_class":"P",
    "gn:feature_code":"PPL",
    "gn:name":"Tomend\u00e1n",
    "gn:population":1291,
    "gn:timezone":"America/Mexico_City",
    "iso:country":"MX",
    "name:spa_x_preferred":[
        "Tomend\u00e1n"
    ],
    "wof:name":"Tomendan",
    "wof:placetype":"locality",
    "wof:population":1291
},
  "geometry": {"coordinates":[-101.8603,19.31142],"type":"Point"}
}