{
  "type": "Feature",
  "properties": {
    "gn:admin1_code":"30",
    "gn:admin2_code":"58.0",
    "gn:asciiname":"El Chote Santa Teresa",
    "gn:country_code":"MX",
    "gn:dem":79,
    "gn:feature_class":"P",
    "gn:feature_code":"PPL",
    "gn:name":"El Chote Santa Teresa",
    "gn:population":0,
    "gn:timezone":"America/Mexico_City",
    "iso:country":"MX",
    "name:spa_x_preferred":[
        "El Chote Santa Teresa"
    ],
    "wof:name":"El Chote Santa Teresa",
    "wof:placetype":"locality"
},
  "geometry": {"coordinates":[-97.90184000000001,20.9046],"type":"Point"}
}