{
  "type": "Feature",
  "properties": {
    "gn:admin1_code":"28.0",
    "gn:admin2_code":"2.0",
    "gn:asciiname":"Los Ebanos",
    "gn:country_code":"MX",
    "gn:dem":153,
    "gn:feature_class":"P",
    "gn:feature_code":"PPL",
    "gn:name":"Los Ebanos",
    "gn:population":0,
    "gn:timezone":"America/Monterrey",
    "iso:country":"MX",
    "name:spa_x_preferred":[
        "Los Ebanos"
    ],
    "wof:name":"Los Ebanos",
    "wof:placetype":"locality"
},
  "geometry": {"coordinates":[-98.31012,22.9149],"type":"Point"}
}