{
  "type": "Feature",
  "properties": {
    "gn:admin1_code":"5",
    "gn:admin2_code":"59.0",
    "gn:asciiname":"Quexil",
    "gn:country_code":"MX",
    "gn:dem":897,
    "gn:feature_class":"P",
    "gn:feature_code":"PPL",
    "gn:name":"Quexil",
    "gn:population":0,
    "gn:timezone":"America/Mexico_City",
    "iso:country":"MX",
    "name:spa_x_preferred":[
        "Quexil"
    ],
    "name:spa_x_variant":[
        "Questil"
    ],
    "wof:name":"Quexil",
    "wof:placetype":"locality"
},
  "geometry": {"coordinates":[-91.94887,16.92592],"type":"Point"}
}