{
  "type": "Feature",
  "properties": {
    "gn:admin1_code":"5",
    "gn:admin2_code":"11.0",
    "gn:asciiname":"Nuevo Yucatan",
    "gn:country_code":"MX",
    "gn:dem":1476,
    "gn:feature_class":"P",
    "gn:feature_code":"PPL",
    "gn:name":"Nuevo Yucat\u00e1n",
    "gn:population":326,
    "gn:timezone":"America/Mexico_City",
    "iso:country":"MX",
    "name:und_x_variant":[
        "Nuevo Yucat\u00e1n"
    ],
    "wof:name":"Nuevo Yucatan",
    "wof:placetype":"locality",
    "wof:population":326
},
  "geometry": {"coordinates":[-92.19694,15.62694],"type":"Point"}
}