{
  "type": "Feature",
  "properties": {
    "gn:admin1_code":"24",
    "gn:admin2_code":"33.0",
    "gn:asciiname":"El Jardin",
    "gn:country_code":"MX",
    "gn:dem":2009,
    "gn:feature_class":"P",
    "gn:feature_code":"PPL",
    "gn:name":"El Jard\u00edn",
    "gn:population":8,
    "gn:timezone":"America/Mexico_City",
    "iso:country":"MX",
    "name:spa_x_preferred":[
        "Casa El Jard\u00edn"
    ],
    "name:und_x_variant":[
        "El Jard\u00edn"
    ],
    "wof:name":"El Jardin",
    "wof:placetype":"locality",
    "wof:population":8
},
  "geometry": {"coordinates":[-101.64417,23.25028],"type":"Point"}
}