{
  "type": "Feature",
  "properties": {
    "gn:admin1_code":"26",
    "gn:admin2_code":"18",
    "gn:asciiname":"Campo Emilio Carrasco",
    "gn:country_code":"MX",
    "gn:dem":28,
    "gn:feature_class":"P",
    "gn:feature_code":"PPL",
    "gn:name":"Campo Emilio Carrasco",
    "gn:population":11,
    "gn:timezone":"America/Hermosillo",
    "iso:country":"MX",
    "wof:name":"Campo Emilio Carrasco",
    "wof:placetype":"locality",
    "wof:population":11
},
  "geometry": {"coordinates":[-109.98888999999998,27.39056],"type":"Point"}
}