{
  "type": "Feature",
  "properties": {
    "gn:admin1_code":"19",
    "gn:admin2_code":"33.0",
    "gn:asciiname":"El Aguacate (El Rosario)",
    "gn:country_code":"MX",
    "gn:dem":333,
    "gn:feature_class":"P",
    "gn:feature_code":"PPL",
    "gn:name":"El Aguacate (El Rosario)",
    "gn:population":5,
    "gn:timezone":"America/Monterrey",
    "iso:country":"MX",
    "wof:name":"El Aguacate (El Rosario)",
    "wof:placetype":"locality",
    "wof:population":5
},
  "geometry": {"coordinates":[-99.53443,24.87174],"type":"Point"}
}