{
  "type": "Feature",
  "properties": {
    "gn:admin1_code":"20",
    "gn:admin2_code":"59.0",
    "gn:asciiname":"San Guillermo",
    "gn:country_code":"MX",
    "gn:dem":1504,
    "gn:feature_class":"P",
    "gn:feature_code":"PPL",
    "gn:name":"San Guillermo",
    "gn:population":0,
    "gn:timezone":"America/Mexico_City",
    "iso:country":"MX",
    "name:spa_x_preferred":[
        "La Ca\u00f1ada"
    ],
    "name:spa_x_variant":[
        "San Guillermo"
    ],
    "wof:name":"San Guillermo",
    "wof:placetype":"locality"
},
  "geometry": {"coordinates":[-96.70845,16.44211],"type":"Point"}
}