{
  "type": "Feature",
  "properties": {
    "gn:admin1_code":"6",
    "gn:admin2_code":"27",
    "gn:asciiname":"Nacipa",
    "gn:country_code":"MX",
    "gn:dem":2230,
    "gn:feature_class":"P",
    "gn:feature_code":"PPL",
    "gn:name":"Nacipa",
    "gn:population":9,
    "gn:timezone":"America/Chihuahua",
    "iso:country":"MX",
    "wof:name":"Nacipa",
    "wof:placetype":"locality",
    "wof:population":9
},
  "geometry": {"coordinates":[-107.36019,27.52659],"type":"Point"}
}