{
  "type": "Feature",
  "properties": {
    "gn:admin1_code":"30",
    "gn:admin2_code":"191",
    "gn:asciiname":"La Zanja",
    "gn:country_code":"MX",
    "gn:dem":16,
    "gn:feature_class":"P",
    "gn:feature_code":"PPL",
    "gn:name":"La Zanja",
    "gn:population":24,
    "gn:timezone":"America/Mexico_City",
    "iso:country":"MX",
    "wof:name":"La Zanja",
    "wof:placetype":"locality",
    "wof:population":24
},
  "geometry": {"coordinates":[-96.35056,19.42472],"type":"Point"}
}