{
  "type": "Feature",
  "properties": {
    "gn:admin1_code":"5",
    "gn:admin2_code":"83.0",
    "gn:asciiname":"San Nicolas",
    "gn:country_code":"MX",
    "gn:dem":625,
    "gn:feature_class":"P",
    "gn:feature_code":"PPL",
    "gn:name":"San Nicol\u00e1s",
    "gn:population":5,
    "gn:timezone":"America/Mexico_City",
    "iso:country":"MX",
    "name:und_x_variant":[
        "San Nicol\u00e1s"
    ],
    "wof:name":"San Nicolas",
    "wof:placetype":"locality",
    "wof:population":5
},
  "geometry": {"coordinates":[-92.32246000000001,16.14326],"type":"Point"}
}