{
  "type": "Feature",
  "properties": {
    "gn:admin1_code":"12",
    "gn:admin2_code":"44.0",
    "gn:asciiname":"Zacaxtlahuacan",
    "gn:country_code":"MX",
    "gn:dem":866,
    "gn:feature_class":"P",
    "gn:feature_code":"PPL",
    "gn:name":"Zacaxtlahuac\u00e1n",
    "gn:population":28,
    "gn:timezone":"America/Mexico_City",
    "iso:country":"MX",
    "wof:name":"Zacaxtlahuacan",
    "wof:placetype":"locality",
    "wof:population":28
},
  "geometry": {"coordinates":[-99.37078,17.30522],"type":"Point"}
}