{
  "type": "Feature",
  "properties": {
    "gn:admin1_code":"32",
    "gn:admin2_code":"31",
    "gn:asciiname":"Jacome",
    "gn:country_code":"MX",
    "gn:dem":1967,
    "gn:feature_class":"P",
    "gn:feature_code":"PPL",
    "gn:name":"J\u00e1come",
    "gn:population":31,
    "gn:timezone":"America/Mexico_City",
    "iso:country":"MX",
    "name:und_x_variant":[
        "J\u00e1come"
    ],
    "wof:name":"Jacome",
    "wof:placetype":"locality",
    "wof:population":31
},
  "geometry": {"coordinates":[-103.44750000000001,22.3525],"type":"Point"}
}