{
  "type": "Feature",
  "properties": {
    "gn:admin1_code":"25.0",
    "gn:asciiname":"Dona Maria",
    "gn:country_code":"MX",
    "gn:dem":25,
    "gn:feature_class":"P",
    "gn:feature_code":"PPL",
    "gn:name":"Do\u00f1a Mar\u00eda",
    "gn:population":0,
    "gn:timezone":"America/Mazatlan",
    "iso:country":"MX",
    "name:spa_x_preferred":[
        "Do\u00f1a Mar\u00eda"
    ],
    "wof:name":"Dona Maria",
    "wof:placetype":"locality"
},
  "geometry": {"coordinates":[-105.83247,22.89488],"type":"Point"}
}