{
  "type": "Feature",
  "properties": {
    "gn:admin1_code":"1",
    "gn:admin2_code":"7.0",
    "gn:asciiname":"Rancho de los Pitufos",
    "gn:country_code":"MX",
    "gn:dem":1919,
    "gn:feature_class":"P",
    "gn:feature_code":"PPL",
    "gn:name":"Rancho de los Pitufos",
    "gn:population":4,
    "gn:timezone":"America/Mexico_City",
    "iso:country":"MX",
    "wof:name":"Rancho de los Pitufos",
    "wof:placetype":"locality",
    "wof:population":4
},
  "geometry": {"coordinates":[-102.26443999999999,22.23028],"type":"Point"}
}