{
  "type": "Feature",
  "properties": {
    "gn:admin1_code":"6",
    "gn:admin2_code":"27",
    "gn:asciiname":"Banoachi",
    "gn:country_code":"MX",
    "gn:dem":2186,
    "gn:feature_class":"P",
    "gn:feature_code":"PPL",
    "gn:name":"Banoachi",
    "gn:population":19,
    "gn:timezone":"America/Chihuahua",
    "iso:country":"MX",
    "wof:name":"Banoachi",
    "wof:placetype":"locality",
    "wof:population":19
},
  "geometry": {"coordinates":[-106.98462000000001,27.28577],"type":"Point"}
}