{
  "type": "Feature",
  "properties": {
    "gn:admin1_code":"24",
    "gn:admin2_code":"36.0",
    "gn:asciiname":"La Alberca",
    "gn:country_code":"MX",
    "gn:dem":445,
    "gn:feature_class":"P",
    "gn:feature_code":"PPL",
    "gn:name":"La Alberca",
    "gn:population":0,
    "gn:timezone":"America/Mexico_City",
    "iso:country":"MX",
    "name:spa_x_preferred":[
        "La Alberca"
    ],
    "wof:name":"La Alberca",
    "wof:placetype":"locality"
},
  "geometry": {"coordinates":[-99.42697,21.70903],"type":"Point"}
}