{
  "type": "Feature",
  "properties": {
    "gn:admin1_code":"27.0",
    "gn:admin2_code":"12.0",
    "gn:asciiname":"Profesor Caparrosa Seguna Seccion",
    "gn:country_code":"MX",
    "gn:dem":29,
    "gn:feature_class":"P",
    "gn:feature_code":"PPL",
    "gn:name":"Profesor Caparrosa Seguna Secci\u00f3n",
    "gn:population":0,
    "gn:timezone":"America/Mexico_City",
    "iso:country":"MX",
    "name:spa_x_preferred":[
        "Profesor Caparrosa Seguna Secci\u00f3n"
    ],
    "wof:name":"Profesor Caparrosa Seguna Seccion",
    "wof:placetype":"locality"
},
  "geometry": {"coordinates":[-92.51521,17.61422],"type":"Point"}
}