{
  "type": "Feature",
  "properties": {
    "gn:admin1_code":"27",
    "gn:admin2_code":"14.0",
    "gn:asciiname":"El Amatillo",
    "gn:country_code":"MX",
    "gn:dem":12,
    "gn:feature_class":"P",
    "gn:feature_code":"PPL",
    "gn:name":"El Amatillo",
    "gn:population":0,
    "gn:timezone":"America/Mexico_City",
    "iso:country":"MX",
    "name:spa_x_preferred":[
        "El Amatillo"
    ],
    "wof:name":"El Amatillo",
    "wof:placetype":"locality"
},
  "geometry": {"coordinates":[-93.31180999999999,18.43505],"type":"Point"}
}