{
  "type": "Feature",
  "properties": {
    "gn:admin1_code":"6",
    "gn:admin2_code":"47.0",
    "gn:asciiname":"Victorio",
    "gn:cc2":"MX",
    "gn:country_code":"MX",
    "gn:dem":1081,
    "gn:feature_class":"P",
    "gn:feature_code":"PPL",
    "gn:name":"Victorio",
    "gn:population":0,
    "gn:timezone":"America/Chihuahua",
    "iso:country":"MX",
    "name:und_x_variant":[
        "Victoria",
        "Victorio"
    ],
    "wof:name":"Victorio",
    "wof:placetype":"locality"
},
  "geometry": {"coordinates":[-108.51667,28.08333],"type":"Point"}
}