{
  "type": "Feature",
  "properties": {
    "gn:admin1_code":"6",
    "gn:admin2_code":"47.0",
    "gn:asciiname":"Victorio",
    "gn:cc2":"MX",
    "gn:country_code":"MX",
    "gn:dem":1081,
    "gn:feature_class":"P",
    "gn:feature_code":"PPL",
    "gn:name":"Victorio",
    "gn:population":0,
    "gn:timezone":"America/Chihuahua",
    "iso:country":"MX",
    "name:cat_x_preferred":[
        "Victorio"
    ],
    "name:deu_x_preferred":[
        "Victorio"
    ],
    "name:fin_x_preferred":[
        "Victorio"
    ],
    "name:fra_x_preferred":[
        "Victorio"
    ],
    "name:hun_x_preferred":[
        "Victorio"
    ],
    "name:ita_x_preferred":[
        "Victorio"
    ],
    "name:lit_x_preferred":[
        "Victorio"
    ],
    "name:nds_x_preferred":[
        "Victorio"
    ],
    "name:por_x_preferred":[
        "Victorio"
    ],
    "name:rus_x_preferred":[
        "\u0412\u0438\u043a\u0442\u043e\u0440\u0438\u043e"
    ],
    "name:spa_x_preferred":[
        "Victorio"
    ],
    "name:und_x_variant":[
        "Victoria",
        "Victorio"
    ],
    "wof:name":"Victorio",
    "wof:placetype":"locality"
},
  "geometry": {"coordinates":[-108.51667,28.08333],"type":"Point"}
}