{
  "type": "Feature",
  "properties": {
    "gn:admin1_code":"11.0",
    "gn:admin2_code":"38.0",
    "gn:asciiname":"San Jose de Hidalgo",
    "gn:country_code":"MX",
    "gn:dem":1920,
    "gn:feature_class":"P",
    "gn:feature_code":"PPL",
    "gn:name":"San Jos\u00e9 de Hidalgo",
    "gn:population":0,
    "gn:timezone":"America/Mexico_City",
    "iso:country":"MX",
    "name:spa_x_preferred":[
        "San Jos\u00e9 de Hidalgo"
    ],
    "name:spa_x_variant":[
        "San Jos\u00e9 de Porto"
    ],
    "wof:name":"San Jose de Hidalgo",
    "wof:placetype":"locality"
},
  "geometry": {"coordinates":[-100.56270000000001,20.0351],"type":"Point"}
}