{
  "type": "Feature",
  "properties": {
    "gn:admin1_code":"24",
    "gn:admin2_code":"26.0",
    "gn:asciiname":"Pa'tnel",
    "gn:country_code":"MX",
    "gn:dem":170,
    "gn:feature_class":"P",
    "gn:feature_code":"PPL",
    "gn:name":"Pa'tnel",
    "gn:population":398,
    "gn:timezone":"America/Mexico_City",
    "iso:country":"MX",
    "wof:name":"Pa'tnel",
    "wof:placetype":"locality",
    "wof:population":398
},
  "geometry": {"coordinates":[-98.86194,21.65556],"type":"Point"}
}