{
  "type": "Feature",
  "properties": {
    "gn:admin1_code":"18",
    "gn:admin2_code":"20.0",
    "gn:asciiname":"Colonia el Mirador",
    "gn:country_code":"MX",
    "gn:dem":31,
    "gn:feature_class":"P",
    "gn:feature_code":"PPL",
    "gn:name":"Colonia el Mirador",
    "gn:population":267,
    "gn:timezone":"America/Mazatlan",
    "iso:country":"MX",
    "wof:name":"Colonia el Mirador",
    "wof:placetype":"locality",
    "wof:population":267
},
  "geometry": {"coordinates":[-105.19444,20.80194],"type":"Point"}
}