{
  "type": "Feature",
  "properties": {
    "gn:admin1_code":"15",
    "gn:admin2_code":"100.0",
    "gn:asciiname":"Ejido el Rosario",
    "gn:country_code":"MX",
    "gn:dem":2254,
    "gn:feature_class":"P",
    "gn:feature_code":"PPL",
    "gn:name":"Ejido el Rosario",
    "gn:population":199,
    "gn:timezone":"America/Mexico_City",
    "iso:country":"MX",
    "wof:name":"Ejido el Rosario",
    "wof:placetype":"locality",
    "wof:population":199
},
  "geometry": {"coordinates":[-98.90389999999999,19.58441],"type":"Point"}
}