{
  "type": "Feature",
  "properties": {
    "gn:admin1_code":"28",
    "gn:admin2_code":"42.0",
    "gn:asciiname":"General Lucio Blanco",
    "gn:country_code":"MX",
    "gn:dem":286,
    "gn:feature_class":"P",
    "gn:feature_code":"PPL",
    "gn:name":"General Lucio Blanco",
    "gn:population":566,
    "gn:timezone":"America/Monterrey",
    "iso:country":"MX",
    "wof:name":"General Lucio Blanco",
    "wof:placetype":"locality",
    "wof:population":566
},
  "geometry": {"coordinates":[-99.40228,24.73324],"type":"Point"}
}