{
  "type": "Feature",
  "properties": {
    "gn:admin1_code":"13",
    "gn:admin2_code":"84.0",
    "gn:asciiname":"Los Carrizos",
    "gn:country_code":"MX",
    "gn:dem":1832,
    "gn:feature_class":"P",
    "gn:feature_code":"PPL",
    "gn:name":"Los Carrizos",
    "gn:population":62,
    "gn:timezone":"America/Mexico_City",
    "iso:country":"MX",
    "wof:name":"Los Carrizos",
    "wof:placetype":"locality",
    "wof:population":62
},
  "geometry": {"coordinates":[-99.35028,20.75389],"type":"Point"}
}