{
  "type": "Feature",
  "properties": {
    "gn:admin1_code":"5",
    "gn:admin2_code":"78.0",
    "gn:asciiname":"Dos Lagunas (La Soledad Fraccion Dos)",
    "gn:country_code":"MX",
    "gn:dem":2485,
    "gn:feature_class":"P",
    "gn:feature_code":"PPL",
    "gn:name":"Dos Lagunas (La Soledad Fracci\u00f3n Dos)",
    "gn:population":248,
    "gn:timezone":"America/Mexico_City",
    "iso:country":"MX",
    "name:und_x_variant":[
        "Dos Lagunas (La Soledad Fracci\u00f3n Dos)"
    ],
    "wof:name":"Dos Lagunas (La Soledad Fraccion Dos)",
    "wof:placetype":"locality",
    "wof:population":248
},
  "geometry": {"coordinates":[-92.52083,16.65694],"type":"Point"}
}