{
  "type": "Feature",
  "properties": {
    "gn:admin1_code":"26",
    "gn:admin2_code":"30.0",
    "gn:asciiname":"Molino de Camou",
    "gn:country_code":"MX",
    "gn:dem":267,
    "gn:feature_class":"P",
    "gn:feature_code":"PPL",
    "gn:name":"Molino de Camou",
    "gn:population":0,
    "gn:timezone":"America/Hermosillo",
    "iso:country":"MX",
    "name:spa_x_preferred":[
        "Molino de Camou"
    ],
    "wof:name":"Molino de Camou",
    "wof:placetype":"locality"
},
  "geometry": {"coordinates":[-110.75767999999999,29.20409],"type":"Point"}
}