{
  "type": "Feature",
  "properties": {
    "gn:admin1_code":"21",
    "gn:admin2_code":"212.0",
    "gn:asciiname":"Xopanaco",
    "gn:country_code":"MX",
    "gn:dem":2060,
    "gn:feature_class":"P",
    "gn:feature_code":"PPL",
    "gn:name":"Xopanaco",
    "gn:population":239,
    "gn:timezone":"America/Mexico_City",
    "iso:country":"MX",
    "wof:name":"Xopanaco",
    "wof:placetype":"locality",
    "wof:population":239
},
  "geometry": {"coordinates":[-97.65333,19.72148],"type":"Point"}
}