{
  "type": "Feature",
  "properties": {
    "gn:admin1_code":"24",
    "gn:admin2_code":"28.0",
    "gn:asciiname":"La Morita",
    "gn:country_code":"MX",
    "gn:dem":1670,
    "gn:feature_class":"P",
    "gn:feature_code":"PPL",
    "gn:name":"La Morita",
    "gn:population":0,
    "gn:timezone":"America/Mexico_City",
    "iso:country":"MX",
    "wof:name":"La Morita",
    "wof:placetype":"locality"
},
  "geometry": {"coordinates":[-100.97852,22.57452],"type":"Point"}
}