{
  "type": "Feature",
  "properties": {
    "gn:admin1_code":"14",
    "gn:admin2_code":"53.0",
    "gn:asciiname":"La Estancia",
    "gn:country_code":"MX",
    "gn:dem":2000,
    "gn:feature_class":"P",
    "gn:feature_code":"PPL",
    "gn:name":"La Estancia",
    "gn:population":6,
    "gn:timezone":"America/Mexico_City",
    "iso:country":"MX",
    "name:ceb_x_preferred":[
        "La Estancia"
    ],
    "name:deu_x_preferred":[
        "La Estancia"
    ],
    "name:spa_x_preferred":[
        "La Estancia"
    ],
    "name:swe_x_preferred":[
        "La Estancia"
    ],
    "wof:name":"La Estancia",
    "wof:placetype":"locality",
    "wof:population":6
},
  "geometry": {"coordinates":[-101.78917,21.26639],"type":"Point"}
}