{
  "type": "Feature",
  "properties": {
    "gn:admin1_code":"5",
    "gn:admin2_code":"8.0",
    "gn:asciiname":"Barrio el 9",
    "gn:country_code":"MX",
    "gn:dem":887,
    "gn:feature_class":"P",
    "gn:feature_code":"PPL",
    "gn:name":"Barrio el 9",
    "gn:population":73,
    "gn:timezone":"America/Mexico_City",
    "iso:country":"MX",
    "wof:name":"Barrio el 9",
    "wof:placetype":"locality",
    "wof:population":73
},
  "geometry": {"coordinates":[-92.82028,15.76611],"type":"Point"}
}