{
  "type": "Feature",
  "properties": {
    "gn:admin1_code":"21",
    "gn:admin2_code":"116.0",
    "gn:asciiname":"Barrio Nuevo",
    "gn:country_code":"MX",
    "gn:dem":2009,
    "gn:feature_class":"P",
    "gn:feature_code":"PPL",
    "gn:name":"Barrio Nuevo",
    "gn:population":138,
    "gn:timezone":"America/Mexico_City",
    "iso:country":"MX",
    "wof:name":"Barrio Nuevo",
    "wof:placetype":"locality",
    "wof:population":138
},
  "geometry": {"coordinates":[-97.0441,19.28235],"type":"Point"}
}