{
  "type": "Feature",
  "properties": {
    "gn:admin1_code":"14.0",
    "gn:admin2_code":"49.0",
    "gn:asciiname":"El Remolino",
    "gn:country_code":"MX",
    "gn:dem":389,
    "gn:feature_class":"P",
    "gn:feature_code":"PPL",
    "gn:name":"El Remolino",
    "gn:population":0,
    "gn:timezone":"America/Mexico_City",
    "iso:country":"MX",
    "name:fra_x_preferred":[
        "El Remolino"
    ],
    "name:spa_x_preferred":[
        "El Remolino"
    ],
    "wof:name":"El Remolino",
    "wof:placetype":"locality"
},
  "geometry": {"coordinates":[-102.77453,19.28178],"type":"Point"}
}