{
  "type": "Feature",
  "properties": {
    "gn:admin1_code":"10",
    "gn:admin2_code":"5.0",
    "gn:asciiname":"Retiro de la Cruz",
    "gn:country_code":"MX",
    "gn:dem":2635,
    "gn:feature_class":"P",
    "gn:feature_code":"PPL",
    "gn:name":"Retiro de la Cruz",
    "gn:population":0,
    "gn:timezone":"America/Monterrey",
    "iso:country":"MX",
    "name:spa_x_preferred":[
        "Retiro de la Cruz"
    ],
    "wof:name":"Retiro de la Cruz",
    "wof:placetype":"locality"
},
  "geometry": {"coordinates":[-104.59737,23.73439],"type":"Point"}
}