{
  "type": "Feature",
  "properties": {
    "gn:admin1_code":"13",
    "gn:admin2_code":"76",
    "gn:asciiname":"El Puendho",
    "gn:country_code":"MX",
    "gn:dem":2074,
    "gn:feature_class":"P",
    "gn:feature_code":"PPL",
    "gn:name":"El Puendh\u00f3",
    "gn:population":13,
    "gn:timezone":"America/Mexico_City",
    "iso:country":"MX",
    "name:und_x_variant":[
        "El Puendh\u00f3"
    ],
    "wof:name":"El Puendho",
    "wof:placetype":"locality",
    "wof:population":13
},
  "geometry": {"coordinates":[-99.31361,19.9875],"type":"Point"}
}