{
  "type": "Feature",
  "properties": {
    "gn:admin1_code":"27",
    "gn:admin2_code":"12.0",
    "gn:asciiname":"Vernet Segunda Seccion",
    "gn:country_code":"MX",
    "gn:dem":21,
    "gn:feature_class":"P",
    "gn:feature_code":"PPL",
    "gn:name":"Vernet Segunda Secci\u00f3n",
    "gn:population":0,
    "gn:timezone":"America/Mexico_City",
    "iso:country":"MX",
    "name:spa_x_preferred":[
        "Vernet Segunda Secci\u00f3n"
    ],
    "name:spa_x_variant":[
        "Vernet",
        "Segunda Secci\u00f3n"
    ],
    "wof:name":"Vernet Segunda Seccion",
    "wof:placetype":"locality"
},
  "geometry": {"coordinates":[-92.54773,17.86561],"type":"Point"}
}