{
  "type": "Feature",
  "properties": {
    "gn:admin1_code":"12.0",
    "gn:admin2_code":"16.0",
    "gn:asciiname":"Cuahulotal",
    "gn:country_code":"MX",
    "gn:dem":502,
    "gn:feature_class":"P",
    "gn:feature_code":"PPL",
    "gn:name":"Cuahulotal",
    "gn:population":0,
    "gn:timezone":"America/Mexico_City",
    "iso:country":"MX",
    "name:spa_x_preferred":[
        "Cuahulotal"
    ],
    "wof:name":"Cuahulotal",
    "wof:placetype":"locality"
},
  "geometry": {"coordinates":[-101.82303,18.30939],"type":"Point"}
}