{
  "type": "Feature",
  "properties": {
    "gn:admin1_code":"27",
    "gn:admin2_code":"9.0",
    "gn:asciiname":"San Cristobal Primera Seccion",
    "gn:country_code":"MX",
    "gn:dem":32,
    "gn:feature_class":"P",
    "gn:feature_code":"PPL",
    "gn:name":"San Crist\u00f3bal Primera Secci\u00f3n",
    "gn:population":0,
    "gn:timezone":"America/Mexico_City",
    "iso:country":"MX",
    "name:spa_x_preferred":[
        "San Cristobal Primera Secci\u00f3n"
    ],
    "name:spa_x_variant":[
        "San Crist\u00f3bal Primera Secci\u00f3n"
    ],
    "wof:name":"San Cristobal Primera Seccion",
    "wof:placetype":"locality"
},
  "geometry": {"coordinates":[-92.6985,17.83915],"type":"Point"}
}