{
  "type": "Feature",
  "properties": {
    "gn:admin1_code":"6.0",
    "gn:admin2_code":"27.0",
    "gn:asciiname":"Calonachi",
    "gn:country_code":"MX",
    "gn:dem":1852,
    "gn:feature_class":"P",
    "gn:feature_code":"PPL",
    "gn:name":"Calonachi",
    "gn:population":0,
    "gn:timezone":"America/Chihuahua",
    "iso:country":"MX",
    "name:spa_x_preferred":[
        "Calonachi"
    ],
    "wof:name":"Calonachi",
    "wof:placetype":"locality"
},
  "geometry": {"coordinates":[-107.46101000000002,27.37599],"type":"Point"}
}