{
  "type": "Feature",
  "properties": {
    "gn:admin1_code":"4.0",
    "gn:asciiname":"Cuatro Hermanos",
    "gn:country_code":"MX",
    "gn:dem":18,
    "gn:feature_class":"P",
    "gn:feature_code":"PPL",
    "gn:name":"Cuatro Hermanos",
    "gn:population":0,
    "gn:timezone":"America/Merida",
    "iso:country":"MX",
    "name:spa_x_preferred":[
        "Cuatro Hermanos"
    ],
    "wof:name":"Cuatro Hermanos",
    "wof:placetype":"locality"
},
  "geometry": {"coordinates":[-90.63193,19.03183],"type":"Point"}
}