{
  "type": "Feature",
  "properties": {
    "gn:admin1_code":"32",
    "gn:admin2_code":"10.0",
    "gn:asciiname":"El Pasito",
    "gn:country_code":"MX",
    "gn:dem":2087,
    "gn:feature_class":"P",
    "gn:feature_code":"PPL",
    "gn:name":"El Pasito",
    "gn:population":0,
    "gn:timezone":"America/Mexico_City",
    "iso:country":"MX",
    "wof:name":"El Pasito",
    "wof:placetype":"locality"
},
  "geometry": {"coordinates":[-102.83333,23.36667000000001],"type":"Point"}
}