{
  "type": "Feature",
  "properties": {
    "gn:admin1_code":"25.0",
    "gn:asciiname":"Las Vacas Viejas",
    "gn:country_code":"MX",
    "gn:dem":5,
    "gn:feature_class":"P",
    "gn:feature_code":"PPL",
    "gn:name":"Las Vacas Viejas",
    "gn:population":0,
    "gn:timezone":"America/Mazatlan",
    "iso:country":"MX",
    "name:spa_x_preferred":[
        "Las Vacas Viejas"
    ],
    "wof:name":"Las Vacas Viejas",
    "wof:placetype":"locality"
},
  "geometry": {"coordinates":[-108.84057,25.79644],"type":"Point"}
}