{
  "type": "Feature",
  "properties": {
    "gn:admin1_code":"16.0",
    "gn:admin2_code":"22.0",
    "gn:asciiname":"Francisco I. Madero (El Pantano)",
    "gn:country_code":"MX",
    "gn:dem":1977,
    "gn:feature_class":"P",
    "gn:feature_code":"PPL",
    "gn:name":"Francisco I. Madero (El Pantano)",
    "gn:population":699,
    "gn:timezone":"America/Mexico_City",
    "iso:country":"MX",
    "wof:name":"Francisco I. Madero (El Pantano)",
    "wof:placetype":"locality",
    "wof:population":699
},
  "geometry": {"coordinates":[-101.02887,19.70042],"type":"Point"}
}