{
  "type": "Feature",
  "properties": {
    "gn:admin1_code":"30",
    "gn:admin2_code":"38.0",
    "gn:asciiname":"Las Canadas",
    "gn:country_code":"MX",
    "gn:dem":973,
    "gn:feature_class":"P",
    "gn:feature_code":"PPL",
    "gn:name":"Las Ca\u00f1adas",
    "gn:population":5,
    "gn:timezone":"America/Mexico_City",
    "iso:country":"MX",
    "name:und_x_variant":[
        "Las Ca\u00f1adas"
    ],
    "wof:name":"Las Canadas",
    "wof:placetype":"locality",
    "wof:population":5
},
  "geometry": {"coordinates":[-96.91028,19.41389],"type":"Point"}
}