{
  "type": "Feature",
  "properties": {
    "gn:admin1_code":"30.0",
    "gn:admin2_code":"161.0",
    "gn:asciiname":"El Manantial",
    "gn:country_code":"MX",
    "gn:dem":67,
    "gn:feature_class":"P",
    "gn:feature_code":"PPL",
    "gn:name":"El Manantial",
    "gn:population":0,
    "gn:timezone":"America/Mexico_City",
    "iso:country":"MX",
    "name:spa_x_preferred":[
        "El Manantial"
    ],
    "wof:name":"El Manantial",
    "wof:placetype":"locality"
},
  "geometry": {"coordinates":[-98.37139000000001,21.51944],"type":"Point"}
}