{
  "type": "Feature",
  "properties": {
    "gn:admin1_code":"10",
    "gn:admin2_code":"2",
    "gn:asciiname":"Taunitas",
    "gn:country_code":"MX",
    "gn:dem":2347,
    "gn:feature_class":"P",
    "gn:feature_code":"PPL",
    "gn:name":"Taunitas",
    "gn:population":18,
    "gn:timezone":"America/Monterrey",
    "iso:country":"MX",
    "wof:name":"Taunitas",
    "wof:placetype":"locality",
    "wof:population":18
},
  "geometry": {"coordinates":[-106.16758,25.11665],"type":"Point"}
}