{
  "type": "Feature",
  "properties": {
    "gn:admin1_code":"22",
    "gn:admin2_code":"4",
    "gn:asciiname":"Rancho el Magueyal",
    "gn:country_code":"MX",
    "gn:dem":2052,
    "gn:feature_class":"P",
    "gn:feature_code":"PPL",
    "gn:name":"Rancho el Magueyal",
    "gn:population":25,
    "gn:timezone":"America/Mexico_City",
    "iso:country":"MX",
    "wof:name":"Rancho el Magueyal",
    "wof:placetype":"locality",
    "wof:population":25
},
  "geometry": {"coordinates":[-99.78167000000001,20.70306],"type":"Point"}
}