{
  "type": "Feature",
  "properties": {
    "gn:admin1_code":"16",
    "gn:admin2_code":"15",
    "gn:asciiname":"El Perro del Agua",
    "gn:country_code":"MX",
    "gn:dem":1203,
    "gn:feature_class":"P",
    "gn:feature_code":"PPL",
    "gn:name":"El Perro del Agua",
    "gn:population":10,
    "gn:timezone":"America/Mexico_City",
    "iso:country":"MX",
    "wof:name":"El Perro del Agua",
    "wof:placetype":"locality",
    "wof:population":10
},
  "geometry": {"coordinates":[-102.87667,18.52167],"type":"Point"}
}