{
  "type": "Feature",
  "properties": {
    "gn:admin1_code":"28",
    "gn:admin2_code":"18.0",
    "gn:asciiname":"Comas Altas",
    "gn:cc2":"MX",
    "gn:country_code":"MX",
    "gn:dem":138,
    "gn:feature_class":"P",
    "gn:feature_code":"PPL",
    "gn:name":"Comas Altas",
    "gn:population":0,
    "gn:timezone":"America/Monterrey",
    "iso:country":"MX",
    "name:und_x_variant":[
        "Rancho Comas Altas",
        "Comas Altas"
    ],
    "wof:name":"Comas Altas",
    "wof:placetype":"locality"
},
  "geometry": {"coordinates":[-98.53333000000001,24.26667],"type":"Point"}
}