{
  "type": "Feature",
  "properties": {
    "gn:admin1_code":"30",
    "gn:admin2_code":"144",
    "gn:asciiname":"El Aguacate",
    "gn:country_code":"MX",
    "gn:dem":90,
    "gn:feature_class":"P",
    "gn:feature_code":"PPL",
    "gn:name":"El Aguacate",
    "gn:population":10,
    "gn:timezone":"America/Mexico_City",
    "iso:country":"MX",
    "wof:name":"El Aguacate",
    "wof:placetype":"locality",
    "wof:population":10
},
  "geometry": {"coordinates":[-94.96278,17.83306],"type":"Point"}
}