{
  "type": "Feature",
  "properties": {
    "gn:admin1_code":"14",
    "gn:admin2_code":"20",
    "gn:asciiname":"Graciano Sanchez",
    "gn:country_code":"MX",
    "gn:dem":49,
    "gn:feature_class":"P",
    "gn:feature_code":"PPL",
    "gn:name":"Graciano S\u00e1nchez",
    "gn:population":23,
    "gn:timezone":"America/Mexico_City",
    "iso:country":"MX",
    "name:und_x_variant":[
        "Graciano S\u00e1nchez"
    ],
    "wof:name":"Graciano Sanchez",
    "wof:placetype":"locality",
    "wof:population":23
},
  "geometry": {"coordinates":[-105.575,20.32667],"type":"Point"}
}