{
  "type": "Feature",
  "properties": {
    "gn:admin1_code":"28",
    "gn:admin2_code":"24.0",
    "gn:asciiname":"El Campo",
    "gn:country_code":"MX",
    "gn:dem":133,
    "gn:feature_class":"P",
    "gn:feature_code":"PPL",
    "gn:name":"El Campo",
    "gn:population":0,
    "gn:timezone":"America/Monterrey",
    "iso:country":"MX",
    "name:spa_x_preferred":[
        "El Campo"
    ],
    "name:und_x_variant":[
        "Rancho del Campo"
    ],
    "wof:name":"El Campo",
    "wof:placetype":"locality"
},
  "geometry": {"coordinates":[-99.25217000000001,26.30019],"type":"Point"}
}