{
  "type": "Feature",
  "properties": {
    "gn:admin1_code":"21",
    "gn:admin2_code":"53.0",
    "gn:asciiname":"La Ocopilera (El Capulin)",
    "gn:country_code":"MX",
    "gn:dem":2676,
    "gn:feature_class":"P",
    "gn:feature_code":"PPL",
    "gn:name":"La Ocopilera (El Capul\u00edn)",
    "gn:population":60,
    "gn:timezone":"America/Mexico_City",
    "iso:country":"MX",
    "name:und_x_variant":[
        "La Ocopilera (El Capul\u00edn)"
    ],
    "wof:name":"La Ocopilera (El Capulin)",
    "wof:placetype":"locality",
    "wof:population":60
},
  "geometry": {"coordinates":[-98.13254000000001,19.82284],"type":"Point"}
}