{
  "type": "Feature",
  "properties": {
    "gn:admin1_code":"26",
    "gn:admin2_code":"33.0",
    "gn:asciiname":"El Segojo",
    "gn:country_code":"MX",
    "gn:dem":3,
    "gn:feature_class":"P",
    "gn:feature_code":"PPL",
    "gn:name":"El Segojo",
    "gn:population":0,
    "gn:timezone":"America/Hermosillo",
    "iso:country":"MX",
    "name:spa_x_preferred":[
        "El Segojo"
    ],
    "wof:name":"El Segojo",
    "wof:placetype":"locality"
},
  "geometry": {"coordinates":[-109.84061,26.88504],"type":"Point"}
}