{
  "type": "Feature",
  "properties": {
    "gn:admin1_code":"5",
    "gn:admin2_code":"69.0",
    "gn:asciiname":"Tres de Mayo",
    "gn:country_code":"MX",
    "gn:dem":29,
    "gn:feature_class":"P",
    "gn:feature_code":"PPL",
    "gn:name":"Tres de Mayo",
    "gn:population":5,
    "gn:timezone":"America/Mexico_City",
    "iso:country":"MX",
    "wof:name":"Tres de Mayo",
    "wof:placetype":"locality",
    "wof:population":5
},
  "geometry": {"coordinates":[-93.09699999999999,15.56825],"type":"Point"}
}