{
  "type": "Feature",
  "properties": {
    "gn:admin1_code":"13",
    "gn:asciiname":"Tecoyunca",
    "gn:country_code":"MX",
    "gn:dem":2890,
    "gn:feature_class":"P",
    "gn:feature_code":"PPL",
    "gn:name":"Tecoyunca",
    "gn:population":0,
    "gn:timezone":"America/Mexico_City",
    "iso:country":"MX",
    "name:spa_x_preferred":[
        "Tecoyunca"
    ],
    "wof:name":"Tecoyunca",
    "wof:placetype":"locality"
},
  "geometry": {"coordinates":[-98.30457,19.6955],"type":"Point"}
}