{
  "type": "Feature",
  "properties": {
    "gn:admin1_code":"10",
    "gn:admin2_code":"27",
    "gn:asciiname":"Buenavista",
    "gn:country_code":"MX",
    "gn:dem":1634,
    "gn:feature_class":"P",
    "gn:feature_code":"PPL",
    "gn:name":"Buenavista",
    "gn:population":40,
    "gn:timezone":"America/Monterrey",
    "iso:country":"MX",
    "wof:name":"Buenavista",
    "wof:placetype":"locality",
    "wof:population":40
},
  "geometry": {"coordinates":[-102.75194999999999,24.51059],"type":"Point"}
}