{
  "type": "Feature",
  "properties": {
    "gn:admin1_code":"19",
    "gn:admin2_code":"22.0",
    "gn:asciiname":"El Perdiceno",
    "gn:country_code":"MX",
    "gn:dem":213,
    "gn:feature_class":"P",
    "gn:feature_code":"PPL",
    "gn:name":"El Perdice\u00f1o",
    "gn:population":0,
    "gn:timezone":"America/Monterrey",
    "iso:country":"MX",
    "name:spa_x_preferred":[
        "El Perdice\u00f1o"
    ],
    "wof:name":"El Perdiceno",
    "wof:placetype":"locality"
},
  "geometry": {"coordinates":[-99.40994000000001,25.38772],"type":"Point"}
}