{
  "type": "Feature",
  "properties": {
    "gn:admin1_code":"15.0",
    "gn:admin2_code":"105.0",
    "gn:asciiname":"El Puerto de la Parota",
    "gn:country_code":"MX",
    "gn:dem":947,
    "gn:feature_class":"P",
    "gn:feature_code":"PPL",
    "gn:name":"El Puerto de la Parota",
    "gn:population":0,
    "gn:timezone":"America/Mexico_City",
    "iso:country":"MX",
    "name:spa_x_preferred":[
        "El Puerto de la Parota"
    ],
    "wof:name":"El Puerto de la Parota",
    "wof:placetype":"locality"
},
  "geometry": {"coordinates":[-100.37425,18.55881],"type":"Point"}
}