{
  "type": "Feature",
  "properties": {
    "gn:admin1_code":"21",
    "gn:admin2_code":"183",
    "gn:asciiname":"Atenco",
    "gn:country_code":"MX",
    "gn:dem":1284,
    "gn:feature_class":"P",
    "gn:feature_code":"PPL",
    "gn:name":"Atenco",
    "gn:population":32,
    "gn:timezone":"America/Mexico_City",
    "iso:country":"MX",
    "wof:name":"Atenco",
    "wof:placetype":"locality",
    "wof:population":32
},
  "geometry": {"coordinates":[-97.96666,20.17333],"type":"Point"}
}