{
  "type": "Feature",
  "properties": {
    "gn:admin1_code":"14",
    "gn:admin2_code":"120",
    "gn:asciiname":"Guadalupana [Granja]",
    "gn:country_code":"MX",
    "gn:dem":1609,
    "gn:feature_class":"P",
    "gn:feature_code":"PPL",
    "gn:name":"Guadalupana [Granja]",
    "gn:population":20,
    "gn:timezone":"America/Mexico_City",
    "iso:country":"MX",
    "wof:name":"Guadalupana [Granja]",
    "wof:placetype":"locality",
    "wof:population":20
},
  "geometry": {"coordinates":[-103.45778,20.82],"type":"Point"}
}