{
  "type": "Feature",
  "properties": {
    "gn:admin1_code":"32",
    "gn:admin2_code":"48",
    "gn:asciiname":"Mesa Colorada",
    "gn:country_code":"MX",
    "gn:dem":2104,
    "gn:feature_class":"P",
    "gn:feature_code":"PPL",
    "gn:name":"Mesa Colorada",
    "gn:population":18,
    "gn:timezone":"America/Mexico_City",
    "iso:country":"MX",
    "wof:name":"Mesa Colorada",
    "wof:placetype":"locality",
    "wof:population":18
},
  "geometry": {"coordinates":[-103.09917,21.82806],"type":"Point"}
}