{
  "type": "Feature",
  "properties": {
    "gn:admin1_code":"5",
    "gn:admin2_code":"19.0",
    "gn:asciiname":"La Tapadera",
    "gn:country_code":"MX",
    "gn:dem":1564,
    "gn:feature_class":"P",
    "gn:feature_code":"PPL",
    "gn:name":"La Tapadera",
    "gn:population":5,
    "gn:timezone":"America/Mexico_City",
    "iso:country":"MX",
    "wof:name":"La Tapadera",
    "wof:placetype":"locality",
    "wof:population":5
},
  "geometry": {"coordinates":[-92.09556000000001,16.23611],"type":"Point"}
}