{
  "type": "Feature",
  "properties": {
    "gn:admin1_code":"16",
    "gn:admin2_code":"6.0",
    "gn:asciiname":"Terrero",
    "gn:country_code":"MX",
    "gn:dem":233,
    "gn:feature_class":"P",
    "gn:feature_code":"PPL",
    "gn:name":"Terrero",
    "gn:population":0,
    "gn:timezone":"America/Mexico_City",
    "iso:country":"MX",
    "wof:name":"Terrero",
    "wof:placetype":"locality"
},
  "geometry": {"coordinates":[-102.46666999999999,18.96667],"type":"Point"}
}