{
  "type": "Feature",
  "properties": {
    "gn:admin1_code":"30",
    "gn:admin2_code":"155.0",
    "gn:asciiname":"La Sabana",
    "gn:country_code":"MX",
    "gn:dem":144,
    "gn:feature_class":"P",
    "gn:feature_code":"PPL",
    "gn:name":"La Sabana",
    "gn:population":0,
    "gn:timezone":"America/Mexico_City",
    "iso:country":"MX",
    "name:ceb_x_preferred":[
        "La S\u00e1bana"
    ],
    "name:spa_x_preferred":[
        "La Sabana"
    ],
    "name:spa_x_variant":[
        "La Brecha"
    ],
    "name:urd_x_preferred":[
        "\u0644\u0627 \u0633\u0627\u0628\u0627\u0646\u0627"
    ],
    "wof:name":"La Sabana",
    "wof:placetype":"locality"
},
  "geometry": {"coordinates":[-98.06473,21.18296],"type":"Point"}
}