{
  "type": "Feature",
  "properties": {
    "gn:admin1_code":"20",
    "gn:admin2_code":"13.0",
    "gn:asciiname":"La Olegaria (Los Rosalitos)",
    "gn:country_code":"MX",
    "gn:dem":1497,
    "gn:feature_class":"P",
    "gn:feature_code":"PPL",
    "gn:name":"La Olegaria (Los Rosalitos)",
    "gn:population":5,
    "gn:timezone":"America/Mexico_City",
    "iso:country":"MX",
    "wof:name":"La Olegaria (Los Rosalitos)",
    "wof:placetype":"locality",
    "wof:population":5
},
  "geometry": {"coordinates":[-96.76333,16.89889],"type":"Point"}
}