{
  "type": "Feature",
  "properties": {
    "gn:admin1_code":"20",
    "gn:admin2_code":"548",
    "gn:asciiname":"El Rosario",
    "gn:country_code":"MX",
    "gn:dem":2118,
    "gn:feature_class":"P",
    "gn:feature_code":"PPL",
    "gn:name":"El Rosario",
    "gn:population":18,
    "gn:timezone":"America/Mexico_City",
    "iso:country":"MX",
    "wof:name":"El Rosario",
    "wof:placetype":"locality",
    "wof:population":18
},
  "geometry": {"coordinates":[-97.31528,17.93972],"type":"Point"}
}