{
  "type": "Feature",
  "properties": {
    "gn:admin1_code":"16",
    "gn:admin2_code":"99.0",
    "gn:asciiname":"El Cirian de Cimientillos",
    "gn:country_code":"MX",
    "gn:dem":1332,
    "gn:feature_class":"P",
    "gn:feature_code":"PPL",
    "gn:name":"El Ciri\u00e1n de Cimientillos",
    "gn:population":0,
    "gn:timezone":"America/Mexico_City",
    "iso:country":"MX",
    "name:spa_x_preferred":[
        "El Ciri\u00e1n de Cimientillos"
    ],
    "wof:name":"El Cirian de Cimientillos",
    "wof:placetype":"locality"
},
  "geometry": {"coordinates":[-100.67894,19.32422],"type":"Point"}
}