{
  "type": "Feature",
  "properties": {
    "gn:admin1_code":"10.0",
    "gn:admin2_code":"25.0",
    "gn:asciiname":"El Cuarenta",
    "gn:country_code":"MX",
    "gn:dem":1761,
    "gn:feature_class":"P",
    "gn:feature_code":"PPL",
    "gn:name":"El Cuarenta",
    "gn:population":0,
    "gn:timezone":"America/Monterrey",
    "iso:country":"MX",
    "name:spa_x_preferred":[
        "El Cuarenta"
    ],
    "wof:name":"El Cuarenta",
    "wof:placetype":"locality"
},
  "geometry": {"coordinates":[-105.53740000000001,26.14347],"type":"Point"}
}