{
  "type": "Feature",
  "properties": {
    "gn:admin1_code":"32.0",
    "gn:admin2_code":"16.0",
    "gn:asciiname":"La Palma Larga",
    "gn:country_code":"MX",
    "gn:dem":2055,
    "gn:feature_class":"P",
    "gn:feature_code":"PPL",
    "gn:name":"La Palma Larga",
    "gn:population":0,
    "gn:timezone":"America/Mexico_City",
    "iso:country":"MX",
    "name:spa_x_preferred":[
        "La Palma Larga"
    ],
    "wof:name":"La Palma Larga",
    "wof:placetype":"locality"
},
  "geometry": {"coordinates":[-102.05325000000001,22.7047],"type":"Point"}
}