{
  "type": "Feature",
  "properties": {
    "gn:admin1_code":"26",
    "gn:admin2_code":"18.0",
    "gn:asciiname":"El Rodeo (La Mosca)",
    "gn:country_code":"MX",
    "gn:dem":42,
    "gn:feature_class":"P",
    "gn:feature_code":"PPL",
    "gn:name":"El Rodeo (La Mosca)",
    "gn:population":9,
    "gn:timezone":"America/Hermosillo",
    "iso:country":"MX",
    "wof:name":"El Rodeo (La Mosca)",
    "wof:placetype":"locality",
    "wof:population":9
},
  "geometry": {"coordinates":[-109.89028,27.44389],"type":"Point"}
}