{
  "type": "Feature",
  "properties": {
    "gn:admin1_code":"23.0",
    "gn:asciiname":"Las Ilusiones",
    "gn:country_code":"MX",
    "gn:dem":72,
    "gn:feature_class":"P",
    "gn:feature_code":"PPL",
    "gn:name":"Las Ilusiones",
    "gn:population":0,
    "gn:timezone":"America/Cancun",
    "iso:country":"MX",
    "name:spa_x_preferred":[
        "Las Ilusiones"
    ],
    "wof:name":"Las Ilusiones",
    "wof:placetype":"locality"
},
  "geometry": {"coordinates":[-89.06308,19.00949],"type":"Point"}
}