{
  "type": "Feature",
  "properties": {
    "gn:admin1_code":"30.0",
    "gn:admin2_code":"155.0",
    "gn:asciiname":"El Mamey",
    "gn:country_code":"MX",
    "gn:dem":188,
    "gn:feature_class":"P",
    "gn:feature_code":"PPL",
    "gn:name":"El Mamey",
    "gn:population":253,
    "gn:timezone":"America/Mexico_City",
    "iso:country":"MX",
    "name:spa_x_preferred":[
        "El Mamey"
    ],
    "wof:name":"El Mamey",
    "wof:placetype":"locality",
    "wof:population":253
},
  "geometry": {"coordinates":[-98.26555999999999,21.34083],"type":"Point"}
}