{
  "type": "Feature",
  "properties": {
    "gn:admin1_code":"14",
    "gn:admin2_code":"99.0",
    "gn:asciiname":"Las Tunas",
    "gn:country_code":"MX",
    "gn:dem":845,
    "gn:feature_class":"P",
    "gn:feature_code":"PPL",
    "gn:name":"Las Tunas",
    "gn:population":8,
    "gn:timezone":"America/Mexico_City",
    "iso:country":"MX",
    "name:ceb_x_preferred":[
        "Las Tunas"
    ],
    "name:deu_x_preferred":[
        "Las Tunas"
    ],
    "name:heb_x_preferred":[
        "\u05dc\u05d0\u05e1 \u05d8\u05d5\u05e0\u05d0\u05e1"
    ],
    "name:nld_x_preferred":[
        "Las Tunas"
    ],
    "name:pol_x_preferred":[
        "Las Tunas"
    ],
    "name:por_x_preferred":[
        "Las Tunas"
    ],
    "name:sco_x_preferred":[
        "Las Tunas"
    ],
    "name:spa_x_preferred":[
        "Las Tunas"
    ],
    "name:srp_x_preferred":[
        "\u041b\u0430\u0441 \u0422\u0443\u043d\u0430\u0441"
    ],
    "name:swe_x_preferred":[
        "Las Tunas"
    ],
    "name:tur_x_preferred":[
        "Las Tunas"
    ],
    "wof:name":"Las Tunas",
    "wof:placetype":"locality",
    "wof:population":8
},
  "geometry": {"coordinates":[-103.88833,19.56528],"type":"Point"}
}