{
  "type": "Feature",
  "properties": {
    "gn:admin1_code":"10",
    "gn:admin2_code":"21.0",
    "gn:asciiname":"Burrolas",
    "gn:country_code":"MX",
    "gn:dem":1938,
    "gn:feature_class":"P",
    "gn:feature_code":"PPL",
    "gn:name":"Burrolas",
    "gn:population":0,
    "gn:timezone":"America/Monterrey",
    "iso:country":"MX",
    "name:spa_x_preferred":[
        "Burrolas"
    ],
    "wof:name":"Burrolas",
    "wof:placetype":"locality"
},
  "geometry": {"coordinates":[-103.95619000000001,24.59312000000001],"type":"Point"}
}