{
  "type": "Feature",
  "properties": {
    "gn:admin1_code":"11",
    "gn:admin2_code":"33",
    "gn:asciiname":"Praga",
    "gn:country_code":"MX",
    "gn:dem":2017,
    "gn:feature_class":"P",
    "gn:feature_code":"PPL",
    "gn:name":"Praga",
    "gn:population":32,
    "gn:timezone":"America/Mexico_City",
    "iso:country":"MX",
    "name:ces_x_preferred":[
        "Praga"
    ],
    "name:deu_x_preferred":[
        "Praga"
    ],
    "name:epo_x_preferred":[
        "Praga"
    ],
    "name:est_x_preferred":[
        "Praga"
    ],
    "name:fra_x_preferred":[
        "Praga"
    ],
    "name:ita_x_preferred":[
        "Praga"
    ],
    "name:nld_x_preferred":[
        "Praga"
    ],
    "name:pol_x_preferred":[
        "Praga"
    ],
    "name:por_x_preferred":[
        "Praga"
    ],
    "name:rus_x_preferred":[
        "\u041f\u0440\u0430\u0433\u0430"
    ],
    "name:slk_x_preferred":[
        "Praga"
    ],
    "name:swe_x_preferred":[
        "Praga"
    ],
    "name:ukr_x_preferred":[
        "\u041f\u0440\u0430\u0433\u0430"
    ],
    "name:vie_x_preferred":[
        "Praga"
    ],
    "wof:name":"Praga",
    "wof:placetype":"locality",
    "wof:population":32
},
  "geometry": {"coordinates":[-100.67694,21.34056],"type":"Point"}
}