{
  "type": "Feature",
  "properties": {
    "gn:admin1_code":"11",
    "gn:admin2_code":"33",
    "gn:asciiname":"Praga",
    "gn:country_code":"MX",
    "gn:dem":2017,
    "gn:feature_class":"P",
    "gn:feature_code":"PPL",
    "gn:name":"Praga",
    "gn:population":32,
    "gn:timezone":"America/Mexico_City",
    "iso:country":"MX",
    "wof:name":"Praga",
    "wof:placetype":"locality",
    "wof:population":32
},
  "geometry": {"coordinates":[-100.67694,21.34056],"type":"Point"}
}