{
  "type": "Feature",
  "properties": {
    "gn:admin1_code":"19.0",
    "gn:asciiname":"El Chamal",
    "gn:country_code":"MX",
    "gn:dem":521,
    "gn:feature_class":"P",
    "gn:feature_code":"PPL",
    "gn:name":"El Chamal",
    "gn:population":0,
    "gn:timezone":"America/Monterrey",
    "iso:country":"MX",
    "name:spa_x_preferred":[
        "El Chamal"
    ],
    "wof:name":"El Chamal",
    "wof:placetype":"locality"
},
  "geometry": {"coordinates":[-99.72194,24.77723],"type":"Point"}
}