{
  "type": "Feature",
  "properties": {
    "gn:admin1_code":"25",
    "gn:admin2_code":"12",
    "gn:asciiname":"El Varal de Arriba",
    "gn:country_code":"MX",
    "gn:dem":132,
    "gn:feature_class":"P",
    "gn:feature_code":"PPL",
    "gn:name":"El Varal de Arriba",
    "gn:population":13,
    "gn:timezone":"America/Mazatlan",
    "iso:country":"MX",
    "wof:name":"El Varal de Arriba",
    "wof:placetype":"locality",
    "wof:population":13
},
  "geometry": {"coordinates":[-106.40304999999999,23.48233],"type":"Point"}
}