{
  "type": "Feature",
  "properties": {
    "iso:country":"MX",
    "name:ast_x_preferred":[
        "Solidaridad"
    ],
    "name:ben_x_preferred":[
        "\u09b8\u09cb\u09b2\u09bf\u09a6\u09be\u09b0\u09bf\u09a6\u09be\u09a6 \u09aa\u09cc\u09b0\u09b8\u09ad\u09be"
    ],
    "name:cat_x_preferred":[
        "Solidaridad"
    ],
    "name:ceb_x_preferred":[
        "Solidaridad"
    ],
    "name:deu_x_preferred":[
        "Municipio Solidaridad"
    ],
    "name:deu_x_variant":[
        "Solidaridad"
    ],
    "name:eng_x_preferred":[
        "Solidaridad"
    ],
    "name:epo_x_preferred":[
        "Solidaridad"
    ],
    "name:eus_x_preferred":[
        "Solidaridad"
    ],
    "name:fra_x_preferred":[
        "Solidaridad"
    ],
    "name:hbs_x_preferred":[
        "Op\u0161tina Solidaridad"
    ],
    "name:ita_x_preferred":[
        "Solidaridad"
    ],
    "name:lad_x_preferred":[
        "Solidaridad"
    ],
    "name:nah_x_preferred":[
        "Solidaridad"
    ],
    "name:nld_x_preferred":[
        "Solidaridad"
    ],
    "name:nob_x_preferred":[
        "Solidaridad"
    ],
    "name:nor_x_preferred":[
        "Solidaridad"
    ],
    "name:pol_x_preferred":[
        "Solidaridad"
    ],
    "name:por_x_preferred":[
        "Solidaridad"
    ],
    "name:rus_x_preferred":[
        "\u0421\u043e\u043b\u0438\u0434\u0430\u0440\u0438\u0434\u0430\u0434"
    ],
    "name:sco_x_preferred":[
        "Solidaridad"
    ],
    "name:spa_x_preferred":[
        "Solidaridad"
    ],
    "name:srp_x_preferred":[
        "\u041e\u043f\u0448\u0442\u0438\u043d\u0430 \u0421\u043e\u043b\u0438\u0434\u0430\u0440\u0438\u0434\u0430\u0434"
    ],
    "name:swe_x_preferred":[
        "Solidaridad"
    ],
    "name:urd_x_preferred":[
        "\u0633\u0648\u0644\u06cc\u062f\u0627\u0631\u06cc\u062f\u0627\u062f\u060c \u06a9\u0648\u06cc\u0646\u062a\u0627\u0646\u0627 \u0631\u0648"
    ],
    "name:urd_x_variant":[
        "\u0633\u0648\u0644\u06cc\u062f\u0627\u0631\u06cc\u062f\u0627\u062f"
    ],
    "name:vie_x_preferred":[
        "Solidaridad"
    ],
    "name:zho_x_preferred":[
        "\u7d22\u5229\u9054\u9e97\u9054\u7279"
    ],
    "qs:gn_adm0_cc":"MX",
    "qs:gn_fcode":"PPL",
    "qs:gn_local":3521342,
    "qs:gn_nam_loc":"playa del carmen",
    "qs:gn_namadm1":"23",
    "qs:gn_name":"Solidaridad",
    "qs:local_max":10960,
    "qs:local_sum":28603,
    "qs:localhoods":9,
    "qs:name":"Solidaridad",
    "qs:name_adm0":"M\u00e9xico",
    "qs:name_adm1":"Quintana Roo",
    "qs:name_adm2":"Solidaridad",
    "qs:name_local":"Playa del Carmen",
    "qs:photo_max":1420,
    "qs:photo_sum":6226,
    "qs:placetype":"Suburb",
    "qs:quad_count":50,
    "qs:woe_adm0":23424900,
    "qs:woe_adm1":2346286,
    "qs:woe_adm2":24550675,
    "qs:woe_lau":0,
    "qs:woe_local":136973,
    "qs:woe_ver":"7.10.0",
    "wd:wordcount":543,
    "wof:lang":[
        "spa"
    ],
    "wof:name":"Solidaridad",
    "wof:placetype":"neighbourhood"
},
  "geometry": {"coordinates":[-87.094559,20.606564],"type":"Point"}
}