{
  "type": "Feature",
  "properties": {
    "gn:admin1_code":"20",
    "gn:admin2_code":"124",
    "gn:asciiname":"Comun (Bioongo)",
    "gn:country_code":"MX",
    "gn:dem":25,
    "gn:feature_class":"P",
    "gn:feature_code":"PPL",
    "gn:name":"Com\u00fan (Bioongo)",
    "gn:population":32,
    "gn:timezone":"America/Mexico_City",
    "iso:country":"MX",
    "name:und_x_variant":[
        "Com\u00fan (Bioongo)"
    ],
    "wof:name":"Comun (Bioongo)",
    "wof:placetype":"locality",
    "wof:population":32
},
  "geometry": {"coordinates":[-95.16083,16.29111],"type":"Point"}
}