{
  "type": "Feature",
  "properties": {
    "gn:admin1_code":"11.0",
    "gn:admin2_code":"33.0",
    "gn:asciiname":"Las Adjuntas de San Jose",
    "gn:country_code":"MX",
    "gn:dem":2199,
    "gn:feature_class":"P",
    "gn:feature_code":"PPL",
    "gn:name":"Las Adjuntas de San Jos\u00e9",
    "gn:population":0,
    "gn:timezone":"America/Mexico_City",
    "iso:country":"MX",
    "name:spa_x_preferred":[
        "Las Adjuntas de San Jos\u00e9"
    ],
    "wof:name":"Las Adjuntas de San Jose",
    "wof:placetype":"locality"
},
  "geometry": {"coordinates":[-100.66039000000001,21.49141],"type":"Point"}
}