{
  "type": "Feature",
  "properties": {
    "gn:admin1_code":"30",
    "gn:admin2_code":"143.0",
    "gn:asciiname":"Colonia Cuesta Abajo",
    "gn:country_code":"MX",
    "gn:dem":281,
    "gn:feature_class":"P",
    "gn:feature_code":"PPL",
    "gn:name":"Colonia Cuesta Abajo",
    "gn:population":60,
    "gn:timezone":"America/Mexico_City",
    "iso:country":"MX",
    "wof:name":"Colonia Cuesta Abajo",
    "wof:placetype":"locality",
    "wof:population":60
},
  "geometry": {"coordinates":[-95.2925,18.46306],"type":"Point"}
}