{
  "type": "Feature",
  "properties": {
    "gn:admin1_code":"26",
    "gn:admin2_code":"30.0",
    "gn:asciiname":"Danny",
    "gn:country_code":"MX",
    "gn:dem":272,
    "gn:feature_class":"P",
    "gn:feature_code":"PPL",
    "gn:name":"Danny",
    "gn:population":9,
    "gn:timezone":"America/Hermosillo",
    "iso:country":"MX",
    "wof:name":"Danny",
    "wof:placetype":"locality",
    "wof:population":9
},
  "geometry": {"coordinates":[-110.79389,29.03306],"type":"Point"}
}