{
  "type": "Feature",
  "properties": {
    "gn:admin1_code":"30",
    "gn:admin2_code":"23.0",
    "gn:asciiname":"Tepanapa",
    "gn:country_code":"MX",
    "gn:dem":728,
    "gn:feature_class":"P",
    "gn:feature_code":"PPL",
    "gn:name":"Tepanapa",
    "gn:population":5,
    "gn:timezone":"America/Mexico_City",
    "iso:country":"MX",
    "wof:name":"Tepanapa",
    "wof:placetype":"locality",
    "wof:population":5
},
  "geometry": {"coordinates":[-97.15222,19.86139],"type":"Point"}
}