{
  "type": "Feature",
  "properties": {
    "gn:admin1_code":"1",
    "gn:admin2_code":"9",
    "gn:asciiname":"Kilometro 2",
    "gn:country_code":"MX",
    "gn:dem":1951,
    "gn:feature_class":"P",
    "gn:feature_code":"PPL",
    "gn:name":"Kil\u00f3metro 2",
    "gn:population":11,
    "gn:timezone":"America/Mexico_City",
    "iso:country":"MX",
    "name:und_x_variant":[
        "Kil\u00f3metro 2"
    ],
    "wof:name":"Kilometro 2",
    "wof:placetype":"locality",
    "wof:population":11
},
  "geometry": {"coordinates":[-102.22778,22.18639],"type":"Point"}
}