{
  "type": "Feature",
  "properties": {
    "gn:admin1_code":"32",
    "gn:admin2_code":"12.0",
    "gn:asciiname":"El Salto Prieto",
    "gn:country_code":"MX",
    "gn:dem":2333,
    "gn:feature_class":"P",
    "gn:feature_code":"PPL",
    "gn:name":"El Salto Prieto",
    "gn:population":76,
    "gn:timezone":"America/Mexico_City",
    "iso:country":"MX",
    "wof:name":"El Salto Prieto",
    "wof:placetype":"locality",
    "wof:population":76
},
  "geometry": {"coordinates":[-102.52278,22.50306],"type":"Point"}
}