{
  "type": "Feature",
  "properties": {
    "gn:admin1_code":"20",
    "gn:admin2_code":"24",
    "gn:asciiname":"El Zacatal",
    "gn:country_code":"MX",
    "gn:dem":1109,
    "gn:feature_class":"P",
    "gn:feature_code":"PPL",
    "gn:name":"El Zacatal",
    "gn:population":30,
    "gn:timezone":"America/Mexico_City",
    "iso:country":"MX",
    "wof:name":"El Zacatal",
    "wof:placetype":"locality",
    "wof:population":30
},
  "geometry": {"coordinates":[-96.83556,17.99667],"type":"Point"}
}