{
  "type": "Feature",
  "properties": {
    "gn:admin1_code":"15",
    "gn:asciiname":"Zamayoa",
    "gn:cc2":"MX",
    "gn:country_code":"MX",
    "gn:dem":1174,
    "gn:feature_class":"P",
    "gn:feature_code":"PPL",
    "gn:name":"Zamayoa",
    "gn:population":0,
    "gn:timezone":"America/Mexico_City",
    "iso:country":"MX",
    "name:und_x_variant":[
        "Zamaya",
        "Zamayoa"
    ],
    "wof:name":"Zamayoa",
    "wof:placetype":"locality"
},
  "geometry": {"coordinates":[-99.45,18.76667],"type":"Point"}
}