{
  "type": "Feature",
  "properties": {
    "gn:admin1_code":"25",
    "gn:admin2_code":"1.0",
    "gn:asciiname":"Cerro Cabezon (El Chorrito)",
    "gn:country_code":"MX",
    "gn:dem":6,
    "gn:feature_class":"P",
    "gn:feature_code":"PPL",
    "gn:name":"Cerro Cabez\u00f3n (El Chorrito)",
    "gn:population":173,
    "gn:timezone":"America/Mazatlan",
    "iso:country":"MX",
    "wof:name":"Cerro Cabezon (El Chorrito)",
    "wof:placetype":"locality",
    "wof:population":173
},
  "geometry": {"coordinates":[-108.88647,25.6351],"type":"Point"}
}