{
  "type": "Feature",
  "properties": {
    "gn:admin1_code":"15.0",
    "gn:admin2_code":"82.0",
    "gn:asciiname":"Las Juntas",
    "gn:country_code":"MX",
    "gn:dem":521,
    "gn:feature_class":"P",
    "gn:feature_code":"PPL",
    "gn:name":"Las Juntas",
    "gn:population":0,
    "gn:timezone":"America/Mexico_City",
    "iso:country":"MX",
    "name:ceb_x_preferred":[
        "Las Juntas"
    ],
    "name:deu_x_preferred":[
        "Las Juntas"
    ],
    "name:spa_x_preferred":[
        "Las Juntas"
    ],
    "name:swe_x_preferred":[
        "Las Juntas"
    ],
    "wof:name":"Las Juntas",
    "wof:placetype":"locality"
},
  "geometry": {"coordinates":[-100.44748,18.78229],"type":"Point"}
}