{
  "type": "Feature",
  "properties": {
    "gn:admin1_code":"28",
    "gn:admin2_code":"2",
    "gn:asciiname":"La Playa Dos (Barra del Tordo)",
    "gn:country_code":"MX",
    "gn:dem":4,
    "gn:feature_class":"P",
    "gn:feature_code":"PPL",
    "gn:name":"La Playa Dos (Barra del Tordo)",
    "gn:population":36,
    "gn:timezone":"America/Monterrey",
    "iso:country":"MX",
    "wof:name":"La Playa Dos (Barra del Tordo)",
    "wof:placetype":"locality",
    "wof:population":36
},
  "geometry": {"coordinates":[-97.76195,23.02722],"type":"Point"}
}