{
  "type": "Feature",
  "properties": {
    "gn:admin1_code":"20.0",
    "gn:asciiname":"La Pochota",
    "gn:country_code":"MX",
    "gn:dem":825,
    "gn:feature_class":"P",
    "gn:feature_code":"PPL",
    "gn:name":"La Pochota",
    "gn:population":0,
    "gn:timezone":"America/Mexico_City",
    "iso:country":"MX",
    "name:spa_x_preferred":[
        "La Pochota"
    ],
    "name:spa_x_variant":[
        "Arroyo Tambor"
    ],
    "wof:name":"La Pochota",
    "wof:placetype":"locality"
},
  "geometry": {"coordinates":[-96.57612,17.95326],"type":"Point"}
}