{
  "type": "Feature",
  "properties": {
    "gn:admin1_code":"6.0",
    "gn:admin2_code":"8.0",
    "gn:asciiname":"Rayevo",
    "gn:country_code":"MX",
    "gn:dem":2270,
    "gn:feature_class":"P",
    "gn:feature_code":"PPL",
    "gn:name":"Rayevo",
    "gn:population":0,
    "gn:timezone":"America/Chihuahua",
    "iso:country":"MX",
    "name:bak_x_preferred":[
        "\u0420\u0430\u0435\u0432"
    ],
    "name:che_x_preferred":[
        "\u0420\u0430\u0435\u0432\u043e"
    ],
    "name:hye_x_preferred":[
        "\u054c\u0561\u0587\u0578"
    ],
    "name:kaz_x_preferred":[
        "\u0420\u0430"
    ],
    "name:kir_x_preferred":[
        "\u0420\u0430"
    ],
    "name:rus_x_preferred":[
        "\u0420\u0430\u0435\u0432\u043e"
    ],
    "name:spa_x_preferred":[
        "Rayevo"
    ],
    "name:tat_x_preferred":[
        "\u0420\u0430\u0435\u0432\u043e"
    ],
    "name:ukr_x_preferred":[
        "\u0420\u0430\u0454\u0432\u043e"
    ],
    "wof:name":"Rayevo",
    "wof:placetype":"locality"
},
  "geometry": {"coordinates":[-107.46877000000001,27.002],"type":"Point"}
}