{
  "type": "Feature",
  "properties": {
    "gn:admin1_code":"30",
    "gn:admin2_code":"70.0",
    "gn:asciiname":"Galapata",
    "gn:country_code":"MX",
    "gn:dem":12,
    "gn:feature_class":"P",
    "gn:feature_code":"PPL",
    "gn:name":"Galapata",
    "gn:population":69,
    "gn:timezone":"America/Mexico_City",
    "iso:country":"MX",
    "wof:name":"Galapata",
    "wof:placetype":"locality",
    "wof:population":69
},
  "geometry": {"coordinates":[-94.67417,17.71111],"type":"Point"}
}