{
  "type": "Feature",
  "properties": {
    "gn:admin1_code":"1",
    "gn:admin2_code":"10",
    "gn:asciiname":"El 65 [Rancho]",
    "gn:country_code":"MX",
    "gn:dem":1996,
    "gn:feature_class":"P",
    "gn:feature_code":"PPL",
    "gn:name":"El 65 [Rancho]",
    "gn:population":13,
    "gn:timezone":"America/Mexico_City",
    "iso:country":"MX",
    "wof:name":"El 65 [Rancho]",
    "wof:placetype":"locality",
    "wof:population":13
},
  "geometry": {"coordinates":[-102.13527999999999,21.82639],"type":"Point"}
}