{
  "type": "Feature",
  "properties": {
    "gn:admin1_code":"24",
    "gn:admin2_code":"37",
    "gn:asciiname":"Acuapich (Pixteyo)",
    "gn:country_code":"MX",
    "gn:dem":174,
    "gn:feature_class":"P",
    "gn:feature_code":"PPL",
    "gn:name":"Acuapich (Pixteyo)",
    "gn:population":52,
    "gn:timezone":"America/Mexico_City",
    "iso:country":"MX",
    "wof:name":"Acuapich (Pixteyo)",
    "wof:placetype":"locality",
    "wof:population":52
},
  "geometry": {"coordinates":[-98.66444,21.20361],"type":"Point"}
}