{
  "type": "Feature",
  "properties": {
    "gn:admin1_code":"30",
    "gn:admin2_code":"130.0",
    "gn:asciiname":"Arroyo Bermejo",
    "gn:country_code":"MX",
    "gn:dem":39,
    "gn:feature_class":"P",
    "gn:feature_code":"PPL",
    "gn:name":"Arroyo Bermejo",
    "gn:population":0,
    "gn:timezone":"America/Mexico_City",
    "iso:country":"MX",
    "name:spa_x_preferred":[
        "Arroyo Bermejo"
    ],
    "wof:name":"Arroyo Bermejo",
    "wof:placetype":"locality"
},
  "geometry": {"coordinates":[-95.72741000000001,17.8925],"type":"Point"}
}