{
  "type": "Feature",
  "properties": {
    "gn:admin1_code":"20",
    "gn:admin2_code":"44.0",
    "gn:asciiname":"Santa Sofia Monte Rosa",
    "gn:country_code":"MX",
    "gn:dem":63,
    "gn:feature_class":"P",
    "gn:feature_code":"PPL",
    "gn:name":"Santa Sofia Monte Rosa",
    "gn:population":0,
    "gn:timezone":"America/Mexico_City",
    "iso:country":"MX",
    "name:spa_x_preferred":[
        "Santa Sofia Monte Rosa"
    ],
    "name:spa_x_variant":[
        "Monte Rosa"
    ],
    "wof:name":"Santa Sofia Monte Rosa",
    "wof:placetype":"locality"
},
  "geometry": {"coordinates":[-95.90937,17.78223999999999],"type":"Point"}
}