{
  "type": "Feature",
  "properties": {
    "gn:admin1_code":"24.0",
    "gn:admin2_code":"32.0",
    "gn:asciiname":"Agua de Pascual",
    "gn:cc2":"MX",
    "gn:country_code":"MX",
    "gn:dem":1983,
    "gn:feature_class":"P",
    "gn:feature_code":"PPL",
    "gn:name":"Agua de Pascual",
    "gn:population":0,
    "gn:timezone":"America/Mexico_City",
    "iso:country":"MX",
    "name:und_x_variant":[
        "Agua Pascual",
        "Agua de Pascual"
    ],
    "wof:name":"Agua de Pascual",
    "wof:placetype":"locality"
},
  "geometry": {"coordinates":[-100.68333,21.58333],"type":"Point"}
}