{
  "type": "Feature",
  "properties": {
    "gn:admin1_code":"24",
    "gn:admin2_code":"24.0",
    "gn:asciiname":"Ildefonso Turrubiates",
    "gn:country_code":"MX",
    "gn:dem":1022,
    "gn:feature_class":"P",
    "gn:feature_code":"PPL",
    "gn:name":"Ildefonso Turrubiates",
    "gn:population":0,
    "gn:timezone":"America/Mexico_City",
    "iso:country":"MX",
    "name:spa_x_preferred":[
        "Ildefonso Turrubiates"
    ],
    "name:spa_x_variant":[
        "La Boquilla"
    ],
    "name:und_x_variant":[
        "Ildelfonso Turrubiates",
        "Idelfonso Turrubiates",
        "Boquilla"
    ],
    "wof:name":"Ildefonso Turrubiates",
    "wof:placetype":"locality"
},
  "geometry": {"coordinates":[-99.87063999999999,21.92559],"type":"Point"}
}