{
  "type": "Feature",
  "properties": {
    "gn:admin1_code":"30",
    "gn:admin2_code":"123.0",
    "gn:asciiname":"El Sendero",
    "gn:country_code":"MX",
    "gn:dem":4,
    "gn:feature_class":"P",
    "gn:feature_code":"PPL",
    "gn:name":"El Sendero",
    "gn:population":0,
    "gn:timezone":"America/Mexico_City",
    "iso:country":"MX",
    "name:und_x_variant":[
        "El Cerrito"
    ],
    "wof:name":"El Sendero",
    "wof:placetype":"locality"
},
  "geometry": {"coordinates":[-98.00896,22.16286],"type":"Point"}
}