{
  "type": "Feature",
  "properties": {
    "gn:admin1_code":"11",
    "gn:admin2_code":"27.0",
    "gn:asciiname":"Union de Liebres (Las Conejas)",
    "gn:country_code":"MX",
    "gn:dem":1721,
    "gn:feature_class":"P",
    "gn:feature_code":"PPL",
    "gn:name":"Uni\u00f3n de Liebres (Las Conejas)",
    "gn:population":433,
    "gn:timezone":"America/Mexico_City",
    "iso:country":"MX",
    "name:und_x_variant":[
        "Uni\u00f3n de Liebres (Las Conejas)"
    ],
    "wof:name":"Union de Liebres (Las Conejas)",
    "wof:placetype":"locality",
    "wof:population":433
},
  "geometry": {"coordinates":[-101.18167,20.64278],"type":"Point"}
}