{
  "type": "Feature",
  "properties": {
    "gn:admin1_code":"14.0",
    "gn:admin2_code":"84.0",
    "gn:asciiname":"Atalaya",
    "gn:country_code":"MX",
    "gn:dem":609,
    "gn:feature_class":"P",
    "gn:feature_code":"PPL",
    "gn:name":"Atalaya",
    "gn:population":0,
    "gn:timezone":"America/Mexico_City",
    "iso:country":"MX",
    "name:cat_x_preferred":[
        "Atalaya"
    ],
    "name:ceb_x_preferred":[
        "Atalaya"
    ],
    "name:deu_x_preferred":[
        "Atalaya"
    ],
    "name:fra_x_preferred":[
        "Atalaya"
    ],
    "name:ita_x_preferred":[
        "Atalaya"
    ],
    "name:nld_x_preferred":[
        "Atalaya"
    ],
    "name:nor_x_preferred":[
        "Atalaya"
    ],
    "name:pol_x_preferred":[
        "Atalaya"
    ],
    "name:por_x_preferred":[
        "Atalaya"
    ],
    "name:spa_x_preferred":[
        "Atalaya"
    ],
    "name:swe_x_preferred":[
        "Atalaya"
    ],
    "wof:name":"Atalaya",
    "wof:placetype":"locality"
},
  "geometry": {"coordinates":[-104.84986000000001,20.18277],"type":"Point"}
}