{
  "type": "Feature",
  "properties": {
    "gn:admin1_code":"21",
    "gn:admin2_code":"43",
    "gn:asciiname":"Tenexteta",
    "gn:country_code":"MX",
    "gn:dem":320,
    "gn:feature_class":"P",
    "gn:feature_code":"PPL",
    "gn:name":"Tenexteta",
    "gn:population":28,
    "gn:timezone":"America/Mexico_City",
    "iso:country":"MX",
    "wof:name":"Tenexteta",
    "wof:placetype":"locality",
    "wof:population":28
},
  "geometry": {"coordinates":[-97.45528,20.07137],"type":"Point"}
}