{
  "type": "Feature",
  "properties": {
    "gn:admin1_code":"14.0",
    "gn:asciiname":"Cabrito",
    "gn:country_code":"MX",
    "gn:dem":1894,
    "gn:feature_class":"P",
    "gn:feature_code":"PPL",
    "gn:name":"Cabrito",
    "gn:population":0,
    "gn:timezone":"America/Mexico_City",
    "iso:country":"MX",
    "name:jpn_x_preferred":[
        "\u30ab\u30d6\u30ea\u30c8"
    ],
    "name:kor_x_preferred":[
        "\uce74\ube0c\ub9ac\ud1a0"
    ],
    "name:scn_x_preferred":[
        "Crapettu"
    ],
    "name:spa_x_preferred":[
        "Cabrito"
    ],
    "name:tur_x_preferred":[
        "Cabrito"
    ],
    "wof:name":"Cabrito",
    "wof:placetype":"locality"
},
  "geometry": {"coordinates":[-102.27297,21.0925],"type":"Point"}
}