{
  "type": "Feature",
  "properties": {
    "gn:admin1_code":"18.0",
    "gn:admin2_code":"9.0",
    "gn:asciiname":"Don Calixtro",
    "gn:country_code":"MX",
    "gn:dem":1206,
    "gn:feature_class":"P",
    "gn:feature_code":"PPL",
    "gn:name":"Don Calixtro",
    "gn:population":0,
    "gn:timezone":"America/Mazatlan",
    "iso:country":"MX",
    "name:spa_x_preferred":[
        "Don Calixtro"
    ],
    "wof:name":"Don Calixtro",
    "wof:placetype":"locality"
},
  "geometry": {"coordinates":[-104.64918,22.03884],"type":"Point"}
}