{
  "type": "Feature",
  "properties": {
    "gn:admin1_code":"8",
    "gn:admin2_code":"8.0",
    "gn:asciiname":"Potrero Grande",
    "gn:country_code":"MX",
    "gn:dem":695,
    "gn:feature_class":"P",
    "gn:feature_code":"PPL",
    "gn:name":"Potrero Grande",
    "gn:population":0,
    "gn:timezone":"America/Mexico_City",
    "iso:country":"MX",
    "name:ceb_x_preferred":[
        "Potrero Grande"
    ],
    "name:spa_x_preferred":[
        "Potrero Grande"
    ],
    "wof:name":"Potrero Grande",
    "wof:placetype":"locality"
},
  "geometry": {"coordinates":[-104.08725,19.31475],"type":"Point"}
}