{
  "type": "Feature",
  "properties": {
    "gn:admin1_code":"15.0",
    "gn:asciiname":"Colonia Javier Barrios",
    "gn:country_code":"MX",
    "gn:dem":2459,
    "gn:feature_class":"P",
    "gn:feature_code":"PPL",
    "gn:name":"Colonia Jav\u00eder Barrios",
    "gn:population":0,
    "gn:timezone":"America/Mexico_City",
    "iso:country":"MX",
    "name:spa_x_preferred":[
        "Colonia Jav\u00eder Barrios"
    ],
    "wof:name":"Colonia Javier Barrios",
    "wof:placetype":"locality"
},
  "geometry": {"coordinates":[-99.53542,19.96739],"type":"Point"}
}