{
  "type": "Feature",
  "properties": {
    "gn:admin1_code":"20",
    "gn:admin2_code":"327.0",
    "gn:asciiname":"Amatillo",
    "gn:country_code":"MX",
    "gn:dem":51,
    "gn:feature_class":"P",
    "gn:feature_code":"PPL",
    "gn:name":"Amatillo",
    "gn:population":6,
    "gn:timezone":"America/Mexico_City",
    "iso:country":"MX",
    "wof:name":"Amatillo",
    "wof:placetype":"locality",
    "wof:population":6
},
  "geometry": {"coordinates":[-94.09972,16.33167000000001],"type":"Point"}
}