{
  "type": "Feature",
  "properties": {
    "gn:admin1_code":"16",
    "gn:admin2_code":"6.0",
    "gn:asciiname":"Las Bateas (El Venteadero)",
    "gn:country_code":"MX",
    "gn:dem":222,
    "gn:feature_class":"P",
    "gn:feature_code":"PPL",
    "gn:name":"Las Bateas (El Venteadero)",
    "gn:population":227,
    "gn:timezone":"America/Mexico_City",
    "iso:country":"MX",
    "wof:name":"Las Bateas (El Venteadero)",
    "wof:placetype":"locality",
    "wof:population":227
},
  "geometry": {"coordinates":[-102.48694,18.99306],"type":"Point"}
}