{
  "type": "Feature",
  "properties": {
    "gn:admin1_code":"30",
    "gn:admin2_code":"153.0",
    "gn:asciiname":"El Cafetal",
    "gn:country_code":"MX",
    "gn:dem":245,
    "gn:feature_class":"P",
    "gn:feature_code":"PPL",
    "gn:name":"El Cafetal",
    "gn:population":5,
    "gn:timezone":"America/Mexico_City",
    "iso:country":"MX",
    "name:spa_x_preferred":[
        "El Cafetal"
    ],
    "wof:name":"El Cafetal",
    "wof:placetype":"locality",
    "wof:population":5
},
  "geometry": {"coordinates":[-97.77889,21.25778],"type":"Point"}
}