{
  "type": "Feature",
  "properties": {
    "gn:admin1_code":"14",
    "gn:admin2_code":"93.0",
    "gn:asciiname":"La Majada",
    "gn:country_code":"MX",
    "gn:dem":1775,
    "gn:feature_class":"P",
    "gn:feature_code":"PPL",
    "gn:name":"La Majada",
    "gn:population":70,
    "gn:timezone":"America/Mexico_City",
    "iso:country":"MX",
    "wof:name":"La Majada",
    "wof:placetype":"locality",
    "wof:population":70
},
  "geometry": {"coordinates":[-102.75778,20.75361],"type":"Point"}
}