{
  "type": "Feature",
  "properties": {
    "gn:admin1_code":"13",
    "gn:admin2_code":"40.0",
    "gn:asciiname":"La Soledad (El Enebro)",
    "gn:country_code":"MX",
    "gn:dem":1044,
    "gn:feature_class":"P",
    "gn:feature_code":"PPL",
    "gn:name":"La Soledad (El Enebro)",
    "gn:population":388,
    "gn:timezone":"America/Mexico_City",
    "iso:country":"MX",
    "wof:name":"La Soledad (El Enebro)",
    "wof:placetype":"locality",
    "wof:population":388
},
  "geometry": {"coordinates":[-99.05753,21.13489],"type":"Point"}
}