{
  "type": "Feature",
  "properties": {
    "gn:admin1_code":"31",
    "gn:admin2_code":"104.0",
    "gn:asciiname":"Cacalchen",
    "gn:cc2":"MX",
    "gn:country_code":"MX",
    "gn:dem":25,
    "gn:feature_class":"P",
    "gn:feature_code":"PPL",
    "gn:name":"Cacalch\u00e9n",
    "gn:population":0,
    "gn:timezone":"America/Merida",
    "iso:country":"MX",
    "name:und_x_variant":[
        "Cacalghen",
        "Cacalch\u00e9n"
    ],
    "wof:name":"Cacalchen",
    "wof:placetype":"locality"
},
  "geometry": {"coordinates":[-88.76666999999998,20.51667],"type":"Point"}
}