{
  "type": "Feature",
  "properties": {
    "iso:country":"MX",
    "name:spa_x_preferred":[
        "Banamichi Centro"
    ],
    "qs:gn_adm0_cc":"MX",
    "qs:gn_local":4017582,
    "qs:gn_nam_loc":"banamichi",
    "qs:gn_namadm1":"26",
    "qs:local_max":77,
    "qs:local_sum":77,
    "qs:localhoods":1,
    "qs:name":"Banamichi Centro",
    "qs:name_adm0":"M\u00e9xico",
    "qs:name_adm1":"Sonora",
    "qs:name_adm2":"Banamichi",
    "qs:name_local":"Ban\u00e1michi",
    "qs:photo_max":77,
    "qs:photo_sum":77,
    "qs:placetype":"Suburb",
    "qs:quad_count":1,
    "qs:woe_adm0":23424900,
    "qs:woe_adm1":2346289,
    "qs:woe_adm2":12601557,
    "qs:woe_lau":0,
    "qs:woe_local":113030,
    "qs:woe_ver":"7.10.0",
    "wof:lang":[
        "spa"
    ],
    "wof:name":"Banamichi Centro",
    "wof:placetype":"neighbourhood"
},
  "geometry": {"coordinates":[-110.216217,30.008463],"type":"Point"}
}