{
  "type": "Feature",
  "properties": {
    "gn:admin1_code":"15",
    "gn:admin2_code":"74.0",
    "gn:asciiname":"Ejido de Tlalchichilpa",
    "gn:country_code":"MX",
    "gn:dem":2810,
    "gn:feature_class":"P",
    "gn:feature_code":"PPL",
    "gn:name":"Ejido de Tlalchichilpa",
    "gn:population":0,
    "gn:timezone":"America/Mexico_City",
    "iso:country":"MX",
    "name:spa_x_preferred":[
        "Ejido de Tlalchichilpa"
    ],
    "name:und_x_variant":[
        "Tlachichilpa"
    ],
    "wof:name":"Ejido de Tlalchichilpa",
    "wof:placetype":"locality"
},
  "geometry": {"coordinates":[-100.03198,19.72127],"type":"Point"}
}