{
  "type": "Feature",
  "properties": {
    "gn:admin1_code":"32",
    "gn:admin2_code":"9.0",
    "gn:asciiname":"Las Marinas",
    "gn:country_code":"MX",
    "gn:dem":2235,
    "gn:feature_class":"P",
    "gn:feature_code":"PPL",
    "gn:name":"Las Marinas",
    "gn:population":0,
    "gn:timezone":"America/Mexico_City",
    "iso:country":"MX",
    "name:spa_x_preferred":[
        "Las Marinas"
    ],
    "wof:name":"Las Marinas",
    "wof:placetype":"locality"
},
  "geometry": {"coordinates":[-103.95398,23.42049],"type":"Point"}
}