{
  "type": "Feature",
  "properties": {
    "gn:admin1_code":"32",
    "gn:admin2_code":"45.0",
    "gn:asciiname":"Las Chivas",
    "gn:country_code":"MX",
    "gn:dem":1814,
    "gn:feature_class":"P",
    "gn:feature_code":"PPL",
    "gn:name":"Las Chivas",
    "gn:population":0,
    "gn:timezone":"America/Mexico_City",
    "iso:country":"MX",
    "name:spa_x_preferred":[
        "Las Chivas"
    ],
    "wof:name":"Las Chivas",
    "wof:placetype":"locality"
},
  "geometry": {"coordinates":[-103.29782,21.62479],"type":"Point"}
}