{
  "type": "Feature",
  "properties": {
    "gn:admin1_code":"27",
    "gn:admin2_code":"1",
    "gn:asciiname":"Rancho Alegre",
    "gn:country_code":"MX",
    "gn:dem":35,
    "gn:feature_class":"P",
    "gn:feature_code":"PPL",
    "gn:name":"Rancho Alegre",
    "gn:population":15,
    "gn:timezone":"America/Mexico_City",
    "iso:country":"MX",
    "name:ceb_x_preferred":[
        "Rancho Alegre"
    ],
    "name:nld_x_preferred":[
        "Rancho Alegre"
    ],
    "name:por_x_preferred":[
        "Rancho Alegre"
    ],
    "name:swe_x_preferred":[
        "Rancho Alegre"
    ],
    "name:vol_x_preferred":[
        "Rancho Alegre"
    ],
    "wof:name":"Rancho Alegre",
    "wof:placetype":"locality",
    "wof:population":15
},
  "geometry": {"coordinates":[-91.26194,17.78917000000001],"type":"Point"}
}