{
  "type": "Feature",
  "properties": {
    "gn:admin1_code":"29",
    "gn:admin2_code":"37.0",
    "gn:asciiname":"Guadalupe los Capulines",
    "gn:country_code":"MX",
    "gn:dem":2619,
    "gn:feature_class":"P",
    "gn:feature_code":"PPL",
    "gn:name":"Guadalupe los Capulines",
    "gn:population":106,
    "gn:timezone":"America/Mexico_City",
    "iso:country":"MX",
    "wof:name":"Guadalupe los Capulines",
    "wof:placetype":"locality",
    "wof:population":106
},
  "geometry": {"coordinates":[-97.93043,19.17624],"type":"Point"}
}