{
  "type": "Feature",
  "properties": {
    "gn:admin1_code":"21.0",
    "gn:admin2_code":"197.0",
    "gn:asciiname":"Atequexquitla",
    "gn:country_code":"MX",
    "gn:dem":707,
    "gn:feature_class":"P",
    "gn:feature_code":"PPL",
    "gn:name":"Atequexquitla",
    "gn:population":858,
    "gn:timezone":"America/Mexico_City",
    "iso:country":"MX",
    "name:spa_x_preferred":[
        "Atequexquitla"
    ],
    "wof:name":"Atequexquitla",
    "wof:placetype":"locality",
    "wof:population":858
},
  "geometry": {"coordinates":[-97.8916,20.26454],"type":"Point"}
}