{
  "type": "Feature",
  "properties": {
    "gn:admin1_code":"27",
    "gn:admin2_code":"13.0",
    "gn:asciiname":"Amaton",
    "gn:country_code":"MX",
    "gn:dem":6,
    "gn:feature_class":"P",
    "gn:feature_code":"PPL",
    "gn:name":"Amat\u00f3n",
    "gn:population":74,
    "gn:timezone":"America/Mexico_City",
    "iso:country":"MX",
    "name:und_x_variant":[
        "Amat\u00f3n"
    ],
    "wof:name":"Amaton",
    "wof:placetype":"locality",
    "wof:population":74
},
  "geometry": {"coordinates":[-92.8925,18.08889],"type":"Point"}
}