{
  "type": "Feature",
  "properties": {
    "gn:admin1_code":"3.0",
    "gn:admin2_code":"2.0",
    "gn:asciiname":"Belisape Dominguez",
    "gn:country_code":"MX",
    "gn:dem":31,
    "gn:feature_class":"P",
    "gn:feature_code":"PPL",
    "gn:name":"Belisape Dom\u00ednguez",
    "gn:population":0,
    "gn:timezone":"America/Mazatlan",
    "iso:country":"MX",
    "name:spa_x_preferred":[
        "Belisape Dom\u00ednguez"
    ],
    "wof:name":"Belisape Dominguez",
    "wof:placetype":"locality"
},
  "geometry": {"coordinates":[-113.64751,27.53851],"type":"Point"}
}