{
  "type": "Feature",
  "properties": {
    "gn:admin1_code":"3",
    "gn:admin2_code":"3.0",
    "gn:asciiname":"El Aguajito",
    "gn:country_code":"MX",
    "gn:dem":230,
    "gn:feature_class":"P",
    "gn:feature_code":"PPL",
    "gn:name":"El Aguajito",
    "gn:population":0,
    "gn:timezone":"America/Mazatlan",
    "iso:country":"MX",
    "name:spa_x_preferred":[
        "El Aguajito"
    ],
    "wof:name":"El Aguajito",
    "wof:placetype":"locality"
},
  "geometry": {"coordinates":[-110.08279,23.30063],"type":"Point"}
}