{
  "type": "Feature",
  "properties": {
    "gn:admin1_code":"23",
    "gn:admin2_code":"4.0",
    "gn:asciiname":"Piedras Negras",
    "gn:country_code":"MX",
    "gn:dem":133,
    "gn:feature_class":"P",
    "gn:feature_code":"PPL",
    "gn:name":"Piedras Negras",
    "gn:population":0,
    "gn:timezone":"America/Cancun",
    "iso:country":"MX",
    "name:ceb_x_preferred":[
        "Piedras Negras"
    ],
    "name:deu_x_preferred":[
        "Piedras Negras"
    ],
    "name:fra_x_preferred":[
        "Piedras Negras"
    ],
    "name:ita_x_preferred":[
        "Piedras Negras"
    ],
    "name:nld_x_preferred":[
        "Piedras Negras"
    ],
    "name:spa_x_preferred":[
        "Piedras Negras"
    ],
    "name:swe_x_preferred":[
        "Piedras Negras"
    ],
    "name:vie_x_preferred":[
        "Piedras Negras"
    ],
    "wof:name":"Piedras Negras",
    "wof:placetype":"locality"
},
  "geometry": {"coordinates":[-89.01666999999998,18.46667],"type":"Point"}
}