{
  "type": "Feature",
  "properties": {
    "gn:admin1_code":"27",
    "gn:admin2_code":"2.0",
    "gn:asciiname":"Ampliacion Carrizal",
    "gn:country_code":"MX",
    "gn:dem":25,
    "gn:feature_class":"P",
    "gn:feature_code":"PPL",
    "gn:name":"Ampliaci\u00f3n Carrizal",
    "gn:population":192,
    "gn:timezone":"America/Mexico_City",
    "iso:country":"MX",
    "name:und_x_variant":[
        "Ampliaci\u00f3n Carrizal"
    ],
    "wof:name":"Ampliacion Carrizal",
    "wof:placetype":"locality",
    "wof:population":192
},
  "geometry": {"coordinates":[-93.395,18.02139],"type":"Point"}
}