{
  "type": "Feature",
  "properties": {
    "gn:admin1_code":"10",
    "gn:admin2_code":"34",
    "gn:asciiname":"Carricitos",
    "gn:country_code":"MX",
    "gn:dem":792,
    "gn:feature_class":"P",
    "gn:feature_code":"PPL",
    "gn:name":"Carricitos",
    "gn:population":26,
    "gn:timezone":"America/Monterrey",
    "iso:country":"MX",
    "wof:name":"Carricitos",
    "wof:placetype":"locality",
    "wof:population":26
},
  "geometry": {"coordinates":[-106.82868999999999,24.83581],"type":"Point"}
}