{
  "type": "Feature",
  "properties": {
    "gn:admin1_code":"10",
    "gn:admin2_code":"21.0",
    "gn:asciiname":"Los Panales",
    "gn:country_code":"MX",
    "gn:dem":1612,
    "gn:feature_class":"P",
    "gn:feature_code":"PPL",
    "gn:name":"Los Panales",
    "gn:population":8,
    "gn:timezone":"America/Monterrey",
    "iso:country":"MX",
    "wof:name":"Los Panales",
    "wof:placetype":"locality",
    "wof:population":8
},
  "geometry": {"coordinates":[-104.05482000000001,24.87373],"type":"Point"}
}