{
  "type": "Feature",
  "properties": {
    "gn:admin1_code":"7",
    "gn:admin2_code":"36.0",
    "gn:asciiname":"Noria Siete",
    "gn:country_code":"MX",
    "gn:dem":1136,
    "gn:feature_class":"P",
    "gn:feature_code":"PPL",
    "gn:name":"Noria Siete",
    "gn:population":0,
    "gn:timezone":"America/Monterrey",
    "iso:country":"MX",
    "name:spa_x_preferred":[
        "Noria Siete"
    ],
    "wof:name":"Noria Siete",
    "wof:placetype":"locality"
},
  "geometry": {"coordinates":[-103.22753,25.3041],"type":"Point"}
}