{
  "type": "Feature",
  "properties": {
    "gn:admin1_code":"30",
    "gn:admin2_code":"72.0",
    "gn:asciiname":"El Petandu",
    "gn:country_code":"MX",
    "gn:dem":1404,
    "gn:feature_class":"P",
    "gn:feature_code":"PPL",
    "gn:name":"El Petand\u00fa",
    "gn:population":7,
    "gn:timezone":"America/Mexico_City",
    "iso:country":"MX",
    "name:und_x_variant":[
        "El Petand\u00fa"
    ],
    "wof:name":"El Petandu",
    "wof:placetype":"locality",
    "wof:population":7
},
  "geometry": {"coordinates":[-98.40222,20.65806],"type":"Point"}
}