{
  "type": "Feature",
  "properties": {
    "gn:admin1_code":"31.0",
    "gn:asciiname":"El Girasol",
    "gn:country_code":"MX",
    "gn:dem":20,
    "gn:feature_class":"P",
    "gn:feature_code":"PPL",
    "gn:name":"El Girasol",
    "gn:population":0,
    "gn:timezone":"America/Merida",
    "iso:country":"MX",
    "name:spa_x_preferred":[
        "El Girasol"
    ],
    "wof:name":"El Girasol",
    "wof:placetype":"locality"
},
  "geometry": {"coordinates":[-88.25646999999999,21.22392],"type":"Point"}
}