{
  "type": "Feature",
  "properties": {
    "gn:admin1_code":"5",
    "gn:admin2_code":"79",
    "gn:asciiname":"Niquidambar",
    "gn:country_code":"MX",
    "gn:dem":1043,
    "gn:feature_class":"P",
    "gn:feature_code":"PPL",
    "gn:name":"Niquid\u00e1mbar",
    "gn:population":46,
    "gn:timezone":"America/Mexico_City",
    "iso:country":"MX",
    "name:und_x_variant":[
        "Niquid\u00e1mbar"
    ],
    "wof:name":"Niquidambar",
    "wof:placetype":"locality",
    "wof:population":46
},
  "geometry": {"coordinates":[-93.23917,16.89611],"type":"Point"}
}