{
  "type": "Feature",
  "properties": {
    "gn:admin1_code":"14",
    "gn:admin2_code":"119",
    "gn:asciiname":"La Playita",
    "gn:country_code":"MX",
    "gn:dem":1355,
    "gn:feature_class":"P",
    "gn:feature_code":"PPL",
    "gn:name":"La Playita",
    "gn:population":15,
    "gn:timezone":"America/Mexico_City",
    "iso:country":"MX",
    "wof:name":"La Playita",
    "wof:placetype":"locality",
    "wof:population":15
},
  "geometry": {"coordinates":[-103.59694,20.30139],"type":"Point"}
}