{
  "type": "Feature",
  "properties": {
    "gn:admin1_code":"32",
    "gn:admin2_code":"5.0",
    "gn:asciiname":"Los Tejabanes (Senor del Consuelo)",
    "gn:country_code":"MX",
    "gn:dem":2144,
    "gn:feature_class":"P",
    "gn:feature_code":"PPL",
    "gn:name":"Los Tejabanes (Se\u00f1or del Consuelo)",
    "gn:population":7,
    "gn:timezone":"America/Mexico_City",
    "iso:country":"MX",
    "name:und_x_variant":[
        "Los Tejabanes (Se\u00f1or del Consuelo)"
    ],
    "wof:name":"Los Tejabanes (Senor del Consuelo)",
    "wof:placetype":"locality",
    "wof:population":7
},
  "geometry": {"coordinates":[-102.64444,22.97806],"type":"Point"}
}