{
  "type": "Feature",
  "properties": {
    "gn:admin1_code":"6",
    "gn:admin2_code":"65.0",
    "gn:asciiname":"La Casita (Rancho Acosta)",
    "gn:country_code":"MX",
    "gn:dem":1875,
    "gn:feature_class":"P",
    "gn:feature_code":"PPL",
    "gn:name":"La Casita (Rancho Acosta)",
    "gn:population":6,
    "gn:timezone":"America/Chihuahua",
    "iso:country":"MX",
    "wof:name":"La Casita (Rancho Acosta)",
    "wof:placetype":"locality",
    "wof:population":6
},
  "geometry": {"coordinates":[-108.00055999999999,27.31056],"type":"Point"}
}