{
  "type": "Feature",
  "properties": {
    "gn:admin1_code":"24.0",
    "gn:admin2_code":"1.0",
    "gn:asciiname":"El Zapatero",
    "gn:country_code":"MX",
    "gn:dem":1908,
    "gn:feature_class":"P",
    "gn:feature_code":"PPL",
    "gn:name":"El Zapatero",
    "gn:population":252,
    "gn:timezone":"America/Mexico_City",
    "iso:country":"MX",
    "name:und_x_variant":[
        "Zapatero",
        "El Zapatero"
    ],
    "wof:name":"El Zapatero",
    "wof:placetype":"locality",
    "wof:population":252
},
  "geometry": {"coordinates":[-101.16849000000001,22.44049],"type":"Point"}
}