{
  "type": "Feature",
  "properties": {
    "gn:admin1_code":"16.0",
    "gn:asciiname":"San Antonio Parangare",
    "gn:country_code":"MX",
    "gn:dem":1922,
    "gn:feature_class":"P",
    "gn:feature_code":"PPL",
    "gn:name":"San Antonio Parangare",
    "gn:population":0,
    "gn:timezone":"America/Mexico_City",
    "iso:country":"MX",
    "name:spa_x_preferred":[
        "San Antonio Parangare"
    ],
    "wof:name":"San Antonio Parangare",
    "wof:placetype":"locality"
},
  "geometry": {"coordinates":[-101.29304,19.64616],"type":"Point"}
}