{
  "type": "Feature",
  "properties": {
    "gn:admin1_code":"21",
    "gn:admin2_code":"87",
    "gn:asciiname":"Teotlalcingo",
    "gn:country_code":"MX",
    "gn:dem":1277,
    "gn:feature_class":"P",
    "gn:feature_code":"PPL",
    "gn:name":"Teotlalcingo",
    "gn:population":46,
    "gn:timezone":"America/Mexico_City",
    "iso:country":"MX",
    "wof:name":"Teotlalcingo",
    "wof:placetype":"locality",
    "wof:population":46
},
  "geometry": {"coordinates":[-98.89473,18.35714],"type":"Point"}
}