{
  "type": "Feature",
  "properties": {
    "gn:admin1_code":"16",
    "gn:admin2_code":"69.0",
    "gn:asciiname":"Nuevo Cereso",
    "gn:country_code":"MX",
    "gn:dem":1789,
    "gn:feature_class":"P",
    "gn:feature_code":"PPL",
    "gn:name":"Nuevo Cereso",
    "gn:population":355,
    "gn:timezone":"America/Mexico_City",
    "iso:country":"MX",
    "wof:name":"Nuevo Cereso",
    "wof:placetype":"locality",
    "wof:population":355
},
  "geometry": {"coordinates":[-102.0425,20.29444],"type":"Point"}
}