{
  "type": "Feature",
  "properties": {
    "gn:admin1_code":"7",
    "gn:admin2_code":"24.0",
    "gn:asciiname":"Palo Alto (El Carrizal)",
    "gn:country_code":"MX",
    "gn:dem":1464,
    "gn:feature_class":"P",
    "gn:feature_code":"PPL",
    "gn:name":"Palo Alto (El Carrizal)",
    "gn:population":36,
    "gn:timezone":"America/Monterrey",
    "iso:country":"MX",
    "wof:name":"Palo Alto (El Carrizal)",
    "wof:placetype":"locality",
    "wof:population":36
},
  "geometry": {"coordinates":[-101.95475999999999,25.50892],"type":"Point"}
}