{
  "type": "Feature",
  "properties": {
    "gn:admin1_code":"20",
    "gn:admin2_code":"232",
    "gn:asciiname":"Colonia 22 de Noviembre",
    "gn:country_code":"MX",
    "gn:dem":87,
    "gn:feature_class":"P",
    "gn:feature_code":"PPL",
    "gn:name":"Colonia 22 de Noviembre",
    "gn:population":16,
    "gn:timezone":"America/Mexico_City",
    "iso:country":"MX",
    "wof:name":"Colonia 22 de Noviembre",
    "wof:placetype":"locality",
    "wof:population":16
},
  "geometry": {"coordinates":[-96.39167,18.10167],"type":"Point"}
}