{
  "type": "Feature",
  "properties": {
    "gn:admin1_code":"11",
    "gn:admin2_code":"3",
    "gn:asciiname":"Providencia de los Urbina",
    "gn:country_code":"MX",
    "gn:dem":2013,
    "gn:feature_class":"P",
    "gn:feature_code":"PPL",
    "gn:name":"Providencia de los Urbina",
    "gn:population":51,
    "gn:timezone":"America/Mexico_City",
    "iso:country":"MX",
    "wof:name":"Providencia de los Urbina",
    "wof:placetype":"locality",
    "wof:population":51
},
  "geometry": {"coordinates":[-100.58,21.07389],"type":"Point"}
}