{
  "type": "Feature",
  "properties": {
    "gn:admin1_code":"6",
    "gn:admin2_code":"49.0",
    "gn:asciiname":"Paraje Rancho Viejo",
    "gn:country_code":"MX",
    "gn:dem":1781,
    "gn:feature_class":"P",
    "gn:feature_code":"PPL",
    "gn:name":"Paraje Rancho Viejo",
    "gn:population":0,
    "gn:timezone":"America/Chihuahua",
    "iso:country":"MX",
    "name:spa_x_preferred":[
        "Paraje Rancho Viejo"
    ],
    "name:und_x_variant":[
        "Rancho Viejo"
    ],
    "wof:name":"Paraje Rancho Viejo",
    "wof:placetype":"locality"
},
  "geometry": {"coordinates":[-106.77889,27.21834],"type":"Point"}
}