{
  "type": "Feature",
  "properties": {
    "gn:admin1_code":"7",
    "gn:admin2_code":"38.0",
    "gn:asciiname":"La Manga el Oso",
    "gn:country_code":"MX",
    "gn:dem":694,
    "gn:feature_class":"P",
    "gn:feature_code":"PPL",
    "gn:name":"La Manga el Oso",
    "gn:population":0,
    "gn:timezone":"America/Monterrey",
    "iso:country":"MX",
    "name:spa_x_preferred":[
        "La Manga el Oso"
    ],
    "name:und_x_variant":[
        "Manga del Oso"
    ],
    "wof:name":"La Manga el Oso",
    "wof:placetype":"locality"
},
  "geometry": {"coordinates":[-101.5527,29.06218],"type":"Point"}
}