{
  "type": "Feature",
  "properties": {
    "gn:admin1_code":"6",
    "gn:admin2_code":"21.0",
    "gn:asciiname":"Vista Hermosa",
    "gn:country_code":"MX",
    "gn:dem":1201,
    "gn:feature_class":"P",
    "gn:feature_code":"PPL",
    "gn:name":"Vista Hermosa",
    "gn:population":5,
    "gn:timezone":"America/Chihuahua",
    "iso:country":"MX",
    "wof:name":"Vista Hermosa",
    "wof:placetype":"locality",
    "wof:population":5
},
  "geometry": {"coordinates":[-105.46963,28.15238],"type":"Point"}
}