{
  "type": "Feature",
  "properties": {
    "gn:admin1_code":"6",
    "gn:admin2_code":"23.0",
    "gn:asciiname":"Le Baron",
    "gn:country_code":"MX",
    "gn:dem":1471,
    "gn:feature_class":"P",
    "gn:feature_code":"PPL",
    "gn:name":"Le Bar\u00f3n",
    "gn:population":0,
    "gn:timezone":"America/Chihuahua",
    "iso:country":"MX",
    "name:spa_x_preferred":[
        "Le Bar\u00f3n"
    ],
    "wof:name":"Le Baron",
    "wof:placetype":"locality"
},
  "geometry": {"coordinates":[-107.56628000000001,30.0124],"type":"Point"}
}