{
  "type": "Feature",
  "properties": {
    "gn:admin1_code":"11",
    "gn:admin2_code":"27.0",
    "gn:asciiname":"Puerto de Valle",
    "gn:country_code":"MX",
    "gn:dem":1721,
    "gn:feature_class":"P",
    "gn:feature_code":"PPL",
    "gn:name":"Puerto de Valle",
    "gn:population":857,
    "gn:timezone":"America/Mexico_City",
    "iso:country":"MX",
    "wof:name":"Puerto de Valle",
    "wof:placetype":"locality",
    "wof:population":857
},
  "geometry": {"coordinates":[-101.13500000000001,20.48861],"type":"Point"}
}