{
  "type": "Feature",
  "properties": {
    "gn:admin1_code":"21",
    "gn:admin2_code":"19",
    "gn:asciiname":"Moyotzingo",
    "gn:country_code":"MX",
    "gn:dem":1939,
    "gn:feature_class":"P",
    "gn:feature_code":"PPL",
    "gn:name":"Moyotzingo",
    "gn:population":24,
    "gn:timezone":"America/Mexico_City",
    "iso:country":"MX",
    "wof:name":"Moyotzingo",
    "wof:placetype":"locality",
    "wof:population":24
},
  "geometry": {"coordinates":[-98.47581,18.91821],"type":"Point"}
}