{
  "type": "Feature",
  "properties": {
    "gn:admin1_code":"21.0",
    "gn:admin2_code":"15.0",
    "gn:asciiname":"San Mateo Mendizabal",
    "gn:country_code":"MX",
    "gn:dem":2279,
    "gn:feature_class":"P",
    "gn:feature_code":"PPL",
    "gn:name":"San Mateo Mendiz\u00e1bal",
    "gn:population":0,
    "gn:timezone":"America/Mexico_City",
    "iso:country":"MX",
    "name:spa_x_preferred":[
        "San Mateo Mendiz\u00e1val"
    ],
    "name:spa_x_variant":[
        "San Mateo Mendiz\u00e1bal"
    ],
    "wof:name":"San Mateo Mendizabal",
    "wof:placetype":"locality"
},
  "geometry": {"coordinates":[-98.0748,19.04119],"type":"Point"}
}