{
  "type": "Feature",
  "properties": {
    "gn:admin1_code":"25.0",
    "gn:admin2_code":"17.0",
    "gn:asciiname":"Chacoapana",
    "gn:country_code":"MX",
    "gn:dem":281,
    "gn:feature_class":"P",
    "gn:feature_code":"PPL",
    "gn:name":"Chacoapana",
    "gn:population":0,
    "gn:timezone":"America/Mazatlan",
    "iso:country":"MX",
    "name:spa_x_preferred":[
        "Chacoapana"
    ],
    "name:und_x_variant":[
        "Chacuapana"
    ],
    "wof:name":"Chacoapana",
    "wof:placetype":"locality"
},
  "geometry": {"coordinates":[-107.80897,25.87013],"type":"Point"}
}