{
  "type": "Feature",
  "properties": {
    "iso:country":"MX",
    "name:deu_x_preferred":[
        "Ojo de Agua"
    ],
    "name:nld_x_preferred":[
        "Ojo de Agua"
    ],
    "name:slk_x_preferred":[
        "Ojo de Agua"
    ],
    "name:spa_x_preferred":[
        "Ojo de Agua"
    ],
    "name:unk_x_variant":[
        "Ojo de Agua de Ixtla",
        "Ojo de Agua"
    ],
    "qs:gn_adm0_cc":"MX",
    "qs:gn_fcode":"PPL",
    "qs:gn_local":3985344,
    "qs:gn_nam_loc":"san miguel de allende",
    "qs:gn_namadm1":"11",
    "qs:gn_name":"Ojo de Agua",
    "qs:local_max":3714,
    "qs:local_sum":6237,
    "qs:localhoods":10,
    "qs:name":"Ojo de Agua",
    "qs:name_adm0":"M\u00e9xico",
    "qs:name_adm1":"Guanajuato",
    "qs:name_adm2":"Allende",
    "qs:name_local":"San Miguel de Allende",
    "qs:photo_max":101,
    "qs:photo_sum":146,
    "qs:placetype":"Suburb",
    "qs:quad_count":6,
    "qs:woe_adm0":23424900,
    "qs:woe_adm1":2346274,
    "qs:woe_adm2":12599991,
    "qs:woe_lau":0,
    "qs:woe_local":144620,
    "qs:woe_ver":"7.10.0",
    "wof:lang":[
        "spa"
    ],
    "wof:name":"Ojo de Agua",
    "wof:placetype":"neighbourhood"
},
  "geometry": {"coordinates":[-100.73873500000001,20.906503],"type":"Point"}
}