{
  "type": "Feature",
  "properties": {
    "gn:admin1_code":"2",
    "gn:admin2_code":"3.0",
    "gn:asciiname":"Juliana [Granja]",
    "gn:country_code":"MX",
    "gn:dem":606,
    "gn:feature_class":"P",
    "gn:feature_code":"PPL",
    "gn:name":"Juliana [Granja]",
    "gn:population":110,
    "gn:timezone":"America/Tijuana",
    "iso:country":"MX",
    "wof:name":"Juliana [Granja]",
    "wof:placetype":"locality",
    "wof:population":110
},
  "geometry": {"coordinates":[-116.64139,32.54583],"type":"Point"}
}