{
  "type": "Feature",
  "properties": {
    "gn:admin1_code":"30",
    "gn:admin2_code":"178.0",
    "gn:asciiname":"Montepio",
    "gn:country_code":"MX",
    "gn:dem":4,
    "gn:feature_class":"P",
    "gn:feature_code":"PPL",
    "gn:name":"Montep\u00edo",
    "gn:population":5,
    "gn:timezone":"America/Mexico_City",
    "iso:country":"MX",
    "name:und_x_variant":[
        "Montep\u00edo"
    ],
    "wof:name":"Montepio",
    "wof:placetype":"locality",
    "wof:population":5
},
  "geometry": {"coordinates":[-95.60444,18.60028],"type":"Point"}
}