{
  "type": "Feature",
  "properties": {
    "gn:admin1_code":"5.0",
    "gn:admin2_code":"108.0",
    "gn:asciiname":"Nambiyihua",
    "gn:country_code":"MX",
    "gn:dem":1035,
    "gn:feature_class":"P",
    "gn:feature_code":"PPLL",
    "gn:name":"Nambiyihua",
    "gn:population":0,
    "gn:timezone":"America/Mexico_City",
    "iso:country":"MX",
    "name:spa_x_preferred":[
        "Nambiyihua"
    ],
    "wof:name":"Nambiyihua",
    "wof:placetype":"locality"
},
  "geometry": {"coordinates":[-93.22416,16.46187999999999],"type":"Point"}
}