{
  "type": "Feature",
  "properties": {
    "gn:admin1_code":"7",
    "gn:admin2_code":"35.0",
    "gn:asciiname":"Avila Camacho",
    "gn:country_code":"MX",
    "gn:dem":1249,
    "gn:feature_class":"P",
    "gn:feature_code":"PPL",
    "gn:name":"Avila Camacho",
    "gn:population":0,
    "gn:timezone":"America/Monterrey",
    "iso:country":"MX",
    "name:spa_x_preferred":[
        "Avila Camacho"
    ],
    "wof:name":"Avila Camacho",
    "wof:placetype":"locality"
},
  "geometry": {"coordinates":[-103.39364,25.16234],"type":"Point"}
}