{
  "type": "Feature",
  "properties": {
    "gn:admin1_code":"20",
    "gn:admin2_code":"278.0",
    "gn:asciiname":"Rancho Orozco",
    "gn:country_code":"MX",
    "gn:dem":29,
    "gn:feature_class":"P",
    "gn:feature_code":"PPL",
    "gn:name":"Rancho Orozco",
    "gn:population":6,
    "gn:timezone":"America/Mexico_City",
    "iso:country":"MX",
    "wof:name":"Rancho Orozco",
    "wof:placetype":"locality",
    "wof:population":6
},
  "geometry": {"coordinates":[-96.325,18.28944],"type":"Point"}
}