{
  "type": "Feature",
  "properties": {
    "gn:admin1_code":"19",
    "gn:admin2_code":"22.0",
    "gn:asciiname":"La Sierrita",
    "gn:country_code":"MX",
    "gn:dem":264,
    "gn:feature_class":"P",
    "gn:feature_code":"PPL",
    "gn:name":"La Sierrita",
    "gn:population":8,
    "gn:timezone":"America/Monterrey",
    "iso:country":"MX",
    "name:und_x_variant":[
        "Sierrita",
        "La Sierrita"
    ],
    "wof:name":"La Sierrita",
    "wof:placetype":"locality",
    "wof:population":8
},
  "geometry": {"coordinates":[-99.49902,25.22305],"type":"Point"}
}