{
  "type": "Feature",
  "properties": {
    "gn:admin1_code":"14.0",
    "gn:admin2_code":"100.0",
    "gn:asciiname":"Las Bugambilias",
    "gn:country_code":"MX",
    "gn:dem":25,
    "gn:feature_class":"P",
    "gn:feature_code":"PPL",
    "gn:name":"Las Bugambilias",
    "gn:population":0,
    "gn:timezone":"America/Mexico_City",
    "iso:country":"MX",
    "name:spa_x_preferred":[
        "Las Bugambilias"
    ],
    "wof:name":"Las Bugambilias",
    "wof:placetype":"locality"
},
  "geometry": {"coordinates":[-105.43741,19.9659],"type":"Point"}
}