{
  "type": "Feature",
  "properties": {
    "gn:admin1_code":"16",
    "gn:admin2_code":"46.0",
    "gn:asciiname":"Trincheras",
    "gn:country_code":"MX",
    "gn:dem":1447,
    "gn:feature_class":"P",
    "gn:feature_code":"PPL",
    "gn:name":"Trincheras",
    "gn:population":118,
    "gn:timezone":"America/Mexico_City",
    "iso:country":"MX",
    "name:deu_x_preferred":[
        "Trincheras"
    ],
    "name:epo_x_preferred":[
        "Trincheras"
    ],
    "name:ita_x_preferred":[
        "Trincheras"
    ],
    "name:ron_x_preferred":[
        "Trincheras"
    ],
    "name:spa_x_preferred":[
        "Trincheras"
    ],
    "name:vie_x_preferred":[
        "Trincheras"
    ],
    "wof:name":"Trincheras",
    "wof:placetype":"locality",
    "wof:population":118
},
  "geometry": {"coordinates":[-100.41083,19.33194],"type":"Point"}
}