{
  "type": "Feature",
  "properties": {
    "gn:admin1_code":"6",
    "gn:admin2_code":"8",
    "gn:asciiname":"La Tescalama",
    "gn:country_code":"MX",
    "gn:dem":417,
    "gn:feature_class":"P",
    "gn:feature_code":"PPL",
    "gn:name":"La Tescalama",
    "gn:population":45,
    "gn:timezone":"America/Chihuahua",
    "iso:country":"MX",
    "wof:name":"La Tescalama",
    "wof:placetype":"locality",
    "wof:population":45
},
  "geometry": {"coordinates":[-107.76795,26.84188],"type":"Point"}
}