{
  "type": "Feature",
  "properties": {
    "gn:admin1_code":"7.0",
    "gn:admin2_code":"19.0",
    "gn:asciiname":"Los Banos",
    "gn:country_code":"MX",
    "gn:dem":541,
    "gn:feature_class":"P",
    "gn:feature_code":"PPL",
    "gn:name":"Los Ba\u00f1os",
    "gn:population":0,
    "gn:timezone":"America/Monterrey",
    "iso:country":"MX",
    "name:ceb_x_preferred":[
        "Los Ba\u00f1os"
    ],
    "name:deu_x_preferred":[
        "Los Ba\u00f1os"
    ],
    "name:fra_x_preferred":[
        "Los Banos"
    ],
    "name:spa_x_preferred":[
        "Los Ba\u00f1os"
    ],
    "name:swe_x_preferred":[
        "Los Ba\u00f1os"
    ],
    "wof:name":"Los Banos",
    "wof:placetype":"locality"
},
  "geometry": {"coordinates":[-101.2064,28.36811],"type":"Point"}
}