{
  "type": "Feature",
  "properties": {
    "gn:admin1_code":"6",
    "gn:admin2_code":"27.0",
    "gn:asciiname":"Rorogochachi",
    "gn:country_code":"MX",
    "gn:dem":2230,
    "gn:feature_class":"P",
    "gn:feature_code":"PPL",
    "gn:name":"Rorog\u00f3chachi",
    "gn:population":0,
    "gn:timezone":"America/Chihuahua",
    "iso:country":"MX",
    "name:spa_x_preferred":[
        "Rorog\u00f3chachi"
    ],
    "wof:name":"Rorogochachi",
    "wof:placetype":"locality"
},
  "geometry": {"coordinates":[-107.12797,27.23641],"type":"Point"}
}