{
  "type": "Feature",
  "properties": {
    "gn:admin1_code":"3",
    "gn:admin2_code":"8.0",
    "gn:asciiname":"La Otra Agua",
    "gn:country_code":"MX",
    "gn:dem":383,
    "gn:feature_class":"P",
    "gn:feature_code":"PPL",
    "gn:name":"La Otra Agua",
    "gn:population":0,
    "gn:timezone":"America/Mazatlan",
    "iso:country":"MX",
    "name:spa_x_preferred":[
        "La Otra Agua"
    ],
    "wof:name":"La Otra Agua",
    "wof:placetype":"locality"
},
  "geometry": {"coordinates":[-109.59659000000001,23.28614],"type":"Point"}
}