{
  "type": "Feature",
  "properties": {
    "gn:admin1_code":"16.0",
    "gn:admin2_code":"72.0",
    "gn:asciiname":"Cerro de Dolores",
    "gn:country_code":"MX",
    "gn:dem":2257,
    "gn:feature_class":"P",
    "gn:feature_code":"PPL",
    "gn:name":"Cerro de Dolores",
    "gn:population":0,
    "gn:timezone":"America/Mexico_City",
    "iso:country":"MX",
    "name:spa_x_preferred":[
        "Cerro de Dolores"
    ],
    "wof:name":"Cerro de Dolores",
    "wof:placetype":"locality"
},
  "geometry": {"coordinates":[-100.86788,19.64848],"type":"Point"}
}