{
  "type": "Feature",
  "properties": {
    "gn:admin1_code":"11",
    "gn:admin2_code":"35",
    "gn:asciiname":"La Gloria",
    "gn:country_code":"MX",
    "gn:dem":1751,
    "gn:feature_class":"P",
    "gn:feature_code":"PPL",
    "gn:name":"La Gloria",
    "gn:population":20,
    "gn:timezone":"America/Mexico_City",
    "iso:country":"MX",
    "wof:name":"La Gloria",
    "wof:placetype":"locality",
    "wof:population":20
},
  "geometry": {"coordinates":[-100.99444,20.62889],"type":"Point"}
}