{
  "type": "Feature",
  "properties": {
    "gn:admin1_code":"12",
    "gn:admin2_code":"10",
    "gn:asciiname":"Cocoyotzin",
    "gn:country_code":"MX",
    "gn:dem":1857,
    "gn:feature_class":"P",
    "gn:feature_code":"PPL",
    "gn:name":"Cocoyotzin",
    "gn:population":26,
    "gn:timezone":"America/Mexico_City",
    "iso:country":"MX",
    "wof:name":"Cocoyotzin",
    "wof:placetype":"locality",
    "wof:population":26
},
  "geometry": {"coordinates":[-98.78433,17.63014],"type":"Point"}
}