{
  "type": "Feature",
  "properties": {
    "gn:admin1_code":"7",
    "gn:admin2_code":"7.0",
    "gn:asciiname":"El Madero",
    "gn:country_code":"MX",
    "gn:dem":947,
    "gn:feature_class":"P",
    "gn:feature_code":"PPL",
    "gn:name":"El Madero",
    "gn:population":35,
    "gn:timezone":"America/Monterrey",
    "iso:country":"MX",
    "name:spa_x_preferred":[
        "El Madero"
    ],
    "wof:name":"El Madero",
    "wof:placetype":"locality",
    "wof:population":35
},
  "geometry": {"coordinates":[-101.97127999999999,26.52752000000001],"type":"Point"}
}