{
  "type": "Feature",
  "properties": {
    "gn:admin1_code":"13",
    "gn:admin2_code":"68.0",
    "gn:asciiname":"Mazahuacan",
    "gn:country_code":"MX",
    "gn:dem":847,
    "gn:feature_class":"P",
    "gn:feature_code":"PPL",
    "gn:name":"Mazahuac\u00e1n",
    "gn:population":134,
    "gn:timezone":"America/Mexico_City",
    "iso:country":"MX",
    "name:und_x_variant":[
        "Mazahuac\u00e1n"
    ],
    "wof:name":"Mazahuacan",
    "wof:placetype":"locality",
    "wof:population":134
},
  "geometry": {"coordinates":[-98.47704,20.80205],"type":"Point"}
}