{
  "type": "Feature",
  "properties": {
    "gn:admin1_code":"27",
    "gn:admin2_code":"5.0",
    "gn:asciiname":"Eugenia",
    "gn:country_code":"MX",
    "gn:dem":20,
    "gn:feature_class":"P",
    "gn:feature_code":"PPL",
    "gn:name":"Eugenia",
    "gn:population":0,
    "gn:timezone":"America/Mexico_City",
    "iso:country":"MX",
    "name:afr_x_preferred":[
        "Eugenia"
    ],
    "name:ara_x_preferred":[
        "\u0642\u0631\u0646\u0641\u0648\u0644"
    ],
    "name:aze_x_preferred":[
        "Evgeniya"
    ],
    "name:bel_x_preferred":[
        "Eugenia"
    ],
    "name:cat_x_preferred":[
        "Eugenia"
    ],
    "name:ces_x_preferred":[
        "Eugenie"
    ],
    "name:deu_x_preferred":[
        "Kirschmyrten"
    ],
    "name:fas_x_preferred":[
        "\u0627\u0648\u062c\u0646"
    ],
    "name:fra_x_preferred":[
        "Eugenia"
    ],
    "name:ilo_x_preferred":[
        "Eugenia"
    ],
    "name:ita_x_preferred":[
        "Eugenia"
    ],
    "name:lat_x_preferred":[
        "Eugenia"
    ],
    "name:nor_x_preferred":[
        "Eugenia"
    ],
    "name:pnb_x_preferred":[
        "\u06cc\u0648\u062c\u06cc\u0646\u06cc\u0627"
    ],
    "name:pol_x_preferred":[
        "Go\u017adzikowiec"
    ],
    "name:por_x_preferred":[
        "Eugenia"
    ],
    "name:que_x_preferred":[
        "Unka"
    ],
    "name:ron_x_preferred":[
        "Eugenia"
    ],
    "name:rus_x_preferred":[
        "\u0415\u0432\u0433\u0435\u043d\u0438\u044f"
    ],
    "name:spa_x_preferred":[
        "Eugenia"
    ],
    "name:sqi_x_preferred":[
        "Eugenia"
    ],
    "name:swe_x_preferred":[
        "Eugeniamyrtensl\u00e4ktet"
    ],
    "name:zho_x_preferred":[
        "\u756a\u6a31\u6843\u5c5e"
    ],
    "wof:name":"Eugenia",
    "wof:placetype":"locality"
},
  "geometry": {"coordinates":[-93.26667,18.16667],"type":"Point"}
}