{
  "type": "Feature",
  "properties": {
    "gn:admin1_code":"27",
    "gn:admin2_code":"5.0",
    "gn:asciiname":"Eugenia",
    "gn:country_code":"MX",
    "gn:dem":20,
    "gn:feature_class":"P",
    "gn:feature_code":"PPL",
    "gn:name":"Eugenia",
    "gn:population":0,
    "gn:timezone":"America/Mexico_City",
    "iso:country":"MX",
    "wof:name":"Eugenia",
    "wof:placetype":"locality"
},
  "geometry": {"coordinates":[-93.26667,18.16667],"type":"Point"}
}