{
  "type": "Feature",
  "properties": {
    "gn:admin1_code":"10.0",
    "gn:admin2_code":"9.0",
    "gn:asciiname":"Guadanas",
    "gn:cc2":"MX",
    "gn:country_code":"MX",
    "gn:dem":2182,
    "gn:feature_class":"P",
    "gn:feature_code":"PPL",
    "gn:name":"Guada\u00f1as",
    "gn:population":0,
    "gn:timezone":"America/Monterrey",
    "iso:country":"MX",
    "name:und_x_variant":[
        "Guada\u00f1a",
        "Guada\u00f1as"
    ],
    "wof:name":"Guadanas",
    "wof:placetype":"locality"
},
  "geometry": {"coordinates":[-105.91667,25.96667],"type":"Point"}
}