{
  "type": "Feature",
  "properties": {
    "gn:admin1_code":"19",
    "gn:admin2_code":"5.0",
    "gn:asciiname":"El Jonuco",
    "gn:country_code":"MX",
    "gn:dem":187,
    "gn:feature_class":"P",
    "gn:feature_code":"PPL",
    "gn:name":"El Jonuco",
    "gn:population":0,
    "gn:timezone":"America/Matamoros",
    "iso:country":"MX",
    "name:spa_x_preferred":[
        "El Jonuco"
    ],
    "name:und_x_variant":[
        "Rancho El Jonuco",
        "El Januco"
    ],
    "wof:name":"El Jonuco",
    "wof:placetype":"locality"
},
  "geometry": {"coordinates":[-99.86375,27.02994],"type":"Point"}
}