{
  "type": "Feature",
  "properties": {
    "gn:admin1_code":"15",
    "gn:admin2_code":"110.0",
    "gn:asciiname":"Loma de Rodriguez",
    "gn:country_code":"MX",
    "gn:dem":2028,
    "gn:feature_class":"P",
    "gn:feature_code":"PPL",
    "gn:name":"Loma de Rodr\u00edguez",
    "gn:population":188,
    "gn:timezone":"America/Mexico_City",
    "iso:country":"MX",
    "name:und_x_variant":[
        "Loma de Rodr\u00edguez"
    ],
    "wof:name":"Loma de Rodriguez",
    "wof:placetype":"locality",
    "wof:population":188
},
  "geometry": {"coordinates":[-100.08892,19.18374],"type":"Point"}
}