{
  "type": "Feature",
  "properties": {
    "gn:admin1_code":"16",
    "gn:admin2_code":"6.0",
    "gn:asciiname":"San Antonio la Labor",
    "gn:cc2":"MX",
    "gn:country_code":"MX",
    "gn:dem":238,
    "gn:feature_class":"P",
    "gn:feature_code":"PPL",
    "gn:name":"San Antonio la Labor",
    "gn:population":0,
    "gn:timezone":"America/Mexico_City",
    "iso:country":"MX",
    "name:und_x_variant":[
        "San Antonio",
        "San Antonio la Labor"
    ],
    "wof:name":"San Antonio la Labor",
    "wof:placetype":"locality"
},
  "geometry": {"coordinates":[-102.48333,19.08333],"type":"Point"}
}