{
  "type": "Feature",
  "properties": {
    "gn:admin1_code":"14.0",
    "gn:admin2_code":"100.0",
    "gn:asciiname":"El Caimanero",
    "gn:country_code":"MX",
    "gn:dem":75,
    "gn:feature_class":"P",
    "gn:feature_code":"PPL",
    "gn:name":"El Caimanero",
    "gn:population":0,
    "gn:timezone":"America/Mexico_City",
    "iso:country":"MX",
    "name:spa_x_preferred":[
        "El Caimanero"
    ],
    "wof:name":"El Caimanero",
    "wof:placetype":"locality"
},
  "geometry": {"coordinates":[-105.18097,19.9662],"type":"Point"}
}