{
  "type": "Feature",
  "properties": {
    "gn:admin1_code":"26.0",
    "gn:admin2_code":"55.0",
    "gn:asciiname":"Ejido Leyes de Reforma 2",
    "gn:country_code":"MX",
    "gn:dem":17,
    "gn:feature_class":"P",
    "gn:feature_code":"PPL",
    "gn:name":"Ejido Leyes de Reforma 2",
    "gn:population":32,
    "gn:timezone":"America/Hermosillo",
    "iso:country":"MX",
    "name:spa_x_preferred":[
        "Ejido Leyes de Reforma"
    ],
    "wof:name":"Ejido Leyes de Reforma 2",
    "wof:placetype":"locality",
    "wof:population":32
},
  "geometry": {"coordinates":[-114.88667,32.23806],"type":"Point"}
}