{
  "type": "Feature",
  "properties": {
    "gn:admin1_code":"3.0",
    "gn:admin2_code":"2.0",
    "gn:asciiname":"El Carricito",
    "gn:country_code":"MX",
    "gn:dem":374,
    "gn:feature_class":"P",
    "gn:feature_code":"PPL",
    "gn:name":"El Carricito",
    "gn:population":16,
    "gn:timezone":"America/Mazatlan",
    "iso:country":"MX",
    "name:spa_x_preferred":[
        "El Carricito"
    ],
    "wof:name":"El Carricito",
    "wof:placetype":"locality",
    "wof:population":16
},
  "geometry": {"coordinates":[-112.84329,27.4643],"type":"Point"}
}