{
  "type": "Feature",
  "properties": {
    "gn:admin1_code":"3",
    "gn:admin2_code":"9.0",
    "gn:asciiname":"Timbabichi",
    "gn:country_code":"MX",
    "gn:dem":7,
    "gn:feature_class":"P",
    "gn:feature_code":"PPL",
    "gn:name":"Timbabichi",
    "gn:population":0,
    "gn:timezone":"America/Mazatlan",
    "iso:country":"MX",
    "name:und_x_variant":[
        "Tambobiche",
        "Tembabiche",
        "Tembambiche",
        "Timbabichi",
        "Tembobiche",
        "Temjabiche"
    ],
    "wof:name":"Timbabichi",
    "wof:placetype":"locality"
},
  "geometry": {"coordinates":[-110.9559,25.25801],"type":"Point"}
}