{
  "type": "Feature",
  "properties": {
    "gn:admin1_code":"22",
    "gn:admin2_code":"2.0",
    "gn:asciiname":"La Meca",
    "gn:country_code":"MX",
    "gn:dem":1713,
    "gn:feature_class":"P",
    "gn:feature_code":"PPL",
    "gn:name":"La Meca",
    "gn:population":51,
    "gn:timezone":"America/Mexico_City",
    "iso:country":"MX",
    "wof:name":"La Meca",
    "wof:placetype":"locality",
    "wof:population":51
},
  "geometry": {"coordinates":[-99.57583,21.00667],"type":"Point"}
}