{
  "type": "Feature",
  "properties": {
    "gn:admin1_code":"7",
    "gn:admin2_code":"25",
    "gn:asciiname":"Ruben Espinoza",
    "gn:country_code":"MX",
    "gn:dem":262,
    "gn:feature_class":"P",
    "gn:feature_code":"PPL",
    "gn:name":"Rub\u00e9n Espinoza",
    "gn:population":21,
    "gn:timezone":"America/Matamoros",
    "iso:country":"MX",
    "name:und_x_variant":[
        "Rub\u00e9n Espinoza"
    ],
    "wof:name":"Ruben Espinoza",
    "wof:placetype":"locality",
    "wof:population":21
},
  "geometry": {"coordinates":[-100.58286,28.69635],"type":"Point"}
}