{
  "type": "Feature",
  "properties": {
    "gn:admin1_code":"6",
    "gn:admin2_code":"14.0",
    "gn:asciiname":"Cuevas",
    "gn:country_code":"MX",
    "gn:dem":1607,
    "gn:feature_class":"P",
    "gn:feature_code":"PPL",
    "gn:name":"Cuevas",
    "gn:population":0,
    "gn:timezone":"America/Chihuahua",
    "iso:country":"MX",
    "wof:name":"Cuevas",
    "wof:placetype":"locality"
},
  "geometry": {"coordinates":[-104.90000000000001,26.63333],"type":"Point"}
}