{
  "type": "Feature",
  "properties": {
    "gn:admin1_code":"16",
    "gn:admin2_code":"49",
    "gn:asciiname":"Tepame (Tepamis)",
    "gn:country_code":"MX",
    "gn:dem":1846,
    "gn:feature_class":"P",
    "gn:feature_code":"PPL",
    "gn:name":"Tepame (Tepamis)",
    "gn:population":12,
    "gn:timezone":"America/Mexico_City",
    "iso:country":"MX",
    "wof:name":"Tepame (Tepamis)",
    "wof:placetype":"locality",
    "wof:population":12
},
  "geometry": {"coordinates":[-101.10194,19.35917],"type":"Point"}
}