{
  "type": "Feature",
  "properties": {
    "gn:admin1_code":"26",
    "gn:admin2_code":"33.0",
    "gn:asciiname":"El Gato",
    "gn:country_code":"MX",
    "gn:dem":4,
    "gn:feature_class":"P",
    "gn:feature_code":"PPL",
    "gn:name":"El Gato",
    "gn:population":5,
    "gn:timezone":"America/Hermosillo",
    "iso:country":"MX",
    "name:spa_x_preferred":[
        "El Gato"
    ],
    "wof:name":"El Gato",
    "wof:placetype":"locality",
    "wof:population":5
},
  "geometry": {"coordinates":[-109.76139000000001,26.81556],"type":"Point"}
}