{
  "type": "Feature",
  "properties": {
    "gn:admin1_code":"2",
    "gn:admin2_code":"5",
    "gn:asciiname":"Campo Castillo",
    "gn:country_code":"MX",
    "gn:dem":14,
    "gn:feature_class":"P",
    "gn:feature_code":"PPL",
    "gn:name":"Campo Castillo",
    "gn:population":20,
    "gn:timezone":"America/Tijuana",
    "iso:country":"MX",
    "wof:name":"Campo Castillo",
    "wof:placetype":"locality",
    "wof:population":20
},
  "geometry": {"coordinates":[-117.09305999999999,32.41028],"type":"Point"}
}