{
  "type": "Feature",
  "properties": {
    "gn:admin1_code":"7",
    "gn:admin2_code":"13.0",
    "gn:asciiname":"La Pina",
    "gn:country_code":"MX",
    "gn:dem":178,
    "gn:feature_class":"P",
    "gn:feature_code":"PPL",
    "gn:name":"La Pi\u00f1a",
    "gn:population":4,
    "gn:timezone":"America/Monterrey",
    "iso:country":"MX",
    "name:und_x_variant":[
        "La Pi\u00f1a"
    ],
    "wof:name":"La Pina",
    "wof:placetype":"locality",
    "wof:population":4
},
  "geometry": {"coordinates":[-99.91395,27.78583],"type":"Point"}
}