{
  "type": "Feature",
  "properties": {
    "gn:admin1_code":"24",
    "gn:admin2_code":"29",
    "gn:asciiname":"Zapotito",
    "gn:country_code":"MX",
    "gn:dem":185,
    "gn:feature_class":"P",
    "gn:feature_code":"PPL",
    "gn:name":"Zapotito",
    "gn:population":35,
    "gn:timezone":"America/Mexico_City",
    "iso:country":"MX",
    "wof:name":"Zapotito",
    "wof:placetype":"locality",
    "wof:population":35
},
  "geometry": {"coordinates":[-98.63278,21.39472],"type":"Point"}
}