{
  "type": "Feature",
  "properties": {
    "gn:admin1_code":"11",
    "gn:admin2_code":"17",
    "gn:asciiname":"Fraccionamiento Pia Monte",
    "gn:country_code":"MX",
    "gn:dem":1726,
    "gn:feature_class":"P",
    "gn:feature_code":"PPL",
    "gn:name":"Fraccionamiento P\u00eda Monte",
    "gn:population":42,
    "gn:timezone":"America/Mexico_City",
    "iso:country":"MX",
    "name:und_x_variant":[
        "Fraccionamiento P\u00eda Monte"
    ],
    "wof:name":"Fraccionamiento Pia Monte",
    "wof:placetype":"locality",
    "wof:population":42
},
  "geometry": {"coordinates":[-101.4025,20.67833],"type":"Point"}
}