{
  "type": "Feature",
  "properties": {
    "gn:admin1_code":"6",
    "gn:admin2_code":"8.0",
    "gn:asciiname":"Capa Rosa",
    "gn:country_code":"MX",
    "gn:dem":471,
    "gn:feature_class":"P",
    "gn:feature_code":"PPL",
    "gn:name":"Capa Rosa",
    "gn:population":7,
    "gn:timezone":"America/Chihuahua",
    "iso:country":"MX",
    "wof:name":"Capa Rosa",
    "wof:placetype":"locality",
    "wof:population":7
},
  "geometry": {"coordinates":[-107.84350999999999,26.78355],"type":"Point"}
}