{
  "type": "Feature",
  "properties": {
    "gn:admin1_code":"19.0",
    "gn:admin2_code":"13.0",
    "gn:asciiname":"Puerto de Salinillas",
    "gn:country_code":"MX",
    "gn:dem":170,
    "gn:feature_class":"P",
    "gn:feature_code":"PPL",
    "gn:name":"Puerto de Salinillas",
    "gn:population":0,
    "gn:timezone":"America/Monterrey",
    "iso:country":"MX",
    "name:spa_x_preferred":[
        "Puerto de Salinillas"
    ],
    "wof:name":"Puerto de Salinillas",
    "wof:placetype":"locality"
},
  "geometry": {"coordinates":[-99.17424,25.57761],"type":"Point"}
}