{
  "type": "Feature",
  "properties": {
    "gn:admin1_code":"30",
    "gn:admin2_code":"84.0",
    "gn:asciiname":"Rincon Largo",
    "gn:cc2":"MX",
    "gn:country_code":"MX",
    "gn:dem":9,
    "gn:feature_class":"P",
    "gn:feature_code":"PPL",
    "gn:name":"Rinc\u00f3n Largo",
    "gn:population":2,
    "gn:timezone":"America/Mexico_City",
    "iso:country":"MX",
    "name:und_x_variant":[
        "Rinc\u00f3n Largo",
        "Rinc\u00f3n Lagarto"
    ],
    "wof:name":"Rincon Largo",
    "wof:placetype":"locality",
    "wof:population":2
},
  "geometry": {"coordinates":[-95.98444000000001,18.44444],"type":"Point"}
}