{
  "type": "Feature",
  "properties": {
    "gn:admin1_code":"10",
    "gn:admin2_code":"27.0",
    "gn:asciiname":"El Tanquecillo",
    "gn:country_code":"MX",
    "gn:dem":1609,
    "gn:feature_class":"P",
    "gn:feature_code":"PPL",
    "gn:name":"El Tanquecillo",
    "gn:population":0,
    "gn:timezone":"America/Monterrey",
    "iso:country":"MX",
    "name:spa_x_preferred":[
        "El Tanquecillo"
    ],
    "wof:name":"El Tanquecillo",
    "wof:placetype":"locality"
},
  "geometry": {"coordinates":[-102.64275000000001,24.61731],"type":"Point"}
}