{
  "type": "Feature",
  "properties": {
    "gn:admin1_code":"5",
    "gn:admin2_code":"13.0",
    "gn:asciiname":"Andulio Galvez",
    "gn:country_code":"MX",
    "gn:dem":1200,
    "gn:feature_class":"P",
    "gn:feature_code":"PPL",
    "gn:name":"Andulio G\u00e1lvez",
    "gn:population":0,
    "gn:timezone":"America/Mexico_City",
    "iso:country":"MX",
    "name:spa_x_preferred":[
        "Santo Domingo"
    ],
    "name:spa_x_variant":[
        "Andulio G\u00e1lvez"
    ],
    "wof:name":"Andulio Galvez",
    "wof:placetype":"locality"
},
  "geometry": {"coordinates":[-92.87604,16.98674],"type":"Point"}
}