{
  "type": "Feature",
  "properties": {
    "gn:admin1_code":"5",
    "gn:admin2_code":"26.0",
    "gn:asciiname":"Stenlejtic",
    "gn:country_code":"MX",
    "gn:dem":1138,
    "gn:feature_class":"P",
    "gn:feature_code":"PPL",
    "gn:name":"Stenlejtic",
    "gn:population":72,
    "gn:timezone":"America/Mexico_City",
    "iso:country":"MX",
    "wof:name":"Stenlejtic",
    "wof:placetype":"locality",
    "wof:population":72
},
  "geometry": {"coordinates":[-92.68611,16.96194],"type":"Point"}
}