{
  "type": "Feature",
  "properties": {
    "gn:admin1_code":"11",
    "gn:admin2_code":"3.0",
    "gn:asciiname":"Cienega de Juana Ruiz",
    "gn:country_code":"MX",
    "gn:dem":1887,
    "gn:feature_class":"P",
    "gn:feature_code":"PPL",
    "gn:name":"Ci\u00e9nega de Juana Ruiz",
    "gn:population":466,
    "gn:timezone":"America/Mexico_City",
    "iso:country":"MX",
    "name:spa_x_preferred":[
        "Ci\u00e9nega de Juana Ruiz"
    ],
    "name:und_x_variant":[
        "Ci\u00e9nega de Juana Ruiz"
    ],
    "wof:name":"Cienega de Juana Ruiz",
    "wof:placetype":"locality",
    "wof:population":466
},
  "geometry": {"coordinates":[-100.86722,20.90472],"type":"Point"}
}