{
  "type": "Feature",
  "properties": {
    "gn:admin1_code":"12",
    "gn:admin2_code":"48.0",
    "gn:asciiname":"Hacienda de los Solis",
    "gn:country_code":"MX",
    "gn:dem":1240,
    "gn:feature_class":"P",
    "gn:feature_code":"PPL",
    "gn:name":"Hacienda de los Sol\u00eds",
    "gn:population":8,
    "gn:timezone":"America/Mexico_City",
    "iso:country":"MX",
    "name:und_x_variant":[
        "Hacienda de los Sol\u00eds"
    ],
    "wof:name":"Hacienda de los Solis",
    "wof:placetype":"locality",
    "wof:population":8
},
  "geometry": {"coordinates":[-101.13927,17.55372],"type":"Point"}
}