{
  "type": "Feature",
  "properties": {
    "gn:admin1_code":"15",
    "gn:admin2_code":"38",
    "gn:asciiname":"Los Panales (Mina los Panales)",
    "gn:country_code":"MX",
    "gn:dem":2521,
    "gn:feature_class":"P",
    "gn:feature_code":"PPL",
    "gn:name":"Los Panales (Mina los Panales)",
    "gn:population":11,
    "gn:timezone":"America/Mexico_City",
    "iso:country":"MX",
    "wof:name":"Los Panales (Mina los Panales)",
    "wof:placetype":"locality",
    "wof:population":11
},
  "geometry": {"coordinates":[-99.37106,19.57991],"type":"Point"}
}