{
  "type": "Feature",
  "properties": {
    "gn:admin1_code":"14",
    "gn:admin2_code":"25.0",
    "gn:asciiname":"Los Castro",
    "gn:country_code":"MX",
    "gn:dem":1754,
    "gn:feature_class":"P",
    "gn:feature_code":"PPL",
    "gn:name":"Los Castro",
    "gn:population":0,
    "gn:timezone":"America/Mexico_City",
    "iso:country":"MX",
    "name:spa_x_preferred":[
        "Los Castro"
    ],
    "wof:name":"Los Castro",
    "wof:placetype":"locality"
},
  "geometry": {"coordinates":[-103.33493,22.03133],"type":"Point"}
}