{
  "type": "Feature",
  "properties": {
    "gn:admin1_code":"14.0",
    "gn:admin2_code":"49.0",
    "gn:asciiname":"El Rodeo",
    "gn:country_code":"MX",
    "gn:dem":889,
    "gn:feature_class":"P",
    "gn:feature_code":"PPL",
    "gn:name":"El Rodeo",
    "gn:population":0,
    "gn:timezone":"America/Mexico_City",
    "iso:country":"MX",
    "name:spa_x_preferred":[
        "El Rodeo"
    ],
    "wof:name":"El Rodeo",
    "wof:placetype":"locality"
},
  "geometry": {"coordinates":[-103.06187,19.33261],"type":"Point"}
}