{
  "type": "Feature",
  "properties": {
    "gn:admin1_code":"19.0",
    "gn:admin2_code":"24.0",
    "gn:asciiname":"El Bano",
    "gn:country_code":"MX",
    "gn:dem":1956,
    "gn:feature_class":"P",
    "gn:feature_code":"PPL",
    "gn:name":"El Ba\u00f1o",
    "gn:population":6,
    "gn:timezone":"America/Monterrey",
    "iso:country":"MX",
    "name:spa_x_preferred":[
        "El Ba\u00f1o"
    ],
    "wof:name":"El Bano",
    "wof:placetype":"locality",
    "wof:population":6
},
  "geometry": {"coordinates":[-99.57634,23.9912],"type":"Point"}
}