{
  "type": "Feature",
  "properties": {
    "gn:admin1_code":"11",
    "gn:admin2_code":"44",
    "gn:asciiname":"Rancho Viejo (Labradores)",
    "gn:country_code":"MX",
    "gn:dem":1742,
    "gn:feature_class":"P",
    "gn:feature_code":"PPL",
    "gn:name":"Rancho Viejo (Labradores)",
    "gn:population":13,
    "gn:timezone":"America/Mexico_City",
    "iso:country":"MX",
    "wof:name":"Rancho Viejo (Labradores)",
    "wof:placetype":"locality",
    "wof:population":13
},
  "geometry": {"coordinates":[-100.94167,20.53306],"type":"Point"}
}