{
  "type": "Feature",
  "properties": {
    "gn:admin1_code":"30",
    "gn:admin2_code":"141.0",
    "gn:asciiname":"Cobaltepec",
    "gn:country_code":"MX",
    "gn:dem":133,
    "gn:feature_class":"P",
    "gn:feature_code":"PPL",
    "gn:name":"Cobaltepec",
    "gn:population":211,
    "gn:timezone":"America/Mexico_City",
    "iso:country":"MX",
    "wof:name":"Cobaltepec",
    "wof:placetype":"locality",
    "wof:population":211
},
  "geometry": {"coordinates":[-95.255,18.37417],"type":"Point"}
}