{
  "type": "Feature",
  "properties": {
    "gn:admin1_code":"28",
    "gn:admin2_code":"32.0",
    "gn:asciiname":"Vamos Tamaulipas",
    "gn:country_code":"MX",
    "gn:dem":41,
    "gn:feature_class":"P",
    "gn:feature_code":"PPL",
    "gn:name":"Vamos Tamaulipas",
    "gn:population":1774,
    "gn:timezone":"America/Matamoros",
    "iso:country":"MX",
    "wof:name":"Vamos Tamaulipas",
    "wof:placetype":"locality",
    "wof:population":1774
},
  "geometry": {"coordinates":[-98.22167,25.98667],"type":"Point"}
}