{
  "type": "Feature",
  "properties": {
    "gn:admin1_code":"2.0",
    "gn:admin2_code":"3.0",
    "gn:asciiname":"Nuevo Oasis (Casa de Piedra)",
    "gn:country_code":"MX",
    "gn:dem":256,
    "gn:feature_class":"P",
    "gn:feature_code":"PPL",
    "gn:name":"Nuevo Oasis (Casa de Piedra)",
    "gn:population":1,
    "gn:timezone":"America/Tijuana",
    "iso:country":"MX",
    "name:spa_x_preferred":[
        "Nuevo Oasis"
    ],
    "wof:name":"Nuevo Oasis (Casa de Piedra)",
    "wof:placetype":"locality",
    "wof:population":1
},
  "geometry": {"coordinates":[-115.92138,32.56675],"type":"Point"}
}