{
  "type": "Feature",
  "properties": {
    "gn:admin1_code":"28",
    "gn:admin2_code":"12.0",
    "gn:asciiname":"La Mision",
    "gn:country_code":"MX",
    "gn:dem":258,
    "gn:feature_class":"P",
    "gn:feature_code":"PPL",
    "gn:name":"La Misi\u00f3n",
    "gn:population":0,
    "gn:timezone":"America/Monterrey",
    "iso:country":"MX",
    "name:und_x_variant":[
        "Misi\u00f3n",
        "La Misi\u00f3n"
    ],
    "wof:name":"La Mision",
    "wof:placetype":"locality"
},
  "geometry": {"coordinates":[-98.40049,22.97876],"type":"Point"}
}