{
  "type": "Feature",
  "properties": {
    "gn:admin1_code":"21.0",
    "gn:admin2_code":"122.0",
    "gn:asciiname":"Huitlale",
    "gn:country_code":"MX",
    "gn:dem":2439,
    "gn:feature_class":"P",
    "gn:feature_code":"PPL",
    "gn:name":"Huitlale",
    "gn:population":0,
    "gn:timezone":"America/Mexico_City",
    "iso:country":"MX",
    "name:spa_x_preferred":[
        "Huitlale"
    ],
    "wof:name":"Huitlale",
    "wof:placetype":"locality"
},
  "geometry": {"coordinates":[-98.51175000000001,19.24752],"type":"Point"}
}