{
  "type": "Feature",
  "properties": {
    "gn:admin1_code":"30",
    "gn:admin2_code":"139.0",
    "gn:asciiname":"El Cardon",
    "gn:country_code":"MX",
    "gn:dem":8,
    "gn:feature_class":"P",
    "gn:feature_code":"PPL",
    "gn:name":"El Card\u00f3n",
    "gn:population":7,
    "gn:timezone":"America/Mexico_City",
    "iso:country":"MX",
    "name:und_x_variant":[
        "El Card\u00f3n"
    ],
    "wof:name":"El Cardon",
    "wof:placetype":"locality",
    "wof:population":7
},
  "geometry": {"coordinates":[-95.51778,18.56528],"type":"Point"}
}