{
  "type": "Feature",
  "properties": {
    "gn:admin1_code":"11",
    "gn:admin2_code":"27",
    "gn:asciiname":"Granja Salmeron",
    "gn:country_code":"MX",
    "gn:dem":1752,
    "gn:feature_class":"P",
    "gn:feature_code":"PPL",
    "gn:name":"Granja Salmer\u00f3n",
    "gn:population":13,
    "gn:timezone":"America/Mexico_City",
    "iso:country":"MX",
    "name:und_x_variant":[
        "Granja Salmer\u00f3n"
    ],
    "wof:name":"Granja Salmeron",
    "wof:placetype":"locality",
    "wof:population":13
},
  "geometry": {"coordinates":[-101.26721999999999,20.53361],"type":"Point"}
}