{
  "type": "Feature",
  "properties": {
    "gn:admin1_code":"6.0",
    "gn:admin2_code":"19.0",
    "gn:asciiname":"Quintas Carolinas",
    "gn:country_code":"MX",
    "gn:dem":1439,
    "gn:feature_class":"P",
    "gn:feature_code":"PPL",
    "gn:name":"Quintas Carolinas",
    "gn:population":0,
    "gn:timezone":"America/Chihuahua",
    "iso:country":"MX",
    "name:und_x_variant":[
        "Carolinas",
        "Carolina",
        "Quintas Carolinas"
    ],
    "wof:name":"Quintas Carolinas",
    "wof:placetype":"locality"
},
  "geometry": {"coordinates":[-106.09678999999998,28.72838],"type":"Point"}
}