{
  "type": "Feature",
  "properties": {
    "gn:admin1_code":"10",
    "gn:admin2_code":"24.0",
    "gn:asciiname":"San Jose de los Ojitos",
    "gn:country_code":"MX",
    "gn:dem":1516,
    "gn:feature_class":"P",
    "gn:feature_code":"PPL",
    "gn:name":"San Jos\u00e9 de los Ojitos",
    "gn:population":0,
    "gn:timezone":"America/Monterrey",
    "iso:country":"MX",
    "name:spa_x_preferred":[
        "San Jos\u00e9 de los Ojitos"
    ],
    "wof:name":"San Jose de los Ojitos",
    "wof:placetype":"locality"
},
  "geometry": {"coordinates":[-104.6596,25.21129],"type":"Point"}
}