{
  "type": "Feature",
  "properties": {
    "gn:admin1_code":"4.0",
    "gn:admin2_code":"4.0",
    "gn:asciiname":"La Perseverancia",
    "gn:country_code":"MX",
    "gn:dem":24,
    "gn:feature_class":"P",
    "gn:feature_code":"PPL",
    "gn:name":"La Perseverancia",
    "gn:population":11,
    "gn:timezone":"America/Merida",
    "iso:country":"MX",
    "name:spa_x_preferred":[
        "La Perseverancia"
    ],
    "wof:name":"La Perseverancia",
    "wof:placetype":"locality",
    "wof:population":11
},
  "geometry": {"coordinates":[-90.72667,18.93278],"type":"Point"}
}