{
  "type": "Feature",
  "properties": {
    "gn:admin1_code":"12",
    "gn:admin2_code":"28.0",
    "gn:asciiname":"San Antonio (Hueitepec)",
    "gn:country_code":"MX",
    "gn:dem":2203,
    "gn:feature_class":"P",
    "gn:feature_code":"PPL",
    "gn:name":"San Antonio (Hueitepec)",
    "gn:population":361,
    "gn:timezone":"America/Mexico_City",
    "iso:country":"MX",
    "wof:name":"San Antonio (Hueitepec)",
    "wof:placetype":"locality",
    "wof:population":361
},
  "geometry": {"coordinates":[-98.919,17.46647999999999],"type":"Point"}
}