{
  "type": "Feature",
  "properties": {
    "gn:admin1_code":"30",
    "gn:admin2_code":"150.0",
    "gn:asciiname":"Boca la Mar",
    "gn:country_code":"MX",
    "gn:dem":3,
    "gn:feature_class":"P",
    "gn:feature_code":"PPL",
    "gn:name":"Boca la Mar",
    "gn:population":7,
    "gn:timezone":"America/Mexico_City",
    "iso:country":"MX",
    "wof:name":"Boca la Mar",
    "wof:placetype":"locality",
    "wof:population":7
},
  "geometry": {"coordinates":[-97.65472,21.60556],"type":"Point"}
}