{
  "type": "Feature",
  "properties": {
    "gn:admin1_code":"14.0",
    "gn:asciiname":"El Cerrito",
    "gn:country_code":"MX",
    "gn:dem":1952,
    "gn:feature_class":"P",
    "gn:feature_code":"PPL",
    "gn:name":"El Cerrito",
    "gn:population":0,
    "gn:timezone":"America/Mexico_City",
    "iso:country":"MX",
    "name:spa_x_preferred":[
        "El Cerrito"
    ],
    "wof:name":"El Cerrito",
    "wof:placetype":"locality"
},
  "geometry": {"coordinates":[-102.14722999999999,21.10786],"type":"Point"}
}