{
  "type": "Feature",
  "properties": {
    "gn:admin1_code":"32.0",
    "gn:admin2_code":"49.0",
    "gn:asciiname":"La Lagunilla",
    "gn:country_code":"MX",
    "gn:dem":2182,
    "gn:feature_class":"P",
    "gn:feature_code":"PPL",
    "gn:name":"La Lagunilla",
    "gn:population":0,
    "gn:timezone":"America/Mexico_City",
    "iso:country":"MX",
    "name:spa_x_preferred":[
        "La Lagunilla"
    ],
    "wof:name":"La Lagunilla",
    "wof:placetype":"locality"
},
  "geometry": {"coordinates":[-103.46595000000001,22.72597],"type":"Point"}
}