{
  "type": "Feature",
  "properties": {
    "gn:admin1_code":"12.0",
    "gn:admin2_code":"14.0",
    "gn:asciiname":"La Subida",
    "gn:country_code":"MX",
    "gn:dem":15,
    "gn:feature_class":"P",
    "gn:feature_code":"PPL",
    "gn:name":"La Subida",
    "gn:population":0,
    "gn:timezone":"America/Mexico_City",
    "iso:country":"MX",
    "name:spa_x_preferred":[
        "La Subida"
    ],
    "wof:name":"La Subida",
    "wof:placetype":"locality"
},
  "geometry": {"coordinates":[-100.45963999999999,17.07905],"type":"Point"}
}