{
  "type": "Feature",
  "properties": {
    "gn:admin1_code":"7",
    "gn:admin2_code":"8.0",
    "gn:asciiname":"El Caracol",
    "gn:country_code":"MX",
    "gn:dem":482,
    "gn:feature_class":"P",
    "gn:feature_code":"PPL",
    "gn:name":"El Caracol",
    "gn:population":0,
    "gn:timezone":"America/Monterrey",
    "iso:country":"MX",
    "name:spa_x_preferred":[
        "El Caracol"
    ],
    "name:und_x_variant":[
        "Rancho El Caracol"
    ],
    "wof:name":"El Caracol",
    "wof:placetype":"locality"
},
  "geometry": {"coordinates":[-101.0625,27.1372],"type":"Point"}
}