{
  "type": "Feature",
  "properties": {
    "gn:admin1_code":"30",
    "gn:admin2_code":"124.0",
    "gn:asciiname":"Arroyo Colorado",
    "gn:country_code":"MX",
    "gn:dem":96,
    "gn:feature_class":"P",
    "gn:feature_code":"PPL",
    "gn:name":"Arroyo Colorado",
    "gn:population":284,
    "gn:timezone":"America/Mexico_City",
    "iso:country":"MX",
    "name:spa_x_preferred":[
        "Arroyo Colorado"
    ],
    "wof:name":"Arroyo Colorado",
    "wof:placetype":"locality",
    "wof:population":284
},
  "geometry": {"coordinates":[-97.3006,20.50194],"type":"Point"}
}