{
  "type": "Feature",
  "properties": {
    "gn:admin1_code":"10",
    "gn:admin2_code":"2.0",
    "gn:asciiname":"El Guacatal",
    "gn:country_code":"MX",
    "gn:dem":1177,
    "gn:feature_class":"P",
    "gn:feature_code":"PPL",
    "gn:name":"El Guacatal",
    "gn:population":0,
    "gn:timezone":"America/Monterrey",
    "iso:country":"MX",
    "name:spa_x_preferred":[
        "El Guacatal"
    ],
    "wof:name":"El Guacatal",
    "wof:placetype":"locality"
},
  "geometry": {"coordinates":[-106.6019,25.11461],"type":"Point"}
}