{
  "type": "Feature",
  "properties": {
    "gn:admin1_code":"32",
    "gn:admin2_code":"42.0",
    "gn:asciiname":"Salas Perez",
    "gn:country_code":"MX",
    "gn:dem":2134,
    "gn:feature_class":"P",
    "gn:feature_code":"PPL",
    "gn:name":"Salas P\u00e9rez",
    "gn:population":0,
    "gn:timezone":"America/Mexico_City",
    "iso:country":"MX",
    "name:spa_x_preferred":[
        "Salas P\u00e9rez"
    ],
    "wof:name":"Salas Perez",
    "wof:placetype":"locality"
},
  "geometry": {"coordinates":[-103.84247000000001,23.77547],"type":"Point"}
}