{
  "type": "Feature",
  "properties": {
    "gn:admin1_code":"26",
    "gn:admin2_code":"20.0",
    "gn:asciiname":"La Cuesta Blanca",
    "gn:country_code":"MX",
    "gn:dem":774,
    "gn:feature_class":"P",
    "gn:feature_code":"PPL",
    "gn:name":"La Cuesta Blanca",
    "gn:population":0,
    "gn:timezone":"America/Hermosillo",
    "iso:country":"MX",
    "name:spa_x_preferred":[
        "La Cuesta Blanca"
    ],
    "wof:name":"La Cuesta Blanca",
    "wof:placetype":"locality"
},
  "geometry": {"coordinates":[-111.41864,29.86464],"type":"Point"}
}