{
  "type": "Feature",
  "properties": {
    "gn:admin1_code":"32",
    "gn:admin2_code":"38.0",
    "gn:asciiname":"El Coyote (Fonseca)",
    "gn:country_code":"MX",
    "gn:dem":2163,
    "gn:feature_class":"P",
    "gn:feature_code":"PPL",
    "gn:name":"El Coyote (Fonseca)",
    "gn:population":88,
    "gn:timezone":"America/Mexico_City",
    "iso:country":"MX",
    "wof:name":"El Coyote (Fonseca)",
    "wof:placetype":"locality",
    "wof:population":88
},
  "geometry": {"coordinates":[-101.48583000000001,22.43778],"type":"Point"}
}