{
  "type": "Feature",
  "properties": {
    "gn:admin1_code":"30",
    "gn:admin2_code":"189",
    "gn:asciiname":"Felix Sanchez",
    "gn:country_code":"MX",
    "gn:dem":55,
    "gn:feature_class":"P",
    "gn:feature_code":"PPL",
    "gn:name":"F\u00e9lix S\u00e1nchez",
    "gn:population":14,
    "gn:timezone":"America/Mexico_City",
    "iso:country":"MX",
    "name:und_x_variant":[
        "F\u00e9lix S\u00e1nchez"
    ],
    "wof:name":"Felix Sanchez",
    "wof:placetype":"locality",
    "wof:population":14
},
  "geometry": {"coordinates":[-97.4725,20.81444],"type":"Point"}
}