{
  "type": "Feature",
  "properties": {
    "gn:admin1_code":"14",
    "gn:admin2_code":"93",
    "gn:asciiname":"Juntas de Arriba",
    "gn:country_code":"MX",
    "gn:dem":1891,
    "gn:feature_class":"P",
    "gn:feature_code":"PPL",
    "gn:name":"Juntas de Arriba",
    "gn:population":29,
    "gn:timezone":"America/Mexico_City",
    "iso:country":"MX",
    "wof:name":"Juntas de Arriba",
    "wof:placetype":"locality",
    "wof:population":29
},
  "geometry": {"coordinates":[-102.6825,20.78056],"type":"Point"}
}