{
  "type": "Feature",
  "properties": {
    "gn:admin1_code":"4.0",
    "gn:admin2_code":"3.0",
    "gn:asciiname":"El Triangulo",
    "gn:country_code":"MX",
    "gn:dem":6,
    "gn:feature_class":"P",
    "gn:feature_code":"PPL",
    "gn:name":"El Tri\u00e1ngulo",
    "gn:population":0,
    "gn:timezone":"America/Merida",
    "iso:country":"MX",
    "name:spa_x_preferred":[
        "El Tri\u00e1ngulo"
    ],
    "wof:name":"El Triangulo",
    "wof:placetype":"locality"
},
  "geometry": {"coordinates":[-91.28010999999999,18.28623],"type":"Point"}
}