{
  "type": "Feature",
  "properties": {
    "gn:admin1_code":"16",
    "gn:admin2_code":"108.0",
    "gn:asciiname":"Colonia Carmen Serdan (Loma Bonita)",
    "gn:country_code":"MX",
    "gn:dem":1628,
    "gn:feature_class":"P",
    "gn:feature_code":"PPL",
    "gn:name":"Colonia Carmen Serd\u00e1n (Loma Bonita)",
    "gn:population":221,
    "gn:timezone":"America/Mexico_City",
    "iso:country":"MX",
    "name:und_x_variant":[
        "Colonia Carmen Serd\u00e1n (Loma Bonita)"
    ],
    "wof:name":"Colonia Carmen Serdan (Loma Bonita)",
    "wof:placetype":"locality",
    "wof:population":221
},
  "geometry": {"coordinates":[-102.25749999999999,19.97139],"type":"Point"}
}