{
  "type": "Feature",
  "properties": {
    "gn:admin1_code":"16.0",
    "gn:admin2_code":"2.0",
    "gn:asciiname":"El Mamey",
    "gn:country_code":"MX",
    "gn:dem":751,
    "gn:feature_class":"P",
    "gn:feature_code":"PPL",
    "gn:name":"El Mamey",
    "gn:population":0,
    "gn:timezone":"America/Mexico_City",
    "iso:country":"MX",
    "name:spa_x_preferred":[
        "El Mamey"
    ],
    "wof:name":"El Mamey",
    "wof:placetype":"locality"
},
  "geometry": {"coordinates":[-102.82017,18.81345],"type":"Point"}
}