{
  "type": "Feature",
  "properties": {
    "gn:admin1_code":"11",
    "gn:admin2_code":"17.0",
    "gn:asciiname":"Comunal Emiliano Zapata",
    "gn:country_code":"MX",
    "gn:dem":1724,
    "gn:feature_class":"P",
    "gn:feature_code":"PPL",
    "gn:name":"Comunal Emiliano Zapata",
    "gn:population":261,
    "gn:timezone":"America/Mexico_City",
    "iso:country":"MX",
    "wof:name":"Comunal Emiliano Zapata",
    "wof:placetype":"locality",
    "wof:population":261
},
  "geometry": {"coordinates":[-101.33083000000001,20.64111],"type":"Point"}
}