{
  "type": "Feature",
  "properties": {
    "gn:admin1_code":"5",
    "gn:admin2_code":"19.0",
    "gn:asciiname":"San Francisco Uninajab [Los Banos]",
    "gn:country_code":"MX",
    "gn:dem":1153,
    "gn:feature_class":"P",
    "gn:feature_code":"PPL",
    "gn:name":"San Francisco Uninajab [Los Ba\u00f1os]",
    "gn:population":83,
    "gn:timezone":"America/Mexico_City",
    "iso:country":"MX",
    "name:und_x_variant":[
        "San Francisco Uninajab [Los Ba\u00f1os]"
    ],
    "wof:name":"San Francisco Uninajab [Los Banos]",
    "wof:placetype":"locality",
    "wof:population":83
},
  "geometry": {"coordinates":[-92.15443999999999,16.10556],"type":"Point"}
}