{
  "type": "Feature",
  "properties": {
    "gn:admin1_code":"16",
    "gn:admin2_code":"34.0",
    "gn:asciiname":"La Resinera",
    "gn:country_code":"MX",
    "gn:dem":1976,
    "gn:feature_class":"P",
    "gn:feature_code":"PPL",
    "gn:name":"La Resinera",
    "gn:population":124,
    "gn:timezone":"America/Mexico_City",
    "iso:country":"MX",
    "wof:name":"La Resinera",
    "wof:placetype":"locality",
    "wof:population":124
},
  "geometry": {"coordinates":[-100.51111,19.67167],"type":"Point"}
}