{
  "type": "Feature",
  "properties": {
    "gn:admin1_code":"6.0",
    "gn:admin2_code":"52.0",
    "gn:asciiname":"Agua de Isidro",
    "gn:country_code":"MX",
    "gn:dem":1106,
    "gn:feature_class":"P",
    "gn:feature_code":"PPL",
    "gn:name":"Agua de Isidro",
    "gn:population":0,
    "gn:timezone":"America/Ojinaga",
    "iso:country":"MX",
    "name:spa_x_preferred":[
        "Agua de Isidro"
    ],
    "wof:name":"Agua de Isidro",
    "wof:placetype":"locality"
},
  "geometry": {"coordinates":[-104.78834999999999,30.10849],"type":"Point"}
}