{
  "type": "Feature",
  "properties": {
    "gn:admin1_code":"14",
    "gn:admin2_code":"93",
    "gn:asciiname":"Labor Nueva",
    "gn:country_code":"MX",
    "gn:dem":1946,
    "gn:feature_class":"P",
    "gn:feature_code":"PPL",
    "gn:name":"Labor Nueva",
    "gn:population":15,
    "gn:timezone":"America/Mexico_City",
    "iso:country":"MX",
    "wof:name":"Labor Nueva",
    "wof:placetype":"locality",
    "wof:population":15
},
  "geometry": {"coordinates":[-102.80583,20.88556],"type":"Point"}
}