{
  "type": "Feature",
  "properties": {
    "gn:admin1_code":"10",
    "gn:admin2_code":"37.0",
    "gn:asciiname":"La Hacienda",
    "gn:country_code":"MX",
    "gn:dem":810,
    "gn:feature_class":"P",
    "gn:feature_code":"PPL",
    "gn:name":"La Hacienda",
    "gn:population":7,
    "gn:timezone":"America/Monterrey",
    "iso:country":"MX",
    "wof:name":"La Hacienda",
    "wof:placetype":"locality",
    "wof:population":7
},
  "geometry": {"coordinates":[-106.76593,25.27081],"type":"Point"}
}