{
  "type": "Feature",
  "properties": {
    "gn:admin1_code":"6",
    "gn:admin2_code":"2.0",
    "gn:asciiname":"La Matiana",
    "gn:country_code":"MX",
    "gn:dem":1231,
    "gn:feature_class":"P",
    "gn:feature_code":"PPL",
    "gn:name":"La Matiana",
    "gn:population":0,
    "gn:timezone":"America/Chihuahua",
    "iso:country":"MX",
    "name:spa_x_preferred":[
        "La Matiana"
    ],
    "name:und_x_variant":[
        "La Materna"
    ],
    "wof:name":"La Matiana",
    "wof:placetype":"locality"
},
  "geometry": {"coordinates":[-105.81111,28.81986],"type":"Point"}
}