{
  "type": "Feature",
  "properties": {
    "gn:admin1_code":"20",
    "gn:admin2_code":"108.0",
    "gn:asciiname":"Arriba de la Cienega Rica",
    "gn:country_code":"MX",
    "gn:dem":2329,
    "gn:feature_class":"P",
    "gn:feature_code":"PPL",
    "gn:name":"Arriba de la Ci\u00e9nega Rica",
    "gn:population":7,
    "gn:timezone":"America/Mexico_City",
    "iso:country":"MX",
    "name:und_x_variant":[
        "Arriba de la Ci\u00e9nega Rica"
    ],
    "wof:name":"Arriba de la Cienega Rica",
    "wof:placetype":"locality",
    "wof:population":7
},
  "geometry": {"coordinates":[-97.14417,16.92527999999999],"type":"Point"}
}