{
  "type": "Feature",
  "properties": {
    "gn:admin1_code":"12",
    "gn:admin2_code":"32",
    "gn:asciiname":"Las Papitas (Los Duraznitos)",
    "gn:country_code":"MX",
    "gn:dem":2586,
    "gn:feature_class":"P",
    "gn:feature_code":"PPL",
    "gn:name":"Las Papitas (Los Duraznitos)",
    "gn:population":15,
    "gn:timezone":"America/Mexico_City",
    "iso:country":"MX",
    "wof:name":"Las Papitas (Los Duraznitos)",
    "wof:placetype":"locality",
    "wof:population":15
},
  "geometry": {"coordinates":[-100.14919999999999,17.51803],"type":"Point"}
}