{
  "type": "Feature",
  "properties": {
    "gn:admin1_code":"26",
    "gn:admin2_code":"18.0",
    "gn:asciiname":"Hacienda de Guadalupe",
    "gn:country_code":"MX",
    "gn:dem":83,
    "gn:feature_class":"P",
    "gn:feature_code":"PPL",
    "gn:name":"Hacienda de Guadalupe",
    "gn:population":0,
    "gn:timezone":"America/Hermosillo",
    "iso:country":"MX",
    "name:spa_x_preferred":[
        "San Francisco"
    ],
    "name:spa_x_variant":[
        "Hacienda de Guadalupe"
    ],
    "wof:name":"Hacienda de Guadalupe",
    "wof:placetype":"locality"
},
  "geometry": {"coordinates":[-109.72586,27.37766],"type":"Point"}
}