{
  "type": "Feature",
  "properties": {
    "gn:admin1_code":"21",
    "gn:admin2_code":"19.0",
    "gn:asciiname":"Santo Domingo Atoyatempan",
    "gn:cc2":"MX",
    "gn:country_code":"MX",
    "gn:dem":1861,
    "gn:feature_class":"P",
    "gn:feature_code":"PPL",
    "gn:name":"Santo Domingo Atoyatempan",
    "gn:population":1400,
    "gn:timezone":"America/Mexico_City",
    "iso:country":"MX",
    "name:und_x_variant":[
        "Santo Domingo",
        "Santo Domingo Atoyatempan"
    ],
    "wof:name":"Santo Domingo Atoyatempan",
    "wof:placetype":"locality",
    "wof:population":1400
},
  "geometry": {"coordinates":[-98.37306,18.90444],"type":"Point"}
}