{
  "type": "Feature",
  "properties": {
    "gn:admin1_code":"25",
    "gn:admin2_code":"8.0",
    "gn:asciiname":"Ninguno",
    "gn:country_code":"MX",
    "gn:dem":196,
    "gn:feature_class":"P",
    "gn:feature_code":"PPL",
    "gn:name":"Ninguno",
    "gn:population":5,
    "gn:timezone":"America/Mazatlan",
    "iso:country":"MX",
    "wof:name":"Ninguno",
    "wof:placetype":"locality",
    "wof:population":5
},
  "geometry": {"coordinates":[-106.74169000000001,24.1472],"type":"Point"}
}