{
  "type": "Feature",
  "properties": {
    "gn:admin1_code":"22",
    "gn:admin2_code":"3.0",
    "gn:asciiname":"Rio del Carrizal",
    "gn:country_code":"MX",
    "gn:dem":623,
    "gn:feature_class":"P",
    "gn:feature_code":"PPL",
    "gn:name":"R\u00edo del Carrizal",
    "gn:population":0,
    "gn:timezone":"America/Mexico_City",
    "iso:country":"MX",
    "name:spa_x_preferred":[
        "R\u00edo del Carrizal"
    ],
    "name:und_x_variant":[
        "El Carrizal"
    ],
    "wof:name":"Rio del Carrizal",
    "wof:placetype":"locality"
},
  "geometry": {"coordinates":[-99.7016,21.48278],"type":"Point"}
}