{
  "type": "Feature",
  "properties": {
    "gn:admin1_code":"23.0",
    "gn:admin2_code":"2.0",
    "gn:asciiname":"Kilometro Cincuenta",
    "gn:country_code":"MX",
    "gn:dem":7,
    "gn:feature_class":"P",
    "gn:feature_code":"PPL",
    "gn:name":"Kil\u00f3metro Cincuenta",
    "gn:population":0,
    "gn:timezone":"America/Cancun",
    "iso:country":"MX",
    "name:spa_x_preferred":[
        "Kil\u00f3metro Cincuenta"
    ],
    "wof:name":"Kilometro Cincuenta",
    "wof:placetype":"locality"
},
  "geometry": {"coordinates":[-87.77167,19.94772],"type":"Point"}
}