{
  "type": "Feature",
  "properties": {
    "gn:admin1_code":"24.0",
    "gn:admin2_code":"40.0",
    "gn:asciiname":"El Caseral",
    "gn:country_code":"MX",
    "gn:dem":44,
    "gn:feature_class":"P",
    "gn:feature_code":"PPL",
    "gn:name":"El Caseral",
    "gn:population":0,
    "gn:timezone":"America/Mexico_City",
    "iso:country":"MX",
    "name:spa_x_preferred":[
        "El Caseral"
    ],
    "wof:name":"El Caseral",
    "wof:placetype":"locality"
},
  "geometry": {"coordinates":[-98.83611999999999,22.08526],"type":"Point"}
}