{
  "type": "Feature",
  "properties": {
    "gn:admin1_code":"5",
    "gn:admin2_code":"79",
    "gn:asciiname":"La Gloria",
    "gn:country_code":"MX",
    "gn:dem":913,
    "gn:feature_class":"P",
    "gn:feature_code":"PPL",
    "gn:name":"La Gloria",
    "gn:population":34,
    "gn:timezone":"America/Mexico_City",
    "iso:country":"MX",
    "wof:name":"La Gloria",
    "wof:placetype":"locality",
    "wof:population":34
},
  "geometry": {"coordinates":[-93.24861,16.96333],"type":"Point"}
}