{
  "type": "Feature",
  "properties": {
    "gn:admin1_code":"6",
    "gn:admin2_code":"65.0",
    "gn:asciiname":"Mesa de Huateivo",
    "gn:country_code":"MX",
    "gn:dem":1719,
    "gn:feature_class":"P",
    "gn:feature_code":"PPL",
    "gn:name":"Mesa de Huateivo",
    "gn:population":0,
    "gn:timezone":"America/Chihuahua",
    "iso:country":"MX",
    "name:spa_x_preferred":[
        "Mesa de Huateivo"
    ],
    "wof:name":"Mesa de Huateivo",
    "wof:placetype":"locality"
},
  "geometry": {"coordinates":[-108.03946000000001,27.33446],"type":"Point"}
}