{
  "type": "Feature",
  "properties": {
    "gn:admin1_code":"31",
    "gn:admin2_code":"96.0",
    "gn:asciiname":"San Isidro Kilometro Catorce (San Isidro)",
    "gn:country_code":"MX",
    "gn:dem":13,
    "gn:feature_class":"P",
    "gn:feature_code":"PPL",
    "gn:name":"San Isidro Kil\u00f3metro Catorce (San Isidro)",
    "gn:population":185,
    "gn:timezone":"America/Merida",
    "iso:country":"MX",
    "name:und_x_variant":[
        "San Isidro Kil\u00f3metro Catorce (San Isidro)"
    ],
    "wof:name":"San Isidro Kilometro Catorce (San Isidro)",
    "wof:placetype":"locality",
    "wof:population":185
},
  "geometry": {"coordinates":[-87.67333000000001,21.09639],"type":"Point"}
}