{
  "type": "Feature",
  "properties": {
    "gn:admin1_code":"6",
    "gn:admin2_code":"3.0",
    "gn:asciiname":"San Antonio del Alto Corralejo",
    "gn:cc2":"MX",
    "gn:country_code":"MX",
    "gn:dem":1536,
    "gn:feature_class":"P",
    "gn:feature_code":"PPL",
    "gn:name":"San Antonio del Alto Corralejo",
    "gn:population":0,
    "gn:timezone":"America/Chihuahua",
    "iso:country":"MX",
    "name:spa_x_preferred":[
        "San Antonio el Alto"
    ],
    "name:und_x_variant":[
        "Corralejo",
        "San Antonio Corralejo",
        "San Antonio Corraleso de Abaso"
    ],
    "wof:name":"San Antonio del Alto Corralejo",
    "wof:placetype":"locality",
    "wof:population":324
},
  "geometry": {"coordinates":[-105.39427000000001,27.08692],"type":"Point"}
}