{
  "type": "Feature",
  "properties": {
    "gn:admin1_code":"14.0",
    "gn:admin2_code":"112.0",
    "gn:asciiname":"Rio de Gomez",
    "gn:country_code":"MX",
    "gn:dem":1723,
    "gn:feature_class":"P",
    "gn:feature_code":"PPL",
    "gn:name":"R\u00edo de G\u00f3mez",
    "gn:population":0,
    "gn:timezone":"America/Mexico_City",
    "iso:country":"MX",
    "name:spa_x_preferred":[
        "R\u00edo de G\u00f3mez"
    ],
    "wof:name":"Rio de Gomez",
    "wof:placetype":"locality"
},
  "geometry": {"coordinates":[-102.99894,19.80666],"type":"Point"}
}