{
  "type": "Feature",
  "properties": {
    "gn:admin1_code":"30",
    "gn:admin2_code":"23.0",
    "gn:asciiname":"Cerro de Barreras",
    "gn:country_code":"MX",
    "gn:dem":974,
    "gn:feature_class":"P",
    "gn:feature_code":"PPL",
    "gn:name":"Cerro de Barreras",
    "gn:population":201,
    "gn:timezone":"America/Mexico_City",
    "iso:country":"MX",
    "wof:name":"Cerro de Barreras",
    "wof:placetype":"locality",
    "wof:population":201
},
  "geometry": {"coordinates":[-97.18694000000001,19.87528],"type":"Point"}
}