{
  "type": "Feature",
  "properties": {
    "gn:admin1_code":"25",
    "gn:admin2_code":"10.0",
    "gn:asciiname":"El Parnaso",
    "gn:country_code":"MX",
    "gn:dem":26,
    "gn:feature_class":"P",
    "gn:feature_code":"PPL",
    "gn:name":"El Parnaso",
    "gn:population":70,
    "gn:timezone":"America/Mazatlan",
    "iso:country":"MX",
    "wof:name":"El Parnaso",
    "wof:placetype":"locality",
    "wof:population":70
},
  "geometry": {"coordinates":[-108.89239999999999,26.01044],"type":"Point"}
}