{
  "type": "Feature",
  "properties": {
    "gn:admin1_code":"12",
    "gn:asciiname":"Zania",
    "gn:cc2":"MX",
    "gn:country_code":"MX",
    "gn:dem":14,
    "gn:feature_class":"P",
    "gn:feature_code":"PPL",
    "gn:name":"Zania",
    "gn:population":0,
    "gn:timezone":"America/Mexico_City",
    "iso:country":"MX",
    "name:und_x_variant":[
        "Zanja",
        "Zania"
    ],
    "wof:name":"Zania",
    "wof:placetype":"locality"
},
  "geometry": {"coordinates":[-102.15000000000001,17.96667],"type":"Point"}
}