{
  "type": "Feature",
  "properties": {
    "gn:admin1_code":"24",
    "gn:admin2_code":"20.0",
    "gn:asciiname":"Estanque de Agua Buena",
    "gn:country_code":"MX",
    "gn:dem":1549,
    "gn:feature_class":"P",
    "gn:feature_code":"PPL",
    "gn:name":"Estanque de Agua Buena",
    "gn:population":0,
    "gn:timezone":"America/Mexico_City",
    "iso:country":"MX",
    "name:und_x_variant":[
        "El Estanque",
        "Agua Buena"
    ],
    "wof:name":"Estanque de Agua Buena",
    "wof:placetype":"locality"
},
  "geometry": {"coordinates":[-100.58574,23.70669],"type":"Point"}
}