{
  "type": "Feature",
  "properties": {
    "gn:admin1_code":"18.0",
    "gn:admin2_code":"10.0",
    "gn:asciiname":"Los Petates",
    "gn:country_code":"MX",
    "gn:dem":876,
    "gn:feature_class":"P",
    "gn:feature_code":"PPL",
    "gn:name":"Los Petates",
    "gn:population":0,
    "gn:timezone":"America/Mazatlan",
    "iso:country":"MX",
    "wof:name":"Los Petates",
    "wof:placetype":"locality"
},
  "geometry": {"coordinates":[-105.1121,22.28663],"type":"Point"}
}