{
  "type": "Feature",
  "properties": {
    "gn:admin1_code":"28",
    "gn:admin2_code":"37.0",
    "gn:asciiname":"La Clinica (Los Felinos)",
    "gn:country_code":"MX",
    "gn:dem":95,
    "gn:feature_class":"P",
    "gn:feature_code":"PPL",
    "gn:name":"La Cl\u00ednica (Los Felinos)",
    "gn:population":7,
    "gn:timezone":"America/Monterrey",
    "iso:country":"MX",
    "name:und_x_variant":[
        "La Cl\u00ednica (Los Felinos)"
    ],
    "wof:name":"La Clinica (Los Felinos)",
    "wof:placetype":"locality",
    "wof:population":7
},
  "geometry": {"coordinates":[-97.96083,23.33694],"type":"Point"}
}