{
  "type": "Feature",
  "properties": {
    "gn:admin1_code":"26",
    "gn:admin2_code":"51.0",
    "gn:asciiname":"Piedra Escrita",
    "gn:country_code":"MX",
    "gn:dem":492,
    "gn:feature_class":"P",
    "gn:feature_code":"PPL",
    "gn:name":"Piedra Escrita",
    "gn:population":0,
    "gn:timezone":"America/Hermosillo",
    "iso:country":"MX",
    "name:spa_x_preferred":[
        "Piedra Escrita"
    ],
    "wof:name":"Piedra Escrita",
    "wof:placetype":"locality"
},
  "geometry": {"coordinates":[-109.47410000000001,28.12394],"type":"Point"}
}