{
  "type": "Feature",
  "properties": {
    "gn:admin1_code":"10",
    "gn:admin2_code":"14.0",
    "gn:asciiname":"Los Guayces",
    "gn:country_code":"MX",
    "gn:dem":1027,
    "gn:feature_class":"P",
    "gn:feature_code":"PPL",
    "gn:name":"Los Guayces",
    "gn:population":0,
    "gn:timezone":"America/Mazatlan",
    "iso:country":"MX",
    "name:spa_x_preferred":[
        "Los Guayces"
    ],
    "wof:name":"Los Guayces",
    "wof:placetype":"locality"
},
  "geometry": {"coordinates":[-104.57207,22.42967],"type":"Point"}
}