{
  "type": "Feature",
  "properties": {
    "gn:admin1_code":"27.0",
    "gn:admin2_code":"8.0",
    "gn:asciiname":"Charito",
    "gn:country_code":"MX",
    "gn:dem":34,
    "gn:feature_class":"P",
    "gn:feature_code":"PPL",
    "gn:name":"Charito",
    "gn:population":0,
    "gn:timezone":"America/Mexico_City",
    "iso:country":"MX",
    "name:spa_x_preferred":[
        "Charito"
    ],
    "wof:name":"Charito",
    "wof:placetype":"locality"
},
  "geometry": {"coordinates":[-93.70416,17.73957],"type":"Point"}
}