{
  "type": "Feature",
  "properties": {
    "gn:admin1_code":"27.0",
    "gn:admin2_code":"8.0",
    "gn:asciiname":"Charito",
    "gn:country_code":"MX",
    "gn:dem":34,
    "gn:feature_class":"P",
    "gn:feature_code":"PPL",
    "gn:name":"Charito",
    "gn:population":0,
    "gn:timezone":"America/Mexico_City",
    "iso:country":"MX",
    "name:bul_x_preferred":[
        "\u0425\u0430\u0440\u0438\u0442\u043e"
    ],
    "name:ell_x_preferred":[
        "\u03a7\u03b1\u03c1\u03b9\u03c4\u03ce"
    ],
    "name:ita_x_preferred":[
        "Charito"
    ],
    "name:por_x_preferred":[
        "C\u00e1rito"
    ],
    "name:spa_x_preferred":[
        "Charito"
    ],
    "name:swe_x_preferred":[
        "Charito"
    ],
    "name:ukr_x_preferred":[
        "\u0425\u0430\u0440\u0456\u0442\u043e"
    ],
    "wof:name":"Charito",
    "wof:placetype":"locality"
},
  "geometry": {"coordinates":[-93.70416,17.73957],"type":"Point"}
}