{
  "type": "Feature",
  "properties": {
    "gn:admin1_code":"2",
    "gn:admin2_code":"1.0",
    "gn:asciiname":"General Leandro Valle",
    "gn:country_code":"MX",
    "gn:dem":1105,
    "gn:feature_class":"P",
    "gn:feature_code":"PPL",
    "gn:name":"General Leandro Valle",
    "gn:population":0,
    "gn:timezone":"America/Tijuana",
    "iso:country":"MX",
    "name:spa_x_preferred":[
        "General Leandro Valle"
    ],
    "name:und_x_variant":[
        "Ejido General Leandro Valle",
        "Los Pocitos"
    ],
    "wof:name":"General Leandro Valle",
    "wof:placetype":"locality"
},
  "geometry": {"coordinates":[-115.76609999999999,31.26651],"type":"Point"}
}