{
  "type": "Feature",
  "properties": {
    "gn:admin1_code":"12",
    "gn:admin2_code":"10",
    "gn:asciiname":"Cuapexco",
    "gn:country_code":"MX",
    "gn:dem":1674,
    "gn:feature_class":"P",
    "gn:feature_code":"PPL",
    "gn:name":"Cuapexco",
    "gn:population":17,
    "gn:timezone":"America/Mexico_City",
    "iso:country":"MX",
    "wof:name":"Cuapexco",
    "wof:placetype":"locality",
    "wof:population":17
},
  "geometry": {"coordinates":[-98.92263,17.54809],"type":"Point"}
}