{
  "type": "Feature",
  "properties": {
    "gn:admin1_code":"26",
    "gn:admin2_code":"71.0",
    "gn:asciiname":"El Aleman",
    "gn:country_code":"MX",
    "gn:dem":20,
    "gn:feature_class":"P",
    "gn:feature_code":"PPL",
    "gn:name":"El Alem\u00e1n",
    "gn:population":0,
    "gn:timezone":"America/Hermosillo",
    "iso:country":"MX",
    "name:spa_x_preferred":[
        "El Alem\u00e1n"
    ],
    "wof:name":"El Aleman",
    "wof:placetype":"locality"
},
  "geometry": {"coordinates":[-109.75932,27.09775],"type":"Point"}
}