{
  "type": "Feature",
  "properties": {
    "gn:admin1_code":"20",
    "gn:admin2_code":"141.0",
    "gn:asciiname":"Pozo San Juan",
    "gn:country_code":"MX",
    "gn:dem":9,
    "gn:feature_class":"P",
    "gn:feature_code":"PPL",
    "gn:name":"Pozo San Juan",
    "gn:population":0,
    "gn:timezone":"America/Mexico_City",
    "iso:country":"MX",
    "name:spa_x_preferred":[
        "Pozo San Juan"
    ],
    "name:und_x_variant":[
        "San Juan"
    ],
    "wof:name":"Pozo San Juan",
    "wof:placetype":"locality"
},
  "geometry": {"coordinates":[-94.47281,16.1832],"type":"Point"}
}