{
  "type": "Feature",
  "properties": {
    "gn:admin1_code":"7.0",
    "gn:admin2_code":"23.0",
    "gn:asciiname":"La Mora",
    "gn:country_code":"MX",
    "gn:dem":1242,
    "gn:feature_class":"P",
    "gn:feature_code":"PPL",
    "gn:name":"La Mora",
    "gn:population":7,
    "gn:timezone":"America/Monterrey",
    "iso:country":"MX",
    "wof:name":"La Mora",
    "wof:placetype":"locality",
    "wof:population":7
},
  "geometry": {"coordinates":[-102.50490000000001,27.72642],"type":"Point"}
}