{
  "type": "Feature",
  "properties": {
    "gn:admin1_code":"6.0",
    "gn:asciiname":"Los Mendez",
    "gn:country_code":"MX",
    "gn:dem":1218,
    "gn:feature_class":"P",
    "gn:feature_code":"PPL",
    "gn:name":"Los M\u00e9ndez",
    "gn:population":0,
    "gn:timezone":"America/Chihuahua",
    "iso:country":"MX",
    "name:spa_x_preferred":[
        "Los M\u00e9ndez"
    ],
    "wof:name":"Los Mendez",
    "wof:placetype":"locality"
},
  "geometry": {"coordinates":[-105.47306,28.09312000000001],"type":"Point"}
}