{
  "type": "Feature",
  "properties": {
    "gn:admin1_code":"28.0",
    "gn:admin2_code":"29.0",
    "gn:asciiname":"Piedras Chinas",
    "gn:country_code":"MX",
    "gn:dem":135,
    "gn:feature_class":"P",
    "gn:feature_code":"PPL",
    "gn:name":"Piedras Chinas",
    "gn:population":0,
    "gn:timezone":"America/Monterrey",
    "iso:country":"MX",
    "name:spa_x_preferred":[
        "Piedras Chinas"
    ],
    "wof:name":"Piedras Chinas",
    "wof:placetype":"locality"
},
  "geometry": {"coordinates":[-99.16764000000001,22.81846],"type":"Point"}
}