{
  "type": "Feature",
  "properties": {
    "gn:admin1_code":"10",
    "gn:admin2_code":"35.0",
    "gn:asciiname":"Ojos Azules II",
    "gn:country_code":"MX",
    "gn:dem":2119,
    "gn:feature_class":"P",
    "gn:feature_code":"PPL",
    "gn:name":"Ojos Azules II",
    "gn:population":16,
    "gn:timezone":"America/Monterrey",
    "iso:country":"MX",
    "wof:name":"Ojos Azules II",
    "wof:placetype":"locality",
    "wof:population":16
},
  "geometry": {"coordinates":[-106.07847,25.58413],"type":"Point"}
}