{
  "type": "Feature",
  "properties": {
    "gn:admin1_code":"20",
    "gn:admin2_code":"141.0",
    "gn:asciiname":"Los Tules",
    "gn:country_code":"MX",
    "gn:dem":8,
    "gn:feature_class":"P",
    "gn:feature_code":"PPL",
    "gn:name":"Los Tules",
    "gn:population":0,
    "gn:timezone":"America/Mexico_City",
    "iso:country":"MX",
    "wof:name":"Los Tules",
    "wof:placetype":"locality"
},
  "geometry": {"coordinates":[-94.57899,16.30877000000001],"type":"Point"}
}