{
  "type": "Feature",
  "properties": {
    "gn:admin1_code":"32",
    "gn:admin2_code":"38.0",
    "gn:asciiname":"El Tecomate",
    "gn:country_code":"MX",
    "gn:dem":2207,
    "gn:feature_class":"P",
    "gn:feature_code":"PPL",
    "gn:name":"El Tecomate",
    "gn:population":0,
    "gn:timezone":"America/Mexico_City",
    "iso:country":"MX",
    "name:und_x_variant":[
        "Tecomate"
    ],
    "wof:name":"El Tecomate",
    "wof:placetype":"locality"
},
  "geometry": {"coordinates":[-101.61099,22.53432],"type":"Point"}
}