{
  "type": "Feature",
  "properties": {
    "gn:admin1_code":"25",
    "gn:admin2_code":"18.0",
    "gn:asciiname":"Campo Cinco Hermanos (Emiliano Zapata)",
    "gn:country_code":"MX",
    "gn:dem":8,
    "gn:feature_class":"P",
    "gn:feature_code":"PPL",
    "gn:name":"Campo Cinco Hermanos (Emiliano Zapata)",
    "gn:population":544,
    "gn:timezone":"America/Mazatlan",
    "iso:country":"MX",
    "wof:name":"Campo Cinco Hermanos (Emiliano Zapata)",
    "wof:placetype":"locality",
    "wof:population":544
},
  "geometry": {"coordinates":[-107.85944000000001,24.80861],"type":"Point"}
}