{
  "type": "Feature",
  "properties": {
    "gn:admin1_code":"22.0",
    "gn:admin2_code":"12.0",
    "gn:asciiname":"Aguacaliente",
    "gn:country_code":"MX",
    "gn:dem":1924,
    "gn:feature_class":"P",
    "gn:feature_code":"PPL",
    "gn:name":"Aguacaliente",
    "gn:population":0,
    "gn:timezone":"America/Mexico_City",
    "iso:country":"MX",
    "name:spa_x_preferred":[
        "Aguacaliente"
    ],
    "wof:name":"Aguacaliente",
    "wof:placetype":"locality"
},
  "geometry": {"coordinates":[-100.20443,20.53171],"type":"Point"}
}