{
  "type": "Feature",
  "properties": {
    "gn:admin1_code":"32",
    "gn:admin2_code":"18.0",
    "gn:asciiname":"Los Moralenos",
    "gn:country_code":"MX",
    "gn:dem":1475,
    "gn:feature_class":"P",
    "gn:feature_code":"PPL",
    "gn:name":"Los Morale\u00f1os",
    "gn:population":96,
    "gn:timezone":"America/Mexico_City",
    "iso:country":"MX",
    "name:und_x_variant":[
        "Los Morale\u00f1os"
    ],
    "wof:name":"Los Moralenos",
    "wof:placetype":"locality",
    "wof:population":96
},
  "geometry": {"coordinates":[-102.89778,21.72361],"type":"Point"}
}