{
  "type": "Feature",
  "properties": {
    "gn:admin1_code":"6.0",
    "gn:admin2_code":"31.0",
    "gn:asciiname":"Los Dos Amigos",
    "gn:country_code":"MX",
    "gn:dem":2148,
    "gn:feature_class":"P",
    "gn:feature_code":"PPL",
    "gn:name":"Los Dos Amigos",
    "gn:population":0,
    "gn:timezone":"America/Chihuahua",
    "iso:country":"MX",
    "name:spa_x_preferred":[
        "Los Dos Amigos"
    ],
    "wof:name":"Los Dos Amigos",
    "wof:placetype":"locality"
},
  "geometry": {"coordinates":[-107.25593000000001,28.39811],"type":"Point"}
}