{
  "type": "Feature",
  "properties": {
    "gn:admin1_code":"25.0",
    "gn:admin2_code":"17.0",
    "gn:asciiname":"La Higuerita",
    "gn:country_code":"MX",
    "gn:dem":110,
    "gn:feature_class":"P",
    "gn:feature_code":"PPL",
    "gn:name":"La Higuerita",
    "gn:population":0,
    "gn:timezone":"America/Mazatlan",
    "iso:country":"MX",
    "name:spa_x_preferred":[
        "La Higuerita"
    ],
    "wof:name":"La Higuerita",
    "wof:placetype":"locality"
},
  "geometry": {"coordinates":[-108.08052000000001,25.68819],"type":"Point"}
}