{
  "type": "Feature",
  "properties": {
    "gn:admin1_code":"6",
    "gn:admin2_code":"63.0",
    "gn:asciiname":"El Riito",
    "gn:country_code":"MX",
    "gn:dem":1664,
    "gn:feature_class":"P",
    "gn:feature_code":"PPL",
    "gn:name":"El Ri\u00edto",
    "gn:population":6,
    "gn:timezone":"America/Chihuahua",
    "iso:country":"MX",
    "name:und_x_variant":[
        "El Ri\u00edto"
    ],
    "wof:name":"El Riito",
    "wof:placetype":"locality",
    "wof:population":6
},
  "geometry": {"coordinates":[-108.06858,28.71934000000001],"type":"Point"}
}