{
  "type": "Feature",
  "properties": {
    "gn:admin1_code":"6",
    "gn:admin2_code":"56.0",
    "gn:asciiname":"La Batea",
    "gn:country_code":"MX",
    "gn:dem":1617,
    "gn:feature_class":"P",
    "gn:feature_code":"PPL",
    "gn:name":"La Batea",
    "gn:population":0,
    "gn:timezone":"America/Chihuahua",
    "iso:country":"MX",
    "name:spa_x_preferred":[
        "La Batea"
    ],
    "wof:name":"La Batea",
    "wof:placetype":"locality"
},
  "geometry": {"coordinates":[-106.41545000000001,27.26688],"type":"Point"}
}