{
  "type": "Feature",
  "properties": {
    "gn:admin1_code":"5",
    "gn:admin2_code":"17",
    "gn:asciiname":"San Judas (San Jacinto)",
    "gn:country_code":"MX",
    "gn:dem":730,
    "gn:feature_class":"P",
    "gn:feature_code":"PPL",
    "gn:name":"San Judas (San Jacinto)",
    "gn:population":14,
    "gn:timezone":"America/Mexico_City",
    "iso:country":"MX",
    "wof:name":"San Judas (San Jacinto)",
    "wof:placetype":"locality",
    "wof:population":14
},
  "geometry": {"coordinates":[-93.92694,16.775],"type":"Point"}
}