{
  "type": "Feature",
  "properties": {
    "gn:admin1_code":"30",
    "gn:admin2_code":"163.0",
    "gn:asciiname":"Hidalgotitlan",
    "gn:country_code":"MX",
    "gn:dem":1038,
    "gn:feature_class":"P",
    "gn:feature_code":"PPL",
    "gn:name":"Hidalgotitl\u00e1n",
    "gn:population":54,
    "gn:timezone":"America/Mexico_City",
    "iso:country":"MX",
    "name:und_x_variant":[
        "Hidalgotitl\u00e1n"
    ],
    "wof:name":"Hidalgotitlan",
    "wof:placetype":"locality",
    "wof:population":54
},
  "geometry": {"coordinates":[-96.97583,19.83667],"type":"Point"}
}