{
  "type": "Feature",
  "properties": {
    "gn:admin1_code":"30",
    "gn:admin2_code":"10.0",
    "gn:asciiname":"Colonia 3 de Mayo",
    "gn:country_code":"MX",
    "gn:dem":2489,
    "gn:feature_class":"P",
    "gn:feature_code":"PPL",
    "gn:name":"Colonia 3 de Mayo",
    "gn:population":181,
    "gn:timezone":"America/Mexico_City",
    "iso:country":"MX",
    "wof:name":"Colonia 3 de Mayo",
    "wof:placetype":"locality",
    "wof:population":181
},
  "geometry": {"coordinates":[-97.19917,19.69778],"type":"Point"}
}