{
  "type": "Feature",
  "properties": {
    "gn:admin1_code":"28",
    "gn:admin2_code":"35.0",
    "gn:asciiname":"Simon Bolivar",
    "gn:country_code":"MX",
    "gn:dem":8,
    "gn:feature_class":"P",
    "gn:feature_code":"PPL",
    "gn:name":"Sim\u00f3n Bol\u00edvar",
    "gn:population":0,
    "gn:timezone":"America/Monterrey",
    "iso:country":"MX",
    "name:spa_x_preferred":[
        "Sim\u00f3n Bol\u00edvar"
    ],
    "wof:name":"Simon Bolivar",
    "wof:placetype":"locality"
},
  "geometry": {"coordinates":[-97.91168999999999,24.56807],"type":"Point"}
}