{
  "type": "Feature",
  "properties": {
    "gn:admin1_code":"7.0",
    "gn:admin2_code":"34.0",
    "gn:asciiname":"La Atravesada",
    "gn:country_code":"MX",
    "gn:dem":1291,
    "gn:feature_class":"P",
    "gn:feature_code":"PPL",
    "gn:name":"La Atravesada",
    "gn:population":0,
    "gn:timezone":"America/Monterrey",
    "iso:country":"MX",
    "name:spa_x_preferred":[
        "La Atravesada"
    ],
    "name:und_x_variant":[
        "Rancho Atravesada",
        "Atravesada"
    ],
    "wof:name":"La Atravesada",
    "wof:placetype":"locality"
},
  "geometry": {"coordinates":[-103.58602999999999,27.26],"type":"Point"}
}