{
  "type": "Feature",
  "properties": {
    "gn:admin1_code":"15",
    "gn:admin2_code":"10.0",
    "gn:asciiname":"Colonia el Pixquay (Colonia el Carmen)",
    "gn:country_code":"MX",
    "gn:dem":2241,
    "gn:feature_class":"P",
    "gn:feature_code":"PPL",
    "gn:name":"Colonia el Pixquay (Colonia el Carmen)",
    "gn:population":539,
    "gn:timezone":"America/Mexico_City",
    "iso:country":"MX",
    "wof:name":"Colonia el Pixquay (Colonia el Carmen)",
    "wof:placetype":"locality",
    "wof:population":539
},
  "geometry": {"coordinates":[-99.18889,19.96361],"type":"Point"}
}