{
  "type": "Feature",
  "properties": {
    "gn:admin1_code":"6",
    "gn:admin2_code":"29.0",
    "gn:asciiname":"Las Iglesias",
    "gn:country_code":"MX",
    "gn:dem":2829,
    "gn:feature_class":"P",
    "gn:feature_code":"PPL",
    "gn:name":"Las Iglesias",
    "gn:population":4,
    "gn:timezone":"America/Chihuahua",
    "iso:country":"MX",
    "wof:name":"Las Iglesias",
    "wof:placetype":"locality",
    "wof:population":4
},
  "geometry": {"coordinates":[-106.60984999999999,26.25329],"type":"Point"}
}