{
  "type": "Feature",
  "properties": {
    "gn:admin1_code":"30",
    "gn:admin2_code":"144.0",
    "gn:asciiname":"El Juile",
    "gn:country_code":"MX",
    "gn:dem":37,
    "gn:feature_class":"P",
    "gn:feature_code":"PPL",
    "gn:name":"El Juile",
    "gn:population":0,
    "gn:timezone":"America/Mexico_City",
    "iso:country":"MX",
    "name:und_x_variant":[
        "Juile",
        "El Juile"
    ],
    "wof:name":"El Juile",
    "wof:placetype":"locality"
},
  "geometry": {"coordinates":[-94.98945999999999,17.74412000000001],"type":"Point"}
}