{
  "type": "Feature",
  "properties": {
    "gn:admin1_code":"25",
    "gn:admin2_code":"6.0",
    "gn:asciiname":"Campo Moroleon",
    "gn:country_code":"MX",
    "gn:dem":29,
    "gn:feature_class":"P",
    "gn:feature_code":"PPL",
    "gn:name":"Campo Morole\u00f3n",
    "gn:population":80,
    "gn:timezone":"America/Mazatlan",
    "iso:country":"MX",
    "name:und_x_variant":[
        "Campo Morole\u00f3n"
    ],
    "wof:name":"Campo Moroleon",
    "wof:placetype":"locality",
    "wof:population":80
},
  "geometry": {"coordinates":[-107.52194,24.7725],"type":"Point"}
}