{
  "type": "Feature",
  "properties": {
    "gn:admin1_code":"5",
    "gn:admin2_code":"57",
    "gn:asciiname":"Miramar",
    "gn:country_code":"MX",
    "gn:dem":2523,
    "gn:feature_class":"P",
    "gn:feature_code":"PPL",
    "gn:name":"Miramar",
    "gn:population":40,
    "gn:timezone":"America/Mexico_City",
    "iso:country":"MX",
    "name:ara_x_preferred":[
        "\u0645\u064a\u0631\u0627\u0645\u0627\u0631"
    ],
    "name:cat_x_preferred":[
        "Miramar"
    ],
    "name:ceb_x_preferred":[
        "Miramar"
    ],
    "name:deu_x_preferred":[
        "Miramar"
    ],
    "name:fra_x_preferred":[
        "Miramar"
    ],
    "name:glg_x_preferred":[
        "Miramar"
    ],
    "name:ita_x_preferred":[
        "Miramar"
    ],
    "name:jpn_x_preferred":[
        "\u30df\u30e9\u30de\u30fc"
    ],
    "name:lit_x_preferred":[
        "Miramaras"
    ],
    "name:nds_x_preferred":[
        "Miramar"
    ],
    "name:nld_x_preferred":[
        "Miramar"
    ],
    "name:pol_x_preferred":[
        "Miramar"
    ],
    "name:por_x_preferred":[
        "Miramar"
    ],
    "name:rus_x_preferred":[
        "\u041c\u0438\u0440\u0430\u043c\u0430\u0440"
    ],
    "name:spa_x_preferred":[
        "Miramar"
    ],
    "name:srp_x_preferred":[
        "\u041c\u0438\u0440\u0430\u043c\u0430\u0440"
    ],
    "name:swe_x_preferred":[
        "Miramar"
    ],
    "name:ukr_x_preferred":[
        "\u041c\u0456\u0440\u0430\u043c\u0430\u0440"
    ],
    "wof:name":"Miramar",
    "wof:placetype":"locality",
    "wof:population":40
},
  "geometry": {"coordinates":[-92.23889,15.25056],"type":"Point"}
}