{
  "type": "Feature",
  "properties": {
    "gn:admin1_code":"30.0",
    "gn:admin2_code":"207.0",
    "gn:asciiname":"San Pedro los Pinos",
    "gn:country_code":"MX",
    "gn:dem":46,
    "gn:feature_class":"P",
    "gn:feature_code":"PPL",
    "gn:name":"San Pedro los Pinos",
    "gn:population":0,
    "gn:timezone":"America/Mexico_City",
    "iso:country":"MX",
    "name:spa_x_preferred":[
        "San Pedro los Pinos"
    ],
    "wof:name":"San Pedro los Pinos",
    "wof:placetype":"locality"
},
  "geometry": {"coordinates":[-96.24764999999999,18.39268],"type":"Point"}
}