{
  "type": "Feature",
  "properties": {
    "gn:admin1_code":"5",
    "gn:admin2_code":"26.0",
    "gn:asciiname":"Chimtic",
    "gn:country_code":"MX",
    "gn:dem":2046,
    "gn:feature_class":"P",
    "gn:feature_code":"PPL",
    "gn:name":"Chimtic",
    "gn:population":0,
    "gn:timezone":"America/Mexico_City",
    "iso:country":"MX",
    "name:spa_x_preferred":[
        "Chimtic"
    ],
    "name:spa_x_variant":[
        "Chintic"
    ],
    "wof:name":"Chimtic",
    "wof:placetype":"locality"
},
  "geometry": {"coordinates":[-92.6014,16.92184],"type":"Point"}
}