{
  "type": "Feature",
  "properties": {
    "gn:gn_country":"MX",
    "gn:gn_fcode":"PPL",
    "gn:gn_pop":0,
    "iso:country":"MX",
    "name:spa_x_preferred":[
        "La Puebla"
    ],
    "qs_pg:aaroncc":"MX",
    "qs_pg:gn_country":"MX",
    "qs_pg:gn_fcode":"PPL",
    "qs_pg:gn_pop":0,
    "qs_pg:name":"Puebla",
    "qs_pg:name_adm0":"M\u00e9xico",
    "qs_pg:name_adm1":"Distrito Federal",
    "qs_pg:photos":23,
    "qs_pg:photos_1k":5,
    "qs_pg:photos_9k":1,
    "qs_pg:photos_9r":1,
    "qs_pg:photos_all":23,
    "qs_pg:photos_sr":1,
    "qs_pg:pop_sr":0,
    "qs_pg:qs_pg_placetype":"neighbourhood",
    "qs_pg:qs_pg_placetype_gp":"Suburb",
    "qs_pg:woe_adm0":23424900,
    "woe:adm0_id":23424900,
    "woe:name_adm0":"M\u00e9xico",
    "woe:name_adm1":"Distrito Federal",
    "woe:placetype":"Suburb",
    "wof:name":"Puebla",
    "wof:placetype":"neighbourhood"
},
  "geometry": {"coordinates":[-98.66916999999999,20.27541],"type":"Point"}
}