{
  "type": "Feature",
  "properties": {
    "gn:admin1_code":"15",
    "gn:admin2_code":"123",
    "gn:asciiname":"Sesteadero de Arriba",
    "gn:country_code":"MX",
    "gn:dem":652,
    "gn:feature_class":"P",
    "gn:feature_code":"PPL",
    "gn:name":"Sesteadero de Arriba",
    "gn:population":13,
    "gn:timezone":"America/Mexico_City",
    "iso:country":"MX",
    "wof:name":"Sesteadero de Arriba",
    "wof:placetype":"locality",
    "wof:population":13
},
  "geometry": {"coordinates":[-100.56255,18.85378],"type":"Point"}
}