{
  "type": "Feature",
  "properties": {
    "gn:admin1_code":"3.0",
    "gn:admin2_code":"8.0",
    "gn:asciiname":"El Bedito",
    "gn:cc2":"MX",
    "gn:country_code":"MX",
    "gn:dem":38,
    "gn:feature_class":"P",
    "gn:feature_code":"PPL",
    "gn:name":"El Bedito",
    "gn:population":0,
    "gn:timezone":"America/Mazatlan",
    "iso:country":"MX",
    "name:und_x_variant":[
        "El Bledito",
        "El Bedito"
    ],
    "wof:name":"El Bedito",
    "wof:placetype":"locality"
},
  "geometry": {"coordinates":[-109.76667,22.98333],"type":"Point"}
}