{
  "type": "Feature",
  "properties": {
    "gn:admin1_code":"12.0",
    "gn:asciiname":"Plan del Pollo",
    "gn:country_code":"MX",
    "gn:dem":801,
    "gn:feature_class":"P",
    "gn:feature_code":"PPL",
    "gn:name":"Plan del Pollo",
    "gn:population":0,
    "gn:timezone":"America/Mexico_City",
    "iso:country":"MX",
    "name:spa_x_preferred":[
        "Plan del Pollo"
    ],
    "wof:name":"Plan del Pollo",
    "wof:placetype":"locality"
},
  "geometry": {"coordinates":[-99.71993000000001,17.14302],"type":"Point"}
}