{
  "type": "Feature",
  "properties": {
    "gn:admin1_code":"18",
    "gn:admin2_code":"19.0",
    "gn:asciiname":"Colonia Nueva",
    "gn:country_code":"MX",
    "gn:dem":1086,
    "gn:feature_class":"P",
    "gn:feature_code":"PPL",
    "gn:name":"Colonia Nueva",
    "gn:population":132,
    "gn:timezone":"America/Mazatlan",
    "iso:country":"MX",
    "wof:name":"Colonia Nueva",
    "wof:placetype":"locality",
    "wof:population":132
},
  "geometry": {"coordinates":[-104.35034,21.89841],"type":"Point"}
}