{
  "type": "Feature",
  "properties": {
    "gn:admin1_code":"11",
    "gn:admin2_code":"37",
    "gn:asciiname":"El Trece",
    "gn:country_code":"MX",
    "gn:dem":1792,
    "gn:feature_class":"P",
    "gn:feature_code":"PPL",
    "gn:name":"El Trece",
    "gn:population":27,
    "gn:timezone":"America/Mexico_City",
    "iso:country":"MX",
    "wof:name":"El Trece",
    "wof:placetype":"locality",
    "wof:population":27
},
  "geometry": {"coordinates":[-101.47028,20.97389],"type":"Point"}
}