{
  "type": "Feature",
  "properties": {
    "gn:admin1_code":"24",
    "gn:admin2_code":"44.0",
    "gn:asciiname":"San Vicente",
    "gn:country_code":"MX",
    "gn:dem":1721,
    "gn:feature_class":"P",
    "gn:feature_code":"PPL",
    "gn:name":"San Vicente",
    "gn:population":255,
    "gn:timezone":"America/Mexico_City",
    "iso:country":"MX",
    "name:spa_x_preferred":[
        "San Vicente"
    ],
    "wof:name":"San Vicente",
    "wof:placetype":"locality",
    "wof:population":255
},
  "geometry": {"coordinates":[-100.88369,24.16918],"type":"Point"}
}