{
  "type": "Feature",
  "properties": {
    "gn:admin1_code":"16.0",
    "gn:admin2_code":"101.0",
    "gn:asciiname":"Las Paredes",
    "gn:country_code":"MX",
    "gn:dem":1657,
    "gn:feature_class":"P",
    "gn:feature_code":"PPL",
    "gn:name":"Las Paredes",
    "gn:population":0,
    "gn:timezone":"America/Mexico_City",
    "iso:country":"MX",
    "name:spa_x_preferred":[
        "Las Paredes"
    ],
    "wof:name":"Las Paredes",
    "wof:placetype":"locality"
},
  "geometry": {"coordinates":[-100.95193,19.58387],"type":"Point"}
}