{
  "type": "Feature",
  "properties": {
    "gn:admin1_code":"14.0",
    "gn:admin2_code":"68.0",
    "gn:asciiname":"El Chante",
    "gn:country_code":"MX",
    "gn:dem":312,
    "gn:feature_class":"P",
    "gn:feature_code":"PPL",
    "gn:name":"El Chante",
    "gn:population":0,
    "gn:timezone":"America/Mexico_City",
    "iso:country":"MX",
    "name:spa_x_preferred":[
        "El Chante"
    ],
    "wof:name":"El Chante",
    "wof:placetype":"locality"
},
  "geometry": {"coordinates":[-104.78008,19.66392],"type":"Point"}
}