{
  "type": "Feature",
  "properties": {
    "gn:admin1_code":"22",
    "gn:admin2_code":"3",
    "gn:asciiname":"Las Adjuntas",
    "gn:country_code":"MX",
    "gn:dem":525,
    "gn:feature_class":"P",
    "gn:feature_code":"PPL",
    "gn:name":"Las Adjuntas",
    "gn:population":17,
    "gn:timezone":"America/Mexico_City",
    "iso:country":"MX",
    "name:jpn_x_preferred":[
        "\u30e9\u30b9\u30fb\u30a2\u30c9\u30d5\u30f3\u30bf\u30b9\u99c5"
    ],
    "name:por_x_preferred":[
        "Esta\u00e7\u00e3o Las Adjuntas"
    ],
    "wof:name":"Las Adjuntas",
    "wof:placetype":"locality",
    "wof:population":17
},
  "geometry": {"coordinates":[-99.58194,21.39528],"type":"Point"}
}