{
  "type": "Feature",
  "properties": {
    "gn:admin1_code":"10.0",
    "gn:admin2_code":"11.0",
    "gn:asciiname":"El Salto de Arriba",
    "gn:country_code":"MX",
    "gn:dem":1608,
    "gn:feature_class":"P",
    "gn:feature_code":"PPL",
    "gn:name":"El Salto de Arriba",
    "gn:population":19,
    "gn:timezone":"America/Monterrey",
    "iso:country":"MX",
    "wof:name":"El Salto de Arriba",
    "wof:placetype":"locality",
    "wof:population":19
},
  "geometry": {"coordinates":[-105.13273999999998,25.80869],"type":"Point"}
}