{
  "type": "Feature",
  "properties": {
    "gn:admin1_code":"22",
    "gn:admin2_code":"6",
    "gn:asciiname":"Familia Sanchez",
    "gn:country_code":"MX",
    "gn:dem":1942,
    "gn:feature_class":"P",
    "gn:feature_code":"PPL",
    "gn:name":"Familia S\u00e1nchez",
    "gn:population":10,
    "gn:timezone":"America/Mexico_City",
    "iso:country":"MX",
    "name:und_x_variant":[
        "Familia S\u00e1nchez"
    ],
    "wof:name":"Familia Sanchez",
    "wof:placetype":"locality",
    "wof:population":10
},
  "geometry": {"coordinates":[-100.38833,20.48556],"type":"Point"}
}