{
  "type": "Feature",
  "properties": {
    "gn:admin1_code":"12",
    "gn:admin2_code":"60.0",
    "gn:asciiname":"Xitinga",
    "gn:country_code":"MX",
    "gn:dem":2125,
    "gn:feature_class":"P",
    "gn:feature_code":"PPL",
    "gn:name":"Xitinga",
    "gn:population":0,
    "gn:timezone":"America/Mexico_City",
    "iso:country":"MX",
    "name:spa_x_preferred":[
        "Xitinga"
    ],
    "wof:name":"Xitinga",
    "wof:placetype":"locality"
},
  "geometry": {"coordinates":[-99.73607,18.65826],"type":"Point"}
}