{
  "type": "Feature",
  "properties": {
    "gn:admin1_code":"27",
    "gn:admin2_code":"15.0",
    "gn:asciiname":"Guerrero",
    "gn:country_code":"MX",
    "gn:dem":65,
    "gn:feature_class":"P",
    "gn:feature_code":"PPL",
    "gn:name":"Guerrero",
    "gn:population":0,
    "gn:timezone":"America/Mexico_City",
    "iso:country":"MX",
    "name:spa_x_preferred":[
        "Guerrero"
    ],
    "wof:name":"Guerrero",
    "wof:placetype":"locality"
},
  "geometry": {"coordinates":[-92.75523,17.40929],"type":"Point"}
}