{
  "type": "Feature",
  "properties": {
    "gn:country":"MX",
    "gn:fcode":"PPL",
    "gn:population":0,
    "iso:country":"MX",
    "name:bre_x_preferred":[
        "San Miguel"
    ],
    "name:bul_x_preferred":[
        "\u0421\u0430\u043d \u041c\u0438\u0433\u0435\u043b"
    ],
    "name:cat_x_preferred":[
        "San Miguel"
    ],
    "name:ceb_x_preferred":[
        "San Miguel"
    ],
    "name:deu_x_preferred":[
        "San Miguel"
    ],
    "name:est_x_preferred":[
        "San Miguel"
    ],
    "name:eus_x_preferred":[
        "San Miguel"
    ],
    "name:fra_x_preferred":[
        "San Miguel"
    ],
    "name:glg_x_preferred":[
        "San Miguel"
    ],
    "name:heb_x_preferred":[
        "\u05e1\u05df \u05de\u05d9\u05d2\u05dc"
    ],
    "name:ilo_x_preferred":[
        "San Miguel"
    ],
    "name:ita_x_preferred":[
        "San Miguel"
    ],
    "name:jpn_x_preferred":[
        "\u30b5\u30f3\u30fb\u30df\u30b2\u30eb"
    ],
    "name:kat_x_preferred":[
        "\u10e1\u10d0\u10dc-\u10db\u10d8\u10d2\u10d4\u10da\u10d8"
    ],
    "name:kor_x_preferred":[
        "\uc0b0\ubbf8\uac94"
    ],
    "name:lit_x_preferred":[
        "San Migelis"
    ],
    "name:nah_x_preferred":[
        "San Miguel"
    ],
    "name:nds_x_preferred":[
        "San Miguel"
    ],
    "name:nld_x_preferred":[
        "San Miguel"
    ],
    "name:pol_x_preferred":[
        "San Miguel"
    ],
    "name:por_x_preferred":[
        "San Miguel"
    ],
    "name:que_x_preferred":[
        "San Miyil"
    ],
    "name:ron_x_preferred":[
        "San Miguel"
    ],
    "name:rus_x_preferred":[
        "\u0421\u0430\u043d-\u041c\u0438\u0433\u0435\u043b\u044c"
    ],
    "name:sco_x_preferred":[
        "San Miguel"
    ],
    "name:slk_x_preferred":[
        "San Miguel"
    ],
    "name:spa_x_preferred":[
        "San Miguel"
    ],
    "name:srp_x_preferred":[
        "\u0421\u0430\u043d \u041c\u0438\u0433\u0435\u043b"
    ],
    "name:swe_x_preferred":[
        "San Miguel"
    ],
    "name:tgl_x_preferred":[
        "San Miguel"
    ],
    "name:ukr_x_preferred":[
        "\u0421\u0430\u043d-\u041c\u0456\u0433\u0435\u043b\u044c"
    ],
    "name:war_x_preferred":[
        "San Miguel"
    ],
    "qs_pg:aaroncc":"MX",
    "qs_pg:gn_country":"MX",
    "qs_pg:gn_fcode":"PPL",
    "qs_pg:gn_pop":0,
    "qs_pg:name":"San Miguel",
    "qs_pg:name_adm0":"M\u00e9xico",
    "qs_pg:name_adm1":"Chihuahua",
    "qs_pg:photos":1,
    "qs_pg:photos_1k":1,
    "qs_pg:photos_9k":1,
    "qs_pg:photos_9r":1,
    "qs_pg:photos_all":1,
    "qs_pg:photos_sr":1,
    "qs_pg:pop_sr":0,
    "qs_pg:qs_pg_placetype":"neighbourhood",
    "qs_pg:qs_pg_placetype_gp":"Suburb",
    "qs_pg:woe_adm0":23424900,
    "woe:adm0_id":23424900,
    "woe:name_adm0":"M\u00e9xico",
    "woe:name_adm1":"Chihuahua",
    "woe:placetype":"Suburb",
    "wof:name":"San Miguel",
    "wof:placetype":"neighbourhood"
},
  "geometry": {"coordinates":[-106.25,28.25],"type":"Point"}
}