{
  "type": "Feature",
  "properties": {
    "gn:admin1_code":"27",
    "gn:admin2_code":"12.0",
    "gn:asciiname":"Aquiles Serdan (San Fernando)",
    "gn:country_code":"MX",
    "gn:dem":17,
    "gn:feature_class":"P",
    "gn:feature_code":"PPL",
    "gn:name":"Aquiles Serd\u00e1n (San Fernando)",
    "gn:population":4613,
    "gn:timezone":"America/Mexico_City",
    "iso:country":"MX",
    "name:und_x_variant":[
        "Aquiles Serd\u00e1n (San Fernando)"
    ],
    "wof:name":"Aquiles Serdan (San Fernando)",
    "wof:placetype":"locality",
    "wof:population":4613
},
  "geometry": {"coordinates":[-92.48972000000001,17.80556],"type":"Point"}
}