{
  "type": "Feature",
  "properties": {
    "gn:admin1_code":"12",
    "gn:admin2_code":"58",
    "gn:asciiname":"El Arenal",
    "gn:country_code":"MX",
    "gn:dem":1165,
    "gn:feature_class":"P",
    "gn:feature_code":"PPL",
    "gn:name":"El Arenal",
    "gn:population":14,
    "gn:timezone":"America/Mexico_City",
    "iso:country":"MX",
    "wof:name":"El Arenal",
    "wof:placetype":"locality",
    "wof:population":14
},
  "geometry": {"coordinates":[-100.07255000000001,18.29216],"type":"Point"}
}