{
  "type": "Feature",
  "properties": {
    "gn:admin1_code":"6",
    "gn:admin2_code":"7.0",
    "gn:asciiname":"Rancheria Sapareachi",
    "gn:country_code":"MX",
    "gn:dem":2336,
    "gn:feature_class":"P",
    "gn:feature_code":"PPL",
    "gn:name":"Rancher\u00eda Sapareachi",
    "gn:population":0,
    "gn:timezone":"America/Chihuahua",
    "iso:country":"MX",
    "name:spa_x_preferred":[
        "Rancher\u00eda Sapareachi"
    ],
    "name:und_x_variant":[
        "Sapareachi"
    ],
    "wof:name":"Rancheria Sapareachi",
    "wof:placetype":"locality"
},
  "geometry": {"coordinates":[-106.82850000000001,26.65997],"type":"Point"}
}