{
  "type": "Feature",
  "properties": {
    "gn:admin1_code":"2.0",
    "gn:admin2_code":"1.0",
    "gn:asciiname":"El Coyote",
    "gn:country_code":"MX",
    "gn:dem":278,
    "gn:feature_class":"P",
    "gn:feature_code":"PPL",
    "gn:name":"El Coyote",
    "gn:population":1,
    "gn:timezone":"America/Tijuana",
    "iso:country":"MX",
    "name:spa_x_preferred":[
        "El Coyote"
    ],
    "wof:name":"El Coyote",
    "wof:placetype":"locality",
    "wof:population":1
},
  "geometry": {"coordinates":[-116.47556000000002,31.72556],"type":"Point"}
}