{
  "type": "Feature",
  "properties": {
    "gn:admin1_code":"13",
    "gn:admin2_code":"43.0",
    "gn:asciiname":"Puerto Mental",
    "gn:country_code":"MX",
    "gn:dem":2191,
    "gn:feature_class":"P",
    "gn:feature_code":"PPL",
    "gn:name":"Puerto Mental",
    "gn:population":0,
    "gn:timezone":"America/Mexico_City",
    "iso:country":"MX",
    "name:spa_x_preferred":[
        "Puerto Mental"
    ],
    "wof:name":"Puerto Mental",
    "wof:placetype":"locality"
},
  "geometry": {"coordinates":[-99.23381999999999,20.78972000000001],"type":"Point"}
}