{
  "type": "Feature",
  "properties": {
    "gn:admin1_code":"24",
    "gn:admin2_code":"36.0",
    "gn:asciiname":"El Carrizalito",
    "gn:country_code":"MX",
    "gn:dem":1294,
    "gn:feature_class":"P",
    "gn:feature_code":"PPL",
    "gn:name":"El Carrizalito",
    "gn:population":0,
    "gn:timezone":"America/Mexico_City",
    "iso:country":"MX",
    "name:spa_x_preferred":[
        "El Carrizalito"
    ],
    "wof:name":"El Carrizalito",
    "wof:placetype":"locality"
},
  "geometry": {"coordinates":[-99.4584,22.02489],"type":"Point"}
}