{
  "type": "Feature",
  "properties": {
    "gn:admin1_code":"24",
    "gn:admin2_code":"37.0",
    "gn:asciiname":"Xanthoca",
    "gn:country_code":"MX",
    "gn:dem":359,
    "gn:feature_class":"P",
    "gn:feature_code":"PPL",
    "gn:name":"Xanthoca",
    "gn:population":0,
    "gn:timezone":"America/Mexico_City",
    "iso:country":"MX",
    "name:spa_x_preferred":[
        "Xanthoca"
    ],
    "wof:name":"Xanthoca",
    "wof:placetype":"locality"
},
  "geometry": {"coordinates":[-98.85711000000001,21.26187],"type":"Point"}
}