{
  "type": "Feature",
  "properties": {
    "gn:admin1_code":"23",
    "gn:admin2_code":"4.0",
    "gn:asciiname":"Los Pinos",
    "gn:country_code":"MX",
    "gn:dem":44,
    "gn:feature_class":"P",
    "gn:feature_code":"PPL",
    "gn:name":"Los Pinos",
    "gn:population":5,
    "gn:timezone":"America/Cancun",
    "iso:country":"MX",
    "wof:name":"Los Pinos",
    "wof:placetype":"locality",
    "wof:population":5
},
  "geometry": {"coordinates":[-88.64971,18.24998],"type":"Point"}
}