{
  "type": "Feature",
  "properties": {
    "gn:admin1_code":"19",
    "gn:admin2_code":"5.0",
    "gn:asciiname":"Estacion Jarita",
    "gn:country_code":"MX",
    "gn:dem":201,
    "gn:feature_class":"P",
    "gn:feature_code":"PPL",
    "gn:name":"Estaci\u00f3n Jarita",
    "gn:population":0,
    "gn:timezone":"America/Matamoros",
    "iso:country":"MX",
    "name:spa_x_preferred":[
        "Estaci\u00f3n Jarita"
    ],
    "name:und_x_variant":[
        "Jarita",
        "La Jarita"
    ],
    "wof:name":"Estacion Jarita",
    "wof:placetype":"locality"
},
  "geometry": {"coordinates":[-99.80378,27.43231],"type":"Point"}
}