{
  "type": "Feature",
  "properties": {
    "gn:admin1_code":"16",
    "gn:admin2_code":"103",
    "gn:asciiname":"Colonia Pedro Romero Numero Cuatro",
    "gn:country_code":"MX",
    "gn:dem":1527,
    "gn:feature_class":"P",
    "gn:feature_code":"PPL",
    "gn:name":"Colonia Pedro Romero N\u00famero Cuatro",
    "gn:population":52,
    "gn:timezone":"America/Mexico_City",
    "iso:country":"MX",
    "name:und_x_variant":[
        "Colonia Pedro Romero N\u00famero Cuatro"
    ],
    "wof:name":"Colonia Pedro Romero Numero Cuatro",
    "wof:placetype":"locality",
    "wof:population":52
},
  "geometry": {"coordinates":[-102.75333000000001,20.14667],"type":"Point"}
}