{
  "type": "Feature",
  "properties": {
    "gn:admin1_code":"15",
    "gn:admin2_code":"114.0",
    "gn:asciiname":"Barrio de Centro del Cerrillo",
    "gn:country_code":"MX",
    "gn:dem":2842,
    "gn:feature_class":"P",
    "gn:feature_code":"PPL",
    "gn:name":"Barrio de Centro del Cerrillo",
    "gn:population":2203,
    "gn:timezone":"America/Mexico_City",
    "iso:country":"MX",
    "wof:name":"Barrio de Centro del Cerrillo",
    "wof:placetype":"locality",
    "wof:population":2203
},
  "geometry": {"coordinates":[-99.95417,19.53694],"type":"Point"}
}