{
  "type": "Feature",
  "properties": {
    "gn:admin1_code":"11.0",
    "gn:admin2_code":"37.0",
    "gn:asciiname":"Guadalupe de Ramales",
    "gn:country_code":"MX",
    "gn:dem":1769,
    "gn:feature_class":"P",
    "gn:feature_code":"PPL",
    "gn:name":"Guadalupe de Ramales",
    "gn:population":0,
    "gn:timezone":"America/Mexico_City",
    "iso:country":"MX",
    "name:und_x_variant":[
        "El Pescuezo"
    ],
    "wof:name":"Guadalupe de Ramales",
    "wof:placetype":"locality"
},
  "geometry": {"coordinates":[-101.48513,20.92668],"type":"Point"}
}