{
  "type": "Feature",
  "properties": {
    "gn:admin1_code":"31",
    "gn:admin2_code":"76.0",
    "gn:asciiname":"Xpakay",
    "gn:country_code":"MX",
    "gn:dem":20,
    "gn:feature_class":"P",
    "gn:feature_code":"PPL",
    "gn:name":"Xpakay",
    "gn:population":0,
    "gn:timezone":"America/Merida",
    "iso:country":"MX",
    "name:spa_x_preferred":[
        "Xpakay"
    ],
    "name:und_x_variant":[
        "Xpacay"
    ],
    "wof:name":"Xpakay",
    "wof:placetype":"locality"
},
  "geometry": {"coordinates":[-89.41058000000002,20.55693],"type":"Point"}
}