{
  "type": "Feature",
  "properties": {
    "gn:admin1_code":"28.0",
    "gn:admin2_code":"2.0",
    "gn:asciiname":"La Garrapata",
    "gn:country_code":"MX",
    "gn:dem":77,
    "gn:feature_class":"P",
    "gn:feature_code":"PPL",
    "gn:name":"La Garrapata",
    "gn:population":0,
    "gn:timezone":"America/Monterrey",
    "iso:country":"MX",
    "name:spa_x_preferred":[
        "La Garrapata"
    ],
    "wof:name":"La Garrapata",
    "wof:placetype":"locality"
},
  "geometry": {"coordinates":[-98.19318,22.82805],"type":"Point"}
}