{
  "type": "Feature",
  "properties": {
    "gn:admin1_code":"32",
    "gn:admin2_code":"55",
    "gn:asciiname":"Las Varas",
    "gn:country_code":"MX",
    "gn:dem":1827,
    "gn:feature_class":"P",
    "gn:feature_code":"PPL",
    "gn:name":"Las Varas",
    "gn:population":31,
    "gn:timezone":"America/Mexico_City",
    "iso:country":"MX",
    "name:ceb_x_preferred":[
        "Las Varas"
    ],
    "name:srp_x_preferred":[
        "\u041b\u0430\u0441 \u0412\u0430\u0440\u0430\u0441"
    ],
    "name:swe_x_preferred":[
        "Las Varas"
    ],
    "wof:name":"Las Varas",
    "wof:placetype":"locality",
    "wof:population":31
},
  "geometry": {"coordinates":[-102.93083,22.10583],"type":"Point"}
}