{
  "type": "Feature",
  "properties": {
    "gn:admin1_code":"20",
    "gn:admin2_code":"397.0",
    "gn:asciiname":"Ejido Ojo de Agua (El Vergelito)",
    "gn:country_code":"MX",
    "gn:dem":2060,
    "gn:feature_class":"P",
    "gn:feature_code":"PPL",
    "gn:name":"Ejido Ojo de Agua (El Vergelito)",
    "gn:population":160,
    "gn:timezone":"America/Mexico_City",
    "iso:country":"MX",
    "wof:name":"Ejido Ojo de Agua (El Vergelito)",
    "wof:placetype":"locality",
    "wof:population":160
},
  "geometry": {"coordinates":[-97.6825,17.22861],"type":"Point"}
}