{
  "type": "Feature",
  "properties": {
    "gn:admin1_code":"10.0",
    "gn:admin2_code":"28.0",
    "gn:asciiname":"Diez de Octubre",
    "gn:country_code":"MX",
    "gn:dem":1884,
    "gn:feature_class":"P",
    "gn:feature_code":"PPL",
    "gn:name":"Diez de Octubre",
    "gn:population":0,
    "gn:timezone":"America/Monterrey",
    "iso:country":"MX",
    "name:und_x_variant":[
        "San Lucas de Ocampo",
        "Ocampo",
        "San Lucas",
        "Diez de Octubre"
    ],
    "wof:name":"Diez de Octubre",
    "wof:placetype":"locality"
},
  "geometry": {"coordinates":[-104.63625999999999,24.72849],"type":"Point"}
}