{
  "type": "Feature",
  "properties": {
    "gn:admin1_code":"20.0",
    "gn:asciiname":"Las Victorias",
    "gn:country_code":"MX",
    "gn:dem":121,
    "gn:feature_class":"P",
    "gn:feature_code":"PPL",
    "gn:name":"Las Victorias",
    "gn:population":0,
    "gn:timezone":"America/Mexico_City",
    "iso:country":"MX",
    "name:spa_x_preferred":[
        "Las Victorias"
    ],
    "wof:name":"Las Victorias",
    "wof:placetype":"locality"
},
  "geometry": {"coordinates":[-95.91145,17.82718999999999],"type":"Point"}
}