{
  "type": "Feature",
  "properties": {
    "gn:admin1_code":"30",
    "gn:admin2_code":"44.0",
    "gn:asciiname":"Quinta Manzana del Barreal",
    "gn:country_code":"MX",
    "gn:dem":1124,
    "gn:feature_class":"P",
    "gn:feature_code":"PPL",
    "gn:name":"Quinta Manzana del Barreal",
    "gn:population":366,
    "gn:timezone":"America/Mexico_City",
    "iso:country":"MX",
    "wof:name":"Quinta Manzana del Barreal",
    "wof:placetype":"locality",
    "wof:population":366
},
  "geometry": {"coordinates":[-96.98361,18.965],"type":"Point"}
}