{
  "type": "Feature",
  "properties": {
    "gn:admin1_code":"17",
    "gn:asciiname":"San Diego",
    "gn:country_code":"MX",
    "gn:dem":2460,
    "gn:feature_class":"P",
    "gn:feature_code":"PPL",
    "gn:name":"San Diego",
    "gn:population":0,
    "gn:timezone":"America/Mexico_City",
    "iso:country":"MX",
    "name:spa_x_preferred":[
        "San Diego"
    ],
    "wof:name":"San Diego",
    "wof:placetype":"locality"
},
  "geometry": {"coordinates":[-99.65497000000001,19.01117],"type":"Point"}
}