{
  "type": "Feature",
  "properties": {
    "gn:admin1_code":"30",
    "gn:admin2_code":"193.0",
    "gn:asciiname":"Residencial del Bosque",
    "gn:country_code":"MX",
    "gn:dem":34,
    "gn:feature_class":"P",
    "gn:feature_code":"PPL",
    "gn:name":"Residencial del Bosque",
    "gn:population":103,
    "gn:timezone":"America/Mexico_City",
    "iso:country":"MX",
    "wof:name":"Residencial del Bosque",
    "wof:placetype":"locality",
    "wof:population":103
},
  "geometry": {"coordinates":[-96.22694,19.13361],"type":"Point"}
}