{
  "type": "Feature",
  "properties": {
    "gn:admin1_code":"28",
    "gn:admin2_code":"33.0",
    "gn:asciiname":"La Mucura",
    "gn:country_code":"MX",
    "gn:dem":26,
    "gn:feature_class":"P",
    "gn:feature_code":"PPL",
    "gn:name":"La Mucura",
    "gn:population":7,
    "gn:timezone":"America/Monterrey",
    "iso:country":"MX",
    "wof:name":"La Mucura",
    "wof:placetype":"locality",
    "wof:population":7
},
  "geometry": {"coordinates":[-98.00888999999999,25.82083],"type":"Point"}
}