{
  "type": "Feature",
  "properties": {
    "gn:admin1_code":"31",
    "gn:admin2_code":"40.0",
    "gn:asciiname":"Kancabchen",
    "gn:country_code":"MX",
    "gn:dem":11,
    "gn:feature_class":"P",
    "gn:feature_code":"PPL",
    "gn:name":"Kancabch\u00e9n",
    "gn:population":0,
    "gn:timezone":"America/Merida",
    "iso:country":"MX",
    "wof:name":"Kancabchen",
    "wof:placetype":"locality"
},
  "geometry": {"coordinates":[-88.93472,20.9425],"type":"Point"}
}