{
  "type": "Feature",
  "properties": {
    "gn:admin1_code":"2.0",
    "gn:admin2_code":"4.0",
    "gn:asciiname":"Los Granados",
    "gn:country_code":"MX",
    "gn:dem":152,
    "gn:feature_class":"P",
    "gn:feature_code":"PPL",
    "gn:name":"Los Granados",
    "gn:population":0,
    "gn:timezone":"America/Tijuana",
    "iso:country":"MX",
    "name:spa_x_preferred":[
        "Los Granados"
    ],
    "wof:name":"Los Granados",
    "wof:placetype":"locality"
},
  "geometry": {"coordinates":[-117.06220999999999,32.47109],"type":"Point"}
}