{
  "type": "Feature",
  "properties": {
    "gn:admin1_code":"10",
    "gn:admin2_code":"26.0",
    "gn:asciiname":"Calerita",
    "gn:country_code":"MX",
    "gn:dem":1956,
    "gn:feature_class":"P",
    "gn:feature_code":"PPL",
    "gn:name":"Calerita",
    "gn:population":59,
    "gn:timezone":"America/Monterrey",
    "iso:country":"MX",
    "wof:name":"Calerita",
    "wof:placetype":"locality",
    "wof:population":59
},
  "geometry": {"coordinates":[-106.14700000000001,24.47749],"type":"Point"}
}