{
  "type": "Feature",
  "properties": {
    "gn:gn_country":"MX",
    "gn:gn_fcode":"PPL",
    "gn:gn_pop":0,
    "iso:country":"MX",
    "name:ceb_x_preferred":[
        "El Prado"
    ],
    "name:spa_x_preferred":[
        "El Dorado"
    ],
    "name:spa_x_variant":[
        "El Prado"
    ],
    "name:srp_x_preferred":[
        "\u0415\u043b \u041f\u0440\u0430\u0434\u043e"
    ],
    "name:swe_x_preferred":[
        "El Prado"
    ],
    "qs_pg:aaroncc":"MX",
    "qs_pg:gn_country":"MX",
    "qs_pg:gn_fcode":"PPL",
    "qs_pg:gn_pop":0,
    "qs_pg:name":"El Prado",
    "qs_pg:name_adm0":"M\u00e9xico",
    "qs_pg:name_adm1":"Distrito Federal",
    "qs_pg:photos":129,
    "qs_pg:photos_1k":26,
    "qs_pg:photos_9k":1,
    "qs_pg:photos_9r":3,
    "qs_pg:photos_all":129,
    "qs_pg:photos_sr":3,
    "qs_pg:pop_sr":0,
    "qs_pg:qs_pg_placetype":"neighbourhood",
    "qs_pg:qs_pg_placetype_gp":"Suburb",
    "qs_pg:woe_adm0":23424900,
    "woe:adm0_id":23424900,
    "woe:name_adm0":"M\u00e9xico",
    "woe:name_adm1":"Distrito Federal",
    "woe:placetype":"Suburb",
    "wof:name":"El Prado",
    "wof:placetype":"neighbourhood"
},
  "geometry": {"coordinates":[-98.92784,19.90191],"type":"Point"}
}