{
  "type": "Feature",
  "properties": {
    "gn:admin1_code":"21",
    "gn:admin2_code":"172",
    "gn:asciiname":"Tamacelicia",
    "gn:country_code":"MX",
    "gn:dem":2577,
    "gn:feature_class":"P",
    "gn:feature_code":"PPL",
    "gn:name":"Tamacelicia",
    "gn:population":31,
    "gn:timezone":"America/Mexico_City",
    "iso:country":"MX",
    "wof:name":"Tamacelicia",
    "wof:placetype":"locality",
    "wof:population":31
},
  "geometry": {"coordinates":[-97.71707000000001,19.8115],"type":"Point"}
}