{
  "type": "Feature",
  "properties": {
    "gn:admin1_code":"14",
    "gn:admin2_code":"17",
    "gn:asciiname":"La Mesa de los Nuno",
    "gn:country_code":"MX",
    "gn:dem":1449,
    "gn:feature_class":"P",
    "gn:feature_code":"PPL",
    "gn:name":"La Mesa de los Nu\u00f1o",
    "gn:population":44,
    "gn:timezone":"America/Mexico_City",
    "iso:country":"MX",
    "name:und_x_variant":[
        "La Mesa de los Nu\u00f1o"
    ],
    "wof:name":"La Mesa de los Nuno",
    "wof:placetype":"locality",
    "wof:population":44
},
  "geometry": {"coordinates":[-104.31,20.17583],"type":"Point"}
}