{
  "type": "Feature",
  "properties": {
    "gn:admin1_code":"10",
    "gn:admin2_code":"12.0",
    "gn:asciiname":"Pequena Propiedad el Alamo",
    "gn:country_code":"MX",
    "gn:dem":1164,
    "gn:feature_class":"P",
    "gn:feature_code":"PPL",
    "gn:name":"Peque\u00f1a Propiedad el \u00c1lamo",
    "gn:population":7,
    "gn:timezone":"America/Monterrey",
    "iso:country":"MX",
    "name:und_x_variant":[
        "Peque\u00f1a Propiedad el \u00c1lamo"
    ],
    "wof:name":"Pequena Propiedad el Alamo",
    "wof:placetype":"locality",
    "wof:population":7
},
  "geometry": {"coordinates":[-103.69812,25.44985],"type":"Point"}
}