{
  "type": "Feature",
  "properties": {
    "gn:admin1_code":"5",
    "gn:admin2_code":"30.0",
    "gn:asciiname":"Dolores Hidalgo",
    "gn:country_code":"MX",
    "gn:dem":664,
    "gn:feature_class":"P",
    "gn:feature_code":"PPL",
    "gn:name":"Dolores Hidalgo",
    "gn:population":170,
    "gn:timezone":"America/Mexico_City",
    "iso:country":"MX",
    "name:ara_x_preferred":[
        "\u062f\u0648\u0644\u0648\u0631\u064a\u0633 \u0625\u064a\u062f\u0627\u0644\u063a\u0648"
    ],
    "name:epo_x_preferred":[
        "Dolores Hidalgo"
    ],
    "name:fas_x_preferred":[
        "\u062f\u0648\u0644\u0648\u0631\u0633 \u0647\u06cc\u062f\u0627\u0644\u06af\u0648"
    ],
    "name:fra_x_preferred":[
        "Dolores Hidalgo"
    ],
    "name:ita_x_preferred":[
        "Dolores Hidalgo"
    ],
    "name:jpn_x_preferred":[
        "\u30c9\u30ed\u30fc\u30ec\u30b9\u30fb\u30a4\u30c0\u30eb\u30b4"
    ],
    "name:kor_x_preferred":[
        "\ub3cc\ub85c\ub808\uc2a4\uc774\ub2ec\uace0"
    ],
    "name:lad_x_preferred":[
        "Dolores Hidalgo"
    ],
    "name:nah_x_preferred":[
        "Dolores Hidalgo"
    ],
    "name:nor_x_preferred":[
        "Dolores Hidalgo"
    ],
    "name:por_x_preferred":[
        "Dolores Hidalgo"
    ],
    "name:ron_x_preferred":[
        "Dolores Hidalgo"
    ],
    "name:rus_x_preferred":[
        "\u0414\u043e\u043b\u043e\u0440\u0435\u0441-\u0418\u0434\u0430\u043b\u044c\u0433\u043e"
    ],
    "name:sco_x_preferred":[
        "Dolores Hidalgo"
    ],
    "name:spa_x_preferred":[
        "Dolores Hidalgo"
    ],
    "name:swe_x_preferred":[
        "Dolores Hidalgo"
    ],
    "name:vie_x_preferred":[
        "Dolores Hidalgo"
    ],
    "name:zho_x_preferred":[
        "\u591a\u6d1b\u96f7\u65af-\u4f0a\u8fbe\u5c14\u6208"
    ],
    "wof:name":"Dolores Hidalgo",
    "wof:placetype":"locality",
    "wof:population":170
},
  "geometry": {"coordinates":[-92.34166999999999,15.86472],"type":"Point"}
}