{
  "type": "Feature",
  "properties": {
    "gn:admin1_code":"21",
    "gn:admin2_code":"142.0",
    "gn:asciiname":"Aljibes",
    "gn:country_code":"MX",
    "gn:dem":2436,
    "gn:feature_class":"P",
    "gn:feature_code":"PPL",
    "gn:name":"Aljibes",
    "gn:population":0,
    "gn:timezone":"America/Mexico_City",
    "iso:country":"MX",
    "name:spa_x_preferred":[
        "Aljibes"
    ],
    "wof:name":"Aljibes",
    "wof:placetype":"locality"
},
  "geometry": {"coordinates":[-97.64251,19.08454],"type":"Point"}
}