{
  "type": "Feature",
  "properties": {
    "gn:admin1_code":"14",
    "gn:admin2_code":"118",
    "gn:asciiname":"El Faro",
    "gn:country_code":"MX",
    "gn:dem":1781,
    "gn:feature_class":"P",
    "gn:feature_code":"PPL",
    "gn:name":"El Faro",
    "gn:population":39,
    "gn:timezone":"America/Mexico_City",
    "iso:country":"MX",
    "name:ceb_x_preferred":[
        "El Faro"
    ],
    "name:srp_x_preferred":[
        "\u0415\u043b \u0424\u0430\u0440\u043e"
    ],
    "name:swe_x_preferred":[
        "El Faro"
    ],
    "wof:name":"El Faro",
    "wof:placetype":"locality",
    "wof:population":39
},
  "geometry": {"coordinates":[-102.88194,21.16444],"type":"Point"}
}