{
  "type": "Feature",
  "properties": {
    "gn:admin1_code":"6",
    "gn:admin2_code":"65.0",
    "gn:asciiname":"Rimigomachi",
    "gn:country_code":"MX",
    "gn:dem":2227,
    "gn:feature_class":"P",
    "gn:feature_code":"PPL",
    "gn:name":"Rimigomachi",
    "gn:population":5,
    "gn:timezone":"America/Chihuahua",
    "iso:country":"MX",
    "wof:name":"Rimigomachi",
    "wof:placetype":"locality",
    "wof:population":5
},
  "geometry": {"coordinates":[-107.84353,27.46464000000001],"type":"Point"}
}