{
  "type": "Feature",
  "properties": {
    "gn:admin1_code":"14.0",
    "gn:admin2_code":"68.0",
    "gn:asciiname":"El Fresno",
    "gn:country_code":"MX",
    "gn:dem":919,
    "gn:feature_class":"P",
    "gn:feature_code":"PPL",
    "gn:name":"El Fresno",
    "gn:population":0,
    "gn:timezone":"America/Mexico_City",
    "iso:country":"MX",
    "name:spa_x_preferred":[
        "El Fresno"
    ],
    "name:spa_x_variant":[
        "Los Fresnos"
    ],
    "wof:name":"El Fresno",
    "wof:placetype":"locality"
},
  "geometry": {"coordinates":[-104.50127000000001,19.80927],"type":"Point"}
}