{
  "type": "Feature",
  "properties": {
    "gn:admin1_code":"10",
    "gn:admin2_code":"23.0",
    "gn:asciiname":"Adolfo Ruiz Cortines",
    "gn:country_code":"MX",
    "gn:dem":2460,
    "gn:feature_class":"P",
    "gn:feature_code":"PPL",
    "gn:name":"Adolfo Ru\u00edz Cort\u00ednes",
    "gn:population":0,
    "gn:timezone":"America/Monterrey",
    "iso:country":"MX",
    "name:ara_x_preferred":[
        "\u0623\u062f\u0648\u0644\u0641\u0648 \u0631\u0648\u064a\u0632 \u0643\u0648\u0631\u062a\u064a\u0646\u064a\u0633"
    ],
    "name:ast_x_preferred":[
        "Adolfo Ruiz Cortines"
    ],
    "name:cat_x_preferred":[
        "Adolfo Ruiz Cortines"
    ],
    "name:deu_x_preferred":[
        "Adolfo Ruiz Cortines"
    ],
    "name:fas_x_preferred":[
        "\u0622\u062f\u0648\u0644\u0641\u0648 \u0631\u0648\u06cc\u0632 \u06a9\u0648\u0631\u062a\u06cc\u0646"
    ],
    "name:fra_x_preferred":[
        "Adolfo Ruiz Cortines"
    ],
    "name:heb_x_preferred":[
        "\u05d0\u05d3\u05d5\u05dc\u05e4\u05d5 \u05e8\u05d5\u05d0\u05d9\u05e1 \u05e7\u05d5\u05e8\u05d8\u05d9\u05e0\u05e1"
    ],
    "name:ido_x_preferred":[
        "Adolfo Ruiz Cortines"
    ],
    "name:ita_x_preferred":[
        "Adolfo Ruiz Cortines"
    ],
    "name:kat_x_preferred":[
        "\u10d0\u10d3\u10dd\u10da\u10e4\u10dd \u10e0\u10e3\u10d8\u10e1 \u10d9\u10dd\u10e0\u10e2\u10d8\u10dc\u10d4\u10e1\u10d8"
    ],
    "name:kor_x_preferred":[
        "\uc544\ub3cc\ud3ec \ub8e8\uc774\uc2a4 \ucf54\ub974\ud2f0\ub124\uc2a4"
    ],
    "name:lat_x_preferred":[
        "Adolphus Ruiz Cortines"
    ],
    "name:nld_x_preferred":[
        "Adolfo Ruiz Cortines"
    ],
    "name:nor_x_preferred":[
        "Adolfo Ruiz Cortines"
    ],
    "name:oci_x_preferred":[
        "Adolfo Ruiz Cortines"
    ],
    "name:pol_x_preferred":[
        "Adolfo Ruiz Cortines"
    ],
    "name:por_x_preferred":[
        "Adolfo Ruiz Cortines"
    ],
    "name:que_x_preferred":[
        "Adolfo Ruiz"
    ],
    "name:rus_x_preferred":[
        "\u0420\u0443\u0438\u0441 \u041a\u043e\u0440\u0442\u0438\u043d\u0435\u0441"
    ],
    "name:spa_x_preferred":[
        "Adolfo Ru\u00edz Cort\u00ednes"
    ],
    "name:spa_x_variant":[
        "Marraneras",
        "Adolfo Ruiz Cortines"
    ],
    "name:swe_x_preferred":[
        "Adolfo Ruiz Cortines"
    ],
    "name:und_x_variant":[
        "La Marranera"
    ],
    "name:vie_x_preferred":[
        "Adolfo Ruiz Cortines"
    ],
    "name:yor_x_preferred":[
        "Adolfo Ruiz Cortines"
    ],
    "name:zho_x_preferred":[
        "\u963f\u9053\u5f17\u00b7\u9c81\u4f0a\u65af\u00b7\u79d1\u5c14\u8482\u5185\u65af"
    ],
    "wof:name":"Adolfo Ruiz Cortines",
    "wof:placetype":"locality"
},
  "geometry": {"coordinates":[-105.29823,23.73568],"type":"Point"}
}