{
  "type": "Feature",
  "properties": {
    "gn:admin1_code":"10",
    "gn:admin2_code":"23.0",
    "gn:asciiname":"Adolfo Ruiz Cortines",
    "gn:country_code":"MX",
    "gn:dem":2460,
    "gn:feature_class":"P",
    "gn:feature_code":"PPL",
    "gn:name":"Adolfo Ru\u00edz Cort\u00ednes",
    "gn:population":0,
    "gn:timezone":"America/Monterrey",
    "iso:country":"MX",
    "name:spa_x_preferred":[
        "Adolfo Ru\u00edz Cort\u00ednes"
    ],
    "name:spa_x_variant":[
        "Marraneras"
    ],
    "name:und_x_variant":[
        "La Marranera"
    ],
    "wof:name":"Adolfo Ruiz Cortines",
    "wof:placetype":"locality"
},
  "geometry": {"coordinates":[-105.29823,23.73568],"type":"Point"}
}