{
  "type": "Feature",
  "properties": {
    "gn:admin1_code":"16",
    "gn:admin2_code":"72.0",
    "gn:asciiname":"Otzumatlan",
    "gn:country_code":"MX",
    "gn:dem":2084,
    "gn:feature_class":"P",
    "gn:feature_code":"PPL",
    "gn:name":"Otzumatl\u00e1n",
    "gn:population":0,
    "gn:timezone":"America/Mexico_City",
    "iso:country":"MX",
    "name:und_x_variant":[
        "Ozumatlan",
        "Otzumatl\u00e1n"
    ],
    "wof:name":"Otzumatlan",
    "wof:placetype":"locality"
},
  "geometry": {"coordinates":[-100.86449,19.77597],"type":"Point"}
}