{
  "type": "Feature",
  "properties": {
    "gn:admin1_code":"24",
    "gn:admin2_code":"3.0",
    "gn:asciiname":"Barrio el Progreso",
    "gn:country_code":"MX",
    "gn:dem":674,
    "gn:feature_class":"P",
    "gn:feature_code":"PPL",
    "gn:name":"Barrio el Progreso",
    "gn:population":182,
    "gn:timezone":"America/Mexico_City",
    "iso:country":"MX",
    "wof:name":"Barrio el Progreso",
    "wof:placetype":"locality",
    "wof:population":182
},
  "geometry": {"coordinates":[-99.08667,21.63306],"type":"Point"}
}