{
  "type": "Feature",
  "properties": {
    "gn:admin1_code":"6.0",
    "gn:admin2_code":"65.0",
    "gn:asciiname":"Vitorachi",
    "gn:country_code":"MX",
    "gn:dem":2270,
    "gn:feature_class":"P",
    "gn:feature_code":"PPL",
    "gn:name":"Vitorachi",
    "gn:population":0,
    "gn:timezone":"America/Chihuahua",
    "iso:country":"MX",
    "name:spa_x_preferred":[
        "Vitorachi"
    ],
    "wof:name":"Vitorachi",
    "wof:placetype":"locality"
},
  "geometry": {"coordinates":[-107.67255,27.27095],"type":"Point"}
}