{
  "type": "Feature",
  "properties": {
    "gn:admin1_code":"7",
    "gn:admin2_code":"23.0",
    "gn:asciiname":"La Vinata",
    "gn:country_code":"MX",
    "gn:dem":1113,
    "gn:feature_class":"P",
    "gn:feature_code":"PPL",
    "gn:name":"La Vinata",
    "gn:population":0,
    "gn:timezone":"America/Monterrey",
    "iso:country":"MX",
    "name:spa_x_preferred":[
        "La Vinata"
    ],
    "name:und_x_variant":[
        "Las Esperanzas",
        "La Esperanza"
    ],
    "wof:name":"La Vinata",
    "wof:placetype":"locality"
},
  "geometry": {"coordinates":[-103.15443999999999,28.47915],"type":"Point"}
}