{
  "type": "Feature",
  "properties": {
    "gn:admin1_code":"32",
    "gn:admin2_code":"26.0",
    "gn:asciiname":"Leocadio Guerrero Uno (Cuba)",
    "gn:country_code":"MX",
    "gn:dem":1639,
    "gn:feature_class":"P",
    "gn:feature_code":"PPL",
    "gn:name":"Leocadio Guerrero Uno (Cuba)",
    "gn:population":14,
    "gn:timezone":"America/Mexico_City",
    "iso:country":"MX",
    "wof:name":"Leocadio Guerrero Uno (Cuba)",
    "wof:placetype":"locality",
    "wof:population":14
},
  "geometry": {"coordinates":[-102.2299,24.34888],"type":"Point"}
}