{
  "type": "Feature",
  "properties": {
    "gn:admin1_code":"26",
    "gn:admin2_code":"3.0",
    "gn:asciiname":"Rio Viejo",
    "gn:cc2":"MX",
    "gn:country_code":"MX",
    "gn:dem":177,
    "gn:feature_class":"P",
    "gn:feature_code":"PPL",
    "gn:name":"R\u00edo Viejo",
    "gn:population":0,
    "gn:timezone":"America/Hermosillo",
    "iso:country":"MX",
    "name:und_x_variant":[
        "Rancho Viejo",
        "R\u00edo Viejo"
    ],
    "wof:name":"Rio Viejo",
    "wof:placetype":"locality"
},
  "geometry": {"coordinates":[-109.13333,27.13333],"type":"Point"}
}