{
  "type": "Feature",
  "properties": {
    "gn:admin1_code":"12",
    "gn:admin2_code":"12.0",
    "gn:asciiname":"Coapinola",
    "gn:country_code":"MX",
    "gn:dem":949,
    "gn:feature_class":"P",
    "gn:feature_code":"PPL",
    "gn:name":"Coapinola",
    "gn:population":382,
    "gn:timezone":"America/Mexico_City",
    "iso:country":"MX",
    "wof:name":"Coapinola",
    "wof:placetype":"locality",
    "wof:population":382
},
  "geometry": {"coordinates":[-99.00806,16.94582999999999],"type":"Point"}
}