{
  "type": "Feature",
  "properties": {
    "gn:admin1_code":"31",
    "gn:admin2_code":"57.0",
    "gn:asciiname":"Santa Raque",
    "gn:country_code":"MX",
    "gn:dem":8,
    "gn:feature_class":"P",
    "gn:feature_code":"PPL",
    "gn:name":"Santa Raque",
    "gn:population":0,
    "gn:timezone":"America/Merida",
    "iso:country":"MX",
    "name:spa_x_preferred":[
        "Santa Raque"
    ],
    "wof:name":"Santa Raque",
    "wof:placetype":"locality"
},
  "geometry": {"coordinates":[-88.37966999999998,21.31997],"type":"Point"}
}