{
  "type": "Feature",
  "properties": {
    "gn:admin1_code":"20",
    "gn:admin2_code":"207.0",
    "gn:asciiname":"Santiago Zacatepec",
    "gn:country_code":"MX",
    "gn:dem":377,
    "gn:feature_class":"P",
    "gn:feature_code":"PPL",
    "gn:name":"Santiago Zacatepec",
    "gn:population":0,
    "gn:timezone":"America/Mexico_City",
    "iso:country":"MX",
    "name:ceb_x_preferred":[
        "Santiago Zacatepec"
    ],
    "name:epo_x_preferred":[
        "Santiago Zacatepec"
    ],
    "name:eus_x_preferred":[
        "Santiago Zacatepec"
    ],
    "name:ita_x_preferred":[
        "Santiago Zacatepec"
    ],
    "name:rus_x_preferred":[
        "\u0421\u0430\u043d\u0442\u044c\u044f\u0433\u043e-\u0421\u0430\u043a\u0430\u0442\u0435\u043f\u0435\u043a"
    ],
    "name:sco_x_preferred":[
        "Santiago Zacatepec"
    ],
    "name:spa_x_preferred":[
        "Santiago Zacatepec"
    ],
    "name:srp_x_preferred":[
        "\u041e\u043f\u0448\u0442\u0438\u043d\u0430 \u0421\u0430\u043d\u0442\u0438\u0458\u0430\u0433\u043e \u0417\u0430\u043a\u0430\u0442\u0435\u043f\u0435\u043a"
    ],
    "name:swe_x_preferred":[
        "Santiago Zacatepec"
    ],
    "name:vie_x_preferred":[
        "Santiago Zacatepec"
    ],
    "wof:name":"Santiago Zacatepec",
    "wof:placetype":"locality"
},
  "geometry": {"coordinates":[-95.41444,17.1675],"type":"Point"}
}