{
  "type": "Feature",
  "properties": {
    "gn:admin1_code":"20",
    "gn:admin2_code":"207.0",
    "gn:asciiname":"Santiago Zacatepec",
    "gn:country_code":"MX",
    "gn:dem":377,
    "gn:feature_class":"P",
    "gn:feature_code":"PPL",
    "gn:name":"Santiago Zacatepec",
    "gn:population":0,
    "gn:timezone":"America/Mexico_City",
    "iso:country":"MX",
    "name:spa_x_preferred":[
        "Santiago Zacatepec"
    ],
    "wof:name":"Santiago Zacatepec",
    "wof:placetype":"locality"
},
  "geometry": {"coordinates":[-95.41444,17.1675],"type":"Point"}
}