{
  "type": "Feature",
  "properties": {
    "gn:admin1_code":"14",
    "gn:admin2_code":"113",
    "gn:asciiname":"Puerto de la Estacada",
    "gn:country_code":"MX",
    "gn:dem":2384,
    "gn:feature_class":"P",
    "gn:feature_code":"PPL",
    "gn:name":"Puerto de la Estacada",
    "gn:population":18,
    "gn:timezone":"America/Mexico_City",
    "iso:country":"MX",
    "wof:name":"Puerto de la Estacada",
    "wof:placetype":"locality",
    "wof:population":18
},
  "geometry": {"coordinates":[-103.61778,19.65583],"type":"Point"}
}