{
  "type": "Feature",
  "properties": {
    "gn:admin1_code":"3",
    "gn:admin2_code":"3.0",
    "gn:asciiname":"San Clemente",
    "gn:country_code":"MX",
    "gn:dem":106,
    "gn:feature_class":"P",
    "gn:feature_code":"PPL",
    "gn:name":"San Clemente",
    "gn:population":6,
    "gn:timezone":"America/Mazatlan",
    "iso:country":"MX",
    "wof:name":"San Clemente",
    "wof:placetype":"locality",
    "wof:population":6
},
  "geometry": {"coordinates":[-111.01511000000001,24.47678],"type":"Point"}
}