{
  "type": "Feature",
  "properties": {
    "gn:admin1_code":"1.0",
    "gn:admin2_code":"2.0",
    "gn:asciiname":"La Minerva",
    "gn:country_code":"MX",
    "gn:dem":2274,
    "gn:feature_class":"P",
    "gn:feature_code":"PPL",
    "gn:name":"La Minerva",
    "gn:population":0,
    "gn:timezone":"America/Mexico_City",
    "iso:country":"MX",
    "name:spa_x_preferred":[
        "La Minerva"
    ],
    "wof:name":"La Minerva",
    "wof:placetype":"locality"
},
  "geometry": {"coordinates":[-102.11304,22.2354],"type":"Point"}
}