{
  "type": "Feature",
  "properties": {
    "gn:admin1_code":"13",
    "gn:admin2_code":"39.0",
    "gn:asciiname":"Santa Rosalia",
    "gn:country_code":"MX",
    "gn:dem":2897,
    "gn:feature_class":"P",
    "gn:feature_code":"PPL",
    "gn:name":"Santa Rosal\u00eda",
    "gn:population":0,
    "gn:timezone":"America/Mexico_City",
    "iso:country":"MX",
    "name:spa_x_preferred":[
        "Santa Rosal\u00eda"
    ],
    "wof:name":"Santa Rosalia",
    "wof:placetype":"locality"
},
  "geometry": {"coordinates":[-98.63569,20.1203],"type":"Point"}
}