{
  "type": "Feature",
  "properties": {
    "gn:admin1_code":"15",
    "gn:admin2_code":"39.0",
    "gn:asciiname":"Ampliacion 6 de Junio",
    "gn:country_code":"MX",
    "gn:dem":2480,
    "gn:feature_class":"P",
    "gn:feature_code":"PPL",
    "gn:name":"Ampliaci\u00f3n 6 de Junio",
    "gn:population":738,
    "gn:timezone":"America/Mexico_City",
    "iso:country":"MX",
    "name:und_x_variant":[
        "Ampliaci\u00f3n 6 de Junio"
    ],
    "wof:name":"Ampliacion 6 de Junio",
    "wof:placetype":"locality",
    "wof:population":738
},
  "geometry": {"coordinates":[-98.92610999999999,19.33694],"type":"Point"}
}