{
  "type": "Feature",
  "properties": {
    "gn:admin1_code":"12",
    "gn:admin2_code":"19.0",
    "gn:asciiname":"Papalutla",
    "gn:country_code":"MX",
    "gn:dem":648,
    "gn:feature_class":"P",
    "gn:feature_code":"PPL",
    "gn:name":"Papalutla",
    "gn:population":0,
    "gn:timezone":"America/Mexico_City",
    "iso:country":"MX",
    "name:spa_x_preferred":[
        "Papalutla"
    ],
    "wof:name":"Papalutla",
    "wof:placetype":"locality"
},
  "geometry": {"coordinates":[-98.90434999999999,18.0217],"type":"Point"}
}