{
  "type": "Feature",
  "properties": {
    "gn:admin1_code":"12.0",
    "gn:admin2_code":"47.0",
    "gn:asciiname":"Tulatengo",
    "gn:country_code":"MX",
    "gn:dem":825,
    "gn:feature_class":"P",
    "gn:feature_code":"PPL",
    "gn:name":"Tulatengo",
    "gn:population":0,
    "gn:timezone":"America/Mexico_City",
    "iso:country":"MX",
    "name:spa_x_preferred":[
        "Tulatengo"
    ],
    "wof:name":"Tulatengo",
    "wof:placetype":"locality"
},
  "geometry": {"coordinates":[-99.94969,18.54457],"type":"Point"}
}