{
  "type": "Feature",
  "properties": {
    "gn:admin1_code":"6",
    "gn:admin2_code":"9.0",
    "gn:asciiname":"Rejuybo",
    "gn:country_code":"MX",
    "gn:dem":2227,
    "gn:feature_class":"P",
    "gn:feature_code":"PPL",
    "gn:name":"Rejuybo",
    "gn:population":8,
    "gn:timezone":"America/Chihuahua",
    "iso:country":"MX",
    "wof:name":"Rejuybo",
    "wof:placetype":"locality",
    "wof:population":8
},
  "geometry": {"coordinates":[-107.78937000000001,27.67686],"type":"Point"}
}