{
  "type": "Feature",
  "properties": {
    "gn:admin1_code":"16.0",
    "gn:admin2_code":"15.0",
    "gn:asciiname":"Casas Viejas",
    "gn:country_code":"MX",
    "gn:dem":1585,
    "gn:feature_class":"P",
    "gn:feature_code":"PPL",
    "gn:name":"Casas Viejas",
    "gn:population":0,
    "gn:timezone":"America/Mexico_City",
    "iso:country":"MX",
    "name:spa_x_preferred":[
        "Casas Viejas"
    ],
    "wof:name":"Casas Viejas",
    "wof:placetype":"locality"
},
  "geometry": {"coordinates":[-102.97915,18.62963],"type":"Point"}
}