{
  "type": "Feature",
  "properties": {
    "gn:admin1_code":"14",
    "gn:admin2_code":"43.0",
    "gn:asciiname":"San Borja",
    "gn:country_code":"MX",
    "gn:dem":257,
    "gn:feature_class":"P",
    "gn:feature_code":"PPL",
    "gn:name":"San Borja",
    "gn:population":0,
    "gn:timezone":"America/Mexico_City",
    "iso:country":"MX",
    "name:ceb_x_preferred":[
        "San Borja"
    ],
    "name:deu_x_preferred":[
        "San Borja"
    ],
    "name:ita_x_preferred":[
        "San Borja"
    ],
    "name:nld_x_preferred":[
        "San Borja"
    ],
    "name:por_x_preferred":[
        "San Borja"
    ],
    "name:sco_x_preferred":[
        "San Borja"
    ],
    "name:spa_x_preferred":[
        "San Borja"
    ],
    "name:swe_x_preferred":[
        "San Borja"
    ],
    "wof:name":"San Borja",
    "wof:placetype":"locality"
},
  "geometry": {"coordinates":[-104.96525,19.59273],"type":"Point"}
}