{
  "type": "Feature",
  "properties": {
    "gn:admin1_code":"14",
    "gn:admin2_code":"43.0",
    "gn:asciiname":"San Borja",
    "gn:country_code":"MX",
    "gn:dem":257,
    "gn:feature_class":"P",
    "gn:feature_code":"PPL",
    "gn:name":"San Borja",
    "gn:population":0,
    "gn:timezone":"America/Mexico_City",
    "iso:country":"MX",
    "name:ben_x_preferred":[
        "\u09b8\u09be\u09a8 \u09ac\u09cb\u09b0\u099c\u09be"
    ],
    "name:ceb_x_preferred":[
        "San Borja"
    ],
    "name:deu_x_preferred":[
        "San Borja"
    ],
    "name:ell_x_preferred":[
        "\u03a3\u03b1\u03bd \u039c\u03c0\u03cc\u03c1\u03c7\u03b1"
    ],
    "name:heb_x_preferred":[
        "\u05e1\u05df \u05d1\u05d5\u05e8\u05d7\u05d4"
    ],
    "name:hin_x_preferred":[
        "\u0938\u0948\u0928 \u092c\u094b\u0930\u094d\u091c\u093e"
    ],
    "name:hun_x_preferred":[
        "San Borja"
    ],
    "name:ind_x_preferred":[
        "San Borja"
    ],
    "name:ita_x_preferred":[
        "San Borja"
    ],
    "name:kor_x_preferred":[
        "\uc0b0 \ubcf4\ub974\uc790"
    ],
    "name:nld_x_preferred":[
        "San Borja"
    ],
    "name:por_x_preferred":[
        "San Borja"
    ],
    "name:rus_x_preferred":[
        "\u0421\u0430\u043d-\u0411\u043e\u0440\u0445\u0430"
    ],
    "name:sco_x_preferred":[
        "San Borja"
    ],
    "name:spa_x_preferred":[
        "San Borja"
    ],
    "name:swe_x_preferred":[
        "San Borja"
    ],
    "name:tur_x_preferred":[
        "San Borja"
    ],
    "name:urd_x_preferred":[
        "\u0633\u0627\u0646 \u0628\u0648\u0631\u062c\u0627"
    ],
    "name:vie_x_preferred":[
        "San Borja"
    ],
    "wof:name":"San Borja",
    "wof:placetype":"locality"
},
  "geometry": {"coordinates":[-104.96525,19.59273],"type":"Point"}
}