{
  "type": "Feature",
  "properties": {
    "gn:admin1_code":"30",
    "gn:admin2_code":"105",
    "gn:asciiname":"Salazar (El Bosque)",
    "gn:country_code":"MX",
    "gn:dem":23,
    "gn:feature_class":"P",
    "gn:feature_code":"PPL",
    "gn:name":"Salazar (El Bosque)",
    "gn:population":37,
    "gn:timezone":"America/Mexico_City",
    "iso:country":"MX",
    "wof:name":"Salazar (El Bosque)",
    "wof:placetype":"locality",
    "wof:population":37
},
  "geometry": {"coordinates":[-96.09999999999999,18.99361],"type":"Point"}
}