{
  "type": "Feature",
  "properties": {
    "gn:admin1_code":"7.0",
    "gn:admin2_code":"23.0",
    "gn:asciiname":"Agua Verde",
    "gn:country_code":"MX",
    "gn:dem":1013,
    "gn:feature_class":"P",
    "gn:feature_code":"PPL",
    "gn:name":"Agua Verde",
    "gn:population":0,
    "gn:timezone":"America/Monterrey",
    "iso:country":"MX",
    "name:und_x_variant":[
        "Rancho San Jos\u00e9 de Agua Verde",
        "Agua Verde"
    ],
    "wof:name":"Agua Verde",
    "wof:placetype":"locality"
},
  "geometry": {"coordinates":[-102.23168,27.31691],"type":"Point"}
}