{
  "type": "Feature",
  "properties": {
    "gn:admin1_code":"6",
    "gn:admin2_code":"12",
    "gn:asciiname":"Ahuecherare",
    "gn:country_code":"MX",
    "gn:dem":2095,
    "gn:feature_class":"P",
    "gn:feature_code":"PPL",
    "gn:name":"Ahuecherare",
    "gn:population":23,
    "gn:timezone":"America/Chihuahua",
    "iso:country":"MX",
    "wof:name":"Ahuecherare",
    "wof:placetype":"locality",
    "wof:population":23
},
  "geometry": {"coordinates":[-107.04835,27.7349],"type":"Point"}
}