{
  "type": "Feature",
  "properties": {
    "gn:admin1_code":"2",
    "gn:admin2_code":"4",
    "gn:asciiname":"Santa Monica",
    "gn:country_code":"MX",
    "gn:dem":234,
    "gn:feature_class":"P",
    "gn:feature_code":"PPL",
    "gn:name":"Santa M\u00f3nica",
    "gn:population":15,
    "gn:timezone":"America/Tijuana",
    "iso:country":"MX",
    "name:und_x_variant":[
        "Santa M\u00f3nica"
    ],
    "wof:name":"Santa Monica",
    "wof:placetype":"locality",
    "wof:population":15
},
  "geometry": {"coordinates":[-116.94806,32.415],"type":"Point"}
}