{
  "type": "Feature",
  "properties": {
    "gn:admin1_code":"16",
    "gn:admin2_code":"8",
    "gn:asciiname":"Crucero del Faro",
    "gn:country_code":"MX",
    "gn:dem":39,
    "gn:feature_class":"P",
    "gn:feature_code":"PPL",
    "gn:name":"Crucero del Faro",
    "gn:population":12,
    "gn:timezone":"America/Mexico_City",
    "iso:country":"MX",
    "wof:name":"Crucero del Faro",
    "wof:placetype":"locality",
    "wof:population":12
},
  "geometry": {"coordinates":[-103.49917000000001,18.36083],"type":"Point"}
}