{
  "type": "Feature",
  "properties": {
    "gn:admin1_code":"13",
    "gn:admin2_code":"1.0",
    "gn:asciiname":"Magueyes Verdes",
    "gn:country_code":"MX",
    "gn:dem":2222,
    "gn:feature_class":"P",
    "gn:feature_code":"PPL",
    "gn:name":"Magueyes Verdes",
    "gn:population":0,
    "gn:timezone":"America/Mexico_City",
    "iso:country":"MX",
    "name:spa_x_preferred":[
        "Magueyes Verdes"
    ],
    "wof:name":"Magueyes Verdes",
    "wof:placetype":"locality"
},
  "geometry": {"coordinates":[-98.47812,20.32521],"type":"Point"}
}