{
  "type": "Feature",
  "properties": {
    "gn:admin1_code":"12",
    "gn:admin2_code":"55.0",
    "gn:asciiname":"El Mirador",
    "gn:country_code":"MX",
    "gn:dem":1194,
    "gn:feature_class":"P",
    "gn:feature_code":"PPL",
    "gn:name":"El Mirador",
    "gn:population":331,
    "gn:timezone":"America/Mexico_City",
    "iso:country":"MX",
    "wof:name":"El Mirador",
    "wof:placetype":"locality",
    "wof:population":331
},
  "geometry": {"coordinates":[-99.4996,18.60701],"type":"Point"}
}