{
  "type": "Feature",
  "properties": {
    "gn:admin1_code":"30",
    "gn:admin2_code":"105.0",
    "gn:asciiname":"La Loma (Kilometro Uno)",
    "gn:country_code":"MX",
    "gn:dem":38,
    "gn:feature_class":"P",
    "gn:feature_code":"PPL",
    "gn:name":"La Loma (Kil\u00f3metro Uno)",
    "gn:population":7,
    "gn:timezone":"America/Mexico_City",
    "iso:country":"MX",
    "name:und_x_variant":[
        "La Loma (Kil\u00f3metro Uno)"
    ],
    "wof:name":"La Loma (Kilometro Uno)",
    "wof:placetype":"locality",
    "wof:population":7
},
  "geometry": {"coordinates":[-96.11611000000001,18.99722],"type":"Point"}
}