{
  "type": "Feature",
  "properties": {
    "gn:admin1_code":"4.0",
    "gn:admin2_code":"9.0",
    "gn:asciiname":"La Porfiria",
    "gn:country_code":"MX",
    "gn:dem":63,
    "gn:feature_class":"P",
    "gn:feature_code":"PPL",
    "gn:name":"La Porfiria",
    "gn:population":0,
    "gn:timezone":"America/Merida",
    "iso:country":"MX",
    "name:spa_x_preferred":[
        "La Porfiria"
    ],
    "wof:name":"La Porfiria",
    "wof:placetype":"locality"
},
  "geometry": {"coordinates":[-90.73894,18.41469],"type":"Point"}
}