{
  "type": "Feature",
  "properties": {
    "gn:admin1_code":"28.0",
    "gn:admin2_code":"8.0",
    "gn:asciiname":"El Palmar",
    "gn:country_code":"MX",
    "gn:dem":181,
    "gn:feature_class":"P",
    "gn:feature_code":"PPL",
    "gn:name":"El Palmar",
    "gn:population":0,
    "gn:timezone":"America/Monterrey",
    "iso:country":"MX",
    "name:ceb_x_preferred":[
        "El Palmar"
    ],
    "name:fra_x_preferred":[
        "El Palmar"
    ],
    "name:glg_x_preferred":[
        "El Palmar"
    ],
    "name:lit_x_preferred":[
        "El Palmaras"
    ],
    "name:spa_x_preferred":[
        "El Palmar"
    ],
    "name:spa_x_variant":[
        "Tres Hermanos"
    ],
    "name:srp_x_preferred":[
        "\u0415\u043b \u041f\u0430\u043b\u043c\u0430\u0440"
    ],
    "name:swe_x_preferred":[
        "El Palmar"
    ],
    "wof:name":"El Palmar",
    "wof:placetype":"locality"
},
  "geometry": {"coordinates":[-98.83611000000001,23.69312],"type":"Point"}
}