{
  "type": "Feature",
  "properties": {
    "gn:admin1_code":"15",
    "gn:admin2_code":"85.0",
    "gn:asciiname":"El Tejocote (La Loma)",
    "gn:country_code":"MX",
    "gn:dem":2384,
    "gn:feature_class":"P",
    "gn:feature_code":"PPL",
    "gn:name":"El Tejocote (La Loma)",
    "gn:population":515,
    "gn:timezone":"America/Mexico_City",
    "iso:country":"MX",
    "wof:name":"El Tejocote (La Loma)",
    "wof:placetype":"locality",
    "wof:population":515
},
  "geometry": {"coordinates":[-100.14632,20.04647000000001],"type":"Point"}
}