{
  "type": "Feature",
  "properties": {
    "gn:admin1_code":"19.0",
    "gn:asciiname":"El Quelite",
    "gn:country_code":"MX",
    "gn:dem":359,
    "gn:feature_class":"P",
    "gn:feature_code":"PPL",
    "gn:name":"El Quelite",
    "gn:population":0,
    "gn:timezone":"America/Monterrey",
    "iso:country":"MX",
    "name:spa_x_preferred":[
        "El Quelite"
    ],
    "wof:name":"El Quelite",
    "wof:placetype":"locality"
},
  "geometry": {"coordinates":[-100.09227,25.81421],"type":"Point"}
}