{
  "type": "Feature",
  "properties": {
    "gn:admin1_code":"15",
    "gn:admin2_code":"9",
    "gn:asciiname":"Rancho el Risco",
    "gn:country_code":"MX",
    "gn:dem":2490,
    "gn:feature_class":"P",
    "gn:feature_code":"PPL",
    "gn:name":"Rancho el Risco",
    "gn:population":24,
    "gn:timezone":"America/Mexico_City",
    "iso:country":"MX",
    "wof:name":"Rancho el Risco",
    "wof:placetype":"locality",
    "wof:population":24
},
  "geometry": {"coordinates":[-98.78749000000001,19.16457],"type":"Point"}
}