{
  "type": "Feature",
  "properties": {
    "gn:admin1_code":"21",
    "gn:admin2_code":"67.0",
    "gn:asciiname":"San Luis Atexcac",
    "gn:country_code":"MX",
    "gn:dem":2418,
    "gn:feature_class":"P",
    "gn:feature_code":"PPL",
    "gn:name":"San Luis Atexcac",
    "gn:population":0,
    "gn:timezone":"America/Mexico_City",
    "iso:country":"MX",
    "name:spa_x_preferred":[
        "San Luis Atexcac"
    ],
    "wof:name":"San Luis Atexcac",
    "wof:placetype":"locality"
},
  "geometry": {"coordinates":[-97.45123,19.34519],"type":"Point"}
}