{
  "type": "Feature",
  "properties": {
    "gn:admin1_code":"6",
    "gn:admin2_code":"30.0",
    "gn:asciiname":"La Vinorama",
    "gn:country_code":"MX",
    "gn:dem":1421,
    "gn:feature_class":"P",
    "gn:feature_code":"PPL",
    "gn:name":"La Vinorama",
    "gn:population":8,
    "gn:timezone":"America/Chihuahua",
    "iso:country":"MX",
    "wof:name":"La Vinorama",
    "wof:placetype":"locality",
    "wof:population":8
},
  "geometry": {"coordinates":[-108.28576,27.54881],"type":"Point"}
}