{
  "type": "Feature",
  "properties": {
    "gn:admin1_code":"26.0",
    "gn:admin2_code":"50.0",
    "gn:asciiname":"La Jarilla",
    "gn:country_code":"MX",
    "gn:dem":803,
    "gn:feature_class":"P",
    "gn:feature_code":"PPL",
    "gn:name":"La Jarilla",
    "gn:population":0,
    "gn:timezone":"America/Hermosillo",
    "iso:country":"MX",
    "name:spa_x_preferred":[
        "La Jarilla"
    ],
    "wof:name":"La Jarilla",
    "wof:placetype":"locality"
},
  "geometry": {"coordinates":[-110.54300000000001,29.91138],"type":"Point"}
}