{
  "type": "Feature",
  "properties": {
    "gn:admin1_code":"6",
    "gn:admin2_code":"63.0",
    "gn:asciiname":"Rancho los Martinez",
    "gn:country_code":"MX",
    "gn:dem":1583,
    "gn:feature_class":"P",
    "gn:feature_code":"PPL",
    "gn:name":"Rancho los Mart\u00ednez",
    "gn:population":5,
    "gn:timezone":"America/Chihuahua",
    "iso:country":"MX",
    "name:und_x_variant":[
        "Rancho los Mart\u00ednez"
    ],
    "wof:name":"Rancho los Martinez",
    "wof:placetype":"locality",
    "wof:population":5
},
  "geometry": {"coordinates":[-108.4226,28.5931],"type":"Point"}
}