{
  "type": "Feature",
  "properties": {
    "gn:admin1_code":"6.0",
    "gn:admin2_code":"1.0",
    "gn:asciiname":"Los Garcia",
    "gn:country_code":"MX",
    "gn:dem":1198,
    "gn:feature_class":"P",
    "gn:feature_code":"PPL",
    "gn:name":"Los Garc\u00eda",
    "gn:population":0,
    "gn:timezone":"America/Chihuahua",
    "iso:country":"MX",
    "name:spa_x_preferred":[
        "Los Garc\u00eda"
    ],
    "name:und_x_variant":[
        "Banco el Lucero"
    ],
    "wof:name":"Los Garcia",
    "wof:placetype":"locality"
},
  "geometry": {"coordinates":[-106.50165,30.81993],"type":"Point"}
}