{
  "type": "Feature",
  "properties": {
    "gn:admin1_code":"26",
    "gn:admin2_code":"29.0",
    "gn:asciiname":"Condominios Pilar",
    "gn:country_code":"MX",
    "gn:dem":5,
    "gn:feature_class":"P",
    "gn:feature_code":"PPL",
    "gn:name":"Condominios Pilar",
    "gn:population":0,
    "gn:timezone":"America/Hermosillo",
    "iso:country":"MX",
    "name:spa_x_preferred":[
        "Condominios Pilar"
    ],
    "name:und_x_variant":[
        "El Pilar"
    ],
    "wof:name":"Condominios Pilar",
    "wof:placetype":"locality"
},
  "geometry": {"coordinates":[-110.98421,27.95952],"type":"Point"}
}