{
  "type": "Feature",
  "properties": {
    "gn:admin1_code":"6",
    "gn:admin2_code":"40.0",
    "gn:asciiname":"Chihuahuita",
    "gn:country_code":"MX",
    "gn:dem":2201,
    "gn:feature_class":"P",
    "gn:feature_code":"PPL",
    "gn:name":"Chihuahuita",
    "gn:population":0,
    "gn:timezone":"America/Chihuahua",
    "iso:country":"MX",
    "name:spa_x_preferred":[
        "Chihuahuita"
    ],
    "wof:name":"Chihuahuita",
    "wof:placetype":"locality"
},
  "geometry": {"coordinates":[-108.25283,29.66581],"type":"Point"}
}