{
  "type": "Feature",
  "properties": {
    "gn:admin1_code":"31",
    "gn:admin2_code":"19.0",
    "gn:asciiname":"Cocoh",
    "gn:country_code":"MX",
    "gn:dem":22,
    "gn:feature_class":"P",
    "gn:feature_code":"PPL",
    "gn:name":"Cocoh",
    "gn:population":0,
    "gn:timezone":"America/Merida",
    "iso:country":"MX",
    "name:spa_x_preferred":[
        "Cocoh"
    ],
    "wof:name":"Cocoh",
    "wof:placetype":"locality"
},
  "geometry": {"coordinates":[-87.88221999999998,20.69516],"type":"Point"}
}