{
  "type": "Feature",
  "properties": {
    "gn:admin1_code":"12",
    "gn:admin2_code":"48.0",
    "gn:asciiname":"La Pequena",
    "gn:country_code":"MX",
    "gn:dem":14,
    "gn:feature_class":"P",
    "gn:feature_code":"PPL",
    "gn:name":"La Peque\u00f1a",
    "gn:population":0,
    "gn:timezone":"America/Mexico_City",
    "iso:country":"MX",
    "name:spa_x_preferred":[
        "La Peque\u00f1a"
    ],
    "wof:name":"La Pequena",
    "wof:placetype":"locality"
},
  "geometry": {"coordinates":[-101.09227,17.36788],"type":"Point"}
}