{
  "type": "Feature",
  "properties": {
    "gn:admin1_code":"10",
    "gn:admin2_code":"5.0",
    "gn:asciiname":"Rio Verde",
    "gn:country_code":"MX",
    "gn:dem":2445,
    "gn:feature_class":"P",
    "gn:feature_code":"PPL",
    "gn:name":"R\u00edo Verde",
    "gn:population":202,
    "gn:timezone":"America/Monterrey",
    "iso:country":"MX",
    "name:spa_x_preferred":[
        "R\u00edo Verde"
    ],
    "wof:name":"Rio Verde",
    "wof:placetype":"locality",
    "wof:population":202
},
  "geometry": {"coordinates":[-104.9979,24.27248],"type":"Point"}
}