{
  "type": "Feature",
  "properties": {
    "gn:admin1_code":"28",
    "gn:admin2_code":"18.0",
    "gn:asciiname":"Jose Silva Sanchez",
    "gn:country_code":"MX",
    "gn:dem":193,
    "gn:feature_class":"P",
    "gn:feature_code":"PPL",
    "gn:name":"Jos\u00e9 Silva S\u00e1nchez",
    "gn:population":111,
    "gn:timezone":"America/Monterrey",
    "iso:country":"MX",
    "name:und_x_variant":[
        "Jos\u00e9 Silva S\u00e1nchez"
    ],
    "wof:name":"Jose Silva Sanchez",
    "wof:placetype":"locality",
    "wof:population":111
},
  "geometry": {"coordinates":[-98.45444000000001,24.28056],"type":"Point"}
}