{
  "type": "Feature",
  "properties": {
    "gn:admin1_code":"25",
    "gn:admin2_code":"17.0",
    "gn:asciiname":"San Jose de las Delicias",
    "gn:country_code":"MX",
    "gn:dem":319,
    "gn:feature_class":"P",
    "gn:feature_code":"PPL",
    "gn:name":"San Jos\u00e9 de las Delicias",
    "gn:population":0,
    "gn:timezone":"America/Mazatlan",
    "iso:country":"MX",
    "name:spa_x_preferred":[
        "San Jos\u00e9 de las Delicias"
    ],
    "name:und_x_variant":[
        "San Jos\u00e9 de las Delic\u00edas"
    ],
    "wof:name":"San Jose de las Delicias",
    "wof:placetype":"locality"
},
  "geometry": {"coordinates":[-107.78482,25.80607],"type":"Point"}
}