{
  "type": "Feature",
  "properties": {
    "gn:admin1_code":"14.0",
    "gn:admin2_code":"20.0",
    "gn:asciiname":"Los Ojuelos",
    "gn:country_code":"MX",
    "gn:dem":698,
    "gn:feature_class":"P",
    "gn:feature_code":"PPL",
    "gn:name":"Los Ojuelos",
    "gn:population":0,
    "gn:timezone":"America/Mexico_City",
    "iso:country":"MX",
    "name:spa_x_preferred":[
        "Los Ojuelos"
    ],
    "wof:name":"Los Ojuelos",
    "wof:placetype":"locality"
},
  "geometry": {"coordinates":[-105.32532,20.34992],"type":"Point"}
}