{
  "type": "Feature",
  "properties": {
    "gn:admin1_code":"24",
    "gn:admin2_code":"29.0",
    "gn:asciiname":"Buenavista (Palmar Alto)",
    "gn:country_code":"MX",
    "gn:dem":113,
    "gn:feature_class":"P",
    "gn:feature_code":"PPL",
    "gn:name":"Buenavista (Palmar Alto)",
    "gn:population":362,
    "gn:timezone":"America/Mexico_City",
    "iso:country":"MX",
    "wof:name":"Buenavista (Palmar Alto)",
    "wof:placetype":"locality",
    "wof:population":362
},
  "geometry": {"coordinates":[-98.535,21.4425],"type":"Point"}
}