{
  "type": "Feature",
  "properties": {
    "gn:admin1_code":"19",
    "gn:admin2_code":"9.0",
    "gn:asciiname":"Las Palmas",
    "gn:country_code":"MX",
    "gn:dem":350,
    "gn:feature_class":"P",
    "gn:feature_code":"PPL",
    "gn:name":"Las Palmas",
    "gn:population":0,
    "gn:timezone":"America/Monterrey",
    "iso:country":"MX",
    "name:spa_x_preferred":[
        "Las Palmas"
    ],
    "wof:name":"Las Palmas",
    "wof:placetype":"locality"
},
  "geometry": {"coordinates":[-99.98658,25.43201],"type":"Point"}
}