{
  "type": "Feature",
  "properties": {
    "gn:admin1_code":"3.0",
    "gn:admin2_code":"3.0",
    "gn:asciiname":"Alfredo V. Bonfil",
    "gn:country_code":"MX",
    "gn:dem":71,
    "gn:feature_class":"P",
    "gn:feature_code":"PPL",
    "gn:name":"Alfredo V. Bonfil",
    "gn:population":0,
    "gn:timezone":"America/Mazatlan",
    "iso:country":"MX",
    "name:spa_x_preferred":[
        "Alfredo V. Bonfil"
    ],
    "wof:name":"Alfredo V. Bonfil",
    "wof:placetype":"locality"
},
  "geometry": {"coordinates":[-110.56679,24.14878],"type":"Point"}
}