{
  "type": "Feature",
  "properties": {
    "gn:admin1_code":"24",
    "gn:admin2_code":"57.0",
    "gn:asciiname":"Tlamaya",
    "gn:country_code":"MX",
    "gn:dem":108,
    "gn:feature_class":"P",
    "gn:feature_code":"PPL",
    "gn:name":"Tlamaya",
    "gn:population":303,
    "gn:timezone":"America/Mexico_City",
    "iso:country":"MX",
    "wof:name":"Tlamaya",
    "wof:placetype":"locality",
    "wof:population":303
},
  "geometry": {"coordinates":[-98.79778,21.34194],"type":"Point"}
}