{
  "type": "Feature",
  "properties": {
    "gn:admin1_code":"6.0",
    "gn:admin2_code":"1.0",
    "gn:asciiname":"La Bodega",
    "gn:country_code":"MX",
    "gn:dem":1234,
    "gn:feature_class":"P",
    "gn:feature_code":"PPL",
    "gn:name":"La Bodega",
    "gn:population":0,
    "gn:timezone":"America/Chihuahua",
    "iso:country":"MX",
    "name:spa_x_preferred":[
        "La Bodega"
    ],
    "wof:name":"La Bodega",
    "wof:placetype":"locality"
},
  "geometry": {"coordinates":[-106.7251,30.58078],"type":"Point"}
}