{
  "type": "Feature",
  "properties": {
    "gn:admin1_code":"18.0",
    "gn:admin2_code":"11.0",
    "gn:asciiname":"El Sombrero",
    "gn:country_code":"MX",
    "gn:dem":714,
    "gn:feature_class":"P",
    "gn:feature_code":"PPL",
    "gn:name":"El Sombrero",
    "gn:population":0,
    "gn:timezone":"America/Mazatlan",
    "iso:country":"MX",
    "name:spa_x_preferred":[
        "El Sombrero"
    ],
    "wof:name":"El Sombrero",
    "wof:placetype":"locality"
},
  "geometry": {"coordinates":[-104.85551,22.07858],"type":"Point"}
}