{
  "type": "Feature",
  "properties": {
    "gn:admin1_code":"20",
    "gn:admin2_code":"328",
    "gn:asciiname":"Piedra Gacha (Arroyo del Sauce)",
    "gn:country_code":"MX",
    "gn:dem":1706,
    "gn:feature_class":"P",
    "gn:feature_code":"PPL",
    "gn:name":"Piedra Gacha (Arroyo del Sauce)",
    "gn:population":38,
    "gn:timezone":"America/Mexico_City",
    "iso:country":"MX",
    "wof:name":"Piedra Gacha (Arroyo del Sauce)",
    "wof:placetype":"locality",
    "wof:population":38
},
  "geometry": {"coordinates":[-96.53528,16.64528],"type":"Point"}
}