{
  "type": "Feature",
  "properties": {
    "gn:admin1_code":"21",
    "gn:admin2_code":"81.0",
    "gn:asciiname":"El Organal",
    "gn:country_code":"MX",
    "gn:dem":715,
    "gn:feature_class":"P",
    "gn:feature_code":"PPL",
    "gn:name":"El Organal",
    "gn:population":269,
    "gn:timezone":"America/Mexico_City",
    "iso:country":"MX",
    "wof:name":"El Organal",
    "wof:placetype":"locality",
    "wof:population":269
},
  "geometry": {"coordinates":[-98.69917,18.01556],"type":"Point"}
}