{
  "type": "Feature",
  "properties": {
    "gn:admin1_code":"16",
    "gn:admin2_code":"96",
    "gn:asciiname":"Las Salinas",
    "gn:country_code":"MX",
    "gn:dem":610,
    "gn:feature_class":"P",
    "gn:feature_code":"PPL",
    "gn:name":"Las Salinas",
    "gn:population":10,
    "gn:timezone":"America/Mexico_City",
    "iso:country":"MX",
    "name:ceb_x_preferred":[
        "Las Salinas"
    ],
    "name:ita_x_preferred":[
        "Las Salinas"
    ],
    "name:por_x_preferred":[
        "Las Salinas"
    ],
    "name:spa_x_preferred":[
        "Las Salinas"
    ],
    "name:urd_x_preferred":[
        "\u0644\u0627\u0633 \u0633\u0627\u0644\u06cc\u0646\u0627\u0633"
    ],
    "name:zho_x_preferred":[
        "\u62c9\u65af\u85a9\u5229\u7d0d\u65af"
    ],
    "wof:name":"Las Salinas",
    "wof:placetype":"locality",
    "wof:population":10
},
  "geometry": {"coordinates":[-102.79889,18.49917],"type":"Point"}
}