{
  "type": "Feature",
  "properties": {
    "gn:admin1_code":"16",
    "gn:admin2_code":"96",
    "gn:asciiname":"Las Salinas",
    "gn:country_code":"MX",
    "gn:dem":610,
    "gn:feature_class":"P",
    "gn:feature_code":"PPL",
    "gn:name":"Las Salinas",
    "gn:population":10,
    "gn:timezone":"America/Mexico_City",
    "iso:country":"MX",
    "wof:name":"Las Salinas",
    "wof:placetype":"locality",
    "wof:population":10
},
  "geometry": {"coordinates":[-102.79889,18.49917],"type":"Point"}
}