{
  "type": "Feature",
  "properties": {
    "gn:admin1_code":"3",
    "gn:admin2_code":"1.0",
    "gn:asciiname":"Jesus Becerro",
    "gn:country_code":"MX",
    "gn:dem":38,
    "gn:feature_class":"P",
    "gn:feature_code":"PPL",
    "gn:name":"Jes\u00fas Becerro",
    "gn:population":0,
    "gn:timezone":"America/Mazatlan",
    "iso:country":"MX",
    "name:spa_x_preferred":[
        "Jes\u00fas Becerro"
    ],
    "name:spa_x_variant":[
        "Fierro Encino"
    ],
    "wof:name":"Jesus Becerro",
    "wof:placetype":"locality"
},
  "geometry": {"coordinates":[-111.80916999999999,25.32975],"type":"Point"}
}