{
  "type": "Feature",
  "properties": {
    "gn:admin1_code":"6",
    "gn:admin2_code":"9.0",
    "gn:asciiname":"La Mesa",
    "gn:country_code":"MX",
    "gn:dem":2392,
    "gn:feature_class":"P",
    "gn:feature_code":"PPL",
    "gn:name":"La Mesa",
    "gn:population":0,
    "gn:timezone":"America/Chihuahua",
    "iso:country":"MX",
    "name:spa_x_preferred":[
        "La Mesa"
    ],
    "wof:name":"La Mesa",
    "wof:placetype":"locality"
},
  "geometry": {"coordinates":[-107.76505,27.89665],"type":"Point"}
}