{
  "type": "Feature",
  "properties": {
    "gn:admin1_code":"10",
    "gn:admin2_code":"9.0",
    "gn:asciiname":"La Hoya",
    "gn:country_code":"MX",
    "gn:dem":2414,
    "gn:feature_class":"P",
    "gn:feature_code":"PPL",
    "gn:name":"La Hoya",
    "gn:population":0,
    "gn:timezone":"America/Monterrey",
    "iso:country":"MX",
    "name:ceb_x_preferred":[
        "La Hoya"
    ],
    "name:fra_x_preferred":[
        "La Hoya"
    ],
    "name:glg_x_preferred":[
        "La Hoya"
    ],
    "name:spa_x_preferred":[
        "La Hoya"
    ],
    "name:swe_x_preferred":[
        "La Hoya"
    ],
    "wof:name":"La Hoya",
    "wof:placetype":"locality"
},
  "geometry": {"coordinates":[-105.94815,26.13467],"type":"Point"}
}