{
  "type": "Feature",
  "properties": {
    "gn:admin1_code":"26.0",
    "gn:admin2_code":"6.0",
    "gn:asciiname":"El Sabino",
    "gn:country_code":"MX",
    "gn:dem":1305,
    "gn:feature_class":"P",
    "gn:feature_code":"PPL",
    "gn:name":"El Sabino",
    "gn:population":0,
    "gn:timezone":"America/Hermosillo",
    "iso:country":"MX",
    "name:spa_x_preferred":[
        "El Sabino"
    ],
    "wof:name":"El Sabino",
    "wof:placetype":"locality"
},
  "geometry": {"coordinates":[-110.39234999999999,30.62295],"type":"Point"}
}