{
  "type": "Feature",
  "properties": {
    "gn:admin1_code":"11",
    "gn:admin2_code":"12.0",
    "gn:asciiname":"Plan Sexenal",
    "gn:country_code":"MX",
    "gn:dem":1705,
    "gn:feature_class":"P",
    "gn:feature_code":"PPL",
    "gn:name":"Plan Sexenal",
    "gn:population":161,
    "gn:timezone":"America/Mexico_City",
    "iso:country":"MX",
    "wof:name":"Plan Sexenal",
    "wof:placetype":"locality",
    "wof:population":161
},
  "geometry": {"coordinates":[-101.64778,20.65583],"type":"Point"}
}