{
  "type": "Feature",
  "properties": {
    "gn:admin1_code":"16",
    "gn:admin2_code":"8.0",
    "gn:asciiname":"El Chivo",
    "gn:country_code":"MX",
    "gn:dem":511,
    "gn:feature_class":"P",
    "gn:feature_code":"PPL",
    "gn:name":"El Chivo",
    "gn:population":8,
    "gn:timezone":"America/Mexico_City",
    "iso:country":"MX",
    "name:bul_x_preferred":[
        "\u041a\u043e\u0437\u0435\u043b\u044a\u0442"
    ],
    "name:fas_x_preferred":[
        "\u0627\u0644 \u0686\u06cc\u0648\u0648"
    ],
    "name:spa_x_preferred":[
        "El Chivo"
    ],
    "wof:name":"El Chivo",
    "wof:placetype":"locality",
    "wof:population":8
},
  "geometry": {"coordinates":[-102.81556,18.21361],"type":"Point"}
}