{
  "type": "Feature",
  "properties": {
    "gn:admin1_code":"17",
    "gn:admin2_code":"31.0",
    "gn:asciiname":"Colonia el Paraiso",
    "gn:country_code":"MX",
    "gn:dem":936,
    "gn:feature_class":"P",
    "gn:feature_code":"PPL",
    "gn:name":"Colonia el Para\u00edso",
    "gn:population":257,
    "gn:timezone":"America/Mexico_City",
    "iso:country":"MX",
    "name:und_x_variant":[
        "Colonia el Para\u00edso"
    ],
    "wof:name":"Colonia el Paraiso",
    "wof:placetype":"locality",
    "wof:population":257
},
  "geometry": {"coordinates":[-99.18891000000001,18.67925],"type":"Point"}
}