{
  "type": "Feature",
  "properties": {
    "gn:admin1_code":"25",
    "gn:admin2_code":"1.0",
    "gn:asciiname":"San Miguelito",
    "gn:country_code":"MX",
    "gn:dem":11,
    "gn:feature_class":"P",
    "gn:feature_code":"PPL",
    "gn:name":"San Miguelito",
    "gn:population":0,
    "gn:timezone":"America/Mazatlan",
    "iso:country":"MX",
    "name:ceb_x_preferred":[
        "San Miguelito"
    ],
    "name:deu_x_preferred":[
        "San Miguelito"
    ],
    "name:ita_x_preferred":[
        "San Miguelito"
    ],
    "name:nld_x_preferred":[
        "San Miguelito"
    ],
    "name:pol_x_preferred":[
        "San Miguelito"
    ],
    "name:spa_x_preferred":[
        "San Miguelito"
    ],
    "name:swe_x_preferred":[
        "San Miguelito"
    ],
    "wof:name":"San Miguelito",
    "wof:placetype":"locality"
},
  "geometry": {"coordinates":[-109.06832,25.84352],"type":"Point"}
}