{
  "type": "Feature",
  "properties": {
    "gn:admin1_code":"10",
    "gn:admin2_code":"5.0",
    "gn:asciiname":"Cienega de Ibarra",
    "gn:country_code":"MX",
    "gn:dem":2630,
    "gn:feature_class":"P",
    "gn:feature_code":"PPL",
    "gn:name":"Ci\u00e9nega de Ibarra",
    "gn:population":0,
    "gn:timezone":"America/Monterrey",
    "iso:country":"MX",
    "name:spa_x_preferred":[
        "Ci\u00e9nega de Ibarra"
    ],
    "wof:name":"Cienega de Ibarra",
    "wof:placetype":"locality"
},
  "geometry": {"coordinates":[-105.01094000000001,23.81729],"type":"Point"}
}