{
  "type": "Feature",
  "properties": {
    "gn:admin1_code":"28.0",
    "gn:admin2_code":"37.0",
    "gn:asciiname":"Los Canones",
    "gn:country_code":"MX",
    "gn:dem":281,
    "gn:feature_class":"P",
    "gn:feature_code":"PPL",
    "gn:name":"Los Ca\u00f1ones",
    "gn:population":5,
    "gn:timezone":"America/Monterrey",
    "iso:country":"MX",
    "name:spa_x_preferred":[
        "Los Ca\u00f1ones"
    ],
    "wof:name":"Los Canones",
    "wof:placetype":"locality",
    "wof:population":5
},
  "geometry": {"coordinates":[-98.30583,23.58083],"type":"Point"}
}