{
  "type": "Feature",
  "properties": {
    "gn:admin1_code":"12.0",
    "gn:admin2_code":"31.0",
    "gn:asciiname":"Mina de la Concepcion",
    "gn:country_code":"MX",
    "gn:dem":507,
    "gn:feature_class":"P",
    "gn:feature_code":"PPL",
    "gn:name":"Mina de la Concepci\u00f3n",
    "gn:population":0,
    "gn:timezone":"America/Mexico_City",
    "iso:country":"MX",
    "name:spa_x_preferred":[
        "Mina de la Concepci\u00f3n"
    ],
    "name:und_x_variant":[
        "Mina la Concepci\u00f3n"
    ],
    "wof:name":"Mina de la Concepcion",
    "wof:placetype":"locality"
},
  "geometry": {"coordinates":[-100.19067,18.43311],"type":"Point"}
}