{
  "type": "Feature",
  "properties": {
    "gn:admin1_code":"24",
    "gn:admin2_code":"37.0",
    "gn:asciiname":"Cuajapa Santiago",
    "gn:country_code":"MX",
    "gn:dem":644,
    "gn:feature_class":"P",
    "gn:feature_code":"PPL",
    "gn:name":"Cuajapa Santiago",
    "gn:population":128,
    "gn:timezone":"America/Mexico_City",
    "iso:country":"MX",
    "wof:name":"Cuajapa Santiago",
    "wof:placetype":"locality",
    "wof:population":128
},
  "geometry": {"coordinates":[-98.86861,21.21889],"type":"Point"}
}