{
  "type": "Feature",
  "properties": {
    "gn:admin1_code":"18",
    "gn:admin2_code":"7",
    "gn:asciiname":"Los Grande",
    "gn:country_code":"MX",
    "gn:dem":1062,
    "gn:feature_class":"P",
    "gn:feature_code":"PPL",
    "gn:name":"Los Grande",
    "gn:population":10,
    "gn:timezone":"America/Mazatlan",
    "iso:country":"MX",
    "wof:name":"Los Grande",
    "wof:placetype":"locality",
    "wof:population":10
},
  "geometry": {"coordinates":[-104.44306,21.09639],"type":"Point"}
}