{
  "type": "Feature",
  "properties": {
    "gn:admin1_code":"11",
    "gn:admin2_code":"17",
    "gn:asciiname":"El Cerrito de en Medio",
    "gn:country_code":"MX",
    "gn:dem":1744,
    "gn:feature_class":"P",
    "gn:feature_code":"PPL",
    "gn:name":"El Cerrito de en Medio",
    "gn:population":12,
    "gn:timezone":"America/Mexico_City",
    "iso:country":"MX",
    "wof:name":"El Cerrito de en Medio",
    "wof:placetype":"locality",
    "wof:population":12
},
  "geometry": {"coordinates":[-101.32693999999999,20.60139],"type":"Point"}
}