{
  "type": "Feature",
  "properties": {
    "gn:admin1_code":"28",
    "gn:admin2_code":"40.0",
    "gn:asciiname":"Brecha 116 con Kilometro 82",
    "gn:country_code":"MX",
    "gn:dem":15,
    "gn:feature_class":"P",
    "gn:feature_code":"PPL",
    "gn:name":"Brecha 116 con Kil\u00f3metro 82",
    "gn:population":7,
    "gn:timezone":"America/Monterrey",
    "iso:country":"MX",
    "name:und_x_variant":[
        "Brecha 116 con Kil\u00f3metro 82"
    ],
    "wof:name":"Brecha 116 con Kilometro 82",
    "wof:placetype":"locality",
    "wof:population":7
},
  "geometry": {"coordinates":[-97.85527999999999,25.65972],"type":"Point"}
}