{
  "type": "Feature",
  "properties": {
    "gn:admin1_code":"7",
    "gn:admin2_code":"36.0",
    "gn:asciiname":"Cinco de Mayo",
    "gn:country_code":"MX",
    "gn:dem":1689,
    "gn:feature_class":"P",
    "gn:feature_code":"PPL",
    "gn:name":"Cinco de Mayo",
    "gn:population":0,
    "gn:timezone":"America/Monterrey",
    "iso:country":"MX",
    "wof:name":"Cinco de Mayo",
    "wof:placetype":"locality"
},
  "geometry": {"coordinates":[-102.63333,25.18333],"type":"Point"}
}