{
  "type": "Feature",
  "properties": {
    "gn:admin1_code":"14",
    "gn:admin2_code":"73",
    "gn:asciiname":"Santa Fe [Granja]",
    "gn:country_code":"MX",
    "gn:dem":1855,
    "gn:feature_class":"P",
    "gn:feature_code":"PPL",
    "gn:name":"Santa Fe [Granja]",
    "gn:population":12,
    "gn:timezone":"America/Mexico_City",
    "iso:country":"MX",
    "wof:name":"Santa Fe [Granja]",
    "wof:placetype":"locality",
    "wof:population":12
},
  "geometry": {"coordinates":[-102.38388999999999,21.1875],"type":"Point"}
}