{
  "type": "Feature",
  "properties": {
    "gn:admin1_code":"24.0",
    "gn:admin2_code":"11.0",
    "gn:asciiname":"Atotonilco",
    "gn:country_code":"MX",
    "gn:dem":1312,
    "gn:feature_class":"P",
    "gn:feature_code":"PPL",
    "gn:name":"Atotonilco",
    "gn:population":0,
    "gn:timezone":"America/Mexico_City",
    "iso:country":"MX",
    "name:spa_x_preferred":[
        "Atotonilco"
    ],
    "wof:name":"Atotonilco",
    "wof:placetype":"locality"
},
  "geometry": {"coordinates":[-100.44219,21.99286],"type":"Point"}
}