{
  "type": "Feature",
  "properties": {
    "gn:admin1_code":"14",
    "gn:admin2_code":"38",
    "gn:asciiname":"Rueda Verde",
    "gn:country_code":"MX",
    "gn:dem":937,
    "gn:feature_class":"P",
    "gn:feature_code":"PPL",
    "gn:name":"Rueda Verde",
    "gn:population":32,
    "gn:timezone":"America/Mexico_City",
    "iso:country":"MX",
    "wof:name":"Rueda Verde",
    "wof:placetype":"locality",
    "wof:population":32
},
  "geometry": {"coordinates":[-104.47778,20.80028],"type":"Point"}
}