{
  "type": "Feature",
  "properties": {
    "gn:admin1_code":"14.0",
    "gn:admin2_code":"60.0",
    "gn:asciiname":"Acasico",
    "gn:country_code":"MX",
    "gn:dem":1622,
    "gn:feature_class":"P",
    "gn:feature_code":"PPL",
    "gn:name":"Acasico",
    "gn:population":0,
    "gn:timezone":"America/Mexico_City",
    "iso:country":"MX",
    "wof:name":"Acasico",
    "wof:placetype":"locality"
},
  "geometry": {"coordinates":[-102.8292,21.21008],"type":"Point"}
}