{
  "type": "Feature",
  "properties": {
    "gn:admin1_code":"6.0",
    "gn:admin2_code":"9.0",
    "gn:asciiname":"Rucahuarachi",
    "gn:country_code":"MX",
    "gn:dem":2310,
    "gn:feature_class":"P",
    "gn:feature_code":"PPL",
    "gn:name":"Rucahuarachi",
    "gn:population":0,
    "gn:timezone":"America/Chihuahua",
    "iso:country":"MX",
    "name:spa_x_preferred":[
        "Rucahuarachi"
    ],
    "wof:name":"Rucahuarachi",
    "wof:placetype":"locality"
},
  "geometry": {"coordinates":[-107.38892,27.70391],"type":"Point"}
}