{
  "type": "Feature",
  "properties": {
    "gn:admin1_code":"12",
    "gn:admin2_code":"12",
    "gn:asciiname":"El Tehuaje",
    "gn:country_code":"MX",
    "gn:dem":268,
    "gn:feature_class":"P",
    "gn:feature_code":"PPL",
    "gn:name":"El Tehuaje",
    "gn:population":39,
    "gn:timezone":"America/Mexico_City",
    "iso:country":"MX",
    "wof:name":"El Tehuaje",
    "wof:placetype":"locality",
    "wof:population":39
},
  "geometry": {"coordinates":[-99.05280999999999,16.78402],"type":"Point"}
}