{
  "type": "Feature",
  "properties": {
    "gn:admin1_code":"13",
    "gn:admin2_code":"67",
    "gn:asciiname":"El Mogote",
    "gn:country_code":"MX",
    "gn:dem":2025,
    "gn:feature_class":"P",
    "gn:feature_code":"PPL",
    "gn:name":"El Mogote",
    "gn:population":10,
    "gn:timezone":"America/Mexico_City",
    "iso:country":"MX",
    "wof:name":"El Mogote",
    "wof:placetype":"locality",
    "wof:population":10
},
  "geometry": {"coordinates":[-99.28639,20.18278],"type":"Point"}
}