{
  "type": "Feature",
  "properties": {
    "gn:admin1_code":"19",
    "gn:admin2_code":"18.0",
    "gn:asciiname":"La Tina",
    "gn:country_code":"MX",
    "gn:dem":1083,
    "gn:feature_class":"P",
    "gn:feature_code":"PPL",
    "gn:name":"La Tina",
    "gn:population":0,
    "gn:timezone":"America/Monterrey",
    "iso:country":"MX",
    "name:spa_x_preferred":[
        "La Tina"
    ],
    "wof:name":"La Tina",
    "wof:placetype":"locality"
},
  "geometry": {"coordinates":[-100.75122,25.74884],"type":"Point"}
}