{
  "type": "Feature",
  "properties": {
    "gn:admin1_code":"19.0",
    "gn:admin2_code":"13.0",
    "gn:asciiname":"Las Presitas",
    "gn:country_code":"MX",
    "gn:dem":138,
    "gn:feature_class":"P",
    "gn:feature_code":"PPL",
    "gn:name":"Las Presitas",
    "gn:population":0,
    "gn:timezone":"America/Monterrey",
    "iso:country":"MX",
    "name:spa_x_preferred":[
        "Las Presitas"
    ],
    "wof:name":"Las Presitas",
    "wof:placetype":"locality"
},
  "geometry": {"coordinates":[-98.73062,25.50166],"type":"Point"}
}