{
  "type": "Feature",
  "properties": {
    "gn:admin1_code":"2.0",
    "gn:admin2_code":"4.0",
    "gn:asciiname":"Ejido Javier Rojo Gomez",
    "gn:country_code":"MX",
    "gn:dem":218,
    "gn:feature_class":"P",
    "gn:feature_code":"PPL",
    "gn:name":"Ejido Javier Rojo G\u00f3mez",
    "gn:population":2408,
    "gn:timezone":"America/Tijuana",
    "iso:country":"MX",
    "name:spa_x_preferred":[
        "Ejido Javier Rojo G\u00f3mez"
    ],
    "wof:name":"Ejido Javier Rojo Gomez",
    "wof:placetype":"locality",
    "wof:population":2408
},
  "geometry": {"coordinates":[-116.82222,32.49389],"type":"Point"}
}