{
  "type": "Feature",
  "properties": {
    "gn:admin1_code":"10.0",
    "gn:asciiname":"La Vinata",
    "gn:country_code":"MX",
    "gn:dem":1587,
    "gn:feature_class":"P",
    "gn:feature_code":"PPL",
    "gn:name":"La Vinata",
    "gn:population":0,
    "gn:timezone":"America/Monterrey",
    "iso:country":"MX",
    "name:spa_x_preferred":[
        "La Vinata"
    ],
    "wof:name":"La Vinata",
    "wof:placetype":"locality"
},
  "geometry": {"coordinates":[-105.80338999999999,24.24736],"type":"Point"}
}