{
  "type": "Feature",
  "properties": {
    "gn:admin1_code":"10",
    "gn:admin2_code":"26.0",
    "gn:asciiname":"El Yaqui",
    "gn:country_code":"MX",
    "gn:dem":2511,
    "gn:feature_class":"P",
    "gn:feature_code":"PPL",
    "gn:name":"El Yaqui",
    "gn:population":5,
    "gn:timezone":"America/Monterrey",
    "iso:country":"MX",
    "wof:name":"El Yaqui",
    "wof:placetype":"locality",
    "wof:population":5
},
  "geometry": {"coordinates":[-105.70663,24.43958],"type":"Point"}
}