{
  "type": "Feature",
  "properties": {
    "gn:admin1_code":"14",
    "gn:admin2_code":"65.0",
    "gn:asciiname":"El Fresnal",
    "gn:country_code":"MX",
    "gn:dem":1241,
    "gn:feature_class":"P",
    "gn:feature_code":"PPL",
    "gn:name":"El Fresnal",
    "gn:population":58,
    "gn:timezone":"America/Mexico_City",
    "iso:country":"MX",
    "wof:name":"El Fresnal",
    "wof:placetype":"locality",
    "wof:population":58
},
  "geometry": {"coordinates":[-103.44028,19.09861],"type":"Point"}
}