{
  "type": "Feature",
  "properties": {
    "gn:admin1_code":"5.0",
    "gn:admin2_code":"65.0",
    "gn:asciiname":"Choles de Palenque",
    "gn:country_code":"MX",
    "gn:dem":50,
    "gn:feature_class":"P",
    "gn:feature_code":"PPL",
    "gn:name":"Choles de Palenque",
    "gn:population":0,
    "gn:timezone":"America/Mexico_City",
    "iso:country":"MX",
    "name:spa_x_preferred":[
        "Choles de Palenque"
    ],
    "wof:name":"Choles de Palenque",
    "wof:placetype":"locality"
},
  "geometry": {"coordinates":[-92.02455999999999,17.51132],"type":"Point"}
}