{
  "type": "Feature",
  "properties": {
    "gn:admin1_code":"5",
    "gn:admin2_code":"65.0",
    "gn:asciiname":"El Abacal",
    "gn:country_code":"MX",
    "gn:dem":119,
    "gn:feature_class":"P",
    "gn:feature_code":"PPL",
    "gn:name":"El Abacal",
    "gn:population":5,
    "gn:timezone":"America/Mexico_City",
    "iso:country":"MX",
    "wof:name":"El Abacal",
    "wof:placetype":"locality",
    "wof:population":5
},
  "geometry": {"coordinates":[-91.40778,17.12139],"type":"Point"}
}