{
  "type": "Feature",
  "properties": {
    "gn:admin1_code":"3",
    "gn:admin2_code":"8.0",
    "gn:asciiname":"La Choya",
    "gn:country_code":"MX",
    "gn:dem":21,
    "gn:feature_class":"P",
    "gn:feature_code":"PPL",
    "gn:name":"La Choya",
    "gn:population":453,
    "gn:timezone":"America/Mazatlan",
    "iso:country":"MX",
    "wof:name":"La Choya",
    "wof:placetype":"locality",
    "wof:population":453
},
  "geometry": {"coordinates":[-109.68028,23.06667],"type":"Point"}
}