{
  "type": "Feature",
  "properties": {
    "gn:admin1_code":"20",
    "gn:admin2_code":"82",
    "gn:asciiname":"La Juquilita (Colonia la Juquilita)",
    "gn:country_code":"MX",
    "gn:dem":260,
    "gn:feature_class":"P",
    "gn:feature_code":"PPL",
    "gn:name":"La Juquilita (Colonia la Juquilita)",
    "gn:population":25,
    "gn:timezone":"America/Mexico_City",
    "iso:country":"MX",
    "wof:name":"La Juquilita (Colonia la Juquilita)",
    "wof:placetype":"locality",
    "wof:population":25
},
  "geometry": {"coordinates":[-97.80806,16.39777999999999],"type":"Point"}
}