{
  "type": "Feature",
  "properties": {
    "gn:admin1_code":"5",
    "gn:admin2_code":"69",
    "gn:asciiname":"Rincon del Bosque",
    "gn:country_code":"MX",
    "gn:dem":300,
    "gn:feature_class":"P",
    "gn:feature_code":"PPL",
    "gn:name":"Rinc\u00f3n del Bosque",
    "gn:population":43,
    "gn:timezone":"America/Mexico_City",
    "iso:country":"MX",
    "name:und_x_variant":[
        "Rinc\u00f3n del Bosque"
    ],
    "wof:name":"Rincon del Bosque",
    "wof:placetype":"locality",
    "wof:population":43
},
  "geometry": {"coordinates":[-93.11667,15.67917],"type":"Point"}
}