{
  "type": "Feature",
  "properties": {
    "gn:admin1_code":"31",
    "gn:admin2_code":"44.0",
    "gn:asciiname":"San Francisco Kana",
    "gn:country_code":"MX",
    "gn:dem":6,
    "gn:feature_class":"P",
    "gn:feature_code":"PPL",
    "gn:name":"San Francisco Kan\u00e1",
    "gn:population":0,
    "gn:timezone":"America/Merida",
    "iso:country":"MX",
    "name:spa_x_preferred":[
        "San Francisco Kana"
    ],
    "name:spa_x_variant":[
        "San Francisco Kan\u00e1"
    ],
    "name:und_x_variant":[
        "Kan\u00e1"
    ],
    "wof:name":"San Francisco Kana",
    "wof:placetype":"locality"
},
  "geometry": {"coordinates":[-90.13582,20.85754],"type":"Point"}
}