{
  "type": "Feature",
  "properties": {
    "gn:admin1_code":"12",
    "gn:admin2_code":"22.0",
    "gn:asciiname":"La Florida",
    "gn:country_code":"MX",
    "gn:dem":2604,
    "gn:feature_class":"P",
    "gn:feature_code":"PPL",
    "gn:name":"La Florida",
    "gn:population":7,
    "gn:timezone":"America/Mexico_City",
    "iso:country":"MX",
    "wof:name":"La Florida",
    "wof:placetype":"locality",
    "wof:population":7
},
  "geometry": {"coordinates":[-101.02076,17.87765],"type":"Point"}
}