{
  "type": "Feature",
  "properties": {
    "gn:admin1_code":"25",
    "gn:admin2_code":"7.0",
    "gn:asciiname":"El Batayacal",
    "gn:country_code":"MX",
    "gn:dem":1706,
    "gn:feature_class":"P",
    "gn:feature_code":"PPL",
    "gn:name":"El Batayacal",
    "gn:population":0,
    "gn:timezone":"America/Mazatlan",
    "iso:country":"MX",
    "name:spa_x_preferred":[
        "El Batayacal"
    ],
    "wof:name":"El Batayacal",
    "wof:placetype":"locality"
},
  "geometry": {"coordinates":[-108.0558,26.76923],"type":"Point"}
}