{
  "type": "Feature",
  "properties": {
    "gn:admin1_code":"31",
    "gn:admin2_code":"96.0",
    "gn:asciiname":"Noh-Cache",
    "gn:country_code":"MX",
    "gn:dem":10,
    "gn:feature_class":"P",
    "gn:feature_code":"PPL",
    "gn:name":"Noh-Cach\u00e9",
    "gn:population":0,
    "gn:timezone":"America/Merida",
    "iso:country":"MX",
    "name:spa_x_preferred":[
        "Noh-Cach\u00e9"
    ],
    "wof:name":"Noh-Cache",
    "wof:placetype":"locality"
},
  "geometry": {"coordinates":[-87.5864,21.19965],"type":"Point"}
}