{
  "type": "Feature",
  "properties": {
    "gn:admin1_code":"21",
    "gn:admin2_code":"85.0",
    "gn:asciiname":"Agustines",
    "gn:country_code":"MX",
    "gn:dem":1276,
    "gn:feature_class":"P",
    "gn:feature_code":"PPL",
    "gn:name":"Agustines",
    "gn:population":6,
    "gn:timezone":"America/Mexico_City",
    "iso:country":"MX",
    "wof:name":"Agustines",
    "wof:placetype":"locality",
    "wof:population":6
},
  "geometry": {"coordinates":[-98.43637,18.57156],"type":"Point"}
}