{
  "type": "Feature",
  "properties": {
    "iso:country":"MX",
    "name:spa_x_preferred":[
        "Del Maestro"
    ],
    "name:unk_x_variant":[
        "Del Maestro"
    ],
    "qs:gn_adm0_cc":"MX",
    "qs:gn_local":4011743,
    "qs:gn_nam_loc":"Victoria de Durango, Durango, Durango, Durango, MX",
    "qs:gn_namadm1":"10",
    "qs:local_max":821,
    "qs:local_sum":1157,
    "qs:localhoods":5,
    "qs:name":"Del Maestro",
    "qs:name_adm0":"M\u00e9xico",
    "qs:name_adm1":"Durango",
    "qs:name_adm2":"Durango",
    "qs:name_local":"Victoria de Durango (durango)",
    "qs:photo_max":7,
    "qs:photo_sum":10,
    "qs:placetype":"Suburb",
    "qs:quad_count":2,
    "qs:woe_adm0":23424900,
    "qs:woe_adm1":2346273,
    "qs:woe_adm2":12599954,
    "qs:woe_lau":0,
    "qs:woe_local":55910400,
    "qs:woe_ver":"7.10.0",
    "wof:lang":[
        "spa"
    ],
    "wof:name":"Del Maestro",
    "wof:placetype":"neighbourhood"
},
  "geometry": {"coordinates":[-104.63653600000001,24.030411],"type":"Point"}
}