{
  "type": "Feature",
  "properties": {
    "gn:admin1_code":"5.0",
    "gn:asciiname":"Belgica",
    "gn:country_code":"MX",
    "gn:dem":502,
    "gn:feature_class":"P",
    "gn:feature_code":"PPL",
    "gn:name":"B\u00e9lgica",
    "gn:population":0,
    "gn:timezone":"America/Mexico_City",
    "iso:country":"MX",
    "name:spa_x_preferred":[
        "B\u00e9lgica"
    ],
    "wof:name":"Belgica",
    "wof:placetype":"locality"
},
  "geometry": {"coordinates":[-93.5664,16.68332],"type":"Point"}
}