{
  "type": "Feature",
  "properties": {
    "gn:admin1_code":"32",
    "gn:admin2_code":"23.0",
    "gn:asciiname":"La Mesa de Chavez",
    "gn:country_code":"MX",
    "gn:dem":2098,
    "gn:feature_class":"P",
    "gn:feature_code":"PPL",
    "gn:name":"La Mesa de Chavez",
    "gn:population":0,
    "gn:timezone":"America/Mexico_City",
    "iso:country":"MX",
    "wof:name":"La Mesa de Chavez",
    "wof:placetype":"locality"
},
  "geometry": {"coordinates":[-103.17534000000001,21.43679],"type":"Point"}
}