{
  "type": "Feature",
  "properties": {
    "gn:admin1_code":"32.0",
    "gn:admin2_code":"29.0",
    "gn:asciiname":"El Venadito",
    "gn:country_code":"MX",
    "gn:dem":2273,
    "gn:feature_class":"P",
    "gn:feature_code":"PPL",
    "gn:name":"El Venadito",
    "gn:population":0,
    "gn:timezone":"America/Mexico_City",
    "iso:country":"MX",
    "name:spa_x_preferred":[
        "El Venadito"
    ],
    "name:und_x_variant":[
        "El Vonadito",
        "Colonio Alegrete"
    ],
    "wof:name":"El Venadito",
    "wof:placetype":"locality"
},
  "geometry": {"coordinates":[-103.66963,24.03803],"type":"Point"}
}