{
  "type": "Feature",
  "properties": {
    "gn:admin1_code":"10.0",
    "gn:admin2_code":"9.0",
    "gn:asciiname":"Cienega del Conejo",
    "gn:country_code":"MX",
    "gn:dem":2621,
    "gn:feature_class":"P",
    "gn:feature_code":"PPL",
    "gn:name":"Ci\u00e9nega del Conejo",
    "gn:population":0,
    "gn:timezone":"America/Monterrey",
    "iso:country":"MX",
    "name:spa_x_preferred":[
        "Ci\u00e9nega del Conejo"
    ],
    "wof:name":"Cienega del Conejo",
    "wof:placetype":"locality"
},
  "geometry": {"coordinates":[-106.24487000000001,25.85904],"type":"Point"}
}