{
  "type": "Feature",
  "properties": {
    "gn:admin1_code":"18.0",
    "gn:admin2_code":"19.0",
    "gn:asciiname":"Las Tinajitas",
    "gn:country_code":"MX",
    "gn:dem":1763,
    "gn:feature_class":"P",
    "gn:feature_code":"PPL",
    "gn:name":"Las Tinajitas",
    "gn:population":0,
    "gn:timezone":"America/Mazatlan",
    "iso:country":"MX",
    "wof:name":"Las Tinajitas",
    "wof:placetype":"locality"
},
  "geometry": {"coordinates":[-104.24464999999999,21.56131],"type":"Point"}
}