{
  "type": "Feature",
  "properties": {
    "gn:admin1_code":"19.0",
    "gn:admin2_code":"48.0",
    "gn:asciiname":"El Hormiguero",
    "gn:country_code":"MX",
    "gn:dem":746,
    "gn:feature_class":"P",
    "gn:feature_code":"PPL",
    "gn:name":"El Hormiguero",
    "gn:population":0,
    "gn:timezone":"America/Monterrey",
    "iso:country":"MX",
    "name:spa_x_preferred":[
        "El Hormiguero"
    ],
    "wof:name":"El Hormiguero",
    "wof:placetype":"locality"
},
  "geometry": {"coordinates":[-100.46053000000001,25.61225],"type":"Point"}
}