{
  "type": "Feature",
  "properties": {
    "gn:admin1_code":"10",
    "gn:admin2_code":"34.0",
    "gn:asciiname":"El Tosiguay",
    "gn:country_code":"MX",
    "gn:dem":808,
    "gn:feature_class":"P",
    "gn:feature_code":"PPL",
    "gn:name":"El Tosiguay",
    "gn:population":6,
    "gn:timezone":"America/Monterrey",
    "iso:country":"MX",
    "wof:name":"El Tosiguay",
    "wof:placetype":"locality",
    "wof:population":6
},
  "geometry": {"coordinates":[-106.64452,24.79804],"type":"Point"}
}