{
  "type": "Feature",
  "properties": {
    "gn:admin1_code":"30",
    "gn:admin2_code":"32.0",
    "gn:asciiname":"Quimixotayo",
    "gn:country_code":"MX",
    "gn:dem":486,
    "gn:feature_class":"P",
    "gn:feature_code":"PPL",
    "gn:name":"Quimixotayo",
    "gn:population":7,
    "gn:timezone":"America/Mexico_City",
    "iso:country":"MX",
    "wof:name":"Quimixotayo",
    "wof:placetype":"locality",
    "wof:population":7
},
  "geometry": {"coordinates":[-95.13,18.34861],"type":"Point"}
}