{
  "type": "Feature",
  "properties": {
    "gn:admin1_code":"11.0",
    "gn:admin2_code":"14.0",
    "gn:asciiname":"Morillos",
    "gn:country_code":"MX",
    "gn:dem":2037,
    "gn:feature_class":"P",
    "gn:feature_code":"PPL",
    "gn:name":"Morillos",
    "gn:population":0,
    "gn:timezone":"America/Mexico_City",
    "iso:country":"MX",
    "name:spa_x_preferred":[
        "Morillos"
    ],
    "name:und_x_variant":[
        "Morillas"
    ],
    "wof:name":"Morillos",
    "wof:placetype":"locality"
},
  "geometry": {"coordinates":[-101.04125999999999,21.25857],"type":"Point"}
}