{
  "type": "Feature",
  "properties": {
    "gn:admin1_code":"26",
    "gn:admin2_code":"30.0",
    "gn:asciiname":"Noe",
    "gn:country_code":"MX",
    "gn:dem":275,
    "gn:feature_class":"P",
    "gn:feature_code":"PPL",
    "gn:name":"No\u00e9",
    "gn:population":0,
    "gn:timezone":"America/Hermosillo",
    "iso:country":"MX",
    "name:nds_x_preferred":[
        "Noe"
    ],
    "name:nld_x_preferred":[
        "Noe"
    ],
    "name:rus_x_preferred":[
        "\u041d\u043e\u044d"
    ],
    "name:slv_x_preferred":[
        "Noe"
    ],
    "name:spa_x_preferred":[
        "No\u00e9"
    ],
    "name:srp_x_preferred":[
        "\u041d\u043e\u0435"
    ],
    "name:ukr_x_preferred":[
        "\u041d\u043e\u0435"
    ],
    "wof:name":"Noe",
    "wof:placetype":"locality"
},
  "geometry": {"coordinates":[-110.8854,29.24868],"type":"Point"}
}