{
  "type": "Feature",
  "properties": {
    "gn:admin1_code":"14",
    "gn:admin2_code":"93.0",
    "gn:asciiname":"La Ge",
    "gn:country_code":"MX",
    "gn:dem":2033,
    "gn:feature_class":"P",
    "gn:feature_code":"PPL",
    "gn:name":"La Ge",
    "gn:population":5,
    "gn:timezone":"America/Mexico_City",
    "iso:country":"MX",
    "wof:name":"La Ge",
    "wof:placetype":"locality",
    "wof:population":5
},
  "geometry": {"coordinates":[-102.53194000000001,20.88778],"type":"Point"}
}