{
  "type": "Feature",
  "properties": {
    "gn:admin1_code":"6",
    "gn:admin2_code":"31",
    "gn:asciiname":"Santa Rita",
    "gn:country_code":"MX",
    "gn:dem":1970,
    "gn:feature_class":"P",
    "gn:feature_code":"PPL",
    "gn:name":"Santa Rita",
    "gn:population":11,
    "gn:timezone":"America/Chihuahua",
    "iso:country":"MX",
    "wof:name":"Santa Rita",
    "wof:placetype":"locality",
    "wof:population":11
},
  "geometry": {"coordinates":[-107.53308,28.66684],"type":"Point"}
}