{
  "type": "Feature",
  "properties": {
    "gn:admin1_code":"29",
    "gn:admin2_code":"6.0",
    "gn:asciiname":"Jagueey de Enmedio",
    "gn:country_code":"MX",
    "gn:dem":2709,
    "gn:feature_class":"P",
    "gn:feature_code":"PPL",
    "gn:name":"Jag\u00fcey de Enmedio",
    "gn:population":0,
    "gn:timezone":"America/Mexico_City",
    "iso:country":"MX",
    "name:spa_x_preferred":[
        "Jag\u00fcey de Enmedio"
    ],
    "wof:name":"Jagueey de Enmedio",
    "wof:placetype":"locality"
},
  "geometry": {"coordinates":[-98.60301,19.55079],"type":"Point"}
}