{
  "type": "Feature",
  "properties": {
    "gn:admin1_code":"20",
    "gn:admin2_code":"10.0",
    "gn:asciiname":"El Ocotal",
    "gn:country_code":"MX",
    "gn:dem":234,
    "gn:feature_class":"P",
    "gn:feature_code":"PPL",
    "gn:name":"El Ocotal",
    "gn:population":0,
    "gn:timezone":"America/Mexico_City",
    "iso:country":"MX",
    "name:spa_x_preferred":[
        "Ocotal Grande"
    ],
    "name:spa_x_variant":[
        "El Ocotal"
    ],
    "wof:name":"El Ocotal",
    "wof:placetype":"locality"
},
  "geometry": {"coordinates":[-94.96849,16.84595],"type":"Point"}
}