{
  "type": "Feature",
  "properties": {
    "gn:admin1_code":"1",
    "gn:admin2_code":"5.0",
    "gn:asciiname":"Rinconada el Country (Principal)",
    "gn:country_code":"MX",
    "gn:dem":1888,
    "gn:feature_class":"P",
    "gn:feature_code":"PPL",
    "gn:name":"Rinconada el Country (Principal)",
    "gn:population":7,
    "gn:timezone":"America/Mexico_City",
    "iso:country":"MX",
    "wof:name":"Rinconada el Country (Principal)",
    "wof:placetype":"locality",
    "wof:population":7
},
  "geometry": {"coordinates":[-102.34193999999999,21.93917],"type":"Point"}
}