{
  "type": "Feature",
  "properties": {
    "gn:admin1_code":"25.0",
    "gn:admin2_code":"17.0",
    "gn:asciiname":"Gallo Viejo",
    "gn:country_code":"MX",
    "gn:dem":192,
    "gn:feature_class":"P",
    "gn:feature_code":"PPL",
    "gn:name":"Gallo Viejo",
    "gn:population":10,
    "gn:timezone":"America/Mazatlan",
    "iso:country":"MX",
    "name:und_x_variant":[
        "El Gallo",
        "Gallo",
        "El Gallo Viejo",
        "Gallo Viejo"
    ],
    "wof:name":"Gallo Viejo",
    "wof:placetype":"locality",
    "wof:population":10
},
  "geometry": {"coordinates":[-108.5693,26.05774],"type":"Point"}
}