{
  "type": "Feature",
  "properties": {
    "gn:admin1_code":"14.0",
    "gn:admin2_code":"59.0",
    "gn:asciiname":"El Fresno",
    "gn:country_code":"MX",
    "gn:dem":2084,
    "gn:feature_class":"P",
    "gn:feature_code":"PPL",
    "gn:name":"El Fresno",
    "gn:population":0,
    "gn:timezone":"America/Mexico_City",
    "iso:country":"MX",
    "name:spa_x_preferred":[
        "El Fresno"
    ],
    "wof:name":"El Fresno",
    "wof:placetype":"locality"
},
  "geometry": {"coordinates":[-103.00103,19.83648],"type":"Point"}
}