{
  "type": "Feature",
  "properties": {
    "gn:admin1_code":"11.0",
    "gn:asciiname":"Tierra de Paz Casa Loma",
    "gn:country_code":"MX",
    "gn:dem":1926,
    "gn:feature_class":"P",
    "gn:feature_code":"PPL",
    "gn:name":"Tierra de Paz Casa Loma",
    "gn:population":0,
    "gn:timezone":"America/Mexico_City",
    "iso:country":"MX",
    "name:spa_x_preferred":[
        "Tierra de Paz Casa Loma"
    ],
    "wof:name":"Tierra de Paz Casa Loma",
    "wof:placetype":"locality"
},
  "geometry": {"coordinates":[-100.77576999999999,20.93968],"type":"Point"}
}