{
  "type": "Feature",
  "properties": {
    "gn:admin1_code":"14",
    "gn:admin2_code":"111.0",
    "gn:asciiname":"Nuestra Senora del Carmen (Las Pilas)",
    "gn:country_code":"MX",
    "gn:dem":1844,
    "gn:feature_class":"P",
    "gn:feature_code":"PPL",
    "gn:name":"Nuestra Se\u00f1ora del Carmen (Las Pilas)",
    "gn:population":9,
    "gn:timezone":"America/Mexico_City",
    "iso:country":"MX",
    "name:und_x_variant":[
        "Nuestra Se\u00f1ora del Carmen (Las Pilas)"
    ],
    "wof:name":"Nuestra Senora del Carmen (Las Pilas)",
    "wof:placetype":"locality",
    "wof:population":9
},
  "geometry": {"coordinates":[-102.65667000000001,21.07028],"type":"Point"}
}