{
  "type": "Feature",
  "properties": {
    "gn:admin1_code":"20",
    "gn:admin2_code":"406.0",
    "gn:asciiname":"San Agustin",
    "gn:country_code":"MX",
    "gn:dem":462,
    "gn:feature_class":"P",
    "gn:feature_code":"PPL",
    "gn:name":"San Agust\u00edn",
    "gn:population":147,
    "gn:timezone":"America/Mexico_City",
    "iso:country":"MX",
    "name:und_x_variant":[
        "San Agust\u00edn"
    ],
    "wof:name":"San Agustin",
    "wof:placetype":"locality",
    "wof:population":147
},
  "geometry": {"coordinates":[-96.73972000000001,18.27167],"type":"Point"}
}