{
  "type": "Feature",
  "properties": {
    "gn:admin1_code":"5.0",
    "gn:asciiname":"Nuestro Senor de Esquipulas",
    "gn:country_code":"MX",
    "gn:dem":1316,
    "gn:feature_class":"P",
    "gn:feature_code":"PPL",
    "gn:name":"Nuestro Se\u00f1or de Esquipulas",
    "gn:population":0,
    "gn:timezone":"America/Mexico_City",
    "iso:country":"MX",
    "name:spa_x_preferred":[
        "Nuestro Se\u00f1or de Esquipulas"
    ],
    "wof:name":"Nuestro Senor de Esquipulas",
    "wof:placetype":"locality"
},
  "geometry": {"coordinates":[-92.01499,16.79003],"type":"Point"}
}