{
  "type": "Feature",
  "properties": {
    "gn:admin1_code":"5.0",
    "gn:asciiname":"La Pomarrosa",
    "gn:country_code":"MX",
    "gn:dem":60,
    "gn:feature_class":"P",
    "gn:feature_code":"PPL",
    "gn:name":"La Pomarrosa",
    "gn:population":0,
    "gn:timezone":"America/Mexico_City",
    "iso:country":"MX",
    "name:spa_x_preferred":[
        "La Pomarrosa"
    ],
    "wof:name":"La Pomarrosa",
    "wof:placetype":"locality"
},
  "geometry": {"coordinates":[-91.9983,17.57769],"type":"Point"}
}