{
  "type": "Feature",
  "properties": {
    "gn:admin1_code":"20",
    "gn:admin2_code":"6.0",
    "gn:asciiname":"Rancho la Esperanza",
    "gn:country_code":"MX",
    "gn:dem":2178,
    "gn:feature_class":"P",
    "gn:feature_code":"PPL",
    "gn:name":"Rancho la Esperanza",
    "gn:population":5,
    "gn:timezone":"America/Mexico_City",
    "iso:country":"MX",
    "wof:name":"Rancho la Esperanza",
    "wof:placetype":"locality",
    "wof:population":5
},
  "geometry": {"coordinates":[-97.20083,17.45528],"type":"Point"}
}