{
  "type": "Feature",
  "properties": {
    "gn:admin1_code":"10",
    "gn:admin2_code":"12",
    "gn:asciiname":"El Pozo (Nestor Rodriguez)",
    "gn:country_code":"MX",
    "gn:dem":1138,
    "gn:feature_class":"P",
    "gn:feature_code":"PPL",
    "gn:name":"El Pozo (N\u00e9stor Rodr\u00edguez)",
    "gn:population":12,
    "gn:timezone":"America/Monterrey",
    "iso:country":"MX",
    "name:und_x_variant":[
        "El Pozo (N\u00e9stor Rodr\u00edguez)"
    ],
    "wof:name":"El Pozo (Nestor Rodriguez)",
    "wof:placetype":"locality",
    "wof:population":12
},
  "geometry": {"coordinates":[-103.51367,25.51473],"type":"Point"}
}