{
  "type": "Feature",
  "properties": {
    "gn:admin1_code":"14",
    "gn:admin2_code":"61.0",
    "gn:asciiname":"San Miguel (San Miguel Huaixtita)",
    "gn:country_code":"MX",
    "gn:dem":1558,
    "gn:feature_class":"P",
    "gn:feature_code":"PPL",
    "gn:name":"San Miguel (San Miguel Huaixtita)",
    "gn:population":539,
    "gn:timezone":"America/Mexico_City",
    "iso:country":"MX",
    "wof:name":"San Miguel (San Miguel Huaixtita)",
    "wof:placetype":"locality",
    "wof:population":539
},
  "geometry": {"coordinates":[-104.32111,22.07028],"type":"Point"}
}