{
  "type": "Feature",
  "properties": {
    "gn:admin1_code":"5.0",
    "gn:asciiname":"Cinco de Mayo",
    "gn:country_code":"MX",
    "gn:dem":1485,
    "gn:feature_class":"P",
    "gn:feature_code":"PPL",
    "gn:name":"Cinco de Mayo",
    "gn:population":0,
    "gn:timezone":"America/Mexico_City",
    "iso:country":"MX",
    "name:spa_x_preferred":[
        "Cinco de Mayo"
    ],
    "wof:name":"Cinco de Mayo",
    "wof:placetype":"locality"
},
  "geometry": {"coordinates":[-92.45757,15.6581],"type":"Point"}
}