{
  "type": "Feature",
  "properties": {
    "gn:admin1_code":"20",
    "gn:admin2_code":"202",
    "gn:asciiname":"San Jose Costa Rica",
    "gn:country_code":"MX",
    "gn:dem":827,
    "gn:feature_class":"P",
    "gn:feature_code":"PPL",
    "gn:name":"San Jos\u00e9 Costa Rica",
    "gn:population":15,
    "gn:timezone":"America/Mexico_City",
    "iso:country":"MX",
    "name:und_x_variant":[
        "San Jos\u00e9 Costa Rica"
    ],
    "wof:name":"San Jose Costa Rica",
    "wof:placetype":"locality",
    "wof:population":15
},
  "geometry": {"coordinates":[-97.08806,16.14222],"type":"Point"}
}