{
  "type": "Feature",
  "properties": {
    "gn:admin1_code":"10",
    "gn:admin2_code":"13.0",
    "gn:asciiname":"Tolimpa",
    "gn:country_code":"MX",
    "gn:dem":1176,
    "gn:feature_class":"P",
    "gn:feature_code":"PPL",
    "gn:name":"Tolimpa",
    "gn:population":0,
    "gn:timezone":"America/Monterrey",
    "iso:country":"MX",
    "name:spa_x_preferred":[
        "Tolimpa"
    ],
    "wof:name":"Tolimpa",
    "wof:placetype":"locality"
},
  "geometry": {"coordinates":[-104.08749,26.53174000000001],"type":"Point"}
}