{
  "type": "Feature",
  "properties": {
    "gn:admin1_code":"12",
    "gn:admin2_code":"34.0",
    "gn:asciiname":"Rancho la Tijera",
    "gn:country_code":"MX",
    "gn:dem":1166,
    "gn:feature_class":"P",
    "gn:feature_code":"PPL",
    "gn:name":"Rancho la Tijera",
    "gn:population":7,
    "gn:timezone":"America/Mexico_City",
    "iso:country":"MX",
    "wof:name":"Rancho la Tijera",
    "wof:placetype":"locality",
    "wof:population":7
},
  "geometry": {"coordinates":[-99.28628999999999,18.24657],"type":"Point"}
}