{
  "type": "Feature",
  "properties": {
    "gn:admin1_code":"21.0",
    "gn:admin2_code":"64.0",
    "gn:asciiname":"Los Pelis",
    "gn:country_code":"MX",
    "gn:dem":215,
    "gn:feature_class":"P",
    "gn:feature_code":"PPL",
    "gn:name":"Los Pelis",
    "gn:population":0,
    "gn:timezone":"America/Mexico_City",
    "iso:country":"MX",
    "name:spa_x_preferred":[
        "Los Pelis"
    ],
    "wof:name":"Los Pelis",
    "wof:placetype":"locality"
},
  "geometry": {"coordinates":[-97.77285000000001,20.6765],"type":"Point"}
}