{
  "type": "Feature",
  "properties": {
    "gn:admin1_code":"30",
    "gn:admin2_code":"1",
    "gn:asciiname":"El Muneco",
    "gn:country_code":"MX",
    "gn:dem":2586,
    "gn:feature_class":"P",
    "gn:feature_code":"PPL",
    "gn:name":"El Mu\u00f1eco",
    "gn:population":22,
    "gn:timezone":"America/Mexico_City",
    "iso:country":"MX",
    "name:und_x_variant":[
        "El Mu\u00f1eco"
    ],
    "wof:name":"El Muneco",
    "wof:placetype":"locality",
    "wof:population":22
},
  "geometry": {"coordinates":[-97.05028,19.58083],"type":"Point"}
}