{
  "type": "Feature",
  "properties": {
    "gn:admin1_code":"24",
    "gn:admin2_code":"57.0",
    "gn:asciiname":"Pilaxtla",
    "gn:country_code":"MX",
    "gn:dem":586,
    "gn:feature_class":"P",
    "gn:feature_code":"PPL",
    "gn:name":"Pilaxtla",
    "gn:population":121,
    "gn:timezone":"America/Mexico_City",
    "iso:country":"MX",
    "wof:name":"Pilaxtla",
    "wof:placetype":"locality",
    "wof:population":121
},
  "geometry": {"coordinates":[-98.85833,21.30444],"type":"Point"}
}