{
  "type": "Feature",
  "properties": {
    "gn:admin1_code":"6",
    "gn:admin2_code":"63.0",
    "gn:asciiname":"La Culebra",
    "gn:country_code":"MX",
    "gn:dem":1710,
    "gn:feature_class":"P",
    "gn:feature_code":"PPL",
    "gn:name":"La Culebra",
    "gn:population":10,
    "gn:timezone":"America/Chihuahua",
    "iso:country":"MX",
    "name:spa_x_preferred":[
        "La Culebra"
    ],
    "wof:name":"La Culebra",
    "wof:placetype":"locality",
    "wof:population":10
},
  "geometry": {"coordinates":[-107.97064,28.81564],"type":"Point"}
}