{
  "type": "Feature",
  "properties": {
    "gn:admin1_code":"16.0",
    "gn:asciiname":"Canada Verde",
    "gn:country_code":"MX",
    "gn:dem":2522,
    "gn:feature_class":"P",
    "gn:feature_code":"PPL",
    "gn:name":"Ca\u00f1ada Verde",
    "gn:population":0,
    "gn:timezone":"America/Mexico_City",
    "iso:country":"MX",
    "name:spa_x_preferred":[
        "Ca\u00f1ada Verde"
    ],
    "wof:name":"Canada Verde",
    "wof:placetype":"locality"
},
  "geometry": {"coordinates":[-100.65029,19.58857],"type":"Point"}
}