{
  "type": "Feature",
  "properties": {
    "gn:admin1_code":"6.0",
    "gn:admin2_code":"44.0",
    "gn:asciiname":"El Terrero",
    "gn:cc2":"MX",
    "gn:country_code":"MX",
    "gn:dem":1786,
    "gn:feature_class":"P",
    "gn:feature_code":"PPL",
    "gn:name":"El Terrero",
    "gn:population":14,
    "gn:timezone":"America/Chihuahua",
    "iso:country":"MX",
    "name:und_x_variant":[
        "Tererro",
        "El Terrero",
        "El Terrero Abajo"
    ],
    "wof:name":"El Terrero",
    "wof:placetype":"locality",
    "wof:population":14
},
  "geometry": {"coordinates":[-105.62575,26.70233],"type":"Point"}
}