{
  "type": "Feature",
  "properties": {
    "gn:admin1_code":"7",
    "gn:admin2_code":"9.0",
    "gn:asciiname":"Los Cuates",
    "gn:country_code":"MX",
    "gn:dem":1110,
    "gn:feature_class":"P",
    "gn:feature_code":"PPL",
    "gn:name":"Los Cuates",
    "gn:population":5,
    "gn:timezone":"America/Monterrey",
    "iso:country":"MX",
    "wof:name":"Los Cuates",
    "wof:placetype":"locality",
    "wof:population":5
},
  "geometry": {"coordinates":[-103.29702,25.77527000000001],"type":"Point"}
}