{
  "type": "Feature",
  "properties": {
    "gn:admin1_code":"31",
    "gn:admin2_code":"96.0",
    "gn:asciiname":"Dos Culebras",
    "gn:country_code":"MX",
    "gn:dem":22,
    "gn:feature_class":"P",
    "gn:feature_code":"PPL",
    "gn:name":"Dos Culebras",
    "gn:population":5,
    "gn:timezone":"America/Merida",
    "iso:country":"MX",
    "wof:name":"Dos Culebras",
    "wof:placetype":"locality",
    "wof:population":5
},
  "geometry": {"coordinates":[-87.93611,21.11389],"type":"Point"}
}