{
  "type": "Feature",
  "properties": {
    "gn:admin1_code":"26.0",
    "gn:admin2_code":"4.0",
    "gn:asciiname":"La Garrapata",
    "gn:country_code":"MX",
    "gn:dem":883,
    "gn:feature_class":"P",
    "gn:feature_code":"PPL",
    "gn:name":"La Garrapata",
    "gn:population":0,
    "gn:timezone":"America/Hermosillo",
    "iso:country":"MX",
    "name:und_x_variant":[
        "Garrapata",
        "Rancho La Garrapata",
        "La Garrapata"
    ],
    "wof:name":"La Garrapata",
    "wof:placetype":"locality"
},
  "geometry": {"coordinates":[-111.68097,31.42555],"type":"Point"}
}