{
  "type": "Feature",
  "properties": {
    "gn:admin1_code":"8.0",
    "gn:admin2_code":"6.0",
    "gn:asciiname":"Agua de la Virgen",
    "gn:country_code":"MX",
    "gn:dem":145,
    "gn:feature_class":"P",
    "gn:feature_code":"PPL",
    "gn:name":"Agua de la Virgen",
    "gn:population":0,
    "gn:timezone":"America/Mexico_City",
    "iso:country":"MX",
    "wof:name":"Agua de la Virgen",
    "wof:placetype":"locality"
},
  "geometry": {"coordinates":[-103.62635,18.93643],"type":"Point"}
}