{
  "type": "Feature",
  "properties": {
    "gn:admin1_code":"5",
    "gn:admin2_code":"108.0",
    "gn:asciiname":"El Lucero",
    "gn:cc2":"MX",
    "gn:country_code":"MX",
    "gn:dem":580,
    "gn:feature_class":"P",
    "gn:feature_code":"PPL",
    "gn:name":"El Lucero",
    "gn:population":1,
    "gn:timezone":"America/Mexico_City",
    "iso:country":"MX",
    "name:und_x_variant":[
        "Lucero",
        "El Lucero"
    ],
    "wof:name":"El Lucero",
    "wof:placetype":"locality",
    "wof:population":1
},
  "geometry": {"coordinates":[-93.26333,16.27889],"type":"Point"}
}