{
  "type": "Feature",
  "properties": {
    "gn:admin1_code":"20",
    "gn:admin2_code":"494",
    "gn:asciiname":"Cuatro Caminos",
    "gn:country_code":"MX",
    "gn:dem":2671,
    "gn:feature_class":"P",
    "gn:feature_code":"PPL",
    "gn:name":"Cuatro Caminos",
    "gn:population":29,
    "gn:timezone":"America/Mexico_City",
    "iso:country":"MX",
    "wof:name":"Cuatro Caminos",
    "wof:placetype":"locality",
    "wof:population":29
},
  "geometry": {"coordinates":[-96.97389,17.00361],"type":"Point"}
}