{
  "type": "Feature",
  "properties": {
    "gn:admin1_code":"10",
    "gn:admin2_code":"14",
    "gn:asciiname":"Acatita",
    "gn:country_code":"MX",
    "gn:dem":1556,
    "gn:feature_class":"P",
    "gn:feature_code":"PPL",
    "gn:name":"Acatita",
    "gn:population":42,
    "gn:timezone":"America/Monterrey",
    "iso:country":"MX",
    "wof:name":"Acatita",
    "wof:placetype":"locality",
    "wof:population":42
},
  "geometry": {"coordinates":[-104.32356,23.66716],"type":"Point"}
}