{
  "type": "Feature",
  "properties": {
    "gn:admin1_code":"7",
    "gn:admin2_code":"35.0",
    "gn:asciiname":"Otto",
    "gn:country_code":"MX",
    "gn:dem":1309,
    "gn:feature_class":"P",
    "gn:feature_code":"PPL",
    "gn:name":"Otto",
    "gn:population":0,
    "gn:timezone":"America/Monterrey",
    "iso:country":"MX",
    "name:bre_x_preferred":[
        "Otto"
    ],
    "name:dan_x_preferred":[
        "Otto"
    ],
    "name:deu_x_preferred":[
        "Otto"
    ],
    "name:epo_x_preferred":[
        "Otto"
    ],
    "name:est_x_preferred":[
        "Otto"
    ],
    "name:fin_x_preferred":[
        "Otto"
    ],
    "name:jpn_x_preferred":[
        "\u30aa\u30c3\u30c8\u30fc"
    ],
    "name:lat_x_preferred":[
        "Otto"
    ],
    "name:nno_x_preferred":[
        "Otto"
    ],
    "name:nor_x_preferred":[
        "Otto"
    ],
    "name:pol_x_preferred":[
        "Otto"
    ],
    "name:spa_x_preferred":[
        "Otto"
    ],
    "name:swe_x_preferred":[
        "Otto"
    ],
    "name:ukr_x_preferred":[
        "\u041e\u0442\u0442\u043e\u043d"
    ],
    "wof:name":"Otto",
    "wof:placetype":"locality"
},
  "geometry": {"coordinates":[-103.28270000000001,25.08212],"type":"Point"}
}