{
  "type": "Feature",
  "properties": {
    "gn:admin1_code":"7",
    "gn:admin2_code":"35.0",
    "gn:asciiname":"Otto",
    "gn:country_code":"MX",
    "gn:dem":1309,
    "gn:feature_class":"P",
    "gn:feature_code":"PPL",
    "gn:name":"Otto",
    "gn:population":0,
    "gn:timezone":"America/Monterrey",
    "iso:country":"MX",
    "name:spa_x_preferred":[
        "Otto"
    ],
    "wof:name":"Otto",
    "wof:placetype":"locality"
},
  "geometry": {"coordinates":[-103.28270000000001,25.08212],"type":"Point"}
}