{
  "type": "Feature",
  "properties": {
    "gn:gn_country":"MX",
    "gn:gn_fcode":"PPL",
    "gn:gn_pop":4100,
    "gn:population":2488,
    "iso:country":"MX",
    "name:ceb_x_preferred":[
        "Zacualpan"
    ],
    "name:deu_x_preferred":[
        "Zacualpan"
    ],
    "name:rus_x_preferred":[
        "\u0421\u0430\u043a\u0443\u0430\u043b\u044c\u043f\u0430\u043d"
    ],
    "name:sco_x_preferred":[
        "Zacualpan"
    ],
    "name:spa_x_preferred":[
        "Zacualpan"
    ],
    "name:swe_x_preferred":[
        "Zacualpan"
    ],
    "name:unk_x_variant":[
        "Zacualpa"
    ],
    "qs_pg:aaroncc":"MX",
    "qs_pg:gn_country":"MX",
    "qs_pg:gn_fcode":"PPL",
    "qs_pg:gn_pop":4100,
    "qs_pg:name":"Zacualpan",
    "qs_pg:name_adm0":"M\u00e9xico",
    "qs_pg:name_adm1":"Guerrero",
    "qs_pg:photos_9k":1,
    "qs_pg:photos_9r":1,
    "qs_pg:photos_all":1,
    "qs_pg:photos_sr":0,
    "qs_pg:pop_sr":4,
    "qs_pg:qs_pg_placetype":"locality",
    "qs_pg:qs_pg_placetype_gp":"Town",
    "qs_pg:woe_adm0":23424900,
    "woe:adm0_id":23424900,
    "woe:name_adm0":"M\u00e9xico",
    "woe:name_adm1":"Guerrero",
    "woe:placetype":"Town",
    "wof:name":"Zacualpan",
    "wof:placetype":"locality",
    "wof:population":2488
},
  "geometry": {"coordinates":[-100.32594,17.08895],"type":"Point"}
}