{
  "type": "Feature",
  "properties": {
    "gn:admin1_code":"14.0",
    "gn:admin2_code":"86.0",
    "gn:asciiname":"El Rosario",
    "gn:country_code":"MX",
    "gn:dem":2239,
    "gn:feature_class":"P",
    "gn:feature_code":"PPL",
    "gn:name":"El Rosario",
    "gn:population":0,
    "gn:timezone":"America/Mexico_City",
    "iso:country":"MX",
    "name:bre_x_preferred":[
        "El Rosario"
    ],
    "name:ceb_x_preferred":[
        "El Rosario"
    ],
    "name:fra_x_preferred":[
        "El Rosario"
    ],
    "name:ita_x_preferred":[
        "El Rosario"
    ],
    "name:msa_x_preferred":[
        "El Rosario"
    ],
    "name:pol_x_preferred":[
        "El Rosario"
    ],
    "name:por_x_preferred":[
        "El Rosario"
    ],
    "name:rus_x_preferred":[
        "\u042d\u043b\u044c-\u0420\u043e\u0441\u0430\u0440\u0438\u043e"
    ],
    "name:sco_x_preferred":[
        "El Rosario"
    ],
    "name:spa_x_preferred":[
        "El Rosario"
    ],
    "name:srp_x_preferred":[
        "\u0415\u043b \u0420\u043e\u0441\u0430\u0440\u0438\u043e"
    ],
    "name:swe_x_preferred":[
        "El Rosario"
    ],
    "name:vie_x_preferred":[
        "El Rosario"
    ],
    "name:war_x_preferred":[
        "El Rosario"
    ],
    "wof:name":"El Rosario",
    "wof:placetype":"locality"
},
  "geometry": {"coordinates":[-103.71317999999999,19.90216],"type":"Point"}
}