{
  "type": "Feature",
  "properties": {
    "gn:admin1_code":"21",
    "gn:admin2_code":"25",
    "gn:asciiname":"Cerro de Malintepec",
    "gn:country_code":"MX",
    "gn:dem":275,
    "gn:feature_class":"P",
    "gn:feature_code":"PPL",
    "gn:name":"Cerro de Malintepec",
    "gn:population":20,
    "gn:timezone":"America/Mexico_City",
    "iso:country":"MX",
    "wof:name":"Cerro de Malintepec",
    "wof:placetype":"locality",
    "wof:population":20
},
  "geometry": {"coordinates":[-97.40857,20.04407],"type":"Point"}
}