{
  "type": "Feature",
  "properties": {
    "gn:admin1_code":"14",
    "gn:admin2_code":"124.0",
    "gn:asciiname":"La Cebolleta",
    "gn:country_code":"MX",
    "gn:dem":1684,
    "gn:feature_class":"P",
    "gn:feature_code":"PPL",
    "gn:name":"La Cebolleta",
    "gn:population":68,
    "gn:timezone":"America/Mexico_City",
    "iso:country":"MX",
    "wof:name":"La Cebolleta",
    "wof:placetype":"locality",
    "wof:population":68
},
  "geometry": {"coordinates":[-103.01000000000001,20.6275],"type":"Point"}
}