{
  "type": "Feature",
  "properties": {
    "gn:admin1_code":"16",
    "gn:admin2_code":"34",
    "gn:asciiname":"El Tejocote Redondo",
    "gn:country_code":"MX",
    "gn:dem":2570,
    "gn:feature_class":"P",
    "gn:feature_code":"PPL",
    "gn:name":"El Tejocote Redondo",
    "gn:population":37,
    "gn:timezone":"America/Mexico_City",
    "iso:country":"MX",
    "wof:name":"El Tejocote Redondo",
    "wof:placetype":"locality",
    "wof:population":37
},
  "geometry": {"coordinates":[-100.64333000000001,19.51194],"type":"Point"}
}