{
  "type": "Feature",
  "properties": {
    "gn:admin1_code":"24.0",
    "gn:admin2_code":"21.0",
    "gn:asciiname":"Iglesia el Desierto",
    "gn:country_code":"MX",
    "gn:dem":2040,
    "gn:feature_class":"P",
    "gn:feature_code":"PPL",
    "gn:name":"Iglesia el Desierto",
    "gn:population":0,
    "gn:timezone":"America/Mexico_City",
    "iso:country":"MX",
    "name:spa_x_preferred":[
        "Iglesia el Desierto"
    ],
    "wof:name":"Iglesia el Desierto",
    "wof:placetype":"locality"
},
  "geometry": {"coordinates":[-101.09056,22.15393],"type":"Point"}
}