{
  "type": "Feature",
  "properties": {
    "gn:admin1_code":"31",
    "gn:admin2_code":"96.0",
    "gn:asciiname":"Los Cedros",
    "gn:country_code":"MX",
    "gn:dem":10,
    "gn:feature_class":"P",
    "gn:feature_code":"PPL",
    "gn:name":"Los Cedros",
    "gn:population":0,
    "gn:timezone":"America/Merida",
    "iso:country":"MX",
    "name:spa_x_preferred":[
        "Los Cedros"
    ],
    "wof:name":"Los Cedros",
    "wof:placetype":"locality"
},
  "geometry": {"coordinates":[-87.70941999999999,21.34567],"type":"Point"}
}