{
  "type": "Feature",
  "properties": {
    "gn:admin1_code":"20",
    "gn:admin2_code":"184.0",
    "gn:asciiname":"Centro de Poblacion Rosario Ibarra de Piedra",
    "gn:country_code":"MX",
    "gn:dem":40,
    "gn:feature_class":"P",
    "gn:feature_code":"PPL",
    "gn:name":"Centro de Poblaci\u00f3n Rosario Ibarra de Piedra",
    "gn:population":171,
    "gn:timezone":"America/Mexico_City",
    "iso:country":"MX",
    "name:und_x_variant":[
        "Centro de Poblaci\u00f3n Rosario Ibarra de Piedra"
    ],
    "wof:name":"Centro de Poblacion Rosario Ibarra de Piedra",
    "wof:placetype":"locality",
    "wof:population":171
},
  "geometry": {"coordinates":[-96.17972,18.01528],"type":"Point"}
}