{
  "type": "Feature",
  "properties": {
    "gn:admin1_code":"23",
    "gn:admin2_code":"6.0",
    "gn:asciiname":"Pozo Pirata",
    "gn:country_code":"MX",
    "gn:dem":73,
    "gn:feature_class":"P",
    "gn:feature_code":"PPL",
    "gn:name":"Pozo Pirata",
    "gn:population":0,
    "gn:timezone":"America/Cancun",
    "iso:country":"MX",
    "name:spa_x_preferred":[
        "Pozo Pirata"
    ],
    "wof:name":"Pozo Pirata",
    "wof:placetype":"locality"
},
  "geometry": {"coordinates":[-88.89107,19.61612],"type":"Point"}
}