{
  "type": "Feature",
  "properties": {
    "gn:admin1_code":"25",
    "gn:admin2_code":"10.0",
    "gn:asciiname":"Taxtes",
    "gn:country_code":"MX",
    "gn:dem":22,
    "gn:feature_class":"P",
    "gn:feature_code":"PPL",
    "gn:name":"Taxtes",
    "gn:population":0,
    "gn:timezone":"America/Mazatlan",
    "iso:country":"MX",
    "name:spa_x_preferred":[
        "Taxtes"
    ],
    "name:und_x_variant":[
        "Los Taxtes"
    ],
    "wof:name":"Taxtes",
    "wof:placetype":"locality"
},
  "geometry": {"coordinates":[-108.93545,25.91625],"type":"Point"}
}