{
  "type": "Feature",
  "properties": {
    "gn:admin1_code":"5",
    "gn:admin2_code":"46.0",
    "gn:asciiname":"Chapultepec",
    "gn:country_code":"MX",
    "gn:dem":606,
    "gn:feature_class":"P",
    "gn:feature_code":"PPL",
    "gn:name":"Chapultepec",
    "gn:population":4,
    "gn:timezone":"America/Mexico_City",
    "iso:country":"MX",
    "wof:name":"Chapultepec",
    "wof:placetype":"locality",
    "wof:population":4
},
  "geometry": {"coordinates":[-93.54000000000001,16.57889],"type":"Point"}
}