{
  "type": "Feature",
  "properties": {
    "gn:admin1_code":"20",
    "gn:admin2_code":"526.0",
    "gn:asciiname":"San Marcos Zapotalito (El Zapote)",
    "gn:country_code":"MX",
    "gn:dem":236,
    "gn:feature_class":"P",
    "gn:feature_code":"PPL",
    "gn:name":"San Marcos Zapotalito (El Zapote)",
    "gn:population":75,
    "gn:timezone":"America/Mexico_City",
    "iso:country":"MX",
    "wof:name":"San Marcos Zapotalito (El Zapote)",
    "wof:placetype":"locality",
    "wof:population":75
},
  "geometry": {"coordinates":[-97.20389,16.01361],"type":"Point"}
}