{
  "type": "Feature",
  "properties": {
    "iso:country":"MX",
    "name:spa_x_preferred":[
        "Barrio Santa Monica"
    ],
    "qs:gn_adm0_cc":"MX",
    "qs:gn_local":3523686,
    "qs:gn_nam_loc":"Malinalco, Malinalco, Mexico, MX",
    "qs:gn_namadm1":"15",
    "qs:local_max":303,
    "qs:local_sum":305,
    "qs:localhoods":2,
    "qs:name":"Barrio Santa Monica",
    "qs:name_adm0":"M\u00e9xico",
    "qs:name_adm1":"Mexico",
    "qs:name_adm2":"Malinalco",
    "qs:name_local":"Malinalco",
    "qs:photo_max":79,
    "qs:photo_sum":303,
    "qs:placetype":"Suburb",
    "qs:quad_count":16,
    "qs:woe_adm0":23424900,
    "qs:woe_adm1":2346278,
    "qs:woe_adm2":12600372,
    "qs:woe_lau":0,
    "qs:woe_local":132786,
    "qs:woe_ver":"7.10.0",
    "wof:lang":[
        "spa"
    ],
    "wof:name":"Barrio Santa Monica",
    "wof:placetype":"neighbourhood"
},
  "geometry": {"coordinates":[-99.49956400000001,18.949456],"type":"Point"}
}