{
  "type": "Feature",
  "properties": {
    "gn:admin1_code":"6",
    "gn:admin2_code":"5.0",
    "gn:asciiname":"El Milagro",
    "gn:country_code":"MX",
    "gn:dem":1263,
    "gn:feature_class":"P",
    "gn:feature_code":"PPL",
    "gn:name":"El Milagro",
    "gn:population":0,
    "gn:timezone":"America/Chihuahua",
    "iso:country":"MX",
    "name:spa_x_preferred":[
        "El Milagro"
    ],
    "name:und_x_variant":[
        "Milagro"
    ],
    "wof:name":"El Milagro",
    "wof:placetype":"locality"
},
  "geometry": {"coordinates":[-108.1664,31.63942],"type":"Point"}
}