{
  "type": "Feature",
  "properties": {
    "gn:admin1_code":"22",
    "gn:admin2_code":"2.0",
    "gn:asciiname":"Agua Cazuela",
    "gn:country_code":"MX",
    "gn:dem":1289,
    "gn:feature_class":"P",
    "gn:feature_code":"PPL",
    "gn:name":"Agua Cazuela",
    "gn:population":5,
    "gn:timezone":"America/Mexico_City",
    "iso:country":"MX",
    "wof:name":"Agua Cazuela",
    "wof:placetype":"locality",
    "wof:population":5
},
  "geometry": {"coordinates":[-99.51778,21.13222],"type":"Point"}
}