{
  "type": "Feature",
  "properties": {
    "gn:admin1_code":"12.0",
    "gn:admin2_code":"27.0",
    "gn:asciiname":"Arcelia de los Libres (Chumbitaro)",
    "gn:country_code":"MX",
    "gn:dem":331,
    "gn:feature_class":"P",
    "gn:feature_code":"PPL",
    "gn:name":"Arcelia de los Libres (Chumb\u00edtaro)",
    "gn:population":134,
    "gn:timezone":"America/Mexico_City",
    "iso:country":"MX",
    "wof:name":"Arcelia de los Libres (Chumbitaro)",
    "wof:placetype":"locality",
    "wof:population":134
},
  "geometry": {"coordinates":[-100.70528,18.48611],"type":"Point"}
}