{
  "type": "Feature",
  "properties": {
    "gn:admin1_code":"20",
    "gn:admin2_code":"275.0",
    "gn:asciiname":"Chuxnaban",
    "gn:country_code":"MX",
    "gn:dem":570,
    "gn:feature_class":"P",
    "gn:feature_code":"PPL",
    "gn:name":"Chuxnaban",
    "gn:population":0,
    "gn:timezone":"America/Mexico_City",
    "iso:country":"MX",
    "name:spa_x_preferred":[
        "Chuxnaban"
    ],
    "name:spa_x_variant":[
        "Chuxnab\u00e1n Quetzaltepec"
    ],
    "wof:name":"Chuxnaban",
    "wof:placetype":"locality"
},
  "geometry": {"coordinates":[-95.83056000000001,17.01952],"type":"Point"}
}