{
  "type": "Feature",
  "properties": {
    "gn:admin1_code":"7.0",
    "gn:admin2_code":"24.0",
    "gn:asciiname":"Abrevadero",
    "gn:country_code":"MX",
    "gn:dem":1673,
    "gn:feature_class":"P",
    "gn:feature_code":"PPL",
    "gn:name":"Abrevadero",
    "gn:population":0,
    "gn:timezone":"America/Monterrey",
    "iso:country":"MX",
    "name:spa_x_preferred":[
        "Abrevadero"
    ],
    "wof:name":"Abrevadero",
    "wof:placetype":"locality"
},
  "geometry": {"coordinates":[-102.06393,25.4067],"type":"Point"}
}