{
  "type": "Feature",
  "properties": {
    "gn:admin1_code":"20",
    "gn:admin2_code":"24.0",
    "gn:asciiname":"La Orilla",
    "gn:country_code":"MX",
    "gn:dem":1779,
    "gn:feature_class":"P",
    "gn:feature_code":"PPL",
    "gn:name":"La Orilla",
    "gn:population":154,
    "gn:timezone":"America/Mexico_City",
    "iso:country":"MX",
    "wof:name":"La Orilla",
    "wof:placetype":"locality",
    "wof:population":154
},
  "geometry": {"coordinates":[-96.83167,17.95443999999999],"type":"Point"}
}