{
  "type": "Feature",
  "properties": {
    "gn:admin1_code":"20",
    "gn:admin2_code":"6",
    "gn:asciiname":"Cantera",
    "gn:country_code":"MX",
    "gn:dem":2167,
    "gn:feature_class":"P",
    "gn:feature_code":"PPL",
    "gn:name":"Cantera",
    "gn:population":22,
    "gn:timezone":"America/Mexico_City",
    "iso:country":"MX",
    "name:glg_x_preferred":[
        "Canteira"
    ],
    "name:ita_x_preferred":[
        "Cantera"
    ],
    "name:jpn_x_preferred":[
        "\u30ab\u30f3\u30c6\u30e9"
    ],
    "name:lat_x_preferred":[
        "Cantera"
    ],
    "name:nld_x_preferred":[
        "Cantera"
    ],
    "name:rus_x_preferred":[
        "\u041a\u0430\u043d\u0442\u0435\u0440\u0430"
    ],
    "name:ukr_x_preferred":[
        "\u041a\u0430\u043d\u0442\u0435\u0440\u0430"
    ],
    "wof:name":"Cantera",
    "wof:placetype":"locality",
    "wof:population":22
},
  "geometry": {"coordinates":[-97.20972,17.43278],"type":"Point"}
}