{
  "type": "Feature",
  "properties": {
    "gn:admin1_code":"5",
    "gn:admin2_code":"31.0",
    "gn:asciiname":"Chanoha",
    "gn:country_code":"MX",
    "gn:dem":902,
    "gn:feature_class":"P",
    "gn:feature_code":"PPL",
    "gn:name":"Chanoh\u00e1",
    "gn:population":8,
    "gn:timezone":"America/Mexico_City",
    "iso:country":"MX",
    "name:und_x_variant":[
        "Chanoh\u00e1"
    ],
    "wof:name":"Chanoha",
    "wof:placetype":"locality",
    "wof:population":8
},
  "geometry": {"coordinates":[-92.27833,17.09278],"type":"Point"}
}