{
  "type": "Feature",
  "properties": {
    "gn:admin1_code":"30",
    "gn:admin2_code":"58.0",
    "gn:asciiname":"Camaitlan",
    "gn:country_code":"MX",
    "gn:dem":134,
    "gn:feature_class":"P",
    "gn:feature_code":"PPL",
    "gn:name":"Camaitl\u00e1n",
    "gn:population":136,
    "gn:timezone":"America/Mexico_City",
    "iso:country":"MX",
    "name:und_x_variant":[
        "Tamaitl\u00e1n",
        "Camaitl\u00e1n"
    ],
    "wof:name":"Camaitlan",
    "wof:placetype":"locality",
    "wof:population":136
},
  "geometry": {"coordinates":[-98.0783,21.00114],"type":"Point"}
}