{
  "type": "Feature",
  "properties": {
    "gn:admin1_code":"32",
    "gn:admin2_code":"14.0",
    "gn:asciiname":"Pando Los Borregos",
    "gn:country_code":"MX",
    "gn:dem":1802,
    "gn:feature_class":"P",
    "gn:feature_code":"PPL",
    "gn:name":"Pando Los Borregos",
    "gn:population":0,
    "gn:timezone":"America/Mexico_City",
    "iso:country":"MX",
    "wof:name":"Pando Los Borregos",
    "wof:placetype":"locality"
},
  "geometry": {"coordinates":[-102.57329,24.23345],"type":"Point"}
}