{
  "type": "Feature",
  "properties": {
    "gn:admin1_code":"13",
    "gn:admin2_code":"63.0",
    "gn:asciiname":"Canada de Madero",
    "gn:cc2":"MX",
    "gn:country_code":"MX",
    "gn:dem":2128,
    "gn:feature_class":"P",
    "gn:feature_code":"PPL",
    "gn:name":"Ca\u00f1ada de Madero",
    "gn:population":0,
    "gn:timezone":"America/Mexico_City",
    "iso:country":"MX",
    "name:und_x_variant":[
        "Ca\u00f1ada de Madero Hidalgo",
        "Ca\u00f1ada de Madero"
    ],
    "wof:name":"Canada de Madero",
    "wof:placetype":"locality"
},
  "geometry": {"coordinates":[-99.39389,19.96528],"type":"Point"}
}