{
  "type": "Feature",
  "properties": {
    "iso:country":"MX",
    "name:cat_x_preferred":[
        "Independ\u00e8ncia"
    ],
    "name:ceb_x_preferred":[
        "Independencia"
    ],
    "name:deu_x_preferred":[
        "Independencia"
    ],
    "name:epo_x_preferred":[
        "Independencia"
    ],
    "name:fra_x_preferred":[
        "Independencia"
    ],
    "name:ita_x_preferred":[
        "Independencia"
    ],
    "name:kor_x_preferred":[
        "\uc778\ub370\ud39c\ub374\uc2dc\uc544"
    ],
    "name:nld_x_preferred":[
        "Independencia"
    ],
    "name:nor_x_preferred":[
        "Independencia"
    ],
    "name:rus_x_preferred":[
        "\u0418\u043d\u0434\u0435\u043f\u0435\u043d\u0434\u0435\u043d\u0441\u0438\u044f"
    ],
    "name:sco_x_preferred":[
        "Independencia"
    ],
    "name:spa_x_preferred":[
        "Independencia"
    ],
    "name:swe_x_preferred":[
        "Independencia"
    ],
    "name:ukr_x_preferred":[
        "\u0406\u043d\u0434\u0435\u043f\u0435\u043d\u0434\u0435\u043d\u0441\u0456\u044f"
    ],
    "qs:gn_adm0_cc":"MX",
    "qs:gn_local":3530103,
    "qs:gn_nam_loc":"san miguel de cozumel",
    "qs:gn_namadm1":"23",
    "qs:local_max":3537,
    "qs:local_sum":9431,
    "qs:localhoods":6,
    "qs:name":"Independencia",
    "qs:name_adm0":"M\u00e9xico",
    "qs:name_adm1":"Quintana Roo",
    "qs:name_adm2":"Cozumel",
    "qs:name_local":"San Miguel de Cozumel",
    "qs:photo_max":6,
    "qs:photo_sum":6,
    "qs:placetype":"Suburb",
    "qs:quad_count":1,
    "qs:woe_adm0":23424900,
    "qs:woe_adm1":2346286,
    "qs:woe_adm2":12601463,
    "qs:woe_lau":0,
    "qs:woe_local":144625,
    "qs:woe_ver":"7.10.0",
    "wof:lang":[
        "spa"
    ],
    "wof:name":"Independencia",
    "wof:placetype":"neighbourhood"
},
  "geometry": {"coordinates":[-86.954041,20.496492],"type":"Point"}
}