{
  "type": "Feature",
  "properties": {
    "gn:admin1_code":"30",
    "gn:admin2_code":"94.0",
    "gn:asciiname":"San Pablo",
    "gn:country_code":"MX",
    "gn:dem":124,
    "gn:feature_class":"P",
    "gn:feature_code":"PPL",
    "gn:name":"San Pablo",
    "gn:population":7,
    "gn:timezone":"America/Mexico_City",
    "iso:country":"MX",
    "wof:name":"San Pablo",
    "wof:placetype":"locality",
    "wof:population":7
},
  "geometry": {"coordinates":[-95.41472,17.98139],"type":"Point"}
}