{
  "type": "Feature",
  "properties": {
    "gn:admin1_code":"6.0",
    "gn:admin2_code":"7.0",
    "gn:asciiname":"El Treinta y Cuatro",
    "gn:country_code":"MX",
    "gn:dem":1912,
    "gn:feature_class":"P",
    "gn:feature_code":"PPL",
    "gn:name":"El Treinta y Cuatro",
    "gn:population":0,
    "gn:timezone":"America/Chihuahua",
    "iso:country":"MX",
    "name:spa_x_preferred":[
        "El Treinta y Cuatro"
    ],
    "wof:name":"El Treinta y Cuatro",
    "wof:placetype":"locality"
},
  "geometry": {"coordinates":[-106.15371,26.84244],"type":"Point"}
}