{
  "type": "Feature",
  "properties": {
    "gn:admin1_code":"31",
    "gn:admin2_code":"52.0",
    "gn:asciiname":"Santa Teresa Uci",
    "gn:country_code":"MX",
    "gn:dem":9,
    "gn:feature_class":"P",
    "gn:feature_code":"PPL",
    "gn:name":"Santa Teresa Uci",
    "gn:population":0,
    "gn:timezone":"America/Merida",
    "iso:country":"MX",
    "name:spa_x_preferred":[
        "Santa Teresa Uci"
    ],
    "name:spa_x_variant":[
        "Santa Teresa"
    ],
    "wof:name":"Santa Teresa Uci",
    "wof:placetype":"locality"
},
  "geometry": {"coordinates":[-89.22409,21.14709],"type":"Point"}
}