{
  "type": "Feature",
  "properties": {
    "gn:admin1_code":"24",
    "gn:admin2_code":"30.0",
    "gn:asciiname":"Laguna de San Francisco",
    "gn:country_code":"MX",
    "gn:dem":1809,
    "gn:feature_class":"P",
    "gn:feature_code":"PPL",
    "gn:name":"Laguna de San Francisco",
    "gn:population":0,
    "gn:timezone":"America/Mexico_City",
    "iso:country":"MX",
    "wof:name":"Laguna de San Francisco",
    "wof:placetype":"locality"
},
  "geometry": {"coordinates":[-100.52800000000001,22.26379],"type":"Point"}
}