{
  "type": "Feature",
  "properties": {
    "gn:admin1_code":"14.0",
    "gn:admin2_code":"62.0",
    "gn:asciiname":"El Comalito",
    "gn:country_code":"MX",
    "gn:dem":2239,
    "gn:feature_class":"P",
    "gn:feature_code":"PPL",
    "gn:name":"El Comalito",
    "gn:population":0,
    "gn:timezone":"America/Mexico_City",
    "iso:country":"MX",
    "name:spa_x_preferred":[
        "El Comalito"
    ],
    "wof:name":"El Comalito",
    "wof:placetype":"locality"
},
  "geometry": {"coordinates":[-104.60514999999999,20.52592000000001],"type":"Point"}
}