{
  "type": "Feature",
  "properties": {
    "gn:admin1_code":"28",
    "gn:admin2_code":"22.0",
    "gn:asciiname":"Santa Ines (Brecha 132 Sur 88)",
    "gn:country_code":"MX",
    "gn:dem":12,
    "gn:feature_class":"P",
    "gn:feature_code":"PPL",
    "gn:name":"Santa In\u00e9s (Brecha 132 Sur 88)",
    "gn:population":9,
    "gn:timezone":"America/Matamoros",
    "iso:country":"MX",
    "name:und_x_variant":[
        "Santa In\u00e9s (Brecha 132 Sur 88)"
    ],
    "wof:name":"Santa Ines (Brecha 132 Sur 88)",
    "wof:placetype":"locality",
    "wof:population":9
},
  "geometry": {"coordinates":[-97.69528,25.61194],"type":"Point"}
}