{
  "type": "Feature",
  "properties": {
    "gn:admin1_code":"6.0",
    "gn:admin2_code":"52.0",
    "gn:asciiname":"El Socorro",
    "gn:country_code":"MX",
    "gn:dem":1580,
    "gn:feature_class":"P",
    "gn:feature_code":"PPL",
    "gn:name":"El Socorro",
    "gn:population":4,
    "gn:timezone":"America/Chihuahua",
    "iso:country":"MX",
    "name:spa_x_preferred":[
        "El Socorro"
    ],
    "wof:name":"El Socorro",
    "wof:placetype":"locality",
    "wof:population":4
},
  "geometry": {"coordinates":[-104.20556000000001,28.91646],"type":"Point"}
}