{
  "type": "Feature",
  "properties": {
    "gn:admin1_code":"9.0",
    "gn:admin2_code":"12.0",
    "gn:asciiname":"Estrella Mora",
    "gn:country_code":"MX",
    "gn:dem":2781,
    "gn:feature_class":"P",
    "gn:feature_code":"PPL",
    "gn:name":"Estrella Mora",
    "gn:population":0,
    "gn:timezone":"America/Mexico_City",
    "iso:country":"MX",
    "name:spa_x_preferred":[
        "Estrella Mora"
    ],
    "wof:name":"Estrella Mora",
    "wof:placetype":"locality"
},
  "geometry": {"coordinates":[-99.16349,19.19352],"type":"Point"}
}