{
  "type": "Feature",
  "properties": {
    "gn:admin1_code":"16.0",
    "gn:admin2_code":"89.0",
    "gn:asciiname":"La Cocina",
    "gn:country_code":"MX",
    "gn:dem":284,
    "gn:feature_class":"P",
    "gn:feature_code":"PPL",
    "gn:name":"La Cocina",
    "gn:population":0,
    "gn:timezone":"America/Mexico_City",
    "iso:country":"MX",
    "name:spa_x_preferred":[
        "La Cocina"
    ],
    "wof:name":"La Cocina",
    "wof:placetype":"locality"
},
  "geometry": {"coordinates":[-102.7595,19.05551],"type":"Point"}
}