{
  "type": "Feature",
  "properties": {
    "gn:admin1_code":"6",
    "gn:admin2_code":"26.0",
    "gn:asciiname":"Lazo",
    "gn:country_code":"MX",
    "gn:dem":1895,
    "gn:feature_class":"P",
    "gn:feature_code":"PPL",
    "gn:name":"Lazo",
    "gn:population":2,
    "gn:timezone":"America/Chihuahua",
    "iso:country":"MX",
    "name:ceb_x_preferred":[
        "Lazo"
    ],
    "name:deu_x_preferred":[
        "Lazo"
    ],
    "name:fra_x_preferred":[
        "Lazo"
    ],
    "name:por_x_preferred":[
        "Lazo"
    ],
    "name:ron_x_preferred":[
        "Lazo"
    ],
    "name:rus_x_preferred":[
        "\u041b\u0430\u0437\u043e"
    ],
    "name:spa_x_preferred":[
        "Lazo"
    ],
    "name:srp_x_preferred":[
        "\u041b\u0430\u0437\u043e"
    ],
    "name:swe_x_preferred":[
        "Lazo"
    ],
    "name:ukr_x_preferred":[
        "\u041b\u0430\u0437\u043e"
    ],
    "wof:name":"Lazo",
    "wof:placetype":"locality",
    "wof:population":2
},
  "geometry": {"coordinates":[-106.7041,28.30519],"type":"Point"}
}