{
  "type": "Feature",
  "properties": {
    "gn:admin1_code":"20.0",
    "gn:admin2_code":"345.0",
    "gn:asciiname":"San Jose de Arriba",
    "gn:country_code":"MX",
    "gn:dem":164,
    "gn:feature_class":"P",
    "gn:feature_code":"PPL",
    "gn:name":"San Jos\u00e9 de Arriba",
    "gn:population":0,
    "gn:timezone":"America/Mexico_City",
    "iso:country":"MX",
    "name:spa_x_preferred":[
        "San Jos\u00e9 de Arriba"
    ],
    "wof:name":"San Jose de Arriba",
    "wof:placetype":"locality"
},
  "geometry": {"coordinates":[-98.10334,16.51553],"type":"Point"}
}