{
  "type": "Feature",
  "properties": {
    "gn:admin1_code":"20",
    "gn:admin2_code":"107.0",
    "gn:asciiname":"Primera Seccion el Portillo",
    "gn:country_code":"MX",
    "gn:dem":1593,
    "gn:feature_class":"P",
    "gn:feature_code":"PPL",
    "gn:name":"Primera Secci\u00f3n el Portillo",
    "gn:population":138,
    "gn:timezone":"America/Mexico_City",
    "iso:country":"MX",
    "name:und_x_variant":[
        "Primera Secci\u00f3n el Portillo"
    ],
    "wof:name":"Primera Seccion el Portillo",
    "wof:placetype":"locality",
    "wof:population":138
},
  "geometry": {"coordinates":[-96.69333,17.03667],"type":"Point"}
}