{
  "type": "Feature",
  "properties": {
    "gn:admin1_code":"26",
    "gn:admin2_code":"6.0",
    "gn:asciiname":"El Cesar",
    "gn:country_code":"MX",
    "gn:dem":1499,
    "gn:feature_class":"P",
    "gn:feature_code":"PPL",
    "gn:name":"El C\u00e9sar",
    "gn:population":0,
    "gn:timezone":"America/Hermosillo",
    "iso:country":"MX",
    "name:spa_x_preferred":[
        "El C\u00e9sar"
    ],
    "wof:name":"El Cesar",
    "wof:placetype":"locality"
},
  "geometry": {"coordinates":[-110.43411999999999,30.71476],"type":"Point"}
}