{
  "type": "Feature",
  "properties": {
    "gn:admin1_code":"28.0",
    "gn:admin2_code":"37.0",
    "gn:asciiname":"San Patricio",
    "gn:country_code":"MX",
    "gn:dem":101,
    "gn:feature_class":"P",
    "gn:feature_code":"PPL",
    "gn:name":"San Patricio",
    "gn:population":1,
    "gn:timezone":"America/Monterrey",
    "iso:country":"MX",
    "name:spa_x_preferred":[
        "San Patricio"
    ],
    "wof:name":"San Patricio",
    "wof:placetype":"locality",
    "wof:population":1
},
  "geometry": {"coordinates":[-97.93083,23.55083],"type":"Point"}
}