{
  "type": "Feature",
  "properties": {
    "gn:admin1_code":"32",
    "gn:admin2_code":"17.0",
    "gn:asciiname":"Pedernalillo",
    "gn:country_code":"MX",
    "gn:dem":2230,
    "gn:feature_class":"P",
    "gn:feature_code":"PPL",
    "gn:name":"Pedernalillo",
    "gn:population":0,
    "gn:timezone":"America/Mexico_City",
    "iso:country":"MX",
    "wof:name":"Pedernalillo",
    "wof:placetype":"locality"
},
  "geometry": {"coordinates":[-102.48333,22.71667],"type":"Point"}
}