{
  "type": "Feature",
  "properties": {
    "gn:admin1_code":"21",
    "gn:admin2_code":"49.0",
    "gn:asciiname":"San Lorenzo Tlaxipehuala",
    "gn:country_code":"MX",
    "gn:dem":1721,
    "gn:feature_class":"P",
    "gn:feature_code":"PPL",
    "gn:name":"San Lorenzo Tlaxipehuala",
    "gn:population":1966,
    "gn:timezone":"America/Mexico_City",
    "iso:country":"MX",
    "wof:name":"San Lorenzo Tlaxipehuala",
    "wof:placetype":"locality",
    "wof:population":1966
},
  "geometry": {"coordinates":[-97.97360999999999,20.13028],"type":"Point"}
}