{
  "type": "Feature",
  "properties": {
    "gn:admin1_code":"15.0",
    "gn:asciiname":"Tierritas Blancas",
    "gn:country_code":"MX",
    "gn:dem":2347,
    "gn:feature_class":"P",
    "gn:feature_code":"PPL",
    "gn:name":"Tierritas Blancas",
    "gn:population":0,
    "gn:timezone":"America/Mexico_City",
    "iso:country":"MX",
    "name:spa_x_preferred":[
        "Tierritas Blancas"
    ],
    "wof:name":"Tierritas Blancas",
    "wof:placetype":"locality"
},
  "geometry": {"coordinates":[-99.23349,19.7299],"type":"Point"}
}