{
  "type": "Feature",
  "properties": {
    "gn:admin1_code":"7",
    "gn:admin2_code":"23.0",
    "gn:asciiname":"La Reina",
    "gn:country_code":"MX",
    "gn:dem":1171,
    "gn:feature_class":"P",
    "gn:feature_code":"PPL",
    "gn:name":"La Reina",
    "gn:population":0,
    "gn:timezone":"America/Monterrey",
    "iso:country":"MX",
    "name:und_x_variant":[
        "Rancho La Reina",
        "La Reina"
    ],
    "wof:name":"La Reina",
    "wof:placetype":"locality"
},
  "geometry": {"coordinates":[-102.73934,28.17583],"type":"Point"}
}