{
  "type": "Feature",
  "properties": {
    "gn:admin1_code":"7",
    "gn:admin2_code":"23.0",
    "gn:asciiname":"La Reina",
    "gn:country_code":"MX",
    "gn:dem":1171,
    "gn:feature_class":"P",
    "gn:feature_code":"PPL",
    "gn:name":"La Reina",
    "gn:population":0,
    "gn:timezone":"America/Monterrey",
    "iso:country":"MX",
    "name:cat_x_preferred":[
        "La Reina"
    ],
    "name:ceb_x_preferred":[
        "La Reina"
    ],
    "name:eus_x_preferred":[
        "La Reina"
    ],
    "name:fas_x_preferred":[
        "\u0644\u0627 \u0631\u0646\u0627"
    ],
    "name:fra_x_preferred":[
        "La Reina"
    ],
    "name:ita_x_preferred":[
        "La Reina"
    ],
    "name:kor_x_preferred":[
        "\ub77c\ub808\uc774\ub098"
    ],
    "name:nld_x_preferred":[
        "La Reina"
    ],
    "name:oci_x_preferred":[
        "La Reina"
    ],
    "name:pol_x_preferred":[
        "La Reina"
    ],
    "name:por_x_preferred":[
        "La Reina"
    ],
    "name:ron_x_preferred":[
        "La Reina"
    ],
    "name:rus_x_preferred":[
        "\u041b\u0430-\u0420\u0435\u0439\u043d\u0430"
    ],
    "name:spa_x_preferred":[
        "La Reina"
    ],
    "name:srp_x_preferred":[
        "\u041b\u0430 \u0420\u0435\u0458\u043d\u0430"
    ],
    "name:swe_x_preferred":[
        "La Reina"
    ],
    "name:und_x_variant":[
        "Rancho La Reina",
        "La Reina"
    ],
    "name:urd_x_preferred":[
        "\u0644\u0627 \u0631\u06cc\u0646\u0627"
    ],
    "name:zho_x_preferred":[
        "\u62c9\u96f7\u7d0d"
    ],
    "wof:name":"La Reina",
    "wof:placetype":"locality"
},
  "geometry": {"coordinates":[-102.73934,28.17583],"type":"Point"}
}