{
  "type": "Feature",
  "properties": {
    "gn:admin1_code":"31",
    "gn:admin2_code":"96.0",
    "gn:asciiname":"Santa Gabriela",
    "gn:country_code":"MX",
    "gn:dem":6,
    "gn:feature_class":"P",
    "gn:feature_code":"PPL",
    "gn:name":"Santa Gabriela",
    "gn:population":0,
    "gn:timezone":"America/Merida",
    "iso:country":"MX",
    "name:spa_x_preferred":[
        "Santa Gabriela"
    ],
    "wof:name":"Santa Gabriela",
    "wof:placetype":"locality"
},
  "geometry": {"coordinates":[-88.07465999999999,21.40363],"type":"Point"}
}