{
  "type": "Feature",
  "properties": {
    "gn:admin1_code":"5.0",
    "gn:admin2_code":"61.0",
    "gn:asciiname":"El Negro",
    "gn:country_code":"MX",
    "gn:dem":968,
    "gn:feature_class":"P",
    "gn:feature_code":"PPL",
    "gn:name":"El Negro",
    "gn:population":0,
    "gn:timezone":"America/Mexico_City",
    "iso:country":"MX",
    "name:ceb_x_preferred":[
        "El Negro"
    ],
    "name:nld_x_preferred":[
        "El Negro"
    ],
    "name:spa_x_preferred":[
        "El Negro"
    ],
    "name:srp_x_preferred":[
        "\u0415\u043b \u041d\u0435\u0433\u0440\u043e"
    ],
    "name:swe_x_preferred":[
        "El Negro"
    ],
    "wof:name":"El Negro",
    "wof:placetype":"locality"
},
  "geometry": {"coordinates":[-93.43591000000001,16.84602000000001],"type":"Point"}
}