{
  "type": "Feature",
  "properties": {
    "gn:admin1_code":"19",
    "gn:admin2_code":"5.0",
    "gn:asciiname":"Maravillas",
    "gn:country_code":"MX",
    "gn:dem":238,
    "gn:feature_class":"P",
    "gn:feature_code":"PPL",
    "gn:name":"Maravillas",
    "gn:population":0,
    "gn:timezone":"America/Matamoros",
    "iso:country":"MX",
    "name:ceb_x_preferred":[
        "Maravillas"
    ],
    "name:deu_x_preferred":[
        "Maravillas"
    ],
    "name:swe_x_preferred":[
        "Maravillas"
    ],
    "wof:name":"Maravillas",
    "wof:placetype":"locality"
},
  "geometry": {"coordinates":[-99.96666999999999,27.56667],"type":"Point"}
}