{
  "type": "Feature",
  "properties": {
    "gn:admin1_code":"19.0",
    "gn:asciiname":"San Mauro",
    "gn:country_code":"MX",
    "gn:dem":400,
    "gn:feature_class":"P",
    "gn:feature_code":"PPL",
    "gn:name":"San Mauro",
    "gn:population":0,
    "gn:timezone":"America/Monterrey",
    "iso:country":"MX",
    "name:spa_x_preferred":[
        "San Mauro"
    ],
    "name:spa_x_variant":[
        "Mauro",
        "Elizondo"
    ],
    "wof:name":"San Mauro",
    "wof:placetype":"locality"
},
  "geometry": {"coordinates":[-99.66416,24.90863],"type":"Point"}
}