{
  "type": "Feature",
  "properties": {
    "gn:admin1_code":"19.0",
    "gn:asciiname":"San Mauro",
    "gn:country_code":"MX",
    "gn:dem":400,
    "gn:feature_class":"P",
    "gn:feature_code":"PPL",
    "gn:name":"San Mauro",
    "gn:population":0,
    "gn:timezone":"America/Monterrey",
    "iso:country":"MX",
    "name:ceb_x_preferred":[
        "San Mauro"
    ],
    "name:deu_x_preferred":[
        "San Mauro"
    ],
    "name:glg_x_preferred":[
        "San Mauro"
    ],
    "name:ita_x_preferred":[
        "San Mauro"
    ],
    "name:nld_x_preferred":[
        "San Mauro"
    ],
    "name:por_x_preferred":[
        "San Mauro"
    ],
    "name:rus_x_preferred":[
        "\u0421\u0432\u044f\u0442\u043e\u0439 \u041c\u0430\u0432\u0440"
    ],
    "name:scn_x_preferred":[
        "Santu M\u00e0uru"
    ],
    "name:sco_x_preferred":[
        "San Mauro"
    ],
    "name:spa_x_preferred":[
        "San Mauro"
    ],
    "name:spa_x_variant":[
        "Mauro",
        "Elizondo"
    ],
    "name:srp_x_preferred":[
        "San Mauro"
    ],
    "name:swe_x_preferred":[
        "San Mauro"
    ],
    "wof:name":"San Mauro",
    "wof:placetype":"locality"
},
  "geometry": {"coordinates":[-99.66416,24.90863],"type":"Point"}
}