{
  "type": "Feature",
  "properties": {
    "gn:admin1_code":"10.0",
    "gn:admin2_code":"9.0",
    "gn:asciiname":"Mesas Coloradas",
    "gn:country_code":"MX",
    "gn:dem":2515,
    "gn:feature_class":"P",
    "gn:feature_code":"PPL",
    "gn:name":"Mesas Coloradas",
    "gn:population":0,
    "gn:timezone":"America/Monterrey",
    "iso:country":"MX",
    "name:spa_x_preferred":[
        "Mesas Coloradas"
    ],
    "wof:name":"Mesas Coloradas",
    "wof:placetype":"locality"
},
  "geometry": {"coordinates":[-106.07165999999999,26.31118],"type":"Point"}
}