{
  "type": "Feature",
  "properties": {
    "gn:admin1_code":"27",
    "gn:admin2_code":"3.0",
    "gn:asciiname":"Ejido Benito Juarez",
    "gn:country_code":"MX",
    "gn:dem":6,
    "gn:feature_class":"P",
    "gn:feature_code":"PPL",
    "gn:name":"Ejido Benito Ju\u00e1rez",
    "gn:population":0,
    "gn:timezone":"America/Mexico_City",
    "iso:country":"MX",
    "name:spa_x_preferred":[
        "Benito Ju\u00e1rez"
    ],
    "name:spa_x_variant":[
        "Ejido Benito Ju\u00e1rez"
    ],
    "wof:name":"Ejido Benito Juarez",
    "wof:placetype":"locality"
},
  "geometry": {"coordinates":[-92.81907,18.45103],"type":"Point"}
}