{
  "type": "Feature",
  "properties": {
    "gn:admin1_code":"20",
    "gn:admin2_code":"466.0",
    "gn:asciiname":"Siniyuya",
    "gn:country_code":"MX",
    "gn:dem":612,
    "gn:feature_class":"P",
    "gn:feature_code":"PPL",
    "gn:name":"Siniyuya",
    "gn:population":0,
    "gn:timezone":"America/Mexico_City",
    "iso:country":"MX",
    "name:spa_x_preferred":[
        "Siniyuva"
    ],
    "name:spa_x_variant":[
        "Siniyuya"
    ],
    "wof:name":"Siniyuya",
    "wof:placetype":"locality"
},
  "geometry": {"coordinates":[-97.6313,16.56493],"type":"Point"}
}