{
  "type": "Feature",
  "properties": {
    "gn:admin1_code":"19",
    "gn:admin2_code":"12.0",
    "gn:asciiname":"La Libertad",
    "gn:country_code":"MX",
    "gn:dem":404,
    "gn:feature_class":"P",
    "gn:feature_code":"PPL",
    "gn:name":"La Libertad",
    "gn:population":8,
    "gn:timezone":"America/Monterrey",
    "iso:country":"MX",
    "wof:name":"La Libertad",
    "wof:placetype":"locality",
    "wof:population":8
},
  "geometry": {"coordinates":[-100.17448,25.9395],"type":"Point"}
}