{
  "type": "Feature",
  "properties": {
    "gn:admin1_code":"1",
    "gn:admin2_code":"2",
    "gn:asciiname":"Las Bovedas [Rancho]",
    "gn:country_code":"MX",
    "gn:dem":2043,
    "gn:feature_class":"P",
    "gn:feature_code":"PPL",
    "gn:name":"Las B\u00f3vedas [Rancho]",
    "gn:population":32,
    "gn:timezone":"America/Mexico_City",
    "iso:country":"MX",
    "name:und_x_variant":[
        "Las B\u00f3vedas [Rancho]"
    ],
    "wof:name":"Las Bovedas [Rancho]",
    "wof:placetype":"locality",
    "wof:population":32
},
  "geometry": {"coordinates":[-101.98361,22.11361],"type":"Point"}
}