{
  "type": "Feature",
  "properties": {
    "gn:admin1_code":"5",
    "gn:admin2_code":"108.0",
    "gn:asciiname":"Rancho Bonito",
    "gn:country_code":"MX",
    "gn:dem":711,
    "gn:feature_class":"P",
    "gn:feature_code":"PPL",
    "gn:name":"Rancho Bonito",
    "gn:population":4,
    "gn:timezone":"America/Mexico_City",
    "iso:country":"MX",
    "wof:name":"Rancho Bonito",
    "wof:placetype":"locality",
    "wof:population":4
},
  "geometry": {"coordinates":[-93.58222000000001,16.33361],"type":"Point"}
}