{
  "type": "Feature",
  "properties": {
    "gn:admin1_code":"12.0",
    "gn:admin2_code":"21.0",
    "gn:asciiname":"El Avillo",
    "gn:country_code":"MX",
    "gn:dem":31,
    "gn:feature_class":"P",
    "gn:feature_code":"PPL",
    "gn:name":"El Avillo",
    "gn:population":0,
    "gn:timezone":"America/Mexico_City",
    "iso:country":"MX",
    "name:spa_x_preferred":[
        "El Avillo"
    ],
    "wof:name":"El Avillo",
    "wof:placetype":"locality"
},
  "geometry": {"coordinates":[-100.26439999999999,17.06322],"type":"Point"}
}