{
  "type": "Feature",
  "properties": {
    "gn:admin1_code":"22",
    "gn:admin2_code":"10",
    "gn:asciiname":"El Sabino",
    "gn:country_code":"MX",
    "gn:dem":1495,
    "gn:feature_class":"P",
    "gn:feature_code":"PPL",
    "gn:name":"El Sabino",
    "gn:population":34,
    "gn:timezone":"America/Mexico_City",
    "iso:country":"MX",
    "wof:name":"El Sabino",
    "wof:placetype":"locality",
    "wof:population":34
},
  "geometry": {"coordinates":[-99.12111,21.26222000000001],"type":"Point"}
}