{
  "type": "Feature",
  "properties": {
    "gn:admin1_code":"5",
    "gn:admin2_code":"61.0",
    "gn:asciiname":"El Billar",
    "gn:country_code":"MX",
    "gn:dem":816,
    "gn:feature_class":"P",
    "gn:feature_code":"PPL",
    "gn:name":"El Billar",
    "gn:population":0,
    "gn:timezone":"America/Mexico_City",
    "iso:country":"MX",
    "name:und_x_variant":[
        "Billar",
        "El Billar"
    ],
    "wof:name":"El Billar",
    "wof:placetype":"locality"
},
  "geometry": {"coordinates":[-93.43725000000001,16.60203],"type":"Point"}
}