{
  "type": "Feature",
  "properties": {
    "gn:admin1_code":"16",
    "gn:admin2_code":"99",
    "gn:asciiname":"Calicanto",
    "gn:country_code":"MX",
    "gn:dem":584,
    "gn:feature_class":"P",
    "gn:feature_code":"PPL",
    "gn:name":"Calicanto",
    "gn:population":47,
    "gn:timezone":"America/Mexico_City",
    "iso:country":"MX",
    "wof:name":"Calicanto",
    "wof:placetype":"locality",
    "wof:population":47
},
  "geometry": {"coordinates":[-100.58472,19.18222],"type":"Point"}
}