{
  "type": "Feature",
  "properties": {
    "gn:admin1_code":"29",
    "gn:admin2_code":"6",
    "gn:asciiname":"Loma de San Agustin",
    "gn:country_code":"MX",
    "gn:dem":2763,
    "gn:feature_class":"P",
    "gn:feature_code":"PPL",
    "gn:name":"Loma de San Agust\u00edn",
    "gn:population":21,
    "gn:timezone":"America/Mexico_City",
    "iso:country":"MX",
    "name:und_x_variant":[
        "Loma de San Agust\u00edn"
    ],
    "wof:name":"Loma de San Agustin",
    "wof:placetype":"locality",
    "wof:population":21
},
  "geometry": {"coordinates":[-98.60868000000001,19.53724],"type":"Point"}
}