{
  "type": "Feature",
  "properties": {
    "gn:admin1_code":"20.0",
    "gn:admin2_code":"306.0",
    "gn:asciiname":"Piedra de Azufre",
    "gn:country_code":"MX",
    "gn:dem":1377,
    "gn:feature_class":"P",
    "gn:feature_code":"PPL",
    "gn:name":"Piedra de Azufre",
    "gn:population":0,
    "gn:timezone":"America/Mexico_City",
    "iso:country":"MX",
    "name:spa_x_preferred":[
        "Piedra de Azufre"
    ],
    "wof:name":"Piedra de Azufre",
    "wof:placetype":"locality"
},
  "geometry": {"coordinates":[-96.51852,16.00391],"type":"Point"}
}