{
  "type": "Feature",
  "properties": {
    "gn:admin1_code":"10",
    "gn:admin2_code":"5.0",
    "gn:asciiname":"Carnitas Dany [Restaurante]",
    "gn:country_code":"MX",
    "gn:dem":2513,
    "gn:feature_class":"P",
    "gn:feature_code":"PPL",
    "gn:name":"Carnitas Dany [Restaurante]",
    "gn:population":5,
    "gn:timezone":"America/Monterrey",
    "iso:country":"MX",
    "wof:name":"Carnitas Dany [Restaurante]",
    "wof:placetype":"locality",
    "wof:population":5
},
  "geometry": {"coordinates":[-105.17025,23.86975],"type":"Point"}
}