{
  "type": "Feature",
  "properties": {
    "gn:admin1_code":"19",
    "gn:admin2_code":"13",
    "gn:asciiname":"Via Nueva (Villa Nueva)",
    "gn:country_code":"MX",
    "gn:dem":165,
    "gn:feature_class":"P",
    "gn:feature_code":"PPL",
    "gn:name":"V\u00eda Nueva (Villa Nueva)",
    "gn:population":16,
    "gn:timezone":"America/Monterrey",
    "iso:country":"MX",
    "name:und_x_variant":[
        "V\u00eda Nueva (Villa Nueva)"
    ],
    "wof:name":"Via Nueva (Villa Nueva)",
    "wof:placetype":"locality",
    "wof:population":16
},
  "geometry": {"coordinates":[-99.35835,25.72285],"type":"Point"}
}