{
  "type": "Feature",
  "properties": {
    "gn:admin1_code":"25",
    "gn:admin2_code":"12",
    "gn:asciiname":"Los Cedros",
    "gn:country_code":"MX",
    "gn:dem":93,
    "gn:feature_class":"P",
    "gn:feature_code":"PPL",
    "gn:name":"Los Cedros",
    "gn:population":17,
    "gn:timezone":"America/Mazatlan",
    "iso:country":"MX",
    "wof:name":"Los Cedros",
    "wof:placetype":"locality",
    "wof:population":17
},
  "geometry": {"coordinates":[-106.35321,23.33139],"type":"Point"}
}