{
  "type": "Feature",
  "properties": {
    "gn:admin1_code":"19",
    "gn:admin2_code":"13.0",
    "gn:asciiname":"Altamira",
    "gn:country_code":"MX",
    "gn:dem":179,
    "gn:feature_class":"P",
    "gn:feature_code":"PPL",
    "gn:name":"Altamira",
    "gn:population":7,
    "gn:timezone":"America/Monterrey",
    "iso:country":"MX",
    "wof:name":"Altamira",
    "wof:placetype":"locality",
    "wof:population":7
},
  "geometry": {"coordinates":[-98.96638,25.16453],"type":"Point"}
}