{
  "type": "Feature",
  "properties": {
    "gn:admin1_code":"19.0",
    "gn:admin2_code":"50.0",
    "gn:asciiname":"Las Penas",
    "gn:country_code":"MX",
    "gn:dem":205,
    "gn:feature_class":"P",
    "gn:feature_code":"PPL",
    "gn:name":"Las Pe\u00f1as",
    "gn:population":0,
    "gn:timezone":"America/Monterrey",
    "iso:country":"MX",
    "name:spa_x_preferred":[
        "Las Pe\u00f1as"
    ],
    "wof:name":"Las Penas",
    "wof:placetype":"locality"
},
  "geometry": {"coordinates":[-99.82684999999999,26.48206],"type":"Point"}
}