{
  "type": "Feature",
  "properties": {
    "gn:admin1_code":"15",
    "gn:admin2_code":"57.0",
    "gn:asciiname":"El Puerto",
    "gn:country_code":"MX",
    "gn:dem":2508,
    "gn:feature_class":"P",
    "gn:feature_code":"PPL",
    "gn:name":"El Puerto",
    "gn:population":78,
    "gn:timezone":"America/Mexico_City",
    "iso:country":"MX",
    "wof:name":"El Puerto",
    "wof:placetype":"locality",
    "wof:population":78
},
  "geometry": {"coordinates":[-99.31088,19.48747],"type":"Point"}
}