{
  "type": "Feature",
  "properties": {
    "gn:admin1_code":"5",
    "gn:admin2_code":"82",
    "gn:asciiname":"San Jeronimo",
    "gn:country_code":"MX",
    "gn:dem":785,
    "gn:feature_class":"P",
    "gn:feature_code":"PPL",
    "gn:name":"San Jer\u00f3nimo",
    "gn:population":17,
    "gn:timezone":"America/Mexico_City",
    "iso:country":"MX",
    "name:und_x_variant":[
        "San Jer\u00f3nimo"
    ],
    "wof:name":"San Jeronimo",
    "wof:placetype":"locality",
    "wof:population":17
},
  "geometry": {"coordinates":[-92.39917,17.01583],"type":"Point"}
}