{
  "type": "Feature",
  "properties": {
    "gn:admin1_code":"5",
    "gn:admin2_code":"72.0",
    "gn:asciiname":"Delirio",
    "gn:country_code":"MX",
    "gn:dem":987,
    "gn:feature_class":"P",
    "gn:feature_code":"PPL",
    "gn:name":"Delirio",
    "gn:population":103,
    "gn:timezone":"America/Mexico_City",
    "iso:country":"MX",
    "name:ceb_x_preferred":[
        "Delirio"
    ],
    "name:deu_x_preferred":[
        "Delirio"
    ],
    "name:eus_x_preferred":[
        "Delirio"
    ],
    "name:ita_x_preferred":[
        "Delirio"
    ],
    "name:por_x_preferred":[
        "Del\u00edrio"
    ],
    "name:spa_x_preferred":[
        "Delirio"
    ],
    "name:srp_x_preferred":[
        "\u0414\u0435\u043b\u0438\u0440\u0438\u043e"
    ],
    "name:swe_x_preferred":[
        "Delirio"
    ],
    "wof:name":"Delirio",
    "wof:placetype":"locality",
    "wof:population":103
},
  "geometry": {"coordinates":[-92.82917,17.21111],"type":"Point"}
}