{
  "type": "Feature",
  "properties": {
    "gn:admin1_code":"12.0",
    "gn:admin2_code":"72.0",
    "gn:asciiname":"Piedra Larga",
    "gn:country_code":"MX",
    "gn:dem":1617,
    "gn:feature_class":"P",
    "gn:feature_code":"PPL",
    "gn:name":"Piedra Larga",
    "gn:population":0,
    "gn:timezone":"America/Mexico_City",
    "iso:country":"MX",
    "name:spa_x_preferred":[
        "Piedra Larga"
    ],
    "wof:name":"Piedra Larga",
    "wof:placetype":"locality"
},
  "geometry": {"coordinates":[-98.87203,17.18719],"type":"Point"}
}