{
  "type": "Feature",
  "properties": {
    "gn:admin1_code":"16",
    "gn:admin2_code":"10.0",
    "gn:asciiname":"La Mesa de los Horcones",
    "gn:country_code":"MX",
    "gn:dem":919,
    "gn:feature_class":"P",
    "gn:feature_code":"PPL",
    "gn:name":"La Mesa de los Horcones",
    "gn:population":5,
    "gn:timezone":"America/Mexico_City",
    "iso:country":"MX",
    "wof:name":"La Mesa de los Horcones",
    "wof:placetype":"locality",
    "wof:population":5
},
  "geometry": {"coordinates":[-102.31694,18.33056],"type":"Point"}
}