{
  "type": "Feature",
  "properties": {
    "gn:admin1_code":"20",
    "gn:admin2_code":"486",
    "gn:asciiname":"Tercera Seccion (Diniyaya)",
    "gn:country_code":"MX",
    "gn:dem":2136,
    "gn:feature_class":"P",
    "gn:feature_code":"PPL",
    "gn:name":"Tercera Secci\u00f3n (Diniyaya)",
    "gn:population":15,
    "gn:timezone":"America/Mexico_City",
    "iso:country":"MX",
    "name:und_x_variant":[
        "Tercera Secci\u00f3n (Diniyaya)"
    ],
    "wof:name":"Tercera Seccion (Diniyaya)",
    "wof:placetype":"locality",
    "wof:population":15
},
  "geometry": {"coordinates":[-97.46306,17.66972],"type":"Point"}
}