{
  "type": "Feature",
  "properties": {
    "gn:admin1_code":"32",
    "gn:admin2_code":"42.0",
    "gn:asciiname":"Colonia Cuatro de Menonitas (Tierra Limpia)",
    "gn:country_code":"MX",
    "gn:dem":2434,
    "gn:feature_class":"P",
    "gn:feature_code":"PPL",
    "gn:name":"Colonia Cuatro de Menonitas (Tierra Limpia)",
    "gn:population":96,
    "gn:timezone":"America/Mexico_City",
    "iso:country":"MX",
    "wof:name":"Colonia Cuatro de Menonitas (Tierra Limpia)",
    "wof:placetype":"locality",
    "wof:population":96
},
  "geometry": {"coordinates":[-103.50583,23.21778],"type":"Point"}
}