{
  "type": "Feature",
  "properties": {
    "gn:admin1_code":"15",
    "gn:admin2_code":"14",
    "gn:asciiname":"Rancho San Martin",
    "gn:country_code":"MX",
    "gn:dem":2524,
    "gn:feature_class":"P",
    "gn:feature_code":"PPL",
    "gn:name":"Rancho San Mart\u00edn",
    "gn:population":38,
    "gn:timezone":"America/Mexico_City",
    "iso:country":"MX",
    "name:und_x_variant":[
        "Rancho San Mart\u00edn"
    ],
    "wof:name":"Rancho San Martin",
    "wof:placetype":"locality",
    "wof:population":38
},
  "geometry": {"coordinates":[-99.87101,19.78177],"type":"Point"}
}