{
  "type": "Feature",
  "properties": {
    "gn:admin1_code":"6",
    "gn:admin2_code":"20.0",
    "gn:asciiname":"Los Coscomates",
    "gn:country_code":"MX",
    "gn:dem":636,
    "gn:feature_class":"P",
    "gn:feature_code":"PPL",
    "gn:name":"Los Coscomates",
    "gn:population":4,
    "gn:timezone":"America/Chihuahua",
    "iso:country":"MX",
    "name:spa_x_preferred":[
        "Los Coscomates"
    ],
    "wof:name":"Los Coscomates",
    "wof:placetype":"locality",
    "wof:population":4
},
  "geometry": {"coordinates":[-108.47972,27.58002],"type":"Point"}
}