{
  "type": "Feature",
  "properties": {
    "gn:admin1_code":"30.0",
    "gn:admin2_code":"124.0",
    "gn:asciiname":"La Sabana",
    "gn:country_code":"MX",
    "gn:dem":163,
    "gn:feature_class":"P",
    "gn:feature_code":"PPL",
    "gn:name":"La Sabana",
    "gn:population":5,
    "gn:timezone":"America/Mexico_City",
    "iso:country":"MX",
    "name:spa_x_preferred":[
        "La Sabana"
    ],
    "wof:name":"La Sabana",
    "wof:placetype":"locality",
    "wof:population":5
},
  "geometry": {"coordinates":[-97.42332,20.38652],"type":"Point"}
}