{
  "type": "Feature",
  "properties": {
    "gn:admin1_code":"14",
    "gn:admin2_code":"41.0",
    "gn:asciiname":"El Llano de las Flores",
    "gn:country_code":"MX",
    "gn:dem":2190,
    "gn:feature_class":"P",
    "gn:feature_code":"PPL",
    "gn:name":"El Llano de las Flores",
    "gn:population":5,
    "gn:timezone":"America/Mexico_City",
    "iso:country":"MX",
    "wof:name":"El Llano de las Flores",
    "wof:placetype":"locality",
    "wof:population":5
},
  "geometry": {"coordinates":[-103.355,22.33944],"type":"Point"}
}