{
  "type": "Feature",
  "properties": {
    "gn:admin1_code":"7",
    "gn:admin2_code":"24.0",
    "gn:asciiname":"San Rafael de los Yeguales",
    "gn:country_code":"MX",
    "gn:dem":1741,
    "gn:feature_class":"P",
    "gn:feature_code":"PPL",
    "gn:name":"San Rafael de los Yeguales",
    "gn:population":0,
    "gn:timezone":"America/Monterrey",
    "iso:country":"MX",
    "name:spa_x_preferred":[
        "San Rafael de los Yeguales"
    ],
    "name:und_x_variant":[
        "Rancho Los Yeguales"
    ],
    "wof:name":"San Rafael de los Yeguales",
    "wof:placetype":"locality"
},
  "geometry": {"coordinates":[-102.03583999999999,25.27546],"type":"Point"}
}