{
  "type": "Feature",
  "properties": {
    "gn:admin1_code":"4",
    "gn:admin2_code":"3.0",
    "gn:asciiname":"Toluca",
    "gn:country_code":"MX",
    "gn:dem":0,
    "gn:feature_class":"P",
    "gn:feature_code":"PPL",
    "gn:name":"Toluca",
    "gn:population":3,
    "gn:timezone":"America/Merida",
    "iso:country":"MX",
    "wof:name":"Toluca",
    "wof:placetype":"locality",
    "wof:population":3
},
  "geometry": {"coordinates":[-91.25082999999999,18.95972],"type":"Point"}
}