{
  "type": "Feature",
  "properties": {
    "gn:admin1_code":"4",
    "gn:admin2_code":"3.0",
    "gn:asciiname":"Toluca",
    "gn:country_code":"MX",
    "gn:dem":0,
    "gn:feature_class":"P",
    "gn:feature_code":"PPL",
    "gn:name":"Toluca",
    "gn:population":3,
    "gn:timezone":"America/Merida",
    "iso:country":"MX",
    "name:ara_x_preferred":[
        "\u062a\u0648\u0644\u0648\u0643\u0627"
    ],
    "name:bre_x_preferred":[
        "Toluca"
    ],
    "name:bul_x_preferred":[
        "\u0422\u043e\u043b\u0443\u043a\u0430"
    ],
    "name:ceb_x_preferred":[
        "Toluca"
    ],
    "name:ces_x_preferred":[
        "Toluca"
    ],
    "name:dan_x_preferred":[
        "Toluca"
    ],
    "name:ell_x_preferred":[
        "\u03a4\u03bf\u03bb\u03bf\u03cd\u03ba\u03b1"
    ],
    "name:fas_x_preferred":[
        "\u062a\u0648\u0644\u0648\u06a9\u0627"
    ],
    "name:fin_x_preferred":[
        "Toluca"
    ],
    "name:fra_x_preferred":[
        "Toluca"
    ],
    "name:heb_x_preferred":[
        "\u05d8\u05d5\u05dc\u05d5\u05e7\u05d4"
    ],
    "name:ido_x_preferred":[
        "Toluca"
    ],
    "name:ilo_x_preferred":[
        "Toluca"
    ],
    "name:ind_x_preferred":[
        "Toluca"
    ],
    "name:ita_x_preferred":[
        "Toluca"
    ],
    "name:jpn_x_preferred":[
        "\u30c8\u30eb\u30fc\u30ab"
    ],
    "name:kal_x_preferred":[
        "Toluca"
    ],
    "name:kat_x_preferred":[
        "\u10e2\u10dd\u10da\u10e3\u10d9\u10d0"
    ],
    "name:kik_x_preferred":[
        "Toluca"
    ],
    "name:kor_x_preferred":[
        "\ud1a8\ub8e8\uce74"
    ],
    "name:lat_x_preferred":[
        "Toluca"
    ],
    "name:lit_x_preferred":[
        "Toluka"
    ],
    "name:mar_x_preferred":[
        "\u0924\u094b\u0932\u0941\u0915\u093e"
    ],
    "name:msa_x_preferred":[
        "Toluca"
    ],
    "name:nld_x_preferred":[
        "Toluca"
    ],
    "name:nno_x_preferred":[
        "Toluca"
    ],
    "name:nor_x_preferred":[
        "Toluca"
    ],
    "name:pan_x_preferred":[
        "\u0a24\u0a4b\u0a32\u0a42\u0a15\u0a3e"
    ],
    "name:pol_x_preferred":[
        "Toluca"
    ],
    "name:por_x_preferred":[
        "Toluca"
    ],
    "name:rus_x_preferred":[
        "\u0422\u043e\u043b\u0443\u043a\u0430-\u0434\u0435-\u041b\u0435\u0440\u0434\u043e"
    ],
    "name:sco_x_preferred":[
        "Toluca"
    ],
    "name:slk_x_preferred":[
        "Toluca"
    ],
    "name:srp_x_preferred":[
        "\u0422\u043e\u043b\u0443\u043a\u0430"
    ],
    "name:swa_x_preferred":[
        "Toluca"
    ],
    "name:tgl_x_preferred":[
        "Toluca"
    ],
    "name:tha_x_preferred":[
        "\u0e42\u0e15\u0e25\u0e39\u0e01\u0e32"
    ],
    "name:tur_x_preferred":[
        "Toluca"
    ],
    "name:ukr_x_preferred":[
        "\u0422\u043e\u043b\u0443\u043a\u0430-\u0434\u0435-\u041b\u0435\u0440\u0434\u043e"
    ],
    "name:urd_x_preferred":[
        "\u062a\u0648\u0644\u0648\u06a9\u0627"
    ],
    "name:uzb_x_preferred":[
        "Toluka"
    ],
    "name:vie_x_preferred":[
        "Toluca"
    ],
    "name:war_x_preferred":[
        "Toluca"
    ],
    "name:wuu_x_preferred":[
        "\u6258\u5362\u5361"
    ],
    "name:xmf_x_preferred":[
        "\u10e2\u10dd\u10da\u10e3\u10d9\u10d0"
    ],
    "name:zho_x_preferred":[
        "\u6258\u5362\u5361"
    ],
    "wof:name":"Toluca",
    "wof:placetype":"locality",
    "wof:population":3
},
  "geometry": {"coordinates":[-91.25082999999999,18.95972],"type":"Point"}
}