{
  "type": "Feature",
  "properties": {
    "gn:admin1_code":"20",
    "gn:admin2_code":"469.0",
    "gn:asciiname":"Santa Maria Yucunicoco",
    "gn:country_code":"MX",
    "gn:dem":2454,
    "gn:feature_class":"P",
    "gn:feature_code":"PPL",
    "gn:name":"Santa Mar\u00eda Yucunicoco",
    "gn:population":0,
    "gn:timezone":"America/Mexico_City",
    "iso:country":"MX",
    "name:spa_x_preferred":[
        "Yacunicoco"
    ],
    "name:spa_x_variant":[
        "Santa Mar\u00eda",
        "Santa Mar\u00eda Yucunicoco"
    ],
    "wof:name":"Santa Maria Yucunicoco",
    "wof:placetype":"locality"
},
  "geometry": {"coordinates":[-97.91698,17.23754],"type":"Point"}
}