{
  "type": "Feature",
  "properties": {
    "gn:admin1_code":"28.0",
    "gn:admin2_code":"17.0",
    "gn:asciiname":"Las Letras",
    "gn:country_code":"MX",
    "gn:dem":1905,
    "gn:feature_class":"P",
    "gn:feature_code":"PPL",
    "gn:name":"Las Letras",
    "gn:population":1,
    "gn:timezone":"America/Monterrey",
    "iso:country":"MX",
    "name:spa_x_preferred":[
        "Las Letras"
    ],
    "wof:name":"Las Letras",
    "wof:placetype":"locality",
    "wof:population":1
},
  "geometry": {"coordinates":[-99.51972000000001,23.80306],"type":"Point"}
}