{
  "type": "Feature",
  "properties": {
    "gn:admin1_code":"24",
    "gn:admin2_code":"17.0",
    "gn:asciiname":"Entronque de Guadalcazar",
    "gn:country_code":"MX",
    "gn:dem":1483,
    "gn:feature_class":"P",
    "gn:feature_code":"PPL",
    "gn:name":"Entronque de Guadalc\u00e1zar",
    "gn:population":9,
    "gn:timezone":"America/Mexico_City",
    "iso:country":"MX",
    "name:und_x_variant":[
        "Entronque de Guadalc\u00e1zar"
    ],
    "wof:name":"Entronque de Guadalcazar",
    "wof:placetype":"locality",
    "wof:population":9
},
  "geometry": {"coordinates":[-100.51694000000001,22.64222],"type":"Point"}
}