{
  "type": "Feature",
  "properties": {
    "gn:admin1_code":"16.0",
    "gn:admin2_code":"104.0",
    "gn:asciiname":"Jaripeo",
    "gn:country_code":"MX",
    "gn:dem":1608,
    "gn:feature_class":"P",
    "gn:feature_code":"PPL",
    "gn:name":"Jaripeo",
    "gn:population":0,
    "gn:timezone":"America/Mexico_City",
    "iso:country":"MX",
    "wof:name":"Jaripeo",
    "wof:placetype":"locality"
},
  "geometry": {"coordinates":[-102.59166999999999,19.93333],"type":"Point"}
}