{
  "type": "Feature",
  "properties": {
    "gn:admin1_code":"16",
    "gn:admin2_code":"9.0",
    "gn:asciiname":"El Colorin",
    "gn:country_code":"MX",
    "gn:dem":1799,
    "gn:feature_class":"P",
    "gn:feature_code":"PPL",
    "gn:name":"El Color\u00edn",
    "gn:population":64,
    "gn:timezone":"America/Mexico_City",
    "iso:country":"MX",
    "name:und_x_variant":[
        "El Color\u00edn"
    ],
    "wof:name":"El Colorin",
    "wof:placetype":"locality",
    "wof:population":64
},
  "geometry": {"coordinates":[-101.73417000000001,19.2325],"type":"Point"}
}