{
  "type": "Feature",
  "properties": {
    "gn:admin1_code":"15.0",
    "gn:admin2_code":"66.0",
    "gn:asciiname":"El Grajenal",
    "gn:country_code":"MX",
    "gn:dem":1084,
    "gn:feature_class":"P",
    "gn:feature_code":"PPL",
    "gn:name":"El Grajenal",
    "gn:population":0,
    "gn:timezone":"America/Mexico_City",
    "iso:country":"MX",
    "name:spa_x_preferred":[
        "El Grajenal"
    ],
    "wof:name":"El Grajenal",
    "wof:placetype":"locality"
},
  "geometry": {"coordinates":[-100.36891,19.09399],"type":"Point"}
}