{
  "type": "Feature",
  "properties": {
    "gn:admin1_code":"5",
    "gn:admin2_code":"51.0",
    "gn:asciiname":"Juan Becerra (Maria Belen Cruz Hilario)",
    "gn:country_code":"MX",
    "gn:dem":35,
    "gn:feature_class":"P",
    "gn:feature_code":"PPL",
    "gn:name":"Juan Becerra (Mar\u00eda Bel\u00e9n Cruz Hilario)",
    "gn:population":6,
    "gn:timezone":"America/Mexico_City",
    "iso:country":"MX",
    "name:und_x_variant":[
        "Juan Becerra (Mar\u00eda Bel\u00e9n Cruz Hilario)"
    ],
    "wof:name":"Juan Becerra (Maria Belen Cruz Hilario)",
    "wof:placetype":"locality",
    "wof:population":6
},
  "geometry": {"coordinates":[-92.91249999999999,15.425],"type":"Point"}
}