{
  "type": "Feature",
  "properties": {
    "gn:admin1_code":"23.0",
    "gn:asciiname":"El Mandarin",
    "gn:country_code":"MX",
    "gn:dem":6,
    "gn:feature_class":"P",
    "gn:feature_code":"PPL",
    "gn:name":"El Mandar\u00edn",
    "gn:population":0,
    "gn:timezone":"America/Cancun",
    "iso:country":"MX",
    "name:spa_x_preferred":[
        "El Mandar\u00edn"
    ],
    "wof:name":"El Mandarin",
    "wof:placetype":"locality"
},
  "geometry": {"coordinates":[-87.02865,20.69979],"type":"Point"}
}