{
  "type": "Feature",
  "properties": {
    "gn:admin1_code":"26",
    "gn:admin2_code":"38.0",
    "gn:asciiname":"La Villita",
    "gn:country_code":"MX",
    "gn:dem":705,
    "gn:feature_class":"P",
    "gn:feature_code":"PPL",
    "gn:name":"La Villita",
    "gn:population":5,
    "gn:timezone":"America/Hermosillo",
    "iso:country":"MX",
    "wof:name":"La Villita",
    "wof:placetype":"locality",
    "wof:population":5
},
  "geometry": {"coordinates":[-109.65582999999999,29.86583],"type":"Point"}
}