{
  "type": "Feature",
  "properties": {
    "gn:admin1_code":"30.0",
    "gn:asciiname":"San Pedro Candelaria",
    "gn:country_code":"MX",
    "gn:dem":51,
    "gn:feature_class":"P",
    "gn:feature_code":"PPL",
    "gn:name":"San Pedro Candelaria",
    "gn:population":0,
    "gn:timezone":"America/Mexico_City",
    "iso:country":"MX",
    "name:spa_x_preferred":[
        "San Pedro Candelaria"
    ],
    "wof:name":"San Pedro Candelaria",
    "wof:placetype":"locality"
},
  "geometry": {"coordinates":[-95.24154,17.76706],"type":"Point"}
}