{
  "type": "Feature",
  "properties": {
    "gn:admin1_code":"32",
    "gn:admin2_code":"38.0",
    "gn:asciiname":"La Majadita",
    "gn:country_code":"MX",
    "gn:dem":2389,
    "gn:feature_class":"P",
    "gn:feature_code":"PPL",
    "gn:name":"La Majadita",
    "gn:population":0,
    "gn:timezone":"America/Mexico_City",
    "iso:country":"MX",
    "name:spa_x_preferred":[
        "La Majadita"
    ],
    "wof:name":"La Majadita",
    "wof:placetype":"locality"
},
  "geometry": {"coordinates":[-101.47913,22.28822000000001],"type":"Point"}
}