{
  "type": "Feature",
  "properties": {
    "gn:admin1_code":"6",
    "gn:admin2_code":"21",
    "gn:asciiname":"Ladrilleras de la Revolucion",
    "gn:country_code":"MX",
    "gn:dem":1174,
    "gn:feature_class":"P",
    "gn:feature_code":"PPL",
    "gn:name":"Ladrilleras de la Revoluci\u00f3n",
    "gn:population":9,
    "gn:timezone":"America/Chihuahua",
    "iso:country":"MX",
    "name:und_x_variant":[
        "Ladrilleras de la Revoluci\u00f3n"
    ],
    "wof:name":"Ladrilleras de la Revolucion",
    "wof:placetype":"locality",
    "wof:population":9
},
  "geometry": {"coordinates":[-105.44352000000001,28.22659],"type":"Point"}
}