{
  "type": "Feature",
  "properties": {
    "gn:admin1_code":"19.0",
    "gn:admin2_code":"14.0",
    "gn:asciiname":"La Chiripa",
    "gn:country_code":"MX",
    "gn:dem":1793,
    "gn:feature_class":"P",
    "gn:feature_code":"PPL",
    "gn:name":"La Chiripa",
    "gn:population":152,
    "gn:timezone":"America/Monterrey",
    "iso:country":"MX",
    "name:spa_x_preferred":[
        "El Chiripa"
    ],
    "wof:name":"La Chiripa",
    "wof:placetype":"locality",
    "wof:population":152
},
  "geometry": {"coordinates":[-100.37007,23.72129],"type":"Point"}
}