{
  "type": "Feature",
  "properties": {
    "gn:admin1_code":"26.0",
    "gn:admin2_code":"8.0",
    "gn:asciiname":"Rodadero",
    "gn:country_code":"MX",
    "gn:dem":911,
    "gn:feature_class":"P",
    "gn:feature_code":"PPL",
    "gn:name":"Rodadero",
    "gn:population":0,
    "gn:timezone":"America/Hermosillo",
    "iso:country":"MX",
    "name:spa_x_preferred":[
        "Rodadero"
    ],
    "wof:name":"Rodadero",
    "wof:placetype":"locality"
},
  "geometry": {"coordinates":[-109.0882,29.73224],"type":"Point"}
}