{
  "type": "Feature",
  "properties": {
    "gn:admin1_code":"6",
    "gn:admin2_code":"27.0",
    "gn:asciiname":"Sarabeachi",
    "gn:country_code":"MX",
    "gn:dem":2145,
    "gn:feature_class":"P",
    "gn:feature_code":"PPL",
    "gn:name":"Sarabeachi",
    "gn:population":81,
    "gn:timezone":"America/Chihuahua",
    "iso:country":"MX",
    "name:spa_x_preferred":[
        "Sarabeachi"
    ],
    "wof:name":"Sarabeachi",
    "wof:placetype":"locality",
    "wof:population":81
},
  "geometry": {"coordinates":[-107.14628999999999,27.19965],"type":"Point"}
}