{
  "type": "Feature",
  "properties": {
    "gn:admin1_code":"2",
    "gn:admin2_code":"2.0",
    "gn:asciiname":"El Misterioso",
    "gn:country_code":"MX",
    "gn:dem":7,
    "gn:feature_class":"P",
    "gn:feature_code":"PPL",
    "gn:name":"El Misterioso",
    "gn:population":0,
    "gn:timezone":"America/Tijuana",
    "iso:country":"MX",
    "wof:name":"El Misterioso",
    "wof:placetype":"locality"
},
  "geometry": {"coordinates":[-115.22574,32.18852],"type":"Point"}
}