{
  "type": "Feature",
  "properties": {
    "gn:admin1_code":"20",
    "gn:admin2_code":"71",
    "gn:asciiname":"Las Flores",
    "gn:country_code":"MX",
    "gn:dem":670,
    "gn:feature_class":"P",
    "gn:feature_code":"PPL",
    "gn:name":"Las Flores",
    "gn:population":25,
    "gn:timezone":"America/Mexico_City",
    "iso:country":"MX",
    "wof:name":"Las Flores",
    "wof:placetype":"locality",
    "wof:population":25
},
  "geometry": {"coordinates":[-96.45417,15.8975],"type":"Point"}
}