{
  "type": "Feature",
  "properties": {
    "gn:admin1_code":"5",
    "gn:admin2_code":"54.0",
    "gn:asciiname":"Cuatro Rios",
    "gn:cc2":"MX",
    "gn:country_code":"MX",
    "gn:dem":12,
    "gn:feature_class":"P",
    "gn:feature_code":"PPL",
    "gn:name":"Cuatro R\u00edos",
    "gn:population":0,
    "gn:timezone":"America/Mexico_City",
    "iso:country":"MX",
    "name:und_x_variant":[
        "Finca Cuatro Rios",
        "Cuatre Rios",
        "Cuatro R\u00edos"
    ],
    "wof:name":"Cuatro Rios",
    "wof:placetype":"locality"
},
  "geometry": {"coordinates":[-92.43333,14.78333],"type":"Point"}
}