{
  "type": "Feature",
  "properties": {
    "gn:admin1_code":"17",
    "gn:asciiname":"San Lorenzo Nenamicoyan",
    "gn:country_code":"MX",
    "gn:dem":2773,
    "gn:feature_class":"P",
    "gn:feature_code":"PPL",
    "gn:name":"San Lorenzo Nenamicoyan",
    "gn:population":0,
    "gn:timezone":"America/Mexico_City",
    "iso:country":"MX",
    "name:spa_x_preferred":[
        "San Lorenzo Nenamicoyan"
    ],
    "wof:name":"San Lorenzo Nenamicoyan",
    "wof:placetype":"locality"
},
  "geometry": {"coordinates":[-99.63876999999999,20.13699],"type":"Point"}
}