{
  "type": "Feature",
  "properties": {
    "gn:admin1_code":"6",
    "gn:admin2_code":"29.0",
    "gn:asciiname":"Rancheria Ojo Frio de Abajo",
    "gn:country_code":"MX",
    "gn:dem":2517,
    "gn:feature_class":"P",
    "gn:feature_code":"PPL",
    "gn:name":"Rancher\u00eda Ojo Fr\u00edo de Abajo",
    "gn:population":0,
    "gn:timezone":"America/Chihuahua",
    "iso:country":"MX",
    "name:spa_x_preferred":[
        "Rancher\u00eda Ojo Fr\u00edo de Abajo"
    ],
    "name:und_x_variant":[
        "Ojo Fr\u00edo"
    ],
    "wof:name":"Rancheria Ojo Frio de Abajo",
    "wof:placetype":"locality"
},
  "geometry": {"coordinates":[-106.8746,26.07699],"type":"Point"}
}