{
  "type": "Feature",
  "properties": {
    "gn:admin1_code":"30",
    "gn:admin2_code":"24.0",
    "gn:asciiname":"Xotla",
    "gn:country_code":"MX",
    "gn:dem":202,
    "gn:feature_class":"P",
    "gn:feature_code":"PPL",
    "gn:name":"Xotla",
    "gn:population":354,
    "gn:timezone":"America/Mexico_City",
    "iso:country":"MX",
    "wof:name":"Xotla",
    "wof:placetype":"locality",
    "wof:population":354
},
  "geometry": {"coordinates":[-96.61028,19.33028],"type":"Point"}
}