{
  "type": "Feature",
  "properties": {
    "gn:admin1_code":"5",
    "gn:admin2_code":"108.0",
    "gn:asciiname":"El Oeste",
    "gn:country_code":"MX",
    "gn:dem":603,
    "gn:feature_class":"P",
    "gn:feature_code":"PPL",
    "gn:name":"El Oeste",
    "gn:population":4,
    "gn:timezone":"America/Mexico_City",
    "iso:country":"MX",
    "wof:name":"El Oeste",
    "wof:placetype":"locality",
    "wof:population":4
},
  "geometry": {"coordinates":[-93.27528,16.27028],"type":"Point"}
}