{
  "type": "Feature",
  "properties": {
    "gn:admin1_code":"13",
    "gn:asciiname":"Tepexcatitlan",
    "gn:country_code":"MX",
    "gn:dem":2598,
    "gn:feature_class":"P",
    "gn:feature_code":"PPL",
    "gn:name":"Tepexcatitl\u00e1n",
    "gn:population":0,
    "gn:timezone":"America/Mexico_City",
    "iso:country":"MX",
    "wof:name":"Tepexcatitlan",
    "wof:placetype":"locality"
},
  "geometry": {"coordinates":[-99.61667,19.35],"type":"Point"}
}