{
  "type": "Feature",
  "properties": {
    "gn:admin1_code":"21",
    "gn:admin2_code":"83.0",
    "gn:asciiname":"San Antonio de los Pinos",
    "gn:country_code":"MX",
    "gn:dem":2785,
    "gn:feature_class":"P",
    "gn:feature_code":"PPL",
    "gn:name":"San Antonio de los Pinos",
    "gn:population":0,
    "gn:timezone":"America/Mexico_City",
    "iso:country":"MX",
    "name:spa_x_preferred":[
        "San Antonio de los Pinos"
    ],
    "name:und_x_variant":[
        "Los Pinos"
    ],
    "wof:name":"San Antonio de los Pinos",
    "wof:placetype":"locality"
},
  "geometry": {"coordinates":[-97.97574,19.68555],"type":"Point"}
}