{
  "type": "Feature",
  "properties": {
    "gn:admin1_code":"19",
    "gn:admin2_code":"38.0",
    "gn:asciiname":"Canoas",
    "gn:country_code":"MX",
    "gn:dem":438,
    "gn:feature_class":"P",
    "gn:feature_code":"PPL",
    "gn:name":"Canoas",
    "gn:population":0,
    "gn:timezone":"America/Monterrey",
    "iso:country":"MX",
    "name:spa_x_preferred":[
        "Canoas"
    ],
    "wof:name":"Canoas",
    "wof:placetype":"locality"
},
  "geometry": {"coordinates":[-99.95532,25.24366],"type":"Point"}
}