{
  "type": "Feature",
  "properties": {
    "gn:admin1_code":"24",
    "gn:admin2_code":"37.0",
    "gn:asciiname":"Atehuac",
    "gn:country_code":"MX",
    "gn:dem":189,
    "gn:feature_class":"P",
    "gn:feature_code":"PPL",
    "gn:name":"Atehuac",
    "gn:population":334,
    "gn:timezone":"America/Mexico_City",
    "iso:country":"MX",
    "wof:name":"Atehuac",
    "wof:placetype":"locality",
    "wof:population":334
},
  "geometry": {"coordinates":[-98.78639,21.18806],"type":"Point"}
}