{
  "type": "Feature",
  "properties": {
    "gn:admin1_code":"5",
    "gn:admin2_code":"107.0",
    "gn:asciiname":"La Joya",
    "gn:country_code":"MX",
    "gn:dem":751,
    "gn:feature_class":"P",
    "gn:feature_code":"PPL",
    "gn:name":"La Joya",
    "gn:population":7,
    "gn:timezone":"America/Mexico_City",
    "iso:country":"MX",
    "wof:name":"La Joya",
    "wof:placetype":"locality",
    "wof:population":7
},
  "geometry": {"coordinates":[-93.08,16.26111],"type":"Point"}
}