{
  "type": "Feature",
  "properties": {
    "gn:admin1_code":"16",
    "gn:admin2_code":"77.0",
    "gn:asciiname":"La Chica",
    "gn:country_code":"MX",
    "gn:dem":261,
    "gn:feature_class":"P",
    "gn:feature_code":"PPL",
    "gn:name":"La Chica",
    "gn:population":92,
    "gn:timezone":"America/Mexico_City",
    "iso:country":"MX",
    "wof:name":"La Chica",
    "wof:placetype":"locality",
    "wof:population":92
},
  "geometry": {"coordinates":[-100.62166999999999,18.37806],"type":"Point"}
}