{
  "type": "Feature",
  "properties": {
    "gn:admin1_code":"28.0",
    "gn:admin2_code":"21.0",
    "gn:asciiname":"El Huastequillo",
    "gn:country_code":"MX",
    "gn:dem":85,
    "gn:feature_class":"P",
    "gn:feature_code":"PPL",
    "gn:name":"El Huastequillo",
    "gn:population":130,
    "gn:timezone":"America/Monterrey",
    "iso:country":"MX",
    "name:spa_x_preferred":[
        "El Huastequillo"
    ],
    "wof:name":"El Huastequillo",
    "wof:placetype":"locality",
    "wof:population":130
},
  "geometry": {"coordinates":[-98.96194,22.69],"type":"Point"}
}