{
  "type": "Feature",
  "properties": {
    "gn:admin1_code":"31",
    "gn:admin2_code":"57.0",
    "gn:asciiname":"Mocche",
    "gn:country_code":"MX",
    "gn:dem":14,
    "gn:feature_class":"P",
    "gn:feature_code":"PPL",
    "gn:name":"Mocch\u00e9",
    "gn:population":0,
    "gn:timezone":"America/Merida",
    "iso:country":"MX",
    "name:spa_x_preferred":[
        "Mocch\u00e9"
    ],
    "wof:name":"Mocche",
    "wof:placetype":"locality"
},
  "geometry": {"coordinates":[-88.28907,21.32625],"type":"Point"}
}