{
  "type": "Feature",
  "properties": {
    "gn:admin1_code":"6",
    "gn:admin2_code":"32.0",
    "gn:asciiname":"Palomas",
    "gn:country_code":"MX",
    "gn:dem":1549,
    "gn:feature_class":"P",
    "gn:feature_code":"PPL",
    "gn:name":"Palomas",
    "gn:population":0,
    "gn:timezone":"America/Chihuahua",
    "iso:country":"MX",
    "name:cat_x_preferred":[
        "Palomas"
    ],
    "name:ceb_x_preferred":[
        "Palomas"
    ],
    "name:deu_x_preferred":[
        "Palomas"
    ],
    "name:nld_x_preferred":[
        "Palomas"
    ],
    "name:pol_x_preferred":[
        "Palomas"
    ],
    "name:spa_x_preferred":[
        "Palomas"
    ],
    "name:srp_x_preferred":[
        "\u041f\u0430\u043b\u043e\u043c\u0430\u0441"
    ],
    "name:swe_x_preferred":[
        "Palomas"
    ],
    "wof:name":"Palomas",
    "wof:placetype":"locality"
},
  "geometry": {"coordinates":[-105.89713999999999,27.1621],"type":"Point"}
}