{
  "type": "Feature",
  "properties": {
    "gn:admin1_code":"30",
    "gn:asciiname":"El Naranjal",
    "gn:country_code":"MX",
    "gn:dem":80,
    "gn:feature_class":"P",
    "gn:feature_code":"PPL",
    "gn:name":"El Naranjal",
    "gn:population":0,
    "gn:timezone":"America/Mexico_City",
    "iso:country":"MX",
    "name:spa_x_preferred":[
        "El Naranjal"
    ],
    "wof:name":"El Naranjal",
    "wof:placetype":"locality"
},
  "geometry": {"coordinates":[-96.40523,18.41233],"type":"Point"}
}