{
  "type": "Feature",
  "properties": {
    "gn:admin1_code":"31",
    "gn:admin2_code":"30.0",
    "gn:asciiname":"Mul-itza",
    "gn:country_code":"MX",
    "gn:dem":29,
    "gn:feature_class":"P",
    "gn:feature_code":"PPL",
    "gn:name":"Mul-itza",
    "gn:population":0,
    "gn:timezone":"America/Merida",
    "iso:country":"MX",
    "name:spa_x_preferred":[
        "Mul-itza"
    ],
    "wof:name":"Mul-itza",
    "wof:placetype":"locality"
},
  "geometry": {"coordinates":[-88.49476999999997,20.86664],"type":"Point"}
}