{
  "type": "Feature",
  "properties": {
    "gn:admin1_code":"25",
    "gn:admin2_code":"4.0",
    "gn:asciiname":"Chirimollos",
    "gn:country_code":"MX",
    "gn:dem":1574,
    "gn:feature_class":"P",
    "gn:feature_code":"PPL",
    "gn:name":"Chirimollos",
    "gn:population":0,
    "gn:timezone":"America/Mazatlan",
    "iso:country":"MX",
    "name:spa_x_preferred":[
        "Chirimollos"
    ],
    "wof:name":"Chirimollos",
    "wof:placetype":"locality"
},
  "geometry": {"coordinates":[-105.81016,23.43574],"type":"Point"}
}