{
  "type": "Feature",
  "properties": {
    "gn:admin1_code":"6",
    "gn:asciiname":"La Cienega de Camilo",
    "gn:country_code":"MX",
    "gn:dem":1518,
    "gn:feature_class":"P",
    "gn:feature_code":"PPL",
    "gn:name":"La Ci\u00e9nega de Camilo",
    "gn:population":0,
    "gn:timezone":"America/Chihuahua",
    "iso:country":"MX",
    "name:spa_x_preferred":[
        "La Ci\u00e9nega de Camilo"
    ],
    "wof:name":"La Cienega de Camilo",
    "wof:placetype":"locality"
},
  "geometry": {"coordinates":[-108.56583000000001,28.42859],"type":"Point"}
}