{
  "type": "Feature",
  "properties": {
    "gn:admin1_code":"6",
    "gn:admin2_code":"9.0",
    "gn:asciiname":"Guichajorare",
    "gn:country_code":"MX",
    "gn:dem":2436,
    "gn:feature_class":"P",
    "gn:feature_code":"PPL",
    "gn:name":"Guichajorare",
    "gn:population":8,
    "gn:timezone":"America/Chihuahua",
    "iso:country":"MX",
    "wof:name":"Guichajorare",
    "wof:placetype":"locality",
    "wof:population":8
},
  "geometry": {"coordinates":[-107.42076000000002,27.86686],"type":"Point"}
}