{
  "type": "Feature",
  "properties": {
    "gn:admin1_code":"14",
    "gn:admin2_code":"97",
    "gn:asciiname":"Aldea India",
    "gn:country_code":"MX",
    "gn:dem":1547,
    "gn:feature_class":"P",
    "gn:feature_code":"PPL",
    "gn:name":"Aldea India",
    "gn:population":23,
    "gn:timezone":"America/Mexico_City",
    "iso:country":"MX",
    "wof:name":"Aldea India",
    "wof:placetype":"locality",
    "wof:population":23
},
  "geometry": {"coordinates":[-103.26278000000001,20.47222],"type":"Point"}
}