{
  "type": "Feature",
  "properties": {
    "gn:admin1_code":"16",
    "gn:admin2_code":"97.0",
    "gn:asciiname":"Ojo de Agua de los Maldonado",
    "gn:country_code":"MX",
    "gn:dem":781,
    "gn:feature_class":"P",
    "gn:feature_code":"PPL",
    "gn:name":"Ojo de Agua de los Maldonado",
    "gn:population":134,
    "gn:timezone":"America/Mexico_City",
    "iso:country":"MX",
    "wof:name":"Ojo de Agua de los Maldonado",
    "wof:placetype":"locality",
    "wof:population":134
},
  "geometry": {"coordinates":[-101.43944,18.86861],"type":"Point"}
}