{
  "type": "Feature",
  "properties": {
    "gn:admin1_code":"25.0",
    "gn:admin2_code":"7.0",
    "gn:asciiname":"Agua Prietilla",
    "gn:country_code":"MX",
    "gn:dem":305,
    "gn:feature_class":"P",
    "gn:feature_code":"PPL",
    "gn:name":"Agua Prietilla",
    "gn:population":0,
    "gn:timezone":"America/Mazatlan",
    "iso:country":"MX",
    "name:spa_x_preferred":[
        "Agua Prietilla"
    ],
    "wof:name":"Agua Prietilla",
    "wof:placetype":"locality"
},
  "geometry": {"coordinates":[-108.28099,26.729],"type":"Point"}
}