{
  "type": "Feature",
  "properties": {
    "gn:admin1_code":"20",
    "gn:admin2_code":"450.0",
    "gn:asciiname":"Piedra Liza",
    "gn:country_code":"MX",
    "gn:dem":1252,
    "gn:feature_class":"P",
    "gn:feature_code":"PPL",
    "gn:name":"Piedra Liza",
    "gn:population":0,
    "gn:timezone":"America/Mexico_City",
    "iso:country":"MX",
    "name:spa_x_preferred":[
        "Piedra Liza"
    ],
    "wof:name":"Piedra Liza",
    "wof:placetype":"locality"
},
  "geometry": {"coordinates":[-97.52011,16.63148],"type":"Point"}
}