{
  "type": "Feature",
  "properties": {
    "gn:admin1_code":"25",
    "gn:admin2_code":"6.0",
    "gn:asciiname":"Ganadera Verdugo",
    "gn:country_code":"MX",
    "gn:dem":66,
    "gn:feature_class":"P",
    "gn:feature_code":"PPL",
    "gn:name":"Ganadera Verdugo",
    "gn:population":6,
    "gn:timezone":"America/Mazatlan",
    "iso:country":"MX",
    "wof:name":"Ganadera Verdugo",
    "wof:placetype":"locality",
    "wof:population":6
},
  "geometry": {"coordinates":[-107.52423,24.9222],"type":"Point"}
}