{
  "type": "Feature",
  "properties": {
    "gn:admin1_code":"24",
    "gn:admin2_code":"37.0",
    "gn:asciiname":"Aguacate",
    "gn:country_code":"MX",
    "gn:dem":117,
    "gn:feature_class":"P",
    "gn:feature_code":"PPL",
    "gn:name":"Aguacate",
    "gn:population":0,
    "gn:timezone":"America/Mexico_City",
    "iso:country":"MX",
    "name:ceb_x_preferred":[
        "Aguacate"
    ],
    "name:nds_x_preferred":[
        "Aguacate"
    ],
    "name:spa_x_preferred":[
        "Aguacate"
    ],
    "name:swe_x_preferred":[
        "Aguacate"
    ],
    "wof:name":"Aguacate",
    "wof:placetype":"locality"
},
  "geometry": {"coordinates":[-98.71666999999999,21.28333],"type":"Point"}
}