{
  "type": "Feature",
  "properties": {
    "gn:admin1_code":"30",
    "gn:admin2_code":"32.0",
    "gn:asciiname":"Boca del Monte",
    "gn:country_code":"MX",
    "gn:dem":442,
    "gn:feature_class":"P",
    "gn:feature_code":"PPL",
    "gn:name":"Boca del Monte",
    "gn:population":5,
    "gn:timezone":"America/Mexico_City",
    "iso:country":"MX",
    "name:ita_x_preferred":[
        "Boca del Monte"
    ],
    "name:spa_x_preferred":[
        "Boca del Monte"
    ],
    "name:zho_x_preferred":[
        "\u535a\u5361\u5fb7\u5c14\u8499\u7279"
    ],
    "wof:name":"Boca del Monte",
    "wof:placetype":"locality",
    "wof:population":5
},
  "geometry": {"coordinates":[-95.07666999999999,18.46667],"type":"Point"}
}