{
  "type": "Feature",
  "properties": {
    "gn:admin1_code":"11",
    "gn:admin2_code":"26.0",
    "gn:asciiname":"El Tecolote",
    "gn:country_code":"MX",
    "gn:dem":1741,
    "gn:feature_class":"P",
    "gn:feature_code":"PPL",
    "gn:name":"El Tecolote",
    "gn:population":67,
    "gn:timezone":"America/Mexico_City",
    "iso:country":"MX",
    "name:ceb_x_preferred":[
        "El Tecolote"
    ],
    "name:swe_x_preferred":[
        "El Tecolote"
    ],
    "wof:name":"El Tecolote",
    "wof:placetype":"locality",
    "wof:population":67
},
  "geometry": {"coordinates":[-101.48193999999999,20.82417],"type":"Point"}
}