{
  "type": "Feature",
  "properties": {
    "gn:admin1_code":"19",
    "gn:admin2_code":"15.0",
    "gn:asciiname":"Las Adjuntas",
    "gn:country_code":"MX",
    "gn:dem":117,
    "gn:feature_class":"P",
    "gn:feature_code":"PPL",
    "gn:name":"Las Adjuntas",
    "gn:population":2,
    "gn:timezone":"America/Monterrey",
    "iso:country":"MX",
    "wof:name":"Las Adjuntas",
    "wof:placetype":"locality",
    "wof:population":2
},
  "geometry": {"coordinates":[-99.18662999999999,25.90681],"type":"Point"}
}