{
  "type": "Feature",
  "properties": {
    "gn:admin1_code":"14",
    "gn:admin2_code":"116",
    "gn:asciiname":"Ejido Santa Teresa",
    "gn:country_code":"MX",
    "gn:dem":1980,
    "gn:feature_class":"P",
    "gn:feature_code":"PPL",
    "gn:name":"Ejido Santa Teresa",
    "gn:population":37,
    "gn:timezone":"America/Mexico_City",
    "iso:country":"MX",
    "wof:name":"Ejido Santa Teresa",
    "wof:placetype":"locality",
    "wof:population":37
},
  "geometry": {"coordinates":[-102.60861,21.68167],"type":"Point"}
}