{
  "type": "Feature",
  "properties": {
    "gn:admin1_code":"2",
    "gn:admin2_code":"3.0",
    "gn:asciiname":"El Orusos",
    "gn:country_code":"MX",
    "gn:dem":831,
    "gn:feature_class":"P",
    "gn:feature_code":"PPL",
    "gn:name":"El Orusos",
    "gn:population":5,
    "gn:timezone":"America/Tijuana",
    "iso:country":"MX",
    "wof:name":"El Orusos",
    "wof:placetype":"locality",
    "wof:population":5
},
  "geometry": {"coordinates":[-116.44777999999999,32.56028],"type":"Point"}
}