{
  "type": "Feature",
  "properties": {
    "gn:admin1_code":"2.0",
    "gn:admin2_code":"3.0",
    "gn:asciiname":"Quinta Maria Luisa",
    "gn:country_code":"MX",
    "gn:dem":598,
    "gn:feature_class":"P",
    "gn:feature_code":"PPL",
    "gn:name":"Quinta Mar\u00eda Luisa",
    "gn:population":8,
    "gn:timezone":"America/Tijuana",
    "iso:country":"MX",
    "name:spa_x_preferred":[
        "Mar\u00eda Luisa"
    ],
    "wof:name":"Quinta Maria Luisa",
    "wof:placetype":"locality",
    "wof:population":8
},
  "geometry": {"coordinates":[-116.62944,32.53556],"type":"Point"}
}