{
  "type": "Feature",
  "properties": {
    "gn:admin1_code":"2",
    "gn:admin2_code":"1.0",
    "gn:asciiname":"Cuarteria los Grillos",
    "gn:country_code":"MX",
    "gn:dem":36,
    "gn:feature_class":"P",
    "gn:feature_code":"PPL",
    "gn:name":"Cuarter\u00eda los Grillos",
    "gn:population":68,
    "gn:timezone":"America/Tijuana",
    "iso:country":"MX",
    "name:und_x_variant":[
        "Cuarter\u00eda los Grillos"
    ],
    "wof:name":"Cuarteria los Grillos",
    "wof:placetype":"locality",
    "wof:population":68
},
  "geometry": {"coordinates":[-116.04778,30.85417],"type":"Point"}
}