{
  "type": "Feature",
  "properties": {
    "gn:admin1_code":"5",
    "gn:admin2_code":"65",
    "gn:asciiname":"Romo",
    "gn:country_code":"MX",
    "gn:dem":180,
    "gn:feature_class":"P",
    "gn:feature_code":"PPL",
    "gn:name":"Romo",
    "gn:population":23,
    "gn:timezone":"America/Mexico_City",
    "iso:country":"MX",
    "name:jpn_x_preferred":[
        "\u30ed\u30de\u30f3\u30c6\u30a3\u30c3\u30af\u30fb\u30e2\u30c0\u30cb\u30ba\u30e0"
    ],
    "wof:name":"Romo",
    "wof:placetype":"locality",
    "wof:population":23
},
  "geometry": {"coordinates":[-91.56889,17.2325],"type":"Point"}
}