{
  "type": "Feature",
  "properties": {
    "gn:admin1_code":"5",
    "gn:admin2_code":"65.0",
    "gn:asciiname":"La Jahua",
    "gn:country_code":"MX",
    "gn:dem":62,
    "gn:feature_class":"P",
    "gn:feature_code":"PPL",
    "gn:name":"La Jahua",
    "gn:population":7,
    "gn:timezone":"America/Mexico_City",
    "iso:country":"MX",
    "wof:name":"La Jahua",
    "wof:placetype":"locality",
    "wof:population":7
},
  "geometry": {"coordinates":[-91.94444,17.59083],"type":"Point"}
}