{
  "type": "Feature",
  "properties": {
    "gn:admin1_code":"14",
    "gn:admin2_code":"25",
    "gn:asciiname":"El Terrero",
    "gn:country_code":"MX",
    "gn:dem":1687,
    "gn:feature_class":"P",
    "gn:feature_code":"PPL",
    "gn:name":"El Terrero",
    "gn:population":12,
    "gn:timezone":"America/Mexico_City",
    "iso:country":"MX",
    "wof:name":"El Terrero",
    "wof:placetype":"locality",
    "wof:population":12
},
  "geometry": {"coordinates":[-103.24388999999999,22.14806],"type":"Point"}
}