{
  "type": "Feature",
  "properties": {
    "gn:admin1_code":"5",
    "gn:admin2_code":"108.0",
    "gn:asciiname":"La Esmeralda",
    "gn:country_code":"MX",
    "gn:dem":676,
    "gn:feature_class":"P",
    "gn:feature_code":"PPL",
    "gn:name":"La Esmeralda",
    "gn:population":5,
    "gn:timezone":"America/Mexico_City",
    "iso:country":"MX",
    "wof:name":"La Esmeralda",
    "wof:placetype":"locality",
    "wof:population":5
},
  "geometry": {"coordinates":[-93.42889,16.29444],"type":"Point"}
}