{
  "type": "Feature",
  "properties": {
    "gn:admin1_code":"10",
    "gn:admin2_code":"26.0",
    "gn:asciiname":"El Palmillar",
    "gn:country_code":"MX",
    "gn:dem":1119,
    "gn:feature_class":"P",
    "gn:feature_code":"PPL",
    "gn:name":"El Palmillar",
    "gn:population":64,
    "gn:timezone":"America/Mazatlan",
    "iso:country":"MX",
    "wof:name":"El Palmillar",
    "wof:placetype":"locality",
    "wof:population":64
},
  "geometry": {"coordinates":[-105.92307,23.67334],"type":"Point"}
}