{
  "type": "Feature",
  "properties": {
    "gn:admin1_code":"24.0",
    "gn:admin2_code":"16.0",
    "gn:asciiname":"El Veintitres",
    "gn:country_code":"MX",
    "gn:dem":18,
    "gn:feature_class":"P",
    "gn:feature_code":"PPL",
    "gn:name":"El Veintitres",
    "gn:population":0,
    "gn:timezone":"America/Mexico_City",
    "iso:country":"MX",
    "name:spa_x_preferred":[
        "El Veintitres"
    ],
    "name:spa_x_variant":[
        "Laguna Seca"
    ],
    "wof:name":"El Veintitres",
    "wof:placetype":"locality"
},
  "geometry": {"coordinates":[-98.4689,22.17165],"type":"Point"}
}