{
  "type": "Feature",
  "properties": {
    "gn:admin1_code":"26.0",
    "gn:admin2_code":"39.0",
    "gn:asciiname":"La Puerta de Bonaran",
    "gn:country_code":"MX",
    "gn:dem":1596,
    "gn:feature_class":"P",
    "gn:feature_code":"PPL",
    "gn:name":"La Puerta de Bonar\u00e1n",
    "gn:population":0,
    "gn:timezone":"America/Hermosillo",
    "iso:country":"MX",
    "name:spa_x_preferred":[
        "La Puerta de Bonar\u00e1n"
    ],
    "wof:name":"La Puerta de Bonaran",
    "wof:placetype":"locality"
},
  "geometry": {"coordinates":[-109.99266,31.2836],"type":"Point"}
}