{
  "type": "Feature",
  "properties": {
    "gn:admin1_code":"7.0",
    "gn:admin2_code":"8.0",
    "gn:asciiname":"Lampacitos Viejo",
    "gn:country_code":"MX",
    "gn:dem":397,
    "gn:feature_class":"P",
    "gn:feature_code":"PPL",
    "gn:name":"Lampacitos Viejo",
    "gn:population":0,
    "gn:timezone":"America/Monterrey",
    "iso:country":"MX",
    "name:spa_x_preferred":[
        "Lampacitos Viejo"
    ],
    "wof:name":"Lampacitos Viejo",
    "wof:placetype":"locality"
},
  "geometry": {"coordinates":[-101.29967000000001,27.39178],"type":"Point"}
}