{
  "type": "Feature",
  "properties": {
    "gn:admin1_code":"22",
    "gn:admin2_code":"14.0",
    "gn:asciiname":"Loma Real de Queretaro [Fraccionamiento]",
    "gn:country_code":"MX",
    "gn:dem":1884,
    "gn:feature_class":"P",
    "gn:feature_code":"PPL",
    "gn:name":"Loma Real de Quer\u00e9taro [Fraccionamiento]",
    "gn:population":128,
    "gn:timezone":"America/Mexico_City",
    "iso:country":"MX",
    "name:und_x_variant":[
        "Loma Real de Quer\u00e9taro [Fraccionamiento]"
    ],
    "wof:name":"Loma Real de Queretaro [Fraccionamiento]",
    "wof:placetype":"locality",
    "wof:population":128
},
  "geometry": {"coordinates":[-100.47417,20.63861],"type":"Point"}
}