{
  "type": "Feature",
  "properties": {
    "gn:admin1_code":"18.0",
    "gn:admin2_code":"20.0",
    "gn:asciiname":"Conchas",
    "gn:cc2":"MX",
    "gn:country_code":"MX",
    "gn:dem":32,
    "gn:feature_class":"P",
    "gn:feature_code":"PPL",
    "gn:name":"Conchas",
    "gn:population":0,
    "gn:timezone":"America/Bahia_Banderas",
    "iso:country":"MX",
    "name:und_x_variant":[
        "Concha",
        "Conchas"
    ],
    "wof:name":"Conchas",
    "wof:placetype":"locality"
},
  "geometry": {"coordinates":[-105.25,20.76667],"type":"Point"}
}