{
  "type": "Feature",
  "properties": {
    "gn:admin1_code":"18.0",
    "gn:admin2_code":"20.0",
    "gn:asciiname":"Conchas",
    "gn:cc2":"MX",
    "gn:country_code":"MX",
    "gn:dem":32,
    "gn:feature_class":"P",
    "gn:feature_code":"PPL",
    "gn:name":"Conchas",
    "gn:population":0,
    "gn:timezone":"America/Bahia_Banderas",
    "iso:country":"MX",
    "name:bpy_x_preferred":[
        "\u0995\u09cb\u09a8\u099a\u09be\u09b8"
    ],
    "name:ceb_x_preferred":[
        "Conchas"
    ],
    "name:epo_x_preferred":[
        "Conchas"
    ],
    "name:eus_x_preferred":[
        "Conchas"
    ],
    "name:fra_x_preferred":[
        "Conchas"
    ],
    "name:ita_x_preferred":[
        "Conchas"
    ],
    "name:kaz_x_preferred":[
        "\u041a\u043e\u043d\u0448\u0430\u0441"
    ],
    "name:mlg_x_preferred":[
        "Conchas"
    ],
    "name:nld_x_preferred":[
        "Conchas"
    ],
    "name:nor_x_preferred":[
        "Conchas"
    ],
    "name:pol_x_preferred":[
        "Conchas"
    ],
    "name:por_x_preferred":[
        "Conchas"
    ],
    "name:ron_x_preferred":[
        "Conchas"
    ],
    "name:rus_x_preferred":[
        "\u041a\u043e\u043d\u0448\u0430\u0441"
    ],
    "name:swe_x_preferred":[
        "Conchas"
    ],
    "name:und_x_variant":[
        "Concha",
        "Conchas"
    ],
    "name:vie_x_preferred":[
        "Conchas"
    ],
    "name:vol_x_preferred":[
        "Conchas"
    ],
    "name:war_x_preferred":[
        "Conchas"
    ],
    "name:zho_x_preferred":[
        "\u5b54\u67e5\u65af"
    ],
    "wof:name":"Conchas",
    "wof:placetype":"locality"
},
  "geometry": {"coordinates":[-105.25,20.76667],"type":"Point"}
}