{
  "type": "Feature",
  "properties": {
    "gn:admin1_code":"25",
    "gn:admin2_code":"16.0",
    "gn:asciiname":"Colompo",
    "gn:country_code":"MX",
    "gn:dem":198,
    "gn:feature_class":"P",
    "gn:feature_code":"PPL",
    "gn:name":"Colompo",
    "gn:population":0,
    "gn:timezone":"America/Mazatlan",
    "iso:country":"MX",
    "name:spa_x_preferred":[
        "Chacualtita"
    ],
    "wof:name":"Colompo",
    "wof:placetype":"locality"
},
  "geometry": {"coordinates":[-106.44135,23.98903],"type":"Point"}
}