{
  "type": "Feature",
  "properties": {
    "gn:admin1_code":"30",
    "gn:admin2_code":"189.0",
    "gn:asciiname":"El Remate",
    "gn:country_code":"MX",
    "gn:dem":25,
    "gn:feature_class":"P",
    "gn:feature_code":"PPL",
    "gn:name":"El Remate",
    "gn:population":0,
    "gn:timezone":"America/Mexico_City",
    "iso:country":"MX",
    "name:spa_x_preferred":[
        "El Remate"
    ],
    "name:und_x_variant":[
        "Remate"
    ],
    "wof:name":"El Remate",
    "wof:placetype":"locality"
},
  "geometry": {"coordinates":[-97.44338,21.00923],"type":"Point"}
}