{
  "type": "Feature",
  "properties": {
    "gn:admin1_code":"16",
    "gn:admin2_code":"12",
    "gn:asciiname":"Paraje el Seis",
    "gn:country_code":"MX",
    "gn:dem":722,
    "gn:feature_class":"P",
    "gn:feature_code":"PPL",
    "gn:name":"Paraje el Seis",
    "gn:population":25,
    "gn:timezone":"America/Mexico_City",
    "iso:country":"MX",
    "wof:name":"Paraje el Seis",
    "wof:placetype":"locality",
    "wof:population":25
},
  "geometry": {"coordinates":[-102.55777999999999,19.28972000000001],"type":"Point"}
}