{
  "type": "Feature",
  "properties": {
    "gn:admin1_code":"32.0",
    "gn:admin2_code":"26.0",
    "gn:asciiname":"El Mesquite",
    "gn:country_code":"MX",
    "gn:dem":1876,
    "gn:feature_class":"P",
    "gn:feature_code":"PPL",
    "gn:name":"El Mesquite",
    "gn:population":0,
    "gn:timezone":"America/Mexico_City",
    "iso:country":"MX",
    "wof:name":"El Mesquite",
    "wof:placetype":"locality"
},
  "geometry": {"coordinates":[-102.06667,24.61667000000001],"type":"Point"}
}