{
  "type": "Feature",
  "properties": {
    "gn:admin1_code":"6.0",
    "gn:admin2_code":"63.0",
    "gn:asciiname":"El Canon",
    "gn:country_code":"MX",
    "gn:dem":1964,
    "gn:feature_class":"P",
    "gn:feature_code":"PPL",
    "gn:name":"El Ca\u00f1\u00f3n",
    "gn:population":0,
    "gn:timezone":"America/Chihuahua",
    "iso:country":"MX",
    "wof:name":"El Canon",
    "wof:placetype":"locality"
},
  "geometry": {"coordinates":[-107.88333,29.11667000000001],"type":"Point"}
}