{
  "type": "Feature",
  "properties": {
    "gn:admin1_code":"5",
    "gn:admin2_code":"59.0",
    "gn:asciiname":"Nuevo Tumbala",
    "gn:country_code":"MX",
    "gn:dem":355,
    "gn:feature_class":"P",
    "gn:feature_code":"PPL",
    "gn:name":"Nuevo Tumbal\u00e1",
    "gn:population":123,
    "gn:timezone":"America/Mexico_City",
    "iso:country":"MX",
    "name:und_x_variant":[
        "Nuevo Tumbal\u00e1"
    ],
    "wof:name":"Nuevo Tumbala",
    "wof:placetype":"locality",
    "wof:population":123
},
  "geometry": {"coordinates":[-91.24250000000001,16.9825],"type":"Point"}
}