{
  "type": "Feature",
  "properties": {
    "gn:admin1_code":"30",
    "gn:admin2_code":"92.0",
    "gn:asciiname":"La Chiveria",
    "gn:country_code":"MX",
    "gn:dem":993,
    "gn:feature_class":"P",
    "gn:feature_code":"PPL",
    "gn:name":"La Chiver\u00eda",
    "gn:population":176,
    "gn:timezone":"America/Mexico_City",
    "iso:country":"MX",
    "name:und_x_variant":[
        "La Chiver\u00eda"
    ],
    "wof:name":"La Chiveria",
    "wof:placetype":"locality",
    "wof:population":176
},
  "geometry": {"coordinates":[-96.92610999999999,19.38972],"type":"Point"}
}