{
  "type": "Feature",
  "properties": {
    "gn:admin1_code":"30",
    "gn:admin2_code":"31.0",
    "gn:asciiname":"El Cedro",
    "gn:country_code":"MX",
    "gn:dem":276,
    "gn:feature_class":"P",
    "gn:feature_code":"PPL",
    "gn:name":"El Cedro",
    "gn:population":73,
    "gn:timezone":"America/Mexico_City",
    "iso:country":"MX",
    "wof:name":"El Cedro",
    "wof:placetype":"locality",
    "wof:population":73
},
  "geometry": {"coordinates":[-96.65639,18.8125],"type":"Point"}
}