{
  "type": "Feature",
  "properties": {
    "gn:admin1_code":"24",
    "gn:admin2_code":"13.0",
    "gn:asciiname":"Los Nopales",
    "gn:country_code":"MX",
    "gn:dem":53,
    "gn:feature_class":"P",
    "gn:feature_code":"PPL",
    "gn:name":"Los Nopales",
    "gn:population":0,
    "gn:timezone":"America/Mexico_City",
    "iso:country":"MX",
    "name:spa_x_preferred":[
        "Los Nopales"
    ],
    "wof:name":"Los Nopales",
    "wof:placetype":"locality"
},
  "geometry": {"coordinates":[-98.96357999999999,21.92682000000001],"type":"Point"}
}