{
  "type": "Feature",
  "properties": {
    "gn:admin1_code":"11",
    "gn:admin2_code":"33.0",
    "gn:asciiname":"Dulces Nombres",
    "gn:country_code":"MX",
    "gn:dem":1985,
    "gn:feature_class":"P",
    "gn:feature_code":"PPL",
    "gn:name":"Dulces Nombres",
    "gn:population":89,
    "gn:timezone":"America/Mexico_City",
    "iso:country":"MX",
    "wof:name":"Dulces Nombres",
    "wof:placetype":"locality",
    "wof:population":89
},
  "geometry": {"coordinates":[-100.59721999999999,21.23],"type":"Point"}
}