{
  "type": "Feature",
  "properties": {
    "gn:admin1_code":"17.0",
    "gn:asciiname":"Jardines de Tlayacapan",
    "gn:country_code":"MX",
    "gn:dem":1574,
    "gn:feature_class":"P",
    "gn:feature_code":"PPL",
    "gn:name":"Jardines de Tlayacapan",
    "gn:population":0,
    "gn:timezone":"America/Mexico_City",
    "iso:country":"MX",
    "name:spa_x_preferred":[
        "Jardines de Tlayacapan"
    ],
    "name:spa_x_variant":[
        "Jard\u00ednes de Tlayacapan"
    ],
    "wof:name":"Jardines de Tlayacapan",
    "wof:placetype":"locality"
},
  "geometry": {"coordinates":[-98.96464,18.93727],"type":"Point"}
}