{
  "type": "Feature",
  "properties": {
    "gn:admin1_code":"14",
    "gn:admin2_code":"53.0",
    "gn:asciiname":"Quinta San Francisco",
    "gn:country_code":"MX",
    "gn:dem":1887,
    "gn:feature_class":"P",
    "gn:feature_code":"PPL",
    "gn:name":"Quinta San Francisco",
    "gn:population":7,
    "gn:timezone":"America/Mexico_City",
    "iso:country":"MX",
    "wof:name":"Quinta San Francisco",
    "wof:placetype":"locality",
    "wof:population":7
},
  "geometry": {"coordinates":[-101.91167,21.40861],"type":"Point"}
}