{
  "type": "Feature",
  "properties": {
    "gn:admin1_code":"30",
    "gn:admin2_code":"155.0",
    "gn:asciiname":"El Ocaso",
    "gn:country_code":"MX",
    "gn:dem":131,
    "gn:feature_class":"P",
    "gn:feature_code":"PPL",
    "gn:name":"El Ocaso",
    "gn:population":3,
    "gn:timezone":"America/Mexico_City",
    "iso:country":"MX",
    "name:spa_x_preferred":[
        "El Ocaso"
    ],
    "wof:name":"El Ocaso",
    "wof:placetype":"locality",
    "wof:population":3
},
  "geometry": {"coordinates":[-98.07554,21.18174],"type":"Point"}
}