{
  "type": "Feature",
  "properties": {
    "gn:admin1_code":"7.0",
    "gn:admin2_code":"27.0",
    "gn:asciiname":"San Miguel",
    "gn:country_code":"MX",
    "gn:dem":958,
    "gn:feature_class":"P",
    "gn:feature_code":"PPL",
    "gn:name":"San Miguel",
    "gn:population":40,
    "gn:timezone":"America/Monterrey",
    "iso:country":"MX",
    "name:spa_x_preferred":[
        "San Miguel"
    ],
    "name:und_x_variant":[
        "Ejido San Miguel"
    ],
    "wof:name":"San Miguel",
    "wof:placetype":"locality",
    "wof:population":40
},
  "geometry": {"coordinates":[-101.27500999999999,25.90448],"type":"Point"}
}