{
  "type": "Feature",
  "properties": {
    "gn:admin1_code":"12",
    "gn:admin2_code":"18.0",
    "gn:asciiname":"La Fortuna (La Yeguada)",
    "gn:country_code":"MX",
    "gn:dem":8,
    "gn:feature_class":"P",
    "gn:feature_code":"PPL",
    "gn:name":"La Fortuna (La Yeguada)",
    "gn:population":140,
    "gn:timezone":"America/Mexico_City",
    "iso:country":"MX",
    "wof:name":"La Fortuna (La Yeguada)",
    "wof:placetype":"locality",
    "wof:population":140
},
  "geometry": {"coordinates":[-99.03769,16.6105],"type":"Point"}
}