{
  "type": "Feature",
  "properties": {
    "gn:admin1_code":"11",
    "gn:admin2_code":"19.0",
    "gn:asciiname":"Cerrito de la Cruz",
    "gn:country_code":"MX",
    "gn:dem":2135,
    "gn:feature_class":"P",
    "gn:feature_code":"PPL",
    "gn:name":"Cerrito de la Cruz",
    "gn:population":119,
    "gn:timezone":"America/Mexico_City",
    "iso:country":"MX",
    "wof:name":"Cerrito de la Cruz",
    "wof:placetype":"locality",
    "wof:population":119
},
  "geometry": {"coordinates":[-100.52417,20.315],"type":"Point"}
}