{
  "type": "Feature",
  "properties": {
    "gn:admin1_code":"19.0",
    "gn:asciiname":"El Satelite",
    "gn:country_code":"MX",
    "gn:dem":446,
    "gn:feature_class":"P",
    "gn:feature_code":"PPL",
    "gn:name":"El Sat\u00e9lite",
    "gn:population":0,
    "gn:timezone":"America/Monterrey",
    "iso:country":"MX",
    "name:spa_x_preferred":[
        "El Sat\u00e9lite"
    ],
    "wof:name":"El Satelite",
    "wof:placetype":"locality"
},
  "geometry": {"coordinates":[-100.26990000000001,25.92138],"type":"Point"}
}