{
  "type": "Feature",
  "properties": {
    "gn:admin1_code":"14.0",
    "gn:admin2_code":"18.0",
    "gn:asciiname":"El Potrero de la Zorra",
    "gn:country_code":"MX",
    "gn:dem":1538,
    "gn:feature_class":"P",
    "gn:feature_code":"PPL",
    "gn:name":"El Potrero de la Zorra",
    "gn:population":0,
    "gn:timezone":"America/Mexico_City",
    "iso:country":"MX",
    "name:spa_x_preferred":[
        "El Potrero de la Zorra"
    ],
    "wof:name":"El Potrero de la Zorra",
    "wof:placetype":"locality"
},
  "geometry": {"coordinates":[-102.42131000000001,20.33749],"type":"Point"}
}