{
  "type": "Feature",
  "properties": {
    "gn:admin1_code":"21.0",
    "gn:admin2_code":"194.0",
    "gn:asciiname":"El Lindero",
    "gn:country_code":"MX",
    "gn:dem":85,
    "gn:feature_class":"P",
    "gn:feature_code":"PPL",
    "gn:name":"El Lindero",
    "gn:population":109,
    "gn:timezone":"America/Mexico_City",
    "iso:country":"MX",
    "name:spa_x_preferred":[
        "El Lindero"
    ],
    "wof:name":"El Lindero",
    "wof:placetype":"locality",
    "wof:population":109
},
  "geometry": {"coordinates":[-97.54738,20.49307],"type":"Point"}
}