{
  "type": "Feature",
  "properties": {
    "gn:admin1_code":"15.0",
    "gn:asciiname":"Barrio de la Luz",
    "gn:country_code":"MX",
    "gn:dem":2433,
    "gn:feature_class":"P",
    "gn:feature_code":"PPL",
    "gn:name":"Barrio de la Luz",
    "gn:population":0,
    "gn:timezone":"America/Mexico_City",
    "iso:country":"MX",
    "name:spa_x_preferred":[
        "Barrio de la Luz"
    ],
    "wof:name":"Barrio de la Luz",
    "wof:placetype":"locality"
},
  "geometry": {"coordinates":[-99.33647999999999,19.68457],"type":"Point"}
}