{
  "type": "Feature",
  "properties": {
    "gn:admin1_code":"14",
    "gn:admin2_code":"85.0",
    "gn:asciiname":"Pena Colorada",
    "gn:country_code":"MX",
    "gn:dem":1525,
    "gn:feature_class":"P",
    "gn:feature_code":"PPL",
    "gn:name":"Pe\u00f1a Colorada",
    "gn:population":0,
    "gn:timezone":"America/Mexico_City",
    "iso:country":"MX",
    "name:spa_x_preferred":[
        "Pe\u00f1a Colorada"
    ],
    "wof:name":"Pena Colorada",
    "wof:placetype":"locality"
},
  "geometry": {"coordinates":[-103.05978,19.72712000000001],"type":"Point"}
}