{
  "type": "Feature",
  "properties": {
    "gn:admin1_code":"19",
    "gn:admin2_code":"7.0",
    "gn:asciiname":"Las Virgenes",
    "gn:country_code":"MX",
    "gn:dem":1031,
    "gn:feature_class":"P",
    "gn:feature_code":"PPL",
    "gn:name":"Las V\u00edrgenes",
    "gn:population":0,
    "gn:timezone":"America/Monterrey",
    "iso:country":"MX",
    "name:und_x_variant":[
        "Las V\u00edrgenes"
    ],
    "wof:name":"Las Virgenes",
    "wof:placetype":"locality"
},
  "geometry": {"coordinates":[-99.69407,24.23574],"type":"Point"}
}