{
  "type": "Feature",
  "properties": {
    "gn:admin1_code":"26.0",
    "gn:admin2_code":"21.0",
    "gn:asciiname":"El Ahogado",
    "gn:country_code":"MX",
    "gn:dem":471,
    "gn:feature_class":"P",
    "gn:feature_code":"PPL",
    "gn:name":"El Ahogado",
    "gn:population":0,
    "gn:timezone":"America/Hermosillo",
    "iso:country":"MX",
    "name:spa_x_preferred":[
        "El Ahogado"
    ],
    "wof:name":"El Ahogado",
    "wof:placetype":"locality"
},
  "geometry": {"coordinates":[-110.227,28.90698],"type":"Point"}
}