{
  "type": "Feature",
  "properties": {
    "gn:admin1_code":"30.0",
    "gn:admin2_code":"205.0",
    "gn:asciiname":"El Chilacatozo",
    "gn:country_code":"MX",
    "gn:dem":63,
    "gn:feature_class":"P",
    "gn:feature_code":"PPL",
    "gn:name":"El Chilacatozo",
    "gn:population":0,
    "gn:timezone":"America/Mexico_City",
    "iso:country":"MX",
    "name:spa_x_preferred":[
        "El Chilacatozo"
    ],
    "wof:name":"El Chilacatozo",
    "wof:placetype":"locality"
},
  "geometry": {"coordinates":[-98.36333999999999,21.67339],"type":"Point"}
}