{
  "type": "Feature",
  "properties": {
    "gn:admin1_code":"19.0",
    "gn:admin2_code":"33.0",
    "gn:asciiname":"Dos de Octubre",
    "gn:country_code":"MX",
    "gn:dem":374,
    "gn:feature_class":"P",
    "gn:feature_code":"PPL",
    "gn:name":"Dos de Octubre",
    "gn:population":0,
    "gn:timezone":"America/Monterrey",
    "iso:country":"MX",
    "name:spa_x_preferred":[
        "San Antonio"
    ],
    "name:spa_x_variant":[
        "Dos de Octubre"
    ],
    "wof:name":"Dos de Octubre",
    "wof:placetype":"locality"
},
  "geometry": {"coordinates":[-99.54061,24.67046],"type":"Point"}
}