{
  "type": "Feature",
  "properties": {
    "gn:admin1_code":"6",
    "gn:admin2_code":"27.0",
    "gn:asciiname":"Ruchebo",
    "gn:country_code":"MX",
    "gn:dem":1944,
    "gn:feature_class":"P",
    "gn:feature_code":"PPL",
    "gn:name":"Ruchebo",
    "gn:population":5,
    "gn:timezone":"America/Chihuahua",
    "iso:country":"MX",
    "wof:name":"Ruchebo",
    "wof:placetype":"locality",
    "wof:population":5
},
  "geometry": {"coordinates":[-107.48408000000001,27.31909000000001],"type":"Point"}
}