{
  "type": "Feature",
  "properties": {
    "gn:admin1_code":"14.0",
    "gn:admin2_code":"88.0",
    "gn:asciiname":"Los Duendes",
    "gn:country_code":"MX",
    "gn:dem":1226,
    "gn:feature_class":"P",
    "gn:feature_code":"PPL",
    "gn:name":"Los Duendes",
    "gn:population":0,
    "gn:timezone":"America/Mexico_City",
    "iso:country":"MX",
    "name:spa_x_preferred":[
        "Los Duendes"
    ],
    "wof:name":"Los Duendes",
    "wof:placetype":"locality"
},
  "geometry": {"coordinates":[-104.01911,20.22524],"type":"Point"}
}