{
  "type": "Feature",
  "properties": {
    "gn:admin1_code":"32.0",
    "gn:asciiname":"El Gigante",
    "gn:country_code":"MX",
    "gn:dem":2185,
    "gn:feature_class":"P",
    "gn:feature_code":"PPL",
    "gn:name":"El Gigante",
    "gn:population":0,
    "gn:timezone":"America/Mexico_City",
    "iso:country":"MX",
    "name:spa_x_preferred":[
        "El Gigante"
    ],
    "wof:name":"El Gigante",
    "wof:placetype":"locality"
},
  "geometry": {"coordinates":[-101.38267999999999,22.36116],"type":"Point"}
}