{
  "type": "Feature",
  "properties": {
    "gn:admin1_code":"10.0",
    "gn:admin2_code":"14.0",
    "gn:asciiname":"La Joyas",
    "gn:country_code":"MX",
    "gn:dem":2002,
    "gn:feature_class":"P",
    "gn:feature_code":"PPL",
    "gn:name":"La Joyas",
    "gn:population":0,
    "gn:timezone":"America/Monterrey",
    "iso:country":"MX",
    "name:spa_x_preferred":[
        "La Joyas"
    ],
    "name:spa_x_variant":[
        "Las Joyas"
    ],
    "wof:name":"La Joyas",
    "wof:placetype":"locality"
},
  "geometry": {"coordinates":[-104.73347,23.06803],"type":"Point"}
}