{
  "type": "Feature",
  "properties": {
    "gn:admin1_code":"7",
    "gn:admin2_code":"17.0",
    "gn:asciiname":"Penjamo",
    "gn:country_code":"MX",
    "gn:dem":1118,
    "gn:feature_class":"P",
    "gn:feature_code":"PPL",
    "gn:name":"Penjamo",
    "gn:population":0,
    "gn:timezone":"America/Monterrey",
    "iso:country":"MX",
    "name:spa_x_preferred":[
        "Penjamo"
    ],
    "wof:name":"Penjamo",
    "wof:placetype":"locality"
},
  "geometry": {"coordinates":[-103.16325999999999,25.44227],"type":"Point"}
}