{
  "type": "Feature",
  "properties": {
    "gn:admin1_code":"20",
    "gn:admin2_code":"59",
    "gn:asciiname":"Rio Canela",
    "gn:country_code":"MX",
    "gn:dem":1854,
    "gn:feature_class":"P",
    "gn:feature_code":"PPL",
    "gn:name":"R\u00edo Canela",
    "gn:population":22,
    "gn:timezone":"America/Mexico_City",
    "iso:country":"MX",
    "name:und_x_variant":[
        "R\u00edo Canela"
    ],
    "wof:name":"Rio Canela",
    "wof:placetype":"locality",
    "wof:population":22
},
  "geometry": {"coordinates":[-96.52388999999999,16.26444],"type":"Point"}
}