{
  "type": "Feature",
  "properties": {
    "gn:admin1_code":"30",
    "gn:admin2_code":"124.0",
    "gn:asciiname":"Cruz Verde",
    "gn:country_code":"MX",
    "gn:dem":56,
    "gn:feature_class":"P",
    "gn:feature_code":"PPL",
    "gn:name":"Cruz Verde",
    "gn:population":193,
    "gn:timezone":"America/Mexico_City",
    "iso:country":"MX",
    "name:und_x_variant":[
        "Carrizal",
        "Cruz Verde"
    ],
    "wof:name":"Cruz Verde",
    "wof:placetype":"locality",
    "wof:population":193
},
  "geometry": {"coordinates":[-97.273,20.54214],"type":"Point"}
}