{
  "type": "Feature",
  "properties": {
    "gn:admin1_code":"16",
    "gn:admin2_code":"50.0",
    "gn:asciiname":"Apeo",
    "gn:country_code":"MX",
    "gn:dem":2033,
    "gn:feature_class":"P",
    "gn:feature_code":"PPL",
    "gn:name":"Apeo",
    "gn:population":1897,
    "gn:timezone":"America/Mexico_City",
    "iso:country":"MX",
    "wof:name":"Apeo",
    "wof:placetype":"locality",
    "wof:population":1897
},
  "geometry": {"coordinates":[-100.34193999999999,19.88722000000001],"type":"Point"}
}