{
  "type": "Feature",
  "properties": {
    "gn:admin1_code":"5",
    "gn:admin2_code":"65",
    "gn:asciiname":"Puente Michol (Key)",
    "gn:country_code":"MX",
    "gn:dem":58,
    "gn:feature_class":"P",
    "gn:feature_code":"PPL",
    "gn:name":"Puente Michol (Key)",
    "gn:population":31,
    "gn:timezone":"America/Mexico_City",
    "iso:country":"MX",
    "wof:name":"Puente Michol (Key)",
    "wof:placetype":"locality",
    "wof:population":31
},
  "geometry": {"coordinates":[-92.02528,17.49083],"type":"Point"}
}