{
  "type": "Feature",
  "properties": {
    "gn:admin1_code":"16",
    "gn:admin2_code":"112.0",
    "gn:asciiname":"El Derrumbadero",
    "gn:country_code":"MX",
    "gn:dem":2114,
    "gn:feature_class":"P",
    "gn:feature_code":"PPL",
    "gn:name":"El Derrumbadero",
    "gn:population":124,
    "gn:timezone":"America/Mexico_City",
    "iso:country":"MX",
    "wof:name":"El Derrumbadero",
    "wof:placetype":"locality",
    "wof:population":124
},
  "geometry": {"coordinates":[-100.3725,19.52556],"type":"Point"}
}