{
  "type": "Feature",
  "properties": {
    "gn:admin1_code":"6",
    "gn:admin2_code":"65.0",
    "gn:asciiname":"Puerto del Gallego",
    "gn:country_code":"MX",
    "gn:dem":2174,
    "gn:feature_class":"P",
    "gn:feature_code":"PPL",
    "gn:name":"Puerto del Gallego",
    "gn:population":4,
    "gn:timezone":"America/Chihuahua",
    "iso:country":"MX",
    "wof:name":"Puerto del Gallego",
    "wof:placetype":"locality",
    "wof:population":4
},
  "geometry": {"coordinates":[-107.95278,27.24222],"type":"Point"}
}