{
  "type": "Feature",
  "properties": {
    "gn:admin1_code":"11",
    "gn:admin2_code":"3",
    "gn:asciiname":"Micaela Ortega (Los Ugalde)",
    "gn:country_code":"MX",
    "gn:dem":2115,
    "gn:feature_class":"P",
    "gn:feature_code":"PPL",
    "gn:name":"Micaela Ortega (Los Ugalde)",
    "gn:population":10,
    "gn:timezone":"America/Mexico_City",
    "iso:country":"MX",
    "wof:name":"Micaela Ortega (Los Ugalde)",
    "wof:placetype":"locality",
    "wof:population":10
},
  "geometry": {"coordinates":[-100.71832999999999,20.86722],"type":"Point"}
}