{
  "type": "Feature",
  "properties": {
    "gn:admin1_code":"20",
    "gn:admin2_code":"44.0",
    "gn:asciiname":"Benito Lopez Sanchez",
    "gn:country_code":"MX",
    "gn:dem":56,
    "gn:feature_class":"P",
    "gn:feature_code":"PPL",
    "gn:name":"Benito L\u00f3pez S\u00e1nchez",
    "gn:population":5,
    "gn:timezone":"America/Mexico_City",
    "iso:country":"MX",
    "name:und_x_variant":[
        "Benito L\u00f3pez S\u00e1nchez"
    ],
    "wof:name":"Benito Lopez Sanchez",
    "wof:placetype":"locality",
    "wof:population":5
},
  "geometry": {"coordinates":[-95.82693999999999,18.055],"type":"Point"}
}