{
  "type": "Feature",
  "properties": {
    "gn:admin1_code":"10",
    "gn:admin2_code":"2.0",
    "gn:asciiname":"El Tragadero",
    "gn:country_code":"MX",
    "gn:dem":1432,
    "gn:feature_class":"P",
    "gn:feature_code":"PPL",
    "gn:name":"El Tragadero",
    "gn:population":0,
    "gn:timezone":"America/Monterrey",
    "iso:country":"MX",
    "name:spa_x_preferred":[
        "El Tragadero"
    ],
    "wof:name":"El Tragadero",
    "wof:placetype":"locality"
},
  "geometry": {"coordinates":[-106.53628999999999,25.05046],"type":"Point"}
}