{
  "type": "Feature",
  "properties": {
    "gn:admin1_code":"4",
    "gn:admin2_code":"3.0",
    "gn:asciiname":"La Maria",
    "gn:country_code":"MX",
    "gn:dem":3,
    "gn:feature_class":"P",
    "gn:feature_code":"PPL",
    "gn:name":"La Mar\u00eda",
    "gn:population":4,
    "gn:timezone":"America/Merida",
    "iso:country":"MX",
    "name:und_x_variant":[
        "La Mar\u00eda"
    ],
    "wof:name":"La Maria",
    "wof:placetype":"locality",
    "wof:population":4
},
  "geometry": {"coordinates":[-91.60722,18.30556],"type":"Point"}
}