{
  "type": "Feature",
  "properties": {
    "gn:admin1_code":"14.0",
    "gn:admin2_code":"42.0",
    "gn:asciiname":"Potrero de Madera",
    "gn:country_code":"MX",
    "gn:dem":1722,
    "gn:feature_class":"P",
    "gn:feature_code":"PPL",
    "gn:name":"Potrero de Madera",
    "gn:population":0,
    "gn:timezone":"America/Mexico_City",
    "iso:country":"MX",
    "name:spa_x_preferred":[
        "Potrero de Madera"
    ],
    "wof:name":"Potrero de Madera",
    "wof:placetype":"locality"
},
  "geometry": {"coordinates":[-103.92783,22.58146],"type":"Point"}
}