{
  "type": "Feature",
  "properties": {
    "gn:admin1_code":"6",
    "gn:admin2_code":"29.0",
    "gn:asciiname":"Mesa del Chiquero",
    "gn:country_code":"MX",
    "gn:dem":2189,
    "gn:feature_class":"P",
    "gn:feature_code":"PPL",
    "gn:name":"Mesa del Chiquero",
    "gn:population":7,
    "gn:timezone":"America/Chihuahua",
    "iso:country":"MX",
    "wof:name":"Mesa del Chiquero",
    "wof:placetype":"locality",
    "wof:population":7
},
  "geometry": {"coordinates":[-106.74139,25.67667],"type":"Point"}
}