{
  "type": "Feature",
  "properties": {
    "gn:admin1_code":"4",
    "gn:admin2_code":"11.0",
    "gn:asciiname":"Caballo de San Lazaro",
    "gn:country_code":"MX",
    "gn:dem":70,
    "gn:feature_class":"P",
    "gn:feature_code":"PPL",
    "gn:name":"Caballo de San L\u00e1zaro",
    "gn:population":6,
    "gn:timezone":"America/Merida",
    "iso:country":"MX",
    "name:und_x_variant":[
        "Caballo de San L\u00e1zaro"
    ],
    "wof:name":"Caballo de San Lazaro",
    "wof:placetype":"locality",
    "wof:population":6
},
  "geometry": {"coordinates":[-90.62,18.12139],"type":"Point"}
}