{
  "type": "Feature",
  "properties": {
    "gn:admin1_code":"16",
    "gn:admin2_code":"89",
    "gn:asciiname":"El Fuerte",
    "gn:country_code":"MX",
    "gn:dem":1501,
    "gn:feature_class":"P",
    "gn:feature_code":"PPL",
    "gn:name":"El Fuerte",
    "gn:population":14,
    "gn:timezone":"America/Mexico_City",
    "iso:country":"MX",
    "name:ara_x_preferred":[
        "\u0627\u0644\u0641\u0648\u064a\u0631\u062a\u0627"
    ],
    "name:ben_x_preferred":[
        "\u098f\u09b2 \u09ab\u09c1\u09df\u09c7\u09b0\u09cd\u09a4\u09c7"
    ],
    "name:bre_x_preferred":[
        "El Fuerte"
    ],
    "name:ceb_x_preferred":[
        "El Fuerte"
    ],
    "name:ell_x_preferred":[
        "\u0395\u03bb \u03a6\u03bf\u03c5\u03ad\u03c1\u03c4\u03b5"
    ],
    "name:heb_x_preferred":[
        "\u05d0\u05dc \u05e4\u05d5\u05d0\u05e8\u05d8\u05d4"
    ],
    "name:hin_x_preferred":[
        "\u090f\u0932 \u092b\u093c\u094d\u092f\u0942\u0930\u094d\u091f\u0947"
    ],
    "name:ita_x_preferred":[
        "El Fuerte"
    ],
    "name:kor_x_preferred":[
        "\uc5d8 \ud478\uc5d0\ub974\ud14c"
    ],
    "name:nld_x_preferred":[
        "El Fuerte"
    ],
    "name:rus_x_preferred":[
        "\u042d\u043b\u044c-\u0424\u0443\u044d\u0440\u0442\u0435"
    ],
    "name:spa_x_preferred":[
        "El Fuerte"
    ],
    "name:srp_x_preferred":[
        "\u0415\u043b \u0424\u0443\u0435\u0440\u0442\u0435"
    ],
    "name:swe_x_preferred":[
        "El Fuerte"
    ],
    "name:ukr_x_preferred":[
        "\u0415\u043b\u044c-\u0424\u0443\u0435\u0440\u0442\u0435"
    ],
    "name:urd_x_preferred":[
        "\u0627\u06cc\u0644 \u0641\u0648\u0631\u0679\u06d2"
    ],
    "name:vie_x_preferred":[
        "El Fuerte"
    ],
    "name:zho_cn_x_preferred":[
        "\u57c3\u5c14\u5bcc\u57c3\u5c14\u7279"
    ],
    "name:zho_tw_x_preferred":[
        "\u5bcc\u57c3\u723e\u7279"
    ],
    "wof:name":"El Fuerte",
    "wof:placetype":"locality",
    "wof:population":14
},
  "geometry": {"coordinates":[-102.97694,18.98083],"type":"Point"}
}