{
  "type": "Feature",
  "properties": {
    "gn:admin1_code":"10",
    "gn:admin2_code":"23",
    "gn:asciiname":"El Gueinacastle",
    "gn:country_code":"MX",
    "gn:dem":516,
    "gn:feature_class":"P",
    "gn:feature_code":"PPL",
    "gn:name":"El G\u00fcinacastle",
    "gn:population":24,
    "gn:timezone":"America/Monterrey",
    "iso:country":"MX",
    "name:und_x_variant":[
        "El G\u00fcinacastle"
    ],
    "wof:name":"El Gueinacastle",
    "wof:placetype":"locality",
    "wof:population":24
},
  "geometry": {"coordinates":[-105.52916,23.36724],"type":"Point"}
}