{
  "type": "Feature",
  "properties": {
    "gn:admin1_code":"2",
    "gn:admin2_code":"1.0",
    "gn:asciiname":"Villa Morelos",
    "gn:country_code":"MX",
    "gn:dem":11,
    "gn:feature_class":"P",
    "gn:feature_code":"PPL",
    "gn:name":"Villa Morelos",
    "gn:population":0,
    "gn:timezone":"America/Tijuana",
    "iso:country":"MX",
    "name:spa_x_preferred":[
        "Villa Morelos"
    ],
    "wof:name":"Villa Morelos",
    "wof:placetype":"locality"
},
  "geometry": {"coordinates":[-116.25894,30.99065],"type":"Point"}
}