{
  "type": "Feature",
  "properties": {
    "gn:admin1_code":"6.0",
    "gn:admin2_code":"66.0",
    "gn:asciiname":"Guasaremos",
    "gn:country_code":"MX",
    "gn:dem":811,
    "gn:feature_class":"P",
    "gn:feature_code":"PPL",
    "gn:name":"Guasaremos",
    "gn:population":0,
    "gn:timezone":"America/Chihuahua",
    "iso:country":"MX",
    "name:und_x_variant":[
        "Rancho Guasaremos",
        "Guazaremos",
        "Guasaremos"
    ],
    "wof:name":"Guasaremos",
    "wof:placetype":"locality"
},
  "geometry": {"coordinates":[-108.70734,27.66024],"type":"Point"}
}