{
  "type": "Feature",
  "properties": {
    "iso:country":"MX",
    "name:bre_x_preferred":[
        "Esperanza"
    ],
    "name:ceb_x_preferred":[
        "Esperanza"
    ],
    "name:deu_x_preferred":[
        "Esperanza"
    ],
    "name:epo_x_preferred":[
        "Esperanza"
    ],
    "name:fra_x_preferred":[
        "Esperanza"
    ],
    "name:glg_x_preferred":[
        "Esperanza"
    ],
    "name:hye_x_preferred":[
        "\u0537\u057d\u057a\u0565\u0580\u0561\u0576\u057d\u0561"
    ],
    "name:ita_x_preferred":[
        "Esperanza"
    ],
    "name:jpn_x_preferred":[
        "\u30a8\u30b9\u30da\u30e9\u30f3\u30b5"
    ],
    "name:kor_x_preferred":[
        "\uc5d0\uc2a4\ud398\ub780\uc0ac"
    ],
    "name:nds_x_preferred":[
        "Esperanza"
    ],
    "name:nld_x_preferred":[
        "Esperanza"
    ],
    "name:por_x_preferred":[
        "Esperanza"
    ],
    "name:rus_x_preferred":[
        "\u042d\u0441\u043f\u0435\u0440\u0430\u043d\u0441\u0430"
    ],
    "name:spa_x_preferred":[
        "Esperanza"
    ],
    "name:spa_x_variant":[
        "La Esperanza"
    ],
    "name:srp_x_preferred":[
        "\u0415\u0441\u043f\u0435\u0440\u0430\u043d\u0437\u0430"
    ],
    "name:swe_x_preferred":[
        "Esperanza"
    ],
    "name:tgl_x_preferred":[
        "Esperanza"
    ],
    "name:unk_x_variant":[
        "Esperanza"
    ],
    "name:vie_x_preferred":[
        "Esperanza"
    ],
    "name:war_x_preferred":[
        "Esperanza"
    ],
    "qs:gn_adm0_cc":"MX",
    "qs:gn_fcode":"PPL",
    "qs:gn_local":3530589,
    "qs:gn_nam_loc":"Nezahualcoyotl, Ciudad Netzahualc\u00f3yotl, Mexico, MX",
    "qs:gn_namadm1":"15",
    "qs:gn_name":"La Esperanza",
    "qs:local_max":88,
    "qs:local_sum":236,
    "qs:localhoods":6,
    "qs:name":"Esperanza",
    "qs:name_adm0":"M\u00e9xico",
    "qs:name_adm1":"Mexico",
    "qs:name_adm2":"Nezahualcoyotl",
    "qs:name_local":"Ciudad Netzahualc\u00f3yotl",
    "qs:photo_max":23,
    "qs:photo_sum":88,
    "qs:placetype":"Suburb",
    "qs:quad_count":10,
    "qs:woe_adm0":23424900,
    "qs:woe_adm1":2346278,
    "qs:woe_adm2":12600379,
    "qs:woe_lau":0,
    "qs:woe_local":116564,
    "qs:woe_ver":"7.10.0",
    "wof:lang":[
        "spa"
    ],
    "wof:name":"Esperanza",
    "wof:placetype":"neighbourhood"
},
  "geometry": {"coordinates":[-98.982456,19.398911],"type":"Point"}
}