{
  "type": "Feature",
  "properties": {
    "gn:admin1_code":"12",
    "gn:admin2_code":"10.0",
    "gn:asciiname":"San Pedro Huitzapula Norte (Huitzapula Norte)",
    "gn:country_code":"MX",
    "gn:dem":1867,
    "gn:feature_class":"P",
    "gn:feature_code":"PPL",
    "gn:name":"San Pedro Huitzapula Norte (Huitzapula Norte)",
    "gn:population":1297,
    "gn:timezone":"America/Mexico_City",
    "iso:country":"MX",
    "wof:name":"San Pedro Huitzapula Norte (Huitzapula Norte)",
    "wof:placetype":"locality",
    "wof:population":1297
},
  "geometry": {"coordinates":[-98.80588,17.42642],"type":"Point"}
}