{
  "type": "Feature",
  "properties": {
    "gn:admin1_code":"4",
    "gn:admin2_code":"11.0",
    "gn:asciiname":"La Zanja",
    "gn:country_code":"MX",
    "gn:dem":44,
    "gn:feature_class":"P",
    "gn:feature_code":"PPL",
    "gn:name":"La Zanja",
    "gn:population":0,
    "gn:timezone":"America/Merida",
    "iso:country":"MX",
    "name:und_x_variant":[
        "La Palma"
    ],
    "wof:name":"La Zanja",
    "wof:placetype":"locality"
},
  "geometry": {"coordinates":[-90.83548,17.96892],"type":"Point"}
}