{
  "type": "Feature",
  "properties": {
    "gn:admin1_code":"10",
    "gn:admin2_code":"14.0",
    "gn:asciiname":"Pinos Rodeados",
    "gn:country_code":"MX",
    "gn:dem":1988,
    "gn:feature_class":"P",
    "gn:feature_code":"PPL",
    "gn:name":"Pinos Rodeados",
    "gn:population":7,
    "gn:timezone":"America/Monterrey",
    "iso:country":"MX",
    "wof:name":"Pinos Rodeados",
    "wof:placetype":"locality",
    "wof:population":7
},
  "geometry": {"coordinates":[-104.43136,23.06003],"type":"Point"}
}