{
  "type": "Feature",
  "properties": {
    "gn:admin1_code":"14.0",
    "gn:admin2_code":"85.0",
    "gn:asciiname":"El Saltillo",
    "gn:country_code":"MX",
    "gn:dem":1687,
    "gn:feature_class":"P",
    "gn:feature_code":"PPL",
    "gn:name":"El Saltillo",
    "gn:population":0,
    "gn:timezone":"America/Mexico_City",
    "iso:country":"MX",
    "name:spa_x_preferred":[
        "El Saltillo"
    ],
    "wof:name":"El Saltillo",
    "wof:placetype":"locality"
},
  "geometry": {"coordinates":[-103.02997000000001,19.67915],"type":"Point"}
}