{
  "type": "Feature",
  "properties": {
    "gn:admin1_code":"6.0",
    "gn:admin2_code":"54.0",
    "gn:asciiname":"Casa Colorada",
    "gn:country_code":"MX",
    "gn:dem":2155,
    "gn:feature_class":"P",
    "gn:feature_code":"PPL",
    "gn:name":"Casa Colorada",
    "gn:population":0,
    "gn:timezone":"America/Chihuahua",
    "iso:country":"MX",
    "name:por_x_preferred":[
        "Casa Colorada"
    ],
    "name:spa_x_preferred":[
        "Casa Colorada"
    ],
    "wof:name":"Casa Colorada",
    "wof:placetype":"locality"
},
  "geometry": {"coordinates":[-106.75,28.88333],"type":"Point"}
}