{
  "type": "Feature",
  "properties": {
    "gn:admin1_code":"32",
    "gn:admin2_code":"37.0",
    "gn:asciiname":"San Jose de Gracia",
    "gn:country_code":"MX",
    "gn:dem":2357,
    "gn:feature_class":"P",
    "gn:feature_code":"PPL",
    "gn:name":"San Jos\u00e9 de Gracia",
    "gn:population":0,
    "gn:timezone":"America/Mexico_City",
    "iso:country":"MX",
    "name:spa_x_preferred":[
        "San Jos\u00e9 de Gracia"
    ],
    "wof:name":"San Jose de Gracia",
    "wof:placetype":"locality"
},
  "geometry": {"coordinates":[-102.55515,22.89373],"type":"Point"}
}