{
  "type": "Feature",
  "properties": {
    "gn:admin1_code":"24",
    "gn:admin2_code":"26.0",
    "gn:asciiname":"Los Naranjos",
    "gn:country_code":"MX",
    "gn:dem":158,
    "gn:feature_class":"P",
    "gn:feature_code":"PPL",
    "gn:name":"Los Naranjos",
    "gn:population":0,
    "gn:timezone":"America/Mexico_City",
    "iso:country":"MX",
    "name:bre_x_preferred":[
        "Los Naranjos"
    ],
    "name:ceb_x_preferred":[
        "Los Naranjos"
    ],
    "name:deu_x_preferred":[
        "Los Naranjos"
    ],
    "name:spa_x_preferred":[
        "Los Naranjos"
    ],
    "name:spa_x_variant":[
        "Naranjo"
    ],
    "name:swe_x_preferred":[
        "Los Naranjos"
    ],
    "wof:name":"Los Naranjos",
    "wof:placetype":"locality"
},
  "geometry": {"coordinates":[-98.84021,21.63385],"type":"Point"}
}