{
  "type": "Feature",
  "properties": {
    "gn:admin1_code":"20",
    "gn:admin2_code":"21",
    "gn:asciiname":"Colonia Chema Martinez",
    "gn:country_code":"MX",
    "gn:dem":183,
    "gn:feature_class":"P",
    "gn:feature_code":"PPL",
    "gn:name":"Colonia Chema Mart\u00ednez",
    "gn:population":47,
    "gn:timezone":"America/Mexico_City",
    "iso:country":"MX",
    "name:und_x_variant":[
        "Colonia Chema Mart\u00ednez"
    ],
    "wof:name":"Colonia Chema Martinez",
    "wof:placetype":"locality",
    "wof:population":47
},
  "geometry": {"coordinates":[-96.65582999999999,18.59583],"type":"Point"}
}