{
  "type": "Feature",
  "properties": {
    "gn:admin1_code":"16",
    "gn:admin2_code":"95.0",
    "gn:asciiname":"La Charanda",
    "gn:country_code":"MX",
    "gn:dem":1646,
    "gn:feature_class":"P",
    "gn:feature_code":"PPL",
    "gn:name":"La Charanda",
    "gn:population":97,
    "gn:timezone":"America/Mexico_City",
    "iso:country":"MX",
    "wof:name":"La Charanda",
    "wof:placetype":"locality",
    "wof:population":97
},
  "geometry": {"coordinates":[-102.52861,19.69583],"type":"Point"}
}