{
  "type": "Feature",
  "properties": {
    "gn:admin1_code":"20",
    "gn:admin2_code":"58",
    "gn:asciiname":"Copalillo (Barrio 5 de Mayo)",
    "gn:country_code":"MX",
    "gn:dem":1615,
    "gn:feature_class":"P",
    "gn:feature_code":"PPL",
    "gn:name":"Copalillo (Barrio 5 de Mayo)",
    "gn:population":24,
    "gn:timezone":"America/Mexico_City",
    "iso:country":"MX",
    "wof:name":"Copalillo (Barrio 5 de Mayo)",
    "wof:placetype":"locality",
    "wof:population":24
},
  "geometry": {"coordinates":[-96.95444000000001,17.96639],"type":"Point"}
}