{
  "type": "Feature",
  "properties": {
    "gn:admin1_code":"29",
    "gn:admin2_code":"59.0",
    "gn:asciiname":"Ayometitla",
    "gn:country_code":"MX",
    "gn:dem":2330,
    "gn:feature_class":"P",
    "gn:feature_code":"PPL",
    "gn:name":"Ayometitla",
    "gn:population":0,
    "gn:timezone":"America/Mexico_City",
    "iso:country":"MX",
    "name:spa_x_preferred":[
        "Ayometitla"
    ],
    "name:spa_x_variant":[
        "Santiago Ayometitla"
    ],
    "name:und_x_variant":[
        "Santiago Yometitla"
    ],
    "wof:name":"Ayometitla",
    "wof:placetype":"locality"
},
  "geometry": {"coordinates":[-98.19267000000001,19.20825],"type":"Point"}
}