{
  "type": "Feature",
  "properties": {
    "gn:admin1_code":"21",
    "gn:admin2_code":"161.0",
    "gn:asciiname":"La Joya (Pablo Hernandez Jimenez)",
    "gn:country_code":"MX",
    "gn:dem":1821,
    "gn:feature_class":"P",
    "gn:feature_code":"PPL",
    "gn:name":"La Joya (Pablo Hern\u00e1ndez Jim\u00e9nez)",
    "gn:population":8,
    "gn:timezone":"America/Mexico_City",
    "iso:country":"MX",
    "name:und_x_variant":[
        "La Joya (Pablo Hern\u00e1ndez Jim\u00e9nez)"
    ],
    "wof:name":"La Joya (Pablo Hernandez Jimenez)",
    "wof:placetype":"locality",
    "wof:population":8
},
  "geometry": {"coordinates":[-97.52715999999999,18.58045],"type":"Point"}
}