{
  "type": "Feature",
  "properties": {
    "gn:admin1_code":"21",
    "gn:admin2_code":"109.0",
    "gn:asciiname":"Acahuales (El Aguacate)",
    "gn:country_code":"MX",
    "gn:dem":1902,
    "gn:feature_class":"P",
    "gn:feature_code":"PPL",
    "gn:name":"Acahuales (El Aguacate)",
    "gn:population":225,
    "gn:timezone":"America/Mexico_City",
    "iso:country":"MX",
    "wof:name":"Acahuales (El Aguacate)",
    "wof:placetype":"locality",
    "wof:population":225
},
  "geometry": {"coordinates":[-98.1935,20.26227],"type":"Point"}
}