{
  "type": "Feature",
  "properties": {
    "gn:admin1_code":"28",
    "gn:admin2_code":"35.0",
    "gn:asciiname":"Santa Margarita",
    "gn:country_code":"MX",
    "gn:dem":107,
    "gn:feature_class":"P",
    "gn:feature_code":"PPL",
    "gn:name":"Santa Margarita",
    "gn:population":0,
    "gn:timezone":"America/Monterrey",
    "iso:country":"MX",
    "name:und_x_variant":[
        "Rancho Santa Margarita",
        "Santa Margarita"
    ],
    "wof:name":"Santa Margarita",
    "wof:placetype":"locality"
},
  "geometry": {"coordinates":[-98.12707,24.5832],"type":"Point"}
}