{
  "type": "Feature",
  "properties": {
    "gn:admin1_code":"28",
    "gn:admin2_code":"35.0",
    "gn:asciiname":"Santa Margarita",
    "gn:country_code":"MX",
    "gn:dem":107,
    "gn:feature_class":"P",
    "gn:feature_code":"PPL",
    "gn:name":"Santa Margarita",
    "gn:population":0,
    "gn:timezone":"America/Monterrey",
    "iso:country":"MX",
    "name:bre_x_preferred":[
        "Santa Margarita"
    ],
    "name:ceb_x_preferred":[
        "Santa Margarita"
    ],
    "name:deu_x_preferred":[
        "Santa Margarita"
    ],
    "name:fin_x_preferred":[
        "Santa Margarita"
    ],
    "name:fra_x_preferred":[
        "Santa Margarita"
    ],
    "name:ita_x_preferred":[
        "Santa Margarita"
    ],
    "name:por_x_preferred":[
        "Santa Margarita"
    ],
    "name:scn_x_preferred":[
        "Santa Margarita"
    ],
    "name:spa_x_preferred":[
        "Santa Margarita"
    ],
    "name:srp_x_preferred":[
        "\u0421\u0430\u043d\u0442\u0430 \u041c\u0430\u0440\u0433\u0430\u0440\u0438\u0442\u0430"
    ],
    "name:swe_x_preferred":[
        "Santa Margarita"
    ],
    "name:und_x_variant":[
        "Rancho Santa Margarita",
        "Santa Margarita"
    ],
    "name:war_x_preferred":[
        "Santa Margarita"
    ],
    "wof:name":"Santa Margarita",
    "wof:placetype":"locality"
},
  "geometry": {"coordinates":[-98.12707,24.5832],"type":"Point"}
}