{
  "type": "Feature",
  "properties": {
    "gn:admin1_code":"16",
    "gn:admin2_code":"57.0",
    "gn:asciiname":"Los Curindales",
    "gn:country_code":"MX",
    "gn:dem":969,
    "gn:feature_class":"P",
    "gn:feature_code":"PPL",
    "gn:name":"Los Curindales",
    "gn:population":0,
    "gn:timezone":"America/Mexico_City",
    "iso:country":"MX",
    "name:spa_x_preferred":[
        "Los Curindales"
    ],
    "wof:name":"Los Curindales",
    "wof:placetype":"locality"
},
  "geometry": {"coordinates":[-101.12478,19.09519],"type":"Point"}
}