{
  "type": "Feature",
  "properties": {
    "gn:admin1_code":"30",
    "gn:admin2_code":"210.0",
    "gn:asciiname":"Alvaro Obregon",
    "gn:country_code":"MX",
    "gn:dem":50,
    "gn:feature_class":"P",
    "gn:feature_code":"PPL",
    "gn:name":"\u00c1lvaro Obreg\u00f3n",
    "gn:population":0,
    "gn:timezone":"America/Mexico_City",
    "iso:country":"MX",
    "name:spa_x_preferred":[
        "\u00c1lvaro Obreg\u00f3n"
    ],
    "wof:name":"Alvaro Obregon",
    "wof:placetype":"locality"
},
  "geometry": {"coordinates":[-94.634,17.31119],"type":"Point"}
}