{
  "type": "Feature",
  "properties": {
    "gn:admin1_code":"16",
    "gn:admin2_code":"10.0",
    "gn:asciiname":"La Mata de Platano",
    "gn:country_code":"MX",
    "gn:dem":589,
    "gn:feature_class":"P",
    "gn:feature_code":"PPL",
    "gn:name":"La Mata de Pl\u00e1tano",
    "gn:population":8,
    "gn:timezone":"America/Mexico_City",
    "iso:country":"MX",
    "name:und_x_variant":[
        "La Mata de Pl\u00e1tano"
    ],
    "wof:name":"La Mata de Platano",
    "wof:placetype":"locality",
    "wof:population":8
},
  "geometry": {"coordinates":[-102.05028,18.28472],"type":"Point"}
}