{
  "type": "Feature",
  "properties": {
    "gn:admin1_code":"15",
    "gn:admin2_code":"97",
    "gn:asciiname":"El Caracol",
    "gn:country_code":"MX",
    "gn:dem":2278,
    "gn:feature_class":"P",
    "gn:feature_code":"PPL",
    "gn:name":"El Caracol",
    "gn:population":49,
    "gn:timezone":"America/Mexico_City",
    "iso:country":"MX",
    "wof:name":"El Caracol",
    "wof:placetype":"locality",
    "wof:population":49
},
  "geometry": {"coordinates":[-99.94635,18.89285],"type":"Point"}
}