{
  "type": "Feature",
  "properties": {
    "gn:admin1_code":"5",
    "gn:admin2_code":"61.0",
    "gn:asciiname":"Camino Real",
    "gn:country_code":"MX",
    "gn:dem":787,
    "gn:feature_class":"P",
    "gn:feature_code":"PPL",
    "gn:name":"Camino Real",
    "gn:population":6,
    "gn:timezone":"America/Mexico_City",
    "iso:country":"MX",
    "wof:name":"Camino Real",
    "wof:placetype":"locality",
    "wof:population":6
},
  "geometry": {"coordinates":[-93.39639,16.72806],"type":"Point"}
}