{
  "type": "Feature",
  "properties": {
    "gn:admin1_code":"7",
    "gn:admin2_code":"4.0",
    "gn:asciiname":"La Bety",
    "gn:country_code":"MX",
    "gn:dem":2366,
    "gn:feature_class":"P",
    "gn:feature_code":"PPL",
    "gn:name":"La Bety",
    "gn:population":0,
    "gn:timezone":"America/Monterrey",
    "iso:country":"MX",
    "name:spa_x_preferred":[
        "La Bety"
    ],
    "wof:name":"La Bety",
    "wof:placetype":"locality"
},
  "geometry": {"coordinates":[-100.5817,25.39808],"type":"Point"}
}