{
  "type": "Feature",
  "properties": {
    "gn:admin1_code":"26.0",
    "gn:asciiname":"El Limon",
    "gn:cc2":"MX",
    "gn:country_code":"MX",
    "gn:dem":64,
    "gn:feature_class":"P",
    "gn:feature_code":"PPL",
    "gn:name":"El Lim\u00f3n",
    "gn:population":0,
    "gn:timezone":"America/Mazatlan",
    "iso:country":"MX",
    "name:und_x_variant":[
        "Lim\u00f3n",
        "El Lim\u00f3n"
    ],
    "wof:name":"El Limon",
    "wof:placetype":"locality"
},
  "geometry": {"coordinates":[-107.06667,24.26667],"type":"Point"}
}