{
  "type": "Feature",
  "properties": {
    "gn:admin1_code":"30",
    "gn:admin2_code":"202",
    "gn:asciiname":"Altamira",
    "gn:country_code":"MX",
    "gn:dem":1259,
    "gn:feature_class":"P",
    "gn:feature_code":"PPL",
    "gn:name":"Altamira",
    "gn:population":52,
    "gn:timezone":"America/Mexico_City",
    "iso:country":"MX",
    "wof:name":"Altamira",
    "wof:placetype":"locality",
    "wof:population":52
},
  "geometry": {"coordinates":[-98.3475,20.70222],"type":"Point"}
}