{
  "type": "Feature",
  "properties": {
    "gn:admin1_code":"6",
    "gn:admin2_code":"65.0",
    "gn:asciiname":"Moribo",
    "gn:country_code":"MX",
    "gn:dem":1371,
    "gn:feature_class":"P",
    "gn:feature_code":"PPL",
    "gn:name":"Moribo",
    "gn:population":95,
    "gn:timezone":"America/Chihuahua",
    "iso:country":"MX",
    "wof:name":"Moribo",
    "wof:placetype":"locality",
    "wof:population":95
},
  "geometry": {"coordinates":[-107.83528,27.24638],"type":"Point"}
}