{
  "type": "Feature",
  "properties": {
    "gn:admin1_code":"30",
    "gn:admin2_code":"23.0",
    "gn:asciiname":"Plan de la Luz",
    "gn:country_code":"MX",
    "gn:dem":516,
    "gn:feature_class":"P",
    "gn:feature_code":"PPL",
    "gn:name":"Plan de la Luz",
    "gn:population":62,
    "gn:timezone":"America/Mexico_City",
    "iso:country":"MX",
    "wof:name":"Plan de la Luz",
    "wof:placetype":"locality",
    "wof:population":62
},
  "geometry": {"coordinates":[-97.03694,19.86667000000001],"type":"Point"}
}