{
  "type": "Feature",
  "properties": {
    "gn:admin1_code":"18",
    "gn:admin2_code":"19.0",
    "gn:asciiname":"Piedra de Amolar",
    "gn:country_code":"MX",
    "gn:dem":1875,
    "gn:feature_class":"P",
    "gn:feature_code":"PPL",
    "gn:name":"Piedra de Amolar",
    "gn:population":8,
    "gn:timezone":"America/Mexico_City",
    "iso:country":"MX",
    "wof:name":"Piedra de Amolar",
    "wof:placetype":"locality",
    "wof:population":8
},
  "geometry": {"coordinates":[-103.96778,21.50833],"type":"Point"}
}