{
  "type": "Feature",
  "properties": {
    "gn:admin1_code":"10",
    "gn:admin2_code":"32.0",
    "gn:asciiname":"El Canoncito",
    "gn:country_code":"MX",
    "gn:dem":1908,
    "gn:feature_class":"P",
    "gn:feature_code":"PPL",
    "gn:name":"El Ca\u00f1oncito",
    "gn:population":0,
    "gn:timezone":"America/Monterrey",
    "iso:country":"MX",
    "name:spa_x_preferred":[
        "El Ca\u00f1oncito"
    ],
    "wof:name":"El Canoncito",
    "wof:placetype":"locality"
},
  "geometry": {"coordinates":[-105.33999,25.27129],"type":"Point"}
}