{
  "type": "Feature",
  "properties": {
    "gn:admin1_code":"21",
    "gn:admin2_code":"110.0",
    "gn:asciiname":"San Francisco Piletas",
    "gn:country_code":"MX",
    "gn:dem":2392,
    "gn:feature_class":"P",
    "gn:feature_code":"PPL",
    "gn:name":"San Francisco Piletas",
    "gn:population":252,
    "gn:timezone":"America/Mexico_City",
    "iso:country":"MX",
    "wof:name":"San Francisco Piletas",
    "wof:placetype":"locality",
    "wof:population":252
},
  "geometry": {"coordinates":[-97.3925,18.82556],"type":"Point"}
}