{
  "type": "Feature",
  "properties": {
    "gn:admin1_code":"21",
    "gn:admin2_code":"35.0",
    "gn:asciiname":"Guadalupe Victoria",
    "gn:country_code":"MX",
    "gn:dem":910,
    "gn:feature_class":"P",
    "gn:feature_code":"PPL",
    "gn:name":"Guadalupe Victoria",
    "gn:population":0,
    "gn:timezone":"America/Mexico_City",
    "iso:country":"MX",
    "name:und_x_variant":[
        "Pueblo Nuevo",
        "Guadalupe Victoria"
    ],
    "wof:name":"Guadalupe Victoria",
    "wof:placetype":"locality"
},
  "geometry": {"coordinates":[-97.16006,18.20905],"type":"Point"}
}