{
  "type": "Feature",
  "properties": {
    "gn:admin1_code":"8.0",
    "gn:admin2_code":"7.0",
    "gn:asciiname":"El Tambo",
    "gn:country_code":"MX",
    "gn:dem":261,
    "gn:feature_class":"P",
    "gn:feature_code":"PPL",
    "gn:name":"El Tambo",
    "gn:population":0,
    "gn:timezone":"America/Mexico_City",
    "iso:country":"MX",
    "name:ceb_x_preferred":[
        "El Tambo"
    ],
    "name:fas_x_preferred":[
        "\u0627\u0644 \u062a\u0627\u0645\u0628\u0648"
    ],
    "name:fra_x_preferred":[
        "El Tambo"
    ],
    "name:ita_x_preferred":[
        "El Tambo"
    ],
    "name:nld_x_preferred":[
        "El Tambo"
    ],
    "name:spa_x_preferred":[
        "El Tambo"
    ],
    "name:swe_x_preferred":[
        "El Tambo"
    ],
    "wof:name":"El Tambo",
    "wof:placetype":"locality"
},
  "geometry": {"coordinates":[-104.14530999999999,19.06535],"type":"Point"}
}