{
  "type": "Feature",
  "properties": {
    "gn:admin1_code":"12",
    "gn:admin2_code":"38.0",
    "gn:asciiname":"Puerto del Pino",
    "gn:country_code":"MX",
    "gn:dem":600,
    "gn:feature_class":"P",
    "gn:feature_code":"PPL",
    "gn:name":"Puerto del Pino",
    "gn:population":0,
    "gn:timezone":"America/Mexico_City",
    "iso:country":"MX",
    "name:spa_x_preferred":[
        "Puerto del Pino"
    ],
    "name:und_x_variant":[
        "Plan de Cuche",
        "Plan del Cuche"
    ],
    "wof:name":"Puerto del Pino",
    "wof:placetype":"locality"
},
  "geometry": {"coordinates":[-101.3997,17.77619],"type":"Point"}
}