{
  "type": "Feature",
  "properties": {
    "gn:admin1_code":"30",
    "gn:admin2_code":"173",
    "gn:asciiname":"Los Montieles",
    "gn:country_code":"MX",
    "gn:dem":136,
    "gn:feature_class":"P",
    "gn:feature_code":"PPL",
    "gn:name":"Los Montieles",
    "gn:population":36,
    "gn:timezone":"America/Mexico_City",
    "iso:country":"MX",
    "wof:name":"Los Montieles",
    "wof:placetype":"locality",
    "wof:population":36
},
  "geometry": {"coordinates":[-96.76917,18.53944],"type":"Point"}
}