{
  "type": "Feature",
  "properties": {
    "gn:admin1_code":"30",
    "gn:admin2_code":"157.0",
    "gn:asciiname":"Ejido la Lima",
    "gn:country_code":"MX",
    "gn:dem":84,
    "gn:feature_class":"P",
    "gn:feature_code":"PPL",
    "gn:name":"Ejido la Lima",
    "gn:population":0,
    "gn:timezone":"America/Mexico_City",
    "iso:country":"MX",
    "name:spa_x_preferred":[
        "Ejido la Lima"
    ],
    "name:spa_x_variant":[
        "La Lima Nueva"
    ],
    "wof:name":"Ejido la Lima",
    "wof:placetype":"locality"
},
  "geometry": {"coordinates":[-97.66719999999999,20.75298],"type":"Point"}
}