{
  "type": "Feature",
  "properties": {
    "gn:admin1_code":"14",
    "gn:admin2_code":"74.0",
    "gn:asciiname":"Hacienda del Llano",
    "gn:country_code":"MX",
    "gn:dem":2118,
    "gn:feature_class":"P",
    "gn:feature_code":"PPL",
    "gn:name":"Hacienda del Llano",
    "gn:population":8,
    "gn:timezone":"America/Mexico_City",
    "iso:country":"MX",
    "wof:name":"Hacienda del Llano",
    "wof:placetype":"locality",
    "wof:population":8
},
  "geometry": {"coordinates":[-102.22917,20.92],"type":"Point"}
}