{
  "type": "Feature",
  "properties": {
    "gn:admin1_code":"12",
    "gn:admin2_code":"55.0",
    "gn:asciiname":"San Jose el Potrero",
    "gn:country_code":"MX",
    "gn:dem":1128,
    "gn:feature_class":"P",
    "gn:feature_code":"PPL",
    "gn:name":"San Jos\u00e9 el Potrero",
    "gn:population":711,
    "gn:timezone":"America/Mexico_City",
    "iso:country":"MX",
    "name:und_x_variant":[
        "San Jos\u00e9 el Potrero"
    ],
    "wof:name":"San Jose el Potrero",
    "wof:placetype":"locality",
    "wof:population":711
},
  "geometry": {"coordinates":[-99.47167,18.64583],"type":"Point"}
}