{
  "type": "Feature",
  "properties": {
    "gn:admin1_code":"32",
    "gn:admin2_code":"49",
    "gn:asciiname":"El Crucero de Santa Cruz",
    "gn:country_code":"MX",
    "gn:dem":2449,
    "gn:feature_class":"P",
    "gn:feature_code":"PPL",
    "gn:name":"El Crucero de Santa Cruz",
    "gn:population":53,
    "gn:timezone":"America/Mazatlan",
    "iso:country":"MX",
    "wof:name":"El Crucero de Santa Cruz",
    "wof:placetype":"locality",
    "wof:population":53
},
  "geometry": {"coordinates":[-104.34528,22.40806],"type":"Point"}
}