{
  "type": "Feature",
  "properties": {
    "gn:admin1_code":"23",
    "gn:asciiname":"San Enrique",
    "gn:country_code":"MX",
    "gn:dem":57,
    "gn:feature_class":"P",
    "gn:feature_code":"PPL",
    "gn:name":"San Enrique",
    "gn:population":0,
    "gn:timezone":"America/Cancun",
    "iso:country":"MX",
    "name:ceb_x_preferred":[
        "San Enrique"
    ],
    "name:deu_x_preferred":[
        "San Enrique"
    ],
    "name:ilo_x_preferred":[
        "San Enrique"
    ],
    "name:ita_x_preferred":[
        "San Enrique"
    ],
    "name:nld_x_preferred":[
        "San Enrique"
    ],
    "name:spa_x_preferred":[
        "San Enrique"
    ],
    "name:swe_x_preferred":[
        "San Enrique"
    ],
    "name:war_x_preferred":[
        "San Enrique"
    ],
    "wof:name":"San Enrique",
    "wof:placetype":"locality"
},
  "geometry": {"coordinates":[-89.00745000000001,19.88668],"type":"Point"}
}