{
  "type": "Feature",
  "properties": {
    "gn:admin1_code":"10",
    "gn:admin2_code":"21.0",
    "gn:asciiname":"El Pial",
    "gn:country_code":"MX",
    "gn:dem":1885,
    "gn:feature_class":"P",
    "gn:feature_code":"PPL",
    "gn:name":"El Pial",
    "gn:population":0,
    "gn:timezone":"America/Monterrey",
    "iso:country":"MX",
    "name:spa_x_preferred":[
        "Morales"
    ],
    "name:spa_x_variant":[
        "El Pial"
    ],
    "wof:name":"El Pial",
    "wof:placetype":"locality"
},
  "geometry": {"coordinates":[-103.89567,24.63165],"type":"Point"}
}