{
  "type": "Feature",
  "properties": {
    "gn:admin1_code":"10",
    "gn:admin2_code":"23.0",
    "gn:asciiname":"Los Barbechos",
    "gn:country_code":"MX",
    "gn:dem":2383,
    "gn:feature_class":"P",
    "gn:feature_code":"PPL",
    "gn:name":"Los Barbechos",
    "gn:population":0,
    "gn:timezone":"America/Monterrey",
    "iso:country":"MX",
    "name:spa_x_preferred":[
        "Los Barbechos"
    ],
    "wof:name":"Los Barbechos",
    "wof:placetype":"locality"
},
  "geometry": {"coordinates":[-105.09690999999999,23.54317],"type":"Point"}
}