{
  "type": "Feature",
  "properties": {
    "gn:admin1_code":"11.0",
    "gn:asciiname":"La Muralla de los Leones",
    "gn:country_code":"MX",
    "gn:dem":1884,
    "gn:feature_class":"P",
    "gn:feature_code":"PPL",
    "gn:name":"La Muralla de los Leones",
    "gn:population":0,
    "gn:timezone":"America/Mexico_City",
    "iso:country":"MX",
    "name:spa_x_preferred":[
        "La Muralla de los Leones"
    ],
    "wof:name":"La Muralla de los Leones",
    "wof:placetype":"locality"
},
  "geometry": {"coordinates":[-101.91876000000001,20.59159],"type":"Point"}
}