{
  "type": "Feature",
  "properties": {
    "gn:admin1_code":"24",
    "gn:admin2_code":"23.0",
    "gn:asciiname":"Granja las Cuatas",
    "gn:country_code":"MX",
    "gn:dem":958,
    "gn:feature_class":"P",
    "gn:feature_code":"PPL",
    "gn:name":"Granja las Cuatas",
    "gn:population":5,
    "gn:timezone":"America/Mexico_City",
    "iso:country":"MX",
    "wof:name":"Granja las Cuatas",
    "wof:placetype":"locality",
    "wof:population":5
},
  "geometry": {"coordinates":[-99.62472,21.83556],"type":"Point"}
}