{
  "type": "Feature",
  "properties": {
    "gn:admin1_code":"20",
    "gn:admin2_code":"352.0",
    "gn:asciiname":"La Salud",
    "gn:country_code":"MX",
    "gn:dem":1782,
    "gn:feature_class":"P",
    "gn:feature_code":"PPL",
    "gn:name":"La Salud",
    "gn:population":178,
    "gn:timezone":"America/Mexico_City",
    "iso:country":"MX",
    "wof:name":"La Salud",
    "wof:placetype":"locality",
    "wof:population":178
},
  "geometry": {"coordinates":[-97.99611,17.83056000000001],"type":"Point"}
}