{
  "type": "Feature",
  "properties": {
    "gn:admin1_code":"30",
    "gn:admin2_code":"152.0",
    "gn:asciiname":"Punta de Bustos",
    "gn:country_code":"MX",
    "gn:dem":14,
    "gn:feature_class":"P",
    "gn:feature_code":"PPL",
    "gn:name":"Punta de Bustos",
    "gn:population":0,
    "gn:timezone":"America/Mexico_City",
    "iso:country":"MX",
    "name:spa_x_preferred":[
        "Punta de Bustos"
    ],
    "wof:name":"Punta de Bustos",
    "wof:placetype":"locality"
},
  "geometry": {"coordinates":[-97.7548,21.99109],"type":"Point"}
}