{
  "type": "Feature",
  "properties": {
    "gn:admin1_code":"10",
    "gn:admin2_code":"32.0",
    "gn:asciiname":"Las Cuarras",
    "gn:country_code":"MX",
    "gn:dem":2101,
    "gn:feature_class":"P",
    "gn:feature_code":"PPL",
    "gn:name":"Las Cuarras",
    "gn:population":0,
    "gn:timezone":"America/Monterrey",
    "iso:country":"MX",
    "name:spa_x_preferred":[
        "Las Cuarras"
    ],
    "wof:name":"Las Cuarras",
    "wof:placetype":"locality"
},
  "geometry": {"coordinates":[-105.31488,25.05245],"type":"Point"}
}