{
  "type": "Feature",
  "properties": {
    "gn:admin1_code":"13",
    "gn:admin2_code":"3.0",
    "gn:asciiname":"Pozo Grande",
    "gn:country_code":"MX",
    "gn:dem":1972,
    "gn:feature_class":"P",
    "gn:feature_code":"PPL",
    "gn:name":"Pozo Grande",
    "gn:population":0,
    "gn:timezone":"America/Mexico_City",
    "iso:country":"MX",
    "name:spa_x_preferred":[
        "Pozo Grande"
    ],
    "wof:name":"Pozo Grande",
    "wof:placetype":"locality"
},
  "geometry": {"coordinates":[-98.96747000000001,20.26536],"type":"Point"}
}