{
  "type": "Feature",
  "properties": {
    "gn:admin1_code":"30",
    "gn:admin2_code":"58",
    "gn:asciiname":"El Molino",
    "gn:country_code":"MX",
    "gn:dem":177,
    "gn:feature_class":"P",
    "gn:feature_code":"PPL",
    "gn:name":"El Molino",
    "gn:population":44,
    "gn:timezone":"America/Mexico_City",
    "iso:country":"MX",
    "wof:name":"El Molino",
    "wof:placetype":"locality",
    "wof:population":44
},
  "geometry": {"coordinates":[-97.99611,20.94694],"type":"Point"}
}