{
  "type": "Feature",
  "properties": {
    "gn:admin1_code":"5",
    "gn:admin2_code":"61.0",
    "gn:asciiname":"El Paraiso (El Eden)",
    "gn:country_code":"MX",
    "gn:dem":895,
    "gn:feature_class":"P",
    "gn:feature_code":"PPL",
    "gn:name":"El Para\u00edso (El Ed\u00e9n)",
    "gn:population":7,
    "gn:timezone":"America/Mexico_City",
    "iso:country":"MX",
    "name:und_x_variant":[
        "El Para\u00edso (El Ed\u00e9n)"
    ],
    "wof:name":"El Paraiso (El Eden)",
    "wof:placetype":"locality",
    "wof:population":7
},
  "geometry": {"coordinates":[-93.28278,16.70139],"type":"Point"}
}