{
  "type": "Feature",
  "properties": {
    "gn:admin1_code":"12",
    "gn:admin2_code":"27",
    "gn:asciiname":"Limon de Pungarancho",
    "gn:country_code":"MX",
    "gn:dem":390,
    "gn:feature_class":"P",
    "gn:feature_code":"PPL",
    "gn:name":"Lim\u00f3n de Pungarancho",
    "gn:population":52,
    "gn:timezone":"America/Mexico_City",
    "iso:country":"MX",
    "name:und_x_variant":[
        "Lim\u00f3n de Pungarancho"
    ],
    "wof:name":"Limon de Pungarancho",
    "wof:placetype":"locality",
    "wof:population":52
},
  "geometry": {"coordinates":[-100.65519999999999,18.82892],"type":"Point"}
}