{
  "type": "Feature",
  "properties": {
    "gn:admin1_code":"5",
    "gn:admin2_code":"9.0",
    "gn:asciiname":"San Carlos las Carolinas (El Salto de Abad)",
    "gn:country_code":"MX",
    "gn:dem":231,
    "gn:feature_class":"P",
    "gn:feature_code":"PPL",
    "gn:name":"San Carlos las Carolinas (El Salto de Abad)",
    "gn:population":5,
    "gn:timezone":"America/Mexico_City",
    "iso:country":"MX",
    "wof:name":"San Carlos las Carolinas (El Salto de Abad)",
    "wof:placetype":"locality",
    "wof:population":5
},
  "geometry": {"coordinates":[-93.77889,16.23306],"type":"Point"}
}