{
  "type": "Feature",
  "properties": {
    "gn:admin1_code":"15.0",
    "gn:admin2_code":"105.0",
    "gn:asciiname":"Puerto Seco",
    "gn:country_code":"MX",
    "gn:dem":936,
    "gn:feature_class":"P",
    "gn:feature_code":"PPL",
    "gn:name":"Puerto Seco",
    "gn:population":0,
    "gn:timezone":"America/Mexico_City",
    "iso:country":"MX",
    "name:spa_x_preferred":[
        "Puerto Seco"
    ],
    "wof:name":"Puerto Seco",
    "wof:placetype":"locality"
},
  "geometry": {"coordinates":[-100.22401000000001,18.5261],"type":"Point"}
}