{
  "type": "Feature",
  "properties": {
    "gn:admin1_code":"19.0",
    "gn:admin2_code":"42.0",
    "gn:asciiname":"Los Laureles",
    "gn:country_code":"MX",
    "gn:dem":216,
    "gn:feature_class":"P",
    "gn:feature_code":"PPL",
    "gn:name":"Los Laureles",
    "gn:population":0,
    "gn:timezone":"America/Monterrey",
    "iso:country":"MX",
    "name:por_x_preferred":[
        "Los Laureles"
    ],
    "name:spa_x_preferred":[
        "Los Laureles"
    ],
    "wof:name":"Los Laureles",
    "wof:placetype":"locality"
},
  "geometry": {"coordinates":[-99.5188,25.66123],"type":"Point"}
}