{
  "type": "Feature",
  "properties": {
    "gn:admin1_code":"6",
    "gn:admin2_code":"65.0",
    "gn:asciiname":"El Tascate",
    "gn:country_code":"MX",
    "gn:dem":2157,
    "gn:feature_class":"P",
    "gn:feature_code":"PPL",
    "gn:name":"El T\u00e1scate",
    "gn:population":6,
    "gn:timezone":"America/Chihuahua",
    "iso:country":"MX",
    "name:und_x_variant":[
        "El T\u00e1scate"
    ],
    "wof:name":"El Tascate",
    "wof:placetype":"locality",
    "wof:population":6
},
  "geometry": {"coordinates":[-107.93075,27.44909],"type":"Point"}
}