{
  "type": "Feature",
  "properties": {
    "gn:admin1_code":"28",
    "gn:admin2_code":"1.0",
    "gn:asciiname":"Los Tajos",
    "gn:country_code":"MX",
    "gn:dem":119,
    "gn:feature_class":"P",
    "gn:feature_code":"PPL",
    "gn:name":"Los Tajos",
    "gn:population":0,
    "gn:timezone":"America/Monterrey",
    "iso:country":"MX",
    "name:spa_x_preferred":[
        "Los Tajos"
    ],
    "name:und_x_variant":[
        "Rancho Los Tajos"
    ],
    "wof:name":"Los Tajos",
    "wof:placetype":"locality"
},
  "geometry": {"coordinates":[-98.12595,24.29299],"type":"Point"}
}