{
  "type": "Feature",
  "properties": {
    "gn:admin1_code":"16.0",
    "gn:admin2_code":"26.0",
    "gn:asciiname":"Solorio",
    "gn:country_code":"MX",
    "gn:dem":782,
    "gn:feature_class":"P",
    "gn:feature_code":"PPL",
    "gn:name":"Solorio",
    "gn:population":0,
    "gn:timezone":"America/Mexico_City",
    "iso:country":"MX",
    "name:spa_x_preferred":[
        "Solorio"
    ],
    "wof:name":"Solorio",
    "wof:placetype":"locality"
},
  "geometry": {"coordinates":[-103.44468000000001,18.88088],"type":"Point"}
}