{
  "type": "Feature",
  "properties": {
    "gn:admin1_code":"14",
    "gn:admin2_code":"49",
    "gn:asciiname":"El Arenal",
    "gn:country_code":"MX",
    "gn:dem":1403,
    "gn:feature_class":"P",
    "gn:feature_code":"PPL",
    "gn:name":"El Arenal",
    "gn:population":32,
    "gn:timezone":"America/Mexico_City",
    "iso:country":"MX",
    "wof:name":"El Arenal",
    "wof:placetype":"locality",
    "wof:population":32
},
  "geometry": {"coordinates":[-103.09860999999999,19.36472],"type":"Point"}
}