{
  "type": "Feature",
  "properties": {
    "gn:admin1_code":"1.0",
    "gn:asciiname":"Los Bancos",
    "gn:country_code":"MX",
    "gn:dem":2213,
    "gn:feature_class":"P",
    "gn:feature_code":"PPL",
    "gn:name":"Los Bancos",
    "gn:population":0,
    "gn:timezone":"America/Mexico_City",
    "iso:country":"MX",
    "wof:name":"Los Bancos",
    "wof:placetype":"locality"
},
  "geometry": {"coordinates":[-102.81667,22.95833],"type":"Point"}
}