{
  "type": "Feature",
  "properties": {
    "gn:admin1_code":"5.0",
    "gn:admin2_code":"87.0",
    "gn:asciiname":"Israel",
    "gn:country_code":"MX",
    "gn:dem":13,
    "gn:feature_class":"P",
    "gn:feature_code":"PPL",
    "gn:name":"Israel",
    "gn:population":0,
    "gn:timezone":"America/Mexico_City",
    "iso:country":"MX",
    "name:spa_x_preferred":[
        "Israel"
    ],
    "wof:name":"Israel",
    "wof:placetype":"locality"
},
  "geometry": {"coordinates":[-92.28972,14.66248],"type":"Point"}
}