{
  "type": "Feature",
  "properties": {
    "gn:admin1_code":"11",
    "gn:admin2_code":"31.0",
    "gn:asciiname":"Kilometro 16",
    "gn:country_code":"MX",
    "gn:dem":1770,
    "gn:feature_class":"P",
    "gn:feature_code":"PPL",
    "gn:name":"Kil\u00f3metro 16",
    "gn:population":64,
    "gn:timezone":"America/Mexico_City",
    "iso:country":"MX",
    "name:und_x_variant":[
        "Kil\u00f3metro 16"
    ],
    "wof:name":"Kilometro 16",
    "wof:placetype":"locality",
    "wof:population":64
},
  "geometry": {"coordinates":[-101.81610999999999,21.03583],"type":"Point"}
}