{
  "type": "Feature",
  "properties": {
    "gn:admin1_code":"14",
    "gn:admin2_code":"48",
    "gn:asciiname":"Los Chiqueros",
    "gn:country_code":"MX",
    "gn:dem":2239,
    "gn:feature_class":"P",
    "gn:feature_code":"PPL",
    "gn:name":"Los Chiqueros",
    "gn:population":11,
    "gn:timezone":"America/Mexico_City",
    "iso:country":"MX",
    "wof:name":"Los Chiqueros",
    "wof:placetype":"locality",
    "wof:population":11
},
  "geometry": {"coordinates":[-102.07917,20.64556],"type":"Point"}
}