{
  "type": "Feature",
  "properties": {
    "gn:admin1_code":"18.0",
    "gn:admin2_code":"1.0",
    "gn:asciiname":"El Alacran",
    "gn:country_code":"MX",
    "gn:dem":21,
    "gn:feature_class":"P",
    "gn:feature_code":"PPL",
    "gn:name":"El Alacr\u00e1n",
    "gn:population":20,
    "gn:timezone":"America/Mazatlan",
    "iso:country":"MX",
    "name:spa_x_preferred":[
        "El Alacr\u00e1n"
    ],
    "wof:name":"El Alacran",
    "wof:placetype":"locality",
    "wof:population":20
},
  "geometry": {"coordinates":[-105.41862999999999,22.47175],"type":"Point"}
}