{
  "type": "Feature",
  "properties": {
    "gn:admin1_code":"27",
    "gn:admin2_code":"1.0",
    "gn:asciiname":"San Joaquin 2da. Seccion",
    "gn:country_code":"MX",
    "gn:dem":25,
    "gn:feature_class":"P",
    "gn:feature_code":"PPL",
    "gn:name":"San Joaqu\u00edn 2da. Secci\u00f3n",
    "gn:population":72,
    "gn:timezone":"America/Mexico_City",
    "iso:country":"MX",
    "name:und_x_variant":[
        "San Joaqu\u00edn 2da. Secci\u00f3n"
    ],
    "wof:name":"San Joaquin 2da. Seccion",
    "wof:placetype":"locality",
    "wof:population":72
},
  "geometry": {"coordinates":[-91.44278,17.99222],"type":"Point"}
}