{
  "type": "Feature",
  "properties": {
    "gn:admin1_code":"10",
    "gn:admin2_code":"7.0",
    "gn:asciiname":"El Pilar",
    "gn:country_code":"MX",
    "gn:dem":1121,
    "gn:feature_class":"P",
    "gn:feature_code":"PPL",
    "gn:name":"El Pilar",
    "gn:population":57,
    "gn:timezone":"America/Monterrey",
    "iso:country":"MX",
    "wof:name":"El Pilar",
    "wof:placetype":"locality",
    "wof:population":57
},
  "geometry": {"coordinates":[-103.46617999999999,25.64834],"type":"Point"}
}