{
  "type": "Feature",
  "properties": {
    "gn:admin1_code":"6",
    "gn:admin2_code":"7.0",
    "gn:asciiname":"Arroyo del Muerto",
    "gn:country_code":"MX",
    "gn:dem":2238,
    "gn:feature_class":"P",
    "gn:feature_code":"PPL",
    "gn:name":"Arroyo del Muerto",
    "gn:population":8,
    "gn:timezone":"America/Chihuahua",
    "iso:country":"MX",
    "wof:name":"Arroyo del Muerto",
    "wof:placetype":"locality",
    "wof:population":8
},
  "geometry": {"coordinates":[-106.82487,26.92677],"type":"Point"}
}