{
  "type": "Feature",
  "properties": {
    "gn:admin1_code":"7.0",
    "gn:admin2_code":"17.0",
    "gn:asciiname":"Escuadron Doscientos Uno",
    "gn:country_code":"MX",
    "gn:dem":1119,
    "gn:feature_class":"P",
    "gn:feature_code":"PPL",
    "gn:name":"Escuadr\u00f3n Doscientos Uno",
    "gn:population":1066,
    "gn:timezone":"America/Monterrey",
    "iso:country":"MX",
    "name:spa_x_preferred":[
        "Escuadr\u00f3n Doscientos Uno"
    ],
    "wof:name":"Escuadron Doscientos Uno",
    "wof:placetype":"locality",
    "wof:population":1066
},
  "geometry": {"coordinates":[-103.34829000000001,25.67433],"type":"Point"}
}