{
  "type": "Feature",
  "properties": {
    "gn:admin1_code":"10",
    "gn:admin2_code":"14.0",
    "gn:asciiname":"Torrecillas",
    "gn:country_code":"MX",
    "gn:dem":2159,
    "gn:feature_class":"P",
    "gn:feature_code":"PPL",
    "gn:name":"Torrecillas",
    "gn:population":0,
    "gn:timezone":"America/Monterrey",
    "iso:country":"MX",
    "name:spa_x_preferred":[
        "Torrecillas"
    ],
    "wof:name":"Torrecillas",
    "wof:placetype":"locality"
},
  "geometry": {"coordinates":[-104.35333,22.69513],"type":"Point"}
}