{
  "type": "Feature",
  "properties": {
    "gn:admin1_code":"32",
    "gn:admin2_code":"40",
    "gn:asciiname":"Laguna Blanca (La Laguna Blanca)",
    "gn:country_code":"MX",
    "gn:dem":2214,
    "gn:feature_class":"P",
    "gn:feature_code":"PPL",
    "gn:name":"Laguna Blanca (La Laguna Blanca)",
    "gn:population":40,
    "gn:timezone":"America/Mexico_City",
    "iso:country":"MX",
    "wof:name":"Laguna Blanca (La Laguna Blanca)",
    "wof:placetype":"locality",
    "wof:population":40
},
  "geometry": {"coordinates":[-103.20860999999999,23.49167000000001],"type":"Point"}
}