{
  "type": "Feature",
  "properties": {
    "gn:admin1_code":"14",
    "gn:admin2_code":"105.0",
    "gn:asciiname":"Ninguno [Camposanto]",
    "gn:country_code":"MX",
    "gn:dem":1549,
    "gn:feature_class":"P",
    "gn:feature_code":"PPL",
    "gn:name":"Ninguno [Camposanto]",
    "gn:population":5,
    "gn:timezone":"America/Mexico_City",
    "iso:country":"MX",
    "wof:name":"Ninguno [Camposanto]",
    "wof:placetype":"locality",
    "wof:population":5
},
  "geometry": {"coordinates":[-102.79528000000001,20.55028],"type":"Point"}
}