{
  "type": "Feature",
  "properties": {
    "gn:admin1_code":"5.0",
    "gn:admin2_code":"20.0",
    "gn:asciiname":"Nueva Espana",
    "gn:country_code":"MX",
    "gn:dem":606,
    "gn:feature_class":"P",
    "gn:feature_code":"PPL",
    "gn:name":"Nueva Espa\u00f1a",
    "gn:population":0,
    "gn:timezone":"America/Mexico_City",
    "iso:country":"MX",
    "name:spa_x_preferred":[
        "Nueva Espa\u00f1a"
    ],
    "wof:name":"Nueva Espana",
    "wof:placetype":"locality"
},
  "geometry": {"coordinates":[-92.91171,16.03002],"type":"Point"}
}