{
  "type": "Feature",
  "properties": {
    "gn:admin1_code":"16",
    "gn:admin2_code":"34.0",
    "gn:asciiname":"Tembendado (Temendao)",
    "gn:country_code":"MX",
    "gn:dem":2101,
    "gn:feature_class":"P",
    "gn:feature_code":"PPL",
    "gn:name":"Tembendado (Temendao)",
    "gn:population":71,
    "gn:timezone":"America/Mexico_City",
    "iso:country":"MX",
    "wof:name":"Tembendado (Temendao)",
    "wof:placetype":"locality",
    "wof:population":71
},
  "geometry": {"coordinates":[-100.60917000000001,19.69111],"type":"Point"}
}