{
  "type": "Feature",
  "properties": {
    "gn:admin1_code":"11",
    "gn:admin2_code":"1",
    "gn:asciiname":"El Pitahayo de Cortes",
    "gn:country_code":"MX",
    "gn:dem":1695,
    "gn:feature_class":"P",
    "gn:feature_code":"PPL",
    "gn:name":"El Pitahayo de Cort\u00e9s",
    "gn:population":50,
    "gn:timezone":"America/Mexico_City",
    "iso:country":"MX",
    "name:und_x_variant":[
        "El Pitahayo de Cort\u00e9s"
    ],
    "wof:name":"El Pitahayo de Cortes",
    "wof:placetype":"locality",
    "wof:population":50
},
  "geometry": {"coordinates":[-101.56806,20.46861],"type":"Point"}
}