{
  "type": "Feature",
  "properties": {
    "gn:admin1_code":"19.0",
    "gn:asciiname":"Paso de la Parrita",
    "gn:country_code":"MX",
    "gn:dem":429,
    "gn:feature_class":"P",
    "gn:feature_code":"PPL",
    "gn:name":"Paso de la Parrita",
    "gn:population":0,
    "gn:timezone":"America/Monterrey",
    "iso:country":"MX",
    "name:spa_x_preferred":[
        "Paso de la Parrita"
    ],
    "wof:name":"Paso de la Parrita",
    "wof:placetype":"locality"
},
  "geometry": {"coordinates":[-99.66567000000001,24.82025],"type":"Point"}
}