{
  "type": "Feature",
  "properties": {
    "gn:admin1_code":"5",
    "gn:admin2_code":"20.0",
    "gn:asciiname":"Ninos Heroes",
    "gn:country_code":"MX",
    "gn:dem":602,
    "gn:feature_class":"P",
    "gn:feature_code":"PPL",
    "gn:name":"Ni\u00f1os H\u00e9roes",
    "gn:population":0,
    "gn:timezone":"America/Mexico_City",
    "iso:country":"MX",
    "name:spa_x_preferred":[
        "Ni\u00f1os H\u00e9roes"
    ],
    "wof:name":"Ninos Heroes",
    "wof:placetype":"locality"
},
  "geometry": {"coordinates":[-92.62293,16.10829],"type":"Point"}
}