{
  "type": "Feature",
  "properties": {
    "gn:admin1_code":"17",
    "gn:admin2_code":"31.0",
    "gn:asciiname":"10 de Abril",
    "gn:country_code":"MX",
    "gn:dem":946,
    "gn:feature_class":"P",
    "gn:feature_code":"PPL",
    "gn:name":"10 de Abril",
    "gn:population":202,
    "gn:timezone":"America/Mexico_City",
    "iso:country":"MX",
    "wof:name":"10 de Abril",
    "wof:placetype":"locality",
    "wof:population":202
},
  "geometry": {"coordinates":[-99.22028,18.64694],"type":"Point"}
}