{
  "type": "Feature",
  "properties": {
    "gn:admin1_code":"10",
    "gn:admin2_code":"14.0",
    "gn:asciiname":"Los Cuervos",
    "gn:country_code":"MX",
    "gn:dem":1565,
    "gn:feature_class":"P",
    "gn:feature_code":"PPL",
    "gn:name":"Los Cuervos",
    "gn:population":5,
    "gn:timezone":"America/Monterrey",
    "iso:country":"MX",
    "wof:name":"Los Cuervos",
    "wof:placetype":"locality",
    "wof:population":5
},
  "geometry": {"coordinates":[-104.70135999999999,23.11919],"type":"Point"}
}