{
  "type": "Feature",
  "properties": {
    "gn:admin1_code":"11",
    "gn:admin2_code":"1.0",
    "gn:asciiname":"Granja la Esperanza",
    "gn:country_code":"MX",
    "gn:dem":1700,
    "gn:feature_class":"P",
    "gn:feature_code":"PPL",
    "gn:name":"Granja la Esperanza",
    "gn:population":4,
    "gn:timezone":"America/Mexico_City",
    "iso:country":"MX",
    "wof:name":"Granja la Esperanza",
    "wof:placetype":"locality",
    "wof:population":4
},
  "geometry": {"coordinates":[-101.48583000000001,20.49556],"type":"Point"}
}