{
  "type": "Feature",
  "properties": {
    "gn:admin1_code":"26.0",
    "gn:admin2_code":"69.0",
    "gn:asciiname":"La Calavera",
    "gn:country_code":"MX",
    "gn:dem":1919,
    "gn:feature_class":"P",
    "gn:feature_code":"PPL",
    "gn:name":"La Calavera",
    "gn:population":0,
    "gn:timezone":"America/Hermosillo",
    "iso:country":"MX",
    "name:spa_x_preferred":[
        "La Calavera"
    ],
    "wof:name":"La Calavera",
    "wof:placetype":"locality"
},
  "geometry": {"coordinates":[-109.04113,28.4891],"type":"Point"}
}