{
  "type": "Feature",
  "properties": {
    "gn:admin1_code":"20",
    "gn:asciiname":"Nuevo San Martin",
    "gn:country_code":"MX",
    "gn:dem":74,
    "gn:feature_class":"P",
    "gn:feature_code":"PPL",
    "gn:name":"Nuevo San Mart\u00edn",
    "gn:population":0,
    "gn:timezone":"America/Mexico_City",
    "iso:country":"MX",
    "name:spa_x_preferred":[
        "Nuevo San Mart\u00edn"
    ],
    "wof:name":"Nuevo San Martin",
    "wof:placetype":"locality"
},
  "geometry": {"coordinates":[-95.52346,17.57987],"type":"Point"}
}