{
  "type": "Feature",
  "properties": {
    "gn:admin1_code":"21",
    "gn:admin2_code":"34.0",
    "gn:asciiname":"San Antonio Mihuacan",
    "gn:country_code":"MX",
    "gn:dem":2208,
    "gn:feature_class":"P",
    "gn:feature_code":"PPL",
    "gn:name":"San Antonio Mihuac\u00e1n",
    "gn:population":0,
    "gn:timezone":"America/Mexico_City",
    "iso:country":"MX",
    "name:spa_x_preferred":[
        "San Antonio Mihuac\u00e1n"
    ],
    "name:und_x_variant":[
        "Minuac\u00e1n"
    ],
    "wof:name":"San Antonio Mihuacan",
    "wof:placetype":"locality"
},
  "geometry": {"coordinates":[-98.30537,19.15107],"type":"Point"}
}