{
  "type": "Feature",
  "properties": {
    "gn:admin1_code":"5",
    "gn:admin2_code":"61.0",
    "gn:asciiname":"La Independencia (Las Pilas)",
    "gn:country_code":"MX",
    "gn:dem":855,
    "gn:feature_class":"P",
    "gn:feature_code":"PPL",
    "gn:name":"La Independencia (Las Pilas)",
    "gn:population":1178,
    "gn:timezone":"America/Mexico_City",
    "iso:country":"MX",
    "wof:name":"La Independencia (Las Pilas)",
    "wof:placetype":"locality",
    "wof:population":1178
},
  "geometry": {"coordinates":[-93.24944000000001,16.6775],"type":"Point"}
}