{
  "type": "Feature",
  "properties": {
    "gn:admin1_code":"26",
    "gn:admin2_code":"27.0",
    "gn:asciiname":"La Sandia",
    "gn:country_code":"MX",
    "gn:dem":1251,
    "gn:feature_class":"P",
    "gn:feature_code":"PPL",
    "gn:name":"La Sand\u00eda",
    "gn:population":0,
    "gn:timezone":"America/Hermosillo",
    "iso:country":"MX",
    "name:spa_x_preferred":[
        "La Sand\u00eda"
    ],
    "name:und_x_variant":[
        "Rancho Las Sandias"
    ],
    "wof:name":"La Sandia",
    "wof:placetype":"locality"
},
  "geometry": {"coordinates":[-109.69033,30.71624000000001],"type":"Point"}
}