{
  "type": "Feature",
  "properties": {
    "gn:admin1_code":"16",
    "gn:admin2_code":"97.0",
    "gn:asciiname":"La Vibora",
    "gn:country_code":"MX",
    "gn:dem":1382,
    "gn:feature_class":"P",
    "gn:feature_code":"PPL",
    "gn:name":"La V\u00edbora",
    "gn:population":9,
    "gn:timezone":"America/Mexico_City",
    "iso:country":"MX",
    "name:und_x_variant":[
        "La V\u00edbora"
    ],
    "wof:name":"La Vibora",
    "wof:placetype":"locality",
    "wof:population":9
},
  "geometry": {"coordinates":[-101.57666999999999,19.08194],"type":"Point"}
}