{
  "type": "Feature",
  "properties": {
    "gn:admin1_code":"5",
    "gn:admin2_code":"83.0",
    "gn:asciiname":"Santa Rita Agua Escondida",
    "gn:country_code":"MX",
    "gn:dem":908,
    "gn:feature_class":"P",
    "gn:feature_code":"PPL",
    "gn:name":"Santa Rita Agua Escondida",
    "gn:population":90,
    "gn:timezone":"America/Mexico_City",
    "iso:country":"MX",
    "wof:name":"Santa Rita Agua Escondida",
    "wof:placetype":"locality",
    "wof:population":90
},
  "geometry": {"coordinates":[-92.35778000000001,16.25083],"type":"Point"}
}