{
  "type": "Feature",
  "properties": {
    "gn:admin1_code":"20",
    "gn:admin2_code":"277.0",
    "gn:asciiname":"Los Limones",
    "gn:country_code":"MX",
    "gn:dem":959,
    "gn:feature_class":"P",
    "gn:feature_code":"PPL",
    "gn:name":"Los Limones",
    "gn:population":100,
    "gn:timezone":"America/Mexico_City",
    "iso:country":"MX",
    "wof:name":"Los Limones",
    "wof:placetype":"locality",
    "wof:population":100
},
  "geometry": {"coordinates":[-97.07889,16.37611],"type":"Point"}
}