{
  "type": "Feature",
  "properties": {
    "gn:admin1_code":"6.0",
    "gn:admin2_code":"7.0",
    "gn:asciiname":"Chiquihuite",
    "gn:country_code":"MX",
    "gn:dem":2232,
    "gn:feature_class":"P",
    "gn:feature_code":"PPL",
    "gn:name":"Chiquihuite",
    "gn:population":0,
    "gn:timezone":"America/Chihuahua",
    "iso:country":"MX",
    "name:spa_x_preferred":[
        "Chiquihuite"
    ],
    "name:und_x_variant":[
        "Rancho Chiquihuite"
    ],
    "wof:name":"Chiquihuite",
    "wof:placetype":"locality"
},
  "geometry": {"coordinates":[-106.65628,26.91259],"type":"Point"}
}