{
  "type": "Feature",
  "properties": {
    "gn:admin1_code":"16",
    "gn:admin2_code":"97.0",
    "gn:asciiname":"El Llano",
    "gn:country_code":"MX",
    "gn:dem":1262,
    "gn:feature_class":"P",
    "gn:feature_code":"PPL",
    "gn:name":"El Llano",
    "gn:population":0,
    "gn:timezone":"America/Mexico_City",
    "iso:country":"MX",
    "name:ceb_x_preferred":[
        "El Llano"
    ],
    "name:deu_x_preferred":[
        "El Llano"
    ],
    "name:fra_x_preferred":[
        "El Llano"
    ],
    "name:ita_x_preferred":[
        "El Llano"
    ],
    "name:spa_x_preferred":[
        "El Llano"
    ],
    "name:swe_x_preferred":[
        "El Llano"
    ],
    "wof:name":"El Llano",
    "wof:placetype":"locality"
},
  "geometry": {"coordinates":[-101.50756,18.87518],"type":"Point"}
}