{
  "type": "Feature",
  "properties": {
    "gn:admin1_code":"16",
    "gn:admin2_code":"67.0",
    "gn:asciiname":"Colonia Natalio Vazquez Pallares (Norica)",
    "gn:country_code":"MX",
    "gn:dem":1694,
    "gn:feature_class":"P",
    "gn:feature_code":"PPL",
    "gn:name":"Colonia Natalio V\u00e1zquez Pallares (Norica)",
    "gn:population":54,
    "gn:timezone":"America/Mexico_City",
    "iso:country":"MX",
    "name:und_x_variant":[
        "Colonia Natalio V\u00e1zquez Pallares (Norica)"
    ],
    "wof:name":"Colonia Natalio Vazquez Pallares (Norica)",
    "wof:placetype":"locality",
    "wof:population":54
},
  "geometry": {"coordinates":[-101.89221999999999,20.12583],"type":"Point"}
}