{
  "type": "Feature",
  "properties": {
    "gn:admin1_code":"6.0",
    "gn:admin2_code":"11.0",
    "gn:asciiname":"La Verde",
    "gn:country_code":"MX",
    "gn:dem":1521,
    "gn:feature_class":"P",
    "gn:feature_code":"PPL",
    "gn:name":"La Verde",
    "gn:population":0,
    "gn:timezone":"America/Chihuahua",
    "iso:country":"MX",
    "name:ceb_x_preferred":[
        "La Verde"
    ],
    "name:por_x_preferred":[
        "La Verde"
    ],
    "name:spa_x_preferred":[
        "La Verde"
    ],
    "name:swe_x_preferred":[
        "La Verde"
    ],
    "name:urd_x_preferred":[
        "\u0644\u0627 \u0648\u06cc\u0631\u0688\u06cc"
    ],
    "wof:name":"La Verde",
    "wof:placetype":"locality"
},
  "geometry": {"coordinates":[-104.48993,27.65684000000001],"type":"Point"}
}