{
  "type": "Feature",
  "properties": {
    "gn:admin1_code":"30",
    "gn:admin2_code":"143.0",
    "gn:asciiname":"Sabaneta",
    "gn:country_code":"MX",
    "gn:dem":14,
    "gn:feature_class":"P",
    "gn:feature_code":"PPL",
    "gn:name":"Sabaneta",
    "gn:population":116,
    "gn:timezone":"America/Mexico_City",
    "iso:country":"MX",
    "name:bar_x_preferred":[
        "Sabaneta"
    ],
    "name:ceb_x_preferred":[
        "Sabaneta"
    ],
    "name:deu_x_preferred":[
        "Sabaneta"
    ],
    "name:fas_x_preferred":[
        "\u0633\u0627\u0628\u0627\u0646\u062a\u0627"
    ],
    "name:fra_x_preferred":[
        "Sabaneta"
    ],
    "name:ita_x_preferred":[
        "Sabaneta"
    ],
    "name:nld_x_preferred":[
        "Sabaneta"
    ],
    "name:pol_x_preferred":[
        "Sabaneta"
    ],
    "name:por_x_preferred":[
        "Sabaneta"
    ],
    "name:rus_x_preferred":[
        "\u0421\u0430\u0431\u0430\u043d\u0435\u0442\u0430"
    ],
    "name:sco_x_preferred":[
        "Sabaneta"
    ],
    "name:spa_x_preferred":[
        "Sabaneta"
    ],
    "name:srp_x_preferred":[
        "\u0421\u0430\u0431\u0430\u043d\u0435\u0442\u0430"
    ],
    "name:swe_x_preferred":[
        "Sabaneta"
    ],
    "name:vie_x_preferred":[
        "Sabaneta"
    ],
    "name:zho_x_preferred":[
        "\u8428\u74e6\u5185\u5854"
    ],
    "wof:name":"Sabaneta",
    "wof:placetype":"locality",
    "wof:population":116
},
  "geometry": {"coordinates":[-95.46944000000001,18.38528],"type":"Point"}
}