{
  "type": "Feature",
  "properties": {
    "gn:admin1_code":"7.0",
    "gn:admin2_code":"23.0",
    "gn:asciiname":"Punta de la Sierra",
    "gn:country_code":"MX",
    "gn:dem":1060,
    "gn:feature_class":"P",
    "gn:feature_code":"PPL",
    "gn:name":"Punta de la Sierra",
    "gn:population":2,
    "gn:timezone":"America/Monterrey",
    "iso:country":"MX",
    "name:spa_x_preferred":[
        "Punta de la Sierra"
    ],
    "wof:name":"Punta de la Sierra",
    "wof:placetype":"locality",
    "wof:population":2
},
  "geometry": {"coordinates":[-102.74238,29.04937],"type":"Point"}
}