{
  "type": "Feature",
  "properties": {
    "gn:admin1_code":"6.0",
    "gn:admin2_code":"5.0",
    "gn:asciiname":"La Cuchara",
    "gn:country_code":"MX",
    "gn:dem":1319,
    "gn:feature_class":"P",
    "gn:feature_code":"PPL",
    "gn:name":"La Cuchara",
    "gn:population":0,
    "gn:timezone":"America/Chihuahua",
    "iso:country":"MX",
    "name:spa_x_preferred":[
        "La Cuchara"
    ],
    "wof:name":"La Cuchara",
    "wof:placetype":"locality"
},
  "geometry": {"coordinates":[-107.30927,30.95947],"type":"Point"}
}