{
  "type": "Feature",
  "properties": {
    "gn:admin1_code":"16",
    "gn:admin2_code":"8.0",
    "gn:asciiname":"El Paraje del Padre",
    "gn:country_code":"MX",
    "gn:dem":472,
    "gn:feature_class":"P",
    "gn:feature_code":"PPL",
    "gn:name":"El Paraje del Padre",
    "gn:population":5,
    "gn:timezone":"America/Mexico_City",
    "iso:country":"MX",
    "wof:name":"El Paraje del Padre",
    "wof:placetype":"locality",
    "wof:population":5
},
  "geometry": {"coordinates":[-103.42361,18.485],"type":"Point"}
}