{
  "type": "Feature",
  "properties": {
    "gn:admin1_code":"25",
    "gn:admin2_code":"10.0",
    "gn:asciiname":"Saca de Agua",
    "gn:country_code":"MX",
    "gn:dem":258,
    "gn:feature_class":"P",
    "gn:feature_code":"PPL",
    "gn:name":"Saca de Agua",
    "gn:population":73,
    "gn:timezone":"America/Mazatlan",
    "iso:country":"MX",
    "name:spa_x_preferred":[
        "Saca de Agua"
    ],
    "wof:name":"Saca de Agua",
    "wof:placetype":"locality",
    "wof:population":73
},
  "geometry": {"coordinates":[-108.354,26.26875],"type":"Point"}
}