{
  "type": "Feature",
  "properties": {
    "gn:admin1_code":"26",
    "gn:admin2_code":"55",
    "gn:asciiname":"Roberto Conde Lara",
    "gn:country_code":"MX",
    "gn:dem":17,
    "gn:feature_class":"P",
    "gn:feature_code":"PPL",
    "gn:name":"Roberto Conde Lara",
    "gn:population":11,
    "gn:timezone":"America/Hermosillo",
    "iso:country":"MX",
    "wof:name":"Roberto Conde Lara",
    "wof:placetype":"locality",
    "wof:population":11
},
  "geometry": {"coordinates":[-114.91194,32.30639],"type":"Point"}
}