{
  "type": "Feature",
  "properties": {
    "gn:admin1_code":"19",
    "gn:admin2_code":"38.0",
    "gn:asciiname":"San Gerardo",
    "gn:country_code":"MX",
    "gn:dem":376,
    "gn:feature_class":"P",
    "gn:feature_code":"PPL",
    "gn:name":"San Gerardo",
    "gn:population":3,
    "gn:timezone":"America/Monterrey",
    "iso:country":"MX",
    "name:spa_x_preferred":[
        "San Gerardo"
    ],
    "wof:name":"San Gerardo",
    "wof:placetype":"locality",
    "wof:population":3
},
  "geometry": {"coordinates":[-99.7958,25.24877],"type":"Point"}
}