{
  "type": "Feature",
  "properties": {
    "gn:admin1_code":"21.0",
    "gn:admin2_code":"114.0",
    "gn:asciiname":"Tototzinac",
    "gn:country_code":"MX",
    "gn:dem":2740,
    "gn:feature_class":"P",
    "gn:feature_code":"PPL",
    "gn:name":"Tototzinac",
    "gn:population":0,
    "gn:timezone":"America/Mexico_City",
    "iso:country":"MX",
    "name:spa_x_preferred":[
        "Tototzinac"
    ],
    "wof:name":"Tototzinac",
    "wof:placetype":"locality"
},
  "geometry": {"coordinates":[-98.03857000000001,19.14396],"type":"Point"}
}