{
  "type": "Feature",
  "properties": {
    "gn:admin1_code":"5",
    "gn:admin2_code":"20",
    "gn:asciiname":"Berlin",
    "gn:country_code":"MX",
    "gn:dem":1097,
    "gn:feature_class":"P",
    "gn:feature_code":"PPL",
    "gn:name":"Berl\u00edn",
    "gn:population":9,
    "gn:timezone":"America/Mexico_City",
    "iso:country":"MX",
    "name:und_x_variant":[
        "Berl\u00edn"
    ],
    "wof:name":"Berlin",
    "wof:placetype":"locality",
    "wof:population":9
},
  "geometry": {"coordinates":[-92.97778,15.775],"type":"Point"}
}