{
  "type": "Feature",
  "properties": {
    "gn:admin1_code":"5",
    "gn:admin2_code":"31.0",
    "gn:asciiname":"Jolakil",
    "gn:country_code":"MX",
    "gn:dem":1144,
    "gn:feature_class":"P",
    "gn:feature_code":"PPL",
    "gn:name":"Jolakil",
    "gn:population":231,
    "gn:timezone":"America/Mexico_City",
    "iso:country":"MX",
    "wof:name":"Jolakil",
    "wof:placetype":"locality",
    "wof:population":231
},
  "geometry": {"coordinates":[-92.245,17.02389],"type":"Point"}
}