{
  "type": "Feature",
  "properties": {
    "gn:admin1_code":"32.0",
    "gn:admin2_code":"10.0",
    "gn:asciiname":"El Mezquite",
    "gn:country_code":"MX",
    "gn:dem":2093,
    "gn:feature_class":"P",
    "gn:feature_code":"PPL",
    "gn:name":"El Mezquite",
    "gn:population":0,
    "gn:timezone":"America/Mexico_City",
    "iso:country":"MX",
    "name:und_x_variant":[
        "Mezquite",
        "Hacienda Mezquite",
        "El Mezquite"
    ],
    "wof:name":"El Mezquite",
    "wof:placetype":"locality"
},
  "geometry": {"coordinates":[-102.6101,23.33016],"type":"Point"}
}