{
  "type": "Feature",
  "properties": {
    "gn:admin1_code":"30",
    "gn:admin2_code":"142.0",
    "gn:asciiname":"El Nachon (Los Pinos)",
    "gn:country_code":"MX",
    "gn:dem":68,
    "gn:feature_class":"P",
    "gn:feature_code":"PPL",
    "gn:name":"El Nach\u00f3n (Los Pinos)",
    "gn:population":9,
    "gn:timezone":"America/Mexico_City",
    "iso:country":"MX",
    "name:und_x_variant":[
        "El Nach\u00f3n (Los Pinos)"
    ],
    "wof:name":"El Nachon (Los Pinos)",
    "wof:placetype":"locality",
    "wof:population":9
},
  "geometry": {"coordinates":[-95.36417,17.69556],"type":"Point"}
}