{
  "type": "Feature",
  "properties": {
    "gn:admin1_code":"20",
    "gn:admin2_code":"459.0",
    "gn:asciiname":"El Higo",
    "gn:country_code":"MX",
    "gn:dem":1813,
    "gn:feature_class":"P",
    "gn:feature_code":"PPL",
    "gn:name":"El Higo",
    "gn:population":107,
    "gn:timezone":"America/Mexico_City",
    "iso:country":"MX",
    "wof:name":"El Higo",
    "wof:placetype":"locality",
    "wof:population":107
},
  "geometry": {"coordinates":[-97.71972,18.19861],"type":"Point"}
}