{
  "type": "Feature",
  "properties": {
    "gn:admin1_code":"28",
    "gn:admin2_code":"15.0",
    "gn:asciiname":"Las Once Palmas (Las Dos Palmas)",
    "gn:country_code":"MX",
    "gn:dem":46,
    "gn:feature_class":"P",
    "gn:feature_code":"PPL",
    "gn:name":"Las Once Palmas (Las Dos Palmas)",
    "gn:population":6,
    "gn:timezone":"America/Monterrey",
    "iso:country":"MX",
    "wof:name":"Las Once Palmas (Las Dos Palmas)",
    "wof:placetype":"locality",
    "wof:population":6
},
  "geometry": {"coordinates":[-98.66916999999999,26.22028],"type":"Point"}
}