{
  "type": "Feature",
  "properties": {
    "gn:admin1_code":"21",
    "gn:admin2_code":"75.0",
    "gn:asciiname":"Dos Rios",
    "gn:country_code":"MX",
    "gn:dem":1553,
    "gn:feature_class":"P",
    "gn:feature_code":"PPL",
    "gn:name":"Dos R\u00edos",
    "gn:population":56,
    "gn:timezone":"America/Mexico_City",
    "iso:country":"MX",
    "name:und_x_variant":[
        "Dos R\u00edos"
    ],
    "wof:name":"Dos Rios",
    "wof:placetype":"locality",
    "wof:population":56
},
  "geometry": {"coordinates":[-97.41566,19.90048],"type":"Point"}
}