{
  "type": "Feature",
  "properties": {
    "gn:admin1_code":"14.0",
    "gn:admin2_code":"35.0",
    "gn:asciiname":"El Tulillo",
    "gn:country_code":"MX",
    "gn:dem":2075,
    "gn:feature_class":"P",
    "gn:feature_code":"PPL",
    "gn:name":"El Tulillo",
    "gn:population":0,
    "gn:timezone":"America/Mexico_City",
    "iso:country":"MX",
    "name:spa_x_preferred":[
        "El Tulillo"
    ],
    "wof:name":"El Tulillo",
    "wof:placetype":"locality"
},
  "geometry": {"coordinates":[-102.19486000000001,21.6743],"type":"Point"}
}