{
  "type": "Feature",
  "properties": {
    "gn:admin1_code":"5",
    "gn:admin2_code":"59.0",
    "gn:asciiname":"Nuevo Paraiso",
    "gn:country_code":"MX",
    "gn:dem":824,
    "gn:feature_class":"P",
    "gn:feature_code":"PPL",
    "gn:name":"Nuevo Para\u00edso",
    "gn:population":90,
    "gn:timezone":"America/Mexico_City",
    "iso:country":"MX",
    "name:und_x_variant":[
        "Nuevo Para\u00edso"
    ],
    "wof:name":"Nuevo Paraiso",
    "wof:placetype":"locality",
    "wof:population":90
},
  "geometry": {"coordinates":[-91.92528,16.98139],"type":"Point"}
}