{
  "type": "Feature",
  "properties": {
    "gn:admin1_code":"30",
    "gn:admin2_code":"44",
    "gn:asciiname":"Los Olvera",
    "gn:country_code":"MX",
    "gn:dem":970,
    "gn:feature_class":"P",
    "gn:feature_code":"PPL",
    "gn:name":"Los Olvera",
    "gn:population":22,
    "gn:timezone":"America/Mexico_City",
    "iso:country":"MX",
    "wof:name":"Los Olvera",
    "wof:placetype":"locality",
    "wof:population":22
},
  "geometry": {"coordinates":[-96.94861,18.93389],"type":"Point"}
}