{
  "type": "Feature",
  "properties": {
    "gn:admin1_code":"26",
    "gn:admin2_code":"35.0",
    "gn:asciiname":"Los Janos",
    "gn:country_code":"MX",
    "gn:dem":882,
    "gn:feature_class":"P",
    "gn:feature_code":"PPL",
    "gn:name":"Los Janos",
    "gn:population":0,
    "gn:timezone":"America/Hermosillo",
    "iso:country":"MX",
    "name:und_x_variant":[
        "Rancho Los Janos",
        "Los Janos"
    ],
    "wof:name":"Los Janos",
    "wof:placetype":"locality"
},
  "geometry": {"coordinates":[-110.83562999999999,30.83897],"type":"Point"}
}