{
  "type": "Feature",
  "properties": {
    "gn:admin1_code":"25.0",
    "gn:admin2_code":"3.0",
    "gn:asciiname":"El Mimbrito",
    "gn:country_code":"MX",
    "gn:dem":448,
    "gn:feature_class":"P",
    "gn:feature_code":"PPL",
    "gn:name":"El Mimbrito",
    "gn:population":0,
    "gn:timezone":"America/Mazatlan",
    "iso:country":"MX",
    "name:spa_x_preferred":[
        "El Mimbrito"
    ],
    "wof:name":"El Mimbrito",
    "wof:placetype":"locality"
},
  "geometry": {"coordinates":[-107.41902,25.36299],"type":"Point"}
}