{
  "type": "Feature",
  "properties": {
    "gn:admin1_code":"22",
    "gn:admin2_code":"17.0",
    "gn:asciiname":"Pelado",
    "gn:cc2":"MX",
    "gn:country_code":"MX",
    "gn:dem":1967,
    "gn:feature_class":"P",
    "gn:feature_code":"PPL",
    "gn:name":"Pelado",
    "gn:population":0,
    "gn:timezone":"America/Mexico_City",
    "iso:country":"MX",
    "name:und_x_variant":[
        "El Pelado",
        "Pelado"
    ],
    "wof:name":"Pelado",
    "wof:placetype":"locality"
},
  "geometry": {"coordinates":[-99.88333,20.48333],"type":"Point"}
}