{
  "type": "Feature",
  "properties": {
    "gn:admin1_code":"10.0",
    "gn:asciiname":"Arenales",
    "gn:country_code":"MX",
    "gn:dem":2168,
    "gn:feature_class":"P",
    "gn:feature_code":"PPL",
    "gn:name":"Arenales",
    "gn:population":0,
    "gn:timezone":"America/Monterrey",
    "iso:country":"MX",
    "name:spa_x_preferred":[
        "Arenales"
    ],
    "wof:name":"Arenales",
    "wof:placetype":"locality"
},
  "geometry": {"coordinates":[-105.45285,24.02842],"type":"Point"}
}