{
  "type": "Feature",
  "properties": {
    "gn:admin1_code":"15",
    "gn:admin2_code":"117.0",
    "gn:asciiname":"Ixtlahuaca",
    "gn:country_code":"MX",
    "gn:dem":1909,
    "gn:feature_class":"P",
    "gn:feature_code":"PPL",
    "gn:name":"Ixtlahuaca",
    "gn:population":74,
    "gn:timezone":"America/Mexico_City",
    "iso:country":"MX",
    "wof:name":"Ixtlahuaca",
    "wof:placetype":"locality",
    "wof:population":74
},
  "geometry": {"coordinates":[-99.79893,18.65018],"type":"Point"}
}