{
  "type": "Feature",
  "properties": {
    "gn:admin1_code":"6",
    "gn:admin2_code":"29",
    "gn:asciiname":"Mesa de los Pochis",
    "gn:country_code":"MX",
    "gn:dem":2328,
    "gn:feature_class":"P",
    "gn:feature_code":"PPL",
    "gn:name":"Mesa de los Pochis",
    "gn:population":15,
    "gn:timezone":"America/Chihuahua",
    "iso:country":"MX",
    "wof:name":"Mesa de los Pochis",
    "wof:placetype":"locality",
    "wof:population":15
},
  "geometry": {"coordinates":[-106.82317999999999,25.86663],"type":"Point"}
}