{
  "type": "Feature",
  "properties": {
    "gn:admin1_code":"28.0",
    "gn:admin2_code":"21.0",
    "gn:asciiname":"El Esfuerzo",
    "gn:country_code":"MX",
    "gn:dem":79,
    "gn:feature_class":"P",
    "gn:feature_code":"PPL",
    "gn:name":"El Esfuerzo",
    "gn:population":0,
    "gn:timezone":"America/Monterrey",
    "iso:country":"MX",
    "name:spa_x_preferred":[
        "El Esfuerzo"
    ],
    "wof:name":"El Esfuerzo",
    "wof:placetype":"locality"
},
  "geometry": {"coordinates":[-98.88111000000001,22.61472],"type":"Point"}
}