{
  "type": "Feature",
  "properties": {
    "gn:admin1_code":"19.0",
    "gn:asciiname":"Las Bugambilias",
    "gn:country_code":"MX",
    "gn:dem":510,
    "gn:feature_class":"P",
    "gn:feature_code":"PPL",
    "gn:name":"Las Bugambilias",
    "gn:population":0,
    "gn:timezone":"America/Monterrey",
    "iso:country":"MX",
    "name:spa_x_preferred":[
        "Las Bugambilias"
    ],
    "wof:name":"Las Bugambilias",
    "wof:placetype":"locality"
},
  "geometry": {"coordinates":[-100.40733,25.94968],"type":"Point"}
}