{
  "type": "Feature",
  "properties": {
    "gn:admin1_code":"29",
    "gn:admin2_code":"34.0",
    "gn:asciiname":"Conzoquio",
    "gn:country_code":"MX",
    "gn:dem":2837,
    "gn:feature_class":"P",
    "gn:feature_code":"PPL",
    "gn:name":"Conzoquio",
    "gn:population":9,
    "gn:timezone":"America/Mexico_City",
    "iso:country":"MX",
    "wof:name":"Conzoquio",
    "wof:placetype":"locality",
    "wof:population":9
},
  "geometry": {"coordinates":[-98.05394,19.61799],"type":"Point"}
}