{
  "type": "Feature",
  "properties": {
    "gn:admin1_code":"25",
    "gn:admin2_code":"18.0",
    "gn:asciiname":"Hacienda la Aurora",
    "gn:country_code":"MX",
    "gn:dem":9,
    "gn:feature_class":"P",
    "gn:feature_code":"PPL",
    "gn:name":"Hacienda la Aurora",
    "gn:population":7,
    "gn:timezone":"America/Mazatlan",
    "iso:country":"MX",
    "wof:name":"Hacienda la Aurora",
    "wof:placetype":"locality",
    "wof:population":7
},
  "geometry": {"coordinates":[-107.72263999999998,24.83297],"type":"Point"}
}