{
  "type": "Feature",
  "properties": {
    "gn:admin1_code":"30",
    "gn:admin2_code":"63.0",
    "gn:asciiname":"Villa Hermosa (El Crucero)",
    "gn:country_code":"MX",
    "gn:dem":68,
    "gn:feature_class":"P",
    "gn:feature_code":"PPL",
    "gn:name":"Villa Hermosa (El Crucero)",
    "gn:population":6,
    "gn:timezone":"America/Mexico_City",
    "iso:country":"MX",
    "wof:name":"Villa Hermosa (El Crucero)",
    "wof:placetype":"locality",
    "wof:population":6
},
  "geometry": {"coordinates":[-97.98938,21.50705],"type":"Point"}
}