{
  "type": "Feature",
  "properties": {
    "gn:admin1_code":"30",
    "gn:admin2_code":"108",
    "gn:asciiname":"Diaz Ordaz (Las Palmas)",
    "gn:country_code":"MX",
    "gn:dem":19,
    "gn:feature_class":"P",
    "gn:feature_code":"PPL",
    "gn:name":"D\u00edaz Ordaz (Las Palmas)",
    "gn:population":47,
    "gn:timezone":"America/Mexico_City",
    "iso:country":"MX",
    "name:und_x_variant":[
        "D\u00edaz Ordaz (Las Palmas)"
    ],
    "wof:name":"Diaz Ordaz (Las Palmas)",
    "wof:placetype":"locality",
    "wof:population":47
},
  "geometry": {"coordinates":[-94.16388999999999,17.64056],"type":"Point"}
}