{
  "type": "Feature",
  "properties": {
    "gn:admin1_code":"5",
    "gn:admin2_code":"31.0",
    "gn:asciiname":"San Jeronimo Tulija",
    "gn:country_code":"MX",
    "gn:dem":348,
    "gn:feature_class":"P",
    "gn:feature_code":"PPL",
    "gn:name":"San Jer\u00f3nimo Tulij\u00e1",
    "gn:population":0,
    "gn:timezone":"America/Mexico_City",
    "iso:country":"MX",
    "wof:name":"San Jeronimo Tulija",
    "wof:placetype":"locality"
},
  "geometry": {"coordinates":[-91.78972,17.22361],"type":"Point"}
}