{
  "type": "Feature",
  "properties": {
    "gn:admin1_code":"11",
    "gn:admin2_code":"45.0",
    "gn:asciiname":"Pinalito de la Gloria",
    "gn:country_code":"MX",
    "gn:dem":2036,
    "gn:feature_class":"P",
    "gn:feature_code":"PPL",
    "gn:name":"Pinalito de la Gloria",
    "gn:population":130,
    "gn:timezone":"America/Mexico_City",
    "iso:country":"MX",
    "wof:name":"Pinalito de la Gloria",
    "wof:placetype":"locality",
    "wof:population":130
},
  "geometry": {"coordinates":[-99.90206000000001,21.1892],"type":"Point"}
}