{
  "type": "Feature",
  "properties": {
    "gn:admin1_code":"12",
    "gn:admin2_code":"34.0",
    "gn:asciiname":"Escuchapa",
    "gn:country_code":"MX",
    "gn:dem":1136,
    "gn:feature_class":"P",
    "gn:feature_code":"PPL",
    "gn:name":"Escuchapa",
    "gn:population":0,
    "gn:timezone":"America/Mexico_City",
    "iso:country":"MX",
    "name:spa_x_preferred":[
        "Escuchapa"
    ],
    "wof:name":"Escuchapa",
    "wof:placetype":"locality"
},
  "geometry": {"coordinates":[-99.244,18.30716],"type":"Point"}
}