{
  "type": "Feature",
  "properties": {
    "gn:admin1_code":"4",
    "gn:admin2_code":"4",
    "gn:asciiname":"Pablo Garcia",
    "gn:country_code":"MX",
    "gn:dem":1,
    "gn:feature_class":"P",
    "gn:feature_code":"PPL",
    "gn:name":"Pablo Garc\u00eda",
    "gn:population":32,
    "gn:timezone":"America/Merida",
    "iso:country":"MX",
    "name:und_x_variant":[
        "Pablo Garc\u00eda"
    ],
    "wof:name":"Pablo Garcia",
    "wof:placetype":"locality",
    "wof:population":32
},
  "geometry": {"coordinates":[-90.90694000000001,19.09472],"type":"Point"}
}