{
  "type": "Feature",
  "properties": {
    "gn:admin1_code":"10",
    "gn:admin2_code":"35.0",
    "gn:asciiname":"Talisman",
    "gn:country_code":"MX",
    "gn:dem":2529,
    "gn:feature_class":"P",
    "gn:feature_code":"PPL",
    "gn:name":"Talism\u00e1n",
    "gn:population":0,
    "gn:timezone":"America/Monterrey",
    "iso:country":"MX",
    "name:und_x_variant":[
        "Tamasitl\u00e1n",
        "Talism\u00e1n"
    ],
    "wof:name":"Talisman",
    "wof:placetype":"locality"
},
  "geometry": {"coordinates":[-106.22507,25.46108],"type":"Point"}
}