{
  "type": "Feature",
  "properties": {
    "gn:admin1_code":"6",
    "gn:admin2_code":"7.0",
    "gn:asciiname":"El Cordon",
    "gn:country_code":"MX",
    "gn:dem":2340,
    "gn:feature_class":"P",
    "gn:feature_code":"PPL",
    "gn:name":"El Cord\u00f3n",
    "gn:population":0,
    "gn:timezone":"America/Chihuahua",
    "iso:country":"MX",
    "name:spa_x_preferred":[
        "El Cord\u00f3n"
    ],
    "wof:name":"El Cordon",
    "wof:placetype":"locality"
},
  "geometry": {"coordinates":[-106.8253,26.73339],"type":"Point"}
}