{
  "type": "Feature",
  "properties": {
    "gn:admin1_code":"10",
    "gn:admin2_code":"12.0",
    "gn:asciiname":"Las Glorietas",
    "gn:country_code":"MX",
    "gn:dem":1399,
    "gn:feature_class":"P",
    "gn:feature_code":"PPL",
    "gn:name":"Las Glorietas",
    "gn:population":0,
    "gn:timezone":"America/Monterrey",
    "iso:country":"MX",
    "name:spa_x_preferred":[
        "Las Glorietas"
    ],
    "wof:name":"Las Glorietas",
    "wof:placetype":"locality"
},
  "geometry": {"coordinates":[-103.68371999999999,25.63373],"type":"Point"}
}