{
  "type": "Feature",
  "properties": {
    "gn:admin1_code":"25",
    "gn:admin2_code":"1.0",
    "gn:asciiname":"El Vacilon",
    "gn:country_code":"MX",
    "gn:dem":13,
    "gn:feature_class":"P",
    "gn:feature_code":"PPL",
    "gn:name":"El Vacil\u00f3n",
    "gn:population":0,
    "gn:timezone":"America/Mazatlan",
    "iso:country":"MX",
    "name:spa_x_preferred":[
        "El Vacil\u00f3n"
    ],
    "name:und_x_variant":[
        "Rancho El Vacil\u00f3n"
    ],
    "wof:name":"El Vacilon",
    "wof:placetype":"locality"
},
  "geometry": {"coordinates":[-109.00960000000001,26.1628],"type":"Point"}
}