{
  "type": "Feature",
  "properties": {
    "gn:admin1_code":"5",
    "gn:admin2_code":"115.0",
    "gn:asciiname":"Plan de Rio Azul",
    "gn:country_code":"MX",
    "gn:dem":198,
    "gn:feature_class":"P",
    "gn:feature_code":"PPL",
    "gn:name":"Plan de R\u00edo Azul",
    "gn:population":0,
    "gn:timezone":"America/Mexico_City",
    "iso:country":"MX",
    "name:spa_x_preferred":[
        "Plan de R\u00edo Azul"
    ],
    "wof:name":"Plan de Rio Azul",
    "wof:placetype":"locality"
},
  "geometry": {"coordinates":[-91.29795,16.27447],"type":"Point"}
}