{
  "type": "Feature",
  "properties": {
    "gn:admin1_code":"14",
    "gn:admin2_code":"78.0",
    "gn:asciiname":"Las Biznagas",
    "gn:country_code":"MX",
    "gn:dem":2096,
    "gn:feature_class":"P",
    "gn:feature_code":"PPL",
    "gn:name":"Las Biznagas",
    "gn:population":8,
    "gn:timezone":"America/Mexico_City",
    "iso:country":"MX",
    "wof:name":"Las Biznagas",
    "wof:placetype":"locality",
    "wof:population":8
},
  "geometry": {"coordinates":[-102.36472000000001,20.96194],"type":"Point"}
}