{
  "type": "Feature",
  "properties": {
    "gn:admin1_code":"16.0",
    "gn:admin2_code":"102.0",
    "gn:asciiname":"La Joya del Coyote",
    "gn:country_code":"MX",
    "gn:dem":1577,
    "gn:feature_class":"P",
    "gn:feature_code":"PPL",
    "gn:name":"La Joya del Coyote",
    "gn:population":0,
    "gn:timezone":"America/Mexico_City",
    "iso:country":"MX",
    "name:spa_x_preferred":[
        "La Joya del Coyote"
    ],
    "wof:name":"La Joya del Coyote",
    "wof:placetype":"locality"
},
  "geometry": {"coordinates":[-102.02938,19.31611],"type":"Point"}
}