{
  "type": "Feature",
  "properties": {
    "gn:admin1_code":"14",
    "gn:admin2_code":"61.0",
    "gn:asciiname":"San Andres Cohamiata",
    "gn:country_code":"MX",
    "gn:dem":1952,
    "gn:feature_class":"P",
    "gn:feature_code":"PPL",
    "gn:name":"San Andr\u00e9s Cohamiata",
    "gn:population":0,
    "gn:timezone":"America/Mexico_City",
    "iso:country":"MX",
    "name:ceb_x_preferred":[
        "San Andr\u00e9s Cohamiata"
    ],
    "name:spa_x_preferred":[
        "San Andr\u00e9s Cohamiata"
    ],
    "name:srp_x_preferred":[
        "\u0421\u0430\u043d \u0410\u043d\u0434\u0440\u0435\u0441 \u041a\u043e\u0430\u043c\u0438\u0458\u0430\u0442\u0430"
    ],
    "name:swe_x_preferred":[
        "San Andr\u00e9s Cohamiata"
    ],
    "name:und_x_variant":[
        "San Andr\u00e9s"
    ],
    "wof:name":"San Andres Cohamiata",
    "wof:placetype":"locality"
},
  "geometry": {"coordinates":[-104.24124999999999,22.18902000000001],"type":"Point"}
}