{
  "type": "Feature",
  "properties": {
    "gn:admin1_code":"6.0",
    "gn:admin2_code":"11.0",
    "gn:asciiname":"Jordaneno",
    "gn:country_code":"MX",
    "gn:dem":1252,
    "gn:feature_class":"P",
    "gn:feature_code":"PPL",
    "gn:name":"Jordane\u00f1o",
    "gn:population":0,
    "gn:timezone":"America/Chihuahua",
    "iso:country":"MX",
    "name:und_x_variant":[
        "Rancho Jordane\u00f1o",
        "El Sordane\u00f1o",
        "Jordane\u00f1o"
    ],
    "wof:name":"Jordaneno",
    "wof:placetype":"locality"
},
  "geometry": {"coordinates":[-105.04898,27.6091],"type":"Point"}
}