{
  "type": "Feature",
  "properties": {
    "gn:admin1_code":"30",
    "gn:admin2_code":"181.0",
    "gn:asciiname":"Tenacalco",
    "gn:country_code":"MX",
    "gn:dem":61,
    "gn:feature_class":"P",
    "gn:feature_code":"PPL",
    "gn:name":"Tenacalco",
    "gn:population":349,
    "gn:timezone":"America/Mexico_City",
    "iso:country":"MX",
    "wof:name":"Tenacalco",
    "wof:placetype":"locality",
    "wof:population":349
},
  "geometry": {"coordinates":[-96.32556,18.73389],"type":"Point"}
}