{
  "type": "Feature",
  "properties": {
    "gn:admin1_code":"30",
    "gn:admin2_code":"94.0",
    "gn:asciiname":"La Bomba",
    "gn:country_code":"MX",
    "gn:dem":126,
    "gn:feature_class":"P",
    "gn:feature_code":"PPL",
    "gn:name":"La Bomba",
    "gn:population":7,
    "gn:timezone":"America/Mexico_City",
    "iso:country":"MX",
    "name:ceb_x_preferred":[
        "La Bomba"
    ],
    "name:ita_x_preferred":[
        "La bomba"
    ],
    "name:spa_x_preferred":[
        "La bomba"
    ],
    "name:srp_x_preferred":[
        "\u041b\u0430 \u0411\u043e\u043c\u0431\u0430"
    ],
    "name:swe_x_preferred":[
        "La Bomba"
    ],
    "wof:name":"La Bomba",
    "wof:placetype":"locality",
    "wof:population":7
},
  "geometry": {"coordinates":[-95.40306,17.98111],"type":"Point"}
}