{
  "type": "Feature",
  "properties": {
    "gn:admin1_code":"25",
    "gn:admin2_code":"6",
    "gn:asciiname":"El Bambalete (Bagrecitos)",
    "gn:country_code":"MX",
    "gn:dem":292,
    "gn:feature_class":"P",
    "gn:feature_code":"PPL",
    "gn:name":"El Bambalete (Bagrecitos)",
    "gn:population":33,
    "gn:timezone":"America/Mazatlan",
    "iso:country":"MX",
    "wof:name":"El Bambalete (Bagrecitos)",
    "wof:placetype":"locality",
    "wof:population":33
},
  "geometry": {"coordinates":[-107.21986,25.08188],"type":"Point"}
}