{
  "type": "Feature",
  "properties": {
    "gn:admin1_code":"10.0",
    "gn:admin2_code":"11.0",
    "gn:asciiname":"Ignacio Allende",
    "gn:country_code":"MX",
    "gn:dem":1533,
    "gn:feature_class":"P",
    "gn:feature_code":"PPL",
    "gn:name":"Ignacio Allende",
    "gn:population":0,
    "gn:timezone":"America/Monterrey",
    "iso:country":"MX",
    "name:ara_x_preferred":[
        "\u0625\u063a\u0646\u0627\u062b\u064a\u0648 \u0623\u0644\u064a\u0646\u062f"
    ],
    "name:aym_x_preferred":[
        "Ignacio Allende"
    ],
    "name:cat_x_preferred":[
        "Ignacio Allende"
    ],
    "name:deu_x_preferred":[
        "Ignacio Allende"
    ],
    "name:eus_x_preferred":[
        "Ignacio Allende"
    ],
    "name:fra_x_preferred":[
        "Ignacio Allende"
    ],
    "name:glg_x_preferred":[
        "Ignacio Allende"
    ],
    "name:hun_x_preferred":[
        "Ignacio Allende"
    ],
    "name:ita_x_preferred":[
        "Ignacio Allende"
    ],
    "name:jpn_x_preferred":[
        "\u30a4\u30b0\u30ca\u30b7\u30aa\u30fb\u30a2\u30b8\u30a7\u30f3\u30c7"
    ],
    "name:nah_x_preferred":[
        "Ignacio Allende"
    ],
    "name:nor_x_preferred":[
        "Ignacio Allende"
    ],
    "name:que_x_preferred":[
        "Ignacio Allende"
    ],
    "name:rus_x_preferred":[
        "\u0410\u043b\u044c\u0435\u043d\u0434\u0435"
    ],
    "name:spa_x_preferred":[
        "Ignacio Allende"
    ],
    "name:swe_x_preferred":[
        "Ignacio Allende"
    ],
    "name:tur_x_preferred":[
        "Ignacio Allende"
    ],
    "wof:name":"Ignacio Allende",
    "wof:placetype":"locality"
},
  "geometry": {"coordinates":[-105.1037,25.7386],"type":"Point"}
}