{
  "type": "Feature",
  "properties": {
    "gn:admin1_code":"10.0",
    "gn:admin2_code":"11.0",
    "gn:asciiname":"Ignacio Allende",
    "gn:country_code":"MX",
    "gn:dem":1533,
    "gn:feature_class":"P",
    "gn:feature_code":"PPL",
    "gn:name":"Ignacio Allende",
    "gn:population":0,
    "gn:timezone":"America/Monterrey",
    "iso:country":"MX",
    "name:spa_x_preferred":[
        "Ignacio Allende"
    ],
    "wof:name":"Ignacio Allende",
    "wof:placetype":"locality"
},
  "geometry": {"coordinates":[-105.1037,25.7386],"type":"Point"}
}