{
  "type": "Feature",
  "properties": {
    "gn:admin1_code":"4",
    "gn:admin2_code":"11",
    "gn:asciiname":"Pimental",
    "gn:country_code":"MX",
    "gn:dem":105,
    "gn:feature_class":"P",
    "gn:feature_code":"PPL",
    "gn:name":"Pimental",
    "gn:population":9,
    "gn:timezone":"America/Merida",
    "iso:country":"MX",
    "wof:name":"Pimental",
    "wof:placetype":"locality",
    "wof:population":9
},
  "geometry": {"coordinates":[-90.44638999999999,18.49056],"type":"Point"}
}