{
  "type": "Feature",
  "properties": {
    "gn:admin1_code":"14",
    "gn:admin2_code":"78",
    "gn:asciiname":"Salto Prieto",
    "gn:country_code":"MX",
    "gn:dem":2201,
    "gn:feature_class":"P",
    "gn:feature_code":"PPL",
    "gn:name":"Salto Prieto",
    "gn:population":12,
    "gn:timezone":"America/Mexico_City",
    "iso:country":"MX",
    "wof:name":"Salto Prieto",
    "wof:placetype":"locality",
    "wof:population":12
},
  "geometry": {"coordinates":[-102.28,20.94778],"type":"Point"}
}