{
  "type": "Feature",
  "properties": {
    "gn:admin1_code":"26.0",
    "gn:admin2_code":"35.0",
    "gn:asciiname":"La Castrena",
    "gn:country_code":"MX",
    "gn:dem":804,
    "gn:feature_class":"P",
    "gn:feature_code":"PPL",
    "gn:name":"La Castre\u00f1a",
    "gn:population":0,
    "gn:timezone":"America/Hermosillo",
    "iso:country":"MX",
    "name:spa_x_preferred":[
        "La Castre\u00f1a"
    ],
    "wof:name":"La Castrena",
    "wof:placetype":"locality"
},
  "geometry": {"coordinates":[-110.90002,30.74235],"type":"Point"}
}