{
  "type": "Feature",
  "properties": {
    "gn:admin1_code":"26",
    "gn:admin2_code":"63.0",
    "gn:asciiname":"Monton de Lena",
    "gn:country_code":"MX",
    "gn:dem":592,
    "gn:feature_class":"P",
    "gn:feature_code":"PPL",
    "gn:name":"Mont\u00f3n de Le\u00f1a",
    "gn:population":0,
    "gn:timezone":"America/Hermosillo",
    "iso:country":"MX",
    "name:spa_x_preferred":[
        "Mont\u00f3n de Le\u00f1a"
    ],
    "name:und_x_variant":[
        "Rancho Mont\u00f3n de Le\u00f1a"
    ],
    "wof:name":"Monton de Lena",
    "wof:placetype":"locality"
},
  "geometry": {"coordinates":[-109.5889,29.38764],"type":"Point"}
}