{
  "type": "Feature",
  "properties": {
    "gn:admin1_code":"5",
    "gn:admin2_code":"37.0",
    "gn:asciiname":"El Naranjo",
    "gn:cc2":"MX",
    "gn:country_code":"MX",
    "gn:dem":13,
    "gn:feature_class":"P",
    "gn:feature_code":"PPL",
    "gn:name":"El Naranjo",
    "gn:population":7,
    "gn:timezone":"America/Mexico_City",
    "iso:country":"MX",
    "name:und_x_variant":[
        "Para\u00edso",
        "El Para\u00edso"
    ],
    "wof:name":"El Naranjo",
    "wof:placetype":"locality",
    "wof:population":7
},
  "geometry": {"coordinates":[-92.47056000000001,15.03778],"type":"Point"}
}