{
  "type": "Feature",
  "properties": {
    "gn:admin1_code":"26.0",
    "gn:admin2_code":"30.0",
    "gn:asciiname":"Plutarco Elias Calles",
    "gn:country_code":"MX",
    "gn:dem":60,
    "gn:feature_class":"P",
    "gn:feature_code":"PPL",
    "gn:name":"Plutarco Elias Calles",
    "gn:population":0,
    "gn:timezone":"America/Hermosillo",
    "iso:country":"MX",
    "name:spa_x_preferred":[
        "Plutarco Elias Calles"
    ],
    "wof:name":"Plutarco Elias Calles",
    "wof:placetype":"locality"
},
  "geometry": {"coordinates":[-111.35711999999999,28.69194],"type":"Point"}
}