{
  "type": "Feature",
  "properties": {
    "gn:admin1_code":"13",
    "gn:admin2_code":"55.0",
    "gn:asciiname":"Ocotza",
    "gn:country_code":"MX",
    "gn:dem":1887,
    "gn:feature_class":"P",
    "gn:feature_code":"PPL",
    "gn:name":"Ocotza",
    "gn:population":0,
    "gn:timezone":"America/Mexico_City",
    "iso:country":"MX",
    "name:spa_x_preferred":[
        "Ocotza"
    ],
    "wof:name":"Ocotza",
    "wof:placetype":"locality"
},
  "geometry": {"coordinates":[-99.09166999999999,20.42639],"type":"Point"}
}