{
  "type": "Feature",
  "properties": {
    "gn:admin1_code":"13",
    "gn:admin2_code":"46",
    "gn:asciiname":"Ejido la Coneja",
    "gn:country_code":"MX",
    "gn:dem":77,
    "gn:feature_class":"P",
    "gn:feature_code":"PPL",
    "gn:name":"Ejido la Coneja",
    "gn:population":35,
    "gn:timezone":"America/Mexico_City",
    "iso:country":"MX",
    "wof:name":"Ejido la Coneja",
    "wof:placetype":"locality",
    "wof:population":35
},
  "geometry": {"coordinates":[-98.55099,21.31926],"type":"Point"}
}