{
  "type": "Feature",
  "properties": {
    "gn:admin1_code":"8.0",
    "gn:asciiname":"Cerro Prieto",
    "gn:country_code":"MX",
    "gn:dem":1395,
    "gn:feature_class":"P",
    "gn:feature_code":"PPL",
    "gn:name":"Cerro Prieto",
    "gn:population":0,
    "gn:timezone":"America/Mexico_City",
    "iso:country":"MX",
    "name:spa_x_preferred":[
        "Cerro Prieto"
    ],
    "wof:name":"Cerro Prieto",
    "wof:placetype":"locality"
},
  "geometry": {"coordinates":[-104.10442,19.42415],"type":"Point"}
}