{
  "type": "Feature",
  "properties": {
    "gn:admin1_code":"14",
    "gn:admin2_code":"118.0",
    "gn:asciiname":"Las Alazanas",
    "gn:country_code":"MX",
    "gn:dem":2107,
    "gn:feature_class":"P",
    "gn:feature_code":"PPL",
    "gn:name":"Las Alazanas",
    "gn:population":5,
    "gn:timezone":"America/Mexico_City",
    "iso:country":"MX",
    "wof:name":"Las Alazanas",
    "wof:placetype":"locality",
    "wof:population":5
},
  "geometry": {"coordinates":[-102.98694,21.21556],"type":"Point"}
}