{
  "type": "Feature",
  "properties": {
    "gn:admin1_code":"13",
    "gn:admin2_code":"27",
    "gn:asciiname":"La Esmeralda",
    "gn:country_code":"MX",
    "gn:dem":715,
    "gn:feature_class":"P",
    "gn:feature_code":"PPL",
    "gn:name":"La Esmeralda",
    "gn:population":23,
    "gn:timezone":"America/Mexico_City",
    "iso:country":"MX",
    "wof:name":"La Esmeralda",
    "wof:placetype":"locality",
    "wof:population":23
},
  "geometry": {"coordinates":[-98.15083,20.41306],"type":"Point"}
}