{
  "type": "Feature",
  "properties": {
    "gn:admin1_code":"5",
    "gn:admin2_code":"64.0",
    "gn:asciiname":"El Retiro",
    "gn:country_code":"MX",
    "gn:dem":2207,
    "gn:feature_class":"P",
    "gn:feature_code":"PPL",
    "gn:name":"El Retiro",
    "gn:population":619,
    "gn:timezone":"America/Mexico_City",
    "iso:country":"MX",
    "name:ceb_x_preferred":[
        "El Retiro"
    ],
    "name:glg_x_preferred":[
        "O Retiro"
    ],
    "name:srp_x_preferred":[
        "\u0415\u043b \u0420\u0435\u0442\u0438\u0440\u043e"
    ],
    "name:swe_x_preferred":[
        "El Retiro"
    ],
    "wof:name":"El Retiro",
    "wof:placetype":"locality",
    "wof:population":619
},
  "geometry": {"coordinates":[-92.36221999999999,16.79639],"type":"Point"}
}