{
  "type": "Feature",
  "properties": {
    "gn:admin1_code":"19.0",
    "gn:admin2_code":"15.0",
    "gn:asciiname":"El Alto Mezquite",
    "gn:country_code":"MX",
    "gn:dem":113,
    "gn:feature_class":"P",
    "gn:feature_code":"PPL",
    "gn:name":"El Alto Mezquite",
    "gn:population":0,
    "gn:timezone":"America/Monterrey",
    "iso:country":"MX",
    "name:spa_x_preferred":[
        "El Alto Mezquite"
    ],
    "wof:name":"El Alto Mezquite",
    "wof:placetype":"locality"
},
  "geometry": {"coordinates":[-99.10514000000001,25.94091],"type":"Point"}
}