{
  "type": "Feature",
  "properties": {
    "gn:admin1_code":"11",
    "gn:admin2_code":"19.0",
    "gn:asciiname":"Los Cerritos de San Juan",
    "gn:country_code":"MX",
    "gn:dem":2251,
    "gn:feature_class":"P",
    "gn:feature_code":"PPL",
    "gn:name":"Los Cerritos de San Juan",
    "gn:population":110,
    "gn:timezone":"America/Mexico_City",
    "iso:country":"MX",
    "wof:name":"Los Cerritos de San Juan",
    "wof:placetype":"locality",
    "wof:population":110
},
  "geometry": {"coordinates":[-100.47389,20.26917000000001],"type":"Point"}
}