{
  "type": "Feature",
  "properties": {
    "gn:admin1_code":"12",
    "gn:admin2_code":"57",
    "gn:asciiname":"Palo de Arco",
    "gn:country_code":"MX",
    "gn:dem":52,
    "gn:feature_class":"P",
    "gn:feature_code":"PPL",
    "gn:name":"Palo de Arco",
    "gn:population":10,
    "gn:timezone":"America/Mexico_City",
    "iso:country":"MX",
    "wof:name":"Palo de Arco",
    "wof:placetype":"locality",
    "wof:population":10
},
  "geometry": {"coordinates":[-100.82559999999999,17.26179],"type":"Point"}
}