{
  "type": "Feature",
  "properties": {
    "gn:admin1_code":"5.0",
    "gn:asciiname":"El Encanto",
    "gn:country_code":"MX",
    "gn:dem":595,
    "gn:feature_class":"P",
    "gn:feature_code":"PPL",
    "gn:name":"El Encanto",
    "gn:population":0,
    "gn:timezone":"America/Mexico_City",
    "iso:country":"MX",
    "name:spa_x_preferred":[
        "El Encanto"
    ],
    "wof:name":"El Encanto",
    "wof:placetype":"locality"
},
  "geometry": {"coordinates":[-91.99695,15.82001],"type":"Point"}
}