{
  "type": "Feature",
  "properties": {
    "gn:admin1_code":"2.0",
    "gn:admin2_code":"2.0",
    "gn:asciiname":"Duarte",
    "gn:country_code":"MX",
    "gn:dem":4,
    "gn:feature_class":"P",
    "gn:feature_code":"PPL",
    "gn:name":"Duarte",
    "gn:population":0,
    "gn:timezone":"America/Tijuana",
    "iso:country":"MX",
    "name:spa_x_preferred":[
        "Duarte"
    ],
    "wof:name":"Duarte",
    "wof:placetype":"locality"
},
  "geometry": {"coordinates":[-115.02973,32.03099],"type":"Point"}
}