{
  "type": "Feature",
  "properties": {
    "gn:admin1_code":"19",
    "gn:admin2_code":"9.0",
    "gn:asciiname":"San Miguelito",
    "gn:country_code":"MX",
    "gn:dem":283,
    "gn:feature_class":"P",
    "gn:feature_code":"PPL",
    "gn:name":"San Miguelito",
    "gn:population":38,
    "gn:timezone":"America/Monterrey",
    "iso:country":"MX",
    "wof:name":"San Miguelito",
    "wof:placetype":"locality",
    "wof:population":38
},
  "geometry": {"coordinates":[-99.89643,25.53317],"type":"Point"}
}