{
  "type": "Feature",
  "properties": {
    "gn:admin1_code":"28",
    "gn:admin2_code":"25.0",
    "gn:asciiname":"Puerto Oriente",
    "gn:country_code":"MX",
    "gn:dem":96,
    "gn:feature_class":"P",
    "gn:feature_code":"PPL",
    "gn:name":"Puerto Oriente",
    "gn:population":0,
    "gn:timezone":"America/Monterrey",
    "iso:country":"MX",
    "wof:name":"Puerto Oriente",
    "wof:placetype":"locality"
},
  "geometry": {"coordinates":[-98.94564,26.30477],"type":"Point"}
}