{
  "type": "Feature",
  "properties": {
    "gn:admin1_code":"6.0",
    "gn:asciiname":"Corderena",
    "gn:country_code":"MX",
    "gn:dem":1596,
    "gn:feature_class":"P",
    "gn:feature_code":"PPL",
    "gn:name":"Cordere\u00f1a",
    "gn:population":0,
    "gn:timezone":"America/Chihuahua",
    "iso:country":"MX",
    "name:spa_x_preferred":[
        "Cordere\u00f1a"
    ],
    "wof:name":"Corderena",
    "wof:placetype":"locality"
},
  "geometry": {"coordinates":[-105.39417,26.93958],"type":"Point"}
}