{
  "type": "Feature",
  "properties": {
    "gn:admin1_code":"19",
    "gn:admin2_code":"38",
    "gn:asciiname":"Hacienda Paso Lozano (La Reforma)",
    "gn:country_code":"MX",
    "gn:dem":454,
    "gn:feature_class":"P",
    "gn:feature_code":"PPL",
    "gn:name":"Hacienda Paso Lozano (La Reforma)",
    "gn:population":21,
    "gn:timezone":"America/Monterrey",
    "iso:country":"MX",
    "wof:name":"Hacienda Paso Lozano (La Reforma)",
    "wof:placetype":"locality",
    "wof:population":21
},
  "geometry": {"coordinates":[-100.01612,25.25534],"type":"Point"}
}