{
  "type": "Feature",
  "properties": {
    "gn:admin1_code":"11.0",
    "gn:admin2_code":"1.0",
    "gn:asciiname":"La Chinche",
    "gn:country_code":"MX",
    "gn:dem":1700,
    "gn:feature_class":"P",
    "gn:feature_code":"PPL",
    "gn:name":"La Chinche",
    "gn:population":0,
    "gn:timezone":"America/Mexico_City",
    "iso:country":"MX",
    "name:spa_x_preferred":[
        "La Chinche"
    ],
    "wof:name":"La Chinche",
    "wof:placetype":"locality"
},
  "geometry": {"coordinates":[-101.54725000000001,20.47637000000001],"type":"Point"}
}