{
  "type": "Feature",
  "properties": {
    "gn:admin1_code":"7.0",
    "gn:asciiname":"Loma Prieta",
    "gn:country_code":"MX",
    "gn:dem":1120,
    "gn:feature_class":"P",
    "gn:feature_code":"PPL",
    "gn:name":"Loma Prieta",
    "gn:population":0,
    "gn:timezone":"America/Chihuahua",
    "iso:country":"MX",
    "name:ceb_x_preferred":[
        "Loma Prieta"
    ],
    "name:deu_x_preferred":[
        "Loma Prieta"
    ],
    "name:fra_x_preferred":[
        "Pic Loma Prieta"
    ],
    "name:pol_x_preferred":[
        "Loma Prieta"
    ],
    "name:spa_x_preferred":[
        "Loma Prieta"
    ],
    "name:ukr_x_preferred":[
        "\u041b\u043e\u043c\u0430 \u041f\u0440\u0456\u0454\u0442\u0430"
    ],
    "wof:name":"Loma Prieta",
    "wof:placetype":"locality"
},
  "geometry": {"coordinates":[-103.80918,26.79014],"type":"Point"}
}