{
  "type": "Feature",
  "properties": {
    "gn:admin1_code":"7.0",
    "gn:asciiname":"Loma Prieta",
    "gn:country_code":"MX",
    "gn:dem":1120,
    "gn:feature_class":"P",
    "gn:feature_code":"PPL",
    "gn:name":"Loma Prieta",
    "gn:population":0,
    "gn:timezone":"America/Chihuahua",
    "iso:country":"MX",
    "name:spa_x_preferred":[
        "Loma Prieta"
    ],
    "wof:name":"Loma Prieta",
    "wof:placetype":"locality"
},
  "geometry": {"coordinates":[-103.80918,26.79014],"type":"Point"}
}