{
  "type": "Feature",
  "properties": {
    "gn:admin1_code":"21",
    "gn:admin2_code":"147.0",
    "gn:asciiname":"Siete Lomas",
    "gn:country_code":"MX",
    "gn:dem":1733,
    "gn:feature_class":"P",
    "gn:feature_code":"PPL",
    "gn:name":"Siete Lomas",
    "gn:population":8,
    "gn:timezone":"America/Mexico_City",
    "iso:country":"MX",
    "wof:name":"Siete Lomas",
    "wof:placetype":"locality",
    "wof:population":8
},
  "geometry": {"coordinates":[-98.04191,18.49324],"type":"Point"}
}