{
  "type": "Feature",
  "properties": {
    "gn:admin1_code":"11.0",
    "gn:asciiname":"Plan de Providencia",
    "gn:country_code":"MX",
    "gn:dem":1937,
    "gn:feature_class":"P",
    "gn:feature_code":"PPL",
    "gn:name":"Plan de Providencia",
    "gn:population":0,
    "gn:timezone":"America/Mexico_City",
    "iso:country":"MX",
    "name:spa_x_preferred":[
        "Plan de Providencia"
    ],
    "wof:name":"Plan de Providencia",
    "wof:placetype":"locality"
},
  "geometry": {"coordinates":[-100.51097,19.9896],"type":"Point"}
}