{
  "type": "Feature",
  "properties": {
    "gn:admin1_code":"16.0",
    "gn:admin2_code":"53.0",
    "gn:asciiname":"Zajo Grande",
    "gn:country_code":"MX",
    "gn:dem":2221,
    "gn:feature_class":"P",
    "gn:feature_code":"PPL",
    "gn:name":"Zajo Grande",
    "gn:population":257,
    "gn:timezone":"America/Mexico_City",
    "iso:country":"MX",
    "wof:name":"Zajo Grande",
    "wof:placetype":"locality",
    "wof:population":257
},
  "geometry": {"coordinates":[-101.43946,19.74411],"type":"Point"}
}