{
  "type": "Feature",
  "properties": {
    "gn:admin1_code":"26",
    "gn:admin2_code":"12.0",
    "gn:asciiname":"Francisco Javier Mina",
    "gn:country_code":"MX",
    "gn:dem":21,
    "gn:feature_class":"P",
    "gn:feature_code":"PPL",
    "gn:name":"Francisco Javier Mina",
    "gn:population":0,
    "gn:timezone":"America/Hermosillo",
    "iso:country":"MX",
    "name:spa_x_preferred":[
        "Ejido Francisco Javier Mina"
    ],
    "name:spa_x_variant":[
        "Campo Sesenta"
    ],
    "wof:name":"Francisco Javier Mina",
    "wof:placetype":"locality"
},
  "geometry": {"coordinates":[-110.10893,27.46217],"type":"Point"}
}