{
  "type": "Feature",
  "properties": {
    "gn:admin1_code":"11",
    "gn:admin2_code":"7",
    "gn:asciiname":"La Guayaba",
    "gn:country_code":"MX",
    "gn:dem":1758,
    "gn:feature_class":"P",
    "gn:feature_code":"PPL",
    "gn:name":"La Guayaba",
    "gn:population":12,
    "gn:timezone":"America/Mexico_City",
    "iso:country":"MX",
    "wof:name":"La Guayaba",
    "wof:placetype":"locality",
    "wof:population":12
},
  "geometry": {"coordinates":[-100.77110999999999,20.53222],"type":"Point"}
}