{
  "type": "Feature",
  "properties": {
    "gn:admin1_code":"26.0",
    "gn:admin2_code":"6.0",
    "gn:asciiname":"Tres Alamos",
    "gn:country_code":"MX",
    "gn:dem":883,
    "gn:feature_class":"P",
    "gn:feature_code":"PPL",
    "gn:name":"Tres \u00c1lamos",
    "gn:population":0,
    "gn:timezone":"America/Hermosillo",
    "iso:country":"MX",
    "name:spa_x_preferred":[
        "Tres \u00c1lamos"
    ],
    "wof:name":"Tres Alamos",
    "wof:placetype":"locality"
},
  "geometry": {"coordinates":[-110.06131000000001,30.39912],"type":"Point"}
}