{
  "type": "Feature",
  "properties": {
    "gn:admin1_code":"20.0",
    "gn:admin2_code":"153.0",
    "gn:asciiname":"Costoche",
    "gn:country_code":"MX",
    "gn:dem":661,
    "gn:feature_class":"P",
    "gn:feature_code":"PPL",
    "gn:name":"Costoche",
    "gn:population":0,
    "gn:timezone":"America/Mexico_City",
    "iso:country":"MX",
    "name:spa_x_preferred":[
        "Costoche"
    ],
    "wof:name":"Costoche",
    "wof:placetype":"locality"
},
  "geometry": {"coordinates":[-97.10478999999999,16.10648],"type":"Point"}
}