{
  "type": "Feature",
  "properties": {
    "gn:admin1_code":"14",
    "gn:admin2_code":"91",
    "gn:asciiname":"Rancho Cuatro Vientos",
    "gn:country_code":"MX",
    "gn:dem":1716,
    "gn:feature_class":"P",
    "gn:feature_code":"PPL",
    "gn:name":"Rancho Cuatro Vientos",
    "gn:population":11,
    "gn:timezone":"America/Mexico_City",
    "iso:country":"MX",
    "wof:name":"Rancho Cuatro Vientos",
    "wof:placetype":"locality",
    "wof:population":11
},
  "geometry": {"coordinates":[-102.43917,21.52111],"type":"Point"}
}