{
  "type": "Feature",
  "properties": {
    "gn:admin1_code":"24",
    "gn:admin2_code":"50",
    "gn:asciiname":"Granja San Jose (Puente de Dios)",
    "gn:country_code":"MX",
    "gn:dem":1852,
    "gn:feature_class":"P",
    "gn:feature_code":"PPL",
    "gn:name":"Granja San Jos\u00e9 (Puente de Dios)",
    "gn:population":20,
    "gn:timezone":"America/Mexico_City",
    "iso:country":"MX",
    "name:und_x_variant":[
        "Granja San Jos\u00e9 (Puente de Dios)"
    ],
    "wof:name":"Granja San Jose (Puente de Dios)",
    "wof:placetype":"locality",
    "wof:population":20
},
  "geometry": {"coordinates":[-101.02028,21.76833],"type":"Point"}
}