{
  "type": "Feature",
  "properties": {
    "gn:admin1_code":"10",
    "gn:admin2_code":"2",
    "gn:asciiname":"Galeancita",
    "gn:country_code":"MX",
    "gn:dem":2335,
    "gn:feature_class":"P",
    "gn:feature_code":"PPL",
    "gn:name":"Galeancita",
    "gn:population":9,
    "gn:timezone":"America/Monterrey",
    "iso:country":"MX",
    "wof:name":"Galeancita",
    "wof:placetype":"locality",
    "wof:population":9
},
  "geometry": {"coordinates":[-106.17702,25.12081],"type":"Point"}
}