{
  "type": "Feature",
  "properties": {
    "gn:admin1_code":"27",
    "gn:admin2_code":"11.0",
    "gn:asciiname":"Trinidad y Catalina",
    "gn:country_code":"MX",
    "gn:dem":5,
    "gn:feature_class":"P",
    "gn:feature_code":"PPL",
    "gn:name":"Trinidad y Catalina",
    "gn:population":0,
    "gn:timezone":"America/Mexico_City",
    "iso:country":"MX",
    "name:spa_x_preferred":[
        "Trinidad y Catalina"
    ],
    "name:spa_x_variant":[
        "Trinidad y Catalina Primera Secci\u00f3n"
    ],
    "wof:name":"Trinidad y Catalina",
    "wof:placetype":"locality"
},
  "geometry": {"coordinates":[-92.13514000000001,17.93952999999999],"type":"Point"}
}