{
  "type": "Feature",
  "properties": {
    "gn:admin1_code":"7",
    "gn:admin2_code":"15.0",
    "gn:asciiname":"Borregos",
    "gn:country_code":"MX",
    "gn:dem":300,
    "gn:feature_class":"P",
    "gn:feature_code":"PPL",
    "gn:name":"Borregos",
    "gn:population":0,
    "gn:timezone":"America/Monterrey",
    "iso:country":"MX",
    "name:spa_x_preferred":[
        "Borregos"
    ],
    "name:und_x_variant":[
        "Rancho Los Borregos",
        "Los Borregos"
    ],
    "wof:name":"Borregos",
    "wof:placetype":"locality"
},
  "geometry": {"coordinates":[-100.87699000000001,27.66462000000001],"type":"Point"}
}