{
  "type": "Feature",
  "properties": {
    "iso:country":"MX",
    "name:spa_x_preferred":[
        "Zona Pronaf"
    ],
    "qs:gn_adm0_cc":"MX",
    "qs:gn_local":4013708,
    "qs:gn_nam_loc":"Juarez, Ciudad Ju\u00e1rez, Chihuahua, MX",
    "qs:gn_namadm1":"06",
    "qs:local_max":1731,
    "qs:local_sum":2151,
    "qs:localhoods":7,
    "qs:name":"Zona Pronaf",
    "qs:name_adm0":"M\u00e9xico",
    "qs:name_adm1":"Chihuahua",
    "qs:name_adm2":"Juarez",
    "qs:name_local":"Ciudad Ju\u00e1rez",
    "qs:photo_max":59,
    "qs:photo_sum":119,
    "qs:placetype":"Suburb",
    "qs:quad_count":9,
    "qs:woe_adm0":23424900,
    "qs:woe_adm1":2346269,
    "qs:woe_adm2":12599855,
    "qs:woe_lau":0,
    "qs:woe_local":116556,
    "qs:woe_ver":"7.10.0",
    "wof:lang":[
        "spa"
    ],
    "wof:name":"Zona Pronaf",
    "wof:placetype":"neighbourhood"
},
  "geometry": {"coordinates":[-106.45383699999999,31.740131],"type":"Point"}
}