{
  "type": "Feature",
  "properties": {
    "gn:admin1_code":"14",
    "gn:admin2_code":"97",
    "gn:asciiname":"Colonia Nueva Esperanza",
    "gn:country_code":"MX",
    "gn:dem":1531,
    "gn:feature_class":"P",
    "gn:feature_code":"PPL",
    "gn:name":"Colonia Nueva Esperanza",
    "gn:population":33,
    "gn:timezone":"America/Mexico_City",
    "iso:country":"MX",
    "wof:name":"Colonia Nueva Esperanza",
    "wof:placetype":"locality",
    "wof:population":33
},
  "geometry": {"coordinates":[-103.32861,20.535],"type":"Point"}
}