{
  "type": "Feature",
  "properties": {
    "gn:admin1_code":"26.0",
    "gn:admin2_code":"61.0",
    "gn:asciiname":"Tierra Larga",
    "gn:country_code":"MX",
    "gn:dem":223,
    "gn:feature_class":"P",
    "gn:feature_code":"PPL",
    "gn:name":"Tierra Larga",
    "gn:population":0,
    "gn:timezone":"America/Hermosillo",
    "iso:country":"MX",
    "name:spa_x_preferred":[
        "Tierra Larga"
    ],
    "wof:name":"Tierra Larga",
    "wof:placetype":"locality"
},
  "geometry": {"coordinates":[-109.61002000000001,28.89499],"type":"Point"}
}