{
  "type": "Feature",
  "properties": {
    "gn:admin1_code":"6.0",
    "gn:admin2_code":"63.0",
    "gn:asciiname":"El Portal",
    "gn:country_code":"MX",
    "gn:dem":2492,
    "gn:feature_class":"P",
    "gn:feature_code":"PPL",
    "gn:name":"El Portal",
    "gn:population":0,
    "gn:timezone":"America/Chihuahua",
    "iso:country":"MX",
    "name:ceb_x_preferred":[
        "El Portal"
    ],
    "name:deu_x_preferred":[
        "El Portal"
    ],
    "name:fra_x_preferred":[
        "El Portal"
    ],
    "name:nld_x_preferred":[
        "El Portal"
    ],
    "name:spa_x_preferred":[
        "El Portal"
    ],
    "name:srp_x_preferred":[
        "\u0415\u043b \u041f\u043e\u0440\u0442\u0430\u043b"
    ],
    "name:swe_x_preferred":[
        "El Portal"
    ],
    "wof:name":"El Portal",
    "wof:placetype":"locality"
},
  "geometry": {"coordinates":[-108.30816000000002,28.6683],"type":"Point"}
}