{
  "type": "Feature",
  "properties": {
    "gn:admin1_code":"21",
    "gn:admin2_code":"156",
    "gn:asciiname":"Don Pedro (Dona Ofe)",
    "gn:country_code":"MX",
    "gn:dem":1759,
    "gn:feature_class":"P",
    "gn:feature_code":"PPL",
    "gn:name":"Don Pedro (Do\u00f1a Ofe)",
    "gn:population":16,
    "gn:timezone":"America/Mexico_City",
    "iso:country":"MX",
    "name:und_x_variant":[
        "Don Pedro (Do\u00f1a Ofe)"
    ],
    "wof:name":"Don Pedro (Dona Ofe)",
    "wof:placetype":"locality",
    "wof:population":16
},
  "geometry": {"coordinates":[-97.52272000000001,18.52962],"type":"Point"}
}