{
  "type": "Feature",
  "properties": {
    "gn:admin1_code":"16",
    "gn:admin2_code":"49.0",
    "gn:asciiname":"El Ojo de Agua del Venado",
    "gn:country_code":"MX",
    "gn:dem":1887,
    "gn:feature_class":"P",
    "gn:feature_code":"PPL",
    "gn:name":"El Ojo de Agua del Venado",
    "gn:population":9,
    "gn:timezone":"America/Mexico_City",
    "iso:country":"MX",
    "wof:name":"El Ojo de Agua del Venado",
    "wof:placetype":"locality",
    "wof:population":9
},
  "geometry": {"coordinates":[-101.08167,19.44028],"type":"Point"}
}