{
  "type": "Feature",
  "properties": {
    "gn:admin1_code":"12",
    "gn:admin2_code":"71",
    "gn:asciiname":"Cienega Pochota",
    "gn:country_code":"MX",
    "gn:dem":527,
    "gn:feature_class":"P",
    "gn:feature_code":"PPL",
    "gn:name":"Ci\u00e9nega Pochota",
    "gn:population":21,
    "gn:timezone":"America/Mexico_City",
    "iso:country":"MX",
    "name:und_x_variant":[
        "Ci\u00e9nega Pochota"
    ],
    "wof:name":"Cienega Pochota",
    "wof:placetype":"locality",
    "wof:population":21
},
  "geometry": {"coordinates":[-98.20984,16.81927],"type":"Point"}
}