{
  "type": "Feature",
  "properties": {
    "gn:admin1_code":"6.0",
    "gn:admin2_code":"16.0",
    "gn:asciiname":"La Colonia Alegre",
    "gn:country_code":"MX",
    "gn:dem":1206,
    "gn:feature_class":"P",
    "gn:feature_code":"PPL",
    "gn:name":"La Colonia Alegre",
    "gn:population":0,
    "gn:timezone":"America/Chihuahua",
    "iso:country":"MX",
    "name:spa_x_preferred":[
        "La Colonia Alegre"
    ],
    "wof:name":"La Colonia Alegre",
    "wof:placetype":"locality"
},
  "geometry": {"coordinates":[-105.17695999999999,27.90138],"type":"Point"}
}