{
  "type": "Feature",
  "properties": {
    "gn:admin1_code":"15.0",
    "gn:admin2_code":"124.0",
    "gn:asciiname":"San Joaquin Lamillas",
    "gn:country_code":"MX",
    "gn:dem":2745,
    "gn:feature_class":"P",
    "gn:feature_code":"PPL",
    "gn:name":"San Joaqu\u00edn Lamillas",
    "gn:population":0,
    "gn:timezone":"America/Mexico_City",
    "iso:country":"MX",
    "name:spa_x_preferred":[
        "San Joaqu\u00edn Lamillas"
    ],
    "name:und_x_variant":[
        "San Joaqu\u00edn Laminillas"
    ],
    "wof:name":"San Joaquin Lamillas",
    "wof:placetype":"locality"
},
  "geometry": {"coordinates":[-100.1416,19.56873],"type":"Point"}
}