{
  "type": "Feature",
  "properties": {
    "gn:admin1_code":"5",
    "gn:admin2_code":"43.0",
    "gn:asciiname":"Ixtacerpitan",
    "gn:country_code":"MX",
    "gn:dem":193,
    "gn:feature_class":"P",
    "gn:feature_code":"PPL",
    "gn:name":"Ixtacerpit\u00e1n",
    "gn:population":0,
    "gn:timezone":"America/Mexico_City",
    "iso:country":"MX",
    "wof:name":"Ixtacerpitan",
    "wof:placetype":"locality"
},
  "geometry": {"coordinates":[-93.09166999999999,17.43333],"type":"Point"}
}