{
  "type": "Feature",
  "properties": {
    "gn:admin1_code":"27",
    "gn:admin2_code":"4",
    "gn:asciiname":"Buena Vista 2da. Seccion (El Tular)",
    "gn:country_code":"MX",
    "gn:dem":4,
    "gn:feature_class":"P",
    "gn:feature_code":"PPL",
    "gn:name":"Buena Vista 2da. Secci\u00f3n (El Tular)",
    "gn:population":11,
    "gn:timezone":"America/Mexico_City",
    "iso:country":"MX",
    "name:und_x_variant":[
        "Buena Vista 2da. Secci\u00f3n (El Tular)"
    ],
    "wof:name":"Buena Vista 2da. Seccion (El Tular)",
    "wof:placetype":"locality",
    "wof:population":11
},
  "geometry": {"coordinates":[-92.73999999999999,18.17028],"type":"Point"}
}