{
  "type": "Feature",
  "properties": {
    "gn:admin1_code":"19.0",
    "gn:admin2_code":"20.0",
    "gn:asciiname":"Tomatillos",
    "gn:country_code":"MX",
    "gn:dem":137,
    "gn:feature_class":"P",
    "gn:feature_code":"PPL",
    "gn:name":"Tomatillos",
    "gn:population":0,
    "gn:timezone":"America/Monterrey",
    "iso:country":"MX",
    "name:spa_x_preferred":[
        "Tomatillos"
    ],
    "wof:name":"Tomatillos",
    "wof:placetype":"locality"
},
  "geometry": {"coordinates":[-99.09765,25.81252000000001],"type":"Point"}
}