{
  "type": "Feature",
  "properties": {
    "gn:admin1_code":"25",
    "gn:admin2_code":"10.0",
    "gn:asciiname":"La Carrera",
    "gn:country_code":"MX",
    "gn:dem":52,
    "gn:feature_class":"P",
    "gn:feature_code":"PPL",
    "gn:name":"La Carrera",
    "gn:population":329,
    "gn:timezone":"America/Mazatlan",
    "iso:country":"MX",
    "wof:name":"La Carrera",
    "wof:placetype":"locality",
    "wof:population":329
},
  "geometry": {"coordinates":[-108.78417,26.22083],"type":"Point"}
}