{
  "type": "Feature",
  "properties": {
    "gn:admin1_code":"14",
    "gn:admin2_code":"59",
    "gn:asciiname":"Los Rincones",
    "gn:country_code":"MX",
    "gn:dem":1629,
    "gn:feature_class":"P",
    "gn:feature_code":"PPL",
    "gn:name":"Los Rincones",
    "gn:population":10,
    "gn:timezone":"America/Mexico_City",
    "iso:country":"MX",
    "wof:name":"Los Rincones",
    "wof:placetype":"locality",
    "wof:population":10
},
  "geometry": {"coordinates":[-103.07944000000001,19.83639],"type":"Point"}
}