{
  "type": "Feature",
  "properties": {
    "gn:admin1_code":"6.0",
    "gn:admin2_code":"67.0",
    "gn:asciiname":"Salitrito",
    "gn:country_code":"MX",
    "gn:dem":1335,
    "gn:feature_class":"P",
    "gn:feature_code":"PPL",
    "gn:name":"Salitrito",
    "gn:population":0,
    "gn:timezone":"America/Chihuahua",
    "iso:country":"MX",
    "name:spa_x_preferred":[
        "Salitrito"
    ],
    "name:und_x_variant":[
        "El Salitre"
    ],
    "wof:name":"Salitrito",
    "wof:placetype":"locality"
},
  "geometry": {"coordinates":[-105.76848,27.57146],"type":"Point"}
}