{
  "type": "Feature",
  "properties": {
    "gn:admin1_code":"7.0",
    "gn:admin2_code":"24.0",
    "gn:asciiname":"Jalapa",
    "gn:country_code":"MX",
    "gn:dem":1665,
    "gn:feature_class":"P",
    "gn:feature_code":"PPL",
    "gn:name":"Jalapa",
    "gn:population":0,
    "gn:timezone":"America/Monterrey",
    "iso:country":"MX",
    "name:spa_x_preferred":[
        "Jalapa"
    ],
    "wof:name":"Jalapa",
    "wof:placetype":"locality"
},
  "geometry": {"coordinates":[-101.55846,24.88932],"type":"Point"}
}