{
  "type": "Feature",
  "properties": {
    "gn:admin1_code":"13",
    "gn:admin2_code":"54.0",
    "gn:asciiname":"El Tablon",
    "gn:country_code":"MX",
    "gn:dem":2078,
    "gn:feature_class":"P",
    "gn:feature_code":"PPL",
    "gn:name":"El Tabl\u00f3n",
    "gn:population":0,
    "gn:timezone":"America/Mexico_City",
    "iso:country":"MX",
    "name:spa_x_preferred":[
        "El Tabl\u00f3n"
    ],
    "wof:name":"El Tablon",
    "wof:placetype":"locality"
},
  "geometry": {"coordinates":[-98.99002,20.20801],"type":"Point"}
}