{
  "type": "Feature",
  "properties": {
    "gn:admin1_code":"4",
    "gn:admin2_code":"2.0",
    "gn:asciiname":"Lubna",
    "gn:country_code":"MX",
    "gn:dem":38,
    "gn:feature_class":"P",
    "gn:feature_code":"PPL",
    "gn:name":"Lubn\u00e1",
    "gn:population":0,
    "gn:timezone":"America/Merida",
    "iso:country":"MX",
    "name:ceb_x_preferred":[
        "Lubna"
    ],
    "name:ces_x_preferred":[
        "Lubn\u00e1"
    ],
    "name:deu_x_preferred":[
        "Lubn\u00e1"
    ],
    "name:epo_x_preferred":[
        "Lubn\u00e1"
    ],
    "name:fra_x_preferred":[
        "Lubna"
    ],
    "name:ita_x_preferred":[
        "Lubn\u00e1"
    ],
    "name:nld_x_preferred":[
        "Lubn\u00e1"
    ],
    "name:pol_x_preferred":[
        "Lubn\u00e1"
    ],
    "name:rus_x_preferred":[
        "\u041b\u0443\u0431\u043d\u0430"
    ],
    "name:slk_x_preferred":[
        "Lubn\u00e1"
    ],
    "name:spa_x_preferred":[
        "Lubna"
    ],
    "name:spa_x_variant":[
        "Lubn\u00e1"
    ],
    "name:srp_x_preferred":[
        "\u041b\u0443\u0431\u043d\u0430"
    ],
    "name:swe_x_preferred":[
        "Lubna"
    ],
    "name:ukr_x_preferred":[
        "\u041b\u0443\u0431\u043d\u0430"
    ],
    "wof:name":"Lubna",
    "wof:placetype":"locality"
},
  "geometry": {"coordinates":[-90.17668999999999,19.50897],"type":"Point"}
}