{
  "type": "Feature",
  "properties": {
    "gn:admin1_code":"30",
    "gn:admin2_code":"108.0",
    "gn:asciiname":"Ceiba Bonita",
    "gn:country_code":"MX",
    "gn:dem":34,
    "gn:feature_class":"P",
    "gn:feature_code":"PPL",
    "gn:name":"Ceiba Bonita",
    "gn:population":0,
    "gn:timezone":"America/Mexico_City",
    "iso:country":"MX",
    "name:und_x_variant":[
        "La Ceiba"
    ],
    "wof:name":"Ceiba Bonita",
    "wof:placetype":"locality"
},
  "geometry": {"coordinates":[-94.39013,17.80729],"type":"Point"}
}