{
  "type": "Feature",
  "properties": {
    "gn:admin1_code":"4",
    "gn:admin2_code":"3.0",
    "gn:asciiname":"El Pinal del Rio",
    "gn:country_code":"MX",
    "gn:dem":-1,
    "gn:feature_class":"P",
    "gn:feature_code":"PPL",
    "gn:name":"El Pinal del R\u00edo",
    "gn:population":0,
    "gn:timezone":"America/Merida",
    "iso:country":"MX",
    "name:spa_x_preferred":[
        "Final del R\u00edo"
    ],
    "name:spa_x_variant":[
        "El Pinal del R\u00edo"
    ],
    "wof:name":"El Pinal del Rio",
    "wof:placetype":"locality"
},
  "geometry": {"coordinates":[-91.49357000000001,18.32323],"type":"Point"}
}