{
  "type": "Feature",
  "properties": {
    "gn:admin1_code":"10",
    "gn:admin2_code":"24.0",
    "gn:asciiname":"Valle del Recreo",
    "gn:country_code":"MX",
    "gn:dem":1446,
    "gn:feature_class":"P",
    "gn:feature_code":"PPL",
    "gn:name":"Valle del Recreo",
    "gn:population":4,
    "gn:timezone":"America/Monterrey",
    "iso:country":"MX",
    "wof:name":"Valle del Recreo",
    "wof:placetype":"locality",
    "wof:population":4
},
  "geometry": {"coordinates":[-104.62223,25.35272],"type":"Point"}
}