{
  "type": "Feature",
  "properties": {
    "gn:admin1_code":"2.0",
    "gn:admin2_code":"2.0",
    "gn:asciiname":"Campo Diecinueve (Ejido Morelos Colonia el Suspiro)",
    "gn:country_code":"MX",
    "gn:dem":27,
    "gn:feature_class":"P",
    "gn:feature_code":"PPL",
    "gn:name":"Campo Diecinueve (Ejido Morelos Colonia el Suspiro)",
    "gn:population":96,
    "gn:timezone":"America/Tijuana",
    "iso:country":"MX",
    "name:spa_x_preferred":[
        "El Diecinueve"
    ],
    "wof:name":"Campo Diecinueve (Ejido Morelos Colonia el Suspiro)",
    "wof:placetype":"locality",
    "wof:population":96
},
  "geometry": {"coordinates":[-114.85722,32.59056],"type":"Point"}
}