{
  "type": "Feature",
  "properties": {
    "gn:admin1_code":"2.0",
    "gn:admin2_code":"5.0",
    "gn:asciiname":"Ciudad Misericordia",
    "gn:country_code":"MX",
    "gn:dem":126,
    "gn:feature_class":"P",
    "gn:feature_code":"PPL",
    "gn:name":"Ciudad Misericordia",
    "gn:population":0,
    "gn:timezone":"America/Tijuana",
    "iso:country":"MX",
    "name:spa_x_preferred":[
        "Ciudad Misericordia"
    ],
    "wof:name":"Ciudad Misericordia",
    "wof:placetype":"locality"
},
  "geometry": {"coordinates":[-116.95108,32.26918],"type":"Point"}
}