{
  "type": "Feature",
  "properties": {
    "gn:admin1_code":"13",
    "gn:admin2_code":"30.0",
    "gn:asciiname":"Barrio el Progreso",
    "gn:country_code":"MX",
    "gn:dem":1705,
    "gn:feature_class":"P",
    "gn:feature_code":"PPL",
    "gn:name":"Barrio el Progreso",
    "gn:population":0,
    "gn:timezone":"America/Mexico_City",
    "iso:country":"MX",
    "name:spa_x_preferred":[
        "Barrio el Progreso"
    ],
    "wof:name":"Barrio el Progreso",
    "wof:placetype":"locality"
},
  "geometry": {"coordinates":[-99.22754999999999,20.48925],"type":"Point"}
}