{
  "type": "Feature",
  "properties": {
    "gn:admin1_code":"5",
    "gn:admin2_code":"14.0",
    "gn:asciiname":"San Cayetano",
    "gn:country_code":"MX",
    "gn:dem":1511,
    "gn:feature_class":"P",
    "gn:feature_code":"PPL",
    "gn:name":"San Cayetano",
    "gn:population":1833,
    "gn:timezone":"America/Mexico_City",
    "iso:country":"MX",
    "name:ceb_x_preferred":[
        "San Cayetano"
    ],
    "name:deu_x_preferred":[
        "San Cayetano"
    ],
    "name:fra_x_preferred":[
        "San Cayetano"
    ],
    "name:ita_x_preferred":[
        "San Cayetano"
    ],
    "name:msa_x_preferred":[
        "San Cayetano"
    ],
    "name:nld_x_preferred":[
        "San Cayetano"
    ],
    "name:por_x_preferred":[
        "San Cayetano"
    ],
    "name:sco_x_preferred":[
        "San Cayetano"
    ],
    "name:spa_x_preferred":[
        "San Cayetano"
    ],
    "name:swe_x_preferred":[
        "San Cayetano"
    ],
    "name:war_x_preferred":[
        "San Cayetano"
    ],
    "wof:name":"San Cayetano",
    "wof:placetype":"locality",
    "wof:population":1833
},
  "geometry": {"coordinates":[-92.76016,16.96119],"type":"Point"}
}