{
  "type": "Feature",
  "properties": {
    "gn:admin1_code":"16",
    "gn:admin2_code":"53",
    "gn:asciiname":"El Carretero",
    "gn:country_code":"MX",
    "gn:dem":2393,
    "gn:feature_class":"P",
    "gn:feature_code":"PPL",
    "gn:name":"El Carretero",
    "gn:population":17,
    "gn:timezone":"America/Mexico_City",
    "iso:country":"MX",
    "wof:name":"El Carretero",
    "wof:placetype":"locality",
    "wof:population":17
},
  "geometry": {"coordinates":[-101.16500000000001,19.57917],"type":"Point"}
}