{
  "type": "Feature",
  "properties": {
    "gn:admin1_code":"20.0",
    "gn:admin2_code":"141.0",
    "gn:asciiname":"San Eloy",
    "gn:country_code":"MX",
    "gn:dem":7,
    "gn:feature_class":"P",
    "gn:feature_code":"PPL",
    "gn:name":"San Eloy",
    "gn:population":0,
    "gn:timezone":"America/Mexico_City",
    "iso:country":"MX",
    "name:spa_x_preferred":[
        "San Eloy"
    ],
    "wof:name":"San Eloy",
    "wof:placetype":"locality"
},
  "geometry": {"coordinates":[-94.357,16.16475],"type":"Point"}
}