{
  "type": "Feature",
  "properties": {
    "gn:admin1_code":"6",
    "gn:admin2_code":"27.0",
    "gn:asciiname":"Charerachi",
    "gn:country_code":"MX",
    "gn:dem":1903,
    "gn:feature_class":"P",
    "gn:feature_code":"PPL",
    "gn:name":"Char\u00e9rachi",
    "gn:population":0,
    "gn:timezone":"America/Chihuahua",
    "iso:country":"MX",
    "name:spa_x_preferred":[
        "Char\u00e9rachi"
    ],
    "wof:name":"Charerachi",
    "wof:placetype":"locality"
},
  "geometry": {"coordinates":[-107.50863,27.18138],"type":"Point"}
}