{
  "type": "Feature",
  "properties": {
    "gn:admin1_code":"6",
    "gn:admin2_code":"9.0",
    "gn:asciiname":"Sopetare",
    "gn:country_code":"MX",
    "gn:dem":2142,
    "gn:feature_class":"P",
    "gn:feature_code":"PPL",
    "gn:name":"Sopetare",
    "gn:population":5,
    "gn:timezone":"America/Chihuahua",
    "iso:country":"MX",
    "name:spa_x_preferred":[
        "Sopetare"
    ],
    "name:und_x_variant":[
        "Sopelare"
    ],
    "wof:name":"Sopetare",
    "wof:placetype":"locality",
    "wof:population":5
},
  "geometry": {"coordinates":[-107.84684,27.68513],"type":"Point"}
}