{
  "type": "Feature",
  "properties": {
    "gn:admin1_code":"27",
    "gn:admin2_code":"17.0",
    "gn:asciiname":"Pino Suarez Primera Seccion",
    "gn:country_code":"MX",
    "gn:dem":17,
    "gn:feature_class":"P",
    "gn:feature_code":"PPL",
    "gn:name":"Pino Su\u00e1rez Primera Secci\u00f3n",
    "gn:population":0,
    "gn:timezone":"America/Mexico_City",
    "iso:country":"MX",
    "name:spa_x_preferred":[
        "Jos\u00e9 Mar\u00eda Pino Su\u00e1rez"
    ],
    "name:spa_x_variant":[
        "Pino Su\u00e1rez",
        "Primera Secci\u00f3n",
        "Pino Su\u00e1rez Primera Secci\u00f3n"
    ],
    "wof:name":"Pino Suarez Primera Seccion",
    "wof:placetype":"locality"
},
  "geometry": {"coordinates":[-91.45433,17.57048],"type":"Point"}
}