{
  "type": "Feature",
  "properties": {
    "gn:admin1_code":"11.0",
    "gn:admin2_code":"23.0",
    "gn:asciiname":"Corrales de Rabago",
    "gn:country_code":"MX",
    "gn:dem":1704,
    "gn:feature_class":"P",
    "gn:feature_code":"PPL",
    "gn:name":"Corrales de R\u00e1bago",
    "gn:population":0,
    "gn:timezone":"America/Mexico_City",
    "iso:country":"MX",
    "name:spa_x_preferred":[
        "Corrales de R\u00e1bago"
    ],
    "wof:name":"Corrales de Rabago",
    "wof:placetype":"locality"
},
  "geometry": {"coordinates":[-101.85933,20.21423],"type":"Point"}
}