{
  "type": "Feature",
  "properties": {
    "gn:admin1_code":"7",
    "gn:admin2_code":"23.0",
    "gn:asciiname":"La Presa",
    "gn:cc2":"MX",
    "gn:country_code":"MX",
    "gn:dem":1046,
    "gn:feature_class":"P",
    "gn:feature_code":"PPL",
    "gn:name":"La Presa",
    "gn:population":0,
    "gn:timezone":"America/Monterrey",
    "iso:country":"MX",
    "name:und_x_variant":[
        "Presa",
        "La Presa"
    ],
    "wof:name":"La Presa",
    "wof:placetype":"locality"
},
  "geometry": {"coordinates":[-103.25,28.46667],"type":"Point"}
}