{
  "type": "Feature",
  "properties": {
    "gn:admin1_code":"1.0",
    "gn:admin2_code":"5.0",
    "gn:asciiname":"La Boquilla",
    "gn:country_code":"MX",
    "gn:dem":1919,
    "gn:feature_class":"P",
    "gn:feature_code":"PPL",
    "gn:name":"La Boquilla",
    "gn:population":0,
    "gn:timezone":"America/Mexico_City",
    "iso:country":"MX",
    "wof:name":"La Boquilla",
    "wof:placetype":"locality"
},
  "geometry": {"coordinates":[-102.54001,21.85866],"type":"Point"}
}