{
  "type": "Feature",
  "properties": {
    "gn:admin1_code":"7",
    "gn:admin2_code":"30.0",
    "gn:asciiname":"Presa de San Javier",
    "gn:country_code":"MX",
    "gn:dem":1920,
    "gn:feature_class":"P",
    "gn:feature_code":"PPL",
    "gn:name":"Presa de San Javier",
    "gn:population":0,
    "gn:timezone":"America/Monterrey",
    "iso:country":"MX",
    "name:spa_x_preferred":[
        "Presa de San Javier"
    ],
    "wof:name":"Presa de San Javier",
    "wof:placetype":"locality"
},
  "geometry": {"coordinates":[-100.81259,24.74783],"type":"Point"}
}