{
  "type": "Feature",
  "properties": {
    "gn:admin1_code":"12",
    "gn:admin2_code":"80.0",
    "gn:asciiname":"Carrizalillo",
    "gn:country_code":"MX",
    "gn:dem":94,
    "gn:feature_class":"P",
    "gn:feature_code":"PPL",
    "gn:name":"Carrizalillo",
    "gn:population":679,
    "gn:timezone":"America/Mexico_City",
    "iso:country":"MX",
    "wof:name":"Carrizalillo",
    "wof:placetype":"locality",
    "wof:population":679
},
  "geometry": {"coordinates":[-98.76333,16.60861],"type":"Point"}
}