{
  "type": "Feature",
  "properties": {
    "gn:admin1_code":"15",
    "gn:admin2_code":"37.0",
    "gn:asciiname":"Huiloteapan (San Jose Huiloteapan)",
    "gn:country_code":"MX",
    "gn:dem":2896,
    "gn:feature_class":"P",
    "gn:feature_code":"PPL",
    "gn:name":"Huiloteapan (San Jos\u00e9 Huiloteapan)",
    "gn:population":925,
    "gn:timezone":"America/Mexico_City",
    "iso:country":"MX",
    "name:und_x_variant":[
        "Huiloteapan (San Jos\u00e9 Huiloteapan)"
    ],
    "wof:name":"Huiloteapan (San Jose Huiloteapan)",
    "wof:placetype":"locality",
    "wof:population":925
},
  "geometry": {"coordinates":[-99.34732,19.38545],"type":"Point"}
}