{
  "type": "Feature",
  "properties": {
    "gn:admin1_code":"11",
    "gn:admin2_code":"20",
    "gn:asciiname":"Hilario Rocha",
    "gn:country_code":"MX",
    "gn:dem":1848,
    "gn:feature_class":"P",
    "gn:feature_code":"PPL",
    "gn:name":"Hilario Rocha",
    "gn:population":34,
    "gn:timezone":"America/Mexico_City",
    "iso:country":"MX",
    "wof:name":"Hilario Rocha",
    "wof:placetype":"locality",
    "wof:population":34
},
  "geometry": {"coordinates":[-101.59389,21.12389],"type":"Point"}
}