{
  "type": "Feature",
  "properties": {
    "gn:admin1_code":"30",
    "gn:admin2_code":"69.0",
    "gn:asciiname":"Arenal",
    "gn:country_code":"MX",
    "gn:dem":75,
    "gn:feature_class":"P",
    "gn:feature_code":"PPL",
    "gn:name":"Arenal",
    "gn:population":0,
    "gn:timezone":"America/Mexico_City",
    "iso:country":"MX",
    "wof:name":"Arenal",
    "wof:placetype":"locality"
},
  "geometry": {"coordinates":[-97.08501,20.393],"type":"Point"}
}