{
  "type": "Feature",
  "properties": {
    "gn:admin1_code":"20",
    "gn:admin2_code":"207.0",
    "gn:asciiname":"Arroyo Lirio",
    "gn:country_code":"MX",
    "gn:dem":142,
    "gn:feature_class":"P",
    "gn:feature_code":"PPL",
    "gn:name":"Arroyo Lirio",
    "gn:population":0,
    "gn:timezone":"America/Mexico_City",
    "iso:country":"MX",
    "name:spa_x_preferred":[
        "Arroyo Lirio"
    ],
    "wof:name":"Arroyo Lirio",
    "wof:placetype":"locality"
},
  "geometry": {"coordinates":[-95.2996,17.22361],"type":"Point"}
}