{
  "type": "Feature",
  "properties": {
    "gn:admin1_code":"28.0",
    "gn:admin2_code":"16.0",
    "gn:asciiname":"El Tamaulipeco",
    "gn:country_code":"MX",
    "gn:dem":348,
    "gn:feature_class":"P",
    "gn:feature_code":"PPL",
    "gn:name":"El Tamaulipeco",
    "gn:population":0,
    "gn:timezone":"America/Monterrey",
    "iso:country":"MX",
    "name:spa_x_preferred":[
        "El Tamaulipeco"
    ],
    "wof:name":"El Tamaulipeco",
    "wof:placetype":"locality"
},
  "geometry": {"coordinates":[-99.44110999999999,24.27361],"type":"Point"}
}