{
  "type": "Feature",
  "properties": {
    "gn:country":"MX",
    "gn:fcode":"PPL",
    "gn:population":0,
    "iso:country":"MX",
    "name:ces_x_preferred":[
        "Las Pozas"
    ],
    "name:fra_x_preferred":[
        "Las Pozas"
    ],
    "name:hun_x_preferred":[
        "Las Pozas"
    ],
    "name:rus_x_preferred":[
        "\u041b\u0430\u0441-\u041f\u043e\u0441\u0430\u0441"
    ],
    "name:spa_x_preferred":[
        "Las Pozas"
    ],
    "name:ukr_x_preferred":[
        "\u041b\u0430\u0441-\u041f\u043e\u0441\u0430\u0441"
    ],
    "name:und_x_variant":[
        "Pozaz"
    ],
    "qs_pg:aaroncc":"MX",
    "qs_pg:gn_country":"MX",
    "qs_pg:gn_fcode":"PPL",
    "qs_pg:gn_pop":0,
    "qs_pg:name":"Las Pozas",
    "qs_pg:name_adm0":"M\u00e9xico",
    "qs_pg:name_adm1":"Guerrero",
    "qs_pg:photos":587,
    "qs_pg:photos_1k":119,
    "qs_pg:photos_9k":3,
    "qs_pg:photos_9r":5,
    "qs_pg:photos_all":587,
    "qs_pg:photos_sr":8,
    "qs_pg:pop_sr":0,
    "qs_pg:qs_pg_placetype":"locality",
    "qs_pg:qs_pg_placetype_gp":"Town",
    "qs_pg:woe_adm0":23424900,
    "woe:adm0_id":23424900,
    "woe:name_adm0":"M\u00e9xico",
    "woe:name_adm1":"Guerrero",
    "woe:placetype":"Town",
    "wof:name":"Las Pozas",
    "wof:placetype":"locality",
    "wof:population":4
},
  "geometry": {"coordinates":[-101.46666999999999,17.56667],"type":"Point"}
}