{
  "type": "Feature",
  "properties": {
    "gn:admin1_code":"28.0",
    "gn:admin2_code":"15.0",
    "gn:asciiname":"Cinco de Febrero",
    "gn:country_code":"MX",
    "gn:dem":46,
    "gn:feature_class":"P",
    "gn:feature_code":"PPL",
    "gn:name":"Cinco de Febrero",
    "gn:population":0,
    "gn:timezone":"America/Monterrey",
    "iso:country":"MX",
    "name:spa_x_preferred":[
        "Cinco de Febrero"
    ],
    "wof:name":"Cinco de Febrero",
    "wof:placetype":"locality"
},
  "geometry": {"coordinates":[-98.66119,26.20265],"type":"Point"}
}