{
  "type": "Feature",
  "properties": {
    "gn:admin1_code":"15",
    "gn:admin2_code":"82.0",
    "gn:asciiname":"El Capire (Colonia el Capire)",
    "gn:country_code":"MX",
    "gn:dem":1374,
    "gn:feature_class":"P",
    "gn:feature_code":"PPL",
    "gn:name":"El Capire (Colonia el Capire)",
    "gn:population":401,
    "gn:timezone":"America/Mexico_City",
    "iso:country":"MX",
    "wof:name":"El Capire (Colonia el Capire)",
    "wof:placetype":"locality",
    "wof:population":401
},
  "geometry": {"coordinates":[-100.16106000000001,18.90705],"type":"Point"}
}