{
  "type": "Feature",
  "properties": {
    "gn:admin1_code":"16",
    "gn:admin2_code":"50.0",
    "gn:asciiname":"El Colorado",
    "gn:country_code":"MX",
    "gn:dem":2204,
    "gn:feature_class":"P",
    "gn:feature_code":"PPL",
    "gn:name":"El Colorado",
    "gn:population":383,
    "gn:timezone":"America/Mexico_City",
    "iso:country":"MX",
    "name:deu_x_preferred":[
        "El Colorado"
    ],
    "name:fra_x_preferred":[
        "El Colorado"
    ],
    "name:nld_x_preferred":[
        "El Colorado"
    ],
    "name:pol_x_preferred":[
        "El Colorado"
    ],
    "name:por_x_preferred":[
        "El Colorado"
    ],
    "name:spa_x_preferred":[
        "El Colorado"
    ],
    "wof:name":"El Colorado",
    "wof:placetype":"locality",
    "wof:population":383
},
  "geometry": {"coordinates":[-100.24694,19.89083],"type":"Point"}
}