{
  "type": "Feature",
  "properties": {
    "gn:admin1_code":"27",
    "gn:admin2_code":"2.0",
    "gn:asciiname":"Las Coloradas Segunda Seccion B",
    "gn:country_code":"MX",
    "gn:dem":10,
    "gn:feature_class":"P",
    "gn:feature_code":"PPL",
    "gn:name":"Las Coloradas Segunda Secci\u00f3n B",
    "gn:population":0,
    "gn:timezone":"America/Mexico_City",
    "iso:country":"MX",
    "name:spa_x_preferred":[
        "Las Coloradas Segunda Secci\u00f3n B"
    ],
    "wof:name":"Las Coloradas Segunda Seccion B",
    "wof:placetype":"locality"
},
  "geometry": {"coordinates":[-93.55758,18.29024],"type":"Point"}
}