{
  "type": "Feature",
  "properties": {
    "gn:admin1_code":"20",
    "gn:admin2_code":"355",
    "gn:asciiname":"Isidro Perez Hernandez",
    "gn:country_code":"MX",
    "gn:dem":1524,
    "gn:feature_class":"P",
    "gn:feature_code":"PPL",
    "gn:name":"Isidro P\u00e9rez Hern\u00e1ndez",
    "gn:population":24,
    "gn:timezone":"America/Mexico_City",
    "iso:country":"MX",
    "name:und_x_variant":[
        "Isidro P\u00e9rez Hern\u00e1ndez"
    ],
    "wof:name":"Isidro Perez Hernandez",
    "wof:placetype":"locality",
    "wof:population":24
},
  "geometry": {"coordinates":[-96.79111,17.98111],"type":"Point"}
}