{
  "type": "Feature",
  "properties": {
    "gn:admin1_code":"5",
    "gn:admin2_code":"12.0",
    "gn:asciiname":"El Yunque",
    "gn:country_code":"MX",
    "gn:dem":939,
    "gn:feature_class":"P",
    "gn:feature_code":"PPL",
    "gn:name":"El Yunque",
    "gn:population":6,
    "gn:timezone":"America/Mexico_City",
    "iso:country":"MX",
    "name:ceb_x_preferred":[
        "El Yunque"
    ],
    "name:ita_x_preferred":[
        "El Yunque"
    ],
    "name:spa_x_preferred":[
        "El Yunque"
    ],
    "name:swe_x_preferred":[
        "El Yunque"
    ],
    "wof:name":"El Yunque",
    "wof:placetype":"locality",
    "wof:population":6
},
  "geometry": {"coordinates":[-93.28694,16.76667],"type":"Point"}
}