{
  "type": "Feature",
  "properties": {
    "gn:admin1_code":"30.0",
    "gn:admin2_code":"121.0",
    "gn:asciiname":"El Chijolito",
    "gn:country_code":"MX",
    "gn:dem":55,
    "gn:feature_class":"P",
    "gn:feature_code":"PPL",
    "gn:name":"El Chijolito",
    "gn:population":8,
    "gn:timezone":"America/Mexico_City",
    "iso:country":"MX",
    "name:spa_x_preferred":[
        "El Chijolito"
    ],
    "wof:name":"El Chijolito",
    "wof:placetype":"locality",
    "wof:population":8
},
  "geometry": {"coordinates":[-97.95083,21.63778],"type":"Point"}
}