{
  "type": "Feature",
  "properties": {
    "gn:admin1_code":"12.0",
    "gn:admin2_code":"68.0",
    "gn:asciiname":"Huertecillas",
    "gn:country_code":"MX",
    "gn:dem":117,
    "gn:feature_class":"P",
    "gn:feature_code":"PPL",
    "gn:name":"Huertecillas",
    "gn:population":0,
    "gn:timezone":"America/Mexico_City",
    "iso:country":"MX",
    "name:spa_x_preferred":[
        "Huertecillas"
    ],
    "wof:name":"Huertecillas",
    "wof:placetype":"locality"
},
  "geometry": {"coordinates":[-102.11781000000001,18.06645],"type":"Point"}
}