{
  "type": "Feature",
  "properties": {
    "gn:admin1_code":"32",
    "gn:admin2_code":"36.0",
    "gn:asciiname":"Nuevo",
    "gn:country_code":"MX",
    "gn:dem":2024,
    "gn:feature_class":"P",
    "gn:feature_code":"PPL",
    "gn:name":"Nuevo",
    "gn:population":0,
    "gn:timezone":"America/Mexico_City",
    "iso:country":"MX",
    "name:ceb_x_preferred":[
        "Nuevo"
    ],
    "name:deu_x_preferred":[
        "Nuevo"
    ],
    "name:spa_x_preferred":[
        "Nuevo"
    ],
    "name:swe_x_preferred":[
        "Nuevo"
    ],
    "wof:name":"Nuevo",
    "wof:placetype":"locality"
},
  "geometry": {"coordinates":[-102.26667,22.53333],"type":"Point"}
}