{
  "type": "Feature",
  "properties": {
    "gn:admin1_code":"21",
    "gn:admin2_code":"15.0",
    "gn:asciiname":"Ignacio Zaragoza",
    "gn:country_code":"MX",
    "gn:dem":2317,
    "gn:feature_class":"P",
    "gn:feature_code":"PPL",
    "gn:name":"Ignacio Zaragoza",
    "gn:population":732,
    "gn:timezone":"America/Mexico_City",
    "iso:country":"MX",
    "wof:name":"Ignacio Zaragoza",
    "wof:placetype":"locality",
    "wof:population":732
},
  "geometry": {"coordinates":[-98.05944,19.0525],"type":"Point"}
}