{
  "type": "Feature",
  "properties": {
    "gn:admin1_code":"28",
    "gn:admin2_code":"43.0",
    "gn:asciiname":"Los Victorinos",
    "gn:country_code":"MX",
    "gn:dem":92,
    "gn:feature_class":"P",
    "gn:feature_code":"PPL",
    "gn:name":"Los Victorinos",
    "gn:population":0,
    "gn:timezone":"America/Monterrey",
    "iso:country":"MX",
    "name:und_x_variant":[
        "El Ranchito de los Victorinos",
        "Los Victorinos"
    ],
    "wof:name":"Los Victorinos",
    "wof:placetype":"locality"
},
  "geometry": {"coordinates":[-98.97192,22.98217],"type":"Point"}
}