{
  "type": "Feature",
  "properties": {
    "gn:admin1_code":"14",
    "gn:admin2_code":"120.0",
    "gn:asciiname":"Campo Real",
    "gn:country_code":"MX",
    "gn:dem":1600,
    "gn:feature_class":"P",
    "gn:feature_code":"PPL",
    "gn:name":"Campo Real",
    "gn:population":2017,
    "gn:timezone":"America/Mexico_City",
    "iso:country":"MX",
    "name:ara_x_preferred":[
        "\u0643\u0627\u0645\u0628\u0648 \u0631\u064a\u0627\u0644"
    ],
    "name:cat_x_preferred":[
        "Campo Real"
    ],
    "name:ceb_x_preferred":[
        "Campo Real"
    ],
    "name:eus_x_preferred":[
        "Campo Real"
    ],
    "name:fra_x_preferred":[
        "Campo Real"
    ],
    "name:hun_x_preferred":[
        "Campo Real"
    ],
    "name:hye_x_preferred":[
        "\u053f\u0561\u0574\u057a\u0578 \u054c\u0565\u0561\u056c"
    ],
    "name:ita_x_preferred":[
        "Campo Real"
    ],
    "name:ltz_x_preferred":[
        "Campo Real"
    ],
    "name:msa_x_preferred":[
        "Campo Real"
    ],
    "name:nld_x_preferred":[
        "Campo Real"
    ],
    "name:oci_x_preferred":[
        "Campo Real"
    ],
    "name:pol_x_preferred":[
        "Campo Real"
    ],
    "name:por_x_preferred":[
        "Campo Real"
    ],
    "name:rus_x_preferred":[
        "\u041a\u0430\u043c\u043f\u043e-\u0420\u0435\u0430\u043b\u044c"
    ],
    "name:spa_x_preferred":[
        "Campo Real"
    ],
    "name:swe_x_preferred":[
        "Campo Real"
    ],
    "name:ukr_x_preferred":[
        "\u041a\u0430\u043c\u043f\u043e-\u0420\u0435\u0430\u043b\u044c"
    ],
    "name:uzb_x_preferred":[
        "Campo Real"
    ],
    "name:vie_x_preferred":[
        "Campo Real"
    ],
    "name:war_x_preferred":[
        "Campo Real"
    ],
    "name:zho_x_preferred":[
        "\u574e\u6ce2\u96f7\u4e9a\u5c14"
    ],
    "wof:name":"Campo Real",
    "wof:placetype":"locality",
    "wof:population":2017
},
  "geometry": {"coordinates":[-103.44306,20.78722],"type":"Point"}
}