{
  "type": "Feature",
  "properties": {
    "gn:admin1_code":"14",
    "gn:admin2_code":"120.0",
    "gn:asciiname":"Campo Real",
    "gn:country_code":"MX",
    "gn:dem":1600,
    "gn:feature_class":"P",
    "gn:feature_code":"PPL",
    "gn:name":"Campo Real",
    "gn:population":2017,
    "gn:timezone":"America/Mexico_City",
    "iso:country":"MX",
    "wof:name":"Campo Real",
    "wof:placetype":"locality",
    "wof:population":2017
},
  "geometry": {"coordinates":[-103.44306,20.78722],"type":"Point"}
}