{
  "type": "Feature",
  "properties": {
    "gn:admin1_code":"6",
    "gn:admin2_code":"65",
    "gn:asciiname":"Mesa de la Barranca (El Polvorin)",
    "gn:country_code":"MX",
    "gn:dem":2257,
    "gn:feature_class":"P",
    "gn:feature_code":"PPL",
    "gn:name":"Mesa de la Barranca (El Polvor\u00edn)",
    "gn:population":28,
    "gn:timezone":"America/Chihuahua",
    "iso:country":"MX",
    "name:und_x_variant":[
        "Mesa de la Barranca (El Polvor\u00edn)"
    ],
    "wof:name":"Mesa de la Barranca (El Polvorin)",
    "wof:placetype":"locality",
    "wof:population":28
},
  "geometry": {"coordinates":[-107.83881,27.52048],"type":"Point"}
}