{
  "type": "Feature",
  "properties": {
    "gn:admin1_code":"20",
    "gn:admin2_code":"182",
    "gn:asciiname":"Cerro Ardilla",
    "gn:country_code":"MX",
    "gn:dem":1128,
    "gn:feature_class":"P",
    "gn:feature_code":"PPL",
    "gn:name":"Cerro Ardilla",
    "gn:population":13,
    "gn:timezone":"America/Mexico_City",
    "iso:country":"MX",
    "wof:name":"Cerro Ardilla",
    "wof:placetype":"locality",
    "wof:population":13
},
  "geometry": {"coordinates":[-96.58417,17.87972000000001],"type":"Point"}
}