{
  "type": "Feature",
  "properties": {
    "gn:admin1_code":"29",
    "gn:admin2_code":"55.0",
    "gn:asciiname":"Las Canadas",
    "gn:country_code":"MX",
    "gn:dem":2500,
    "gn:feature_class":"P",
    "gn:feature_code":"PPL",
    "gn:name":"Las Ca\u00f1adas",
    "gn:population":0,
    "gn:timezone":"America/Mexico_City",
    "iso:country":"MX",
    "name:spa_x_preferred":[
        "Las Ca\u00f1adas"
    ],
    "wof:name":"Las Canadas",
    "wof:placetype":"locality"
},
  "geometry": {"coordinates":[-98.24657999999999,19.50402],"type":"Point"}
}