{
  "type": "Feature",
  "properties": {
    "gn:admin1_code":"16",
    "gn:admin2_code":"8.0",
    "gn:asciiname":"La Naranja",
    "gn:country_code":"MX",
    "gn:dem":550,
    "gn:feature_class":"P",
    "gn:feature_code":"PPL",
    "gn:name":"La Naranja",
    "gn:population":71,
    "gn:timezone":"America/Mexico_City",
    "iso:country":"MX",
    "wof:name":"La Naranja",
    "wof:placetype":"locality",
    "wof:population":71
},
  "geometry": {"coordinates":[-103.54694000000001,18.65528],"type":"Point"}
}