{
  "type": "Feature",
  "properties": {
    "gn:admin1_code":"24.0",
    "gn:admin2_code":"55.0",
    "gn:asciiname":"Coahulla",
    "gn:country_code":"MX",
    "gn:dem":1912,
    "gn:feature_class":"P",
    "gn:feature_code":"PPL",
    "gn:name":"Coahulla",
    "gn:population":203,
    "gn:timezone":"America/Mexico_City",
    "iso:country":"MX",
    "name:spa_x_preferred":[
        "Coahulla"
    ],
    "name:spa_x_variant":[
        "Coahuila"
    ],
    "wof:name":"Coahulla",
    "wof:placetype":"locality",
    "wof:population":203
},
  "geometry": {"coordinates":[-100.75089,21.93126],"type":"Point"}
}