{
  "type": "Feature",
  "properties": {
    "gn:admin1_code":"20.0",
    "gn:admin2_code":"327.0",
    "gn:asciiname":"La Gloria",
    "gn:country_code":"MX",
    "gn:dem":31,
    "gn:feature_class":"P",
    "gn:feature_code":"PPL",
    "gn:name":"La Gloria",
    "gn:population":0,
    "gn:timezone":"America/Mexico_City",
    "iso:country":"MX",
    "name:ast_x_preferred":[
        "La Gloria"
    ],
    "name:ceb_x_preferred":[
        "La Gloria"
    ],
    "name:deu_x_preferred":[
        "La Gloria"
    ],
    "name:ita_x_preferred":[
        "La Gloria"
    ],
    "name:nld_x_preferred":[
        "La Gloria"
    ],
    "name:spa_x_preferred":[
        "La Gloria"
    ],
    "name:swe_x_preferred":[
        "La Gloria"
    ],
    "name:vie_x_preferred":[
        "La Gloria"
    ],
    "wof:name":"La Gloria",
    "wof:placetype":"locality"
},
  "geometry": {"coordinates":[-94.23044,16.30285],"type":"Point"}
}