{
  "type": "Feature",
  "properties": {
    "gn:admin1_code":"16",
    "gn:admin2_code":"13",
    "gn:asciiname":"El Timbiriche",
    "gn:country_code":"MX",
    "gn:dem":731,
    "gn:feature_class":"P",
    "gn:feature_code":"PPL",
    "gn:name":"El Timbiriche",
    "gn:population":13,
    "gn:timezone":"America/Mexico_City",
    "iso:country":"MX",
    "wof:name":"El Timbiriche",
    "wof:placetype":"locality",
    "wof:population":13
},
  "geometry": {"coordinates":[-101.06999999999999,19.06917],"type":"Point"}
}