{
  "type": "Feature",
  "properties": {
    "gn:admin1_code":"19",
    "gn:admin2_code":"20.0",
    "gn:asciiname":"La Union",
    "gn:country_code":"MX",
    "gn:dem":192,
    "gn:feature_class":"P",
    "gn:feature_code":"PPL",
    "gn:name":"La Uni\u00f3n",
    "gn:population":18,
    "gn:timezone":"America/Monterrey",
    "iso:country":"MX",
    "name:spa_x_preferred":[
        "La Uni\u00f3n"
    ],
    "wof:name":"La Union",
    "wof:placetype":"locality",
    "wof:population":18
},
  "geometry": {"coordinates":[-98.78722999999999,25.75647],"type":"Point"}
}