{
  "type": "Feature",
  "properties": {
    "gn:admin1_code":"25",
    "gn:admin2_code":"11.0",
    "gn:asciiname":"General Emiliano Zapata",
    "gn:country_code":"MX",
    "gn:dem":8,
    "gn:feature_class":"P",
    "gn:feature_code":"PPL",
    "gn:name":"General Emiliano Zapata",
    "gn:population":75,
    "gn:timezone":"America/Mazatlan",
    "iso:country":"MX",
    "wof:name":"General Emiliano Zapata",
    "wof:placetype":"locality",
    "wof:population":75
},
  "geometry": {"coordinates":[-108.71111000000001,25.52944],"type":"Point"}
}