{
  "type": "Feature",
  "properties": {
    "gn:admin1_code":"30",
    "gn:admin2_code":"204",
    "gn:asciiname":"Ramon Pablo (Ejido Tonala)",
    "gn:country_code":"MX",
    "gn:dem":11,
    "gn:feature_class":"P",
    "gn:feature_code":"PPL",
    "gn:name":"Ram\u00f3n Pablo (Ejido Tonal\u00e1)",
    "gn:population":47,
    "gn:timezone":"America/Mexico_City",
    "iso:country":"MX",
    "name:und_x_variant":[
        "Ram\u00f3n Pablo (Ejido Tonal\u00e1)"
    ],
    "wof:name":"Ramon Pablo (Ejido Tonala)",
    "wof:placetype":"locality",
    "wof:population":47
},
  "geometry": {"coordinates":[-94.14694,18.19667],"type":"Point"}
}