{
  "type": "Feature",
  "properties": {
    "gn:admin1_code":"25",
    "gn:admin2_code":"1.0",
    "gn:asciiname":"Oro Nuevo",
    "gn:country_code":"MX",
    "gn:dem":13,
    "gn:feature_class":"P",
    "gn:feature_code":"PPL",
    "gn:name":"Oro Nuevo",
    "gn:population":0,
    "gn:timezone":"America/Mazatlan",
    "iso:country":"MX",
    "name:spa_x_preferred":[
        "Oro Nuevo"
    ],
    "wof:name":"Oro Nuevo",
    "wof:placetype":"locality"
},
  "geometry": {"coordinates":[-109.06874999999999,25.92346],"type":"Point"}
}