{
  "type": "Feature",
  "properties": {
    "gn:admin1_code":"30.0",
    "gn:admin2_code":"161.0",
    "gn:asciiname":"Rancho Cuco",
    "gn:country_code":"MX",
    "gn:dem":48,
    "gn:feature_class":"P",
    "gn:feature_code":"PPL",
    "gn:name":"Rancho Cuco",
    "gn:population":0,
    "gn:timezone":"America/Mexico_City",
    "iso:country":"MX",
    "name:spa_x_preferred":[
        "Rancho Cuco"
    ],
    "name:spa_x_variant":[
        "Fort\u00edn de las Flores"
    ],
    "wof:name":"Rancho Cuco",
    "wof:placetype":"locality"
},
  "geometry": {"coordinates":[-98.35155,21.57369],"type":"Point"}
}