{
  "type": "Feature",
  "properties": {
    "gn:admin1_code":"14",
    "gn:admin2_code":"93.0",
    "gn:asciiname":"Gaviotas",
    "gn:country_code":"MX",
    "gn:dem":1750,
    "gn:feature_class":"P",
    "gn:feature_code":"PPL",
    "gn:name":"Gaviotas",
    "gn:population":9,
    "gn:timezone":"America/Mexico_City",
    "iso:country":"MX",
    "name:deu_x_preferred":[
        "Gaviotas"
    ],
    "name:nld_x_preferred":[
        "Gaviotas"
    ],
    "name:nor_x_preferred":[
        "Gaviotas"
    ],
    "name:por_x_preferred":[
        "Gaviotas"
    ],
    "wof:name":"Gaviotas",
    "wof:placetype":"locality",
    "wof:population":9
},
  "geometry": {"coordinates":[-102.85417,20.69722],"type":"Point"}
}