{
  "type": "Feature",
  "properties": {
    "gn:admin1_code":"21",
    "gn:admin2_code":"53.0",
    "gn:asciiname":"Barrancas",
    "gn:country_code":"MX",
    "gn:dem":2426,
    "gn:feature_class":"P",
    "gn:feature_code":"PPL",
    "gn:name":"Barrancas",
    "gn:population":0,
    "gn:timezone":"America/Mexico_City",
    "iso:country":"MX",
    "wof:name":"Barrancas",
    "wof:placetype":"locality"
},
  "geometry": {"coordinates":[-98.05,19.88333],"type":"Point"}
}