{
  "type": "Feature",
  "properties": {
    "gn:admin1_code":"5",
    "gn:admin2_code":"99",
    "gn:asciiname":"Plan Rio Azul",
    "gn:country_code":"MX",
    "gn:dem":739,
    "gn:feature_class":"P",
    "gn:feature_code":"PPL",
    "gn:name":"Plan R\u00edo Azul",
    "gn:population":32,
    "gn:timezone":"America/Mexico_City",
    "iso:country":"MX",
    "name:und_x_variant":[
        "Plan R\u00edo Azul"
    ],
    "wof:name":"Plan Rio Azul",
    "wof:placetype":"locality",
    "wof:population":32
},
  "geometry": {"coordinates":[-92.08694,16.03167],"type":"Point"}
}