{
  "type": "Feature",
  "properties": {
    "gn:admin1_code":"3.0",
    "gn:admin2_code":"3.0",
    "gn:asciiname":"Agua de San Antonio",
    "gn:country_code":"MX",
    "gn:dem":837,
    "gn:feature_class":"P",
    "gn:feature_code":"PPL",
    "gn:name":"Agua de San Antonio",
    "gn:population":3,
    "gn:timezone":"America/Mazatlan",
    "iso:country":"MX",
    "wof:name":"Agua de San Antonio",
    "wof:placetype":"locality",
    "wof:population":3
},
  "geometry": {"coordinates":[-109.94359,23.68611],"type":"Point"}
}