{
  "type": "Feature",
  "properties": {
    "gn:admin1_code":"10",
    "gn:admin2_code":"14.0",
    "gn:asciiname":"Agua Hedionda",
    "gn:country_code":"MX",
    "gn:dem":1998,
    "gn:feature_class":"P",
    "gn:feature_code":"PPL",
    "gn:name":"Agua Hedionda",
    "gn:population":0,
    "gn:timezone":"America/Monterrey",
    "iso:country":"MX",
    "name:ceb_x_preferred":[
        "Agua Hedionda"
    ],
    "name:spa_x_preferred":[
        "Agua Hedionda"
    ],
    "name:swe_x_preferred":[
        "Agua Hedionda"
    ],
    "wof:name":"Agua Hedionda",
    "wof:placetype":"locality"
},
  "geometry": {"coordinates":[-104.48692,23.28748],"type":"Point"}
}