{
  "type": "Feature",
  "properties": {
    "gn:admin1_code":"22.0",
    "gn:admin2_code":"16.0",
    "gn:asciiname":"Cerritos",
    "gn:country_code":"MX",
    "gn:dem":2038,
    "gn:feature_class":"P",
    "gn:feature_code":"PPL",
    "gn:name":"Cerritos",
    "gn:population":0,
    "gn:timezone":"America/Mexico_City",
    "iso:country":"MX",
    "name:spa_x_preferred":[
        "Cerritos"
    ],
    "wof:name":"Cerritos",
    "wof:placetype":"locality"
},
  "geometry": {"coordinates":[-100.08284,20.36273],"type":"Point"}
}