{
  "type": "Feature",
  "properties": {
    "gn:admin1_code":"10",
    "gn:admin2_code":"14",
    "gn:asciiname":"El Sombrero",
    "gn:country_code":"MX",
    "gn:dem":1564,
    "gn:feature_class":"P",
    "gn:feature_code":"PPL",
    "gn:name":"El Sombrero",
    "gn:population":22,
    "gn:timezone":"America/Monterrey",
    "iso:country":"MX",
    "wof:name":"El Sombrero",
    "wof:placetype":"locality",
    "wof:population":22
},
  "geometry": {"coordinates":[-104.4169,22.83448],"type":"Point"}
}