{
  "type": "Feature",
  "properties": {
    "gn:admin1_code":"26",
    "gn:admin2_code":"50.0",
    "gn:asciiname":"Puerto Cajon",
    "gn:country_code":"MX",
    "gn:dem":657,
    "gn:feature_class":"P",
    "gn:feature_code":"PPL",
    "gn:name":"Puerto Caj\u00f3n",
    "gn:population":0,
    "gn:timezone":"America/Hermosillo",
    "iso:country":"MX",
    "wof:name":"Puerto Cajon",
    "wof:placetype":"locality"
},
  "geometry": {"coordinates":[-110.56667,29.61667000000001],"type":"Point"}
}