{
  "type": "Feature",
  "properties": {
    "gn:admin1_code":"14",
    "gn:admin2_code":"29.0",
    "gn:asciiname":"La Laguna Grande",
    "gn:country_code":"MX",
    "gn:dem":1778,
    "gn:feature_class":"P",
    "gn:feature_code":"PPL",
    "gn:name":"La Laguna Grande",
    "gn:population":129,
    "gn:timezone":"America/Mexico_City",
    "iso:country":"MX",
    "wof:name":"La Laguna Grande",
    "wof:placetype":"locality",
    "wof:population":129
},
  "geometry": {"coordinates":[-103.06111,20.93611],"type":"Point"}
}