{
  "type": "Feature",
  "properties": {
    "gn:admin1_code":"5",
    "gn:admin2_code":"13.0",
    "gn:asciiname":"Palma Real",
    "gn:country_code":"MX",
    "gn:dem":1140,
    "gn:feature_class":"P",
    "gn:feature_code":"PPL",
    "gn:name":"Palma Real",
    "gn:population":79,
    "gn:timezone":"America/Mexico_City",
    "iso:country":"MX",
    "wof:name":"Palma Real",
    "wof:placetype":"locality",
    "wof:population":79
},
  "geometry": {"coordinates":[-93.04944,17.01778],"type":"Point"}
}