{
  "type": "Feature",
  "properties": {
    "gn:admin1_code":"12.0",
    "gn:asciiname":"Barrio el Barrero",
    "gn:country_code":"MX",
    "gn:dem":349,
    "gn:feature_class":"P",
    "gn:feature_code":"PPL",
    "gn:name":"Barrio el Barrero",
    "gn:population":0,
    "gn:timezone":"America/Mexico_City",
    "iso:country":"MX",
    "name:spa_x_preferred":[
        "Barrio el Barrero"
    ],
    "wof:name":"Barrio el Barrero",
    "wof:placetype":"locality"
},
  "geometry": {"coordinates":[-98.75024000000001,16.8946],"type":"Point"}
}