{
  "type": "Feature",
  "properties": {
    "gn:admin1_code":"11",
    "gn:admin2_code":"30",
    "gn:asciiname":"Los Lara (La Noria de Juan Vazquez)",
    "gn:country_code":"MX",
    "gn:dem":1849,
    "gn:feature_class":"P",
    "gn:feature_code":"PPL",
    "gn:name":"Los Lara (La Noria de Juan V\u00e1zquez)",
    "gn:population":36,
    "gn:timezone":"America/Mexico_City",
    "iso:country":"MX",
    "name:und_x_variant":[
        "Los Lara (La Noria de Juan V\u00e1zquez)"
    ],
    "wof:name":"Los Lara (La Noria de Juan Vazquez)",
    "wof:placetype":"locality",
    "wof:population":36
},
  "geometry": {"coordinates":[-101.01778,21.72972],"type":"Point"}
}