{
  "type": "Feature",
  "properties": {
    "gn:admin1_code":"24.0",
    "gn:admin2_code":"32.0",
    "gn:asciiname":"El Potrero de San Isidro",
    "gn:country_code":"MX",
    "gn:dem":1911,
    "gn:feature_class":"P",
    "gn:feature_code":"PPL",
    "gn:name":"El Potrero de San Isidro",
    "gn:population":0,
    "gn:timezone":"America/Mexico_City",
    "iso:country":"MX",
    "name:spa_x_preferred":[
        "El Potrero de San Isidro"
    ],
    "name:und_x_variant":[
        "Portero",
        "El Potrero"
    ],
    "wof:name":"El Potrero de San Isidro",
    "wof:placetype":"locality"
},
  "geometry": {"coordinates":[-100.49751999999999,21.9105],"type":"Point"}
}