{
  "type": "Feature",
  "properties": {
    "gn:admin1_code":"6.0",
    "gn:admin2_code":"62.0",
    "gn:asciiname":"El Indio",
    "gn:cc2":"MX",
    "gn:country_code":"MX",
    "gn:dem":1180,
    "gn:feature_class":"P",
    "gn:feature_code":"PPL",
    "gn:name":"El Indio",
    "gn:population":290,
    "gn:timezone":"America/Chihuahua",
    "iso:country":"MX",
    "name:und_x_variant":[
        "Labor del Indio",
        "El Indio"
    ],
    "wof:name":"El Indio",
    "wof:placetype":"locality",
    "wof:population":290
},
  "geometry": {"coordinates":[-105.32056,28.09056],"type":"Point"}
}