{
  "type": "Feature",
  "properties": {
    "gn:admin1_code":"23.0",
    "gn:admin2_code":"4.0",
    "gn:asciiname":"Pavo",
    "gn:country_code":"MX",
    "gn:dem":5,
    "gn:feature_class":"P",
    "gn:feature_code":"PPL",
    "gn:name":"Pavo",
    "gn:population":0,
    "gn:timezone":"America/Cancun",
    "iso:country":"MX",
    "name:arg_x_preferred":[
        "Pavo"
    ],
    "name:ceb_x_preferred":[
        "Pavo"
    ],
    "name:ces_x_preferred":[
        "Pavo"
    ],
    "name:deu_x_preferred":[
        "Pavo"
    ],
    "name:epo_x_preferred":[
        "Pavo"
    ],
    "name:est_x_preferred":[
        "Pavo"
    ],
    "name:glg_x_preferred":[
        "Pavo"
    ],
    "name:hrv_x_preferred":[
        "Pavo"
    ],
    "name:hun_x_preferred":[
        "P\u00e1va"
    ],
    "name:lat_x_preferred":[
        "Pavo"
    ],
    "name:lav_x_preferred":[
        "Pavo"
    ],
    "name:nld_x_preferred":[
        "Pavo"
    ],
    "name:por_x_preferred":[
        "Pavo"
    ],
    "name:spa_x_preferred":[
        "Pavo"
    ],
    "name:swe_x_preferred":[
        "Pavo"
    ],
    "name:tha_x_preferred":[
        "Pavo"
    ],
    "name:tur_x_preferred":[
        "Pavo"
    ],
    "wof:name":"Pavo",
    "wof:placetype":"locality"
},
  "geometry": {"coordinates":[-87.61369999999999,18.96626],"type":"Point"}
}