{
  "type": "Feature",
  "properties": {
    "gn:admin1_code":"3",
    "gn:admin2_code":"1.0",
    "gn:asciiname":"La Vinorama",
    "gn:country_code":"MX",
    "gn:dem":794,
    "gn:feature_class":"P",
    "gn:feature_code":"PPL",
    "gn:name":"La Vinorama",
    "gn:population":0,
    "gn:timezone":"America/Mazatlan",
    "iso:country":"MX",
    "name:spa_x_preferred":[
        "La Vinorama"
    ],
    "wof:name":"La Vinorama",
    "wof:placetype":"locality"
},
  "geometry": {"coordinates":[-112.16750999999999,26.48984],"type":"Point"}
}