{
  "type": "Feature",
  "properties": {
    "gn:admin1_code":"32",
    "gn:admin2_code":"54.0",
    "gn:asciiname":"Los Lopez (El Pico)",
    "gn:country_code":"MX",
    "gn:dem":2132,
    "gn:feature_class":"P",
    "gn:feature_code":"PPL",
    "gn:name":"Los L\u00f3pez (El Pico)",
    "gn:population":6,
    "gn:timezone":"America/Mexico_City",
    "iso:country":"MX",
    "name:und_x_variant":[
        "Los L\u00f3pez (El Pico)"
    ],
    "wof:name":"Los Lopez (El Pico)",
    "wof:placetype":"locality",
    "wof:population":6
},
  "geometry": {"coordinates":[-101.76056,22.41861],"type":"Point"}
}