{
  "type": "Feature",
  "properties": {
    "gn:admin1_code":"14",
    "gn:admin2_code":"105.0",
    "gn:asciiname":"La Isla",
    "gn:country_code":"MX",
    "gn:dem":1575,
    "gn:feature_class":"P",
    "gn:feature_code":"PPL",
    "gn:name":"La Isla",
    "gn:population":191,
    "gn:timezone":"America/Mexico_City",
    "iso:country":"MX",
    "wof:name":"La Isla",
    "wof:placetype":"locality",
    "wof:population":191
},
  "geometry": {"coordinates":[-102.74889,20.59611],"type":"Point"}
}