{
  "type": "Feature",
  "properties": {
    "gn:admin1_code":"14",
    "gn:admin2_code":"93",
    "gn:asciiname":"La Revoltura",
    "gn:country_code":"MX",
    "gn:dem":2063,
    "gn:feature_class":"P",
    "gn:feature_code":"PPL",
    "gn:name":"La Revoltura",
    "gn:population":18,
    "gn:timezone":"America/Mexico_City",
    "iso:country":"MX",
    "wof:name":"La Revoltura",
    "wof:placetype":"locality",
    "wof:population":18
},
  "geometry": {"coordinates":[-102.52583,20.84306],"type":"Point"}
}