{
  "type": "Feature",
  "properties": {
    "gn:admin1_code":"31",
    "gn:admin2_code":"67.0",
    "gn:asciiname":"Xucu",
    "gn:country_code":"MX",
    "gn:dem":16,
    "gn:feature_class":"P",
    "gn:feature_code":"PPL",
    "gn:name":"Xucu",
    "gn:population":0,
    "gn:timezone":"America/Merida",
    "iso:country":"MX",
    "name:spa_x_preferred":[
        "Xucu"
    ],
    "name:spa_x_variant":[
        "Xuk\u00fa"
    ],
    "wof:name":"Xucu",
    "wof:placetype":"locality"
},
  "geometry": {"coordinates":[-89.31325,20.80268],"type":"Point"}
}