{
  "type": "Feature",
  "properties": {
    "gn:admin1_code":"26",
    "gn:admin2_code":"17.0",
    "gn:asciiname":"El Pinito",
    "gn:country_code":"MX",
    "gn:dem":223,
    "gn:feature_class":"P",
    "gn:feature_code":"PPL",
    "gn:name":"El Pinito",
    "gn:population":5,
    "gn:timezone":"America/Hermosillo",
    "iso:country":"MX",
    "wof:name":"El Pinito",
    "wof:placetype":"locality",
    "wof:population":5
},
  "geometry": {"coordinates":[-112.33333,30.71944],"type":"Point"}
}