{
  "type": "Feature",
  "properties": {
    "gn:admin1_code":"26.0",
    "gn:admin2_code":"69.0",
    "gn:asciiname":"El Bano",
    "gn:country_code":"MX",
    "gn:dem":1565,
    "gn:feature_class":"P",
    "gn:feature_code":"PPL",
    "gn:name":"El Ba\u00f1o",
    "gn:population":0,
    "gn:timezone":"America/Hermosillo",
    "iso:country":"MX",
    "name:spa_x_preferred":[
        "El Ba\u00f1o"
    ],
    "wof:name":"El Bano",
    "wof:placetype":"locality"
},
  "geometry": {"coordinates":[-108.71602,28.44484000000001],"type":"Point"}
}