{
  "type": "Feature",
  "properties": {
    "gn:admin1_code":"7",
    "gn:admin2_code":"31.0",
    "gn:asciiname":"El Ranchito los Rodriguez",
    "gn:country_code":"MX",
    "gn:dem":723,
    "gn:feature_class":"P",
    "gn:feature_code":"PPL",
    "gn:name":"El Ranchito los Rodr\u00edguez",
    "gn:population":4,
    "gn:timezone":"America/Monterrey",
    "iso:country":"MX",
    "name:und_x_variant":[
        "El Ranchito los Rodr\u00edguez"
    ],
    "wof:name":"El Ranchito los Rodriguez",
    "wof:placetype":"locality",
    "wof:population":4
},
  "geometry": {"coordinates":[-101.72204000000001,27.40887],"type":"Point"}
}