{
  "type": "Feature",
  "properties": {
    "gn:admin1_code":"25",
    "gn:asciiname":"El Renguito",
    "gn:country_code":"MX",
    "gn:dem":1381,
    "gn:feature_class":"P",
    "gn:feature_code":"PPL",
    "gn:name":"El Renguito",
    "gn:population":0,
    "gn:timezone":"America/Mazatlan",
    "iso:country":"MX",
    "name:spa_x_preferred":[
        "El Renguito"
    ],
    "wof:name":"El Renguito",
    "wof:placetype":"locality"
},
  "geometry": {"coordinates":[-107.89573,26.44865],"type":"Point"}
}