{
  "type": "Feature",
  "properties": {
    "gn:admin1_code":"5.0",
    "gn:admin2_code":"17.0",
    "gn:asciiname":"Plan de Guadalupe",
    "gn:country_code":"MX",
    "gn:dem":934,
    "gn:feature_class":"P",
    "gn:feature_code":"PPL",
    "gn:name":"Plan de Guadalupe",
    "gn:population":0,
    "gn:timezone":"America/Mexico_City",
    "iso:country":"MX",
    "name:spa_x_preferred":[
        "Plan de Guadalupe"
    ],
    "wof:name":"Plan de Guadalupe",
    "wof:placetype":"locality"
},
  "geometry": {"coordinates":[-93.96787,16.80891],"type":"Point"}
}