{
  "type": "Feature",
  "properties": {
    "gn:admin1_code":"5.0",
    "gn:admin2_code":"23.0",
    "gn:asciiname":"Botatulan",
    "gn:country_code":"MX",
    "gn:dem":2322,
    "gn:feature_class":"P",
    "gn:feature_code":"PPL",
    "gn:name":"Botatul\u00e1n",
    "gn:population":0,
    "gn:timezone":"America/Mexico_City",
    "iso:country":"MX",
    "name:spa_x_preferred":[
        "Jutzbilo"
    ],
    "name:spa_x_variant":[
        "Botatul\u00e1n"
    ],
    "wof:name":"Botatulan",
    "wof:placetype":"locality"
},
  "geometry": {"coordinates":[-92.72583,16.82501],"type":"Point"}
}