{
  "type": "Feature",
  "properties": {
    "gn:admin1_code":"10",
    "gn:admin2_code":"35.0",
    "gn:asciiname":"Las Piedronas",
    "gn:country_code":"MX",
    "gn:dem":2180,
    "gn:feature_class":"P",
    "gn:feature_code":"PPL",
    "gn:name":"Las Piedronas",
    "gn:population":5,
    "gn:timezone":"America/Monterrey",
    "iso:country":"MX",
    "wof:name":"Las Piedronas",
    "wof:placetype":"locality",
    "wof:population":5
},
  "geometry": {"coordinates":[-106.63028,25.44472],"type":"Point"}
}