{
  "type": "Feature",
  "properties": {
    "gn:admin1_code":"14",
    "gn:admin2_code":"81.0",
    "gn:asciiname":"Las Lajas",
    "gn:country_code":"MX",
    "gn:dem":1744,
    "gn:feature_class":"P",
    "gn:feature_code":"PPL",
    "gn:name":"Las Lajas",
    "gn:population":79,
    "gn:timezone":"America/Mexico_City",
    "iso:country":"MX",
    "wof:name":"Las Lajas",
    "wof:placetype":"locality",
    "wof:population":79
},
  "geometry": {"coordinates":[-103.23139,22.24389],"type":"Point"}
}