{
  "type": "Feature",
  "properties": {
    "gn:admin1_code":"30",
    "gn:admin2_code":"61.0",
    "gn:asciiname":"Pueblo Viejo",
    "gn:country_code":"MX",
    "gn:dem":47,
    "gn:feature_class":"P",
    "gn:feature_code":"PPL",
    "gn:name":"Pueblo Viejo",
    "gn:population":0,
    "gn:timezone":"America/Mexico_City",
    "iso:country":"MX",
    "wof:name":"Pueblo Viejo",
    "wof:placetype":"locality"
},
  "geometry": {"coordinates":[-93.78053,17.39353],"type":"Point"}
}