{
  "type": "Feature",
  "properties": {
    "gn:admin1_code":"18.0",
    "gn:asciiname":"Huerta Vieja",
    "gn:country_code":"MX",
    "gn:dem":1019,
    "gn:feature_class":"P",
    "gn:feature_code":"PPL",
    "gn:name":"Huerta Vieja",
    "gn:population":0,
    "gn:timezone":"America/Mazatlan",
    "iso:country":"MX",
    "wof:name":"Huerta Vieja",
    "wof:placetype":"locality"
},
  "geometry": {"coordinates":[-104.32142,20.83746],"type":"Point"}
}