{
  "type": "Feature",
  "properties": {
    "gn:admin1_code":"7.0",
    "gn:admin2_code":"2.0",
    "gn:asciiname":"Venustiano Carranza",
    "gn:country_code":"MX",
    "gn:dem":1033,
    "gn:feature_class":"P",
    "gn:feature_code":"PPL",
    "gn:name":"Venustiano Carranza",
    "gn:population":25,
    "gn:timezone":"America/Matamoros",
    "iso:country":"MX",
    "name:ara_x_preferred":[
        "\u0641\u064a\u0646\u0648\u0633\u062a\u064a\u0627\u0646\u0648 \u0643\u0627\u0631\u0627\u0646\u0633\u0627"
    ],
    "name:ast_x_preferred":[
        "Venustiano Carranza"
    ],
    "name:cat_x_preferred":[
        "Venustiano Carranza"
    ],
    "name:dan_x_preferred":[
        "Venustiano Carranza"
    ],
    "name:deu_x_preferred":[
        "Venustiano Carranza"
    ],
    "name:epo_x_preferred":[
        "Venustiano Carranza"
    ],
    "name:eus_x_preferred":[
        "Venustiano Carranza"
    ],
    "name:fas_x_preferred":[
        "\u0648\u0646\u0648\u0633\u062a\u06cc\u0627\u0646\u0648 \u06a9\u0627\u0631\u0622\u0646\u0633\u0627"
    ],
    "name:fin_x_preferred":[
        "Venustiano Carranza"
    ],
    "name:fra_x_preferred":[
        "Venustiano Carranza"
    ],
    "name:heb_x_preferred":[
        "\u05d5\u05e0\u05d5\u05e1\u05d8\u05d9\u05d0\u05e0\u05d5 \u05e7\u05d0\u05e8\u05d0\u05e0\u05e1\u05d4"
    ],
    "name:hrv_x_preferred":[
        "Venustiano Carranza"
    ],
    "name:hun_x_preferred":[
        "Venustiano Carranza"
    ],
    "name:hye_x_preferred":[
        "\u054e\u0565\u0576\u0578\u0582\u057d\u057f\u056b\u0561\u0576\u0578 \u053f\u0561\u057c\u0561\u0576\u057d\u0561"
    ],
    "name:ido_x_preferred":[
        "Venustiano Carranza"
    ],
    "name:isl_x_preferred":[
        "Venustiano Carranza"
    ],
    "name:ita_x_preferred":[
        "Venustiano Carranza"
    ],
    "name:jpn_x_preferred":[
        "\u30d9\u30cc\u30b9\u30c6\u30a3\u30a2\u30fc\u30ce\u30fb\u30ab\u30e9\u30f3\u30b5"
    ],
    "name:kor_x_preferred":[
        "\ubca0\ub204\uc2a4\ud2f0\uc544\ub178 \uce74\ub780\uc0ac"
    ],
    "name:lat_x_preferred":[
        "Venustianus Carranza"
    ],
    "name:nld_x_preferred":[
        "Venustiano Carranza"
    ],
    "name:nor_x_preferred":[
        "Venustiano Carranza"
    ],
    "name:pol_x_preferred":[
        "Venustiano Carranza"
    ],
    "name:por_x_preferred":[
        "Venustiano Carranza"
    ],
    "name:que_x_preferred":[
        "Venustiano Carranza"
    ],
    "name:rus_x_preferred":[
        "\u041a\u0430\u0440\u0440\u0430\u043d\u0441\u0430"
    ],
    "name:sco_x_preferred":[
        "Venustiano Carranza"
    ],
    "name:slv_x_preferred":[
        "Venustiano Carranza"
    ],
    "name:spa_x_preferred":[
        "Venustiano Carranza"
    ],
    "name:srp_x_preferred":[
        "\u0412\u0435\u043d\u0443\u0441\u0442\u0438\u0458\u0430\u043d\u043e \u041a\u0430\u0440\u0430\u043d\u0437\u0430"
    ],
    "name:swe_x_preferred":[
        "Venustiano Carranza"
    ],
    "name:vie_x_preferred":[
        "Venustiano Carranza"
    ],
    "name:yor_x_preferred":[
        "Venustiano Carranza"
    ],
    "name:zho_x_preferred":[
        "\u8d1d\u52aa\u65af\u8482\u4e9a\u8bfa\u00b7\u5361\u5170\u8428"
    ],
    "wof:name":"Venustiano Carranza",
    "wof:placetype":"locality",
    "wof:population":25
},
  "geometry": {"coordinates":[-102.40736,29.19882],"type":"Point"}
}