{
  "type": "Feature",
  "properties": {
    "gn:admin1_code":"30",
    "gn:admin2_code":"49.0",
    "gn:asciiname":"El Nanche",
    "gn:country_code":"MX",
    "gn:dem":66,
    "gn:feature_class":"P",
    "gn:feature_code":"PPL",
    "gn:name":"El Nanche",
    "gn:population":0,
    "gn:timezone":"America/Mexico_City",
    "iso:country":"MX",
    "name:spa_x_preferred":[
        "El Nanche"
    ],
    "wof:name":"El Nanche",
    "wof:placetype":"locality"
},
  "geometry": {"coordinates":[-96.35137,18.87657],"type":"Point"}
}