{
  "type": "Feature",
  "properties": {
    "gn:admin1_code":"14.0",
    "gn:admin2_code":"61.0",
    "gn:asciiname":"La Ceja",
    "gn:country_code":"MX",
    "gn:dem":2286,
    "gn:feature_class":"P",
    "gn:feature_code":"PPL",
    "gn:name":"La Ceja",
    "gn:population":0,
    "gn:timezone":"America/Mexico_City",
    "iso:country":"MX",
    "name:ceb_x_preferred":[
        "La Ceja"
    ],
    "name:spa_x_preferred":[
        "La Ceja"
    ],
    "name:swe_x_preferred":[
        "La Ceja"
    ],
    "wof:name":"La Ceja",
    "wof:placetype":"locality"
},
  "geometry": {"coordinates":[-104.00967,22.29611],"type":"Point"}
}