{
  "type": "Feature",
  "properties": {
    "gn:admin1_code":"29",
    "gn:admin2_code":"34.0",
    "gn:asciiname":"Las Casitas",
    "gn:country_code":"MX",
    "gn:dem":2687,
    "gn:feature_class":"P",
    "gn:feature_code":"PPL",
    "gn:name":"Las Casitas",
    "gn:population":0,
    "gn:timezone":"America/Mexico_City",
    "iso:country":"MX",
    "name:spa_x_preferred":[
        "Las Casitas"
    ],
    "name:spa_x_variant":[
        "La Pera"
    ],
    "wof:name":"Las Casitas",
    "wof:placetype":"locality"
},
  "geometry": {"coordinates":[-98.08253000000001,19.59977],"type":"Point"}
}