{
  "type": "Feature",
  "properties": {
    "gn:admin1_code":"14",
    "gn:admin2_code":"8",
    "gn:asciiname":"Rancho Guadalupe",
    "gn:country_code":"MX",
    "gn:dem":2144,
    "gn:feature_class":"P",
    "gn:feature_code":"PPL",
    "gn:name":"Rancho Guadalupe",
    "gn:population":51,
    "gn:timezone":"America/Mexico_City",
    "iso:country":"MX",
    "wof:name":"Rancho Guadalupe",
    "wof:placetype":"locality",
    "wof:population":51
},
  "geometry": {"coordinates":[-102.27639000000001,20.68222],"type":"Point"}
}