{
  "type": "Feature",
  "properties": {
    "gn:admin1_code":"25",
    "gn:admin2_code":"17",
    "gn:asciiname":"El Limon",
    "gn:country_code":"MX",
    "gn:dem":758,
    "gn:feature_class":"P",
    "gn:feature_code":"PPL",
    "gn:name":"El Lim\u00f3n",
    "gn:population":12,
    "gn:timezone":"America/Mazatlan",
    "iso:country":"MX",
    "name:und_x_variant":[
        "El Lim\u00f3n"
    ],
    "wof:name":"El Limon",
    "wof:placetype":"locality",
    "wof:population":12
},
  "geometry": {"coordinates":[-107.56292000000001,26.11717],"type":"Point"}
}