{
  "type": "Feature",
  "properties": {
    "gn:admin1_code":"6",
    "gn:admin2_code":"27.0",
    "gn:asciiname":"Sayaguachi",
    "gn:country_code":"MX",
    "gn:dem":2368,
    "gn:feature_class":"P",
    "gn:feature_code":"PPL",
    "gn:name":"Sayaguachi",
    "gn:population":0,
    "gn:timezone":"America/Chihuahua",
    "iso:country":"MX",
    "wof:name":"Sayaguachi",
    "wof:placetype":"locality"
},
  "geometry": {"coordinates":[-106.87769,26.72334],"type":"Point"}
}