{
  "type": "Feature",
  "properties": {
    "gn:admin1_code":"6.0",
    "gn:admin2_code":"47.0",
    "gn:asciiname":"El Piloncillo",
    "gn:country_code":"MX",
    "gn:dem":1178,
    "gn:feature_class":"P",
    "gn:feature_code":"PPL",
    "gn:name":"El Piloncillo",
    "gn:population":0,
    "gn:timezone":"America/Chihuahua",
    "iso:country":"MX",
    "name:und_x_variant":[
        "Piloncillo",
        "El Piloncillo"
    ],
    "wof:name":"El Piloncillo",
    "wof:placetype":"locality"
},
  "geometry": {"coordinates":[-108.74943,28.11682],"type":"Point"}
}