{
  "type": "Feature",
  "properties": {
    "gn:admin1_code":"31",
    "gn:admin2_code":"33.0",
    "gn:asciiname":"San Valentin",
    "gn:country_code":"MX",
    "gn:dem":10,
    "gn:feature_class":"P",
    "gn:feature_code":"PPL",
    "gn:name":"San Valent\u00edn",
    "gn:population":0,
    "gn:timezone":"America/Merida",
    "iso:country":"MX",
    "name:spa_x_preferred":[
        "San Valent\u00edn"
    ],
    "wof:name":"San Valentin",
    "wof:placetype":"locality"
},
  "geometry": {"coordinates":[-90.14085,20.52991],"type":"Point"}
}