{
  "type": "Feature",
  "properties": {
    "gn:admin1_code":"6",
    "gn:admin2_code":"27",
    "gn:asciiname":"Bajio del Tascatito",
    "gn:country_code":"MX",
    "gn:dem":2495,
    "gn:feature_class":"P",
    "gn:feature_code":"PPL",
    "gn:name":"Baj\u00edo del Tascatito",
    "gn:population":33,
    "gn:timezone":"America/Chihuahua",
    "iso:country":"MX",
    "name:und_x_variant":[
        "Baj\u00edo del Tascatito"
    ],
    "wof:name":"Bajio del Tascatito",
    "wof:placetype":"locality",
    "wof:population":33
},
  "geometry": {"coordinates":[-107.15376999999999,26.74939],"type":"Point"}
}