{
  "type": "Feature",
  "properties": {
    "gn:admin1_code":"8.0",
    "gn:admin2_code":"7.0",
    "gn:asciiname":"Los Vishis",
    "gn:country_code":"MX",
    "gn:dem":24,
    "gn:feature_class":"P",
    "gn:feature_code":"PPL",
    "gn:name":"Los Vishis",
    "gn:population":0,
    "gn:timezone":"America/Mexico_City",
    "iso:country":"MX",
    "name:spa_x_preferred":[
        "Los Vishis"
    ],
    "wof:name":"Los Vishis",
    "wof:placetype":"locality"
},
  "geometry": {"coordinates":[-104.51316,19.17679],"type":"Point"}
}