{
  "type": "Feature",
  "properties": {
    "gn:admin1_code":"14",
    "gn:admin2_code":"87",
    "gn:asciiname":"El Cangrejo",
    "gn:country_code":"MX",
    "gn:dem":1356,
    "gn:feature_class":"P",
    "gn:feature_code":"PPL",
    "gn:name":"El Cangrejo",
    "gn:population":13,
    "gn:timezone":"America/Mexico_City",
    "iso:country":"MX",
    "wof:name":"El Cangrejo",
    "wof:placetype":"locality",
    "wof:population":13
},
  "geometry": {"coordinates":[-103.26278000000001,19.22611],"type":"Point"}
}