{
  "type": "Feature",
  "properties": {
    "gn:admin1_code":"28",
    "gn:admin2_code":"13.0",
    "gn:asciiname":"El Solito",
    "gn:cc2":"MX",
    "gn:country_code":"MX",
    "gn:dem":195,
    "gn:feature_class":"P",
    "gn:feature_code":"PPL",
    "gn:name":"El Solito",
    "gn:population":4,
    "gn:timezone":"America/Monterrey",
    "iso:country":"MX",
    "name:und_x_variant":[
        "Cerrito",
        "El Cerrito"
    ],
    "wof:name":"El Solito",
    "wof:placetype":"locality",
    "wof:population":4
},
  "geometry": {"coordinates":[-99.10666999999999,24.06167],"type":"Point"}
}