{
  "type": "Feature",
  "properties": {
    "gn:admin1_code":"5",
    "gn:admin2_code":"13.0",
    "gn:asciiname":"Los Pinitos",
    "gn:country_code":"MX",
    "gn:dem":1209,
    "gn:feature_class":"P",
    "gn:feature_code":"PPL",
    "gn:name":"Los Pinitos",
    "gn:population":172,
    "gn:timezone":"America/Mexico_City",
    "iso:country":"MX",
    "wof:name":"Los Pinitos",
    "wof:placetype":"locality",
    "wof:population":172
},
  "geometry": {"coordinates":[-92.89901,16.98889],"type":"Point"}
}