{
  "type": "Feature",
  "properties": {
    "gn:admin1_code":"11",
    "gn:admin2_code":"30.0",
    "gn:asciiname":"Las Negritas",
    "gn:country_code":"MX",
    "gn:dem":2086,
    "gn:feature_class":"P",
    "gn:feature_code":"PPL",
    "gn:name":"Las Negritas",
    "gn:population":111,
    "gn:timezone":"America/Mexico_City",
    "iso:country":"MX",
    "wof:name":"Las Negritas",
    "wof:placetype":"locality",
    "wof:population":111
},
  "geometry": {"coordinates":[-101.19222000000001,21.57861],"type":"Point"}
}