{
  "type": "Feature",
  "properties": {
    "gn:admin1_code":"12.0",
    "gn:admin2_code":"67.0",
    "gn:asciiname":"El Perdon",
    "gn:country_code":"MX",
    "gn:dem":366,
    "gn:feature_class":"P",
    "gn:feature_code":"PPL",
    "gn:name":"El Perd\u00f3n",
    "gn:population":0,
    "gn:timezone":"America/Mexico_City",
    "iso:country":"MX",
    "name:spa_x_preferred":[
        "El Perd\u00f3n"
    ],
    "wof:name":"El Perdon",
    "wof:placetype":"locality"
},
  "geometry": {"coordinates":[-100.34148,18.30809],"type":"Point"}
}