{
  "type": "Feature",
  "properties": {
    "gn:admin1_code":"26",
    "gn:admin2_code":"17",
    "gn:asciiname":"Laguna Prieta",
    "gn:country_code":"MX",
    "gn:dem":165,
    "gn:feature_class":"P",
    "gn:feature_code":"PPL",
    "gn:name":"Laguna Prieta",
    "gn:population":35,
    "gn:timezone":"America/Hermosillo",
    "iso:country":"MX",
    "wof:name":"Laguna Prieta",
    "wof:placetype":"locality",
    "wof:population":35
},
  "geometry": {"coordinates":[-112.49139,30.69028],"type":"Point"}
}