{
  "type": "Feature",
  "properties": {
    "gn:admin1_code":"18.0",
    "gn:admin2_code":"5.0",
    "gn:asciiname":"Piedra Bola",
    "gn:country_code":"MX",
    "gn:dem":210,
    "gn:feature_class":"P",
    "gn:feature_code":"PPL",
    "gn:name":"Piedra Bola",
    "gn:population":0,
    "gn:timezone":"America/Mazatlan",
    "iso:country":"MX",
    "wof:name":"Piedra Bola",
    "wof:placetype":"locality"
},
  "geometry": {"coordinates":[-105.45833,22.725],"type":"Point"}
}