{
  "type": "Feature",
  "properties": {
    "gn:admin1_code":"6.0",
    "gn:admin2_code":"66.0",
    "gn:asciiname":"El Pino",
    "gn:country_code":"MX",
    "gn:dem":1205,
    "gn:feature_class":"P",
    "gn:feature_code":"PPL",
    "gn:name":"El Pino",
    "gn:population":0,
    "gn:timezone":"America/Chihuahua",
    "iso:country":"MX",
    "name:spa_x_preferred":[
        "El Pino"
    ],
    "wof:name":"El Pino",
    "wof:placetype":"locality"
},
  "geometry": {"coordinates":[-108.50906000000001,27.99392000000001],"type":"Point"}
}