{
  "type": "Feature",
  "properties": {
    "gn:admin1_code":"21.0",
    "gn:admin2_code":"74.0",
    "gn:asciiname":"Ixquiclan",
    "gn:country_code":"MX",
    "gn:dem":2317,
    "gn:feature_class":"P",
    "gn:feature_code":"PPL",
    "gn:name":"Ixquiclan",
    "gn:population":0,
    "gn:timezone":"America/Mexico_City",
    "iso:country":"MX",
    "name:spa_x_preferred":[
        "Ixquiclan"
    ],
    "wof:name":"Ixquiclan",
    "wof:placetype":"locality"
},
  "geometry": {"coordinates":[-98.43003,19.15427],"type":"Point"}
}