{
  "type": "Feature",
  "properties": {
    "gn:admin1_code":"25.0",
    "gn:admin2_code":"11.0",
    "gn:asciiname":"Aceituna",
    "gn:country_code":"MX",
    "gn:dem":17,
    "gn:feature_class":"P",
    "gn:feature_code":"PPL",
    "gn:name":"Aceituna",
    "gn:population":0,
    "gn:timezone":"America/Mazatlan",
    "iso:country":"MX",
    "name:ara_x_preferred":[
        "\u0623\u0633\u064a\u062a\u0648\u0646\u0627"
    ],
    "name:cat_x_preferred":[
        "Aceituna"
    ],
    "name:ceb_x_preferred":[
        "Aceituna"
    ],
    "name:epo_x_preferred":[
        "Aceituna"
    ],
    "name:eus_x_preferred":[
        "Aceituna"
    ],
    "name:fas_x_preferred":[
        "\u0627\u0633\u06cc\u062a\u0648\u0646\u0627"
    ],
    "name:fra_x_preferred":[
        "Aceituna"
    ],
    "name:glg_x_preferred":[
        "Aceituna"
    ],
    "name:hun_x_preferred":[
        "Aceituna"
    ],
    "name:ina_x_preferred":[
        "Aceituna"
    ],
    "name:ita_x_preferred":[
        "Aceituna"
    ],
    "name:msa_x_preferred":[
        "Aceituna"
    ],
    "name:nld_x_preferred":[
        "Aceituna"
    ],
    "name:oci_x_preferred":[
        "Aceituna"
    ],
    "name:pol_x_preferred":[
        "Aceituna"
    ],
    "name:por_x_preferred":[
        "Aceituna"
    ],
    "name:ron_x_preferred":[
        "Aceituna"
    ],
    "name:rus_x_preferred":[
        "\u0410\u0441\u0435\u0439\u0442\u0443\u043d\u0430"
    ],
    "name:spa_x_preferred":[
        "Aceituna"
    ],
    "name:swe_x_preferred":[
        "Aceituna"
    ],
    "name:ukr_x_preferred":[
        "\u0410\u0441\u0435\u0439\u0442\u0443\u043d\u0430"
    ],
    "name:uzb_x_preferred":[
        "Aceituna"
    ],
    "name:vie_x_preferred":[
        "Aceituna"
    ],
    "name:war_x_preferred":[
        "Aceituna"
    ],
    "wof:name":"Aceituna",
    "wof:placetype":"locality"
},
  "geometry": {"coordinates":[-108.65000000000001,25.66667],"type":"Point"}
}