{
  "type": "Feature",
  "properties": {
    "gn:admin1_code":"15",
    "gn:admin2_code":"101.0",
    "gn:asciiname":"Colonia Guadalupe Rhon de Hank",
    "gn:country_code":"MX",
    "gn:dem":2619,
    "gn:feature_class":"P",
    "gn:feature_code":"PPL",
    "gn:name":"Colonia Guadalupe Rhon de Hank",
    "gn:population":457,
    "gn:timezone":"America/Mexico_City",
    "iso:country":"MX",
    "wof:name":"Colonia Guadalupe Rhon de Hank",
    "wof:placetype":"locality",
    "wof:population":457
},
  "geometry": {"coordinates":[-99.47611000000001,19.1775],"type":"Point"}
}