{
  "type": "Feature",
  "properties": {
    "gn:admin1_code":"10",
    "gn:admin2_code":"5.0",
    "gn:asciiname":"El Refugio (El Conejo)",
    "gn:country_code":"MX",
    "gn:dem":1896,
    "gn:feature_class":"P",
    "gn:feature_code":"PPL",
    "gn:name":"El Refugio (El Conejo)",
    "gn:population":668,
    "gn:timezone":"America/Monterrey",
    "iso:country":"MX",
    "wof:name":"El Refugio (El Conejo)",
    "wof:placetype":"locality",
    "wof:population":668
},
  "geometry": {"coordinates":[-104.70028000000001,23.975],"type":"Point"}
}