{
  "type": "Feature",
  "properties": {
    "gn:admin1_code":"27",
    "gn:admin2_code":"10.0",
    "gn:asciiname":"El Juncal",
    "gn:country_code":"MX",
    "gn:dem":18,
    "gn:feature_class":"P",
    "gn:feature_code":"PPL",
    "gn:name":"El Juncal",
    "gn:population":379,
    "gn:timezone":"America/Mexico_City",
    "iso:country":"MX",
    "wof:name":"El Juncal",
    "wof:placetype":"locality",
    "wof:population":379
},
  "geometry": {"coordinates":[-93.125,18.10472],"type":"Point"}
}