{
  "type": "Feature",
  "properties": {
    "gn:admin1_code":"30",
    "gn:admin2_code":"181.0",
    "gn:asciiname":"La Laja",
    "gn:country_code":"MX",
    "gn:dem":73,
    "gn:feature_class":"P",
    "gn:feature_code":"PPL",
    "gn:name":"La Laja",
    "gn:population":181,
    "gn:timezone":"America/Mexico_City",
    "iso:country":"MX",
    "wof:name":"La Laja",
    "wof:placetype":"locality",
    "wof:population":181
},
  "geometry": {"coordinates":[-96.34583000000001,18.78278],"type":"Point"}
}