{
  "type": "Feature",
  "properties": {
    "gn:admin1_code":"30",
    "gn:admin2_code":"121",
    "gn:asciiname":"El Higueron",
    "gn:country_code":"MX",
    "gn:dem":25,
    "gn:feature_class":"P",
    "gn:feature_code":"PPL",
    "gn:name":"El Higuer\u00f3n",
    "gn:population":26,
    "gn:timezone":"America/Mexico_City",
    "iso:country":"MX",
    "name:und_x_variant":[
        "El Higuer\u00f3n"
    ],
    "wof:name":"El Higueron",
    "wof:placetype":"locality",
    "wof:population":26
},
  "geometry": {"coordinates":[-97.83417,21.53389],"type":"Point"}
}