{
  "type": "Feature",
  "properties": {
    "gn:admin1_code":"24",
    "gn:admin2_code":"27.0",
    "gn:asciiname":"Canoitas",
    "gn:country_code":"MX",
    "gn:dem":1118,
    "gn:feature_class":"P",
    "gn:feature_code":"PPL",
    "gn:name":"Cano\u00edtas",
    "gn:population":9,
    "gn:timezone":"America/Mexico_City",
    "iso:country":"MX",
    "wof:name":"Canoitas",
    "wof:placetype":"locality",
    "wof:population":9
},
  "geometry": {"coordinates":[-99.86306,21.54333],"type":"Point"}
}