{
  "type": "Feature",
  "properties": {
    "gn:admin1_code":"5",
    "gn:admin2_code":"99.0",
    "gn:asciiname":"Boloma",
    "gn:country_code":"MX",
    "gn:dem":1533,
    "gn:feature_class":"P",
    "gn:feature_code":"PPL",
    "gn:name":"Bolom\u00e1",
    "gn:population":5,
    "gn:timezone":"America/Mexico_City",
    "iso:country":"MX",
    "name:und_x_variant":[
        "Bolom\u00e1"
    ],
    "wof:name":"Boloma",
    "wof:placetype":"locality",
    "wof:population":5
},
  "geometry": {"coordinates":[-91.82528000000001,16.12222],"type":"Point"}
}