{
  "type": "Feature",
  "properties": {
    "gn:admin1_code":"25",
    "gn:admin2_code":"11.0",
    "gn:asciiname":"Francisco R. Serrano",
    "gn:country_code":"MX",
    "gn:dem":32,
    "gn:feature_class":"P",
    "gn:feature_code":"PPL",
    "gn:name":"Francisco R. Serrano",
    "gn:population":974,
    "gn:timezone":"America/Mazatlan",
    "iso:country":"MX",
    "wof:name":"Francisco R. Serrano",
    "wof:placetype":"locality",
    "wof:population":974
},
  "geometry": {"coordinates":[-108.21687,25.535],"type":"Point"}
}