{
  "type": "Feature",
  "properties": {
    "gn:admin1_code":"24",
    "gn:admin2_code":"41.0",
    "gn:asciiname":"Ejido San Jose Xilatzen",
    "gn:country_code":"MX",
    "gn:dem":103,
    "gn:feature_class":"P",
    "gn:feature_code":"PPL",
    "gn:name":"Ejido San Jos\u00e9 Xilatz\u00e9n",
    "gn:population":1279,
    "gn:timezone":"America/Mexico_City",
    "iso:country":"MX",
    "name:und_x_variant":[
        "Ejido San Jos\u00e9 Xilatz\u00e9n"
    ],
    "wof:name":"Ejido San Jose Xilatzen",
    "wof:placetype":"locality",
    "wof:population":1279
},
  "geometry": {"coordinates":[-98.92749999999999,21.67472],"type":"Point"}
}