{
  "type": "Feature",
  "properties": {
    "gn:admin1_code":"32",
    "gn:admin2_code":"42.0",
    "gn:asciiname":"El Tulipan (El Coyote)",
    "gn:country_code":"MX",
    "gn:dem":2327,
    "gn:feature_class":"P",
    "gn:feature_code":"PPL",
    "gn:name":"El Tulip\u00e1n (El Coyote)",
    "gn:population":9,
    "gn:timezone":"America/Mexico_City",
    "iso:country":"MX",
    "name:und_x_variant":[
        "El Tulip\u00e1n (El Coyote)"
    ],
    "wof:name":"El Tulipan (El Coyote)",
    "wof:placetype":"locality",
    "wof:population":9
},
  "geometry": {"coordinates":[-103.50778,23.76861],"type":"Point"}
}