{
  "type": "Feature",
  "properties": {
    "gn:admin1_code":"30",
    "gn:admin2_code":"23.0",
    "gn:asciiname":"Tinajas",
    "gn:country_code":"MX",
    "gn:dem":714,
    "gn:feature_class":"P",
    "gn:feature_code":"PPL",
    "gn:name":"Tinajas",
    "gn:population":160,
    "gn:timezone":"America/Mexico_City",
    "iso:country":"MX",
    "name:ceb_x_preferred":[
        "Tinajas"
    ],
    "name:spa_x_preferred":[
        "Tinajas"
    ],
    "name:swe_x_preferred":[
        "Tinajas"
    ],
    "wof:name":"Tinajas",
    "wof:placetype":"locality",
    "wof:population":160
},
  "geometry": {"coordinates":[-97.21722,19.8875],"type":"Point"}
}