{
  "type": "Feature",
  "properties": {
    "gn:admin1_code":"21",
    "gn:admin2_code":"164.0",
    "gn:asciiname":"Guadalupe Calderon",
    "gn:country_code":"MX",
    "gn:dem":2232,
    "gn:feature_class":"P",
    "gn:feature_code":"PPL",
    "gn:name":"Guadalupe Calder\u00f3n",
    "gn:population":1100,
    "gn:timezone":"America/Mexico_City",
    "iso:country":"MX",
    "name:und_x_variant":[
        "Guadalupe Calder\u00f3n"
    ],
    "wof:name":"Guadalupe Calderon",
    "wof:placetype":"locality",
    "wof:population":1100
},
  "geometry": {"coordinates":[-97.85833,18.96611],"type":"Point"}
}