{
  "type": "Feature",
  "properties": {
    "gn:admin1_code":"32",
    "gn:admin2_code":"10.0",
    "gn:asciiname":"Los Fracasados",
    "gn:country_code":"MX",
    "gn:dem":2076,
    "gn:feature_class":"P",
    "gn:feature_code":"PPL",
    "gn:name":"Los Fracasados",
    "gn:population":0,
    "gn:timezone":"America/Mexico_City",
    "iso:country":"MX",
    "name:spa_x_preferred":[
        "Los Fracasados"
    ],
    "wof:name":"Los Fracasados",
    "wof:placetype":"locality"
},
  "geometry": {"coordinates":[-102.94593999999999,23.4062],"type":"Point"}
}