{
  "type": "Feature",
  "properties": {
    "gn:admin1_code":"30.0",
    "gn:asciiname":"Ex Hacienda de Horconcitos",
    "gn:country_code":"MX",
    "gn:dem":46,
    "gn:feature_class":"P",
    "gn:feature_code":"PPL",
    "gn:name":"Ex Hacienda de Horconcitos",
    "gn:population":0,
    "gn:timezone":"America/Mexico_City",
    "iso:country":"MX",
    "name:spa_x_preferred":[
        "Ex Hacienda de Horconcitos"
    ],
    "wof:name":"Ex Hacienda de Horconcitos",
    "wof:placetype":"locality"
},
  "geometry": {"coordinates":[-97.7452,21.82318],"type":"Point"}
}