{
  "type": "Feature",
  "properties": {
    "gn:admin1_code":"16",
    "gn:admin2_code":"34.0",
    "gn:asciiname":"Puerto el Becerro",
    "gn:country_code":"MX",
    "gn:dem":2684,
    "gn:feature_class":"P",
    "gn:feature_code":"PPL",
    "gn:name":"Puerto el Becerro",
    "gn:population":0,
    "gn:timezone":"America/Mexico_City",
    "iso:country":"MX",
    "name:spa_x_preferred":[
        "Puerto el Becerro"
    ],
    "wof:name":"Puerto el Becerro",
    "wof:placetype":"locality"
},
  "geometry": {"coordinates":[-100.70863,19.47902],"type":"Point"}
}