{
  "type": "Feature",
  "properties": {
    "gn:admin1_code":"3",
    "gn:admin2_code":"2.0",
    "gn:asciiname":"Las Chivas",
    "gn:country_code":"MX",
    "gn:dem":397,
    "gn:feature_class":"P",
    "gn:feature_code":"PPL",
    "gn:name":"Las Chivas",
    "gn:population":0,
    "gn:timezone":"America/Mazatlan",
    "iso:country":"MX",
    "name:spa_x_preferred":[
        "Las Chivas"
    ],
    "wof:name":"Las Chivas",
    "wof:placetype":"locality"
},
  "geometry": {"coordinates":[-112.28386,26.57745],"type":"Point"}
}