{
  "type": "Feature",
  "properties": {
    "gn:admin1_code":"12.0",
    "gn:admin2_code":"11.0",
    "gn:asciiname":"Puente del Rey",
    "gn:country_code":"MX",
    "gn:dem":858,
    "gn:feature_class":"P",
    "gn:feature_code":"PPL",
    "gn:name":"Puente del Rey",
    "gn:population":0,
    "gn:timezone":"America/Mexico_City",
    "iso:country":"MX",
    "name:spa_x_preferred":[
        "Puente del Rey"
    ],
    "name:und_x_variant":[
        "Puente El Rey"
    ],
    "wof:name":"Puente del Rey",
    "wof:placetype":"locality"
},
  "geometry": {"coordinates":[-100.26232,17.34957],"type":"Point"}
}