{
  "type": "Feature",
  "properties": {
    "gn:admin1_code":"14.0",
    "gn:admin2_code":"13.0",
    "gn:asciiname":"La Puerta de la Arcina",
    "gn:country_code":"MX",
    "gn:dem":1564,
    "gn:feature_class":"P",
    "gn:feature_code":"PPL",
    "gn:name":"La Puerta de la Arcina",
    "gn:population":0,
    "gn:timezone":"America/Mexico_City",
    "iso:country":"MX",
    "name:spa_x_preferred":[
        "La Puerta de la Arcina"
    ],
    "wof:name":"La Puerta de la Arcina",
    "wof:placetype":"locality"
},
  "geometry": {"coordinates":[-102.52800000000001,20.47603],"type":"Point"}
}