{
  "type": "Feature",
  "properties": {
    "gn:admin1_code":"5",
    "gn:admin2_code":"6.0",
    "gn:asciiname":"El Zapote",
    "gn:country_code":"MX",
    "gn:dem":1391,
    "gn:feature_class":"P",
    "gn:feature_code":"PPL",
    "gn:name":"El Zapote",
    "gn:population":74,
    "gn:timezone":"America/Mexico_City",
    "iso:country":"MX",
    "wof:name":"El Zapote",
    "wof:placetype":"locality",
    "wof:population":74
},
  "geometry": {"coordinates":[-92.15083,15.53528],"type":"Point"}
}