{
  "type": "Feature",
  "properties": {
    "gn:admin1_code":"25",
    "gn:admin2_code":"11.0",
    "gn:asciiname":"Alarbito y Caimainero",
    "gn:country_code":"MX",
    "gn:dem":7,
    "gn:feature_class":"P",
    "gn:feature_code":"PPL",
    "gn:name":"Alarbito y Caimainero",
    "gn:population":0,
    "gn:timezone":"America/Mazatlan",
    "iso:country":"MX",
    "wof:name":"Alarbito y Caimainero",
    "wof:placetype":"locality"
},
  "geometry": {"coordinates":[-108.46510000000001,25.30469],"type":"Point"}
}