{
  "type": "Feature",
  "properties": {
    "gn:admin1_code":"6",
    "gn:admin2_code":"29.0",
    "gn:asciiname":"La Lechuguilla",
    "gn:country_code":"MX",
    "gn:dem":2435,
    "gn:feature_class":"P",
    "gn:feature_code":"PPL",
    "gn:name":"La Lechuguilla",
    "gn:population":0,
    "gn:timezone":"America/Chihuahua",
    "iso:country":"MX",
    "name:spa_x_preferred":[
        "La Lechuguilla"
    ],
    "wof:name":"La Lechuguilla",
    "wof:placetype":"locality"
},
  "geometry": {"coordinates":[-106.86053,26.10916],"type":"Point"}
}