{
  "type": "Feature",
  "properties": {
    "gn:admin1_code":"26",
    "gn:admin2_code":"72",
    "gn:asciiname":"Campo Agricola Ejido Chumampaco (Bloque 523)",
    "gn:country_code":"MX",
    "gn:dem":11,
    "gn:feature_class":"P",
    "gn:feature_code":"PPL",
    "gn:name":"Campo Agr\u00edcola Ejido Chumampaco (Bloque 523)",
    "gn:population":11,
    "gn:timezone":"America/Hermosillo",
    "iso:country":"MX",
    "name:und_x_variant":[
        "Campo Agr\u00edcola Ejido Chumampaco (Bloque 523)"
    ],
    "wof:name":"Campo Agricola Ejido Chumampaco (Bloque 523)",
    "wof:placetype":"locality",
    "wof:population":11
},
  "geometry": {"coordinates":[-110.24972,27.42917000000001],"type":"Point"}
}