{
  "type": "Feature",
  "properties": {
    "gn:admin1_code":"31.0",
    "gn:asciiname":"Yokzahum",
    "gn:country_code":"MX",
    "gn:dem":21,
    "gn:feature_class":"P",
    "gn:feature_code":"PPL",
    "gn:name":"Yokzahum",
    "gn:population":0,
    "gn:timezone":"America/Merida",
    "iso:country":"MX",
    "name:spa_x_preferred":[
        "Yokzahum"
    ],
    "name:spa_x_variant":[
        "Yohsahun"
    ],
    "wof:name":"Yokzahum",
    "wof:placetype":"locality"
},
  "geometry": {"coordinates":[-88.17643000000002,21.21618],"type":"Point"}
}