{
  "type": "Feature",
  "properties": {
    "gn:admin1_code":"12",
    "gn:admin2_code":"13.0",
    "gn:asciiname":"Los Cheguees",
    "gn:country_code":"MX",
    "gn:dem":20,
    "gn:feature_class":"P",
    "gn:feature_code":"PPL",
    "gn:name":"Los Cheg\u00fces",
    "gn:population":162,
    "gn:timezone":"America/Mexico_City",
    "iso:country":"MX",
    "name:und_x_variant":[
        "Los Cheg\u00fces"
    ],
    "wof:name":"Los Cheguees",
    "wof:placetype":"locality",
    "wof:population":162
},
  "geometry": {"coordinates":[-98.52388999999999,16.5825],"type":"Point"}
}