{
  "type": "Feature",
  "properties": {
    "gn:admin1_code":"14",
    "gn:admin2_code":"63.0",
    "gn:asciiname":"La Orilla de la Cerca",
    "gn:country_code":"MX",
    "gn:dem":1535,
    "gn:feature_class":"P",
    "gn:feature_code":"PPL",
    "gn:name":"La Orilla de la Cerca",
    "gn:population":256,
    "gn:timezone":"America/Mexico_City",
    "iso:country":"MX",
    "wof:name":"La Orilla de la Cerca",
    "wof:placetype":"locality",
    "wof:population":256
},
  "geometry": {"coordinates":[-102.71666999999999,20.36556],"type":"Point"}
}