{
  "type": "Feature",
  "properties": {
    "gn:admin1_code":"24",
    "gn:admin2_code":"35.0",
    "gn:asciiname":"Rancho las Cuatas (Santa Fe)",
    "gn:country_code":"MX",
    "gn:dem":1842,
    "gn:feature_class":"P",
    "gn:feature_code":"PPL",
    "gn:name":"Rancho las Cuatas (Santa Fe)",
    "gn:population":9,
    "gn:timezone":"America/Mexico_City",
    "iso:country":"MX",
    "wof:name":"Rancho las Cuatas (Santa Fe)",
    "wof:placetype":"locality",
    "wof:population":9
},
  "geometry": {"coordinates":[-100.88194,22.19222],"type":"Point"}
}