{
  "type": "Feature",
  "properties": {
    "gn:admin1_code":"2.0",
    "gn:admin2_code":"3.0",
    "gn:asciiname":"Los Alicitos",
    "gn:country_code":"MX",
    "gn:dem":430,
    "gn:feature_class":"P",
    "gn:feature_code":"PPL",
    "gn:name":"Los Alicitos",
    "gn:population":0,
    "gn:timezone":"America/Tijuana",
    "iso:country":"MX",
    "name:spa_x_preferred":[
        "Los Alicitos"
    ],
    "wof:name":"Los Alicitos",
    "wof:placetype":"locality"
},
  "geometry": {"coordinates":[-116.69123,32.51438],"type":"Point"}
}