{
  "type": "Feature",
  "properties": {
    "gn:admin1_code":"16.0",
    "gn:admin2_code":"2.0",
    "gn:asciiname":"El Palmito",
    "gn:country_code":"MX",
    "gn:dem":1479,
    "gn:feature_class":"P",
    "gn:feature_code":"PPL",
    "gn:name":"El Palmito",
    "gn:population":0,
    "gn:timezone":"America/Mexico_City",
    "iso:country":"MX",
    "name:spa_x_preferred":[
        "El Palmito"
    ],
    "wof:name":"El Palmito",
    "wof:placetype":"locality"
},
  "geometry": {"coordinates":[-102.62652,18.73338],"type":"Point"}
}