{
  "type": "Feature",
  "properties": {
    "gn:admin1_code":"25.0",
    "gn:admin2_code":"16.0",
    "gn:asciiname":"Laguna de los Otates",
    "gn:country_code":"MX",
    "gn:dem":20,
    "gn:feature_class":"P",
    "gn:feature_code":"PPL",
    "gn:name":"Laguna de los Otates",
    "gn:population":0,
    "gn:timezone":"America/Mazatlan",
    "iso:country":"MX",
    "name:spa_x_preferred":[
        "Laguna de los Otates"
    ],
    "wof:name":"Laguna de los Otates",
    "wof:placetype":"locality"
},
  "geometry": {"coordinates":[-106.77097000000001,23.67312],"type":"Point"}
}