{
  "type": "Feature",
  "properties": {
    "gn:admin1_code":"6.0",
    "gn:admin2_code":"7.0",
    "gn:asciiname":"Rancheria Las Coloradas",
    "gn:country_code":"MX",
    "gn:dem":2538,
    "gn:feature_class":"P",
    "gn:feature_code":"PPL",
    "gn:name":"Rancher\u00eda Las Coloradas",
    "gn:population":0,
    "gn:timezone":"America/Chihuahua",
    "iso:country":"MX",
    "name:spa_x_preferred":[
        "Rancher\u00eda Las Coloradas"
    ],
    "name:und_x_variant":[
        "Coloradas"
    ],
    "wof:name":"Rancheria Las Coloradas",
    "wof:placetype":"locality"
},
  "geometry": {"coordinates":[-106.57680000000001,26.53657],"type":"Point"}
}