{
  "type": "Feature",
  "properties": {
    "gn:admin1_code":"22.0",
    "gn:admin2_code":"14.0",
    "gn:asciiname":"San Isidro El Alto",
    "gn:country_code":"MX",
    "gn:dem":2180,
    "gn:feature_class":"P",
    "gn:feature_code":"PPL",
    "gn:name":"San Isidro El Alto",
    "gn:population":0,
    "gn:timezone":"America/Mexico_City",
    "iso:country":"MX",
    "name:spa_x_preferred":[
        "San Isidro El Alto"
    ],
    "wof:name":"San Isidro El Alto",
    "wof:placetype":"locality"
},
  "geometry": {"coordinates":[-100.52812,20.71699],"type":"Point"}
}