{
  "type": "Feature",
  "properties": {
    "gn:admin1_code":"15.0",
    "gn:asciiname":"Puerta Chiquita",
    "gn:country_code":"MX",
    "gn:dem":2734,
    "gn:feature_class":"P",
    "gn:feature_code":"PPL",
    "gn:name":"Puerta Chiquita",
    "gn:population":0,
    "gn:timezone":"America/Mexico_City",
    "iso:country":"MX",
    "name:spa_x_preferred":[
        "Puerta Chiquita"
    ],
    "wof:name":"Puerta Chiquita",
    "wof:placetype":"locality"
},
  "geometry": {"coordinates":[-99.6053,19.50464],"type":"Point"}
}