{
  "type": "Feature",
  "properties": {
    "gn:admin1_code":"20",
    "gn:admin2_code":"530.0",
    "gn:asciiname":"El Tronco de Huamuche",
    "gn:country_code":"MX",
    "gn:dem":1512,
    "gn:feature_class":"P",
    "gn:feature_code":"PPL",
    "gn:name":"El Tronco de Huamuche",
    "gn:population":8,
    "gn:timezone":"America/Mexico_City",
    "iso:country":"MX",
    "wof:name":"El Tronco de Huamuche",
    "wof:placetype":"locality",
    "wof:population":8
},
  "geometry": {"coordinates":[-96.67,16.83694],"type":"Point"}
}