{
  "type": "Feature",
  "properties": {
    "gn:admin1_code":"14",
    "gn:admin2_code":"97",
    "gn:asciiname":"Ninguno [Parque Industrial Aeropuerto]",
    "gn:country_code":"MX",
    "gn:dem":1536,
    "gn:feature_class":"P",
    "gn:feature_code":"PPL",
    "gn:name":"Ninguno [Parque Industrial Aeropuerto]",
    "gn:population":37,
    "gn:timezone":"America/Mexico_City",
    "iso:country":"MX",
    "wof:name":"Ninguno [Parque Industrial Aeropuerto]",
    "wof:placetype":"locality",
    "wof:population":37
},
  "geometry": {"coordinates":[-103.27249999999999,20.49306],"type":"Point"}
}