{
  "type": "Feature",
  "properties": {
    "gn:admin1_code":"5",
    "gn:admin2_code":"107.0",
    "gn:asciiname":"La Ilusion",
    "gn:country_code":"MX",
    "gn:dem":684,
    "gn:feature_class":"P",
    "gn:feature_code":"PPL",
    "gn:name":"La Ilusi\u00f3n",
    "gn:population":8,
    "gn:timezone":"America/Mexico_City",
    "iso:country":"MX",
    "name:und_x_variant":[
        "La Ilusi\u00f3n"
    ],
    "wof:name":"La Ilusion",
    "wof:placetype":"locality",
    "wof:population":8
},
  "geometry": {"coordinates":[-93.42028000000001,16.15444],"type":"Point"}
}