{
  "type": "Feature",
  "properties": {
    "gn:admin1_code":"30",
    "gn:admin2_code":"114.0",
    "gn:asciiname":"Emiliano Zapata",
    "gn:country_code":"MX",
    "gn:dem":18,
    "gn:feature_class":"P",
    "gn:feature_code":"PPL",
    "gn:name":"Emiliano Zapata",
    "gn:population":82,
    "gn:timezone":"America/Mexico_City",
    "iso:country":"MX",
    "wof:name":"Emiliano Zapata",
    "wof:placetype":"locality",
    "wof:population":82
},
  "geometry": {"coordinates":[-96.71417,20.09083],"type":"Point"}
}