{
  "type": "Feature",
  "properties": {
    "gn:admin1_code":"15",
    "gn:admin2_code":"45.0",
    "gn:asciiname":"Xhimojay",
    "gn:country_code":"MX",
    "gn:dem":2662,
    "gn:feature_class":"P",
    "gn:feature_code":"PPL",
    "gn:name":"Xhimojay",
    "gn:population":0,
    "gn:timezone":"America/Mexico_City",
    "iso:country":"MX",
    "name:und_x_variant":[
        "Ximojay"
    ],
    "wof:name":"Xhimojay",
    "wof:placetype":"locality"
},
  "geometry": {"coordinates":[-99.64232,19.92144],"type":"Point"}
}