{
  "type": "Feature",
  "properties": {
    "gn:admin1_code":"5.0",
    "gn:admin2_code":"17.0",
    "gn:asciiname":"Los Aguajitos",
    "gn:country_code":"MX",
    "gn:dem":612,
    "gn:feature_class":"P",
    "gn:feature_code":"PPL",
    "gn:name":"Los Aguajitos",
    "gn:population":0,
    "gn:timezone":"America/Mexico_City",
    "iso:country":"MX",
    "name:spa_x_preferred":[
        "Los Aguajitos"
    ],
    "wof:name":"Los Aguajitos",
    "wof:placetype":"locality"
},
  "geometry": {"coordinates":[-93.90018000000001,16.79082],"type":"Point"}
}