{
  "type": "Feature",
  "properties": {
    "gn:admin1_code":"21",
    "gn:admin2_code":"174.0",
    "gn:asciiname":"Ixtlahuaca",
    "gn:country_code":"MX",
    "gn:dem":1881,
    "gn:feature_class":"P",
    "gn:feature_code":"PPL",
    "gn:name":"Ixtlahuaca",
    "gn:population":1063,
    "gn:timezone":"America/Mexico_City",
    "iso:country":"MX",
    "wof:name":"Ixtlahuaca",
    "wof:placetype":"locality",
    "wof:population":1063
},
  "geometry": {"coordinates":[-97.33496,19.82309],"type":"Point"}
}