{
  "type": "Feature",
  "properties": {
    "gn:admin1_code":"25",
    "gn:admin2_code":"11.0",
    "gn:asciiname":"Tahuilana (El Chorizo)",
    "gn:country_code":"MX",
    "gn:dem":37,
    "gn:feature_class":"P",
    "gn:feature_code":"PPL",
    "gn:name":"Tahuilana (El Chorizo)",
    "gn:population":69,
    "gn:timezone":"America/Mazatlan",
    "iso:country":"MX",
    "wof:name":"Tahuilana (El Chorizo)",
    "wof:placetype":"locality",
    "wof:population":69
},
  "geometry": {"coordinates":[-108.33156,25.65663],"type":"Point"}
}