{
  "type": "Feature",
  "properties": {
    "gn:admin1_code":"7.0",
    "gn:admin2_code":"28.0",
    "gn:asciiname":"Las Amapolas",
    "gn:country_code":"MX",
    "gn:dem":329,
    "gn:feature_class":"P",
    "gn:feature_code":"PPL",
    "gn:name":"Las Amapolas",
    "gn:population":0,
    "gn:timezone":"America/Monterrey",
    "iso:country":"MX",
    "name:spa_x_preferred":[
        "Las Amapolas"
    ],
    "wof:name":"Las Amapolas",
    "wof:placetype":"locality"
},
  "geometry": {"coordinates":[-100.99731,27.77614],"type":"Point"}
}