{
  "type": "Feature",
  "properties": {
    "gn:admin1_code":"26.0",
    "gn:admin2_code":"58.0",
    "gn:asciiname":"Tesotal",
    "gn:country_code":"MX",
    "gn:dem":617,
    "gn:feature_class":"P",
    "gn:feature_code":"PPL",
    "gn:name":"Tesotal",
    "gn:population":0,
    "gn:timezone":"America/Hermosillo",
    "iso:country":"MX",
    "name:spa_x_preferred":[
        "Tesotal"
    ],
    "wof:name":"Tesotal",
    "wof:placetype":"locality"
},
  "geometry": {"coordinates":[-111.24141000000002,30.44444],"type":"Point"}
}