{
  "type": "Feature",
  "properties": {
    "gn:admin1_code":"30",
    "gn:admin2_code":"123.0",
    "gn:asciiname":"Manlio Fabio Altamirano",
    "gn:country_code":"MX",
    "gn:dem":18,
    "gn:feature_class":"P",
    "gn:feature_code":"PPL",
    "gn:name":"Manlio Fabio Altamirano",
    "gn:population":243,
    "gn:timezone":"America/Mexico_City",
    "iso:country":"MX",
    "wof:name":"Manlio Fabio Altamirano",
    "wof:placetype":"locality",
    "wof:population":243
},
  "geometry": {"coordinates":[-98.42111,21.99],"type":"Point"}
}