{
  "type": "Feature",
  "properties": {
    "gn:admin1_code":"13",
    "gn:admin2_code":"83.0",
    "gn:asciiname":"Santa Gertrudis",
    "gn:country_code":"MX",
    "gn:dem":2558,
    "gn:feature_class":"P",
    "gn:feature_code":"PPL",
    "gn:name":"Santa Gertrudis",
    "gn:population":294,
    "gn:timezone":"America/Mexico_City",
    "iso:country":"MX",
    "wof:name":"Santa Gertrudis",
    "wof:placetype":"locality",
    "wof:population":294
},
  "geometry": {"coordinates":[-98.6061,19.90522],"type":"Point"}
}