{
  "type": "Feature",
  "properties": {
    "gn:admin1_code":"6.0",
    "gn:admin2_code":"29.0",
    "gn:asciiname":"La Quebrada",
    "gn:country_code":"MX",
    "gn:dem":1046,
    "gn:feature_class":"P",
    "gn:feature_code":"PPL",
    "gn:name":"La Quebrada",
    "gn:population":0,
    "gn:timezone":"America/Chihuahua",
    "iso:country":"MX",
    "name:ceb_x_preferred":[
        "La Quebrada"
    ],
    "name:spa_x_preferred":[
        "La Quebrada"
    ],
    "name:swe_x_preferred":[
        "La Quebrada"
    ],
    "wof:name":"La Quebrada",
    "wof:placetype":"locality"
},
  "geometry": {"coordinates":[-107.34902,26.1789],"type":"Point"}
}