{
  "type": "Feature",
  "properties": {
    "gn:admin1_code":"5",
    "gn:admin2_code":"107",
    "gn:asciiname":"Belen II",
    "gn:country_code":"MX",
    "gn:dem":1055,
    "gn:feature_class":"P",
    "gn:feature_code":"PPL",
    "gn:name":"Bel\u00e9n II",
    "gn:population":19,
    "gn:timezone":"America/Mexico_City",
    "iso:country":"MX",
    "name:und_x_variant":[
        "Bel\u00e9n II"
    ],
    "wof:name":"Belen II",
    "wof:placetype":"locality",
    "wof:population":19
},
  "geometry": {"coordinates":[-93.37361,15.94389],"type":"Point"}
}