{
  "type": "Feature",
  "properties": {
    "gn:admin1_code":"21",
    "gn:admin2_code":"85.0",
    "gn:asciiname":"Xaltianguis",
    "gn:cc2":"MX",
    "gn:country_code":"MX",
    "gn:dem":1139,
    "gn:feature_class":"P",
    "gn:feature_code":"PPL",
    "gn:name":"Xaltianguis",
    "gn:population":179,
    "gn:timezone":"America/Mexico_City",
    "iso:country":"MX",
    "name:und_x_variant":[
        "Xaltiangus",
        "Xaltianguis",
        "Jaltianguis"
    ],
    "wof:name":"Xaltianguis",
    "wof:placetype":"locality",
    "wof:population":179
},
  "geometry": {"coordinates":[-98.49167,18.42278],"type":"Point"}
}