{
  "type": "Feature",
  "properties": {
    "gn:admin1_code":"16",
    "gn:admin2_code":"68",
    "gn:asciiname":"Cutio",
    "gn:country_code":"MX",
    "gn:dem":1850,
    "gn:feature_class":"P",
    "gn:feature_code":"PPL",
    "gn:name":"Cutio",
    "gn:population":11,
    "gn:timezone":"America/Mexico_City",
    "iso:country":"MX",
    "wof:name":"Cutio",
    "wof:placetype":"locality",
    "wof:population":11
},
  "geometry": {"coordinates":[-102.38472,19.50417],"type":"Point"}
}