{
  "type": "Feature",
  "properties": {
    "gn:admin1_code":"32.0",
    "gn:admin2_code":"55.0",
    "gn:asciiname":"Los Charcos",
    "gn:country_code":"MX",
    "gn:dem":2032,
    "gn:feature_class":"P",
    "gn:feature_code":"PPL",
    "gn:name":"Los Charcos",
    "gn:population":0,
    "gn:timezone":"America/Mexico_City",
    "iso:country":"MX",
    "name:spa_x_preferred":[
        "Los Charcos"
    ],
    "wof:name":"Los Charcos",
    "wof:placetype":"locality"
},
  "geometry": {"coordinates":[-102.84184,22.47167],"type":"Point"}
}