{
  "type": "Feature",
  "properties": {
    "gn:admin1_code":"10.0",
    "gn:admin2_code":"11.0",
    "gn:asciiname":"El Cuervo",
    "gn:country_code":"MX",
    "gn:dem":1829,
    "gn:feature_class":"P",
    "gn:feature_code":"PPL",
    "gn:name":"El Cuervo",
    "gn:population":0,
    "gn:timezone":"America/Monterrey",
    "iso:country":"MX",
    "name:ceb_x_preferred":[
        "El Cuervo"
    ],
    "name:deu_x_preferred":[
        "El Cuervo"
    ],
    "name:spa_x_preferred":[
        "El cuervo"
    ],
    "name:swe_x_preferred":[
        "El Cuervo"
    ],
    "name:und_x_variant":[
        "Cuervo"
    ],
    "wof:name":"El Cuervo",
    "wof:placetype":"locality"
},
  "geometry": {"coordinates":[-105.20589,25.98134],"type":"Point"}
}