{
  "type": "Feature",
  "properties": {
    "gn:admin1_code":"11",
    "gn:admin2_code":"43",
    "gn:asciiname":"La Dalia",
    "gn:country_code":"MX",
    "gn:dem":1005,
    "gn:feature_class":"P",
    "gn:feature_code":"PPL",
    "gn:name":"La Dalia",
    "gn:population":13,
    "gn:timezone":"America/Mexico_City",
    "iso:country":"MX",
    "wof:name":"La Dalia",
    "wof:placetype":"locality",
    "wof:population":13
},
  "geometry": {"coordinates":[-100.13833,21.54306],"type":"Point"}
}