{
  "type": "Feature",
  "properties": {
    "gn:admin1_code":"28",
    "gn:admin2_code":"37.0",
    "gn:asciiname":"La Penita",
    "gn:country_code":"MX",
    "gn:dem":37,
    "gn:feature_class":"P",
    "gn:feature_code":"PPL",
    "gn:name":"La Pe\u00f1ita",
    "gn:population":251,
    "gn:timezone":"America/Monterrey",
    "iso:country":"MX",
    "name:spa_x_preferred":[
        "La Pe\u00f1ita"
    ],
    "wof:name":"La Penita",
    "wof:placetype":"locality",
    "wof:population":251
},
  "geometry": {"coordinates":[-98.23134,23.93387],"type":"Point"}
}