{
  "type": "Feature",
  "properties": {
    "gn:admin1_code":"15.0",
    "gn:asciiname":"Tunguitiro",
    "gn:country_code":"MX",
    "gn:dem":2050,
    "gn:feature_class":"P",
    "gn:feature_code":"PPL",
    "gn:name":"Tung\u00fcitiro",
    "gn:population":0,
    "gn:timezone":"America/Mexico_City",
    "iso:country":"MX",
    "name:spa_x_preferred":[
        "Tung\u00fcitiro"
    ],
    "wof:name":"Tunguitiro",
    "wof:placetype":"locality"
},
  "geometry": {"coordinates":[-101.61059,19.78584],"type":"Point"}
}