{
  "type": "Feature",
  "properties": {
    "gn:admin1_code":"30",
    "gn:admin2_code":"44.0",
    "gn:asciiname":"La Luz Francisco Ignacio Madero",
    "gn:country_code":"MX",
    "gn:dem":910,
    "gn:feature_class":"P",
    "gn:feature_code":"PPL",
    "gn:name":"La Luz Francisco Ignacio Madero",
    "gn:population":0,
    "gn:timezone":"America/Mexico_City",
    "iso:country":"MX",
    "name:spa_x_preferred":[
        "La Luz Francisco Ignacio Madero"
    ],
    "name:spa_x_variant":[
        "La Luz Francisco I. Madero"
    ],
    "name:und_x_variant":[
        "La Luz"
    ],
    "wof:name":"La Luz Francisco Ignacio Madero",
    "wof:placetype":"locality"
},
  "geometry": {"coordinates":[-96.96469999999999,18.87811],"type":"Point"}
}