{
  "type": "Feature",
  "properties": {
    "gn:admin1_code":"6",
    "gn:admin2_code":"20.0",
    "gn:asciiname":"El Recodo",
    "gn:country_code":"MX",
    "gn:dem":445,
    "gn:feature_class":"P",
    "gn:feature_code":"PPL",
    "gn:name":"El Recodo",
    "gn:population":0,
    "gn:timezone":"America/Chihuahua",
    "iso:country":"MX",
    "name:spa_x_preferred":[
        "El Recodo"
    ],
    "wof:name":"El Recodo",
    "wof:placetype":"locality"
},
  "geometry": {"coordinates":[-108.51524000000001,27.36563],"type":"Point"}
}