{
  "type": "Feature",
  "properties": {
    "gn:admin1_code":"26",
    "gn:admin2_code":"18.0",
    "gn:asciiname":"Estacion Corral",
    "gn:country_code":"MX",
    "gn:dem":35,
    "gn:feature_class":"P",
    "gn:feature_code":"PPL",
    "gn:name":"Estaci\u00f3n Corral",
    "gn:population":1788,
    "gn:timezone":"America/Hermosillo",
    "iso:country":"MX",
    "name:und_x_variant":[
        "Estaci\u00f3n Corral"
    ],
    "wof:name":"Estacion Corral",
    "wof:placetype":"locality",
    "wof:population":1788
},
  "geometry": {"coordinates":[-109.96611,27.62889],"type":"Point"}
}