{
  "type": "Feature",
  "properties": {
    "gn:admin1_code":"30",
    "gn:admin2_code":"49.0",
    "gn:asciiname":"La Ceiba",
    "gn:country_code":"MX",
    "gn:dem":100,
    "gn:feature_class":"P",
    "gn:feature_code":"PPL",
    "gn:name":"La Ceiba",
    "gn:population":76,
    "gn:timezone":"America/Mexico_City",
    "iso:country":"MX",
    "wof:name":"La Ceiba",
    "wof:placetype":"locality",
    "wof:population":76
},
  "geometry": {"coordinates":[-96.41722,18.84639],"type":"Point"}
}