{
  "type": "Feature",
  "properties": {
    "gn:admin1_code":"28.0",
    "gn:admin2_code":"29.0",
    "gn:asciiname":"Santa Eugenia",
    "gn:country_code":"MX",
    "gn:dem":318,
    "gn:feature_class":"P",
    "gn:feature_code":"PPL",
    "gn:name":"Santa Eugenia",
    "gn:population":3,
    "gn:timezone":"America/Monterrey",
    "iso:country":"MX",
    "name:spa_x_preferred":[
        "Santa Eugenia"
    ],
    "wof:name":"Santa Eugenia",
    "wof:placetype":"locality",
    "wof:population":3
},
  "geometry": {"coordinates":[-99.27582,22.69262],"type":"Point"}
}