{
  "type": "Feature",
  "properties": {
    "gn:admin1_code":"28",
    "gn:admin2_code":"37",
    "gn:asciiname":"El Zamora",
    "gn:country_code":"MX",
    "gn:dem":169,
    "gn:feature_class":"P",
    "gn:feature_code":"PPL",
    "gn:name":"El Zamora",
    "gn:population":12,
    "gn:timezone":"America/Monterrey",
    "iso:country":"MX",
    "wof:name":"El Zamora",
    "wof:placetype":"locality",
    "wof:population":12
},
  "geometry": {"coordinates":[-97.92222,23.42194],"type":"Point"}
}