{
  "type": "Feature",
  "properties": {
    "gn:admin1_code":"5",
    "gn:admin2_code":"5.0",
    "gn:asciiname":"Nanchital",
    "gn:country_code":"MX",
    "gn:dem":783,
    "gn:feature_class":"P",
    "gn:feature_code":"PPL",
    "gn:name":"Nanchital",
    "gn:population":92,
    "gn:timezone":"America/Mexico_City",
    "iso:country":"MX",
    "name:epo_x_preferred":[
        "Nanchital"
    ],
    "wof:name":"Nanchital",
    "wof:placetype":"locality",
    "wof:population":92
},
  "geometry": {"coordinates":[-92.87889,17.4075],"type":"Point"}
}