{
  "type": "Feature",
  "properties": {
    "gn:admin1_code":"14",
    "gn:admin2_code":"115.0",
    "gn:asciiname":"El Laurel",
    "gn:country_code":"MX",
    "gn:dem":1868,
    "gn:feature_class":"P",
    "gn:feature_code":"PPL",
    "gn:name":"El Laurel",
    "gn:population":0,
    "gn:timezone":"America/Mexico_City",
    "iso:country":"MX",
    "name:spa_x_preferred":[
        "El Laurel"
    ],
    "wof:name":"El Laurel",
    "wof:placetype":"locality"
},
  "geometry": {"coordinates":[-103.79494,22.01298],"type":"Point"}
}