{
  "type": "Feature",
  "properties": {
    "gn:admin1_code":"16",
    "gn:admin2_code":"68.0",
    "gn:asciiname":"Cinco Pinos",
    "gn:country_code":"MX",
    "gn:dem":2823,
    "gn:feature_class":"P",
    "gn:feature_code":"PPL",
    "gn:name":"Cinco Pinos",
    "gn:population":5,
    "gn:timezone":"America/Mexico_City",
    "iso:country":"MX",
    "wof:name":"Cinco Pinos",
    "wof:placetype":"locality",
    "wof:population":5
},
  "geometry": {"coordinates":[-102.35138999999999,19.44944],"type":"Point"}
}