{
  "type": "Feature",
  "properties": {
    "gn:admin1_code":"32.0",
    "gn:admin2_code":"8.0",
    "gn:asciiname":"Vinedos Florencia",
    "gn:country_code":"MX",
    "gn:dem":2033,
    "gn:feature_class":"P",
    "gn:feature_code":"PPL",
    "gn:name":"Vi\u00f1edos Florencia",
    "gn:population":0,
    "gn:timezone":"America/Mexico_City",
    "iso:country":"MX",
    "name:spa_x_preferred":[
        "Vi\u00f1edos Florencia"
    ],
    "wof:name":"Vinedos Florencia",
    "wof:placetype":"locality"
},
  "geometry": {"coordinates":[-102.27864,22.52793],"type":"Point"}
}