{
  "type": "Feature",
  "properties": {
    "gn:admin1_code":"16",
    "gn:admin2_code":"57.0",
    "gn:asciiname":"El Pinzan Dulce",
    "gn:country_code":"MX",
    "gn:dem":637,
    "gn:feature_class":"P",
    "gn:feature_code":"PPL",
    "gn:name":"El Pinz\u00e1n Dulce",
    "gn:population":7,
    "gn:timezone":"America/Mexico_City",
    "iso:country":"MX",
    "name:und_x_variant":[
        "El Pinz\u00e1n Dulce"
    ],
    "wof:name":"El Pinzan Dulce",
    "wof:placetype":"locality",
    "wof:population":7
},
  "geometry": {"coordinates":[-101.10833,19.0975],"type":"Point"}
}