{
  "type": "Feature",
  "properties": {
    "gn:admin1_code":"28",
    "gn:admin2_code":"23.0",
    "gn:asciiname":"Ricardo Espinoza Guerrero",
    "gn:country_code":"MX",
    "gn:dem":66,
    "gn:feature_class":"P",
    "gn:feature_code":"PPL",
    "gn:name":"Ricardo Espinoza Guerrero",
    "gn:population":9,
    "gn:timezone":"America/Monterrey",
    "iso:country":"MX",
    "wof:name":"Ricardo Espinoza Guerrero",
    "wof:placetype":"locality",
    "wof:population":9
},
  "geometry": {"coordinates":[-98.21556,25.34361],"type":"Point"}
}