{
  "type": "Feature",
  "properties": {
    "gn:admin1_code":"6",
    "gn:admin2_code":"17.0",
    "gn:asciiname":"Morelos",
    "gn:country_code":"MX",
    "gn:dem":2001,
    "gn:feature_class":"P",
    "gn:feature_code":"PPL",
    "gn:name":"Morelos",
    "gn:population":254,
    "gn:timezone":"America/Chihuahua",
    "iso:country":"MX",
    "wof:name":"Morelos",
    "wof:placetype":"locality",
    "wof:population":254
},
  "geometry": {"coordinates":[-106.99250000000001,28.67361],"type":"Point"}
}