{
  "type": "Feature",
  "properties": {
    "gn:admin1_code":"17",
    "gn:asciiname":"Chalma",
    "gn:country_code":"MX",
    "gn:dem":2323,
    "gn:feature_class":"P",
    "gn:feature_code":"PPL",
    "gn:name":"Chalma",
    "gn:population":0,
    "gn:timezone":"America/Mexico_City",
    "iso:country":"MX",
    "name:ceb_x_preferred":[
        "Chalma"
    ],
    "name:deu_x_preferred":[
        "Chalma"
    ],
    "name:rus_x_preferred":[
        "\u0427\u0430\u043b\u044c\u043c\u0430"
    ],
    "name:spa_x_preferred":[
        "Chalma"
    ],
    "name:spa_x_variant":[
        "El Polvor\u00edn"
    ],
    "name:swe_x_preferred":[
        "Chalma"
    ],
    "name:vie_x_preferred":[
        "Chalma"
    ],
    "wof:name":"Chalma",
    "wof:placetype":"locality"
},
  "geometry": {"coordinates":[-98.82105,19.65343],"type":"Point"}
}