{
  "type": "Feature",
  "properties": {
    "gn:admin1_code":"6",
    "gn:admin2_code":"66",
    "gn:asciiname":"El Puerto de Buenavista",
    "gn:country_code":"MX",
    "gn:dem":1600,
    "gn:feature_class":"P",
    "gn:feature_code":"PPL",
    "gn:name":"El Puerto de Buenavista",
    "gn:population":9,
    "gn:timezone":"America/Chihuahua",
    "iso:country":"MX",
    "wof:name":"El Puerto de Buenavista",
    "wof:placetype":"locality",
    "wof:population":9
},
  "geometry": {"coordinates":[-108.35133,27.77519],"type":"Point"}
}