{
  "type": "Feature",
  "properties": {
    "gn:admin1_code":"19.0",
    "gn:asciiname":"El Bano",
    "gn:country_code":"MX",
    "gn:dem":2054,
    "gn:feature_class":"P",
    "gn:feature_code":"PPL",
    "gn:name":"El Ba\u00f1o",
    "gn:population":0,
    "gn:timezone":"America/Monterrey",
    "iso:country":"MX",
    "name:spa_x_preferred":[
        "El Ba\u00f1o"
    ],
    "wof:name":"El Bano",
    "wof:placetype":"locality"
},
  "geometry": {"coordinates":[-99.98922,24.60184],"type":"Point"}
}