{
  "type": "Feature",
  "properties": {
    "gn:admin1_code":"20",
    "gn:admin2_code":"438.0",
    "gn:asciiname":"Arroyo Aguacate",
    "gn:country_code":"MX",
    "gn:dem":1143,
    "gn:feature_class":"P",
    "gn:feature_code":"PPL",
    "gn:name":"Arroyo Aguacate",
    "gn:population":53,
    "gn:timezone":"America/Mexico_City",
    "iso:country":"MX",
    "wof:name":"Arroyo Aguacate",
    "wof:placetype":"locality",
    "wof:population":53
},
  "geometry": {"coordinates":[-96.74472,17.95139],"type":"Point"}
}