{
  "type": "Feature",
  "properties": {
    "gn:admin1_code":"6",
    "gn:admin2_code":"40.0",
    "gn:asciiname":"Ejido Jesus Garcia (El Oso)",
    "gn:country_code":"MX",
    "gn:dem":2182,
    "gn:feature_class":"P",
    "gn:feature_code":"PPL",
    "gn:name":"Ejido Jes\u00fas Garc\u00eda (El Oso)",
    "gn:population":185,
    "gn:timezone":"America/Chihuahua",
    "iso:country":"MX",
    "name:und_x_variant":[
        "Ejido Jes\u00fas Garc\u00eda (El Oso)"
    ],
    "wof:name":"Ejido Jesus Garcia (El Oso)",
    "wof:placetype":"locality",
    "wof:population":185
},
  "geometry": {"coordinates":[-108.32832999999999,29.58639],"type":"Point"}
}