{
  "type": "Feature",
  "properties": {
    "gn:admin1_code":"30",
    "gn:admin2_code":"77.0",
    "gn:asciiname":"San Simon",
    "gn:country_code":"MX",
    "gn:dem":29,
    "gn:feature_class":"P",
    "gn:feature_code":"PPL",
    "gn:name":"San Sim\u00f3n",
    "gn:population":0,
    "gn:timezone":"America/Mexico_City",
    "iso:country":"MX",
    "name:ceb_x_preferred":[
        "San Simon"
    ],
    "name:ces_x_preferred":[
        "San Simon"
    ],
    "name:deu_x_preferred":[
        "San Simon"
    ],
    "name:fra_x_preferred":[
        "San Simon"
    ],
    "name:nld_x_preferred":[
        "San Simon"
    ],
    "name:sco_x_preferred":[
        "San Simon"
    ],
    "name:spa_x_preferred":[
        "San Sim\u00f3n"
    ],
    "name:srp_x_preferred":[
        "\u0421\u0430\u043d \u0421\u0438\u043c\u043e\u043d"
    ],
    "name:swe_x_preferred":[
        "San Simon"
    ],
    "name:ukr_x_preferred":[
        "\u0421\u0430\u043d-\u0421\u0456\u043c\u043e\u043d"
    ],
    "name:war_x_preferred":[
        "San Sim\u00f3n"
    ],
    "wof:name":"San Simon",
    "wof:placetype":"locality"
},
  "geometry": {"coordinates":[-95.50785999999999,18.19503],"type":"Point"}
}