{
  "type": "Feature",
  "properties": {
    "gn:admin1_code":"14",
    "gn:admin2_code":"35.0",
    "gn:asciiname":"Las Rosas",
    "gn:country_code":"MX",
    "gn:dem":2056,
    "gn:feature_class":"P",
    "gn:feature_code":"PPL",
    "gn:name":"Las Rosas",
    "gn:population":0,
    "gn:timezone":"America/Mexico_City",
    "iso:country":"MX",
    "name:spa_x_preferred":[
        "Las Rosas"
    ],
    "wof:name":"Las Rosas",
    "wof:placetype":"locality"
},
  "geometry": {"coordinates":[-102.18428,21.66718],"type":"Point"}
}