{
  "type": "Feature",
  "properties": {
    "gn:admin1_code":"16",
    "gn:admin2_code":"8.0",
    "gn:asciiname":"Barrio de San Jose",
    "gn:country_code":"MX",
    "gn:dem":124,
    "gn:feature_class":"P",
    "gn:feature_code":"PPL",
    "gn:name":"Barrio de San Jos\u00e9",
    "gn:population":107,
    "gn:timezone":"America/Mexico_City",
    "iso:country":"MX",
    "name:und_x_variant":[
        "Barrio de San Jos\u00e9"
    ],
    "wof:name":"Barrio de San Jose",
    "wof:placetype":"locality",
    "wof:population":107
},
  "geometry": {"coordinates":[-103.47333,18.50417],"type":"Point"}
}