{
  "type": "Feature",
  "properties": {
    "gn:admin1_code":"11",
    "gn:admin2_code":"17",
    "gn:asciiname":"Tronconales",
    "gn:country_code":"MX",
    "gn:dem":1704,
    "gn:feature_class":"P",
    "gn:feature_code":"PPL",
    "gn:name":"Tronconales",
    "gn:population":20,
    "gn:timezone":"America/Mexico_City",
    "iso:country":"MX",
    "wof:name":"Tronconales",
    "wof:placetype":"locality",
    "wof:population":20
},
  "geometry": {"coordinates":[-101.41083,20.51778],"type":"Point"}
}