{
  "type": "Feature",
  "properties": {
    "gn:admin1_code":"30.0",
    "gn:admin2_code":"161.0",
    "gn:asciiname":"Santa Ada",
    "gn:country_code":"MX",
    "gn:dem":84,
    "gn:feature_class":"P",
    "gn:feature_code":"PPL",
    "gn:name":"Santa Ada",
    "gn:population":2,
    "gn:timezone":"America/Mexico_City",
    "iso:country":"MX",
    "name:spa_x_preferred":[
        "Santa Ada"
    ],
    "wof:name":"Santa Ada",
    "wof:placetype":"locality",
    "wof:population":2
},
  "geometry": {"coordinates":[-98.36111,21.52194],"type":"Point"}
}