{
  "type": "Feature",
  "properties": {
    "gn:admin1_code":"24",
    "gn:admin2_code":"12",
    "gn:asciiname":"Aljuantzintla",
    "gn:country_code":"MX",
    "gn:dem":163,
    "gn:feature_class":"P",
    "gn:feature_code":"PPL",
    "gn:name":"Aljuantzintla",
    "gn:population":36,
    "gn:timezone":"America/Mexico_City",
    "iso:country":"MX",
    "wof:name":"Aljuantzintla",
    "wof:placetype":"locality",
    "wof:population":36
},
  "geometry": {"coordinates":[-98.91306,21.55611],"type":"Point"}
}