{
  "type": "Feature",
  "properties": {
    "gn:admin1_code":"30",
    "gn:admin2_code":"144.0",
    "gn:asciiname":"San Jose del Palmar",
    "gn:country_code":"MX",
    "gn:dem":30,
    "gn:feature_class":"P",
    "gn:feature_code":"PPL",
    "gn:name":"San Jos\u00e9 del Palmar",
    "gn:population":88,
    "gn:timezone":"America/Mexico_City",
    "iso:country":"MX",
    "name:und_x_variant":[
        "San Jos\u00e9 del Palmar"
    ],
    "wof:name":"San Jose del Palmar",
    "wof:placetype":"locality",
    "wof:population":88
},
  "geometry": {"coordinates":[-94.82306,17.68111],"type":"Point"}
}