{
  "type": "Feature",
  "properties": {
    "gn:admin1_code":"15",
    "gn:admin2_code":"90.0",
    "gn:asciiname":"Colonia San Jose",
    "gn:country_code":"MX",
    "gn:dem":2588,
    "gn:feature_class":"P",
    "gn:feature_code":"PPL",
    "gn:name":"Colonia San Jos\u00e9",
    "gn:population":424,
    "gn:timezone":"America/Mexico_City",
    "iso:country":"MX",
    "name:und_x_variant":[
        "Colonia San Jos\u00e9"
    ],
    "wof:name":"Colonia San Jose",
    "wof:placetype":"locality",
    "wof:population":424
},
  "geometry": {"coordinates":[-99.57277999999999,19.10861],"type":"Point"}
}