{
  "type": "Feature",
  "properties": {
    "gn:admin1_code":"21",
    "gn:admin2_code":"35.0",
    "gn:asciiname":"Lomas del Paraiso",
    "gn:country_code":"MX",
    "gn:dem":1125,
    "gn:feature_class":"P",
    "gn:feature_code":"PPL",
    "gn:name":"Lomas del Para\u00edso",
    "gn:population":6,
    "gn:timezone":"America/Mexico_City",
    "iso:country":"MX",
    "name:und_x_variant":[
        "Lomas del Para\u00edso"
    ],
    "wof:name":"Lomas del Paraiso",
    "wof:placetype":"locality",
    "wof:population":6
},
  "geometry": {"coordinates":[-97.16435,18.30071],"type":"Point"}
}