{
  "type": "Feature",
  "properties": {
    "gn:admin1_code":"20.0",
    "gn:admin2_code":"465.0",
    "gn:asciiname":"Corral de Piedra",
    "gn:country_code":"MX",
    "gn:dem":657,
    "gn:feature_class":"P",
    "gn:feature_code":"PPL",
    "gn:name":"Corral de Piedra",
    "gn:population":0,
    "gn:timezone":"America/Mexico_City",
    "iso:country":"MX",
    "name:spa_x_preferred":[
        "Corral de Piedra"
    ],
    "wof:name":"Corral de Piedra",
    "wof:placetype":"locality"
},
  "geometry": {"coordinates":[-95.5955,16.88709],"type":"Point"}
}