{
  "type": "Feature",
  "properties": {
    "gn:admin1_code":"5",
    "gn:admin2_code":"1",
    "gn:asciiname":"Playa Ines Seccion Dos",
    "gn:country_code":"MX",
    "gn:dem":85,
    "gn:feature_class":"P",
    "gn:feature_code":"PPL",
    "gn:name":"Playa In\u00e9s Secci\u00f3n Dos",
    "gn:population":21,
    "gn:timezone":"America/Mexico_City",
    "iso:country":"MX",
    "name:und_x_variant":[
        "Playa In\u00e9s Secci\u00f3n Dos"
    ],
    "wof:name":"Playa Ines Seccion Dos",
    "wof:placetype":"locality",
    "wof:population":21
},
  "geometry": {"coordinates":[-92.66500000000001,15.33778],"type":"Point"}
}