{
  "type": "Feature",
  "properties": {
    "gn:admin1_code":"30",
    "gn:admin2_code":"121.0",
    "gn:asciiname":"La Reforma",
    "gn:country_code":"MX",
    "gn:dem":68,
    "gn:feature_class":"P",
    "gn:feature_code":"PPL",
    "gn:name":"La Reforma",
    "gn:population":7,
    "gn:timezone":"America/Mexico_City",
    "iso:country":"MX",
    "name:cym_x_preferred":[
        "La Reforma"
    ],
    "name:nld_x_preferred":[
        "Reforma"
    ],
    "name:por_x_preferred":[
        "La Reforma"
    ],
    "wof:name":"La Reforma",
    "wof:placetype":"locality",
    "wof:population":7
},
  "geometry": {"coordinates":[-97.98111,21.48111],"type":"Point"}
}