{
  "type": "Feature",
  "properties": {
    "gn:admin1_code":"11",
    "gn:admin2_code":"17.0",
    "gn:asciiname":"Granja de los Castaneda",
    "gn:country_code":"MX",
    "gn:dem":1726,
    "gn:feature_class":"P",
    "gn:feature_code":"PPL",
    "gn:name":"Granja de los Casta\u00f1eda",
    "gn:population":7,
    "gn:timezone":"America/Mexico_City",
    "iso:country":"MX",
    "name:und_x_variant":[
        "Granja de los Casta\u00f1eda"
    ],
    "wof:name":"Granja de los Castaneda",
    "wof:placetype":"locality",
    "wof:population":7
},
  "geometry": {"coordinates":[-101.31139,20.64056],"type":"Point"}
}