{
  "type": "Feature",
  "properties": {
    "gn:admin1_code":"12",
    "gn:admin2_code":"71",
    "gn:asciiname":"Arroyo Platanar",
    "gn:country_code":"MX",
    "gn:dem":737,
    "gn:feature_class":"P",
    "gn:feature_code":"PPL",
    "gn:name":"Arroyo Platanar",
    "gn:population":20,
    "gn:timezone":"America/Mexico_City",
    "iso:country":"MX",
    "wof:name":"Arroyo Platanar",
    "wof:placetype":"locality",
    "wof:population":20
},
  "geometry": {"coordinates":[-98.15609000000001,16.92168],"type":"Point"}
}