{
  "type": "Feature",
  "properties": {
    "gn:admin1_code":"7",
    "gn:admin2_code":"19.0",
    "gn:asciiname":"Mi Ranchito",
    "gn:country_code":"MX",
    "gn:dem":362,
    "gn:feature_class":"P",
    "gn:feature_code":"PPL",
    "gn:name":"Mi Ranchito",
    "gn:population":8,
    "gn:timezone":"America/Monterrey",
    "iso:country":"MX",
    "wof:name":"Mi Ranchito",
    "wof:placetype":"locality",
    "wof:population":8
},
  "geometry": {"coordinates":[-100.86759000000001,28.41191],"type":"Point"}
}