{
  "type": "Feature",
  "properties": {
    "gn:admin1_code":"10",
    "gn:admin2_code":"5.0",
    "gn:asciiname":"Jesus Gonzalez Ortega (Pericos)",
    "gn:country_code":"MX",
    "gn:dem":2382,
    "gn:feature_class":"P",
    "gn:feature_code":"PPL",
    "gn:name":"Jes\u00fas Gonz\u00e1lez Ortega (Pericos)",
    "gn:population":161,
    "gn:timezone":"America/Monterrey",
    "iso:country":"MX",
    "wof:name":"Jesus Gonzalez Ortega (Pericos)",
    "wof:placetype":"locality",
    "wof:population":161
},
  "geometry": {"coordinates":[-105.05365,24.17376],"type":"Point"}
}