{
  "type": "Feature",
  "properties": {
    "gn:admin1_code":"16",
    "gn:admin2_code":"53.0",
    "gn:asciiname":"Nueva Florida",
    "gn:country_code":"MX",
    "gn:dem":2045,
    "gn:feature_class":"P",
    "gn:feature_code":"PPL",
    "gn:name":"Nueva Florida",
    "gn:population":460,
    "gn:timezone":"America/Mexico_City",
    "iso:country":"MX",
    "wof:name":"Nueva Florida",
    "wof:placetype":"locality",
    "wof:population":460
},
  "geometry": {"coordinates":[-101.29611,19.5925],"type":"Point"}
}