{
  "type": "Feature",
  "properties": {
    "gn:admin1_code":"20",
    "gn:admin2_code":"42.0",
    "gn:asciiname":"Yahuiche",
    "gn:country_code":"MX",
    "gn:dem":1807,
    "gn:feature_class":"P",
    "gn:feature_code":"PPL",
    "gn:name":"Yahuiche",
    "gn:population":0,
    "gn:timezone":"America/Mexico_City",
    "iso:country":"MX",
    "name:spa_x_preferred":[
        "Yahuiche"
    ],
    "name:und_x_variant":[
        "Yalmiche",
        "Yahui",
        "Santa Mar\u00eda Yahuiche"
    ],
    "wof:name":"Yahuiche",
    "wof:placetype":"locality"
},
  "geometry": {"coordinates":[-96.48258,17.30019],"type":"Point"}
}