{
  "type": "Feature",
  "properties": {
    "gn:admin1_code":"6",
    "gn:admin2_code":"56.0",
    "gn:asciiname":"Morales",
    "gn:country_code":"MX",
    "gn:dem":1512,
    "gn:feature_class":"P",
    "gn:feature_code":"PPL",
    "gn:name":"Morales",
    "gn:population":0,
    "gn:timezone":"America/Chihuahua",
    "iso:country":"MX",
    "wof:name":"Morales",
    "wof:placetype":"locality"
},
  "geometry": {"coordinates":[-106.31667,27.15],"type":"Point"}
}