{
  "type": "Feature",
  "properties": {
    "gn:admin1_code":"16",
    "gn:admin2_code":"17.0",
    "gn:asciiname":"Atotonilco",
    "gn:country_code":"MX",
    "gn:dem":2322,
    "gn:feature_class":"P",
    "gn:feature_code":"PPL",
    "gn:name":"Atotonilco",
    "gn:population":1401,
    "gn:timezone":"America/Mexico_City",
    "iso:country":"MX",
    "name:ceb_x_preferred":[
        "Atotonilco"
    ],
    "name:deu_x_preferred":[
        "Atotonilco"
    ],
    "name:ita_x_preferred":[
        "Atotonilco"
    ],
    "name:sco_x_preferred":[
        "Atotonilco"
    ],
    "name:spa_x_preferred":[
        "Atotonilco"
    ],
    "name:swe_x_preferred":[
        "Atotonilco"
    ],
    "wof:name":"Atotonilco",
    "wof:placetype":"locality",
    "wof:population":1401
},
  "geometry": {"coordinates":[-100.22306,19.94111],"type":"Point"}
}