{
  "type": "Feature",
  "properties": {
    "gn:admin1_code":"30",
    "gn:admin2_code":"11.0",
    "gn:asciiname":"Santa Catarina",
    "gn:country_code":"MX",
    "gn:dem":3,
    "gn:feature_class":"P",
    "gn:feature_code":"PPL",
    "gn:name":"Santa Catarina",
    "gn:population":6,
    "gn:timezone":"America/Mexico_City",
    "iso:country":"MX",
    "name:bre_x_preferred":[
        "Santa Catarina"
    ],
    "name:cat_x_preferred":[
        "Santa Catarina"
    ],
    "name:ceb_x_preferred":[
        "Santa Catarina"
    ],
    "name:deu_x_preferred":[
        "Santa Catarina"
    ],
    "name:epo_x_preferred":[
        "Sankta Katarino"
    ],
    "name:fin_x_preferred":[
        "Santa Catarina"
    ],
    "name:fra_x_preferred":[
        "Santa Catarina"
    ],
    "name:glg_x_preferred":[
        "Santa Catarina"
    ],
    "name:hrv_x_preferred":[
        "Santa Catarina"
    ],
    "name:hun_x_preferred":[
        "Santa Catarina"
    ],
    "name:ita_x_preferred":[
        "Santa Catarina"
    ],
    "name:jpn_x_preferred":[
        "\u30b5\u30f3\u30bf\u30ab\u30bf\u30ea\u30ca"
    ],
    "name:kor_x_preferred":[
        "\uc0b0\ud0c0\uce74\ud0c0\ub9ac\ub098"
    ],
    "name:nld_x_preferred":[
        "Santa Catarina"
    ],
    "name:nor_x_preferred":[
        "Santa Catarina"
    ],
    "name:pol_x_preferred":[
        "Santa Catarina"
    ],
    "name:por_x_preferred":[
        "Santa Catarina"
    ],
    "name:rus_x_preferred":[
        "\u0421\u0430\u043d\u0442\u0430-\u041a\u0430\u0442\u0430\u0440\u0438\u043d\u0430"
    ],
    "name:scn_x_preferred":[
        "Santa Catarina"
    ],
    "name:sco_x_preferred":[
        "Santa Catarina"
    ],
    "name:spa_x_preferred":[
        "Santa Catarina"
    ],
    "name:srp_x_preferred":[
        "\u0421\u0430\u043d\u0442\u0430 \u041a\u0430\u0442\u0430\u0440\u0438\u043d\u0430"
    ],
    "name:swe_x_preferred":[
        "Santa Catarina"
    ],
    "name:tur_x_preferred":[
        "Santa Catarina"
    ],
    "name:ukr_x_preferred":[
        "\u0421\u0430\u043d\u0442\u0430-\u041a\u0430\u0442\u0430\u0440\u0456\u043d\u0430"
    ],
    "wof:name":"Santa Catarina",
    "wof:placetype":"locality",
    "wof:population":6
},
  "geometry": {"coordinates":[-95.78944,18.69639],"type":"Point"}
}