{
  "type": "Feature",
  "properties": {
    "gn:admin1_code":"16",
    "gn:admin2_code":"6",
    "gn:asciiname":"Pororicua",
    "gn:country_code":"MX",
    "gn:dem":794,
    "gn:feature_class":"P",
    "gn:feature_code":"PPL",
    "gn:name":"Pororicua",
    "gn:population":11,
    "gn:timezone":"America/Mexico_City",
    "iso:country":"MX",
    "wof:name":"Pororicua",
    "wof:placetype":"locality",
    "wof:population":11
},
  "geometry": {"coordinates":[-102.39028,18.835],"type":"Point"}
}