{
  "type": "Feature",
  "properties": {
    "gn:admin1_code":"32",
    "gn:asciiname":"Las Latas",
    "gn:country_code":"MX",
    "gn:dem":2052,
    "gn:feature_class":"P",
    "gn:feature_code":"PPL",
    "gn:name":"Las Latas",
    "gn:population":0,
    "gn:timezone":"America/Mexico_City",
    "iso:country":"MX",
    "name:spa_x_preferred":[
        "Las Latas"
    ],
    "wof:name":"Las Latas",
    "wof:placetype":"locality"
},
  "geometry": {"coordinates":[-104.19247,22.4853],"type":"Point"}
}