{
  "type": "Feature",
  "properties": {
    "gn:admin1_code":"30",
    "gn:admin2_code":"97.0",
    "gn:asciiname":"Colonia Poza Rica",
    "gn:country_code":"MX",
    "gn:dem":9,
    "gn:feature_class":"P",
    "gn:feature_code":"PPL",
    "gn:name":"Colonia Poza Rica",
    "gn:population":78,
    "gn:timezone":"America/Mexico_City",
    "iso:country":"MX",
    "wof:name":"Colonia Poza Rica",
    "wof:placetype":"locality",
    "wof:population":78
},
  "geometry": {"coordinates":[-95.52667,18.61806],"type":"Point"}
}