{
  "type": "Feature",
  "properties": {
    "gn:admin1_code":"17.0",
    "gn:asciiname":"Temilpa Viejo",
    "gn:country_code":"MX",
    "gn:dem":960,
    "gn:feature_class":"P",
    "gn:feature_code":"PPL",
    "gn:name":"Temilpa Viejo",
    "gn:population":0,
    "gn:timezone":"America/Mexico_City",
    "iso:country":"MX",
    "name:spa_x_preferred":[
        "Temilpa Viejo"
    ],
    "wof:name":"Temilpa Viejo",
    "wof:placetype":"locality"
},
  "geometry": {"coordinates":[-99.10500999999999,18.69997],"type":"Point"}
}