{
  "type": "Feature",
  "properties": {
    "gn:admin1_code":"26",
    "gn:admin2_code":"30.0",
    "gn:asciiname":"Las Bombas",
    "gn:country_code":"MX",
    "gn:dem":254,
    "gn:feature_class":"P",
    "gn:feature_code":"PPL",
    "gn:name":"Las Bombas",
    "gn:population":0,
    "gn:timezone":"America/Hermosillo",
    "iso:country":"MX",
    "name:spa_x_preferred":[
        "Las Bombas"
    ],
    "wof:name":"Las Bombas",
    "wof:placetype":"locality"
},
  "geometry": {"coordinates":[-110.77294000000001,29.17838],"type":"Point"}
}