{
  "type": "Feature",
  "properties": {
    "gn:admin1_code":"5",
    "gn:admin2_code":"108",
    "gn:asciiname":"Nueva Holanda",
    "gn:country_code":"MX",
    "gn:dem":633,
    "gn:feature_class":"P",
    "gn:feature_code":"PPL",
    "gn:name":"Nueva Holanda",
    "gn:population":13,
    "gn:timezone":"America/Mexico_City",
    "iso:country":"MX",
    "wof:name":"Nueva Holanda",
    "wof:placetype":"locality",
    "wof:population":13
},
  "geometry": {"coordinates":[-93.35944000000001,16.40306],"type":"Point"}
}