{
  "type": "Feature",
  "properties": {
    "gn:admin1_code":"3",
    "gn:admin2_code":"2.0",
    "gn:asciiname":"Ninguno [CINE]",
    "gn:country_code":"MX",
    "gn:dem":2,
    "gn:feature_class":"P",
    "gn:feature_code":"PPL",
    "gn:name":"Ninguno [CINE]",
    "gn:population":88,
    "gn:timezone":"America/Mazatlan",
    "iso:country":"MX",
    "wof:name":"Ninguno [CINE]",
    "wof:placetype":"locality",
    "wof:population":88
},
  "geometry": {"coordinates":[-112.21584,27.20854000000001],"type":"Point"}
}