{
  "type": "Feature",
  "properties": {
    "gn:admin1_code":"27",
    "gn:admin2_code":"1.0",
    "gn:asciiname":"Frente Unico",
    "gn:country_code":"MX",
    "gn:dem":7,
    "gn:feature_class":"P",
    "gn:feature_code":"PPL",
    "gn:name":"Frente \u00danico",
    "gn:population":55,
    "gn:timezone":"America/Mexico_City",
    "iso:country":"MX",
    "name:und_x_variant":[
        "Frente \u00danico"
    ],
    "wof:name":"Frente Unico",
    "wof:placetype":"locality",
    "wof:population":55
},
  "geometry": {"coordinates":[-91.51139000000001,17.78611],"type":"Point"}
}