{
  "type": "Feature",
  "properties": {
    "gn:admin1_code":"30",
    "gn:admin2_code":"8.0",
    "gn:asciiname":"Tiopa",
    "gn:country_code":"MX",
    "gn:dem":1942,
    "gn:feature_class":"P",
    "gn:feature_code":"PPL",
    "gn:name":"Tiopa",
    "gn:population":0,
    "gn:timezone":"America/Mexico_City",
    "iso:country":"MX",
    "name:spa_x_preferred":[
        "Tiopa"
    ],
    "wof:name":"Tiopa",
    "wof:placetype":"locality"
},
  "geometry": {"coordinates":[-97.11190999999999,19.11502],"type":"Point"}
}