{
  "type": "Feature",
  "properties": {
    "gn:admin1_code":"16",
    "gn:admin2_code":"96.0",
    "gn:asciiname":"El Tejamanil",
    "gn:country_code":"MX",
    "gn:dem":645,
    "gn:feature_class":"P",
    "gn:feature_code":"PPL",
    "gn:name":"El Tejamanil",
    "gn:population":6,
    "gn:timezone":"America/Mexico_City",
    "iso:country":"MX",
    "wof:name":"El Tejamanil",
    "wof:placetype":"locality",
    "wof:population":6
},
  "geometry": {"coordinates":[-102.74558,18.45914],"type":"Point"}
}