{
  "type": "Feature",
  "properties": {
    "gn:admin1_code":"22",
    "gn:admin2_code":"5.0",
    "gn:asciiname":"Tepozan",
    "gn:cc2":"MX",
    "gn:country_code":"MX",
    "gn:dem":2233,
    "gn:feature_class":"P",
    "gn:feature_code":"PPL",
    "gn:name":"Tepoz\u00e1n",
    "gn:population":0,
    "gn:timezone":"America/Mexico_City",
    "iso:country":"MX",
    "name:und_x_variant":[
        "El Tepoz\u00e1n",
        "Tepoz\u00e1n"
    ],
    "wof:name":"Tepozan",
    "wof:placetype":"locality"
},
  "geometry": {"coordinates":[-100.13333,20.78333],"type":"Point"}
}