{
  "type": "Feature",
  "properties": {
    "gn:admin1_code":"26.0",
    "gn:admin2_code":"15.0",
    "gn:asciiname":"Tamaya",
    "gn:country_code":"MX",
    "gn:dem":1136,
    "gn:feature_class":"P",
    "gn:feature_code":"PPL",
    "gn:name":"Tamaya",
    "gn:population":0,
    "gn:timezone":"America/Hermosillo",
    "iso:country":"MX",
    "name:deu_x_preferred":[
        "Tamaya"
    ],
    "name:jpn_x_preferred":[
        "\u7956\u970a\u820e"
    ],
    "name:spa_x_preferred":[
        "Tamaya"
    ],
    "wof:name":"Tamaya",
    "wof:placetype":"locality"
},
  "geometry": {"coordinates":[-108.81444999999999,30.52871],"type":"Point"}
}