{
  "type": "Feature",
  "properties": {
    "gn:admin1_code":"5",
    "gn:admin2_code":"31",
    "gn:asciiname":"Nuevo Limonal",
    "gn:country_code":"MX",
    "gn:dem":1223,
    "gn:feature_class":"P",
    "gn:feature_code":"PPL",
    "gn:name":"Nuevo Limonal",
    "gn:population":52,
    "gn:timezone":"America/Mexico_City",
    "iso:country":"MX",
    "wof:name":"Nuevo Limonal",
    "wof:placetype":"locality",
    "wof:population":52
},
  "geometry": {"coordinates":[-92.23944,16.98889],"type":"Point"}
}