{
  "type": "Feature",
  "properties": {
    "gn:admin1_code":"5",
    "gn:admin2_code":"61.0",
    "gn:asciiname":"Nicolas Bravo",
    "gn:country_code":"MX",
    "gn:dem":435,
    "gn:feature_class":"P",
    "gn:feature_code":"PPL",
    "gn:name":"Nicol\u00e1s Bravo",
    "gn:population":367,
    "gn:timezone":"America/Mexico_City",
    "iso:country":"MX",
    "name:und_x_variant":[
        "Nicol\u00e1s Bravo"
    ],
    "wof:name":"Nicolas Bravo",
    "wof:placetype":"locality",
    "wof:population":367
},
  "geometry": {"coordinates":[-93.64389,17.09528],"type":"Point"}
}