{
  "type": "Feature",
  "properties": {
    "gn:admin1_code":"24",
    "gn:admin2_code":"36.0",
    "gn:asciiname":"La Ceibita",
    "gn:country_code":"MX",
    "gn:dem":281,
    "gn:feature_class":"P",
    "gn:feature_code":"PPL",
    "gn:name":"La Ceibita",
    "gn:population":7,
    "gn:timezone":"America/Mexico_City",
    "iso:country":"MX",
    "wof:name":"La Ceibita",
    "wof:placetype":"locality",
    "wof:population":7
},
  "geometry": {"coordinates":[-99.27611,21.76833],"type":"Point"}
}