{
  "type": "Feature",
  "properties": {
    "gn:admin1_code":"25",
    "gn:admin2_code":"6.0",
    "gn:asciiname":"Las Chicuras",
    "gn:country_code":"MX",
    "gn:dem":164,
    "gn:feature_class":"P",
    "gn:feature_code":"PPL",
    "gn:name":"Las Chicuras",
    "gn:population":7,
    "gn:timezone":"America/Mazatlan",
    "iso:country":"MX",
    "wof:name":"Las Chicuras",
    "wof:placetype":"locality",
    "wof:population":7
},
  "geometry": {"coordinates":[-107.02424999999999,24.87344],"type":"Point"}
}