{
  "type": "Feature",
  "properties": {
    "gn:admin1_code":"24",
    "gn:admin2_code":"13",
    "gn:asciiname":"Jacinto Lopez",
    "gn:country_code":"MX",
    "gn:dem":193,
    "gn:feature_class":"P",
    "gn:feature_code":"PPL",
    "gn:name":"Jacinto L\u00f3pez",
    "gn:population":14,
    "gn:timezone":"America/Mexico_City",
    "iso:country":"MX",
    "name:und_x_variant":[
        "Jacinto L\u00f3pez"
    ],
    "wof:name":"Jacinto Lopez",
    "wof:placetype":"locality",
    "wof:population":14
},
  "geometry": {"coordinates":[-98.92306000000001,21.9325],"type":"Point"}
}