{
  "type": "Feature",
  "properties": {
    "gn:admin1_code":"22",
    "gn:admin2_code":"4",
    "gn:asciiname":"Familia Medina",
    "gn:country_code":"MX",
    "gn:dem":2054,
    "gn:feature_class":"P",
    "gn:feature_code":"PPL",
    "gn:name":"Familia Medina",
    "gn:population":10,
    "gn:timezone":"America/Mexico_City",
    "iso:country":"MX",
    "wof:name":"Familia Medina",
    "wof:placetype":"locality",
    "wof:population":10
},
  "geometry": {"coordinates":[-99.78667,20.7025],"type":"Point"}
}