{
  "type": "Feature",
  "properties": {
    "gn:admin1_code":"6",
    "gn:admin2_code":"36",
    "gn:asciiname":"El Cafetal",
    "gn:country_code":"MX",
    "gn:dem":1349,
    "gn:feature_class":"P",
    "gn:feature_code":"PPL",
    "gn:name":"El Cafetal",
    "gn:population":12,
    "gn:timezone":"America/Chihuahua",
    "iso:country":"MX",
    "name:spa_x_preferred":[
        "El Cafetal"
    ],
    "wof:name":"El Cafetal",
    "wof:placetype":"locality",
    "wof:population":12
},
  "geometry": {"coordinates":[-104.83257999999999,27.21522],"type":"Point"}
}