{
  "type": "Feature",
  "properties": {
    "gn:admin1_code":"10.0",
    "gn:admin2_code":"34.0",
    "gn:asciiname":"La Rinconada",
    "gn:country_code":"MX",
    "gn:dem":2555,
    "gn:feature_class":"P",
    "gn:feature_code":"PPL",
    "gn:name":"La Rinconada",
    "gn:population":0,
    "gn:timezone":"America/Monterrey",
    "iso:country":"MX",
    "name:spa_x_preferred":[
        "La Rinconada"
    ],
    "wof:name":"La Rinconada",
    "wof:placetype":"locality"
},
  "geometry": {"coordinates":[-106.85973,25.46915],"type":"Point"}
}