{
  "type": "Feature",
  "properties": {
    "gn:admin1_code":"6.0",
    "gn:admin2_code":"5.0",
    "gn:asciiname":"Casa de Madera",
    "gn:country_code":"MX",
    "gn:dem":1256,
    "gn:feature_class":"P",
    "gn:feature_code":"PPL",
    "gn:name":"Casa de Madera",
    "gn:population":0,
    "gn:timezone":"America/Chihuahua",
    "iso:country":"MX",
    "name:und_x_variant":[
        "Casa Madera"
    ],
    "wof:name":"Casa de Madera",
    "wof:placetype":"locality"
},
  "geometry": {"coordinates":[-108.10762,31.46539000000001],"type":"Point"}
}