{
  "type": "Feature",
  "properties": {
    "gn:admin1_code":"30",
    "gn:admin2_code":"9",
    "gn:asciiname":"La Guadalupe",
    "gn:country_code":"MX",
    "gn:dem":811,
    "gn:feature_class":"P",
    "gn:feature_code":"PPL",
    "gn:name":"La Guadalupe",
    "gn:population":12,
    "gn:timezone":"America/Mexico_City",
    "iso:country":"MX",
    "wof:name":"La Guadalupe",
    "wof:placetype":"locality",
    "wof:population":12
},
  "geometry": {"coordinates":[-96.60639,19.76194],"type":"Point"}
}