{
  "type": "Feature",
  "properties": {
    "gn:admin1_code":"6",
    "gn:admin2_code":"41.0",
    "gn:asciiname":"Chureachi",
    "gn:country_code":"MX",
    "gn:dem":1947,
    "gn:feature_class":"P",
    "gn:feature_code":"PPL",
    "gn:name":"Chureachi",
    "gn:population":0,
    "gn:timezone":"America/Chihuahua",
    "iso:country":"MX",
    "name:spa_x_preferred":[
        "Chureachi"
    ],
    "wof:name":"Chureachi",
    "wof:placetype":"locality"
},
  "geometry": {"coordinates":[-107.96420000000001,27.67491],"type":"Point"}
}