{
  "type": "Feature",
  "properties": {
    "gn:admin1_code":"24",
    "gn:admin2_code":"45",
    "gn:asciiname":"Toledo",
    "gn:country_code":"MX",
    "gn:dem":2059,
    "gn:feature_class":"P",
    "gn:feature_code":"PPL",
    "gn:name":"Toledo",
    "gn:population":25,
    "gn:timezone":"America/Mexico_City",
    "iso:country":"MX",
    "wof:name":"Toledo",
    "wof:placetype":"locality",
    "wof:population":25
},
  "geometry": {"coordinates":[-101.32222,22.94361],"type":"Point"}
}