{
  "type": "Feature",
  "properties": {
    "gn:admin1_code":"20",
    "gn:admin2_code":"123.0",
    "gn:asciiname":"Asuncion Mixtepec",
    "gn:country_code":"MX",
    "gn:dem":2076,
    "gn:feature_class":"P",
    "gn:feature_code":"PPL",
    "gn:name":"Asunci\u00f3n Mixtepec",
    "gn:population":0,
    "gn:timezone":"America/Mexico_City",
    "iso:country":"MX",
    "name:und_x_variant":[
        "Mixtepec",
        "Asuncion",
        "Asunci\u00f3n Mixtepec"
    ],
    "wof:name":"Asuncion Mixtepec",
    "wof:placetype":"locality"
},
  "geometry": {"coordinates":[-96.96601,16.86694],"type":"Point"}
}