{
  "type": "Feature",
  "properties": {
    "gn:admin1_code":"14.0",
    "gn:admin2_code":"53.0",
    "gn:asciiname":"Los Ocotes",
    "gn:country_code":"MX",
    "gn:dem":1945,
    "gn:feature_class":"P",
    "gn:feature_code":"PPL",
    "gn:name":"Los Ocotes",
    "gn:population":0,
    "gn:timezone":"America/Mexico_City",
    "iso:country":"MX",
    "name:spa_x_preferred":[
        "Los Ocotes"
    ],
    "wof:name":"Los Ocotes",
    "wof:placetype":"locality"
},
  "geometry": {"coordinates":[-102.10275,21.45089],"type":"Point"}
}