{
  "type": "Feature",
  "properties": {
    "gn:admin1_code":"23",
    "gn:admin2_code":"4.0",
    "gn:asciiname":"Los Alacranes",
    "gn:country_code":"MX",
    "gn:dem":11,
    "gn:feature_class":"P",
    "gn:feature_code":"PPL",
    "gn:name":"Los Alacranes",
    "gn:population":7,
    "gn:timezone":"America/Cancun",
    "iso:country":"MX",
    "wof:name":"Los Alacranes",
    "wof:placetype":"locality",
    "wof:population":7
},
  "geometry": {"coordinates":[-88.10972,19.03889],"type":"Point"}
}