{
  "type": "Feature",
  "properties": {
    "gn:admin1_code":"15",
    "gn:admin2_code":"106.0",
    "gn:asciiname":"La Loma Cuexcontitlan",
    "gn:country_code":"MX",
    "gn:dem":2651,
    "gn:feature_class":"P",
    "gn:feature_code":"PPL",
    "gn:name":"La Loma Cuexcontitl\u00e1n",
    "gn:population":1084,
    "gn:timezone":"America/Mexico_City",
    "iso:country":"MX",
    "name:und_x_variant":[
        "La Loma Cuexcontitl\u00e1n"
    ],
    "wof:name":"La Loma Cuexcontitlan",
    "wof:placetype":"locality",
    "wof:population":1084
},
  "geometry": {"coordinates":[-99.64888999999999,19.38],"type":"Point"}
}