{
  "type": "Feature",
  "properties": {
    "gn:admin1_code":"12",
    "gn:admin2_code":"12.0",
    "gn:asciiname":"El Cortijo",
    "gn:country_code":"MX",
    "gn:dem":359,
    "gn:feature_class":"P",
    "gn:feature_code":"PPL",
    "gn:name":"El Cortijo",
    "gn:population":1979,
    "gn:timezone":"America/Mexico_City",
    "iso:country":"MX",
    "wof:name":"El Cortijo",
    "wof:placetype":"locality",
    "wof:population":1979
},
  "geometry": {"coordinates":[-99.14888999999999,16.98972],"type":"Point"}
}