{
  "type": "Feature",
  "properties": {
    "gn:admin1_code":"4",
    "gn:admin2_code":"1.0",
    "gn:asciiname":"El Gran Poder",
    "gn:country_code":"MX",
    "gn:dem":10,
    "gn:feature_class":"P",
    "gn:feature_code":"PPL",
    "gn:name":"El Gran Poder",
    "gn:population":5,
    "gn:timezone":"America/Merida",
    "iso:country":"MX",
    "wof:name":"El Gran Poder",
    "wof:placetype":"locality",
    "wof:population":5
},
  "geometry": {"coordinates":[-90.12166999999999,20.39333],"type":"Point"}
}