{
  "type": "Feature",
  "properties": {
    "gn:admin1_code":"20",
    "gn:admin2_code":"178",
    "gn:asciiname":"El Mangal",
    "gn:country_code":"MX",
    "gn:dem":1814,
    "gn:feature_class":"P",
    "gn:feature_code":"PPL",
    "gn:name":"El Mangal",
    "gn:population":18,
    "gn:timezone":"America/Mexico_City",
    "iso:country":"MX",
    "wof:name":"El Mangal",
    "wof:placetype":"locality",
    "wof:population":18
},
  "geometry": {"coordinates":[-96.76806000000001,17.22028],"type":"Point"}
}