{
  "type": "Feature",
  "properties": {
    "gn:admin1_code":"24",
    "gn:admin2_code":"55.0",
    "gn:asciiname":"Longoria",
    "gn:country_code":"MX",
    "gn:dem":1976,
    "gn:feature_class":"P",
    "gn:feature_code":"PPL",
    "gn:name":"Longoria",
    "gn:population":140,
    "gn:timezone":"America/Mexico_City",
    "iso:country":"MX",
    "wof:name":"Longoria",
    "wof:placetype":"locality",
    "wof:population":140
},
  "geometry": {"coordinates":[-100.70944,21.95667000000001],"type":"Point"}
}