{
  "type": "Feature",
  "properties": {
    "gn:admin1_code":"4.0",
    "gn:asciiname":"El Jobo",
    "gn:country_code":"MX",
    "gn:dem":-2,
    "gn:feature_class":"P",
    "gn:feature_code":"PPL",
    "gn:name":"El Jobo",
    "gn:population":0,
    "gn:timezone":"America/Merida",
    "iso:country":"MX",
    "name:spa_x_preferred":[
        "El Jobo"
    ],
    "wof:name":"El Jobo",
    "wof:placetype":"locality"
},
  "geometry": {"coordinates":[-91.51049999999999,18.41283],"type":"Point"}
}