{
  "type": "Feature",
  "properties": {
    "gn:admin1_code":"20",
    "gn:admin2_code":"154.0",
    "gn:asciiname":"Yojuela",
    "gn:country_code":"MX",
    "gn:dem":1810,
    "gn:feature_class":"P",
    "gn:feature_code":"PPL",
    "gn:name":"Yojuela",
    "gn:population":589,
    "gn:timezone":"America/Mexico_City",
    "iso:country":"MX",
    "wof:name":"Yojuela",
    "wof:placetype":"locality",
    "wof:population":589
},
  "geometry": {"coordinates":[-96.41139,16.26806],"type":"Point"}
}