{
  "type": "Feature",
  "properties": {
    "gn:admin1_code":"5",
    "gn:admin2_code":"108.0",
    "gn:asciiname":"Santa Fe",
    "gn:country_code":"MX",
    "gn:dem":741,
    "gn:feature_class":"P",
    "gn:feature_code":"PPL",
    "gn:name":"Santa Fe",
    "gn:population":4,
    "gn:timezone":"America/Mexico_City",
    "iso:country":"MX",
    "wof:name":"Santa Fe",
    "wof:placetype":"locality",
    "wof:population":4
},
  "geometry": {"coordinates":[-93.48694,16.44194],"type":"Point"}
}