{
  "type": "Feature",
  "properties": {
    "gn:admin1_code":"19",
    "gn:admin2_code":"3.0",
    "gn:asciiname":"Corralitos",
    "gn:country_code":"MX",
    "gn:dem":144,
    "gn:feature_class":"P",
    "gn:feature_code":"PPL",
    "gn:name":"Corralitos",
    "gn:population":0,
    "gn:timezone":"America/Monterrey",
    "iso:country":"MX",
    "wof:name":"Corralitos",
    "wof:placetype":"locality"
},
  "geometry": {"coordinates":[-99.38333,26.13333],"type":"Point"}
}