{
  "type": "Feature",
  "properties": {
    "gn:admin1_code":"9",
    "gn:admin2_code":"12",
    "gn:asciiname":"Colonia Ocotla",
    "gn:country_code":"MX",
    "gn:dem":2822,
    "gn:feature_class":"P",
    "gn:feature_code":"PPL",
    "gn:name":"Colonia Ocotla",
    "gn:population":30,
    "gn:timezone":"America/Mexico_City",
    "iso:country":"MX",
    "wof:name":"Colonia Ocotla",
    "wof:placetype":"locality",
    "wof:population":30
},
  "geometry": {"coordinates":[-99.15946,19.21506],"type":"Point"}
}