{
  "type": "Feature",
  "properties": {
    "gn:admin1_code":"10.0",
    "gn:admin2_code":"35.0",
    "gn:asciiname":"Las Joyitas",
    "gn:country_code":"MX",
    "gn:dem":2295,
    "gn:feature_class":"P",
    "gn:feature_code":"PPL",
    "gn:name":"Las Joyitas",
    "gn:population":0,
    "gn:timezone":"America/Monterrey",
    "iso:country":"MX",
    "name:spa_x_preferred":[
        "Las Joyitas"
    ],
    "wof:name":"Las Joyitas",
    "wof:placetype":"locality"
},
  "geometry": {"coordinates":[-105.85128,25.48354],"type":"Point"}
}