{
  "type": "Feature",
  "properties": {
    "gn:admin1_code":"31",
    "gn:admin2_code":"85.0",
    "gn:asciiname":"Dzonot Ak",
    "gn:country_code":"MX",
    "gn:dem":30,
    "gn:feature_class":"P",
    "gn:feature_code":"PPL",
    "gn:name":"Dzonot Ak",
    "gn:population":0,
    "gn:timezone":"America/Merida",
    "iso:country":"MX",
    "name:spa_x_preferred":[
        "Dzonot Ak"
    ],
    "wof:name":"Dzonot Ak",
    "wof:placetype":"locality"
},
  "geometry": {"coordinates":[-88.07833000000002,20.92149],"type":"Point"}
}