{
  "type": "Feature",
  "properties": {
    "gn:admin1_code":"24.0",
    "gn:admin2_code":"32.0",
    "gn:asciiname":"El Mimbre",
    "gn:country_code":"MX",
    "gn:dem":2023,
    "gn:feature_class":"P",
    "gn:feature_code":"PPL",
    "gn:name":"El Mimbre",
    "gn:population":0,
    "gn:timezone":"America/Mexico_City",
    "iso:country":"MX",
    "name:spa_x_preferred":[
        "El Mimbre"
    ],
    "wof:name":"El Mimbre",
    "wof:placetype":"locality"
},
  "geometry": {"coordinates":[-100.39982999999999,21.78341],"type":"Point"}
}