{
  "type": "Feature",
  "properties": {
    "gn:admin1_code":"28",
    "gn:admin2_code":"3",
    "gn:asciiname":"Los Mezquites",
    "gn:country_code":"MX",
    "gn:dem":5,
    "gn:feature_class":"P",
    "gn:feature_code":"PPL",
    "gn:name":"Los Mezquites",
    "gn:population":15,
    "gn:timezone":"America/Monterrey",
    "iso:country":"MX",
    "wof:name":"Los Mezquites",
    "wof:placetype":"locality",
    "wof:population":15
},
  "geometry": {"coordinates":[-98.23139,22.46222],"type":"Point"}
}