{
  "type": "Feature",
  "properties": {
    "gn:admin1_code":"27",
    "gn:admin2_code":"8.0",
    "gn:asciiname":"Eden",
    "gn:country_code":"MX",
    "gn:dem":34,
    "gn:feature_class":"P",
    "gn:feature_code":"PPL",
    "gn:name":"Ed\u00e9n",
    "gn:population":0,
    "gn:timezone":"America/Mexico_City",
    "iso:country":"MX",
    "name:bre_x_preferred":[
        "Eden"
    ],
    "name:cat_x_preferred":[
        "Eden"
    ],
    "name:ceb_x_preferred":[
        "Eden"
    ],
    "name:ces_x_preferred":[
        "Eden"
    ],
    "name:cym_x_preferred":[
        "Eden"
    ],
    "name:deu_x_preferred":[
        "Eden"
    ],
    "name:est_x_preferred":[
        "Eden"
    ],
    "name:fin_x_preferred":[
        "Eden"
    ],
    "name:fra_x_preferred":[
        "Eden"
    ],
    "name:heb_x_preferred":[
        "\u05e2\u05d3\u05df"
    ],
    "name:ita_x_preferred":[
        "Eden"
    ],
    "name:jpn_x_preferred":[
        "\u30a8\u30c7\u30f3"
    ],
    "name:lav_x_preferred":[
        "Eden"
    ],
    "name:mlg_x_preferred":[
        "Eden"
    ],
    "name:nld_x_preferred":[
        "Eden"
    ],
    "name:nno_x_preferred":[
        "Eden"
    ],
    "name:nor_x_preferred":[
        "Eden"
    ],
    "name:pol_x_preferred":[
        "Eden"
    ],
    "name:por_x_preferred":[
        "Eden"
    ],
    "name:ron_x_preferred":[
        "Categorie:Gr\u0103dina Edenului"
    ],
    "name:rus_x_preferred":[
        "\u042d\u0434\u0435\u043d"
    ],
    "name:slk_x_preferred":[
        "Eden"
    ],
    "name:slv_x_preferred":[
        "Eden"
    ],
    "name:spa_x_preferred":[
        "Eden"
    ],
    "name:srp_x_preferred":[
        "Eden"
    ],
    "name:swe_x_preferred":[
        "Eden"
    ],
    "name:vol_x_preferred":[
        "Eden"
    ],
    "wof:name":"Eden",
    "wof:placetype":"locality"
},
  "geometry": {"coordinates":[-93.40000000000001,17.85],"type":"Point"}
}