{
  "type": "Feature",
  "properties": {
    "gn:admin1_code":"5",
    "gn:admin2_code":"27",
    "gn:asciiname":"Llano Redondo",
    "gn:country_code":"MX",
    "gn:dem":451,
    "gn:feature_class":"P",
    "gn:feature_code":"PPL",
    "gn:name":"Llano Redondo",
    "gn:population":13,
    "gn:timezone":"America/Mexico_City",
    "iso:country":"MX",
    "wof:name":"Llano Redondo",
    "wof:placetype":"locality",
    "wof:population":13
},
  "geometry": {"coordinates":[-93.0425,16.58583],"type":"Point"}
}