{
  "type": "Feature",
  "properties": {
    "gn:admin1_code":"6",
    "gn:admin2_code":"65",
    "gn:asciiname":"Palmarita",
    "gn:country_code":"MX",
    "gn:dem":1862,
    "gn:feature_class":"P",
    "gn:feature_code":"PPL",
    "gn:name":"Palmarita",
    "gn:population":10,
    "gn:timezone":"America/Mazatlan",
    "iso:country":"MX",
    "wof:name":"Palmarita",
    "wof:placetype":"locality",
    "wof:population":10
},
  "geometry": {"coordinates":[-108.04768,26.82632000000001],"type":"Point"}
}