{
  "type": "Feature",
  "properties": {
    "gn:admin1_code":"15.0",
    "gn:asciiname":"Nexcoalanco",
    "gn:country_code":"MX",
    "gn:dem":3444,
    "gn:feature_class":"P",
    "gn:feature_code":"PPL",
    "gn:name":"Nexcoalanco",
    "gn:population":0,
    "gn:timezone":"America/Mexico_City",
    "iso:country":"MX",
    "name:spa_x_preferred":[
        "Nexcoalanco"
    ],
    "wof:name":"Nexcoalanco",
    "wof:placetype":"locality"
},
  "geometry": {"coordinates":[-98.70264,19.20361],"type":"Point"}
}