{
  "type": "Feature",
  "properties": {
    "gn:admin1_code":"11",
    "gn:admin2_code":"46.0",
    "gn:asciiname":"Corrales",
    "gn:country_code":"MX",
    "gn:dem":2416,
    "gn:feature_class":"P",
    "gn:feature_code":"PPL",
    "gn:name":"Corrales",
    "gn:population":200,
    "gn:timezone":"America/Mexico_City",
    "iso:country":"MX",
    "name:cat_x_preferred":[
        "Corrales"
    ],
    "name:ceb_x_preferred":[
        "Corrales"
    ],
    "name:deu_x_preferred":[
        "Corrales"
    ],
    "name:eus_x_preferred":[
        "Corrales"
    ],
    "name:fra_x_preferred":[
        "Corrales"
    ],
    "name:ita_x_preferred":[
        "Corrales"
    ],
    "name:nld_x_preferred":[
        "Corrales"
    ],
    "name:pol_x_preferred":[
        "Corrales"
    ],
    "name:por_x_preferred":[
        "Corrales"
    ],
    "name:rus_x_preferred":[
        "\u041a\u043e\u0440\u0440\u0430\u043b\u0435\u0441"
    ],
    "name:spa_x_preferred":[
        "Corrales"
    ],
    "name:swe_x_preferred":[
        "Corrales"
    ],
    "name:vie_x_preferred":[
        "Corrales"
    ],
    "name:war_x_preferred":[
        "Corrales"
    ],
    "wof:name":"Corrales",
    "wof:placetype":"locality",
    "wof:population":200
},
  "geometry": {"coordinates":[-101.33528,20.03361],"type":"Point"}
}