{
  "type": "Feature",
  "properties": {
    "gn:admin1_code":"24",
    "gn:admin2_code":"12",
    "gn:asciiname":"Tlapani (Texcatl)",
    "gn:country_code":"MX",
    "gn:dem":192,
    "gn:feature_class":"P",
    "gn:feature_code":"PPL",
    "gn:name":"Tlapani (T\u00e9xcatl)",
    "gn:population":25,
    "gn:timezone":"America/Mexico_City",
    "iso:country":"MX",
    "name:und_x_variant":[
        "Tlapani (T\u00e9xcatl)"
    ],
    "wof:name":"Tlapani (Texcatl)",
    "wof:placetype":"locality",
    "wof:population":25
},
  "geometry": {"coordinates":[-98.92778,21.58778],"type":"Point"}
}