{
  "type": "Feature",
  "properties": {
    "gn:admin1_code":"20",
    "gn:admin2_code":"84",
    "gn:asciiname":"Colonia Reforma",
    "gn:country_code":"MX",
    "gn:dem":1813,
    "gn:feature_class":"P",
    "gn:feature_code":"PPL",
    "gn:name":"Colonia Reforma",
    "gn:population":24,
    "gn:timezone":"America/Mexico_City",
    "iso:country":"MX",
    "wof:name":"Colonia Reforma",
    "wof:placetype":"locality",
    "wof:population":24
},
  "geometry": {"coordinates":[-96.75556,17.19],"type":"Point"}
}