{
  "type": "Feature",
  "properties": {
    "gn:admin1_code":"11",
    "gn:admin2_code":"17",
    "gn:asciiname":"Granja San Miguel",
    "gn:country_code":"MX",
    "gn:dem":1730,
    "gn:feature_class":"P",
    "gn:feature_code":"PPL",
    "gn:name":"Granja San Miguel",
    "gn:population":34,
    "gn:timezone":"America/Mexico_City",
    "iso:country":"MX",
    "wof:name":"Granja San Miguel",
    "wof:placetype":"locality",
    "wof:population":34
},
  "geometry": {"coordinates":[-101.33278,20.63167],"type":"Point"}
}