{
  "type": "Feature",
  "properties": {
    "gn:admin1_code":"11.0",
    "gn:admin2_code":"46.0",
    "gn:asciiname":"San Isidro de Calera",
    "gn:country_code":"MX",
    "gn:dem":1844,
    "gn:feature_class":"P",
    "gn:feature_code":"PPL",
    "gn:name":"San Isidro de Calera",
    "gn:population":0,
    "gn:timezone":"America/Mexico_City",
    "iso:country":"MX",
    "name:spa_x_preferred":[
        "San Isidro de Calera"
    ],
    "name:spa_x_variant":[
        "San Isidro"
    ],
    "wof:name":"San Isidro de Calera",
    "wof:placetype":"locality"
},
  "geometry": {"coordinates":[-101.3383,20.14418],"type":"Point"}
}