{
  "type": "Feature",
  "properties": {
    "gn:admin1_code":"30.0",
    "gn:admin2_code":"124.0",
    "gn:asciiname":"Tres Cruces",
    "gn:country_code":"MX",
    "gn:dem":82,
    "gn:feature_class":"P",
    "gn:feature_code":"PPL",
    "gn:name":"Tres Cruces",
    "gn:population":34,
    "gn:timezone":"America/Mexico_City",
    "iso:country":"MX",
    "name:spa_x_preferred":[
        "Tres Cruces"
    ],
    "wof:name":"Tres Cruces",
    "wof:placetype":"locality",
    "wof:population":34
},
  "geometry": {"coordinates":[-97.26056,20.61528],"type":"Point"}
}