{
  "type": "Feature",
  "properties": {
    "gn:admin1_code":"5.0",
    "gn:asciiname":"Rincon Toro",
    "gn:country_code":"MX",
    "gn:dem":749,
    "gn:feature_class":"P",
    "gn:feature_code":"PPL",
    "gn:name":"Rinc\u00f3n Toro",
    "gn:population":0,
    "gn:timezone":"America/Mexico_City",
    "iso:country":"MX",
    "name:spa_x_preferred":[
        "Rinc\u00f3n Toro"
    ],
    "wof:name":"Rincon Toro",
    "wof:placetype":"locality"
},
  "geometry": {"coordinates":[-93.01402,15.96202],"type":"Point"}
}