{
  "type": "Feature",
  "properties": {
    "gn:admin1_code":"5",
    "gn:admin2_code":"65",
    "gn:asciiname":"La Bonita",
    "gn:country_code":"MX",
    "gn:dem":67,
    "gn:feature_class":"P",
    "gn:feature_code":"PPL",
    "gn:name":"La Bonita",
    "gn:population":10,
    "gn:timezone":"America/Mexico_City",
    "iso:country":"MX",
    "wof:name":"La Bonita",
    "wof:placetype":"locality",
    "wof:population":10
},
  "geometry": {"coordinates":[-91.98569999999999,17.55865],"type":"Point"}
}