{
  "type": "Feature",
  "properties": {
    "gn:admin1_code":"19",
    "gn:admin2_code":"11.0",
    "gn:asciiname":"Las Puentes",
    "gn:country_code":"MX",
    "gn:dem":208,
    "gn:feature_class":"P",
    "gn:feature_code":"PPL",
    "gn:name":"Las Puentes",
    "gn:population":0,
    "gn:timezone":"America/Monterrey",
    "iso:country":"MX",
    "name:und_x_variant":[
        "Los Puentes"
    ],
    "wof:name":"Las Puentes",
    "wof:placetype":"locality"
},
  "geometry": {"coordinates":[-99.57769999999999,26.1802],"type":"Point"}
}