{
  "type": "Feature",
  "properties": {
    "gn:admin1_code":"5",
    "gn:admin2_code":"108.0",
    "gn:asciiname":"Rancho Alegre",
    "gn:country_code":"MX",
    "gn:dem":661,
    "gn:feature_class":"P",
    "gn:feature_code":"PPL",
    "gn:name":"Rancho Alegre",
    "gn:population":4,
    "gn:timezone":"America/Mexico_City",
    "iso:country":"MX",
    "name:ceb_x_preferred":[
        "Rancho Alegre"
    ],
    "name:nld_x_preferred":[
        "Rancho Alegre"
    ],
    "name:por_x_preferred":[
        "Rancho Alegre"
    ],
    "name:swe_x_preferred":[
        "Rancho Alegre"
    ],
    "name:vol_x_preferred":[
        "Rancho Alegre"
    ],
    "wof:name":"Rancho Alegre",
    "wof:placetype":"locality",
    "wof:population":4
},
  "geometry": {"coordinates":[-93.42278,16.3125],"type":"Point"}
}