{
  "type": "Feature",
  "properties": {
    "gn:admin1_code":"3",
    "gn:admin2_code":"2.0",
    "gn:asciiname":"Los Ramones",
    "gn:country_code":"MX",
    "gn:dem":89,
    "gn:feature_class":"P",
    "gn:feature_code":"PPL",
    "gn:name":"Los Ramones",
    "gn:population":5,
    "gn:timezone":"America/Mazatlan",
    "iso:country":"MX",
    "name:ceb_x_preferred":[
        "Los Ramones"
    ],
    "name:epo_x_preferred":[
        "Los Ramones"
    ],
    "name:eus_x_preferred":[
        "Los Ramones"
    ],
    "name:ita_x_preferred":[
        "Los Ramones"
    ],
    "name:por_x_preferred":[
        "Los Ramones"
    ],
    "name:spa_x_preferred":[
        "Los Ramones"
    ],
    "name:srp_x_preferred":[
        "\u041b\u043e\u0441 \u0420\u0430\u043c\u043e\u043d\u0435\u0441"
    ],
    "name:swe_x_preferred":[
        "Los Ramones"
    ],
    "name:vie_x_preferred":[
        "Los Ramones"
    ],
    "wof:name":"Los Ramones",
    "wof:placetype":"locality",
    "wof:population":5
},
  "geometry": {"coordinates":[-112.24573999999998,27.21091],"type":"Point"}
}