{
  "type": "Feature",
  "properties": {
    "gn:admin1_code":"26",
    "gn:admin2_code":"49.0",
    "gn:asciiname":"Bachomobampo",
    "gn:country_code":"MX",
    "gn:dem":318,
    "gn:feature_class":"P",
    "gn:feature_code":"PPL",
    "gn:name":"Bachomobampo",
    "gn:population":3,
    "gn:timezone":"America/Hermosillo",
    "iso:country":"MX",
    "wof:name":"Bachomobampo",
    "wof:placetype":"locality",
    "wof:population":3
},
  "geometry": {"coordinates":[-109.68167,27.74417],"type":"Point"}
}