{
  "type": "Feature",
  "properties": {
    "gn:admin1_code":"5",
    "gn:admin2_code":"89.0",
    "gn:asciiname":"Pavencul",
    "gn:country_code":"MX",
    "gn:dem":2011,
    "gn:feature_class":"P",
    "gn:feature_code":"PPL",
    "gn:name":"Pavencul",
    "gn:population":0,
    "gn:timezone":"America/Mexico_City",
    "iso:country":"MX",
    "name:spa_x_preferred":[
        "Pavincul"
    ],
    "name:spa_x_variant":[
        "Pavencul"
    ],
    "name:und_x_variant":[
        "Pavancul"
    ],
    "wof:name":"Pavencul",
    "wof:placetype":"locality"
},
  "geometry": {"coordinates":[-92.17993,15.20249],"type":"Point"}
}