{
  "type": "Feature",
  "properties": {
    "gn:admin1_code":"6",
    "gn:admin2_code":"29",
    "gn:asciiname":"Winolar",
    "gn:country_code":"MX",
    "gn:dem":993,
    "gn:feature_class":"P",
    "gn:feature_code":"PPL",
    "gn:name":"Winolar",
    "gn:population":21,
    "gn:timezone":"America/Chihuahua",
    "iso:country":"MX",
    "wof:name":"Winolar",
    "wof:placetype":"locality",
    "wof:population":21
},
  "geometry": {"coordinates":[-107.14901999999999,25.93079],"type":"Point"}
}