{
  "type": "Feature",
  "properties": {
    "gn:admin1_code":"16.0",
    "gn:admin2_code":"112.0",
    "gn:asciiname":"El Mortelano",
    "gn:country_code":"MX",
    "gn:dem":1869,
    "gn:feature_class":"P",
    "gn:feature_code":"PPL",
    "gn:name":"El Mortelano",
    "gn:population":0,
    "gn:timezone":"America/Mexico_City",
    "iso:country":"MX",
    "name:spa_x_preferred":[
        "El Mortelano"
    ],
    "wof:name":"El Mortelano",
    "wof:placetype":"locality"
},
  "geometry": {"coordinates":[-100.37024,19.47583],"type":"Point"}
}