{
  "type": "Feature",
  "properties": {
    "gn:admin1_code":"18",
    "gn:admin2_code":"9",
    "gn:asciiname":"Puerto de Colomo",
    "gn:country_code":"MX",
    "gn:dem":635,
    "gn:feature_class":"P",
    "gn:feature_code":"PPL",
    "gn:name":"Puerto de Colomo",
    "gn:population":12,
    "gn:timezone":"America/Mazatlan",
    "iso:country":"MX",
    "wof:name":"Puerto de Colomo",
    "wof:placetype":"locality",
    "wof:population":12
},
  "geometry": {"coordinates":[-104.67361,21.81528],"type":"Point"}
}