{
  "type": "Feature",
  "properties": {
    "gn:admin1_code":"9",
    "gn:admin2_code":"9",
    "gn:asciiname":"Tlatilpampa",
    "gn:country_code":"MX",
    "gn:dem":2562,
    "gn:feature_class":"P",
    "gn:feature_code":"PPL",
    "gn:name":"Tlatilpampa",
    "gn:population":15,
    "gn:timezone":"America/Mexico_City",
    "iso:country":"MX",
    "wof:name":"Tlatilpampa",
    "wof:placetype":"locality",
    "wof:population":15
},
  "geometry": {"coordinates":[-99.05804000000001,19.21759],"type":"Point"}
}