{
  "type": "Feature",
  "properties": {
    "gn:admin1_code":"25",
    "gn:admin2_code":"18",
    "gn:asciiname":"El Encanto",
    "gn:country_code":"MX",
    "gn:dem":15,
    "gn:feature_class":"P",
    "gn:feature_code":"PPL",
    "gn:name":"El Encanto",
    "gn:population":13,
    "gn:timezone":"America/Mazatlan",
    "iso:country":"MX",
    "wof:name":"El Encanto",
    "wof:placetype":"locality",
    "wof:population":13
},
  "geometry": {"coordinates":[-107.72671,24.72598],"type":"Point"}
}