{
  "type": "Feature",
  "properties": {
    "gn:admin1_code":"15",
    "gn:admin2_code":"22.0",
    "gn:asciiname":"La Y (Atoyac)",
    "gn:country_code":"MX",
    "gn:dem":2259,
    "gn:feature_class":"P",
    "gn:feature_code":"PPL",
    "gn:name":"La Y (Atoyac)",
    "gn:population":76,
    "gn:timezone":"America/Mexico_City",
    "iso:country":"MX",
    "wof:name":"La Y (Atoyac)",
    "wof:placetype":"locality",
    "wof:population":76
},
  "geometry": {"coordinates":[-98.85252,19.2384],"type":"Point"}
}