{
  "type": "Feature",
  "properties": {
    "gn:admin1_code":"7.0",
    "gn:admin2_code":"14.0",
    "gn:asciiname":"El Pelon",
    "gn:country_code":"MX",
    "gn:dem":438,
    "gn:feature_class":"P",
    "gn:feature_code":"PPL",
    "gn:name":"El Pelon",
    "gn:population":0,
    "gn:timezone":"America/Monterrey",
    "iso:country":"MX",
    "name:spa_x_preferred":[
        "El Pelon"
    ],
    "wof:name":"El Pelon",
    "wof:placetype":"locality"
},
  "geometry": {"coordinates":[-101.25676,29.0831],"type":"Point"}
}