{
  "type": "Feature",
  "properties": {
    "gn:admin1_code":"16",
    "gn:admin2_code":"112.0",
    "gn:asciiname":"Crescencio Morales",
    "gn:country_code":"MX",
    "gn:dem":2453,
    "gn:feature_class":"P",
    "gn:feature_code":"PPL",
    "gn:name":"Crescencio Morales",
    "gn:population":0,
    "gn:timezone":"America/Mexico_City",
    "iso:country":"MX",
    "name:spa_x_preferred":[
        "Crescencio Morales"
    ],
    "name:spa_x_variant":[
        "San Mateo"
    ],
    "wof:name":"Crescencio Morales",
    "wof:placetype":"locality"
},
  "geometry": {"coordinates":[-100.2341,19.495],"type":"Point"}
}