{
  "type": "Feature",
  "properties": {
    "gn:admin1_code":"28.0",
    "gn:admin2_code":"11.0",
    "gn:asciiname":"San Federico",
    "gn:country_code":"MX",
    "gn:dem":83,
    "gn:feature_class":"P",
    "gn:feature_code":"PPL",
    "gn:name":"San Federico",
    "gn:population":0,
    "gn:timezone":"America/Monterrey",
    "iso:country":"MX",
    "name:spa_x_preferred":[
        "San Federico"
    ],
    "wof:name":"San Federico",
    "wof:placetype":"locality"
},
  "geometry": {"coordinates":[-99.12788,22.95884],"type":"Point"}
}