{
  "type": "Feature",
  "properties": {
    "gn:admin1_code":"6",
    "gn:admin2_code":"19.0",
    "gn:asciiname":"Penas Azules",
    "gn:country_code":"MX",
    "gn:dem":1706,
    "gn:feature_class":"P",
    "gn:feature_code":"PPL",
    "gn:name":"Pe\u00f1as Azules",
    "gn:population":0,
    "gn:timezone":"America/Chihuahua",
    "iso:country":"MX",
    "name:spa_x_preferred":[
        "Pe\u00f1as Azules"
    ],
    "wof:name":"Penas Azules",
    "wof:placetype":"locality"
},
  "geometry": {"coordinates":[-106.39870000000001,28.85293],"type":"Point"}
}