{
  "type": "Feature",
  "properties": {
    "gn:admin1_code":"13",
    "gn:admin2_code":"59.0",
    "gn:asciiname":"Bomanxotha",
    "gn:country_code":"MX",
    "gn:dem":1772,
    "gn:feature_class":"P",
    "gn:feature_code":"PPL",
    "gn:name":"Bomanxotha",
    "gn:population":0,
    "gn:timezone":"America/Mexico_City",
    "iso:country":"MX",
    "name:spa_x_preferred":[
        "Bamaxotha"
    ],
    "name:spa_x_variant":[
        "Bomaxota",
        "Bomanxotha"
    ],
    "wof:name":"Bomanxotha",
    "wof:placetype":"locality"
},
  "geometry": {"coordinates":[-99.66679000000001,20.51542],"type":"Point"}
}