{
  "type": "Feature",
  "properties": {
    "gn:admin1_code":"5",
    "gn:admin2_code":"108.0",
    "gn:asciiname":"California",
    "gn:country_code":"MX",
    "gn:dem":973,
    "gn:feature_class":"P",
    "gn:feature_code":"PPL",
    "gn:name":"California",
    "gn:population":321,
    "gn:timezone":"America/Mexico_City",
    "iso:country":"MX",
    "wof:name":"California",
    "wof:placetype":"locality",
    "wof:population":321
},
  "geometry": {"coordinates":[-93.61221999999999,16.26],"type":"Point"}
}