{
  "type": "Feature",
  "properties": {
    "gn:admin1_code":"14",
    "gn:admin2_code":"93",
    "gn:asciiname":"Juan Jimenez (Fraccionamiento la Esperanza)",
    "gn:country_code":"MX",
    "gn:dem":2036,
    "gn:feature_class":"P",
    "gn:feature_code":"PPL",
    "gn:name":"Juan Jim\u00e9nez (Fraccionamiento la Esperanza)",
    "gn:population":15,
    "gn:timezone":"America/Mexico_City",
    "iso:country":"MX",
    "name:und_x_variant":[
        "Juan Jim\u00e9nez (Fraccionamiento la Esperanza)"
    ],
    "wof:name":"Juan Jimenez (Fraccionamiento la Esperanza)",
    "wof:placetype":"locality",
    "wof:population":15
},
  "geometry": {"coordinates":[-102.58222000000001,20.83972],"type":"Point"}
}