{
  "type": "Feature",
  "properties": {
    "gn:admin1_code":"11",
    "gn:admin2_code":"27.0",
    "gn:asciiname":"Rancho los Ramirez (Fraccion el Divisador)",
    "gn:country_code":"MX",
    "gn:dem":1716,
    "gn:feature_class":"P",
    "gn:feature_code":"PPL",
    "gn:name":"Rancho los Ram\u00edrez (Fracci\u00f3n el Divisador)",
    "gn:population":328,
    "gn:timezone":"America/Mexico_City",
    "iso:country":"MX",
    "name:und_x_variant":[
        "Rancho los Ram\u00edrez (Fracci\u00f3n el Divisador)"
    ],
    "wof:name":"Rancho los Ramirez (Fraccion el Divisador)",
    "wof:placetype":"locality",
    "wof:population":328
},
  "geometry": {"coordinates":[-101.15083,20.56583],"type":"Point"}
}