{
  "type": "Feature",
  "properties": {
    "gn:admin1_code":"3",
    "gn:admin2_code":"3.0",
    "gn:asciiname":"Covarrubias",
    "gn:country_code":"MX",
    "gn:dem":686,
    "gn:feature_class":"P",
    "gn:feature_code":"PPL",
    "gn:name":"Covarrubias",
    "gn:population":6,
    "gn:timezone":"America/Mazatlan",
    "iso:country":"MX",
    "name:arg_x_preferred":[
        "Covarrubias"
    ],
    "name:cat_x_preferred":[
        "Covarrubias"
    ],
    "name:ceb_x_preferred":[
        "Covarrubias"
    ],
    "name:deu_x_preferred":[
        "Covarrubias"
    ],
    "name:fra_x_preferred":[
        "Covarrubias"
    ],
    "name:pol_x_preferred":[
        "Covarrubias"
    ],
    "name:spa_x_preferred":[
        "Covarrubias"
    ],
    "name:swe_x_preferred":[
        "Covarrubias"
    ],
    "name:vie_x_preferred":[
        "Covarrubias"
    ],
    "wof:name":"Covarrubias",
    "wof:placetype":"locality",
    "wof:population":6
},
  "geometry": {"coordinates":[-110.04252,23.68389],"type":"Point"}
}