{
  "type": "Feature",
  "properties": {
    "gn:admin1_code":"14.0",
    "gn:admin2_code":"65.0",
    "gn:asciiname":"El Galan",
    "gn:country_code":"MX",
    "gn:dem":688,
    "gn:feature_class":"P",
    "gn:feature_code":"PPL",
    "gn:name":"El Gal\u00e1n",
    "gn:population":0,
    "gn:timezone":"America/Mexico_City",
    "iso:country":"MX",
    "name:spa_x_preferred":[
        "El Gal\u00e1n"
    ],
    "wof:name":"El Galan",
    "wof:placetype":"locality"
},
  "geometry": {"coordinates":[-103.42658,19.19509],"type":"Point"}
}