{
  "type": "Feature",
  "properties": {
    "gn:admin1_code":"5",
    "gn:admin2_code":"89.0",
    "gn:asciiname":"Congregacion Reforma",
    "gn:country_code":"MX",
    "gn:dem":43,
    "gn:feature_class":"P",
    "gn:feature_code":"PPL",
    "gn:name":"Congregaci\u00f3n Reforma",
    "gn:population":1132,
    "gn:timezone":"America/Mexico_City",
    "iso:country":"MX",
    "name:spa_x_preferred":[
        "Congregaci\u00f3n Reforma"
    ],
    "name:und_x_variant":[
        "Congregaci\u00f3n Reforma"
    ],
    "wof:name":"Congregacion Reforma",
    "wof:placetype":"locality",
    "wof:population":1132
},
  "geometry": {"coordinates":[-92.31336,14.78186],"type":"Point"}
}