{
  "type": "Feature",
  "properties": {
    "gn:admin1_code":"12.0",
    "gn:admin2_code":"7.0",
    "gn:asciiname":"Xochitla",
    "gn:country_code":"MX",
    "gn:dem":875,
    "gn:feature_class":"P",
    "gn:feature_code":"PPL",
    "gn:name":"Xochitla",
    "gn:population":0,
    "gn:timezone":"America/Mexico_City",
    "iso:country":"MX",
    "name:spa_x_preferred":[
        "Xochitla"
    ],
    "wof:name":"Xochitla",
    "wof:placetype":"locality"
},
  "geometry": {"coordinates":[-100.14542,18.27235],"type":"Point"}
}