{
  "type": "Feature",
  "properties": {
    "gn:admin1_code":"30.0",
    "gn:admin2_code":"141.0",
    "gn:asciiname":"El Jomate",
    "gn:country_code":"MX",
    "gn:dem":828,
    "gn:feature_class":"P",
    "gn:feature_code":"PPL",
    "gn:name":"El Jomate",
    "gn:population":0,
    "gn:timezone":"America/Mexico_City",
    "iso:country":"MX",
    "name:spa_x_preferred":[
        "El Jomate"
    ],
    "wof:name":"El Jomate",
    "wof:placetype":"locality"
},
  "geometry": {"coordinates":[-95.21596,18.53306],"type":"Point"}
}