{
  "type": "Feature",
  "properties": {
    "gn:admin1_code":"22",
    "gn:admin2_code":"15.0",
    "gn:asciiname":"Agua de Venado",
    "gn:country_code":"MX",
    "gn:dem":2468,
    "gn:feature_class":"P",
    "gn:feature_code":"PPL",
    "gn:name":"Agua de Venado",
    "gn:population":138,
    "gn:timezone":"America/Mexico_City",
    "iso:country":"MX",
    "wof:name":"Agua de Venado",
    "wof:placetype":"locality",
    "wof:population":138
},
  "geometry": {"coordinates":[-99.57472,20.92056],"type":"Point"}
}