{
  "type": "Feature",
  "properties": {
    "gn:admin1_code":"16.0",
    "gn:admin2_code":"10.0",
    "gn:asciiname":"La Timbirichera",
    "gn:country_code":"MX",
    "gn:dem":631,
    "gn:feature_class":"P",
    "gn:feature_code":"PPL",
    "gn:name":"La Timbirichera",
    "gn:population":0,
    "gn:timezone":"America/Mexico_City",
    "iso:country":"MX",
    "name:spa_x_preferred":[
        "La Timbirichera"
    ],
    "wof:name":"La Timbirichera",
    "wof:placetype":"locality"
},
  "geometry": {"coordinates":[-102.72207,18.36597],"type":"Point"}
}