{
  "type": "Feature",
  "properties": {
    "gn:admin1_code":"30",
    "gn:admin2_code":"44.0",
    "gn:asciiname":"Cervantes y Lozada (Santa Rosa)",
    "gn:country_code":"MX",
    "gn:dem":1217,
    "gn:feature_class":"P",
    "gn:feature_code":"PPL",
    "gn:name":"Cervantes y Lozada (Santa Rosa)",
    "gn:population":158,
    "gn:timezone":"America/Mexico_City",
    "iso:country":"MX",
    "wof:name":"Cervantes y Lozada (Santa Rosa)",
    "wof:placetype":"locality",
    "wof:population":158
},
  "geometry": {"coordinates":[-96.93277999999999,18.95556],"type":"Point"}
}