{
  "type": "Feature",
  "properties": {
    "gn:admin1_code":"6",
    "gn:admin2_code":"9.0",
    "gn:asciiname":"Morivo",
    "gn:country_code":"MX",
    "gn:dem":2258,
    "gn:feature_class":"P",
    "gn:feature_code":"PPL",
    "gn:name":"Morivo",
    "gn:population":94,
    "gn:timezone":"America/Chihuahua",
    "iso:country":"MX",
    "wof:name":"Morivo",
    "wof:placetype":"locality",
    "wof:population":94
},
  "geometry": {"coordinates":[-107.82214999999999,27.75964],"type":"Point"}
}