{
  "type": "Feature",
  "properties": {
    "gn:admin1_code":"26",
    "gn:admin2_code":"4.0",
    "gn:asciiname":"Rancho San Javier",
    "gn:country_code":"MX",
    "gn:dem":372,
    "gn:feature_class":"P",
    "gn:feature_code":"PPL",
    "gn:name":"Rancho San Javier",
    "gn:population":0,
    "gn:timezone":"America/Hermosillo",
    "iso:country":"MX",
    "wof:name":"Rancho San Javier",
    "wof:placetype":"locality"
},
  "geometry": {"coordinates":[-111.84999999999999,30.56667],"type":"Point"}
}