{
  "type": "Feature",
  "properties": {
    "gn:admin1_code":"16.0",
    "gn:admin2_code":"92.0",
    "gn:asciiname":"Ceibas de Trujillo",
    "gn:country_code":"MX",
    "gn:dem":606,
    "gn:feature_class":"P",
    "gn:feature_code":"PPL",
    "gn:name":"Ceibas de Trujillo",
    "gn:population":0,
    "gn:timezone":"America/Mexico_City",
    "iso:country":"MX",
    "name:spa_x_preferred":[
        "Ceibas de Trujillo"
    ],
    "name:und_x_variant":[
        "Las Ceibas de Trujillo"
    ],
    "wof:name":"Ceibas de Trujillo",
    "wof:placetype":"locality"
},
  "geometry": {"coordinates":[-100.63330999999999,18.96706],"type":"Point"}
}