{
  "type": "Feature",
  "properties": {
    "gn:admin1_code":"30.0",
    "gn:admin2_code":"123.0",
    "gn:asciiname":"El Ensueno",
    "gn:country_code":"MX",
    "gn:dem":33,
    "gn:feature_class":"P",
    "gn:feature_code":"PPL",
    "gn:name":"El Ensue\u00f1o",
    "gn:population":0,
    "gn:timezone":"America/Mexico_City",
    "iso:country":"MX",
    "name:spa_x_preferred":[
        "El Ensue\u00f1o"
    ],
    "wof:name":"El Ensueno",
    "wof:placetype":"locality"
},
  "geometry": {"coordinates":[-98.24373,21.79917],"type":"Point"}
}