{
  "type": "Feature",
  "properties": {
    "iso:country":"MX",
    "qs_pg:aaroncc":"MX",
    "qs_pg:name":"Uc\u00fam",
    "qs_pg:name_adm0":"M\u00e9xico",
    "qs_pg:name_adm1":"Quintana Roo",
    "qs_pg:photos":12,
    "qs_pg:photos_1k":2,
    "qs_pg:photos_9k":1,
    "qs_pg:photos_9r":1,
    "qs_pg:photos_all":12,
    "qs_pg:photos_sr":1,
    "qs_pg:pop_sr":0,
    "qs_pg:qs_pg_placetype":"locality",
    "qs_pg:qs_pg_placetype_gp":"Town",
    "qs_pg:woe_adm0":23424900,
    "woe:adm0_id":23424900,
    "woe:name_adm0":"M\u00e9xico",
    "woe:name_adm1":"Quintana Roo",
    "woe:placetype":"Town",
    "wof:name":"Uc\u00fam",
    "wof:placetype":"locality"
},
  "geometry": {"coordinates":[-88.53993349999999,18.477166],"type":"Point"}
}