{
  "type": "Feature",
  "properties": {
    "gn:admin1_code":"5",
    "gn:admin2_code":"107.0",
    "gn:asciiname":"Himalaya",
    "gn:country_code":"MX",
    "gn:dem":694,
    "gn:feature_class":"P",
    "gn:feature_code":"PPL",
    "gn:name":"Himalaya",
    "gn:population":5,
    "gn:timezone":"America/Mexico_City",
    "iso:country":"MX",
    "wof:name":"Himalaya",
    "wof:placetype":"locality",
    "wof:population":5
},
  "geometry": {"coordinates":[-93.42778,16.13917],"type":"Point"}
}