{
  "type": "Feature",
  "properties": {
    "gn:admin1_code":"5",
    "gn:admin2_code":"30.0",
    "gn:asciiname":"Francisco I. Madero",
    "gn:country_code":"MX",
    "gn:dem":672,
    "gn:feature_class":"P",
    "gn:feature_code":"PPL",
    "gn:name":"Francisco I. Madero",
    "gn:population":0,
    "gn:timezone":"America/Mexico_City",
    "iso:country":"MX",
    "name:spa_x_preferred":[
        "Francisco I. Madero"
    ],
    "wof:name":"Francisco I. Madero",
    "wof:placetype":"locality"
},
  "geometry": {"coordinates":[-92.19122,15.88218],"type":"Point"}
}