{
  "type": "Feature",
  "properties": {
    "gn:admin1_code":"6",
    "gn:admin2_code":"65.0",
    "gn:asciiname":"Huitron",
    "gn:country_code":"MX",
    "gn:dem":573,
    "gn:feature_class":"P",
    "gn:feature_code":"PPL",
    "gn:name":"Huitr\u00f3n",
    "gn:population":83,
    "gn:timezone":"America/Chihuahua",
    "iso:country":"MX",
    "name:und_x_variant":[
        "Huitr\u00f3n"
    ],
    "wof:name":"Huitron",
    "wof:placetype":"locality",
    "wof:population":83
},
  "geometry": {"coordinates":[-107.90964,27.22215],"type":"Point"}
}