{
  "type": "Feature",
  "properties": {
    "gn:admin1_code":"32.0",
    "gn:admin2_code":"24.0",
    "gn:asciiname":"Bimbaletes",
    "gn:country_code":"MX",
    "gn:dem":2025,
    "gn:feature_class":"P",
    "gn:feature_code":"PPL",
    "gn:name":"Bimbaletes",
    "gn:population":865,
    "gn:timezone":"America/Mexico_City",
    "iso:country":"MX",
    "wof:name":"Bimbaletes",
    "wof:placetype":"locality",
    "wof:population":865
},
  "geometry": {"coordinates":[-102.00306,22.24833],"type":"Point"}
}