{
  "type": "Feature",
  "properties": {
    "gn:admin1_code":"6.0",
    "gn:admin2_code":"38.0",
    "gn:asciiname":"Trincheras",
    "gn:country_code":"MX",
    "gn:dem":1238,
    "gn:feature_class":"P",
    "gn:feature_code":"PPL",
    "gn:name":"Trincheras",
    "gn:population":5,
    "gn:timezone":"America/Chihuahua",
    "iso:country":"MX",
    "name:deu_x_preferred":[
        "Trincheras"
    ],
    "name:epo_x_preferred":[
        "Trincheras"
    ],
    "name:ita_x_preferred":[
        "Trincheras"
    ],
    "name:ron_x_preferred":[
        "Trincheras"
    ],
    "name:spa_x_preferred":[
        "Trincheras"
    ],
    "name:vie_x_preferred":[
        "Trincheras"
    ],
    "wof:name":"Trincheras",
    "wof:placetype":"locality",
    "wof:population":5
},
  "geometry": {"coordinates":[-104.98835,28.73854],"type":"Point"}
}