{
  "type": "Feature",
  "properties": {
    "gn:admin1_code":"7.0",
    "gn:admin2_code":"28.0",
    "gn:asciiname":"La Casa de Piedra",
    "gn:country_code":"MX",
    "gn:dem":334,
    "gn:feature_class":"P",
    "gn:feature_code":"PPL",
    "gn:name":"La Casa de Piedra",
    "gn:population":0,
    "gn:timezone":"America/Monterrey",
    "iso:country":"MX",
    "name:spa_x_preferred":[
        "La Casa de Piedra"
    ],
    "wof:name":"La Casa de Piedra",
    "wof:placetype":"locality"
},
  "geometry": {"coordinates":[-101.05898999999999,27.82924],"type":"Point"}
}