{
  "type": "Feature",
  "properties": {
    "gn:admin1_code":"5.0",
    "gn:admin2_code":"20.0",
    "gn:asciiname":"El Cipres",
    "gn:country_code":"MX",
    "gn:dem":539,
    "gn:feature_class":"P",
    "gn:feature_code":"PPL",
    "gn:name":"El Cipr\u00e9s",
    "gn:population":0,
    "gn:timezone":"America/Mexico_City",
    "iso:country":"MX",
    "name:spa_x_preferred":[
        "Buenavista"
    ],
    "name:spa_x_variant":[
        "El Cipr\u00e9s"
    ],
    "wof:name":"El Cipres",
    "wof:placetype":"locality"
},
  "geometry": {"coordinates":[-92.63831,16.08606],"type":"Point"}
}