{
  "type": "Feature",
  "properties": {
    "gn:admin1_code":"24",
    "gn:admin2_code":"15",
    "gn:asciiname":"La Leona",
    "gn:country_code":"MX",
    "gn:dem":2170,
    "gn:feature_class":"P",
    "gn:feature_code":"PPL",
    "gn:name":"La Leona",
    "gn:population":26,
    "gn:timezone":"America/Mexico_City",
    "iso:country":"MX",
    "name:ceb_x_preferred":[
        "La Leona"
    ],
    "name:spa_x_preferred":[
        "La leona"
    ],
    "name:srp_x_preferred":[
        "\u041b\u0430 \u041b\u0435\u043e\u043d\u0430"
    ],
    "name:swe_x_preferred":[
        "La Leona"
    ],
    "wof:name":"La Leona",
    "wof:placetype":"locality",
    "wof:population":26
},
  "geometry": {"coordinates":[-101.17694,23.36861],"type":"Point"}
}