{
  "type": "Feature",
  "properties": {
    "gn:admin1_code":"12",
    "gn:admin2_code":"16",
    "gn:asciiname":"Palos Altos",
    "gn:country_code":"MX",
    "gn:dem":318,
    "gn:feature_class":"P",
    "gn:feature_code":"PPL",
    "gn:name":"Palos Altos",
    "gn:population":31,
    "gn:timezone":"America/Mexico_City",
    "iso:country":"MX",
    "wof:name":"Palos Altos",
    "wof:placetype":"locality",
    "wof:population":31
},
  "geometry": {"coordinates":[-101.80117,18.43008],"type":"Point"}
}