{
  "type": "Feature",
  "properties": {
    "gn:admin1_code":"10",
    "gn:admin2_code":"32.0",
    "gn:asciiname":"Aranas",
    "gn:country_code":"MX",
    "gn:dem":1793,
    "gn:feature_class":"P",
    "gn:feature_code":"PPL",
    "gn:name":"Aranas",
    "gn:population":0,
    "gn:timezone":"America/Monterrey",
    "iso:country":"MX",
    "name:spa_x_preferred":[
        "Aranas"
    ],
    "name:und_x_variant":[
        "Arenas"
    ],
    "wof:name":"Aranas",
    "wof:placetype":"locality"
},
  "geometry": {"coordinates":[-105.35214000000001,24.86672],"type":"Point"}
}