{
  "type": "Feature",
  "properties": {
    "gn:admin1_code":"20.0",
    "gn:admin2_code":"65.0",
    "gn:asciiname":"Juxtlahuaquilla",
    "gn:country_code":"MX",
    "gn:dem":1921,
    "gn:feature_class":"P",
    "gn:feature_code":"PPL",
    "gn:name":"Juxtlahuaquilla",
    "gn:population":0,
    "gn:timezone":"America/Mexico_City",
    "iso:country":"MX",
    "name:spa_x_preferred":[
        "Juxtlahuaquilla"
    ],
    "wof:name":"Juxtlahuaquilla",
    "wof:placetype":"locality"
},
  "geometry": {"coordinates":[-98.0557,17.47292],"type":"Point"}
}