{
  "type": "Feature",
  "properties": {
    "gn:admin1_code":"15.0",
    "gn:admin2_code":"32.0",
    "gn:asciiname":"San Francisco Mihualtepec",
    "gn:country_code":"MX",
    "gn:dem":2050,
    "gn:feature_class":"P",
    "gn:feature_code":"PPL",
    "gn:name":"San Francisco Mihualtepec",
    "gn:population":0,
    "gn:timezone":"America/Mexico_City",
    "iso:country":"MX",
    "name:spa_x_preferred":[
        "San Francisco Mihualtepec"
    ],
    "wof:name":"San Francisco Mihualtepec",
    "wof:placetype":"locality"
},
  "geometry": {"coordinates":[-100.09829999999999,19.24507],"type":"Point"}
}