{
  "type": "Feature",
  "properties": {
    "gn:admin1_code":"19.0",
    "gn:admin2_code":"27.0",
    "gn:asciiname":"El Saucito",
    "gn:country_code":"MX",
    "gn:dem":189,
    "gn:feature_class":"P",
    "gn:feature_code":"PPL",
    "gn:name":"El Saucito",
    "gn:population":0,
    "gn:timezone":"America/Monterrey",
    "iso:country":"MX",
    "name:spa_x_preferred":[
        "El Saucito"
    ],
    "wof:name":"El Saucito",
    "wof:placetype":"locality"
},
  "geometry": {"coordinates":[-99.51705,25.91152],"type":"Point"}
}