{
  "type": "Feature",
  "properties": {
    "gn:admin1_code":"4",
    "gn:admin2_code":"2.0",
    "gn:asciiname":"San Carlos",
    "gn:country_code":"MX",
    "gn:dem":34,
    "gn:feature_class":"P",
    "gn:feature_code":"PPL",
    "gn:name":"San Carlos",
    "gn:population":0,
    "gn:timezone":"America/Merida",
    "iso:country":"MX",
    "name:spa_x_preferred":[
        "San Carlos"
    ],
    "wof:name":"San Carlos",
    "wof:placetype":"locality"
},
  "geometry": {"coordinates":[-90.17207999999999,19.50895],"type":"Point"}
}