{
  "type": "Feature",
  "properties": {
    "gn:admin1_code":"5",
    "gn:admin2_code":"71",
    "gn:asciiname":"Guapinol",
    "gn:country_code":"MX",
    "gn:dem":35,
    "gn:feature_class":"P",
    "gn:feature_code":"PPL",
    "gn:name":"Guapinol",
    "gn:population":46,
    "gn:timezone":"America/Mexico_City",
    "iso:country":"MX",
    "wof:name":"Guapinol",
    "wof:placetype":"locality",
    "wof:population":46
},
  "geometry": {"coordinates":[-92.56068999999999,15.2026],"type":"Point"}
}