{
  "type": "Feature",
  "properties": {
    "gn:admin1_code":"30",
    "gn:admin2_code":"57.0",
    "gn:asciiname":"Barranca el Maiz",
    "gn:country_code":"MX",
    "gn:dem":1363,
    "gn:feature_class":"P",
    "gn:feature_code":"PPL",
    "gn:name":"Barranca el Ma\u00edz",
    "gn:population":83,
    "gn:timezone":"America/Mexico_City",
    "iso:country":"MX",
    "name:und_x_variant":[
        "Barranca el Ma\u00edz"
    ],
    "wof:name":"Barranca el Maiz",
    "wof:placetype":"locality",
    "wof:population":83
},
  "geometry": {"coordinates":[-96.81778,19.79167],"type":"Point"}
}