{
  "type": "Feature",
  "properties": {
    "gn:admin1_code":"30",
    "gn:admin2_code":"102.0",
    "gn:asciiname":"El Guineo",
    "gn:country_code":"MX",
    "gn:dem":93,
    "gn:feature_class":"P",
    "gn:feature_code":"PPL",
    "gn:name":"El Guineo",
    "gn:population":0,
    "gn:timezone":"America/Mexico_City",
    "iso:country":"MX",
    "name:spa_x_preferred":[
        "El Guineo"
    ],
    "wof:name":"El Guineo",
    "wof:placetype":"locality"
},
  "geometry": {"coordinates":[-97.00637999999999,20.00917],"type":"Point"}
}