{
  "type": "Feature",
  "properties": {
    "gn:admin1_code":"14",
    "gn:admin2_code":"70.0",
    "gn:asciiname":"Hacienda Vieja del Castillo (Castillo Viejo)",
    "gn:country_code":"MX",
    "gn:dem":1539,
    "gn:feature_class":"P",
    "gn:feature_code":"PPL",
    "gn:name":"Hacienda Vieja del Castillo (Castillo Viejo)",
    "gn:population":1913,
    "gn:timezone":"America/Mexico_City",
    "iso:country":"MX",
    "wof:name":"Hacienda Vieja del Castillo (Castillo Viejo)",
    "wof:placetype":"locality",
    "wof:population":1913
},
  "geometry": {"coordinates":[-103.24417,20.54],"type":"Point"}
}