{
  "type": "Feature",
  "properties": {
    "gn:admin1_code":"6",
    "gn:admin2_code":"65.0",
    "gn:asciiname":"Matachio",
    "gn:country_code":"MX",
    "gn:dem":1420,
    "gn:feature_class":"P",
    "gn:feature_code":"PPL",
    "gn:name":"Matach\u00edo",
    "gn:population":0,
    "gn:timezone":"America/Chihuahua",
    "iso:country":"MX",
    "name:spa_x_preferred":[
        "Matach\u00edo"
    ],
    "wof:name":"Matachio",
    "wof:placetype":"locality"
},
  "geometry": {"coordinates":[-108.20448,27.17034],"type":"Point"}
}