{
  "type": "Feature",
  "properties": {
    "gn:admin1_code":"25",
    "gn:admin2_code":"12",
    "gn:asciiname":"Las Moras de Alonso",
    "gn:country_code":"MX",
    "gn:dem":131,
    "gn:feature_class":"P",
    "gn:feature_code":"PPL",
    "gn:name":"Las Moras de Alonso",
    "gn:population":28,
    "gn:timezone":"America/Mazatlan",
    "iso:country":"MX",
    "wof:name":"Las Moras de Alonso",
    "wof:placetype":"locality",
    "wof:population":28
},
  "geometry": {"coordinates":[-106.37654000000001,23.42443],"type":"Point"}
}