{
  "type": "Feature",
  "properties": {
    "gn:admin1_code":"13",
    "gn:admin2_code":"77",
    "gn:asciiname":"Rancho Universitario",
    "gn:country_code":"MX",
    "gn:dem":2163,
    "gn:feature_class":"P",
    "gn:feature_code":"PPL",
    "gn:name":"Rancho Universitario",
    "gn:population":13,
    "gn:timezone":"America/Mexico_City",
    "iso:country":"MX",
    "wof:name":"Rancho Universitario",
    "wof:placetype":"locality",
    "wof:population":13
},
  "geometry": {"coordinates":[-98.38139,20.06083],"type":"Point"}
}