{
  "type": "Feature",
  "properties": {
    "gn:admin1_code":"20",
    "gn:admin2_code":"79.0",
    "gn:asciiname":"Ensenada la Ventosa",
    "gn:country_code":"MX",
    "gn:dem":14,
    "gn:feature_class":"P",
    "gn:feature_code":"PPL",
    "gn:name":"Ensenada la Ventosa",
    "gn:population":0,
    "gn:timezone":"America/Mexico_City",
    "iso:country":"MX",
    "name:spa_x_preferred":[
        "La Ventosa"
    ],
    "name:spa_x_variant":[
        "Ensenada la Ventosa"
    ],
    "wof:name":"Ensenada la Ventosa",
    "wof:placetype":"locality"
},
  "geometry": {"coordinates":[-95.15758,16.17673],"type":"Point"}
}