{
  "type": "Feature",
  "properties": {
    "gn:admin1_code":"2.0",
    "gn:admin2_code":"2.0",
    "gn:asciiname":"Colima 2",
    "gn:country_code":"MX",
    "gn:dem":21,
    "gn:feature_class":"P",
    "gn:feature_code":"PPL",
    "gn:name":"Colima 2",
    "gn:population":35,
    "gn:timezone":"America/Tijuana",
    "iso:country":"MX",
    "name:spa_x_preferred":[
        "Colima Dos"
    ],
    "wof:name":"Colima 2",
    "wof:placetype":"locality",
    "wof:population":35
},
  "geometry": {"coordinates":[-114.99250000000001,32.43333],"type":"Point"}
}