{
  "type": "Feature",
  "properties": {
    "gn:admin1_code":"32",
    "gn:admin2_code":"49.0",
    "gn:asciiname":"J. Jesus Gonzalez Ortega (San Mateo)",
    "gn:country_code":"MX",
    "gn:dem":1998,
    "gn:feature_class":"P",
    "gn:feature_code":"PPL",
    "gn:name":"J. Jes\u00fas Gonz\u00e1lez Ortega (San Mateo)",
    "gn:population":1100,
    "gn:timezone":"America/Mexico_City",
    "iso:country":"MX",
    "name:und_x_variant":[
        "J. Jes\u00fas Gonz\u00e1lez Ortega (San Mateo)"
    ],
    "wof:name":"J. Jesus Gonzalez Ortega (San Mateo)",
    "wof:placetype":"locality",
    "wof:population":1100
},
  "geometry": {"coordinates":[-103.48528,22.88722000000001],"type":"Point"}
}