{
  "type": "Feature",
  "properties": {
    "gn:admin1_code":"7.0",
    "gn:admin2_code":"14.0",
    "gn:asciiname":"El Pinto",
    "gn:country_code":"MX",
    "gn:dem":405,
    "gn:feature_class":"P",
    "gn:feature_code":"PPL",
    "gn:name":"El Pinto",
    "gn:population":0,
    "gn:timezone":"America/Monterrey",
    "iso:country":"MX",
    "name:spa_x_preferred":[
        "El Pinto"
    ],
    "wof:name":"El Pinto",
    "wof:placetype":"locality"
},
  "geometry": {"coordinates":[-101.19446000000001,29.15265],"type":"Point"}
}