{
  "type": "Feature",
  "properties": {
    "gn:admin1_code":"30.0",
    "gn:admin2_code":"181.0",
    "gn:asciiname":"Balaju",
    "gn:country_code":"MX",
    "gn:dem":11,
    "gn:feature_class":"P",
    "gn:feature_code":"PPL",
    "gn:name":"Balaj\u00fa",
    "gn:population":0,
    "gn:timezone":"America/Mexico_City",
    "iso:country":"MX",
    "name:ara_x_preferred":[
        "\u0628\u0627\u0644\u0627\u062c\u0648"
    ],
    "name:fas_x_preferred":[
        "\u0628\u0627\u0644\u0627\u062c\u0648"
    ],
    "name:mzn_x_preferred":[
        "\u0628\u0627\u0644\u0627\u062c\u0648"
    ],
    "name:spa_x_preferred":[
        "Balaj\u00fa"
    ],
    "wof:name":"Balaju",
    "wof:placetype":"locality"
},
  "geometry": {"coordinates":[-96.05071,18.64162],"type":"Point"}
}