{
  "type": "Feature",
  "properties": {
    "gn:admin1_code":"20",
    "gn:admin2_code":"198",
    "gn:asciiname":"El Vaticano (Llano Cola)",
    "gn:country_code":"MX",
    "gn:dem":95,
    "gn:feature_class":"P",
    "gn:feature_code":"PPL",
    "gn:name":"El Vaticano (Llano Cola)",
    "gn:population":12,
    "gn:timezone":"America/Mexico_City",
    "iso:country":"MX",
    "wof:name":"El Vaticano (Llano Cola)",
    "wof:placetype":"locality",
    "wof:population":12
},
  "geometry": {"coordinates":[-95.00028,17.01806],"type":"Point"}
}