{
  "type": "Feature",
  "properties": {
    "gn:admin1_code":"32",
    "gn:admin2_code":"52",
    "gn:asciiname":"Los Chanillos",
    "gn:country_code":"MX",
    "gn:dem":2191,
    "gn:feature_class":"P",
    "gn:feature_code":"PPL",
    "gn:name":"Los Chanillos",
    "gn:population":19,
    "gn:timezone":"America/Mexico_City",
    "iso:country":"MX",
    "wof:name":"Los Chanillos",
    "wof:placetype":"locality",
    "wof:population":19
},
  "geometry": {"coordinates":[-101.935,22.20889],"type":"Point"}
}