{
  "type": "Feature",
  "properties": {
    "gn:admin1_code":"4.0",
    "gn:admin2_code":"10.0",
    "gn:asciiname":"Las Cajeras",
    "gn:country_code":"MX",
    "gn:dem":203,
    "gn:feature_class":"P",
    "gn:feature_code":"PPL",
    "gn:name":"Las Cajeras",
    "gn:population":0,
    "gn:timezone":"America/Cancun",
    "iso:country":"MX",
    "name:spa_x_preferred":[
        "Las Cajeras"
    ],
    "wof:name":"Las Cajeras",
    "wof:placetype":"locality"
},
  "geometry": {"coordinates":[-89.38054,17.89896],"type":"Point"}
}