{
  "type": "Feature",
  "properties": {
    "gn:admin1_code":"5",
    "gn:admin2_code":"115.0",
    "gn:asciiname":"Nuevo Rodulfo Figueroa",
    "gn:country_code":"MX",
    "gn:dem":204,
    "gn:feature_class":"P",
    "gn:feature_code":"PPL",
    "gn:name":"Nuevo Rodulfo Figueroa",
    "gn:population":0,
    "gn:timezone":"America/Mexico_City",
    "iso:country":"MX",
    "name:spa_x_preferred":[
        "Rodolfo Figueroa"
    ],
    "name:spa_x_variant":[
        "Nuevo Rodulfo Figueroa"
    ],
    "name:und_x_variant":[
        "Rodulfo Figueroa",
        "Rodullo Figueroa"
    ],
    "wof:name":"Nuevo Rodulfo Figueroa",
    "wof:placetype":"locality"
},
  "geometry": {"coordinates":[-91.26156,16.22116],"type":"Point"}
}