{
  "type": "Feature",
  "properties": {
    "gn:admin1_code":"6",
    "gn:admin2_code":"66.0",
    "gn:asciiname":"Palo Amarillo",
    "gn:country_code":"MX",
    "gn:dem":1646,
    "gn:feature_class":"P",
    "gn:feature_code":"PPL",
    "gn:name":"Palo Amarillo",
    "gn:population":0,
    "gn:timezone":"America/Chihuahua",
    "iso:country":"MX",
    "name:und_x_variant":[
        "Los Alamillos",
        "Palo Amarillo"
    ],
    "wof:name":"Palo Amarillo",
    "wof:placetype":"locality"
},
  "geometry": {"coordinates":[-108.5188,27.8568],"type":"Point"}
}