{
  "type": "Feature",
  "properties": {
    "gn:admin1_code":"25",
    "gn:admin2_code":"17",
    "gn:asciiname":"Las Papas",
    "gn:country_code":"MX",
    "gn:dem":1097,
    "gn:feature_class":"P",
    "gn:feature_code":"PPL",
    "gn:name":"Las Papas",
    "gn:population":26,
    "gn:timezone":"America/Mazatlan",
    "iso:country":"MX",
    "wof:name":"Las Papas",
    "wof:placetype":"locality",
    "wof:population":26
},
  "geometry": {"coordinates":[-107.71209,26.08662],"type":"Point"}
}