{
  "type": "Feature",
  "properties": {
    "gn:admin1_code":"2.0",
    "gn:admin2_code":"1.0",
    "gn:asciiname":"Los Aguajitos",
    "gn:country_code":"MX",
    "gn:dem":277,
    "gn:feature_class":"P",
    "gn:feature_code":"PPL",
    "gn:name":"Los Aguajitos",
    "gn:population":3,
    "gn:timezone":"America/Tijuana",
    "iso:country":"MX",
    "name:spa_x_preferred":[
        "Los Aguajitos"
    ],
    "wof:name":"Los Aguajitos",
    "wof:placetype":"locality",
    "wof:population":3
},
  "geometry": {"coordinates":[-116.33583,31.53972000000001],"type":"Point"}
}