{
  "type": "Feature",
  "properties": {
    "gn:admin1_code":"19.0",
    "gn:asciiname":"Las Veredas",
    "gn:country_code":"MX",
    "gn:dem":483,
    "gn:feature_class":"P",
    "gn:feature_code":"PPL",
    "gn:name":"Las Veredas",
    "gn:population":0,
    "gn:timezone":"America/Monterrey",
    "iso:country":"MX",
    "name:spa_x_preferred":[
        "Las Veredas"
    ],
    "wof:name":"Las Veredas",
    "wof:placetype":"locality"
},
  "geometry": {"coordinates":[-99.73471000000001,24.92265],"type":"Point"}
}