{
  "type": "Feature",
  "properties": {
    "gn:admin1_code":"22",
    "gn:admin2_code":"4.0",
    "gn:asciiname":"Boye",
    "gn:country_code":"MX",
    "gn:dem":2086,
    "gn:feature_class":"P",
    "gn:feature_code":"PPL",
    "gn:name":"Boy\u00e9",
    "gn:population":0,
    "gn:timezone":"America/Mexico_City",
    "iso:country":"MX",
    "name:und_x_variant":[
        "Barrios de Boy\u00e9",
        "Boy\u00e9"
    ],
    "wof:name":"Boye",
    "wof:placetype":"locality"
},
  "geometry": {"coordinates":[-99.73933,20.68091],"type":"Point"}
}