{
  "type": "Feature",
  "properties": {
    "gn:admin1_code":"14",
    "gn:admin2_code":"13.0",
    "gn:asciiname":"Santa Rita de los Altos (La Angostura)",
    "gn:country_code":"MX",
    "gn:dem":1844,
    "gn:feature_class":"P",
    "gn:feature_code":"PPL",
    "gn:name":"Santa Rita de los Altos (La Angostura)",
    "gn:population":8,
    "gn:timezone":"America/Mexico_City",
    "iso:country":"MX",
    "wof:name":"Santa Rita de los Altos (La Angostura)",
    "wof:placetype":"locality",
    "wof:population":8
},
  "geometry": {"coordinates":[-102.62111,20.59639],"type":"Point"}
}