{
  "type": "Feature",
  "properties": {
    "gn:admin1_code":"16",
    "gn:admin2_code":"57.0",
    "gn:asciiname":"Urbano",
    "gn:country_code":"MX",
    "gn:dem":1073,
    "gn:feature_class":"P",
    "gn:feature_code":"PPL",
    "gn:name":"Urbano",
    "gn:population":0,
    "gn:timezone":"America/Mexico_City",
    "iso:country":"MX",
    "name:ceb_x_preferred":[
        "Urbano"
    ],
    "name:deu_x_preferred":[
        "Urbano"
    ],
    "name:fas_x_preferred":[
        "\u0627\u0648\u0631\u0628\u0627\u0646\u0648"
    ],
    "name:fra_x_preferred":[
        "Urbano"
    ],
    "name:ita_x_preferred":[
        "Urbano"
    ],
    "name:por_x_preferred":[
        "Urbano"
    ],
    "name:rus_x_preferred":[
        "\u0423\u0440\u0431\u0430\u043d\u0443"
    ],
    "name:spa_x_preferred":[
        "Urbano"
    ],
    "name:swe_x_preferred":[
        "Urbano"
    ],
    "wof:name":"Urbano",
    "wof:placetype":"locality"
},
  "geometry": {"coordinates":[-101.12546,19.16971],"type":"Point"}
}