{
  "type": "Feature",
  "properties": {
    "gn:admin1_code":"19.0",
    "gn:asciiname":"La Maza",
    "gn:country_code":"MX",
    "gn:dem":493,
    "gn:feature_class":"P",
    "gn:feature_code":"PPL",
    "gn:name":"La Maza",
    "gn:population":0,
    "gn:timezone":"America/Monterrey",
    "iso:country":"MX",
    "name:spa_x_preferred":[
        "La Maza"
    ],
    "wof:name":"La Maza",
    "wof:placetype":"locality"
},
  "geometry": {"coordinates":[-100.32657,25.85874],"type":"Point"}
}