{
  "type": "Feature",
  "properties": {
    "gn:admin1_code":"30",
    "gn:admin2_code":"210.0",
    "gn:asciiname":"Agustin Melgar",
    "gn:country_code":"MX",
    "gn:dem":93,
    "gn:feature_class":"P",
    "gn:feature_code":"PPL",
    "gn:name":"Agust\u00edn Melgar",
    "gn:population":345,
    "gn:timezone":"America/Mexico_City",
    "iso:country":"MX",
    "name:und_x_variant":[
        "Agust\u00edn Melgar"
    ],
    "wof:name":"Agustin Melgar",
    "wof:placetype":"locality",
    "wof:population":345
},
  "geometry": {"coordinates":[-94.58722,17.25028],"type":"Point"}
}