{
  "type": "Feature",
  "properties": {
    "gn:admin1_code":"13",
    "gn:admin2_code":"1.0",
    "gn:asciiname":"Hueyotlipa",
    "gn:country_code":"MX",
    "gn:dem":2132,
    "gn:feature_class":"P",
    "gn:feature_code":"PPL",
    "gn:name":"Hueyotlipa",
    "gn:population":0,
    "gn:timezone":"America/Mexico_City",
    "iso:country":"MX",
    "name:spa_x_preferred":[
        "Hueyotlipa"
    ],
    "wof:name":"Hueyotlipa",
    "wof:placetype":"locality"
},
  "geometry": {"coordinates":[-98.42967,20.2824],"type":"Point"}
}