{
  "type": "Feature",
  "properties": {
    "gn:admin1_code":"32.0",
    "gn:admin2_code":"49.0",
    "gn:asciiname":"El Almagre",
    "gn:country_code":"MX",
    "gn:dem":2189,
    "gn:feature_class":"P",
    "gn:feature_code":"PPL",
    "gn:name":"El Almagre",
    "gn:population":0,
    "gn:timezone":"America/Mexico_City",
    "iso:country":"MX",
    "name:spa_x_preferred":[
        "El Almagre"
    ],
    "wof:name":"El Almagre",
    "wof:placetype":"locality"
},
  "geometry": {"coordinates":[-103.42112,22.99383],"type":"Point"}
}