{
  "type": "Feature",
  "properties": {
    "gn:admin1_code":"25",
    "gn:admin2_code":"8.0",
    "gn:asciiname":"Guadalupe Allende",
    "gn:country_code":"MX",
    "gn:dem":45,
    "gn:feature_class":"P",
    "gn:feature_code":"PPL",
    "gn:name":"Guadalupe Allende",
    "gn:population":6,
    "gn:timezone":"America/Mazatlan",
    "iso:country":"MX",
    "wof:name":"Guadalupe Allende",
    "wof:placetype":"locality",
    "wof:population":6
},
  "geometry": {"coordinates":[-106.86017,24.02058],"type":"Point"}
}