{
  "type": "Feature",
  "properties": {
    "gn:admin1_code":"32",
    "gn:asciiname":"Ajalpan",
    "gn:country_code":"MX",
    "gn:dem":746,
    "gn:feature_class":"P",
    "gn:feature_code":"PPL",
    "gn:name":"Ajalpan",
    "gn:population":0,
    "gn:timezone":"America/Mexico_City",
    "iso:country":"MX",
    "name:epo_x_preferred":[
        "Ajalpan"
    ],
    "name:fas_x_preferred":[
        "\u0627\u062c\u0627\u0644\u067e\u0627\u0646"
    ],
    "name:rus_x_preferred":[
        "\u0410\u0445\u0430\u043b\u044c\u043f\u0430\u043d"
    ],
    "name:spa_x_preferred":[
        "Ajalpan"
    ],
    "name:vie_x_preferred":[
        "Ajalpan"
    ],
    "wof:name":"Ajalpan",
    "wof:placetype":"locality"
},
  "geometry": {"coordinates":[-96.93333,18.78333],"type":"Point"}
}