{
  "type": "Feature",
  "properties": {
    "gn:admin1_code":"5",
    "gn:admin2_code":"11.0",
    "gn:asciiname":"Cuatro Caminos",
    "gn:country_code":"MX",
    "gn:dem":1527,
    "gn:feature_class":"P",
    "gn:feature_code":"PPL",
    "gn:name":"Cuatro Caminos",
    "gn:population":343,
    "gn:timezone":"America/Mexico_City",
    "iso:country":"MX",
    "name:spa_x_preferred":[
        "Cuatro caminos"
    ],
    "wof:name":"Cuatro Caminos",
    "wof:placetype":"locality",
    "wof:population":343
},
  "geometry": {"coordinates":[-92.21056,15.58889],"type":"Point"}
}