{
  "type": "Feature",
  "properties": {
    "gn:admin1_code":"15",
    "gn:admin2_code":"112.0",
    "gn:asciiname":"Piequexhimo",
    "gn:country_code":"MX",
    "gn:dem":2656,
    "gn:feature_class":"P",
    "gn:feature_code":"PPL",
    "gn:name":"Piequexhimo",
    "gn:population":276,
    "gn:timezone":"America/Mexico_City",
    "iso:country":"MX",
    "wof:name":"Piequexhimo",
    "wof:placetype":"locality",
    "wof:population":276
},
  "geometry": {"coordinates":[-99.43785,19.66176],"type":"Point"}
}