{
  "type": "Feature",
  "properties": {
    "gn:admin1_code":"20",
    "gn:admin2_code":"141.0",
    "gn:asciiname":"Tamarindo",
    "gn:country_code":"MX",
    "gn:dem":9,
    "gn:feature_class":"P",
    "gn:feature_code":"PPL",
    "gn:name":"Tamarindo",
    "gn:population":0,
    "gn:timezone":"America/Mexico_City",
    "iso:country":"MX",
    "wof:name":"Tamarindo",
    "wof:placetype":"locality"
},
  "geometry": {"coordinates":[-94.41667,16.31667],"type":"Point"}
}