{
  "type": "Feature",
  "properties": {
    "gn:admin1_code":"10",
    "gn:admin2_code":"37",
    "gn:asciiname":"Los Fresnos",
    "gn:country_code":"MX",
    "gn:dem":897,
    "gn:feature_class":"P",
    "gn:feature_code":"PPL",
    "gn:name":"Los Fresnos",
    "gn:population":19,
    "gn:timezone":"America/Monterrey",
    "iso:country":"MX",
    "wof:name":"Los Fresnos",
    "wof:placetype":"locality",
    "wof:population":19
},
  "geometry": {"coordinates":[-106.63703,25.16525],"type":"Point"}
}