{
  "type": "Feature",
  "properties": {
    "gn:admin1_code":"6",
    "gn:admin2_code":"1.0",
    "gn:asciiname":"El Petrolero",
    "gn:country_code":"MX",
    "gn:dem":1589,
    "gn:feature_class":"P",
    "gn:feature_code":"PPL",
    "gn:name":"El Petrolero",
    "gn:population":0,
    "gn:timezone":"America/Chihuahua",
    "iso:country":"MX",
    "name:spa_x_preferred":[
        "El Petrolero"
    ],
    "wof:name":"El Petrolero",
    "wof:placetype":"locality"
},
  "geometry": {"coordinates":[-106.68192000000001,30.11459],"type":"Point"}
}