{
  "type": "Feature",
  "properties": {
    "gn:admin1_code":"10.0",
    "gn:admin2_code":"37.0",
    "gn:asciiname":"Los Vasitos",
    "gn:country_code":"MX",
    "gn:dem":2169,
    "gn:feature_class":"P",
    "gn:feature_code":"PPL",
    "gn:name":"Los Vasitos",
    "gn:population":0,
    "gn:timezone":"America/Monterrey",
    "iso:country":"MX",
    "name:spa_x_preferred":[
        "Los Vasitos"
    ],
    "wof:name":"Los Vasitos",
    "wof:placetype":"locality"
},
  "geometry": {"coordinates":[-106.39511,25.2796],"type":"Point"}
}