{
  "type": "Feature",
  "properties": {
    "gn:admin1_code":"5",
    "gn:admin2_code":"76",
    "gn:asciiname":"Las Adelitas",
    "gn:country_code":"MX",
    "gn:dem":752,
    "gn:feature_class":"P",
    "gn:feature_code":"PPL",
    "gn:name":"Las Adelitas",
    "gn:population":29,
    "gn:timezone":"America/Mexico_City",
    "iso:country":"MX",
    "wof:name":"Las Adelitas",
    "wof:placetype":"locality",
    "wof:population":29
},
  "geometry": {"coordinates":[-92.54139000000001,17.23417],"type":"Point"}
}