{
  "type": "Feature",
  "properties": {
    "gn:admin1_code":"17",
    "gn:admin2_code":"17.0",
    "gn:asciiname":"Ampliacion Colonia Jardines de la Herradura",
    "gn:country_code":"MX",
    "gn:dem":918,
    "gn:feature_class":"P",
    "gn:feature_code":"PPL",
    "gn:name":"Ampliaci\u00f3n Colonia Jardines de la Herradura",
    "gn:population":59,
    "gn:timezone":"America/Mexico_City",
    "iso:country":"MX",
    "name:und_x_variant":[
        "Ampliaci\u00f3n Colonia Jardines de la Herradura"
    ],
    "wof:name":"Ampliacion Colonia Jardines de la Herradura",
    "wof:placetype":"locality",
    "wof:population":59
},
  "geometry": {"coordinates":[-99.31139,18.61278],"type":"Point"}
}