{
  "type": "Feature",
  "properties": {
    "gn:admin1_code":"30.0",
    "gn:admin2_code":"151.0",
    "gn:asciiname":"La Puntilla",
    "gn:country_code":"MX",
    "gn:dem":4,
    "gn:feature_class":"P",
    "gn:feature_code":"PPL",
    "gn:name":"La Puntilla",
    "gn:population":301,
    "gn:timezone":"America/Mexico_City",
    "iso:country":"MX",
    "name:ceb_x_preferred":[
        "La Puntilla"
    ],
    "name:deu_x_preferred":[
        "La Puntilla"
    ],
    "name:spa_x_preferred":[
        "La Puntilla"
    ],
    "name:swe_x_preferred":[
        "La Puntilla"
    ],
    "wof:name":"La Puntilla",
    "wof:placetype":"locality",
    "wof:population":301
},
  "geometry": {"coordinates":[-97.43944,21.28722],"type":"Point"}
}