{
  "type": "Feature",
  "properties": {
    "gn:admin1_code":"7",
    "gn:admin2_code":"30.0",
    "gn:asciiname":"Rancho El Puerto de Jesus Gonzalez",
    "gn:country_code":"MX",
    "gn:dem":1832,
    "gn:feature_class":"P",
    "gn:feature_code":"PPL",
    "gn:name":"Rancho El Puerto de Jes\u00fas Gonz\u00e1lez",
    "gn:population":0,
    "gn:timezone":"America/Monterrey",
    "iso:country":"MX",
    "wof:name":"Rancho El Puerto de Jesus Gonzalez",
    "wof:placetype":"locality"
},
  "geometry": {"coordinates":[-101.23333,24.85],"type":"Point"}
}