{
  "type": "Feature",
  "properties": {
    "gn:admin1_code":"30",
    "gn:admin2_code":"178.0",
    "gn:asciiname":"Perez y Jimenez",
    "gn:country_code":"MX",
    "gn:dem":8,
    "gn:feature_class":"P",
    "gn:feature_code":"PPL",
    "gn:name":"P\u00e9rez y Jim\u00e9nez",
    "gn:population":374,
    "gn:timezone":"America/Mexico_City",
    "iso:country":"MX",
    "name:und_x_variant":[
        "P\u00e9rez y Jim\u00e9nez"
    ],
    "wof:name":"Perez y Jimenez",
    "wof:placetype":"locality",
    "wof:population":374
},
  "geometry": {"coordinates":[-95.71167,18.58361],"type":"Point"}
}