{
  "type": "Feature",
  "properties": {
    "gn:admin1_code":"6",
    "gn:admin2_code":"26.0",
    "gn:asciiname":"La Laborcita de San Javier",
    "gn:country_code":"MX",
    "gn:dem":1874,
    "gn:feature_class":"P",
    "gn:feature_code":"PPL",
    "gn:name":"La Laborcita de San Javier",
    "gn:population":0,
    "gn:timezone":"America/Chihuahua",
    "iso:country":"MX",
    "name:und_x_variant":[
        "Laborcita",
        "La Laborcita de San Javier"
    ],
    "wof:name":"La Laborcita de San Javier",
    "wof:placetype":"locality"
},
  "geometry": {"coordinates":[-106.56399999999999,28.38328],"type":"Point"}
}