{
  "type": "Feature",
  "properties": {
    "gn:admin1_code":"32",
    "gn:admin2_code":"46.0",
    "gn:asciiname":"La Cuadrilla",
    "gn:country_code":"MX",
    "gn:dem":1967,
    "gn:feature_class":"P",
    "gn:feature_code":"PPL",
    "gn:name":"La Cuadrilla",
    "gn:population":0,
    "gn:timezone":"America/Mexico_City",
    "iso:country":"MX",
    "wof:name":"La Cuadrilla",
    "wof:placetype":"locality"
},
  "geometry": {"coordinates":[-103.1658,22.488],"type":"Point"}
}