{
  "type": "Feature",
  "properties": {
    "gn:admin1_code":"24",
    "gn:admin2_code":"34.0",
    "gn:asciiname":"El Jopoy",
    "gn:country_code":"MX",
    "gn:dem":30,
    "gn:feature_class":"P",
    "gn:feature_code":"PPL",
    "gn:name":"El Jopoy",
    "gn:population":1,
    "gn:timezone":"America/Mexico_City",
    "iso:country":"MX",
    "name:und_x_variant":[
        "Jopoy",
        "Pojoy",
        "El Jopoy"
    ],
    "wof:name":"El Jopoy",
    "wof:placetype":"locality",
    "wof:population":1
},
  "geometry": {"coordinates":[-98.53046999999999,21.8371],"type":"Point"}
}