{
  "type": "Feature",
  "properties": {
    "gn:admin1_code":"26",
    "gn:admin2_code":"17.0",
    "gn:asciiname":"Ampliacion Fronteras",
    "gn:country_code":"MX",
    "gn:dem":235,
    "gn:feature_class":"P",
    "gn:feature_code":"PPL",
    "gn:name":"Ampliaci\u00f3n Fronteras",
    "gn:population":98,
    "gn:timezone":"America/Hermosillo",
    "iso:country":"MX",
    "name:und_x_variant":[
        "Ampliaci\u00f3n Fronteras"
    ],
    "wof:name":"Ampliacion Fronteras",
    "wof:placetype":"locality",
    "wof:population":98
},
  "geometry": {"coordinates":[-112.29722,30.70222],"type":"Point"}
}