{
  "type": "Feature",
  "properties": {
    "gn:admin1_code":"14",
    "gn:admin2_code":"124.0",
    "gn:asciiname":"Los Tepetates",
    "gn:country_code":"MX",
    "gn:dem":1532,
    "gn:feature_class":"P",
    "gn:feature_code":"PPL",
    "gn:name":"Los Tepetates",
    "gn:population":413,
    "gn:timezone":"America/Mexico_City",
    "iso:country":"MX",
    "wof:name":"Los Tepetates",
    "wof:placetype":"locality",
    "wof:population":413
},
  "geometry": {"coordinates":[-103.045,20.63528],"type":"Point"}
}