{
  "type": "Feature",
  "properties": {
    "gn:admin1_code":"21",
    "gn:admin2_code":"67",
    "gn:asciiname":"San Antonio Mexcaltilahuac",
    "gn:country_code":"MX",
    "gn:dem":2386,
    "gn:feature_class":"P",
    "gn:feature_code":"PPL",
    "gn:name":"San Antonio Mexcaltilahuac",
    "gn:population":14,
    "gn:timezone":"America/Mexico_City",
    "iso:country":"MX",
    "wof:name":"San Antonio Mexcaltilahuac",
    "wof:placetype":"locality",
    "wof:population":14
},
  "geometry": {"coordinates":[-97.42466,19.3154],"type":"Point"}
}