{
  "type": "Feature",
  "properties": {
    "gn:admin1_code":"11",
    "gn:admin2_code":"14.0",
    "gn:asciiname":"La Cabana",
    "gn:country_code":"MX",
    "gn:dem":2049,
    "gn:feature_class":"P",
    "gn:feature_code":"PPL",
    "gn:name":"La Caba\u00f1a",
    "gn:population":122,
    "gn:timezone":"America/Mexico_City",
    "iso:country":"MX",
    "name:und_x_variant":[
        "La Caba\u00f1a"
    ],
    "wof:name":"La Cabana",
    "wof:placetype":"locality",
    "wof:population":122
},
  "geometry": {"coordinates":[-101.04083,21.11556],"type":"Point"}
}