{
  "type": "Feature",
  "properties": {
    "gn:admin1_code":"28.0",
    "gn:admin2_code":"15.0",
    "gn:asciiname":"Marte R. Gomez",
    "gn:country_code":"MX",
    "gn:dem":42,
    "gn:feature_class":"P",
    "gn:feature_code":"PPL",
    "gn:name":"Marte R. G\u00f3mez",
    "gn:population":0,
    "gn:timezone":"America/Monterrey",
    "iso:country":"MX",
    "name:spa_x_preferred":[
        "Marte R. G\u00f3mez"
    ],
    "wof:name":"Marte R. Gomez",
    "wof:placetype":"locality"
},
  "geometry": {"coordinates":[-98.61315999999999,26.18488],"type":"Point"}
}