{
  "type": "Feature",
  "properties": {
    "gn:admin1_code":"5",
    "gn:admin2_code":"101.0",
    "gn:asciiname":"Santa Cecilia Primavera",
    "gn:country_code":"MX",
    "gn:dem":584,
    "gn:feature_class":"P",
    "gn:feature_code":"PPL",
    "gn:name":"Santa Cecilia Primavera",
    "gn:population":53,
    "gn:timezone":"America/Mexico_City",
    "iso:country":"MX",
    "wof:name":"Santa Cecilia Primavera",
    "wof:placetype":"locality",
    "wof:population":53
},
  "geometry": {"coordinates":[-93.19583,16.69028],"type":"Point"}
}