{
  "type": "Feature",
  "properties": {
    "gn:admin1_code":"31",
    "gn:admin2_code":"90",
    "gn:asciiname":"La Libertad",
    "gn:country_code":"MX",
    "gn:dem":18,
    "gn:feature_class":"P",
    "gn:feature_code":"PPL",
    "gn:name":"La Libertad",
    "gn:population":11,
    "gn:timezone":"America/Merida",
    "iso:country":"MX",
    "wof:name":"La Libertad",
    "wof:placetype":"locality",
    "wof:population":11
},
  "geometry": {"coordinates":[-89.51389,20.81806],"type":"Point"}
}