{
  "type": "Feature",
  "properties": {
    "gn:admin1_code":"5.0",
    "gn:asciiname":"Maravilla",
    "gn:country_code":"MX",
    "gn:dem":1527,
    "gn:feature_class":"P",
    "gn:feature_code":"PPL",
    "gn:name":"Maravilla",
    "gn:population":0,
    "gn:timezone":"America/Mexico_City",
    "iso:country":"MX",
    "name:spa_x_preferred":[
        "Maravilla"
    ],
    "wof:name":"Maravilla",
    "wof:placetype":"locality"
},
  "geometry": {"coordinates":[-92.57877999999999,15.56685],"type":"Point"}
}